Workbook
Name ___RM2: [1]PAG19!$J$3:$P$39
Name __RM1: [1]PAG19!$B$3:$I$39
Name __RM2: [2]PAG19!$J$3:$P$39
Name _BancosData_: [3]InputBancos!$B$12:$EL$20
Name _colaentregadopenfdo1_: [3]SaldosBancos!$AD$10
Name _colaentregadopenfdo2_: [3]SaldosBancos!$AD$11
Name _colaentregadopenfdo3_: [3]SaldosBancos!$AD$12
Name _CP_: [3]ModData!$N$5
Name _EmisorLinea_: '[3]Margen Legal'!$D$2
Name _fechaCajaLim_: [3]ModData!$R$9
Name _FechaCarteraReal_: [3]ModData!$D$12
Name _fechalim_: [3]ModData!$C$2
Name _NomInputBancos_: [3]ModData!$F$23
Name _OpeCantSigno_: [3]Operaciones!#REF!
Name _OpeFondoSBS_: [3]Operaciones!#REF!
Name _OpeInstrAntiguos_: [3]Operaciones!#REF!
Name _OpeInstrNuevos_: [3]Operaciones!#REF!
Name _OpeNuevas_: [3]Operaciones!#REF!
Name _OpeNuevoSBS_: [3]Operaciones!#REF!
Name _PatFechaFin_: [3]Patrimonio!$C$15
Name _PatFechaIni_: [3]Patrimonio!$C$14
Name _RegHisOpeFX_: '[3]50'!$D$21
Name _RM1: [2]PAG19!$B$3:$I$39
Name _RM2: [2]PAG19!$J$3:$P$39
Name _TcFechaIni_: [3]TC!$C$4
Name _VectFechIni_: [3]Vector!$C$4
Name a: #REF!
Name ABRE_EMISOR: [5]Parametros!$C$3:$C$14
Name Alternativos_Estrategia: [6]Apoyo!#REF!
Name Alternativos_Estructura_Vehiculo: [6]Apoyo!#REF!
Name Alternativos_Tipo_Activos: [6]Apoyo!#REF!
Name Alternativos_Tipo_Vehiculo: [6]Apoyo!#REF!
Name Aportes: '[7]Ing-Egresos'!$I$166:$IV$171
Name Aportes1: '[7]Ing-Egresos'!$H$166:$IV$171
Name aportexcot: '[8]Aporte x cot'!$10:$16
Name Area_1: '[9]LImites Javier'!$B$2:$Y$94
Name Area_2: '[9]LImites Javier'!$B$96:$Y$138
Name b: #REF!
Name Banco_Central_de_Reserva_del_Perú: [7]Concen!$C$10:$IV$10
Name Banco_Continental: [7]Concen!$C$15:$IV$15
Name Banco_de_Crédito_del_Perú: [7]Concen!$C$13:$IV$13
Name Banco_Internacional_del_Perú_S.A.A.: [7]Concen!$C$18:$IV$18
Name Banco_Santander_Central_Hispano___Perú: [7]Concen!$C$25:$IV$25
Name Banco_Wiese_Sudameris_S.A.: [7]Concen!$C$21:$IV$21
Name BankBoston__N.A.__Sucursal_del_Perú: [7]Concen!$C$22:$IV$22
Name CARTERA_ADMINISTRADA_SPP: [7]Intru!$247:$247
Name Cartera_AFP: '[10]Montos Set'!$A$1:$K$80
Name CartxInstru: [11]Intru!$5:$353
Name Cementos_Lima_S.A.: [7]Concen!$C$11:$IV$11
Name Cía._De_Minas_Buenaventura_S.A.A.: [7]Concen!$C$6:$IV$6
Name Comparación: '[10]Montos Set'!$P$1:$Z$69
Name Comparativo: '[10]Montos Set'!$O$1:$Y$97
Name Credicorp_Ltd.: [7]Concen!$C$7:$IV$7
Name cuadro1: [12]Hoja1!$B$1:$K$67
Name cuadro2: [12]Hoja1!$B$68:$K$136
Name cuadro3: [12]Hoja1!$B$138:$J$207
Name cuadro4: [12]Hoja1!$B$208:$J$239
Name Cuadro5: [12]Hoja3!$B$5:$K$111
Name data: OFFSET([3]CarteraEstimada!$B$8,0,0,MAX([3]CarteraEstimada!$A:$A)+1,37)
Name DStandard: [11]VC_Shar!$L$196:$Q$207

Sheet Valorización de Instrumentos
A1: Fecha Valoración | B1: 20251231
A3: FechaValoracion | B3: TIPO_TITULO | C3: PORTAFOLIO | D3: GRUPO | E3: CODIGO_SBS | F3: CODIGO_ISIN | G3: TITULO | H3: EMISOR | I3: Moneda | J3: VALOR_UNITARIO | K3: VALOR_VECTOR_LOCAL | L3: VALOR_VECTOR_ORIGEN | M3: CANTIDAD | N3: FECHA_VENCIMIENTO | O3: DIAS_VENTIMIENTO | P3: TIPO_CAMBIO | Q3: TIPO_RENTA | R3: VALOR_VECTOR_LOCAL_T-1 | S3: VALOR_VECTOR_ORIGEN_T-1 | T3: GRUPO_ECONOMICO | U3: ACTIVO_DEL_EMISOR | V3: PASIVO_DEL_EMISOR | W3: PASTRIMONIO_DEL_EMISOR | X3: DIFERENCIA | Y3: Column1 | Z3: ID_POS | AA3: Clasificación ERR | AB3: Clasificación General | AC3: Posición Nominal | AD3: Emisor2 | AE3: Nombre (G&P)
A4: 31/12/2025 | B4: 01 | C4: IN-FONDO1 | D4: BGC | E4: 011000112F55 | F4: PEP01000C4S2 | G4: SB12FEB55 | H4: 1000 | I4: 1 | J4: 1000 | K4: 47670526 | L4: 47670526 | M4: 42700 | N4: 56657 | O4: 10635 | P4: 1 | Q4: RENTA FIJA | R4: 47662749 | S4: 47662749 | U4: 0 | V4: 0 | W4: 0 | X4: 0.1821469 | Y4: =+MID(Tabla_Consulta_desde_Reporte_de_Valorización_de_Instrumentos6[[#This Row],[CODIGO_SBS]],7,1) -> 1 | Z4: =Tabla_Consulta_desde_Reporte_de_Valorización_de_Instrumentos6[[#This Row],[CODIGO_SBS]]&"-"&RIGHT(Tabla_Consulta_desde_Reporte_de_Valorización_de_Instrumentos6[[#This Row],[PORTAFOLIO]],1) -> 011000112F55-1 | AA4: Deuda soberana - Local | AB4: Deuda | AC4: =Tabla_Consulta_desde_Reporte_de_Valorización_de_Instrumentos6[[#This Row],[VALOR_UNITARIO]]*Tabla_Consulta_desde_Reporte_de_Valorización_de_Instrumentos6[[#This Row],[CANTIDAD]] -> 42700000 | AD4: Gobierno Central | AE4: =_xlfn.IFNA(_xlfn.XLOOKUP(Tabla_Consulta_desde_Reporte_de_Valorización_de_Instrumentos6[[#This Row],[Emisor2]],'Parametria 2'!G:G,'Parametria 2'!F:F,_xlfn.XLOOKUP(Tabla_Consulta_desde_Reporte_de_Valorización_de_Instrumentos6[[#This Row],[Emisor2]],'Valorización de Instrumentos_of'!H:H,'Valorización de Instrumentos_of'!H:H)),_xlfn.XLOOKUP(Tabla_Consulta_desde_Reporte_de_Valorización_de_Instrumentos6[[#This Row],[TITULO]],'Parametria 2'!K:K,'Parametria 2'!L:L)) -> Gobierno Central
A5: 31/12/2025 | B5: 01 | C5: IN-FONDO2 | D5: BGC | E5: 011000112F55 | F5: PEP01000C4S2 | G5: SB12FEB55 | H5: 1000 | I5: 1 | J5: 1000 | K5: 1.2615385e+08 | L5: 1.2615385e+08 | M5: 113000 | N5: 56657 | O5: 10635 | P5: 1 | Q5: RENTA FIJA | R5: 1.2613327e+08 | S5: 1.2613327e+08 | U5: 0 | V5: 0 | W5: 0 | X5: 0.1821469 | Y5: =+MID(Tabla_Consulta_desde_Reporte_de_Valorización_de_Instrumentos6[[#This Row],[CODIGO_SBS]],7,1) -> 1 | Z5: =Tabla_Consulta_desde_Reporte_de_Valorización_de_Instrumentos6[[#This Row],[CODIGO_SBS]]&"-"&RIGHT(Tabla_Consulta_desde_Reporte_de_Valorización_de_Instrumentos6[[#This Row],[PORTAFOLIO]],1) -> 011000112F55-2 | AA5: Deuda soberana - Local | AB5: Deuda | AC5: =Tabla_Consulta_desde_Reporte_de_Valorización_de_Instrumentos6[[#This Row],[VALOR_UNITARIO]]*Tabla_Consulta_desde_Reporte_de_Valorización_de_Instrumentos6[[#This Row],[CANTIDAD]] -> 113000000 | AD5: Gobierno Central | AE5: =_xlfn.IFNA(_xlfn.XLOOKUP(Tabla_Consulta_desde_Reporte_de_Valorización_de_Instrumentos6[[#This Row],[Emisor2]],'Parametria 2'!G:G,'Parametria 2'!F:F,_xlfn.XLOOKUP(Tabla_Consulta_desde_Reporte_de_Valorización_de_Instrumentos6[[#This Row],[Emisor2]],'Valorización de Instrumentos_of'!H:H,'Valorización de Instrumentos_of'!H:H)),_xlfn.XLOOKUP(Tabla_Consulta_desde_Reporte_de_Valorización_de_Instrumentos6[[#This Row],[TITULO]],'Parametria 2'!K:K,'Parametria 2'!L:L)) -> Gobierno Central
A6: 31/12/2025 | B6: 01 | C6: IN-FONDO1 | D6: BGC | E6: 011000112G37 | F6: PEP01000C2Z1 | G6: SOBAGO2037 | H6: 1000 | I6: 1 | J6: 1000 | K6: 5.2060934e+08 | L6: 5.2060934e+08 | M6: 485359 | N6: 50264 | O6: 4242 | P6: 1 | Q6: RENTA FIJA | R6: 5.1813911e+08 | S6: 5.1813911e+08 | U6: 0 | V6: 0 | W6: 0 | X6: 5.0895012 | Y6: =+MID(Tabla_Consulta_desde_Reporte_de_Valorización_de_Instrumentos6[[#This Row],[CODIGO_SBS]],7,1) -> 1 | Z6: =Tabla_Consulta_desde_Reporte_de_Valorización_de_Instrumentos6[[#This Row],[CODIGO_SBS]]&"-"&RIGHT(Tabla_Consulta_desde_Reporte_de_Valorización_de_Instrumentos6[[#This Row],[PORTAFOLIO]],1) -> 011000112G37-1 | AA6: Deuda soberana - Local | AB6: Deuda | AC6: =Tabla_Consulta_desde_Reporte_de_Valorización_de_Instrumentos6[[#This Row],[VALOR_UNITARIO]]*Tabla_Consulta_desde_Reporte_de_Valorización_de_Instrumentos6[[#This Row],[CANTIDAD]] -> 485359000 | AD6: Gobierno Central | AE6: =_xlfn.IFNA(_xlfn.XLOOKUP(Tabla_Consulta_desde_Reporte_de_Valorización_de_Instrumentos6[[#This Row],[Emisor2]],'Parametria 2'!G:G,'Parametria 2'!F:F,_xlfn.XLOOKUP(Tabla_Consulta_desde_Reporte_de_Valorización_de_Instrumentos6[[#This Row],[Emisor2]],'Valorización de Instrumentos_of'!H:H,'Valorización de Instrumentos_of'!H:H)),_xlfn.XLOOKUP(Tabla_Consulta_desde_Reporte_de_Valorización_de_Instrumentos6[[#This Row],[TITULO]],'Parametria 2'!K:K,'Parametria 2'!L:L)) -> Gobierno Central
A7: 31/12/2025 | B7: 01 | C7: IN-FONDO2 | D7: BGC | E7: 011000112G37 | F7: PEP01000C2Z1 | G7: SOBAGO2037 | H7: 1000 | I7: 1 | J7: 1000 | K7: 1.7105274e+09 | L7: 1.7105274e+09 | M7: 1594708 | N7: 50264 | O7: 4242 | P7: 1 | Q7: RENTA FIJA | R7: 1.7024112e+09 | S7: 1.7024112e+09 | U7: 0 | V7: 0 | W7: 0 | X7: 5.0895012 | Y7: =+MID(Tabla_Consulta_desde_Reporte_de_Valorización_de_Instrumentos6[[#This Row],[CODIGO_SBS]],7,1) -> 1 | Z7: =Tabla_Consulta_desde_Reporte_de_Valorización_de_Instrumentos6[[#This Row],[CODIGO_SBS]]&"-"&RIGHT(Tabla_Consulta_desde_Reporte_de_Valorización_de_Instrumentos6[[#This Row],[PORTAFOLIO]],1) -> 011000112G37-2 | AA7: Deuda soberana - Local | AB7: Deuda | AC7: =Tabla_Consulta_desde_Reporte_de_Valorización_de_Instrumentos6[[#This Row],[VALOR_UNITARIO]]*Tabla_Consulta_desde_Reporte_de_Valorización_de_Instrumentos6[[#This Row],[CANTIDAD]] -> 1594708000 | AD7: Gobierno Central | AE7: =_xlfn.IFNA(_xlfn.XLOOKUP(Tabla_Consulta_desde_Reporte_de_Valorización_de_Instrumentos6[[#This Row],[Emisor2]],'Parametria 2'!G:G,'Parametria 2'!F:F,_xlfn.XLOOKUP(Tabla_Consulta_desde_Reporte_de_Valorización_de_Instrumentos6[[#This Row],[Emisor2]],'Valorización de Instrumentos_of'!H:H,'Valorización de Instrumentos_of'!H:H)),_xlfn.XLOOKUP(Tabla_Consulta_desde_Reporte_de_Valorización_de_Instrumentos6[[#This Row],[TITULO]],'Parametria 2'!K:K,'Parametria 2'!L:L)) -> Gobierno Central
A8: 31/12/2025 | B8: 01 | C8: IN-FONDO1 | D8: BGC | E8: 011000112G39 | F8: PEP01000C5J8 | G8: SB12G39 | H8: 1000 | I8: 1 | J8: 1000 | K8: 8.0004694e+08 | L8: 8.0004694e+08 | M8: 713081 | N8: 50994 | O8: 4972 | P8: 1 | Q8: RENTA FIJA | R8: 7.9692161e+08 | S8: 7.9692161e+08 | U8: 0 | V8: 0 | W8: 0 | X8: 4.3828539 | Y8: =+MID(Tabla_Consulta_desde_Reporte_de_Valorización_de_Instrumentos6[[#This Row],[CODIGO_SBS]],7,1) -> 1 | Z8: =Tabla_Consulta_desde_Reporte_de_Valorización_de_Instrumentos6[[#This Row],[CODIGO_SBS]]&"-"&RIGHT(Tabla_Consulta_desde_Reporte_de_Valorización_de_Instrumentos6[[#This Row],[PORTAFOLIO]],1) -> 011000112G39-1 | AA8: Deuda soberana - Local | AB8: Deuda | AC8: =Tabla_Consulta_desde_Reporte_de_Valorización_de_Instrumentos6[[#This Row],[VALOR_UNITARIO]]*Tabla_Consulta_desde_Reporte_de_Valorización_de_Instrumentos6[[#This Row],[CANTIDAD]] -> 713081000 | AD8: Gobierno Central | AE8: =_xlfn.IFNA(_xlfn.XLOOKUP(Tabla_Consulta_desde_Reporte_de_Valorización_de_Instrumentos6[[#This Row],[Emisor2]],'Parametria 2'!G:G,'Parametria 2'!F:F,_xlfn.XLOOKUP(Tabla_Consulta_desde_Reporte_de_Valorización_de_Instrumentos6[[#This Row],[Emisor2]],'Valorización de Instrumentos_of'!H:H,'Valorización de Instrumentos_of'!H:H)),_xlfn.XLOOKUP(Tabla_Consulta_desde_Reporte_de_Valorización_de_Instrumentos6[[#This Row],[TITULO]],'Parametria 2'!K:K,'Parametria 2'!L:L)) -> Gobierno Central
A9: 31/12/2025 | B9: 01 | C9: IN-FONDO2 | D9: BGC | E9: 011000112G39 | F9: PEP01000C5J8 | G9: SB12G39 | H9: 1000 | I9: 1 | J9: 1000 | K9: 2.0210548e+09 | L9: 2.0210548e+09 | M9: 1801364 | N9: 50994 | O9: 4972 | P9: 1 | Q9: RENTA FIJA | R9: 1.7538822e+09 | S9: 1.7538822e+09 | U9: 0 | V9: 0 | W9: 0 | X9: 4.3828539 | Y9: =+MID(Tabla_Consulta_desde_Reporte_de_Valorización_de_Instrumentos6[[#This Row],[CODIGO_SBS]],7,1) -> 1 | Z9: =Tabla_Consulta_desde_Reporte_de_Valorización_de_Instrumentos6[[#This Row],[CODIGO_SBS]]&"-"&RIGHT(Tabla_Consulta_desde_Reporte_de_Valorización_de_Instrumentos6[[#This Row],[PORTAFOLIO]],1) -> 011000112G39-2 | AA9: Deuda soberana - Local | AB9: Deuda | AC9: =Tabla_Consulta_desde_Reporte_de_Valorización_de_Instrumentos6[[#This Row],[VALOR_UNITARIO]]*Tabla_Consulta_desde_Reporte_de_Valorización_de_Instrumentos6[[#This Row],[CANTIDAD]] -> 1801364000 | AD9: Gobierno Central | AE9: =_xlfn.IFNA(_xlfn.XLOOKUP(Tabla_Consulta_desde_Reporte_de_Valorización_de_Instrumentos6[[#This Row],[Emisor2]],'Parametria 2'!G:G,'Parametria 2'!F:F,_xlfn.XLOOKUP(Tabla_Consulta_desde_Reporte_de_Valorización_de_Instrumentos6[[#This Row],[Emisor2]],'Valorización de Instrumentos_of'!H:H,'Valorización de Instrumentos_of'!H:H)),_xlfn.XLOOKUP(Tabla_Consulta_desde_Reporte_de_Valorización_de_Instrumentos6[[#This Row],[TITULO]],'Parametria 2'!K:K,'Parametria 2'!L:L)) -> Gobierno Central
A10: 31/12/2025 | B10: 01 | C10: IN-FONDO1 | D10: BGC | E10: 011000112G33 | F10: PEP01000C5I0 | G10: SB12AGO33 | H10: 1000 | I10: 1 | J10: 1000 | K10: 1.7522759e+08 | L10: 1.7522759e+08 | M10: 149758 | N10: 48803 | O10: 2781 | P10: 1 | Q10: RENTA FIJA | R10: 1.7480285e+08 | S10: 1.7480285e+08 | U10: 0 | V10: 0 | W10: 0 | X10: 2.8362001 | Y10: =+MID(Tabla_Consulta_desde_Reporte_de_Valorización_de_Instrumentos6[[#This Row],[CODIGO_SBS]],7,1) -> 1 | Z10: =Tabla_Consulta_desde_Reporte_de_Valorización_de_Instrumentos6[[#This Row],[CODIGO_SBS]]&"-"&RIGHT(Tabla_Consulta_desde_Reporte_de_Valorización_de_Instrumentos6[[#This Row],[PORTAFOLIO]],1) -> 011000112G33-1 | AA10: Deuda soberana - Local | AB10: Deuda | AC10: =Tabla_Consulta_desde_Reporte_de_Valorización_de_Instrumentos6[[#This Row],[VALOR_UNITARIO]]*Tabla_Consulta_desde_Reporte_de_Valorización_de_Instrumentos6[[#This Row],[CANTIDAD]] -> 149758000 | AD10: Gobierno Central | AE10: =_xlfn.IFNA(_xlfn.XLOOKUP(Tabla_Consulta_desde_Reporte_de_Valorización_de_Instrumentos6[[#This Row],[Emisor2]],'Parametria 2'!G:G,'Parametria 2'!F:F,_xlfn.XLOOKUP(Tabla_Consulta_desde_Reporte_de_Valorización_de_Instrumentos6[[#This Row],[Emisor2]],'Valorización de Instrumentos_of'!H:H,'Valorización de Instrumentos_of'!H:H)),_xlfn.XLOOKUP(Tabla_Consulta_desde_Reporte_de_Valorización_de_Instrumentos6[[#This Row],[TITULO]],'Parametria 2'!K:K,'Parametria 2'!L:L)) -> Gobierno Central
A11: 31/12/2025 | B11: 01 | C11: IN-FONDO2 | D11: BGC | E11: 011000112G33 | F11: PEP01000C5I0 | G11: SB12AGO33 | H11: 1000 | I11: 1 | J11: 1000 | K11: 1.3456725e+09 | L11: 1.3456725e+09 | M11: 1150077 | N11: 48803 | O11: 2781 | P11: 1 | Q11: RENTA FIJA | R11: 1.3424106e+09 | S11: 1.3424106e+09 | U11: 0 | V11: 0 | W11: 0 | X11: 2.8362001 | Y11: =+MID(Tabla_Consulta_desde_Reporte_de_Valorización_de_Instrumentos6[[#This Row],[CODIGO_SBS]],7,1) -> 1 | Z11: =Tabla_Consulta_desde_Reporte_de_Valorización_de_Instrumentos6[[#This Row],[CODIGO_SBS]]&"-"&RIGHT(Tabla_Consulta_desde_Reporte_de_Valorización_de_Instrumentos6[[#This Row],[PORTAFOLIO]],1) -> 011000112G33-2 | AA11: Deuda soberana - Local | AB11: Deuda | AC11: =Tabla_Consulta_desde_Reporte_de_Valorización_de_Instrumentos6[[#This Row],[VALOR_UNITARIO]]*Tabla_Consulta_desde_Reporte_de_Valorización_de_Instrumentos6[[#This Row],[CANTIDAD]] -> 1150077000 | AD11: Gobierno Central | AE11: =_xlfn.IFNA(_xlfn.XLOOKUP(Tabla_Consulta_desde_Reporte_de_Valorización_de_Instrumentos6[[#This Row],[Emisor2]],'Parametria 2'!G:G,'Parametria 2'!F:F,_xlfn.XLOOKUP(Tabla_Consulta_desde_Reporte_de_Valorización_de_Instrumentos6[[#This Row],[Emisor2]],'Valorización de Instrumentos_of'!H:H,'Valorización de Instrumentos_of'!H:H)),_xlfn.XLOOKUP(Tabla_Consulta_desde_Reporte_de_Valorización_de_Instrumentos6[[#This Row],[TITULO]],'Parametria 2'!K:K,'Parametria 2'!L:L)) -> Gobierno Central
A12: 31/12/2025 | B12: 01 | C12: IN-FONDO1 | D12: BGC | E12: 011000112G40 | F12: PEP01000C5H2 | G12: SB12AGO40 | H12: 1000 | I12: 1 | J12: 1000 | K12: 2.3012165e+08 | L12: 2.3012165e+08 | M12: 252870 | N12: 51360 | O12: 5338 | P12: 1 | Q12: RENTA FIJA | R12: 2.2973463e+08 | S12: 2.2973463e+08 | U12: 0 | V12: 0 | W12: 0 | X12: 1.5305237 | Y12: =+MID(Tabla_Consulta_desde_Reporte_de_Valorización_de_Instrumentos6[[#This Row],[CODIGO_SBS]],7,1) -> 1 | Z12: =Tabla_Consulta_desde_Reporte_de_Valorización_de_Instrumentos6[[#This Row],[CODIGO_SBS]]&"-"&RIGHT(Tabla_Consulta_desde_Reporte_de_Valorización_de_Instrumentos6[[#This Row],[PORTAFOLIO]],1) -> 011000112G40-1 | AA12: Deuda soberana - Local | AB12: Deuda | AC12: =Tabla_Consulta_desde_Reporte_de_Valorización_de_Instrumentos6[[#This Row],[VALOR_UNITARIO]]*Tabla_Consulta_desde_Reporte_de_Valorización_de_Instrumentos6[[#This Row],[CANTIDAD]] -> 252870000 | AD12: Gobierno Central | AE12: =_xlfn.IFNA(_xlfn.XLOOKUP(Tabla_Consulta_desde_Reporte_de_Valorización_de_Instrumentos6[[#This Row],[Emisor2]],'Parametria 2'!G:G,'Parametria 2'!F:F,_xlfn.XLOOKUP(Tabla_Consulta_desde_Reporte_de_Valorización_de_Instrumentos6[[#This Row],[Emisor2]],'Valorización de Instrumentos_of'!H:H,'Valorización de Instrumentos_of'!H:H)),_xlfn.XLOOKUP(Tabla_Consulta_desde_Reporte_de_Valorización_de_Instrumentos6[[#This Row],[TITULO]],'Parametria 2'!K:K,'Parametria 2'!L:L)) -> Gobierno Central
A13: 31/12/2025 | B13: 01 | C13: IN-FONDO2 | D13: BGC | E13: 011000112G40 | F13: PEP01000C5H2 | G13: SB12AGO40 | H13: 1000 | I13: 1 | J13: 1000 | K13: 2.2746707e+08 | L13: 2.2746707e+08 | M13: 249953 | N13: 51360 | O13: 5338 | P13: 1 | Q13: RENTA FIJA | R13: 2.2708451e+08 | S13: 2.2708451e+08 | U13: 0 | V13: 0 | W13: 0 | X13: 1.5305237 | Y13: =+MID(Tabla_Consulta_desde_Reporte_de_Valorización_de_Instrumentos6[[#This Row],[CODIGO_SBS]],7,1) -> 1 | Z13: =Tabla_Consulta_desde_Reporte_de_Valorización_de_Instrumentos6[[#This Row],[CODIGO_SBS]]&"-"&RIGHT(Tabla_Consulta_desde_Reporte_de_Valorización_de_Instrumentos6[[#This Row],[PORTAFOLIO]],1) -> 011000112G40-2 | AA13: Deuda soberana - Local | AB13: Deuda | AC13: =Tabla_Consulta_desde_Reporte_de_Valorización_de_Instrumentos6[[#This Row],[VALOR_UNITARIO]]*Tabla_Consulta_desde_Reporte_de_Valorización_de_Instrumentos6[[#This Row],[CANTIDAD]] -> 249953000 | AD13: Gobierno Central | AE13: =_xlfn.IFNA(_xlfn.XLOOKUP(Tabla_Consulta_desde_Reporte_de_Valorización_de_Instrumentos6[[#This Row],[Emisor2]],'Parametria 2'!G:G,'Parametria 2'!F:F,_xlfn.XLOOKUP(Tabla_Consulta_desde_Reporte_de_Valorización_de_Instrumentos6[[#This Row],[Emisor2]],'Valorización de Instrumentos_of'!H:H,'Valorización de Instrumentos_of'!H:H)),_xlfn.XLOOKUP(Tabla_Consulta_desde_Reporte_de_Valorización_de_Instrumentos6[[#This Row],[TITULO]],'Parametria 2'!K:K,'Parametria 2'!L:L)) -> Gobierno Central
A14: 31/12/2025 | B14: 01 | C14: IN-FONDO1 | D14: BGC | E14: 011000112G32 | F14: PEP01000C5E9 | G14: SB12AGO32 | H14: 1000 | I14: 1 | J14: 1000 | K14: 73619932 | L14: 73619932 | M14: 66706 | N14: 48438 | O14: 2416 | P14: 1 | Q14: RENTA FIJA | R14: 73512435 | S14: 73512435 | U14: 0 | V14: 0 | W14: 0 | X14: 1.6115024 | Y14: =+MID(Tabla_Consulta_desde_Reporte_de_Valorización_de_Instrumentos6[[#This Row],[CODIGO_SBS]],7,1) -> 1 | Z14: =Tabla_Consulta_desde_Reporte_de_Valorización_de_Instrumentos6[[#This Row],[CODIGO_SBS]]&"-"&RIGHT(Tabla_Consulta_desde_Reporte_de_Valorización_de_Instrumentos6[[#This Row],[PORTAFOLIO]],1) -> 011000112G32-1 | AA14: Deuda soberana - Local | AB14: Deuda | AC14: =Tabla_Consulta_desde_Reporte_de_Valorización_de_Instrumentos6[[#This Row],[VALOR_UNITARIO]]*Tabla_Consulta_desde_Reporte_de_Valorización_de_Instrumentos6[[#This Row],[CANTIDAD]] -> 66706000 | AD14: Gobierno Central | AE14: =_xlfn.IFNA(_xlfn.XLOOKUP(Tabla_Consulta_desde_Reporte_de_Valorización_de_Instrumentos6[[#This Row],[Emisor2]],'Parametria 2'!G:G,'Parametria 2'!F:F,_xlfn.XLOOKUP(Tabla_Consulta_desde_Reporte_de_Valorización_de_Instrumentos6[[#This Row],[Emisor2]],'Valorización de Instrumentos_of'!H:H,'Valorización de Instrumentos_of'!H:H)),_xlfn.XLOOKUP(Tabla_Consulta_desde_Reporte_de_Valorización_de_Instrumentos6[[#This Row],[TITULO]],'Parametria 2'!K:K,'Parametria 2'!L:L)) -> Gobierno Central
A15: 31/12/2025 | B15: 01 | C15: IN-FONDO2 | D15: BGC | E15: 011000112G32 | F15: PEP01000C5E9 | G15: SB12AGO32 | H15: 1000 | I15: 1 | J15: 1000 | K15: 611420.9 | L15: 611420.9 | M15: 554 | N15: 48438 | O15: 2416 | P15: 1 | Q15: RENTA FIJA | R15: 610528.12 | S15: 610528.12 | U15: 0 | V15: 0 | W15: 0 | X15: 1.6115024 | Y15: =+MID(Tabla_Consulta_desde_Reporte_de_Valorización_de_Instrumentos6[[#This Row],[CODIGO_SBS]],7,1) -> 1 | Z15: =Tabla_Consulta_desde_Reporte_de_Valorización_de_Instrumentos6[[#This Row],[CODIGO_SBS]]&"-"&RIGHT(Tabla_Consulta_desde_Reporte_de_Valorización_de_Instrumentos6[[#This Row],[PORTAFOLIO]],1) -> 011000112G32-2 | AA15: Deuda soberana - Local | AB15: Deuda | AC15: =Tabla_Consulta_desde_Reporte_de_Valorización_de_Instrumentos6[[#This Row],[VALOR_UNITARIO]]*Tabla_Consulta_desde_Reporte_de_Valorización_de_Instrumentos6[[#This Row],[CANTIDAD]] -> 554000 | AD15: Gobierno Central | AE15: =_xlfn.IFNA(_xlfn.XLOOKUP(Tabla_Consulta_desde_Reporte_de_Valorización_de_Instrumentos6[[#This Row],[Emisor2]],'Parametria 2'!G:G,'Parametria 2'!F:F,_xlfn.XLOOKUP(Tabla_Consulta_desde_Reporte_de_Valorización_de_Instrumentos6[[#This Row],[Emisor2]],'Valorización de Instrumentos_of'!H:H,'Valorización de Instrumentos_of'!H:H)),_xlfn.XLOOKUP(Tabla_Consulta_desde_Reporte_de_Valorización_de_Instrumentos6[[#This Row],[TITULO]],'Parametria 2'!K:K,'Parametria 2'!L:L)) -> Gobierno Central
... A38: 31/12/2025 | B38: 15 | C38: IN-FONDO2 | D38: OSX | E38: 1551192MAD04 | F38: USP1400MAD04 | G38: BANORT 8 3/8 PE | H38: 5119 | I38: 2 | J38: 1000 | K38: 65150544 | L38: 19384851 | M38: 18270 | N38: 54928 | O38: 8906 | P38: 3.3609 | Q38: RENTA FIJA | R38: 65231708 | S38: 19399188 | U38: 2191378000000 | V38: 1948764000000 | W38: 242614000000 | X38: -0.784723 | Y38: =+MID(Tabla_Consulta_desde_Reporte_de_Valorización_de_Instrumentos6[[#This Row],[CODIGO_SBS]],7,1) -> 2 | Z38: =Tabla_Consulta_desde_Reporte_de_Valorización_de_Instrumentos6[[#This Row],[CODIGO_SBS]]&"-"&RIGHT(Tabla_Consulta_desde_Reporte_de_Valorización_de_Instrumentos6[[#This Row],[PORTAFOLIO]],1) -> 1551192MAD04-2 | AA38: Deuda corporativa directa - Internacional | AB38: Deuda | AC38: =Tabla_Consulta_desde_Reporte_de_Valorización_de_Instrumentos6[[#This Row],[VALOR_UNITARIO]]*Tabla_Consulta_desde_Reporte_de_Valorización_de_Instrumentos6[[#This Row],[CANTIDAD]] -> 18270000 | AD38: Grupo Financiero Banorte | AE38: =_xlfn.IFNA(_xlfn.XLOOKUP(Tabla_Consulta_desde_Reporte_de_Valorización_de_Instrumentos6[[#This Row],[Emisor2]],'Parametria 2'!G:G,'Parametria 2'!F:F,_xlfn.XLOOKUP(Tabla_Consulta_desde_Reporte_de_Valorización_de_Instrumentos6[[#This Row],[Emisor2]],'Valorización de Instrumentos_of'!H:H,'Valorización de Instrumentos_of'!H:H)),_xlfn.XLOOKUP(Tabla_Consulta_desde_Reporte_de_Valorización_de_Instrumentos6[[#This Row],[TITULO]],'Parametria 2'!K:K,'Parametria 2'!L:L)) -> #N/A
A39: 31/12/2025 | B39: 15 | C39: IN-FONDO1 | D39: OSX | E39: 1552782GAA15 | F39: USP2000GAA15 | G39: BBVASM 2035 | H39: 5278 | I39: 2 | J39: 1000 | K39: 5456578.7 | L39: 1623546.9 | M39: 1500 | N39: 49351 | O39: 3329 | P39: 3.3609 | Q39: RENTA FIJA | R39: 5469811.8 | S39: 1626661.5 | T39: GBBV | U39: 2808249000000 | V39: 2500434000000 | W39: 307815000000 | X39: -2.076389 | Y39: =+MID(Tabla_Consulta_desde_Reporte_de_Valorización_de_Instrumentos6[[#This Row],[CODIGO_SBS]],7,1) -> 2 | Z39: =Tabla_Consulta_desde_Reporte_de_Valorización_de_Instrumentos6[[#This Row],[CODIGO_SBS]]&"-"&RIGHT(Tabla_Consulta_desde_Reporte_de_Valorización_de_Instrumentos6[[#This Row],[PORTAFOLIO]],1) -> 1552782GAA15-1 | AA39: Deuda corporativa directa - Internacional | AB39: Deuda | AC39: =Tabla_Consulta_desde_Reporte_de_Valorización_de_Instrumentos6[[#This Row],[VALOR_UNITARIO]]*Tabla_Consulta_desde_Reporte_de_Valorización_de_Instrumentos6[[#This Row],[CANTIDAD]] -> 1500000 | AD39: BBVA Bancomer | AE39: =_xlfn.IFNA(_xlfn.XLOOKUP(Tabla_Consulta_desde_Reporte_de_Valorización_de_Instrumentos6[[#This Row],[Emisor2]],'Parametria 2'!G:G,'Parametria 2'!F:F,_xlfn.XLOOKUP(Tabla_Consulta_desde_Reporte_de_Valorización_de_Instrumentos6[[#This Row],[Emisor2]],'Valorización de Instrumentos_of'!H:H,'Valorización de Instrumentos_of'!H:H)),_xlfn.XLOOKUP(Tabla_Consulta_desde_Reporte_de_Valorización_de_Instrumentos6[[#This Row],[TITULO]],'Parametria 2'!K:K,'Parametria 2'!L:L)) -> BBVA Bancomer
A40: 31/12/2025 | B40: 15 | C40: IN-FONDO1 | D40: OSX | E40: 1552782BAB48 | F40: USP1S81BAB48 | G40: BBVASM 2039 | H40: 5278 | I40: 2 | J40: 1000 | K40: 48322572 | L40: 14377867 | M40: 12800 | N40: 50778 | O40: 4756 | P40: 3.3609 | Q40: RENTA FIJA | R40: 48303082 | S40: 14364802 | T40: GBBV | U40: 2808249000000 | V40: 2500434000000 | W40: 307815000000 | X40: 1.020707 | Y40: =+MID(Tabla_Consulta_desde_Reporte_de_Valorización_de_Instrumentos6[[#This Row],[CODIGO_SBS]],7,1) -> 2 | Z40: =Tabla_Consulta_desde_Reporte_de_Valorización_de_Instrumentos6[[#This Row],[CODIGO_SBS]]&"-"&RIGHT(Tabla_Consulta_desde_Reporte_de_Valorización_de_Instrumentos6[[#This Row],[PORTAFOLIO]],1) -> 1552782BAB48-1 | AA40: Deuda corporativa directa - Internacional | AB40: Deuda | AC40: =Tabla_Consulta_desde_Reporte_de_Valorización_de_Instrumentos6[[#This Row],[VALOR_UNITARIO]]*Tabla_Consulta_desde_Reporte_de_Valorización_de_Instrumentos6[[#This Row],[CANTIDAD]] -> 12800000 | AD40: BBVA Bancomer | AE40: =_xlfn.IFNA(_xlfn.XLOOKUP(Tabla_Consulta_desde_Reporte_de_Valorización_de_Instrumentos6[[#This Row],[Emisor2]],'Parametria 2'!G:G,'Parametria 2'!F:F,_xlfn.XLOOKUP(Tabla_Consulta_desde_Reporte_de_Valorización_de_Instrumentos6[[#This Row],[Emisor2]],'Valorización de Instrumentos_of'!H:H,'Valorización de Instrumentos_of'!H:H)),_xlfn.XLOOKUP(Tabla_Consulta_desde_Reporte_de_Valorización_de_Instrumentos6[[#This Row],[TITULO]],'Parametria 2'!K:K,'Parametria 2'!L:L)) -> BBVA Bancomer
A41: 31/12/2025 | B41: 15 | C41: IN-FONDO2 | D41: OSX | E41: 1552782BAB48 | F41: USP1S81BAB48 | G41: BBVASM 2039 | H41: 5278 | I41: 2 | J41: 1000 | K41: 43414811 | L41: 12917615 | M41: 11500 | N41: 50778 | O41: 4756 | P41: 3.3609 | Q41: RENTA FIJA | R41: 43397300 | S41: 12905876 | T41: GBBV | U41: 2808249000000 | V41: 2500434000000 | W41: 307815000000 | X41: 1.020707 | Y41: =+MID(Tabla_Consulta_desde_Reporte_de_Valorización_de_Instrumentos6[[#This Row],[CODIGO_SBS]],7,1) -> 2 | Z41: =Tabla_Consulta_desde_Reporte_de_Valorización_de_Instrumentos6[[#This Row],[CODIGO_SBS]]&"-"&RIGHT(Tabla_Consulta_desde_Reporte_de_Valorización_de_Instrumentos6[[#This Row],[PORTAFOLIO]],1) -> 1552782BAB48-2 | AA41: Deuda corporativa directa - Internacional | AB41: Deuda | AC41: =Tabla_Consulta_desde_Reporte_de_Valorización_de_Instrumentos6[[#This Row],[VALOR_UNITARIO]]*Tabla_Consulta_desde_Reporte_de_Valorización_de_Instrumentos6[[#This Row],[CANTIDAD]] -> 11500000 | AD41: BBVA Bancomer | AE41: =_xlfn.IFNA(_xlfn.XLOOKUP(Tabla_Consulta_desde_Reporte_de_Valorización_de_Instrumentos6[[#This Row],[Emisor2]],'Parametria 2'!G:G,'Parametria 2'!F:F,_xlfn.XLOOKUP(Tabla_Consulta_desde_Reporte_de_Valorización_de_Instrumentos6[[#This Row],[Emisor2]],'Valorización de Instrumentos_of'!H:H,'Valorización de Instrumentos_of'!H:H)),_xlfn.XLOOKUP(Tabla_Consulta_desde_Reporte_de_Valorización_de_Instrumentos6[[#This Row],[TITULO]],'Parametria 2'!K:K,'Parametria 2'!L:L)) -> BBVA Bancomer
A42: 31/12/2025 | B42: 15 | C42: IN-FONDO1 | D42: OSX | E42: 1552782BAA64 | F42: USP1S81BAA64 | G42: BBVASM 2038 | H42: 5278 | I42: 2 | J42: 1000 | K42: 30555199 | L42: 9091374.2 | M42: 8200 | N42: 50585 | O42: 4563 | P42: 3.3609 | Q42: RENTA FIJA | R42: 30559802 | S42: 9088146.6 | T42: GBBV | U42: 2808249000000 | V42: 2500434000000 | W42: 307815000000 | X42: 0.393611 | Y42: =+MID(Tabla_Consulta_desde_Reporte_de_Valorización_de_Instrumentos6[[#This Row],[CODIGO_SBS]],7,1) -> 2 | Z42: =Tabla_Consulta_desde_Reporte_de_Valorización_de_Instrumentos6[[#This Row],[CODIGO_SBS]]&"-"&RIGHT(Tabla_Consulta_desde_Reporte_de_Valorización_de_Instrumentos6[[#This Row],[PORTAFOLIO]],1) -> 1552782BAA64-1 | AA42: Deuda corporativa directa - Internacional | AB42: Deuda | AC42: =Tabla_Consulta_desde_Reporte_de_Valorización_de_Instrumentos6[[#This Row],[VALOR_UNITARIO]]*Tabla_Consulta_desde_Reporte_de_Valorización_de_Instrumentos6[[#This Row],[CANTIDAD]] -> 8200000 | AD42: BBVA Bancomer | AE42: =_xlfn.IFNA(_xlfn.XLOOKUP(Tabla_Consulta_desde_Reporte_de_Valorización_de_Instrumentos6[[#This Row],[Emisor2]],'Parametria 2'!G:G,'Parametria 2'!F:F,_xlfn.XLOOKUP(Tabla_Consulta_desde_Reporte_de_Valorización_de_Instrumentos6[[#This Row],[Emisor2]],'Valorización de Instrumentos_of'!H:H,'Valorización de Instrumentos_of'!H:H)),_xlfn.XLOOKUP(Tabla_Consulta_desde_Reporte_de_Valorización_de_Instrumentos6[[#This Row],[TITULO]],'Parametria 2'!K:K,'Parametria 2'!L:L)) -> BBVA Bancomer
A43: 31/12/2025 | B43: 15 | C43: IN-FONDO2 | D43: OSX | E43: 1552782BAA64 | F43: USP1S81BAA64 | G43: BBVASM 2038 | H43: 5278 | I43: 2 | J43: 1000 | K43: 24965834 | L43: 7428317.9 | M43: 6700 | N43: 50585 | O43: 4563 | P43: 3.3609 | Q43: RENTA FIJA | R43: 24969594 | S43: 7425680.7 | T43: GBBV | U43: 2808249000000 | V43: 2500434000000 | W43: 307815000000 | X43: 0.393611 | Y43: =+MID(Tabla_Consulta_desde_Reporte_de_Valorización_de_Instrumentos6[[#This Row],[CODIGO_SBS]],7,1) -> 2 | Z43: =Tabla_Consulta_desde_Reporte_de_Valorización_de_Instrumentos6[[#This Row],[CODIGO_SBS]]&"-"&RIGHT(Tabla_Consulta_desde_Reporte_de_Valorización_de_Instrumentos6[[#This Row],[PORTAFOLIO]],1) -> 1552782BAA64-2 | AA43: Deuda corporativa directa - Internacional | AB43: Deuda | AC43: =Tabla_Consulta_desde_Reporte_de_Valorización_de_Instrumentos6[[#This Row],[VALOR_UNITARIO]]*Tabla_Consulta_desde_Reporte_de_Valorización_de_Instrumentos6[[#This Row],[CANTIDAD]] -> 6700000 | AD43: BBVA Bancomer | AE43: =_xlfn.IFNA(_xlfn.XLOOKUP(Tabla_Consulta_desde_Reporte_de_Valorización_de_Instrumentos6[[#This Row],[Emisor2]],'Parametria 2'!G:G,'Parametria 2'!F:F,_xlfn.XLOOKUP(Tabla_Consulta_desde_Reporte_de_Valorización_de_Instrumentos6[[#This Row],[Emisor2]],'Valorización de Instrumentos_of'!H:H,'Valorización de Instrumentos_of'!H:H)),_xlfn.XLOOKUP(Tabla_Consulta_desde_Reporte_de_Valorización_de_Instrumentos6[[#This Row],[TITULO]],'Parametria 2'!K:K,'Parametria 2'!L:L)) -> BBVA Bancomer
A44: 31/12/2025 | B44: 15 | C44: IN-FONDO2 | D44: OSX | E44: 15527829AM84 | F44: USP16259AM84 | G44: BBVA 2033 | H44: 5278 | I44: 2 | J44: 1000 | K44: 8467700 | L44: 2519474 | M44: 2500 | N44: 48597 | O44: 2575 | P44: 3.3609 | Q44: RENTA FIJA | R44: 8454457.9 | S44: 2514262.2 | T44: GBBV | U44: 2808249000000 | V44: 2500434000000 | W44: 307815000000 | X44: 2.084722 | Y44: =+MID(Tabla_Consulta_desde_Reporte_de_Valorización_de_Instrumentos6[[#This Row],[CODIGO_SBS]],7,1) -> 2 | Z44: =Tabla_Consulta_desde_Reporte_de_Valorización_de_Instrumentos6[[#This Row],[CODIGO_SBS]]&"-"&RIGHT(Tabla_Consulta_desde_Reporte_de_Valorización_de_Instrumentos6[[#This Row],[PORTAFOLIO]],1) -> 15527829AM84-2 | AA44: Deuda corporativa directa - Internacional | AB44: Deuda | AC44: =Tabla_Consulta_desde_Reporte_de_Valorización_de_Instrumentos6[[#This Row],[VALOR_UNITARIO]]*Tabla_Consulta_desde_Reporte_de_Valorización_de_Instrumentos6[[#This Row],[CANTIDAD]] -> 2500000 | AD44: BBVA Bancomer | AE44: =_xlfn.IFNA(_xlfn.XLOOKUP(Tabla_Consulta_desde_Reporte_de_Valorización_de_Instrumentos6[[#This Row],[Emisor2]],'Parametria 2'!G:G,'Parametria 2'!F:F,_xlfn.XLOOKUP(Tabla_Consulta_desde_Reporte_de_Valorización_de_Instrumentos6[[#This Row],[Emisor2]],'Valorización de Instrumentos_of'!H:H,'Valorización de Instrumentos_of'!H:H)),_xlfn.XLOOKUP(Tabla_Consulta_desde_Reporte_de_Valorización_de_Instrumentos6[[#This Row],[TITULO]],'Parametria 2'!K:K,'Parametria 2'!L:L)) -> BBVA Bancomer
A45: 31/12/2025 | B45: 15 | C45: IN-FONDO1 | D45: OSX | E45: 15527829AN67 | F45: USP16259AN67 | G45: BBVA 2034 | H45: 5278 | I45: 2 | J45: 1000 | K45: 16416058 | L45: 4884423.3 | M45: 4800 | N45: 49200 | O45: 3178 | P45: 3.3609 | Q45: RENTA FIJA | R45: 16381971 | S45: 4871816.7 | T45: GBBV | U45: 2808249000000 | V45: 2500434000000 | W45: 307815000000 | X45: 2.626388 | Y45: =+MID(Tabla_Consulta_desde_Reporte_de_Valorización_de_Instrumentos6[[#This Row],[CODIGO_SBS]],7,1) -> 2 | Z45: =Tabla_Consulta_desde_Reporte_de_Valorización_de_Instrumentos6[[#This Row],[CODIGO_SBS]]&"-"&RIGHT(Tabla_Consulta_desde_Reporte_de_Valorización_de_Instrumentos6[[#This Row],[PORTAFOLIO]],1) -> 15527829AN67-1 | AA45: Deuda corporativa directa - Internacional | AB45: Deuda | AC45: =Tabla_Consulta_desde_Reporte_de_Valorización_de_Instrumentos6[[#This Row],[VALOR_UNITARIO]]*Tabla_Consulta_desde_Reporte_de_Valorización_de_Instrumentos6[[#This Row],[CANTIDAD]] -> 4800000 | AD45: BBVA Bancomer | AE45: =_xlfn.IFNA(_xlfn.XLOOKUP(Tabla_Consulta_desde_Reporte_de_Valorización_de_Instrumentos6[[#This Row],[Emisor2]],'Parametria 2'!G:G,'Parametria 2'!F:F,_xlfn.XLOOKUP(Tabla_Consulta_desde_Reporte_de_Valorización_de_Instrumentos6[[#This Row],[Emisor2]],'Valorización de Instrumentos_of'!H:H,'Valorización de Instrumentos_of'!H:H)),_xlfn.XLOOKUP(Tabla_Consulta_desde_Reporte_de_Valorización_de_Instrumentos6[[#This Row],[TITULO]],'Parametria 2'!K:K,'Parametria 2'!L:L)) -> BBVA Bancomer
A46: 31/12/2025 | B46: 15 | C46: IN-FONDO2 | D46: OSX | E46: 15527829AN67 | F46: USP16259AN67 | G46: BBVA 2034 | H46: 5278 | I46: 2 | J46: 1000 | K46: 20520073 | L46: 6105529.2 | M46: 6000 | N46: 49200 | O46: 3178 | P46: 3.3609 | Q46: RENTA FIJA | R46: 20477463 | S46: 6089770.8 | T46: GBBV | U46: 2808249000000 | V46: 2500434000000 | W46: 307815000000 | X46: 2.626388 | Y46: =+MID(Tabla_Consulta_desde_Reporte_de_Valorización_de_Instrumentos6[[#This Row],[CODIGO_SBS]],7,1) -> 2 | Z46: =Tabla_Consulta_desde_Reporte_de_Valorización_de_Instrumentos6[[#This Row],[CODIGO_SBS]]&"-"&RIGHT(Tabla_Consulta_desde_Reporte_de_Valorización_de_Instrumentos6[[#This Row],[PORTAFOLIO]],1) -> 15527829AN67-2 | AA46: Deuda corporativa directa - Internacional | AB46: Deuda | AC46: =Tabla_Consulta_desde_Reporte_de_Valorización_de_Instrumentos6[[#This Row],[VALOR_UNITARIO]]*Tabla_Consulta_desde_Reporte_de_Valorización_de_Instrumentos6[[#This Row],[CANTIDAD]] -> 6000000 | AD46: BBVA Bancomer | AE46: =_xlfn.IFNA(_xlfn.XLOOKUP(Tabla_Consulta_desde_Reporte_de_Valorización_de_Instrumentos6[[#This Row],[Emisor2]],'Parametria 2'!G:G,'Parametria 2'!F:F,_xlfn.XLOOKUP(Tabla_Consulta_desde_Reporte_de_Valorización_de_Instrumentos6[[#This Row],[Emisor2]],'Valorización de Instrumentos_of'!H:H,'Valorización de Instrumentos_of'!H:H)),_xlfn.XLOOKUP(Tabla_Consulta_desde_Reporte_de_Valorización_de_Instrumentos6[[#This Row],[TITULO]],'Parametria 2'!K:K,'Parametria 2'!L:L)) -> BBVA Bancomer
A47: 31/12/2025 | B47: 15 | C47: IN-FONDO2 | D47: OSX | E47: 15528725AC15 | F47: USG42045AC15 | G47: AVALCB 4 3/8 02 | H47: 5287 | I47: 2 | J47: 1000 | K47: 3807145.4 | L47: 1132775.6 | M47: 1184 | N47: 47518 | O47: 1496 | P47: 3.3609 | Q47: RENTA FIJA | R47: 3808533.4 | S47: 1132615.7 | T47: GAVA | U47: 316615576000000 | V47: 284936353000000 | W47: 3.1679223e+13 | X47: 0.135055 | Y47: =+MID(Tabla_Consulta_desde_Reporte_de_Valorización_de_Instrumentos6[[#This Row],[CODIGO_SBS]],7,1) -> 2 | Z47: =Tabla_Consulta_desde_Reporte_de_Valorización_de_Instrumentos6[[#This Row],[CODIGO_SBS]]&"-"&RIGHT(Tabla_Consulta_desde_Reporte_de_Valorización_de_Instrumentos6[[#This Row],[PORTAFOLIO]],1) -> 15528725AC15-2 | AA47: Deuda corporativa directa - Internacional | AB47: Deuda | AC47: =Tabla_Consulta_desde_Reporte_de_Valorización_de_Instrumentos6[[#This Row],[VALOR_UNITARIO]]*Tabla_Consulta_desde_Reporte_de_Valorización_de_Instrumentos6[[#This Row],[CANTIDAD]] -> 1184000 | AD47: Grupo Aval Acciones y Valores | AE47: =_xlfn.IFNA(_xlfn.XLOOKUP(Tabla_Consulta_desde_Reporte_de_Valorización_de_Instrumentos6[[#This Row],[Emisor2]],'Parametria 2'!G:G,'Parametria 2'!F:F,_xlfn.XLOOKUP(Tabla_Consulta_desde_Reporte_de_Valorización_de_Instrumentos6[[#This Row],[Emisor2]],'Valorización de Instrumentos_of'!H:H,'Valorización de Instrumentos_of'!H:H)),_xlfn.XLOOKUP(Tabla_Consulta_desde_Reporte_de_Valorización_de_Instrumentos6[[#This Row],[TITULO]],'Parametria 2'!K:K,'Parametria 2'!L:L)) -> #N/A
A48: 31/12/2025 | B48: 15 | C48: IN-FONDO1 | D48: OSX | E48: 15532427PD99 | F48: USP0R137PD99 | G48: DAVIVI2035 | H48: 5324 | I48: 2 | J48: 1000 | K48: 41207481 | L48: 12260847 | M48: 11753 | N48: 48397 | O48: 2375 | P48: 3.3609 | Q48: RENTA FIJA | R48: 42836589 | S48: 12739127 | U48: 177149615000000 | V48: 161267686000000 | W48: 15881929000000 | X48: -40.694306 | Y48: =+MID(Tabla_Consulta_desde_Reporte_de_Valorización_de_Instrumentos6[[#This Row],[CODIGO_SBS]],7,1) -> 2 | Z48: =Tabla_Consulta_desde_Reporte_de_Valorización_de_Instrumentos6[[#This Row],[CODIGO_SBS]]&"-"&RIGHT(Tabla_Consulta_desde_Reporte_de_Valorización_de_Instrumentos6[[#This Row],[PORTAFOLIO]],1) -> 15532427PD99-1 | AA48: Deuda corporativa directa - Internacional | AB48: Deuda | AC48: =Tabla_Consulta_desde_Reporte_de_Valorización_de_Instrumentos6[[#This Row],[VALOR_UNITARIO]]*Tabla_Consulta_desde_Reporte_de_Valorización_de_Instrumentos6[[#This Row],[CANTIDAD]] -> 11753000 | AD48: Banco Davivienda S.A. | AE48: =_xlfn.IFNA(_xlfn.XLOOKUP(Tabla_Consulta_desde_Reporte_de_Valorización_de_Instrumentos6[[#This Row],[Emisor2]],'Parametria 2'!G:G,'Parametria 2'!F:F,_xlfn.XLOOKUP(Tabla_Consulta_desde_Reporte_de_Valorización_de_Instrumentos6[[#This Row],[Emisor2]],'Valorización de Instrumentos_of'!H:H,'Valorización de Instrumentos_of'!H:H)),_xlfn.XLOOKUP(Tabla_Consulta_desde_Reporte_de_Valorización_de_Instrumentos6[[#This Row],[TITULO]],'Parametria 2'!K:K,'Parametria 2'!L:L)) -> Banco Davivienda S.A.
A49: 31/12/2025 | B49: 15 | C49: IN-FONDO2 | D49: OSX | E49: 15532427PD99 | F49: USP0R137PD99 | G49: DAVIVI2035 | H49: 5324 | I49: 2 | J49: 1000 | K49: 24307961 | L49: 7232574.9 | M49: 6933 | N49: 48397 | O49: 2375 | P49: 3.3609 | Q49: RENTA FIJA | R49: 25268959 | S49: 7514708.6 | U49: 177149615000000 | V49: 161267686000000 | W49: 15881929000000 | X49: -40.694306 | Y49: =+MID(Tabla_Consulta_desde_Reporte_de_Valorización_de_Instrumentos6[[#This Row],[CODIGO_SBS]],7,1) -> 2 | Z49: =Tabla_Consulta_desde_Reporte_de_Valorización_de_Instrumentos6[[#This Row],[CODIGO_SBS]]&"-"&RIGHT(Tabla_Consulta_desde_Reporte_de_Valorización_de_Instrumentos6[[#This Row],[PORTAFOLIO]],1) -> 15532427PD99-2 | AA49: Deuda corporativa directa - Internacional | AB49: Deuda | AC49: =Tabla_Consulta_desde_Reporte_de_Valorización_de_Instrumentos6[[#This Row],[VALOR_UNITARIO]]*Tabla_Consulta_desde_Reporte_de_Valorización_de_Instrumentos6[[#This Row],[CANTIDAD]] -> 6933000 | AD49: Banco Davivienda S.A. | AE49: =_xlfn.IFNA(_xlfn.XLOOKUP(Tabla_Consulta_desde_Reporte_de_Valorización_de_Instrumentos6[[#This Row],[Emisor2]],'Parametria 2'!G:G,'Parametria 2'!F:F,_xlfn.XLOOKUP(Tabla_Consulta_desde_Reporte_de_Valorización_de_Instrumentos6[[#This Row],[Emisor2]],'Valorización de Instrumentos_of'!H:H,'Valorización de Instrumentos_of'!H:H)),_xlfn.XLOOKUP(Tabla_Consulta_desde_Reporte_de_Valorización_de_Instrumentos6[[#This Row],[TITULO]],'Parametria 2'!K:K,'Parametria 2'!L:L)) -> Banco Davivienda S.A.
A50: 31/12/2025 | B50: 15 | C50: IN-FONDO1 | D50: OSX | E50: 15515123CH47 | F50: USP32133CH47 | G50: BCICI 7 1/2 PE | H50: 5151 | I50: 2 | J50: 1000 | K50: 17937711 | L50: 5337175 | M50: 4920 | N50: 73121 | O50: 27099 | P50: 3.3609 | Q50: RENTA FIJA | R50: 17939891 | S50: 5335125 | U50: 0 | V50: 0 | W50: 0 | X50: 0.416667 | Y50: =+MID(Tabla_Consulta_desde_Reporte_de_Valorización_de_Instrumentos6[[#This Row],[CODIGO_SBS]],7,1) -> 2 | Z50: =Tabla_Consulta_desde_Reporte_de_Valorización_de_Instrumentos6[[#This Row],[CODIGO_SBS]]&"-"&RIGHT(Tabla_Consulta_desde_Reporte_de_Valorización_de_Instrumentos6[[#This Row],[PORTAFOLIO]],1) -> 15515123CH47-1 | AA50: Deuda corporativa directa - Internacional | AB50: Deuda | AC50: =Tabla_Consulta_desde_Reporte_de_Valorización_de_Instrumentos6[[#This Row],[VALOR_UNITARIO]]*Tabla_Consulta_desde_Reporte_de_Valorización_de_Instrumentos6[[#This Row],[CANTIDAD]] -> 4920000 | AD50: Banco de Crédito e Inversiones | AE50: =_xlfn.IFNA(_xlfn.XLOOKUP(Tabla_Consulta_desde_Reporte_de_Valorización_de_Instrumentos6[[#This Row],[Emisor2]],'Parametria 2'!G:G,'Parametria 2'!F:F,_xlfn.XLOOKUP(Tabla_Consulta_desde_Reporte_de_Valorización_de_Instrumentos6[[#This Row],[Emisor2]],'Valorización de Instrumentos_of'!H:H,'Valorización de Instrumentos_of'!H:H)),_xlfn.XLOOKUP(Tabla_Consulta_desde_Reporte_de_Valorización_de_Instrumentos6[[#This Row],[TITULO]],'Parametria 2'!K:K,'Parametria 2'!L:L)) -> Banco de Crédito e Inversiones
A51: 31/12/2025 | B51: 15 | C51: IN-FONDO1 | D51: OSX | E51: 1551112LAN29 | F51: US05968LAN29 | G51: BCOLO 2034 | H51: 5111 | I51: 2 | J51: 1000 | K51: 60957859 | L51: 18137362 | M51: 16900 | N51: 49302 | O51: 3280 | P51: 3.3609 | Q51: RENTA FIJA | R51: 60992718 | S51: 18138559 | U51: 338596669000000 | V51: 301098538000000 | W51: 37498131000000 | X51: -0.070833 | Y51: =+MID(Tabla_Consulta_desde_Reporte_de_Valorización_de_Instrumentos6[[#This Row],[CODIGO_SBS]],7,1) -> 2 | Z51: =Tabla_Consulta_desde_Reporte_de_Valorización_de_Instrumentos6[[#This Row],[CODIGO_SBS]]&"-"&RIGHT(Tabla_Consulta_desde_Reporte_de_Valorización_de_Instrumentos6[[#This Row],[PORTAFOLIO]],1) -> 1551112LAN29-1 | AA51: Deuda corporativa directa - Internacional | AB51: Deuda | AC51: =Tabla_Consulta_desde_Reporte_de_Valorización_de_Instrumentos6[[#This Row],[VALOR_UNITARIO]]*Tabla_Consulta_desde_Reporte_de_Valorización_de_Instrumentos6[[#This Row],[CANTIDAD]] -> 16900000 | AD51: Banco de Colombia | AE51: =_xlfn.IFNA(_xlfn.XLOOKUP(Tabla_Consulta_desde_Reporte_de_Valorización_de_Instrumentos6[[#This Row],[Emisor2]],'Parametria 2'!G:G,'Parametria 2'!F:F,_xlfn.XLOOKUP(Tabla_Consulta_desde_Reporte_de_Valorización_de_Instrumentos6[[#This Row],[Emisor2]],'Valorización de Instrumentos_of'!H:H,'Valorización de Instrumentos_of'!H:H)),_xlfn.XLOOKUP(Tabla_Consulta_desde_Reporte_de_Valorización_de_Instrumentos6[[#This Row],[TITULO]],'Parametria 2'!K:K,'Parametria 2'!L:L)) -> #N/A
A52: 31/12/2025 | B52: 15 | C52: IN-FONDO2 | D52: OSX | E52: 1551112LAN29 | F52: US05968LAN29 | G52: BCOLO 2034 | H52: 5111 | I52: 2 | J52: 1000 | K52: 48614794 | L52: 14464814 | M52: 13478 | N52: 49302 | O52: 3280 | P52: 3.3609 | Q52: RENTA FIJA | R52: 48642595 | S52: 14465769 | U52: 338596669000000 | V52: 301098538000000 | W52: 37498131000000 | X52: -0.070833 | Y52: =+MID(Tabla_Consulta_desde_Reporte_de_Valorización_de_Instrumentos6[[#This Row],[CODIGO_SBS]],7,1) -> 2 | Z52: =Tabla_Consulta_desde_Reporte_de_Valorización_de_Instrumentos6[[#This Row],[CODIGO_SBS]]&"-"&RIGHT(Tabla_Consulta_desde_Reporte_de_Valorización_de_Instrumentos6[[#This Row],[PORTAFOLIO]],1) -> 1551112LAN29-2 | AA52: Deuda corporativa directa - Internacional | AB52: Deuda | AC52: =Tabla_Consulta_desde_Reporte_de_Valorización_de_Instrumentos6[[#This Row],[VALOR_UNITARIO]]*Tabla_Consulta_desde_Reporte_de_Valorización_de_Instrumentos6[[#This Row],[CANTIDAD]] -> 13478000 | AD52: Banco de Colombia | AE52: =_xlfn.IFNA(_xlfn.XLOOKUP(Tabla_Consulta_desde_Reporte_de_Valorización_de_Instrumentos6[[#This Row],[Emisor2]],'Parametria 2'!G:G,'Parametria 2'!F:F,_xlfn.XLOOKUP(Tabla_Consulta_desde_Reporte_de_Valorización_de_Instrumentos6[[#This Row],[Emisor2]],'Valorización de Instrumentos_of'!H:H,'Valorización de Instrumentos_of'!H:H)),_xlfn.XLOOKUP(Tabla_Consulta_desde_Reporte_de_Valorización_de_Instrumentos6[[#This Row],[TITULO]],'Parametria 2'!K:K,'Parametria 2'!L:L)) -> #N/A
A53: 31/12/2025 | B53: 18 | C53: IN-FONDO1 | D53: BNP | E53: 182096345816 | F53: XS0799645816 | G53: IVPRB 6.45 06/3 | H53: 2096 | I53: 3 | J53: 1000 | K53: 21246157 | L53: 21246157 | M53: 18557 | N53: 50221 | O53: 4199 | P53: 1 | Q53: RENTA FIJA | R53: 21210902 | S53: 21210902 | U53: 4252869000 | V53: 3246804000 | W53: 1006065000 | X53: 1.899852 | Y53: =+MID(Tabla_Consulta_desde_Reporte_de_Valorización_de_Instrumentos6[[#This Row],[CODIGO_SBS]],7,1) -> 3 | Z53: =Tabla_Consulta_desde_Reporte_de_Valorización_de_Instrumentos6[[#This Row],[CODIGO_SBS]]&"-"&RIGHT(Tabla_Consulta_desde_Reporte_de_Valorización_de_Instrumentos6[[#This Row],[PORTAFOLIO]],1) -> 182096345816-1 | AA53: Titularización - Renta fija - Internacional | AB53: Deuda | AC53: =Tabla_Consulta_desde_Reporte_de_Valorización_de_Instrumentos6[[#This Row],[VALOR_UNITARIO]]*Tabla_Consulta_desde_Reporte_de_Valorización_de_Instrumentos6[[#This Row],[CANTIDAD]] -> 18557000 | AD53: Línea Amarilla S.A.C. | AE53: =_xlfn.IFNA(_xlfn.XLOOKUP(Tabla_Consulta_desde_Reporte_de_Valorización_de_Instrumentos6[[#This Row],[Emisor2]],'Parametria 2'!G:G,'Parametria 2'!F:F,_xlfn.XLOOKUP(Tabla_Consulta_desde_Reporte_de_Valorización_de_Instrumentos6[[#This Row],[Emisor2]],'Valorización de Instrumentos_of'!H:H,'Valorización de Instrumentos_of'!H:H)),_xlfn.XLOOKUP(Tabla_Consulta_desde_Reporte_de_Valorización_de_Instrumentos6[[#This Row],[TITULO]],'Parametria 2'!K:K,'Parametria 2'!L:L)) -> Lima Expresa
A54: 31/12/2025 | B54: 18 | C54: IN-FONDO2 | D54: BNP | E54: 182096345816 | F54: XS0799645816 | G54: IVPRB 6.45 06/3 | H54: 2096 | I54: 3 | J54: 1000 | K54: 2.4281781e+08 | L54: 2.4281781e+08 | M54: 212084 | N54: 50221 | O54: 4199 | P54: 1 | Q54: RENTA FIJA | R54: 2.4241488e+08 | S54: 2.4241488e+08 | U54: 4252869000 | V54: 3246804000 | W54: 1006065000 | X54: 1.899852 | Y54: =+MID(Tabla_Consulta_desde_Reporte_de_Valorización_de_Instrumentos6[[#This Row],[CODIGO_SBS]],7,1) -> 3 | Z54: =Tabla_Consulta_desde_Reporte_de_Valorización_de_Instrumentos6[[#This Row],[CODIGO_SBS]]&"-"&RIGHT(Tabla_Consulta_desde_Reporte_de_Valorización_de_Instrumentos6[[#This Row],[PORTAFOLIO]],1) -> 182096345816-2 | AA54: Titularización - Renta fija - Internacional | AB54: Deuda | AC54: =Tabla_Consulta_desde_Reporte_de_Valorización_de_Instrumentos6[[#This Row],[VALOR_UNITARIO]]*Tabla_Consulta_desde_Reporte_de_Valorización_de_Instrumentos6[[#This Row],[CANTIDAD]] -> 212084000 | AD54: Línea Amarilla S.A.C. | AE54: =_xlfn.IFNA(_xlfn.XLOOKUP(Tabla_Consulta_desde_Reporte_de_Valorización_de_Instrumentos6[[#This Row],[Emisor2]],'Parametria 2'!G:G,'Parametria 2'!F:F,_xlfn.XLOOKUP(Tabla_Consulta_desde_Reporte_de_Valorización_de_Instrumentos6[[#This Row],[Emisor2]],'Valorización de Instrumentos_of'!H:H,'Valorización de Instrumentos_of'!H:H)),_xlfn.XLOOKUP(Tabla_Consulta_desde_Reporte_de_Valorización_de_Instrumentos6[[#This Row],[TITULO]],'Parametria 2'!K:K,'Parametria 2'!L:L)) -> Lima Expresa
A55: 31/12/2025 | B55: 21 | C55: IN-FONDO1 | D55: BSF | E55: 21003811902A | F55: PEP12100D292 | G55: BIF3BS2A | H55: 0038 | I55: 1 | J55: 1000 | K55: 20536162 | L55: 20536162 | M55: 20000 | N55: 47177 | O55: 1155 | P55: 1 | Q55: RENTA FIJA | R55: 20535736 | S55: 20535736 | T55: GFIE | U55: 22149047000 | V55: 20355021000 | W55: 1794026000 | X55: 0.0212816 | Y55: =+MID(Tabla_Consulta_desde_Reporte_de_Valorización_de_Instrumentos6[[#This Row],[CODIGO_SBS]],7,1) -> 1 | Z55: =Tabla_Consulta_desde_Reporte_de_Valorización_de_Instrumentos6[[#This Row],[CODIGO_SBS]]&"-"&RIGHT(Tabla_Consulta_desde_Reporte_de_Valorización_de_Instrumentos6[[#This Row],[PORTAFOLIO]],1) -> 21003811902A-1 | AA55: Deuda corporativa directa - Local | AB55: Deuda | AC55: =Tabla_Consulta_desde_Reporte_de_Valorización_de_Instrumentos6[[#This Row],[VALOR_UNITARIO]]*Tabla_Consulta_desde_Reporte_de_Valorización_de_Instrumentos6[[#This Row],[CANTIDAD]] -> 20000000 | AD55: Banco Interamericano de Finanzas | AE55: =_xlfn.IFNA(_xlfn.XLOOKUP(Tabla_Consulta_desde_Reporte_de_Valorización_de_Instrumentos6[[#This Row],[Emisor2]],'Parametria 2'!G:G,'Parametria 2'!F:F,_xlfn.XLOOKUP(Tabla_Consulta_desde_Reporte_de_Valorización_de_Instrumentos6[[#This Row],[Emisor2]],'Valorización de Instrumentos_of'!H:H,'Valorización de Instrumentos_of'!H:H)),_xlfn.XLOOKUP(Tabla_Consulta_desde_Reporte_de_Valorización_de_Instrumentos6[[#This Row],[TITULO]],'Parametria 2'!K:K,'Parametria 2'!L:L)) -> Banbif
A56: 31/12/2025 | B56: 21 | C56: IN-FONDO2 | D56: BSF | E56: 21003811902A | F56: PEP12100D292 | G56: BIF3BS2A | H56: 0038 | I56: 1 | J56: 1000 | K56: 5134040.5 | L56: 5134040.5 | M56: 5000 | N56: 47177 | O56: 1155 | P56: 1 | Q56: RENTA FIJA | R56: 5133934 | S56: 5133934 | T56: GFIE | U56: 22149047000 | V56: 20355021000 | W56: 1794026000 | X56: 0.0212816 | Y56: =+MID(Tabla_Consulta_desde_Reporte_de_Valorización_de_Instrumentos6[[#This Row],[CODIGO_SBS]],7,1) -> 1 | Z56: =Tabla_Consulta_desde_Reporte_de_Valorización_de_Instrumentos6[[#This Row],[CODIGO_SBS]]&"-"&RIGHT(Tabla_Consulta_desde_Reporte_de_Valorización_de_Instrumentos6[[#This Row],[PORTAFOLIO]],1) -> 21003811902A-2 | AA56: Deuda corporativa directa - Local | AB56: Deuda | AC56: =Tabla_Consulta_desde_Reporte_de_Valorización_de_Instrumentos6[[#This Row],[VALOR_UNITARIO]]*Tabla_Consulta_desde_Reporte_de_Valorización_de_Instrumentos6[[#This Row],[CANTIDAD]] -> 5000000 | AD56: Banco Interamericano de Finanzas | AE56: =_xlfn.IFNA(_xlfn.XLOOKUP(Tabla_Consulta_desde_Reporte_de_Valorización_de_Instrumentos6[[#This Row],[Emisor2]],'Parametria 2'!G:G,'Parametria 2'!F:F,_xlfn.XLOOKUP(Tabla_Consulta_desde_Reporte_de_Valorización_de_Instrumentos6[[#This Row],[Emisor2]],'Valorización de Instrumentos_of'!H:H,'Valorización de Instrumentos_of'!H:H)),_xlfn.XLOOKUP(Tabla_Consulta_desde_Reporte_de_Valorización_de_Instrumentos6[[#This Row],[TITULO]],'Parametria 2'!K:K,'Parametria 2'!L:L)) -> Banbif
A57: 31/12/2025 | B57: 21 | C57: IN-FONDO2 | D57: BSF | E57: 21001811601A | F57: PEP12030D010 | G57: BN1BS1A | H57: 0018 | I57: 1 | J57: 1000 | K57: 5479726.5 | L57: 5479726.5 | M57: 5176 | N57: 48182 | O57: 2160 | P57: 1 | Q57: RENTA FIJA | R57: 5482093.3 | S57: 5482093.3 | U57: 47334882000 | V57: 43945418000 | W57: 3389464000 | X57: -0.4572594 | Y57: =+MID(Tabla_Consulta_desde_Reporte_de_Valorización_de_Instrumentos6[[#This Row],[CODIGO_SBS]],7,1) -> 1 | Z57: =Tabla_Consulta_desde_Reporte_de_Valorización_de_Instrumentos6[[#This Row],[CODIGO_SBS]]&"-"&RIGHT(Tabla_Consulta_desde_Reporte_de_Valorización_de_Instrumentos6[[#This Row],[PORTAFOLIO]],1) -> 21001811601A-2 | AA57: Deuda corporativa directa - Local | AB57: Deuda | AC57: =Tabla_Consulta_desde_Reporte_de_Valorización_de_Instrumentos6[[#This Row],[VALOR_UNITARIO]]*Tabla_Consulta_desde_Reporte_de_Valorización_de_Instrumentos6[[#This Row],[CANTIDAD]] -> 5176000 | AD57: Banco de la Nación | AE57: =_xlfn.IFNA(_xlfn.XLOOKUP(Tabla_Consulta_desde_Reporte_de_Valorización_de_Instrumentos6[[#This Row],[Emisor2]],'Parametria 2'!G:G,'Parametria 2'!F:F,_xlfn.XLOOKUP(Tabla_Consulta_desde_Reporte_de_Valorización_de_Instrumentos6[[#This Row],[Emisor2]],'Valorización de Instrumentos_of'!H:H,'Valorización de Instrumentos_of'!H:H)),_xlfn.XLOOKUP(Tabla_Consulta_desde_Reporte_de_Valorización_de_Instrumentos6[[#This Row],[TITULO]],'Parametria 2'!K:K,'Parametria 2'!L:L)) -> Banco de la Nación
A58: 31/12/2025 | B58: 21 | C58: IN-FONDO1 | D58: BSF | E58: 2100022V2H78 | F58: US05971V2H78 | G58: BCP 5.8 03/10/2 | H58: 0002 | I58: 2 | J58: 1000 | K58: 50270495 | L58: 14957451 | M58: 14479 | N58: 49378 | O58: 3356 | P58: 3.3609 | Q58: RENTA FIJA | R58: 50280235 | S58: 14952785 | T58: CCOR | U58: 187469765000 | V58: 164938084000 | W58: 22531681000 | X58: 0.322222 | Y58: =+MID(Tabla_Consulta_desde_Reporte_de_Valorización_de_Instrumentos6[[#This Row],[CODIGO_SBS]],7,1) -> 2 | Z58: =Tabla_Consulta_desde_Reporte_de_Valorización_de_Instrumentos6[[#This Row],[CODIGO_SBS]]&"-"&RIGHT(Tabla_Consulta_desde_Reporte_de_Valorización_de_Instrumentos6[[#This Row],[PORTAFOLIO]],1) -> 2100022V2H78-1 | AA58: Deuda corporativa directa - Internacional | AB58: Deuda | AC58: =Tabla_Consulta_desde_Reporte_de_Valorización_de_Instrumentos6[[#This Row],[VALOR_UNITARIO]]*Tabla_Consulta_desde_Reporte_de_Valorización_de_Instrumentos6[[#This Row],[CANTIDAD]] -> 14479000 | AD58: Banco de Crédito del Perú | AE58: =_xlfn.IFNA(_xlfn.XLOOKUP(Tabla_Consulta_desde_Reporte_de_Valorización_de_Instrumentos6[[#This Row],[Emisor2]],'Parametria 2'!G:G,'Parametria 2'!F:F,_xlfn.XLOOKUP(Tabla_Consulta_desde_Reporte_de_Valorización_de_Instrumentos6[[#This Row],[Emisor2]],'Valorización de Instrumentos_of'!H:H,'Valorización de Instrumentos_of'!H:H)),_xlfn.XLOOKUP(Tabla_Consulta_desde_Reporte_de_Valorización_de_Instrumentos6[[#This Row],[TITULO]],'Parametria 2'!K:K,'Parametria 2'!L:L)) -> Banco de Crédito del Perú
A59: 31/12/2025 | B59: 21 | C59: IN-FONDO2 | D59: BSF | E59: 2100022V2H78 | F59: US05971V2H78 | G59: BCP 5.8 03/10/2 | H59: 0002 | I59: 2 | J59: 1000 | K59: 1.0032226e+08 | L59: 29849819 | M59: 28895 | N59: 49378 | O59: 3356 | P59: 3.3609 | Q59: RENTA FIJA | R59: 1.0034169e+08 | S59: 29840509 | T59: CCOR | U59: 187469765000 | V59: 164938084000 | W59: 22531681000 | X59: 0.322222 | Y59: =+MID(Tabla_Consulta_desde_Reporte_de_Valorización_de_Instrumentos6[[#This Row],[CODIGO_SBS]],7,1) -> 2 | Z59: =Tabla_Consulta_desde_Reporte_de_Valorización_de_Instrumentos6[[#This Row],[CODIGO_SBS]]&"-"&RIGHT(Tabla_Consulta_desde_Reporte_de_Valorización_de_Instrumentos6[[#This Row],[PORTAFOLIO]],1) -> 2100022V2H78-2 | AA59: Deuda corporativa directa - Internacional | AB59: Deuda | AC59: =Tabla_Consulta_desde_Reporte_de_Valorización_de_Instrumentos6[[#This Row],[VALOR_UNITARIO]]*Tabla_Consulta_desde_Reporte_de_Valorización_de_Instrumentos6[[#This Row],[CANTIDAD]] -> 28895000 | AD59: Banco de Crédito del Perú | AE59: =_xlfn.IFNA(_xlfn.XLOOKUP(Tabla_Consulta_desde_Reporte_de_Valorización_de_Instrumentos6[[#This Row],[Emisor2]],'Parametria 2'!G:G,'Parametria 2'!F:F,_xlfn.XLOOKUP(Tabla_Consulta_desde_Reporte_de_Valorización_de_Instrumentos6[[#This Row],[Emisor2]],'Valorización de Instrumentos_of'!H:H,'Valorización de Instrumentos_of'!H:H)),_xlfn.XLOOKUP(Tabla_Consulta_desde_Reporte_de_Valorización_de_Instrumentos6[[#This Row],[TITULO]],'Parametria 2'!K:K,'Parametria 2'!L:L)) -> Banco de Crédito del Perú
A60: 31/12/2025 | B60: 21 | C60: IN-FONDO1 | D60: BSF | E60: 2100022V2J35 | F60: US05971V2J35 | G60: BCP2035 | H60: 0002 | I60: 2 | J60: 1000 | K60: 6913698 | L60: 2057097.2 | M60: 1923 | N60: 49520 | O60: 3498 | P60: 3.3609 | Q60: RENTA FIJA | R60: 6914878 | S60: 2056408.1 | T60: CCOR | U60: 187469765000 | V60: 164938084000 | W60: 22531681000 | X60: 0.358333 | Y60: =+MID(Tabla_Consulta_desde_Reporte_de_Valorización_de_Instrumentos6[[#This Row],[CODIGO_SBS]],7,1) -> 2 | Z60: =Tabla_Consulta_desde_Reporte_de_Valorización_de_Instrumentos6[[#This Row],[CODIGO_SBS]]&"-"&RIGHT(Tabla_Consulta_desde_Reporte_de_Valorización_de_Instrumentos6[[#This Row],[PORTAFOLIO]],1) -> 2100022V2J35-1 | AA60: Deuda corporativa directa - Internacional | AB60: Deuda | AC60: =Tabla_Consulta_desde_Reporte_de_Valorización_de_Instrumentos6[[#This Row],[VALOR_UNITARIO]]*Tabla_Consulta_desde_Reporte_de_Valorización_de_Instrumentos6[[#This Row],[CANTIDAD]] -> 1923000 | AD60: Banco de Crédito del Perú | AE60: =_xlfn.IFNA(_xlfn.XLOOKUP(Tabla_Consulta_desde_Reporte_de_Valorización_de_Instrumentos6[[#This Row],[Emisor2]],'Parametria 2'!G:G,'Parametria 2'!F:F,_xlfn.XLOOKUP(Tabla_Consulta_desde_Reporte_de_Valorización_de_Instrumentos6[[#This Row],[Emisor2]],'Valorización de Instrumentos_of'!H:H,'Valorización de Instrumentos_of'!H:H)),_xlfn.XLOOKUP(Tabla_Consulta_desde_Reporte_de_Valorización_de_Instrumentos6[[#This Row],[TITULO]],'Parametria 2'!K:K,'Parametria 2'!L:L)) -> Banco de Crédito del Perú
A61: 31/12/2025 | B61: 21 | C61: IN-FONDO2 | D61: BSF | E61: 2100022V2J35 | F61: US05971V2J35 | G61: BCP2035 | H61: 0002 | I61: 2 | J61: 1000 | K61: 26964501 | L61: 8023000 | M61: 7500 | N61: 49520 | O61: 3498 | P61: 3.3609 | Q61: RENTA FIJA | R61: 26969103 | S61: 8020312.5 | T61: CCOR | U61: 187469765000 | V61: 164938084000 | W61: 22531681000 | X61: 0.358333 | Y61: =+MID(Tabla_Consulta_desde_Reporte_de_Valorización_de_Instrumentos6[[#This Row],[CODIGO_SBS]],7,1) -> 2 | Z61: =Tabla_Consulta_desde_Reporte_de_Valorización_de_Instrumentos6[[#This Row],[CODIGO_SBS]]&"-"&RIGHT(Tabla_Consulta_desde_Reporte_de_Valorización_de_Instrumentos6[[#This Row],[PORTAFOLIO]],1) -> 2100022V2J35-2 | AA61: Deuda corporativa directa - Internacional | AB61: Deuda | AC61: =Tabla_Consulta_desde_Reporte_de_Valorización_de_Instrumentos6[[#This Row],[VALOR_UNITARIO]]*Tabla_Consulta_desde_Reporte_de_Valorización_de_Instrumentos6[[#This Row],[CANTIDAD]] -> 7500000 | AD61: Banco de Crédito del Perú | AE61: =_xlfn.IFNA(_xlfn.XLOOKUP(Tabla_Consulta_desde_Reporte_de_Valorización_de_Instrumentos6[[#This Row],[Emisor2]],'Parametria 2'!G:G,'Parametria 2'!F:F,_xlfn.XLOOKUP(Tabla_Consulta_desde_Reporte_de_Valorización_de_Instrumentos6[[#This Row],[Emisor2]],'Valorización de Instrumentos_of'!H:H,'Valorización de Instrumentos_of'!H:H)),_xlfn.XLOOKUP(Tabla_Consulta_desde_Reporte_de_Valorización_de_Instrumentos6[[#This Row],[TITULO]],'Parametria 2'!K:K,'Parametria 2'!L:L)) -> Banco de Crédito del Perú
A62: 31/12/2025 | B62: 27 | C62: IN-FONDO1 | D62: TCDC | E62: 2721181IRC1U | F62: CVL80070P015 | G62: INRT4.90 | H62: 2118 | I62: 1 | J62: 10000 | K62: 42788373 | L62: 42788373 | M62: 4300 | N62: 46827 | O62: 805 | P62: 1 | Q62: RENTA FIJA | R62: 42794239 | S62: 42794239 | T62: GITC | U62: 15587660000 | V62: 12914429000 | W62: 2673231000 | X62: -1.3640716 | Y62: =+MID(Tabla_Consulta_desde_Reporte_de_Valorización_de_Instrumentos6[[#This Row],[CODIGO_SBS]],7,1) -> 1 | Z62: =Tabla_Consulta_desde_Reporte_de_Valorización_de_Instrumentos6[[#This Row],[CODIGO_SBS]]&"-"&RIGHT(Tabla_Consulta_desde_Reporte_de_Valorización_de_Instrumentos6[[#This Row],[PORTAFOLIO]],1) -> 2721181IRC1U-1 | AA62: Titularización - Renta fija - Internacional | AB62: Deuda | AC62: =Tabla_Consulta_desde_Reporte_de_Valorización_de_Instrumentos6[[#This Row],[VALOR_UNITARIO]]*Tabla_Consulta_desde_Reporte_de_Valorización_de_Instrumentos6[[#This Row],[CANTIDAD]] -> 43000000 | AD62: SINT1INR1U - InRetail | AE62: =_xlfn.IFNA(_xlfn.XLOOKUP(Tabla_Consulta_desde_Reporte_de_Valorización_de_Instrumentos6[[#This Row],[Emisor2]],'Parametria 2'!G:G,'Parametria 2'!F:F,_xlfn.XLOOKUP(Tabla_Consulta_desde_Reporte_de_Valorización_de_Instrumentos6[[#This Row],[Emisor2]],'Valorización de Instrumentos_of'!H:H,'Valorización de Instrumentos_of'!H:H)),_xlfn.XLOOKUP(Tabla_Consulta_desde_Reporte_de_Valorización_de_Instrumentos6[[#This Row],[TITULO]],'Parametria 2'!K:K,'Parametria 2'!L:L)) -> InRetail Consumer
A63: 31/12/2025 | B63: 27 | C63: IN-FONDO2 | D63: TCDC | E63: 2721181IRC1U | F63: CVL80070P015 | G63: INRT4.90 | H63: 2118 | I63: 1 | J63: 10000 | K63: 1.2637496e+08 | L63: 1.2637496e+08 | M63: 12700 | N63: 46827 | O63: 805 | P63: 1 | Q63: RENTA FIJA | R63: 1.2639229e+08 | S63: 1.2639229e+08 | T63: GITC | U63: 15587660000 | V63: 12914429000 | W63: 2673231000 | X63: -1.3640716 | Y63: =+MID(Tabla_Consulta_desde_Reporte_de_Valorización_de_Instrumentos6[[#This Row],[CODIGO_SBS]],7,1) -> 1 | Z63: =Tabla_Consulta_desde_Reporte_de_Valorización_de_Instrumentos6[[#This Row],[CODIGO_SBS]]&"-"&RIGHT(Tabla_Consulta_desde_Reporte_de_Valorización_de_Instrumentos6[[#This Row],[PORTAFOLIO]],1) -> 2721181IRC1U-2 | AA63: Titularización - Renta fija - Internacional | AB63: Deuda | AC63: =Tabla_Consulta_desde_Reporte_de_Valorización_de_Instrumentos6[[#This Row],[VALOR_UNITARIO]]*Tabla_Consulta_desde_Reporte_de_Valorización_de_Instrumentos6[[#This Row],[CANTIDAD]] -> 127000000 | AD63: SINT1INR1U - InRetail | AE63: =_xlfn.IFNA(_xlfn.XLOOKUP(Tabla_Consulta_desde_Reporte_de_Valorización_de_Instrumentos6[[#This Row],[Emisor2]],'Parametria 2'!G:G,'Parametria 2'!F:F,_xlfn.XLOOKUP(Tabla_Consulta_desde_Reporte_de_Valorización_de_Instrumentos6[[#This Row],[Emisor2]],'Valorización de Instrumentos_of'!H:H,'Valorización de Instrumentos_of'!H:H)),_xlfn.XLOOKUP(Tabla_Consulta_desde_Reporte_de_Valorización_de_Instrumentos6[[#This Row],[TITULO]],'Parametria 2'!K:K,'Parametria 2'!L:L)) -> InRetail Consumer
A64: 31/12/2025 | B64: 22 | C64: IN-FONDO1 | D64: BEP | E64: 22211619AA48 | F64: USP82169AA48 | G64: RUTLI 2036 | H64: 2116 | I64: 1 | J64: 1000 | K64: 16219869 | L64: 16219869 | M64: 56108 | N64: 49856 | O64: 3834 | P64: 1 | Q64: RENTA FIJA | R64: 16823030 | S64: 16823030 | U64: 2816710241 | V64: 1846667545 | W64: 970042696 | X64: -10.75 | Y64: =+MID(Tabla_Consulta_desde_Reporte_de_Valorización_de_Instrumentos6[[#This Row],[CODIGO_SBS]],7,1) -> 1 | Z64: =Tabla_Consulta_desde_Reporte_de_Valorización_de_Instrumentos6[[#This Row],[CODIGO_SBS]]&"-"&RIGHT(Tabla_Consulta_desde_Reporte_de_Valorización_de_Instrumentos6[[#This Row],[PORTAFOLIO]],1) -> 22211619AA48-1 | AA64: Deuda corporativa directa - Internacional | AB64: Deuda | AC64: =Tabla_Consulta_desde_Reporte_de_Valorización_de_Instrumentos6[[#This Row],[VALOR_UNITARIO]]*Tabla_Consulta_desde_Reporte_de_Valorización_de_Instrumentos6[[#This Row],[CANTIDAD]] -> 56108000 | AD64: Rutas de Lima | AE64: =_xlfn.IFNA(_xlfn.XLOOKUP(Tabla_Consulta_desde_Reporte_de_Valorización_de_Instrumentos6[[#This Row],[Emisor2]],'Parametria 2'!G:G,'Parametria 2'!F:F,_xlfn.XLOOKUP(Tabla_Consulta_desde_Reporte_de_Valorización_de_Instrumentos6[[#This Row],[Emisor2]],'Valorización de Instrumentos_of'!H:H,'Valorización de Instrumentos_of'!H:H)),_xlfn.XLOOKUP(Tabla_Consulta_desde_Reporte_de_Valorización_de_Instrumentos6[[#This Row],[TITULO]],'Parametria 2'!K:K,'Parametria 2'!L:L)) -> Rutas de Lima
A65: 31/12/2025 | B65: 22 | C65: IN-FONDO2 | D65: BEP | E65: 22211619AA48 | F65: USP82169AA48 | G65: RUTLI 2036 | H65: 2116 | I65: 1 | J65: 1000 | K65: 64445851 | L65: 64445851 | M65: 222932 | N65: 49856 | O65: 3834 | P65: 1 | Q65: RENTA FIJA | R65: 66842370 | S65: 66842370 | U65: 2816710241 | V65: 1846667545 | W65: 970042696 | X65: -10.75 | Y65: =+MID(Tabla_Consulta_desde_Reporte_de_Valorización_de_Instrumentos6[[#This Row],[CODIGO_SBS]],7,1) -> 1 | Z65: =Tabla_Consulta_desde_Reporte_de_Valorización_de_Instrumentos6[[#This Row],[CODIGO_SBS]]&"-"&RIGHT(Tabla_Consulta_desde_Reporte_de_Valorización_de_Instrumentos6[[#This Row],[PORTAFOLIO]],1) -> 22211619AA48-2 | AA65: Deuda corporativa directa - Internacional | AB65: Deuda | AC65: =Tabla_Consulta_desde_Reporte_de_Valorización_de_Instrumentos6[[#This Row],[VALOR_UNITARIO]]*Tabla_Consulta_desde_Reporte_de_Valorización_de_Instrumentos6[[#This Row],[CANTIDAD]] -> 222932000 | AD65: Rutas de Lima | AE65: =_xlfn.IFNA(_xlfn.XLOOKUP(Tabla_Consulta_desde_Reporte_de_Valorización_de_Instrumentos6[[#This Row],[Emisor2]],'Parametria 2'!G:G,'Parametria 2'!F:F,_xlfn.XLOOKUP(Tabla_Consulta_desde_Reporte_de_Valorización_de_Instrumentos6[[#This Row],[Emisor2]],'Valorización de Instrumentos_of'!H:H,'Valorización de Instrumentos_of'!H:H)),_xlfn.XLOOKUP(Tabla_Consulta_desde_Reporte_de_Valorización_de_Instrumentos6[[#This Row],[TITULO]],'Parametria 2'!K:K,'Parametria 2'!L:L)) -> Rutas de Lima
A66: 31/12/2025 | B66: 22 | C66: IN-FONDO1 | D66: BEP | E66: 22212511603A | F66: PEP71320M030 | G66: JPLAZ1BC3A | H66: 2125 | I66: 1 | J66: 1000 | K66: 16444915 | L66: 16444915 | M66: 15000 | N66: 48051 | O66: 2029 | P66: 1 | Q66: RENTA FIJA | R66: 16439629 | S66: 16439629 | T66: GACU | U66: 1960115000 | V66: 1305903000 | W66: 654212000 | X66: 0.3524507 | Y66: =+MID(Tabla_Consulta_desde_Reporte_de_Valorización_de_Instrumentos6[[#This Row],[CODIGO_SBS]],7,1) -> 1 | Z66: =Tabla_Consulta_desde_Reporte_de_Valorización_de_Instrumentos6[[#This Row],[CODIGO_SBS]]&"-"&RIGHT(Tabla_Consulta_desde_Reporte_de_Valorización_de_Instrumentos6[[#This Row],[PORTAFOLIO]],1) -> 22212511603A-1 | AA66: Deuda corporativa directa - Local | AB66: Deuda | AC66: =Tabla_Consulta_desde_Reporte_de_Valorización_de_Instrumentos6[[#This Row],[VALOR_UNITARIO]]*Tabla_Consulta_desde_Reporte_de_Valorización_de_Instrumentos6[[#This Row],[CANTIDAD]] -> 15000000 | AD66: Jockey Plaza | AE66: =_xlfn.IFNA(_xlfn.XLOOKUP(Tabla_Consulta_desde_Reporte_de_Valorización_de_Instrumentos6[[#This Row],[Emisor2]],'Parametria 2'!G:G,'Parametria 2'!F:F,_xlfn.XLOOKUP(Tabla_Consulta_desde_Reporte_de_Valorización_de_Instrumentos6[[#This Row],[Emisor2]],'Valorización de Instrumentos_of'!H:H,'Valorización de Instrumentos_of'!H:H)),_xlfn.XLOOKUP(Tabla_Consulta_desde_Reporte_de_Valorización_de_Instrumentos6[[#This Row],[TITULO]],'Parametria 2'!K:K,'Parametria 2'!L:L)) -> Jockey Plaza
A67: 31/12/2025 | B67: 22 | C67: IN-FONDO2 | D67: BEP | E67: 22212511603A | F67: PEP71320M030 | G67: JPLAZ1BC3A | H67: 2125 | I67: 1 | J67: 1000 | K67: 30697175 | L67: 30697175 | M67: 28000 | N67: 48051 | O67: 2029 | P67: 1 | Q67: RENTA FIJA | R67: 30687307 | S67: 30687307 | T67: GACU | U67: 1960115000 | V67: 1305903000 | W67: 654212000 | X67: 0.3524507 | Y67: =+MID(Tabla_Consulta_desde_Reporte_de_Valorización_de_Instrumentos6[[#This Row],[CODIGO_SBS]],7,1) -> 1 | Z67: =Tabla_Consulta_desde_Reporte_de_Valorización_de_Instrumentos6[[#This Row],[CODIGO_SBS]]&"-"&RIGHT(Tabla_Consulta_desde_Reporte_de_Valorización_de_Instrumentos6[[#This Row],[PORTAFOLIO]],1) -> 22212511603A-2 | AA67: Deuda corporativa directa - Local | AB67: Deuda | AC67: =Tabla_Consulta_desde_Reporte_de_Valorización_de_Instrumentos6[[#This Row],[VALOR_UNITARIO]]*Tabla_Consulta_desde_Reporte_de_Valorización_de_Instrumentos6[[#This Row],[CANTIDAD]] -> 28000000 | AD67: Jockey Plaza | AE67: =_xlfn.IFNA(_xlfn.XLOOKUP(Tabla_Consulta_desde_Reporte_de_Valorización_de_Instrumentos6[[#This Row],[Emisor2]],'Parametria 2'!G:G,'Parametria 2'!F:F,_xlfn.XLOOKUP(Tabla_Consulta_desde_Reporte_de_Valorización_de_Instrumentos6[[#This Row],[Emisor2]],'Valorización de Instrumentos_of'!H:H,'Valorización de Instrumentos_of'!H:H)),_xlfn.XLOOKUP(Tabla_Consulta_desde_Reporte_de_Valorización_de_Instrumentos6[[#This Row],[TITULO]],'Parametria 2'!K:K,'Parametria 2'!L:L)) -> Jockey Plaza
A68: 31/12/2025 | B68: 22 | C68: IN-FONDO1 | D68: BEP | E68: 22212521501A | F68: PEP71320M014 | G68: JPLAZ1BC1A | H68: 2125 | I68: 2 | J68: 1000 | K68: 10015025 | L68: 2979864.1 | M68: 2893 | N68: 47839 | O68: 1817 | P68: 3.3609 | Q68: RENTA FIJA | R68: 10013982 | S68: 2978047.4 | T68: GACU | U68: 1960115000 | V68: 1305903000 | W68: 654212000 | X68: 0.6279485 | Y68: =+MID(Tabla_Consulta_desde_Reporte_de_Valorización_de_Instrumentos6[[#This Row],[CODIGO_SBS]],7,1) -> 2 | Z68: =Tabla_Consulta_desde_Reporte_de_Valorización_de_Instrumentos6[[#This Row],[CODIGO_SBS]]&"-"&RIGHT(Tabla_Consulta_desde_Reporte_de_Valorización_de_Instrumentos6[[#This Row],[PORTAFOLIO]],1) -> 22212521501A-1 | AA68: Deuda corporativa directa - Local | AB68: Deuda | AC68: =Tabla_Consulta_desde_Reporte_de_Valorización_de_Instrumentos6[[#This Row],[VALOR_UNITARIO]]*Tabla_Consulta_desde_Reporte_de_Valorización_de_Instrumentos6[[#This Row],[CANTIDAD]] -> 2893000 | AD68: Jockey Plaza | AE68: =_xlfn.IFNA(_xlfn.XLOOKUP(Tabla_Consulta_desde_Reporte_de_Valorización_de_Instrumentos6[[#This Row],[Emisor2]],'Parametria 2'!G:G,'Parametria 2'!F:F,_xlfn.XLOOKUP(Tabla_Consulta_desde_Reporte_de_Valorización_de_Instrumentos6[[#This Row],[Emisor2]],'Valorización de Instrumentos_of'!H:H,'Valorización de Instrumentos_of'!H:H)),_xlfn.XLOOKUP(Tabla_Consulta_desde_Reporte_de_Valorización_de_Instrumentos6[[#This Row],[TITULO]],'Parametria 2'!K:K,'Parametria 2'!L:L)) -> Jockey Plaza
A69: 31/12/2025 | B69: 22 | C69: IN-FONDO1 | D69: BEP | E69: 22582511802A | F69: PEP73125M056 | G69: PRIMX2BC2A | H69: 5825 | I69: 1 | J69: 10000 | K69: 7682536.7 | L69: 7682536.7 | M69: 700 | N69: 50609 | O69: 4587 | P69: 1 | Q69: RENTA FIJA | R69: 7684712.4 | S69: 7684712.4 | T69: CCOR | U69: 5024202000 | V69: 4179076000 | W69: 845126000 | X69: -3.1082553 | Y69: =+MID(Tabla_Consulta_desde_Reporte_de_Valorización_de_Instrumentos6[[#This Row],[CODIGO_SBS]],7,1) -> 1 | Z69: =Tabla_Consulta_desde_Reporte_de_Valorización_de_Instrumentos6[[#This Row],[CODIGO_SBS]]&"-"&RIGHT(Tabla_Consulta_desde_Reporte_de_Valorización_de_Instrumentos6[[#This Row],[PORTAFOLIO]],1) -> 22582511802A-1 | AA69: Deuda corporativa directa - Local | AB69: Deuda | AC69: =Tabla_Consulta_desde_Reporte_de_Valorización_de_Instrumentos6[[#This Row],[VALOR_UNITARIO]]*Tabla_Consulta_desde_Reporte_de_Valorización_de_Instrumentos6[[#This Row],[CANTIDAD]] -> 7000000 | AD69: Primax | AE69: =_xlfn.IFNA(_xlfn.XLOOKUP(Tabla_Consulta_desde_Reporte_de_Valorización_de_Instrumentos6[[#This Row],[Emisor2]],'Parametria 2'!G:G,'Parametria 2'!F:F,_xlfn.XLOOKUP(Tabla_Consulta_desde_Reporte_de_Valorización_de_Instrumentos6[[#This Row],[Emisor2]],'Valorización de Instrumentos_of'!H:H,'Valorización de Instrumentos_of'!H:H)),_xlfn.XLOOKUP(Tabla_Consulta_desde_Reporte_de_Valorización_de_Instrumentos6[[#This Row],[TITULO]],'Parametria 2'!K:K,'Parametria 2'!L:L)) -> Primax
A70: 31/12/2025 | B70: 22 | C70: IN-FONDO1 | D70: BEP | E70: 22582511801A | F70: PEP73125M049 | G70: PRIMX2BC1A | H70: 5825 | I70: 1 | J70: 10000 | K70: 6323612.7 | L70: 6323612.7 | M70: 584 | N70: 46957 | O70: 935 | P70: 1 | Q70: RENTA FIJA | R70: 6324982.6 | S70: 6324982.6 | T70: CCOR | U70: 5024202000 | V70: 4179076000 | W70: 845126000 | X70: -2.3456718 | Y70: =+MID(Tabla_Consulta_desde_Reporte_de_Valorización_de_Instrumentos6[[#This Row],[CODIGO_SBS]],7,1) -> 1 | Z70: =Tabla_Consulta_desde_Reporte_de_Valorización_de_Instrumentos6[[#This Row],[CODIGO_SBS]]&"-"&RIGHT(Tabla_Consulta_desde_Reporte_de_Valorización_de_Instrumentos6[[#This Row],[PORTAFOLIO]],1) -> 22582511801A-1 | AA70: Deuda corporativa directa - Local | AB70: Deuda | AC70: =Tabla_Consulta_desde_Reporte_de_Valorización_de_Instrumentos6[[#This Row],[VALOR_UNITARIO]]*Tabla_Consulta_desde_Reporte_de_Valorización_de_Instrumentos6[[#This Row],[CANTIDAD]] -> 5840000 | AD70: Primax | AE70: =_xlfn.IFNA(_xlfn.XLOOKUP(Tabla_Consulta_desde_Reporte_de_Valorización_de_Instrumentos6[[#This Row],[Emisor2]],'Parametria 2'!G:G,'Parametria 2'!F:F,_xlfn.XLOOKUP(Tabla_Consulta_desde_Reporte_de_Valorización_de_Instrumentos6[[#This Row],[Emisor2]],'Valorización de Instrumentos_of'!H:H,'Valorización de Instrumentos_of'!H:H)),_xlfn.XLOOKUP(Tabla_Consulta_desde_Reporte_de_Valorización_de_Instrumentos6[[#This Row],[TITULO]],'Parametria 2'!K:K,'Parametria 2'!L:L)) -> Primax
A71: 31/12/2025 | B71: 22 | C71: IN-FONDO2 | D71: BEP | E71: 22582511801A | F71: PEP73125M049 | G71: PRIMX2BC1A | H71: 5825 | I71: 1 | J71: 10000 | K71: 11228744 | L71: 11228744 | M71: 1037 | N71: 46957 | O71: 935 | P71: 1 | Q71: RENTA FIJA | R71: 11231176 | S71: 11231176 | T71: CCOR | U71: 5024202000 | V71: 4179076000 | W71: 845126000 | X71: -2.3456718 | Y71: =+MID(Tabla_Consulta_desde_Reporte_de_Valorización_de_Instrumentos6[[#This Row],[CODIGO_SBS]],7,1) -> 1 | Z71: =Tabla_Consulta_desde_Reporte_de_Valorización_de_Instrumentos6[[#This Row],[CODIGO_SBS]]&"-"&RIGHT(Tabla_Consulta_desde_Reporte_de_Valorización_de_Instrumentos6[[#This Row],[PORTAFOLIO]],1) -> 22582511801A-2 | AA71: Deuda corporativa directa - Local | AB71: Deuda | AC71: =Tabla_Consulta_desde_Reporte_de_Valorización_de_Instrumentos6[[#This Row],[VALOR_UNITARIO]]*Tabla_Consulta_desde_Reporte_de_Valorización_de_Instrumentos6[[#This Row],[CANTIDAD]] -> 10370000 | AD71: Primax | AE71: =_xlfn.IFNA(_xlfn.XLOOKUP(Tabla_Consulta_desde_Reporte_de_Valorización_de_Instrumentos6[[#This Row],[Emisor2]],'Parametria 2'!G:G,'Parametria 2'!F:F,_xlfn.XLOOKUP(Tabla_Consulta_desde_Reporte_de_Valorización_de_Instrumentos6[[#This Row],[Emisor2]],'Valorización de Instrumentos_of'!H:H,'Valorización de Instrumentos_of'!H:H)),_xlfn.XLOOKUP(Tabla_Consulta_desde_Reporte_de_Valorización_de_Instrumentos6[[#This Row],[TITULO]],'Parametria 2'!K:K,'Parametria 2'!L:L)) -> Primax
A72: 31/12/2025 | B72: 22 | C72: IN-FONDO1 | D72: BEP | E72: 22582511603A | F72: PEP73125M031 | G72: PRIMX1BC3A | H72: 5825 | I72: 1 | J72: 1000 | K72: 6225878.9 | L72: 6225878.9 | M72: 5500 | N72: 49955 | O72: 3933 | P72: 1 | Q72: RENTA FIJA | R72: 6214227.8 | S72: 6214227.8 | T72: CCOR | U72: 5024202000 | V72: 4179076000 | W72: 845126000 | X72: 2.1183804 | Y72: =+MID(Tabla_Consulta_desde_Reporte_de_Valorización_de_Instrumentos6[[#This Row],[CODIGO_SBS]],7,1) -> 1 | Z72: =Tabla_Consulta_desde_Reporte_de_Valorización_de_Instrumentos6[[#This Row],[CODIGO_SBS]]&"-"&RIGHT(Tabla_Consulta_desde_Reporte_de_Valorización_de_Instrumentos6[[#This Row],[PORTAFOLIO]],1) -> 22582511603A-1 | AA72: Deuda corporativa directa - Local | AB72: Deuda | AC72: =Tabla_Consulta_desde_Reporte_de_Valorización_de_Instrumentos6[[#This Row],[VALOR_UNITARIO]]*Tabla_Consulta_desde_Reporte_de_Valorización_de_Instrumentos6[[#This Row],[CANTIDAD]] -> 5500000 | AD72: Primax | AE72: =_xlfn.IFNA(_xlfn.XLOOKUP(Tabla_Consulta_desde_Reporte_de_Valorización_de_Instrumentos6[[#This Row],[Emisor2]],'Parametria 2'!G:G,'Parametria 2'!F:F,_xlfn.XLOOKUP(Tabla_Consulta_desde_Reporte_de_Valorización_de_Instrumentos6[[#This Row],[Emisor2]],'Valorización de Instrumentos_of'!H:H,'Valorización de Instrumentos_of'!H:H)),_xlfn.XLOOKUP(Tabla_Consulta_desde_Reporte_de_Valorización_de_Instrumentos6[[#This Row],[TITULO]],'Parametria 2'!K:K,'Parametria 2'!L:L)) -> Primax
A73: 31/12/2025 | B73: 22 | C73: IN-FONDO2 | D73: BEP | E73: 22582511603A | F73: PEP73125M031 | G73: PRIMX1BC3A | H73: 5825 | I73: 1 | J73: 1000 | K73: 19793767 | L73: 19793767 | M73: 17486 | N73: 49955 | O73: 3933 | P73: 1 | Q73: RENTA FIJA | R73: 19756725 | S73: 19756725 | T73: CCOR | U73: 5024202000 | V73: 4179076000 | W73: 845126000 | X73: 2.1183804 | Y73: =+MID(Tabla_Consulta_desde_Reporte_de_Valorización_de_Instrumentos6[[#This Row],[CODIGO_SBS]],7,1) -> 1 | Z73: =Tabla_Consulta_desde_Reporte_de_Valorización_de_Instrumentos6[[#This Row],[CODIGO_SBS]]&"-"&RIGHT(Tabla_Consulta_desde_Reporte_de_Valorización_de_Instrumentos6[[#This Row],[PORTAFOLIO]],1) -> 22582511603A-2 | AA73: Deuda corporativa directa - Local | AB73: Deuda | AC73: =Tabla_Consulta_desde_Reporte_de_Valorización_de_Instrumentos6[[#This Row],[VALOR_UNITARIO]]*Tabla_Consulta_desde_Reporte_de_Valorización_de_Instrumentos6[[#This Row],[CANTIDAD]] -> 17486000 | AD73: Primax | AE73: =_xlfn.IFNA(_xlfn.XLOOKUP(Tabla_Consulta_desde_Reporte_de_Valorización_de_Instrumentos6[[#This Row],[Emisor2]],'Parametria 2'!G:G,'Parametria 2'!F:F,_xlfn.XLOOKUP(Tabla_Consulta_desde_Reporte_de_Valorización_de_Instrumentos6[[#This Row],[Emisor2]],'Valorización de Instrumentos_of'!H:H,'Valorización de Instrumentos_of'!H:H)),_xlfn.XLOOKUP(Tabla_Consulta_desde_Reporte_de_Valorización_de_Instrumentos6[[#This Row],[TITULO]],'Parametria 2'!K:K,'Parametria 2'!L:L)) -> Primax
A74: 31/12/2025 | B74: 22 | C74: IN-FONDO1 | D74: BEP | E74: 22582811701A | F74: PEP73668M014 | G74: HERME1BC1A | H74: 5828 | I74: 1 | J74: 1000 | K74: 6957636.3 | L74: 6957636.3 | M74: 12749 | N74: 47545 | O74: 1523 | P74: 1 | Q74: RENTA FIJA | R74: 6957489.8 | S74: 6957489.8 | U74: 1625198000 | V74: 791660000 | W74: 833538000 | X74: 0.0114911 | Y74: =+MID(Tabla_Consulta_desde_Reporte_de_Valorización_de_Instrumentos6[[#This Row],[CODIGO_SBS]],7,1) -> 1 | Z74: =Tabla_Consulta_desde_Reporte_de_Valorización_de_Instrumentos6[[#This Row],[CODIGO_SBS]]&"-"&RIGHT(Tabla_Consulta_desde_Reporte_de_Valorización_de_Instrumentos6[[#This Row],[PORTAFOLIO]],1) -> 22582811701A-1 | AA74: Deuda corporativa directa - Local | AB74: Deuda | AC74: =Tabla_Consulta_desde_Reporte_de_Valorización_de_Instrumentos6[[#This Row],[VALOR_UNITARIO]]*Tabla_Consulta_desde_Reporte_de_Valorización_de_Instrumentos6[[#This Row],[CANTIDAD]] -> 12749000 | AD74: Hermes | AE74: =_xlfn.IFNA(_xlfn.XLOOKUP(Tabla_Consulta_desde_Reporte_de_Valorización_de_Instrumentos6[[#This Row],[Emisor2]],'Parametria 2'!G:G,'Parametria 2'!F:F,_xlfn.XLOOKUP(Tabla_Consulta_desde_Reporte_de_Valorización_de_Instrumentos6[[#This Row],[Emisor2]],'Valorización de Instrumentos_of'!H:H,'Valorización de Instrumentos_of'!H:H)),_xlfn.XLOOKUP(Tabla_Consulta_desde_Reporte_de_Valorización_de_Instrumentos6[[#This Row],[TITULO]],'Parametria 2'!K:K,'Parametria 2'!L:L)) -> Hermes
A75: 31/12/2025 | B75: 22 | C75: IN-FONDO1 | D75: BEP | E75: 22583521701U | F75: CVL14017HL12 | G75: BCIR1P1ESA | H75: 5835 | I75: 2 | J75: 1000 | K75: 30547552 | L75: 9089098.9 | M75: 12000 | N75: 48570 | O75: 2548 | P75: 3.3609 | Q75: RENTA FIJA | R75: 30535894 | S75: 9081036.6 | U75: 79333000 | V75: 66161000 | W75: 13172000 | X75: 0.6718567 | Y75: =+MID(Tabla_Consulta_desde_Reporte_de_Valorización_de_Instrumentos6[[#This Row],[CODIGO_SBS]],7,1) -> 2 | Z75: =Tabla_Consulta_desde_Reporte_de_Valorización_de_Instrumentos6[[#This Row],[CODIGO_SBS]]&"-"&RIGHT(Tabla_Consulta_desde_Reporte_de_Valorización_de_Instrumentos6[[#This Row],[PORTAFOLIO]],1) -> 22583521701U-1 | AA75: Deuda corporativa directa - Local | AB75: Deuda | AC75: =Tabla_Consulta_desde_Reporte_de_Valorización_de_Instrumentos6[[#This Row],[VALOR_UNITARIO]]*Tabla_Consulta_desde_Reporte_de_Valorización_de_Instrumentos6[[#This Row],[CANTIDAD]] -> 12000000 | AD75: Inca Rail | AE75: =_xlfn.IFNA(_xlfn.XLOOKUP(Tabla_Consulta_desde_Reporte_de_Valorización_de_Instrumentos6[[#This Row],[Emisor2]],'Parametria 2'!G:G,'Parametria 2'!F:F,_xlfn.XLOOKUP(Tabla_Consulta_desde_Reporte_de_Valorización_de_Instrumentos6[[#This Row],[Emisor2]],'Valorización de Instrumentos_of'!H:H,'Valorización de Instrumentos_of'!H:H)),_xlfn.XLOOKUP(Tabla_Consulta_desde_Reporte_de_Valorización_de_Instrumentos6[[#This Row],[TITULO]],'Parametria 2'!K:K,'Parametria 2'!L:L)) -> Inca Rail
A76: 31/12/2025 | B76: 22 | C76: IN-FONDO1 | D76: BEP | E76: 2258402PAE36 | F76: USP5300PAE36 | G76: HNTOIL2038 | H76: 5840 | I76: 2 | J76: 1000 | K76: 46769899 | L76: 13915885 | M76: 12500 | N76: 50714 | O76: 4692 | P76: 3.3609 | Q76: RENTA FIJA | R76: 46750660 | S76: 13903128 | U76: 721469000 | V76: 616993000 | W76: 104476000 | X76: 1.020555 | Y76: =+MID(Tabla_Consulta_desde_Reporte_de_Valorización_de_Instrumentos6[[#This Row],[CODIGO_SBS]],7,1) -> 2 | Z76: =Tabla_Consulta_desde_Reporte_de_Valorización_de_Instrumentos6[[#This Row],[CODIGO_SBS]]&"-"&RIGHT(Tabla_Consulta_desde_Reporte_de_Valorización_de_Instrumentos6[[#This Row],[PORTAFOLIO]],1) -> 2258402PAE36-1 | AA76: Deuda corporativa directa - Internacional | AB76: Deuda | AC76: =Tabla_Consulta_desde_Reporte_de_Valorización_de_Instrumentos6[[#This Row],[VALOR_UNITARIO]]*Tabla_Consulta_desde_Reporte_de_Valorización_de_Instrumentos6[[#This Row],[CANTIDAD]] -> 12500000 | AD76: Hunt Oil | AE76: =_xlfn.IFNA(_xlfn.XLOOKUP(Tabla_Consulta_desde_Reporte_de_Valorización_de_Instrumentos6[[#This Row],[Emisor2]],'Parametria 2'!G:G,'Parametria 2'!F:F,_xlfn.XLOOKUP(Tabla_Consulta_desde_Reporte_de_Valorización_de_Instrumentos6[[#This Row],[Emisor2]],'Valorización de Instrumentos_of'!H:H,'Valorización de Instrumentos_of'!H:H)),_xlfn.XLOOKUP(Tabla_Consulta_desde_Reporte_de_Valorización_de_Instrumentos6[[#This Row],[TITULO]],'Parametria 2'!K:K,'Parametria 2'!L:L)) -> Hunt Oil
A77: 31/12/2025 | B77: 22 | C77: IN-FONDO2 | D77: BEP | E77: 2258402PAE36 | F77: USP5300PAE36 | G77: HNTOIL2038 | H77: 5840 | I77: 2 | J77: 1000 | K77: 41157511 | L77: 12245979 | M77: 11000 | N77: 50714 | O77: 4692 | P77: 3.3609 | Q77: RENTA FIJA | R77: 41140581 | S77: 12234753 | U77: 721469000 | V77: 616993000 | W77: 104476000 | X77: 1.020555 | Y77: =+MID(Tabla_Consulta_desde_Reporte_de_Valorización_de_Instrumentos6[[#This Row],[CODIGO_SBS]],7,1) -> 2 | Z77: =Tabla_Consulta_desde_Reporte_de_Valorización_de_Instrumentos6[[#This Row],[CODIGO_SBS]]&"-"&RIGHT(Tabla_Consulta_desde_Reporte_de_Valorización_de_Instrumentos6[[#This Row],[PORTAFOLIO]],1) -> 2258402PAE36-2 | AA77: Deuda corporativa directa - Internacional | AB77: Deuda | AC77: =Tabla_Consulta_desde_Reporte_de_Valorización_de_Instrumentos6[[#This Row],[VALOR_UNITARIO]]*Tabla_Consulta_desde_Reporte_de_Valorización_de_Instrumentos6[[#This Row],[CANTIDAD]] -> 11000000 | AD77: Hunt Oil | AE77: =_xlfn.IFNA(_xlfn.XLOOKUP(Tabla_Consulta_desde_Reporte_de_Valorización_de_Instrumentos6[[#This Row],[Emisor2]],'Parametria 2'!G:G,'Parametria 2'!F:F,_xlfn.XLOOKUP(Tabla_Consulta_desde_Reporte_de_Valorización_de_Instrumentos6[[#This Row],[Emisor2]],'Valorización de Instrumentos_of'!H:H,'Valorización de Instrumentos_of'!H:H)),_xlfn.XLOOKUP(Tabla_Consulta_desde_Reporte_de_Valorización_de_Instrumentos6[[#This Row],[TITULO]],'Parametria 2'!K:K,'Parametria 2'!L:L)) -> Hunt Oil
A78: 31/12/2025 | B78: 22 | C78: IN-FONDO1 | D78: BEP | E78: 22584221801U | F78: CVL74200B016 | G78: INTBC1A | H78: 5842 | I78: 2 | J78: 5000 | K78: 58341138 | L78: 17358784 | M78: 3470 | N78: 50660 | O78: 4638 | P78: 3.3609 | Q78: RENTA FIJA | R78: 58275762 | S78: 17330566 | T78: GITU | U78: 1692171000 | V78: 1063440000 | W78: 628731000 | X78: 8.1319343 | Y78: =+MID(Tabla_Consulta_desde_Reporte_de_Valorización_de_Instrumentos6[[#This Row],[CODIGO_SBS]],7,1) -> 2 | Z78: =Tabla_Consulta_desde_Reporte_de_Valorización_de_Instrumentos6[[#This Row],[CODIGO_SBS]]&"-"&RIGHT(Tabla_Consulta_desde_Reporte_de_Valorización_de_Instrumentos6[[#This Row],[PORTAFOLIO]],1) -> 22584221801U-1 | AA78: Deuda corporativa directa - Local | AB78: Deuda | AC78: =Tabla_Consulta_desde_Reporte_de_Valorización_de_Instrumentos6[[#This Row],[VALOR_UNITARIO]]*Tabla_Consulta_desde_Reporte_de_Valorización_de_Instrumentos6[[#This Row],[CANTIDAD]] -> 17350000 | AD78: Inversiones Nacionales de Turismo S.A. | AE78: =_xlfn.IFNA(_xlfn.XLOOKUP(Tabla_Consulta_desde_Reporte_de_Valorización_de_Instrumentos6[[#This Row],[Emisor2]],'Parametria 2'!G:G,'Parametria 2'!F:F,_xlfn.XLOOKUP(Tabla_Consulta_desde_Reporte_de_Valorización_de_Instrumentos6[[#This Row],[Emisor2]],'Valorización de Instrumentos_of'!H:H,'Valorización de Instrumentos_of'!H:H)),_xlfn.XLOOKUP(Tabla_Consulta_desde_Reporte_de_Valorización_de_Instrumentos6[[#This Row],[TITULO]],'Parametria 2'!K:K,'Parametria 2'!L:L)) -> Intursa
A79: 31/12/2025 | B79: 22 | C79: IN-FONDO2 | D79: BEP | E79: 22584221801U | F79: CVL74200B016 | G79: INTBC1A | H79: 5842 | I79: 2 | J79: 5000 | K79: 58341138 | L79: 17358784 | M79: 3470 | N79: 50660 | O79: 4638 | P79: 3.3609 | Q79: RENTA FIJA | R79: 58275762 | S79: 17330566 | T79: GITU | U79: 1692171000 | V79: 1063440000 | W79: 628731000 | X79: 8.1319343 | Y79: =+MID(Tabla_Consulta_desde_Reporte_de_Valorización_de_Instrumentos6[[#This Row],[CODIGO_SBS]],7,1) -> 2 | Z79: =Tabla_Consulta_desde_Reporte_de_Valorización_de_Instrumentos6[[#This Row],[CODIGO_SBS]]&"-"&RIGHT(Tabla_Consulta_desde_Reporte_de_Valorización_de_Instrumentos6[[#This Row],[PORTAFOLIO]],1) -> 22584221801U-2 | AA79: Deuda corporativa directa - Local | AB79: Deuda | AC79: =Tabla_Consulta_desde_Reporte_de_Valorización_de_Instrumentos6[[#This Row],[VALOR_UNITARIO]]*Tabla_Consulta_desde_Reporte_de_Valorización_de_Instrumentos6[[#This Row],[CANTIDAD]] -> 17350000 | AD79: Inversiones Nacionales de Turismo S.A. | AE79: =_xlfn.IFNA(_xlfn.XLOOKUP(Tabla_Consulta_desde_Reporte_de_Valorización_de_Instrumentos6[[#This Row],[Emisor2]],'Parametria 2'!G:G,'Parametria 2'!F:F,_xlfn.XLOOKUP(Tabla_Consulta_desde_Reporte_de_Valorización_de_Instrumentos6[[#This Row],[Emisor2]],'Valorización de Instrumentos_of'!H:H,'Valorización de Instrumentos_of'!H:H)),_xlfn.XLOOKUP(Tabla_Consulta_desde_Reporte_de_Valorización_de_Instrumentos6[[#This Row],[TITULO]],'Parametria 2'!K:K,'Parametria 2'!L:L)) -> Intursa
A80: 31/12/2025 | B80: 22 | C80: IN-FONDO1 | D80: BEP | E80: 22586511901A | F80: CVL75840TB14 | G80: TECSB1P1A | H80: 5865 | I80: 1 | J80: 10000 | K80: 1764204.3 | L80: 1764204.3 | M80: 180 | N80: 49221 | O80: 3199 | P80: 1 | Q80: RENTA FIJA | R80: 1760024.5 | S80: 1760024.5 | U80: 208079720 | V80: 112987535 | W80: 95092185 | X80: 23.221147 | Y80: =+MID(Tabla_Consulta_desde_Reporte_de_Valorización_de_Instrumentos6[[#This Row],[CODIGO_SBS]],7,1) -> 1 | Z80: =Tabla_Consulta_desde_Reporte_de_Valorización_de_Instrumentos6[[#This Row],[CODIGO_SBS]]&"-"&RIGHT(Tabla_Consulta_desde_Reporte_de_Valorización_de_Instrumentos6[[#This Row],[PORTAFOLIO]],1) -> 22586511901A-1 | AA80: Deuda corporativa directa - Local | AB80: Deuda | AC80: =Tabla_Consulta_desde_Reporte_de_Valorización_de_Instrumentos6[[#This Row],[VALOR_UNITARIO]]*Tabla_Consulta_desde_Reporte_de_Valorización_de_Instrumentos6[[#This Row],[CANTIDAD]] -> 1800000 | AD80: Tecsup | AE80: =_xlfn.IFNA(_xlfn.XLOOKUP(Tabla_Consulta_desde_Reporte_de_Valorización_de_Instrumentos6[[#This Row],[Emisor2]],'Parametria 2'!G:G,'Parametria 2'!F:F,_xlfn.XLOOKUP(Tabla_Consulta_desde_Reporte_de_Valorización_de_Instrumentos6[[#This Row],[Emisor2]],'Valorización de Instrumentos_of'!H:H,'Valorización de Instrumentos_of'!H:H)),_xlfn.XLOOKUP(Tabla_Consulta_desde_Reporte_de_Valorización_de_Instrumentos6[[#This Row],[TITULO]],'Parametria 2'!K:K,'Parametria 2'!L:L)) -> Tecsup
A81: 31/12/2025 | B81: 22 | C81: IN-FONDO1 | D81: BEP | E81: 225917115156 | F81: XS2693815156 | G81: SILAPE2033 | H81: 5917 | I81: 1 | J81: 1000 | K81: 82812605 | L81: 82812605 | M81: 75800 | N81: 48843 | O81: 2821 | P81: 1 | Q81: RENTA FIJA | R81: 82276436 | S81: 82276436 | T81: GSL | U81: 378150000 | V81: 380055000 | W81: 0 | X81: 7.073472 | Y81: =+MID(Tabla_Consulta_desde_Reporte_de_Valorización_de_Instrumentos6[[#This Row],[CODIGO_SBS]],7,1) -> 1 | Z81: =Tabla_Consulta_desde_Reporte_de_Valorización_de_Instrumentos6[[#This Row],[CODIGO_SBS]]&"-"&RIGHT(Tabla_Consulta_desde_Reporte_de_Valorización_de_Instrumentos6[[#This Row],[PORTAFOLIO]],1) -> 225917115156-1 | AA81: Deuda corporativa directa - Local | AB81: Deuda | AC81: =Tabla_Consulta_desde_Reporte_de_Valorización_de_Instrumentos6[[#This Row],[VALOR_UNITARIO]]*Tabla_Consulta_desde_Reporte_de_Valorización_de_Instrumentos6[[#This Row],[CANTIDAD]] -> 75800000 | AD81: Site del Perú | AE81: =_xlfn.IFNA(_xlfn.XLOOKUP(Tabla_Consulta_desde_Reporte_de_Valorización_de_Instrumentos6[[#This Row],[Emisor2]],'Parametria 2'!G:G,'Parametria 2'!F:F,_xlfn.XLOOKUP(Tabla_Consulta_desde_Reporte_de_Valorización_de_Instrumentos6[[#This Row],[Emisor2]],'Valorización de Instrumentos_of'!H:H,'Valorización de Instrumentos_of'!H:H)),_xlfn.XLOOKUP(Tabla_Consulta_desde_Reporte_de_Valorización_de_Instrumentos6[[#This Row],[TITULO]],'Parametria 2'!K:K,'Parametria 2'!L:L)) -> Site del Perú
A82: 31/12/2025 | B82: 22 | C82: IN-FONDO2 | D82: BEP | E82: 225917115156 | F82: XS2693815156 | G82: SILAPE2033 | H82: 5917 | I82: 1 | J82: 1000 | K82: 1.3896785e+08 | L82: 1.3896785e+08 | M82: 127200 | N82: 48843 | O82: 2821 | P82: 1 | Q82: RENTA FIJA | R82: 1.3806811e+08 | S82: 1.3806811e+08 | T82: GSL | U82: 378150000 | V82: 380055000 | W82: 0 | X82: 7.073472 | Y82: =+MID(Tabla_Consulta_desde_Reporte_de_Valorización_de_Instrumentos6[[#This Row],[CODIGO_SBS]],7,1) -> 1 | Z82: =Tabla_Consulta_desde_Reporte_de_Valorización_de_Instrumentos6[[#This Row],[CODIGO_SBS]]&"-"&RIGHT(Tabla_Consulta_desde_Reporte_de_Valorización_de_Instrumentos6[[#This Row],[PORTAFOLIO]],1) -> 225917115156-2 | AA82: Deuda corporativa directa - Local | AB82: Deuda | AC82: =Tabla_Consulta_desde_Reporte_de_Valorización_de_Instrumentos6[[#This Row],[VALOR_UNITARIO]]*Tabla_Consulta_desde_Reporte_de_Valorización_de_Instrumentos6[[#This Row],[CANTIDAD]] -> 127200000 | AD82: Site del Perú | AE82: =_xlfn.IFNA(_xlfn.XLOOKUP(Tabla_Consulta_desde_Reporte_de_Valorización_de_Instrumentos6[[#This Row],[Emisor2]],'Parametria 2'!G:G,'Parametria 2'!F:F,_xlfn.XLOOKUP(Tabla_Consulta_desde_Reporte_de_Valorización_de_Instrumentos6[[#This Row],[Emisor2]],'Valorización de Instrumentos_of'!H:H,'Valorización de Instrumentos_of'!H:H)),_xlfn.XLOOKUP(Tabla_Consulta_desde_Reporte_de_Valorización_de_Instrumentos6[[#This Row],[TITULO]],'Parametria 2'!K:K,'Parametria 2'!L:L)) -> Site del Perú
A83: 31/12/2025 | B83: 22 | C83: IN-FONDO1 | D83: BEP | E83: 2220111KEA71 | F83: USP0161KEA71 | G83: ALI2032 | H83: 2011 | I83: 1 | J83: 1000 | K83: 1.3301247e+08 | L83: 1.3301247e+08 | M83: 127200 | N83: 48381 | O83: 2359 | P83: 1 | Q83: RENTA FIJA | R83: 1.3293707e+08 | S83: 1.3293707e+08 | T83: GROM | U83: 9255978000 | V83: 6603309000 | W83: 2652669000 | X83: 0.592778 | Y83: =+MID(Tabla_Consulta_desde_Reporte_de_Valorización_de_Instrumentos6[[#This Row],[CODIGO_SBS]],7,1) -> 1 | Z83: =Tabla_Consulta_desde_Reporte_de_Valorización_de_Instrumentos6[[#This Row],[CODIGO_SBS]]&"-"&RIGHT(Tabla_Consulta_desde_Reporte_de_Valorización_de_Instrumentos6[[#This Row],[PORTAFOLIO]],1) -> 2220111KEA71-1 | AA83: Deuda corporativa directa - Internacional | AB83: Deuda | AC83: =Tabla_Consulta_desde_Reporte_de_Valorización_de_Instrumentos6[[#This Row],[VALOR_UNITARIO]]*Tabla_Consulta_desde_Reporte_de_Valorización_de_Instrumentos6[[#This Row],[CANTIDAD]] -> 127200000 | AD83: Alicorp | AE83: =_xlfn.IFNA(_xlfn.XLOOKUP(Tabla_Consulta_desde_Reporte_de_Valorización_de_Instrumentos6[[#This Row],[Emisor2]],'Parametria 2'!G:G,'Parametria 2'!F:F,_xlfn.XLOOKUP(Tabla_Consulta_desde_Reporte_de_Valorización_de_Instrumentos6[[#This Row],[Emisor2]],'Valorización de Instrumentos_of'!H:H,'Valorización de Instrumentos_of'!H:H)),_xlfn.XLOOKUP(Tabla_Consulta_desde_Reporte_de_Valorización_de_Instrumentos6[[#This Row],[TITULO]],'Parametria 2'!K:K,'Parametria 2'!L:L)) -> Alicorp
A84: 31/12/2025 | B84: 22 | C84: IN-FONDO2 | D84: BEP | E84: 2220111KEA71 | F84: USP0161KEA71 | G84: ALI2032 | H84: 2011 | I84: 1 | J84: 1000 | K84: 1.2422863e+08 | L84: 1.2422863e+08 | M84: 118800 | N84: 48381 | O84: 2359 | P84: 1 | Q84: RENTA FIJA | R84: 1.2415821e+08 | S84: 1.2415821e+08 | T84: GROM | U84: 9255978000 | V84: 6603309000 | W84: 2652669000 | X84: 0.592778 | Y84: =+MID(Tabla_Consulta_desde_Reporte_de_Valorización_de_Instrumentos6[[#This Row],[CODIGO_SBS]],7,1) -> 1 | Z84: =Tabla_Consulta_desde_Reporte_de_Valorización_de_Instrumentos6[[#This Row],[CODIGO_SBS]]&"-"&RIGHT(Tabla_Consulta_desde_Reporte_de_Valorización_de_Instrumentos6[[#This Row],[PORTAFOLIO]],1) -> 2220111KEA71-2 | AA84: Deuda corporativa directa - Internacional | AB84: Deuda | AC84: =Tabla_Consulta_desde_Reporte_de_Valorización_de_Instrumentos6[[#This Row],[VALOR_UNITARIO]]*Tabla_Consulta_desde_Reporte_de_Valorización_de_Instrumentos6[[#This Row],[CANTIDAD]] -> 118800000 | AD84: Alicorp | AE84: =_xlfn.IFNA(_xlfn.XLOOKUP(Tabla_Consulta_desde_Reporte_de_Valorización_de_Instrumentos6[[#This Row],[Emisor2]],'Parametria 2'!G:G,'Parametria 2'!F:F,_xlfn.XLOOKUP(Tabla_Consulta_desde_Reporte_de_Valorización_de_Instrumentos6[[#This Row],[Emisor2]],'Valorización de Instrumentos_of'!H:H,'Valorización de Instrumentos_of'!H:H)),_xlfn.XLOOKUP(Tabla_Consulta_desde_Reporte_de_Valorización_de_Instrumentos6[[#This Row],[TITULO]],'Parametria 2'!K:K,'Parametria 2'!L:L)) -> Alicorp
A85: 31/12/2025 | B85: 22 | C85: IN-FONDO1 | D85: BEP | E85: 2220082PAB78 | F85: USP6680PAB78 | G85: BUENAV 6.8 02/0 | H85: 2008 | I85: 2 | J85: 1000 | K85: 53056043 | L85: 15786261 | M85: 14765 | N85: 48248 | O85: 2226 | P85: 3.3609 | Q85: RENTA FIJA | R85: 53003944 | S85: 15762786 | T85: GBUE | U85: 4052129000 | V85: 932087000 | W85: 3120042000 | X85: 1.589893 | Y85: =+MID(Tabla_Consulta_desde_Reporte_de_Valorización_de_Instrumentos6[[#This Row],[CODIGO_SBS]],7,1) -> 2 | Z85: =Tabla_Consulta_desde_Reporte_de_Valorización_de_Instrumentos6[[#This Row],[CODIGO_SBS]]&"-"&RIGHT(Tabla_Consulta_desde_Reporte_de_Valorización_de_Instrumentos6[[#This Row],[PORTAFOLIO]],1) -> 2220082PAB78-1 | AA85: Deuda corporativa directa - Internacional | AB85: Deuda | AC85: =Tabla_Consulta_desde_Reporte_de_Valorización_de_Instrumentos6[[#This Row],[VALOR_UNITARIO]]*Tabla_Consulta_desde_Reporte_de_Valorización_de_Instrumentos6[[#This Row],[CANTIDAD]] -> 14765000 | AD85: Buenaventura | AE85: =_xlfn.IFNA(_xlfn.XLOOKUP(Tabla_Consulta_desde_Reporte_de_Valorización_de_Instrumentos6[[#This Row],[Emisor2]],'Parametria 2'!G:G,'Parametria 2'!F:F,_xlfn.XLOOKUP(Tabla_Consulta_desde_Reporte_de_Valorización_de_Instrumentos6[[#This Row],[Emisor2]],'Valorización de Instrumentos_of'!H:H,'Valorización de Instrumentos_of'!H:H)),_xlfn.XLOOKUP(Tabla_Consulta_desde_Reporte_de_Valorización_de_Instrumentos6[[#This Row],[TITULO]],'Parametria 2'!K:K,'Parametria 2'!L:L)) -> Buenaventura
A86: 31/12/2025 | B86: 22 | C86: IN-FONDO2 | D86: BEP | E86: 2220082PAB78 | F86: USP6680PAB78 | G86: BUENAV 6.8 02/0 | H86: 2008 | I86: 2 | J86: 1000 | K86: 40443330 | L86: 12033482 | M86: 11255 | N86: 48248 | O86: 2226 | P86: 3.3609 | Q86: RENTA FIJA | R86: 40403616 | S86: 12015588 | T86: GBUE | U86: 4052129000 | V86: 932087000 | W86: 3120042000 | X86: 1.589893 | Y86: =+MID(Tabla_Consulta_desde_Reporte_de_Valorización_de_Instrumentos6[[#This Row],[CODIGO_SBS]],7,1) -> 2 | Z86: =Tabla_Consulta_desde_Reporte_de_Valorización_de_Instrumentos6[[#This Row],[CODIGO_SBS]]&"-"&RIGHT(Tabla_Consulta_desde_Reporte_de_Valorización_de_Instrumentos6[[#This Row],[PORTAFOLIO]],1) -> 2220082PAB78-2 | AA86: Deuda corporativa directa - Internacional | AB86: Deuda | AC86: =Tabla_Consulta_desde_Reporte_de_Valorización_de_Instrumentos6[[#This Row],[VALOR_UNITARIO]]*Tabla_Consulta_desde_Reporte_de_Valorización_de_Instrumentos6[[#This Row],[CANTIDAD]] -> 11255000 | AD86: Buenaventura | AE86: =_xlfn.IFNA(_xlfn.XLOOKUP(Tabla_Consulta_desde_Reporte_de_Valorización_de_Instrumentos6[[#This Row],[Emisor2]],'Parametria 2'!G:G,'Parametria 2'!F:F,_xlfn.XLOOKUP(Tabla_Consulta_desde_Reporte_de_Valorización_de_Instrumentos6[[#This Row],[Emisor2]],'Valorización de Instrumentos_of'!H:H,'Valorización de Instrumentos_of'!H:H)),_xlfn.XLOOKUP(Tabla_Consulta_desde_Reporte_de_Valorización_de_Instrumentos6[[#This Row],[TITULO]],'Parametria 2'!K:K,'Parametria 2'!L:L)) -> Buenaventura
A87: 31/12/2025 | B87: 22 | C87: IN-FONDO1 | D87: BEP | E87: 22230411801A | F87: CVL70500T015 | G87: TDP1PP1A | H87: 2304 | I87: 1 | J87: 5000 | K87: 5582694.3 | L87: 5582694.3 | M87: 2833 | N87: 46311 | O87: 289 | P87: 1 | Q87: RENTA FIJA | R87: 5582694.3 | S87: 5582694.3 | T87: GTEL | U87: 11275211000 | V87: 10043242000 | W87: 1231969000 | X87: 0 | Y87: =+MID(Tabla_Consulta_desde_Reporte_de_Valorización_de_Instrumentos6[[#This Row],[CODIGO_SBS]],7,1) -> 1 | Z87: =Tabla_Consulta_desde_Reporte_de_Valorización_de_Instrumentos6[[#This Row],[CODIGO_SBS]]&"-"&RIGHT(Tabla_Consulta_desde_Reporte_de_Valorización_de_Instrumentos6[[#This Row],[PORTAFOLIO]],1) -> 22230411801A-1 | AA87: Deuda corporativa directa - Local | AB87: Deuda | AC87: =Tabla_Consulta_desde_Reporte_de_Valorización_de_Instrumentos6[[#This Row],[VALOR_UNITARIO]]*Tabla_Consulta_desde_Reporte_de_Valorización_de_Instrumentos6[[#This Row],[CANTIDAD]] -> 14165000 | AD87: Telefónica del Perú | AE87: =_xlfn.IFNA(_xlfn.XLOOKUP(Tabla_Consulta_desde_Reporte_de_Valorización_de_Instrumentos6[[#This Row],[Emisor2]],'Parametria 2'!G:G,'Parametria 2'!F:F,_xlfn.XLOOKUP(Tabla_Consulta_desde_Reporte_de_Valorización_de_Instrumentos6[[#This Row],[Emisor2]],'Valorización de Instrumentos_of'!H:H,'Valorización de Instrumentos_of'!H:H)),_xlfn.XLOOKUP(Tabla_Consulta_desde_Reporte_de_Valorización_de_Instrumentos6[[#This Row],[TITULO]],'Parametria 2'!K:K,'Parametria 2'!L:L)) -> Integratel
A88: 31/12/2025 | B88: 22 | C88: IN-FONDO2 | D88: BEP | E88: 22230430819C | F88: PEP70500M459 | G88: TELE4BC19C | H88: 2304 | I88: 3 | J88: 5000 | K88: 654431.38 | L88: 654431.38 | M88: 200 | N88: 46955 | O88: 933 | P88: 1 | Q88: RENTA FIJA | R88: 654431.38 | S88: 654431.38 | T88: GTEL | U88: 11275211000 | V88: 10043242000 | W88: 1231969000 | X88: 0 | Y88: =+MID(Tabla_Consulta_desde_Reporte_de_Valorización_de_Instrumentos6[[#This Row],[CODIGO_SBS]],7,1) -> 3 | Z88: =Tabla_Consulta_desde_Reporte_de_Valorización_de_Instrumentos6[[#This Row],[CODIGO_SBS]]&"-"&RIGHT(Tabla_Consulta_desde_Reporte_de_Valorización_de_Instrumentos6[[#This Row],[PORTAFOLIO]],1) -> 22230430819C-2 | AA88: Deuda corporativa directa - Local | AB88: Deuda | AC88: =Tabla_Consulta_desde_Reporte_de_Valorización_de_Instrumentos6[[#This Row],[VALOR_UNITARIO]]*Tabla_Consulta_desde_Reporte_de_Valorización_de_Instrumentos6[[#This Row],[CANTIDAD]] -> 1000000 | AD88: Telefónica del Perú | AE88: =_xlfn.IFNA(_xlfn.XLOOKUP(Tabla_Consulta_desde_Reporte_de_Valorización_de_Instrumentos6[[#This Row],[Emisor2]],'Parametria 2'!G:G,'Parametria 2'!F:F,_xlfn.XLOOKUP(Tabla_Consulta_desde_Reporte_de_Valorización_de_Instrumentos6[[#This Row],[Emisor2]],'Valorización de Instrumentos_of'!H:H,'Valorización de Instrumentos_of'!H:H)),_xlfn.XLOOKUP(Tabla_Consulta_desde_Reporte_de_Valorización_de_Instrumentos6[[#This Row],[TITULO]],'Parametria 2'!K:K,'Parametria 2'!L:L)) -> Integratel
A89: 31/12/2025 | B89: 22 | C89: IN-FONDO1 | D89: BEP | E89: 22230430719A | F89: PEP70500M335 | G89: TELE4BC19A | H89: 2304 | I89: 3 | J89: 5000 | K89: 581938.77 | L89: 581938.77 | M89: 168 | N89: 46581 | O89: 559 | P89: 1 | Q89: RENTA FIJA | R89: 581938.77 | S89: 581938.77 | T89: GTEL | U89: 11275211000 | V89: 10043242000 | W89: 1231969000 | X89: 0 | Y89: =+MID(Tabla_Consulta_desde_Reporte_de_Valorización_de_Instrumentos6[[#This Row],[CODIGO_SBS]],7,1) -> 3 | Z89: =Tabla_Consulta_desde_Reporte_de_Valorización_de_Instrumentos6[[#This Row],[CODIGO_SBS]]&"-"&RIGHT(Tabla_Consulta_desde_Reporte_de_Valorización_de_Instrumentos6[[#This Row],[PORTAFOLIO]],1) -> 22230430719A-1 | AA89: Deuda corporativa directa - Local | AB89: Deuda | AC89: =Tabla_Consulta_desde_Reporte_de_Valorización_de_Instrumentos6[[#This Row],[VALOR_UNITARIO]]*Tabla_Consulta_desde_Reporte_de_Valorización_de_Instrumentos6[[#This Row],[CANTIDAD]] -> 840000 | AD89: Telefónica del Perú | AE89: =_xlfn.IFNA(_xlfn.XLOOKUP(Tabla_Consulta_desde_Reporte_de_Valorización_de_Instrumentos6[[#This Row],[Emisor2]],'Parametria 2'!G:G,'Parametria 2'!F:F,_xlfn.XLOOKUP(Tabla_Consulta_desde_Reporte_de_Valorización_de_Instrumentos6[[#This Row],[Emisor2]],'Valorización de Instrumentos_of'!H:H,'Valorización de Instrumentos_of'!H:H)),_xlfn.XLOOKUP(Tabla_Consulta_desde_Reporte_de_Valorización_de_Instrumentos6[[#This Row],[TITULO]],'Parametria 2'!K:K,'Parametria 2'!L:L)) -> Integratel
A90: 31/12/2025 | B90: 22 | C90: IN-FONDO2 | D90: BEP | E90: 22230430719A | F90: PEP70500M335 | G90: TELE4BC19A | H90: 2304 | I90: 3 | J90: 5000 | K90: 2320827.2 | L90: 2320827.2 | M90: 670 | N90: 46581 | O90: 559 | P90: 1 | Q90: RENTA FIJA | R90: 2320827.2 | S90: 2320827.2 | T90: GTEL | U90: 11275211000 | V90: 10043242000 | W90: 1231969000 | X90: 0 | Y90: =+MID(Tabla_Consulta_desde_Reporte_de_Valorización_de_Instrumentos6[[#This Row],[CODIGO_SBS]],7,1) -> 3 | Z90: =Tabla_Consulta_desde_Reporte_de_Valorización_de_Instrumentos6[[#This Row],[CODIGO_SBS]]&"-"&RIGHT(Tabla_Consulta_desde_Reporte_de_Valorización_de_Instrumentos6[[#This Row],[PORTAFOLIO]],1) -> 22230430719A-2 | AA90: Deuda corporativa directa - Local | AB90: Deuda | AC90: =Tabla_Consulta_desde_Reporte_de_Valorización_de_Instrumentos6[[#This Row],[VALOR_UNITARIO]]*Tabla_Consulta_desde_Reporte_de_Valorización_de_Instrumentos6[[#This Row],[CANTIDAD]] -> 3350000 | AD90: Telefónica del Perú | AE90: =_xlfn.IFNA(_xlfn.XLOOKUP(Tabla_Consulta_desde_Reporte_de_Valorización_de_Instrumentos6[[#This Row],[Emisor2]],'Parametria 2'!G:G,'Parametria 2'!F:F,_xlfn.XLOOKUP(Tabla_Consulta_desde_Reporte_de_Valorización_de_Instrumentos6[[#This Row],[Emisor2]],'Valorización de Instrumentos_of'!H:H,'Valorización de Instrumentos_of'!H:H)),_xlfn.XLOOKUP(Tabla_Consulta_desde_Reporte_de_Valorización_de_Instrumentos6[[#This Row],[TITULO]],'Parametria 2'!K:K,'Parametria 2'!L:L)) -> Integratel
A91: 31/12/2025 | B91: 22 | C91: IN-FONDO1 | D91: BEP | E91: 2223041GAR67 | F91: USP9T36GAR67 | G91: TELEFO 7 3/8 4 | H91: 2304 | I91: 1 | J91: 500000 | K91: 37878183 | L91: 37878183 | M91: 192 | N91: 46487 | O91: 465 | P91: 1 | Q91: RENTA FIJA | R91: 37878183 | S91: 37878183 | T91: GTEL | U91: 11275211000 | V91: 10043242000 | W91: 1231969000 | X91: 0 | Y91: =+MID(Tabla_Consulta_desde_Reporte_de_Valorización_de_Instrumentos6[[#This Row],[CODIGO_SBS]],7,1) -> 1 | Z91: =Tabla_Consulta_desde_Reporte_de_Valorización_de_Instrumentos6[[#This Row],[CODIGO_SBS]]&"-"&RIGHT(Tabla_Consulta_desde_Reporte_de_Valorización_de_Instrumentos6[[#This Row],[PORTAFOLIO]],1) -> 2223041GAR67-1 | AA91: Deuda corporativa directa - Internacional | AB91: Deuda | AC91: =Tabla_Consulta_desde_Reporte_de_Valorización_de_Instrumentos6[[#This Row],[VALOR_UNITARIO]]*Tabla_Consulta_desde_Reporte_de_Valorización_de_Instrumentos6[[#This Row],[CANTIDAD]] -> 96000000 | AD91: Telefónica del Perú | AE91: =_xlfn.IFNA(_xlfn.XLOOKUP(Tabla_Consulta_desde_Reporte_de_Valorización_de_Instrumentos6[[#This Row],[Emisor2]],'Parametria 2'!G:G,'Parametria 2'!F:F,_xlfn.XLOOKUP(Tabla_Consulta_desde_Reporte_de_Valorización_de_Instrumentos6[[#This Row],[Emisor2]],'Valorización de Instrumentos_of'!H:H,'Valorización de Instrumentos_of'!H:H)),_xlfn.XLOOKUP(Tabla_Consulta_desde_Reporte_de_Valorización_de_Instrumentos6[[#This Row],[TITULO]],'Parametria 2'!K:K,'Parametria 2'!L:L)) -> Integratel
A92: 31/12/2025 | B92: 22 | C92: IN-FONDO2 | D92: BEP | E92: 2223041GAR67 | F92: USP9T36GAR67 | G92: TELEFO 7 3/8 4 | H92: 2304 | I92: 1 | J92: 500000 | K92: 85028630 | L92: 85028630 | M92: 431 | N92: 46487 | O92: 465 | P92: 1 | Q92: RENTA FIJA | R92: 85028630 | S92: 85028630 | T92: GTEL | U92: 11275211000 | V92: 10043242000 | W92: 1231969000 | X92: 0 | Y92: =+MID(Tabla_Consulta_desde_Reporte_de_Valorización_de_Instrumentos6[[#This Row],[CODIGO_SBS]],7,1) -> 1 | Z92: =Tabla_Consulta_desde_Reporte_de_Valorización_de_Instrumentos6[[#This Row],[CODIGO_SBS]]&"-"&RIGHT(Tabla_Consulta_desde_Reporte_de_Valorización_de_Instrumentos6[[#This Row],[PORTAFOLIO]],1) -> 2223041GAR67-2 | AA92: Deuda corporativa directa - Internacional | AB92: Deuda | AC92: =Tabla_Consulta_desde_Reporte_de_Valorización_de_Instrumentos6[[#This Row],[VALOR_UNITARIO]]*Tabla_Consulta_desde_Reporte_de_Valorización_de_Instrumentos6[[#This Row],[CANTIDAD]] -> 215500000 | AD92: Telefónica del Perú | AE92: =_xlfn.IFNA(_xlfn.XLOOKUP(Tabla_Consulta_desde_Reporte_de_Valorización_de_Instrumentos6[[#This Row],[Emisor2]],'Parametria 2'!G:G,'Parametria 2'!F:F,_xlfn.XLOOKUP(Tabla_Consulta_desde_Reporte_de_Valorización_de_Instrumentos6[[#This Row],[Emisor2]],'Valorización de Instrumentos_of'!H:H,'Valorización de Instrumentos_of'!H:H)),_xlfn.XLOOKUP(Tabla_Consulta_desde_Reporte_de_Valorización_de_Instrumentos6[[#This Row],[TITULO]],'Parametria 2'!K:K,'Parametria 2'!L:L)) -> Integratel
... A98: 31/12/2025 | B98: 22 | C98: IN-FONDO2 | D98: BEP | E98: 2220392TAB19 | F98: USP6811TAB19 | G98: MINSUR 4 1/2 10 | H98: 2039 | I98: 2 | J98: 1000 | K98: 10570089 | L98: 3145017.4 | M98: 3251 | N98: 48149 | O98: 2127 | P98: 3.3609 | Q98: RENTA FIJA | R98: 10528507 | S98: 3131061.3 | T98: GITU | U98: 2610762000 | V98: 781816000 | W98: 1828946000 | X98: 4.292857 | Y98: =+MID(Tabla_Consulta_desde_Reporte_de_Valorización_de_Instrumentos6[[#This Row],[CODIGO_SBS]],7,1) -> 2 | Z98: =Tabla_Consulta_desde_Reporte_de_Valorización_de_Instrumentos6[[#This Row],[CODIGO_SBS]]&"-"&RIGHT(Tabla_Consulta_desde_Reporte_de_Valorización_de_Instrumentos6[[#This Row],[PORTAFOLIO]],1) -> 2220392TAB19-2 | AA98: Deuda corporativa directa - Internacional | AB98: Deuda | AC98: =Tabla_Consulta_desde_Reporte_de_Valorización_de_Instrumentos6[[#This Row],[VALOR_UNITARIO]]*Tabla_Consulta_desde_Reporte_de_Valorización_de_Instrumentos6[[#This Row],[CANTIDAD]] -> 3251000 | AD98: MINSUR | AE98: =_xlfn.IFNA(_xlfn.XLOOKUP(Tabla_Consulta_desde_Reporte_de_Valorización_de_Instrumentos6[[#This Row],[Emisor2]],'Parametria 2'!G:G,'Parametria 2'!F:F,_xlfn.XLOOKUP(Tabla_Consulta_desde_Reporte_de_Valorización_de_Instrumentos6[[#This Row],[Emisor2]],'Valorización de Instrumentos_of'!H:H,'Valorización de Instrumentos_of'!H:H)),_xlfn.XLOOKUP(Tabla_Consulta_desde_Reporte_de_Valorización_de_Instrumentos6[[#This Row],[TITULO]],'Parametria 2'!K:K,'Parametria 2'!L:L)) -> Minsur
A99: 31/12/2025 | B99: 23 | C99: IN-FONDO0 | D99: PCOM | E99: 23583412503C | F99: PEP16997V307 | G99: ECSCP2CP3C | H99: 5834 | I99: 1 | J99: 10000 | K99: 18529935 | L99: 18529935 | M99: 1862 | N99: 46060 | O99: 38 | P99: 1 | Q99: RENTA FIJA | R99: 18529001 | S99: 18529001 | T99: GSAN | U99: 1453460000 | V99: 1237682000 | W99: 215778000 | X99: 0.501548 | Y99: =+MID(Tabla_Consulta_desde_Reporte_de_Valorización_de_Instrumentos6[[#This Row],[CODIGO_SBS]],7,1) -> 1 | Z99: =Tabla_Consulta_desde_Reporte_de_Valorización_de_Instrumentos6[[#This Row],[CODIGO_SBS]]&"-"&RIGHT(Tabla_Consulta_desde_Reporte_de_Valorización_de_Instrumentos6[[#This Row],[PORTAFOLIO]],1) -> 23583412503C-0 | AA99: Deuda corporativa directa - Local | AB99: Deuda | AC99: =Tabla_Consulta_desde_Reporte_de_Valorización_de_Instrumentos6[[#This Row],[VALOR_UNITARIO]]*Tabla_Consulta_desde_Reporte_de_Valorización_de_Instrumentos6[[#This Row],[CANTIDAD]] -> 18620000 | AD99: #N/A | AE99: =_xlfn.IFNA(_xlfn.XLOOKUP(Tabla_Consulta_desde_Reporte_de_Valorización_de_Instrumentos6[[#This Row],[Emisor2]],'Parametria 2'!G:G,'Parametria 2'!F:F,_xlfn.XLOOKUP(Tabla_Consulta_desde_Reporte_de_Valorización_de_Instrumentos6[[#This Row],[Emisor2]],'Valorización de Instrumentos_of'!H:H,'Valorización de Instrumentos_of'!H:H)),_xlfn.XLOOKUP(Tabla_Consulta_desde_Reporte_de_Valorización_de_Instrumentos6[[#This Row],[TITULO]],'Parametria 2'!K:K,'Parametria 2'!L:L)) -> Santander Consumer Bank
A100: 31/12/2025 | B100: 23 | C100: IN-FONDO0 | D100: PCOM | E100: 23583412502A | F100: PEP16997V349 | G100: ECSCP3CP2A | H100: 5834 | I100: 1 | J100: 10000 | K100: 34826192 | L100: 34826192 | M100: 3628 | N100: 46346 | O100: 324 | P100: 1 | Q100: RENTA FIJA | R100: 34831581 | S100: 34831581 | T100: GSAN | U100: 1453460000 | V100: 1237682000 | W100: 215778000 | X100: -1.4854461 | Y100: =+MID(Tabla_Consulta_desde_Reporte_de_Valorización_de_Instrumentos6[[#This Row],[CODIGO_SBS]],7,1) -> 1 | Z100: =Tabla_Consulta_desde_Reporte_de_Valorización_de_Instrumentos6[[#This Row],[CODIGO_SBS]]&"-"&RIGHT(Tabla_Consulta_desde_Reporte_de_Valorización_de_Instrumentos6[[#This Row],[PORTAFOLIO]],1) -> 23583412502A-0 | AA100: Deuda corporativa directa - Local | AB100: Deuda | AC100: =Tabla_Consulta_desde_Reporte_de_Valorización_de_Instrumentos6[[#This Row],[VALOR_UNITARIO]]*Tabla_Consulta_desde_Reporte_de_Valorización_de_Instrumentos6[[#This Row],[CANTIDAD]] -> 36280000 | AD100: #N/A | AE100: =_xlfn.IFNA(_xlfn.XLOOKUP(Tabla_Consulta_desde_Reporte_de_Valorización_de_Instrumentos6[[#This Row],[Emisor2]],'Parametria 2'!G:G,'Parametria 2'!F:F,_xlfn.XLOOKUP(Tabla_Consulta_desde_Reporte_de_Valorización_de_Instrumentos6[[#This Row],[Emisor2]],'Valorización de Instrumentos_of'!H:H,'Valorización de Instrumentos_of'!H:H)),_xlfn.XLOOKUP(Tabla_Consulta_desde_Reporte_de_Valorización_de_Instrumentos6[[#This Row],[TITULO]],'Parametria 2'!K:K,'Parametria 2'!L:L)) -> Santander Consumer Bank
A101: 31/12/2025 | B101: 23 | C101: IN-FONDO0 | D101: PCOM | E101: 23583412501A | F101: PEP16997V323 | G101: ECSCP3CP1A | H101: 5834 | I101: 1 | J101: 10000 | K101: 19591286 | L101: 19591286 | M101: 2000 | N101: 46185 | O101: 163 | P101: 1 | Q101: RENTA FIJA | R101: 19593457 | S101: 19593457 | T101: GSAN | U101: 1453460000 | V101: 1237682000 | W101: 215778000 | X101: -1.0850692 | Y101: =+MID(Tabla_Consulta_desde_Reporte_de_Valorización_de_Instrumentos6[[#This Row],[CODIGO_SBS]],7,1) -> 1 | Z101: =Tabla_Consulta_desde_Reporte_de_Valorización_de_Instrumentos6[[#This Row],[CODIGO_SBS]]&"-"&RIGHT(Tabla_Consulta_desde_Reporte_de_Valorización_de_Instrumentos6[[#This Row],[PORTAFOLIO]],1) -> 23583412501A-0 | AA101: Deuda corporativa directa - Local | AB101: Deuda | AC101: =Tabla_Consulta_desde_Reporte_de_Valorización_de_Instrumentos6[[#This Row],[VALOR_UNITARIO]]*Tabla_Consulta_desde_Reporte_de_Valorización_de_Instrumentos6[[#This Row],[CANTIDAD]] -> 20000000 | AD101: #N/A | AE101: =_xlfn.IFNA(_xlfn.XLOOKUP(Tabla_Consulta_desde_Reporte_de_Valorización_de_Instrumentos6[[#This Row],[Emisor2]],'Parametria 2'!G:G,'Parametria 2'!F:F,_xlfn.XLOOKUP(Tabla_Consulta_desde_Reporte_de_Valorización_de_Instrumentos6[[#This Row],[Emisor2]],'Valorización de Instrumentos_of'!H:H,'Valorización de Instrumentos_of'!H:H)),_xlfn.XLOOKUP(Tabla_Consulta_desde_Reporte_de_Valorización_de_Instrumentos6[[#This Row],[TITULO]],'Parametria 2'!K:K,'Parametria 2'!L:L)) -> Santander Consumer Bank
A102: 31/12/2025 | B102: 23 | C102: IN-FONDO0 | D102: PCOM | E102: 23583412503D | F102: PEP16997V315 | G102: ECSCP2CP3D | H102: 5834 | I102: 1 | J102: 10000 | K102: 14247806 | L102: 14247806 | M102: 1443 | N102: 46122 | O102: 100 | P102: 1 | Q102: RENTA FIJA | R102: 14248451 | S102: 14248451 | T102: GSAN | U102: 1453460000 | V102: 1237682000 | W102: 215778000 | X102: -0.4472974 | Y102: =+MID(Tabla_Consulta_desde_Reporte_de_Valorización_de_Instrumentos6[[#This Row],[CODIGO_SBS]],7,1) -> 1 | Z102: =Tabla_Consulta_desde_Reporte_de_Valorización_de_Instrumentos6[[#This Row],[CODIGO_SBS]]&"-"&RIGHT(Tabla_Consulta_desde_Reporte_de_Valorización_de_Instrumentos6[[#This Row],[PORTAFOLIO]],1) -> 23583412503D-0 | AA102: Deuda corporativa directa - Local | AB102: Deuda | AC102: =Tabla_Consulta_desde_Reporte_de_Valorización_de_Instrumentos6[[#This Row],[VALOR_UNITARIO]]*Tabla_Consulta_desde_Reporte_de_Valorización_de_Instrumentos6[[#This Row],[CANTIDAD]] -> 14430000 | AD102: #N/A | AE102: =_xlfn.IFNA(_xlfn.XLOOKUP(Tabla_Consulta_desde_Reporte_de_Valorización_de_Instrumentos6[[#This Row],[Emisor2]],'Parametria 2'!G:G,'Parametria 2'!F:F,_xlfn.XLOOKUP(Tabla_Consulta_desde_Reporte_de_Valorización_de_Instrumentos6[[#This Row],[Emisor2]],'Valorización de Instrumentos_of'!H:H,'Valorización de Instrumentos_of'!H:H)),_xlfn.XLOOKUP(Tabla_Consulta_desde_Reporte_de_Valorización_de_Instrumentos6[[#This Row],[TITULO]],'Parametria 2'!K:K,'Parametria 2'!L:L)) -> Santander Consumer Bank
A103: 31/12/2025 | B103: 23 | C103: IN-FONDO0 | D103: PCOM | E103: 23583412501B | F103: PEP16997V331 | G103: ECSCP3CP1B | H103: 5834 | I103: 1 | J103: 10000 | K103: 15444387 | L103: 15444387 | M103: 1595 | N103: 46277 | O103: 255 | P103: 1 | Q103: RENTA FIJA | R103: 15446790 | S103: 15446790 | T103: GSAN | U103: 1453460000 | V103: 1237682000 | W103: 215778000 | X103: -1.5069192 | Y103: =+MID(Tabla_Consulta_desde_Reporte_de_Valorización_de_Instrumentos6[[#This Row],[CODIGO_SBS]],7,1) -> 1 | Z103: =Tabla_Consulta_desde_Reporte_de_Valorización_de_Instrumentos6[[#This Row],[CODIGO_SBS]]&"-"&RIGHT(Tabla_Consulta_desde_Reporte_de_Valorización_de_Instrumentos6[[#This Row],[PORTAFOLIO]],1) -> 23583412501B-0 | AA103: Deuda corporativa directa - Local | AB103: Deuda | AC103: =Tabla_Consulta_desde_Reporte_de_Valorización_de_Instrumentos6[[#This Row],[VALOR_UNITARIO]]*Tabla_Consulta_desde_Reporte_de_Valorización_de_Instrumentos6[[#This Row],[CANTIDAD]] -> 15950000 | AD103: #N/A | AE103: =_xlfn.IFNA(_xlfn.XLOOKUP(Tabla_Consulta_desde_Reporte_de_Valorización_de_Instrumentos6[[#This Row],[Emisor2]],'Parametria 2'!G:G,'Parametria 2'!F:F,_xlfn.XLOOKUP(Tabla_Consulta_desde_Reporte_de_Valorización_de_Instrumentos6[[#This Row],[Emisor2]],'Valorización de Instrumentos_of'!H:H,'Valorización de Instrumentos_of'!H:H)),_xlfn.XLOOKUP(Tabla_Consulta_desde_Reporte_de_Valorización_de_Instrumentos6[[#This Row],[TITULO]],'Parametria 2'!K:K,'Parametria 2'!L:L)) -> Santander Consumer Bank
A104: 31/12/2025 | B104: 23 | C104: IN-FONDO0 | D104: PCOM | E104: 23203012501A | F104: PEP70101V069 | G104: PLUZ6PC1A | H104: 2030 | I104: 1 | J104: 1000 | K104: 4882320.4 | L104: 4882320.4 | M104: 5000 | N104: 46214 | O104: 192 | P104: 1 | Q104: RENTA FIJA | R104: 4882973.5 | S104: 4882973.5 | T104: GENE | U104: 6803800000 | V104: 3267830000 | W104: 3535970000 | X104: -0.1306278 | Y104: =+MID(Tabla_Consulta_desde_Reporte_de_Valorización_de_Instrumentos6[[#This Row],[CODIGO_SBS]],7,1) -> 1 | Z104: =Tabla_Consulta_desde_Reporte_de_Valorización_de_Instrumentos6[[#This Row],[CODIGO_SBS]]&"-"&RIGHT(Tabla_Consulta_desde_Reporte_de_Valorización_de_Instrumentos6[[#This Row],[PORTAFOLIO]],1) -> 23203012501A-0 | AA104: Deuda corporativa directa - Local | AB104: Deuda | AC104: =Tabla_Consulta_desde_Reporte_de_Valorización_de_Instrumentos6[[#This Row],[VALOR_UNITARIO]]*Tabla_Consulta_desde_Reporte_de_Valorización_de_Instrumentos6[[#This Row],[CANTIDAD]] -> 5000000 | AD104: #N/A | AE104: =_xlfn.IFNA(_xlfn.XLOOKUP(Tabla_Consulta_desde_Reporte_de_Valorización_de_Instrumentos6[[#This Row],[Emisor2]],'Parametria 2'!G:G,'Parametria 2'!F:F,_xlfn.XLOOKUP(Tabla_Consulta_desde_Reporte_de_Valorización_de_Instrumentos6[[#This Row],[Emisor2]],'Valorización de Instrumentos_of'!H:H,'Valorización de Instrumentos_of'!H:H)),_xlfn.XLOOKUP(Tabla_Consulta_desde_Reporte_de_Valorización_de_Instrumentos6[[#This Row],[TITULO]],'Parametria 2'!K:K,'Parametria 2'!L:L)) -> Pluz Energía
A105: 31/12/2025 | B105: 23 | C105: IN-FONDO0 | D105: PCOM | E105: 23200912503C | F105: PEP70252V110 | G105: LUSUR4CP3C | H105: 2009 | I105: 1 | J105: 1000 | K105: 4700592.2 | L105: 4700592.2 | M105: 4761 | N105: 46123 | O105: 101 | P105: 1 | Q105: RENTA FIJA | R105: 4700814.3 | S105: 4700814.3 | T105: GSEM | U105: 9755108000 | V105: 5037943000 | W105: 4717165000 | X105: -0.0466513 | Y105: =+MID(Tabla_Consulta_desde_Reporte_de_Valorización_de_Instrumentos6[[#This Row],[CODIGO_SBS]],7,1) -> 1 | Z105: =Tabla_Consulta_desde_Reporte_de_Valorización_de_Instrumentos6[[#This Row],[CODIGO_SBS]]&"-"&RIGHT(Tabla_Consulta_desde_Reporte_de_Valorización_de_Instrumentos6[[#This Row],[PORTAFOLIO]],1) -> 23200912503C-0 | AA105: Deuda corporativa directa - Local | AB105: Deuda | AC105: =Tabla_Consulta_desde_Reporte_de_Valorización_de_Instrumentos6[[#This Row],[VALOR_UNITARIO]]*Tabla_Consulta_desde_Reporte_de_Valorización_de_Instrumentos6[[#This Row],[CANTIDAD]] -> 4761000 | AD105: #N/A | AE105: =_xlfn.IFNA(_xlfn.XLOOKUP(Tabla_Consulta_desde_Reporte_de_Valorización_de_Instrumentos6[[#This Row],[Emisor2]],'Parametria 2'!G:G,'Parametria 2'!F:F,_xlfn.XLOOKUP(Tabla_Consulta_desde_Reporte_de_Valorización_de_Instrumentos6[[#This Row],[Emisor2]],'Valorización de Instrumentos_of'!H:H,'Valorización de Instrumentos_of'!H:H)),_xlfn.XLOOKUP(Tabla_Consulta_desde_Reporte_de_Valorización_de_Instrumentos6[[#This Row],[TITULO]],'Parametria 2'!K:K,'Parametria 2'!L:L)) -> Luz del Sur
A106: 31/12/2025 | B106: 25 | C106: IN-FONDO2 | D106: OSF | E106: 25210511604A | F106: PEP16880M023 | G106: FMV1BC4A | H106: 2105 | I106: 1 | J106: 5000 | K106: 19086496 | L106: 19086496 | M106: 3664 | N106: 46216 | O106: 194 | P106: 1 | Q106: RENTA FIJA | R106: 19089961 | S106: 19089961 | T106: GFON | U106: 13448377000 | V106: 9913193000 | W106: 3535184000 | X106: -0.9458789 | Y106: =+MID(Tabla_Consulta_desde_Reporte_de_Valorización_de_Instrumentos6[[#This Row],[CODIGO_SBS]],7,1) -> 1 | Z106: =Tabla_Consulta_desde_Reporte_de_Valorización_de_Instrumentos6[[#This Row],[CODIGO_SBS]]&"-"&RIGHT(Tabla_Consulta_desde_Reporte_de_Valorización_de_Instrumentos6[[#This Row],[PORTAFOLIO]],1) -> 25210511604A-2 | AA106: Deuda corporativa directa - Local | AB106: Deuda | AC106: =Tabla_Consulta_desde_Reporte_de_Valorización_de_Instrumentos6[[#This Row],[VALOR_UNITARIO]]*Tabla_Consulta_desde_Reporte_de_Valorización_de_Instrumentos6[[#This Row],[CANTIDAD]] -> 18320000 | AD106: Fondo Mi Vivienda | AE106: =_xlfn.IFNA(_xlfn.XLOOKUP(Tabla_Consulta_desde_Reporte_de_Valorización_de_Instrumentos6[[#This Row],[Emisor2]],'Parametria 2'!G:G,'Parametria 2'!F:F,_xlfn.XLOOKUP(Tabla_Consulta_desde_Reporte_de_Valorización_de_Instrumentos6[[#This Row],[Emisor2]],'Valorización de Instrumentos_of'!H:H,'Valorización de Instrumentos_of'!H:H)),_xlfn.XLOOKUP(Tabla_Consulta_desde_Reporte_de_Valorización_de_Instrumentos6[[#This Row],[TITULO]],'Parametria 2'!K:K,'Parametria 2'!L:L)) -> Fondo Mi Vivienda
A107: 31/12/2025 | B107: 25 | C107: IN-FONDO2 | D107: OSF | E107: 25210511905A | F107: PEP16880M049 | G107: FMV1BC5A | H107: 2105 | I107: 1 | J107: 5000 | K107: 4974764.5 | L107: 4974764.5 | M107: 971 | N107: 46220 | O107: 198 | P107: 1 | Q107: RENTA FIJA | R107: 4975702.1 | S107: 4975702.1 | T107: GFON | U107: 13448377000 | V107: 9913193000 | W107: 3535184000 | X107: -0.9655932 | Y107: =+MID(Tabla_Consulta_desde_Reporte_de_Valorización_de_Instrumentos6[[#This Row],[CODIGO_SBS]],7,1) -> 1 | Z107: =Tabla_Consulta_desde_Reporte_de_Valorización_de_Instrumentos6[[#This Row],[CODIGO_SBS]]&"-"&RIGHT(Tabla_Consulta_desde_Reporte_de_Valorización_de_Instrumentos6[[#This Row],[PORTAFOLIO]],1) -> 25210511905A-2 | AA107: Deuda corporativa directa - Local | AB107: Deuda | AC107: =Tabla_Consulta_desde_Reporte_de_Valorización_de_Instrumentos6[[#This Row],[VALOR_UNITARIO]]*Tabla_Consulta_desde_Reporte_de_Valorización_de_Instrumentos6[[#This Row],[CANTIDAD]] -> 4855000 | AD107: Fondo Mi Vivienda | AE107: =_xlfn.IFNA(_xlfn.XLOOKUP(Tabla_Consulta_desde_Reporte_de_Valorización_de_Instrumentos6[[#This Row],[Emisor2]],'Parametria 2'!G:G,'Parametria 2'!F:F,_xlfn.XLOOKUP(Tabla_Consulta_desde_Reporte_de_Valorización_de_Instrumentos6[[#This Row],[Emisor2]],'Valorización de Instrumentos_of'!H:H,'Valorización de Instrumentos_of'!H:H)),_xlfn.XLOOKUP(Tabla_Consulta_desde_Reporte_de_Valorización_de_Instrumentos6[[#This Row],[TITULO]],'Parametria 2'!K:K,'Parametria 2'!L:L)) -> Fondo Mi Vivienda
A108: 31/12/2025 | B108: 30 | C108: IN-FONDO3 | D108: ACC | E108: 3021012171A1 | F108: PAL1801171A1 | G108: INRETC1 | H108: 2101 | I108: 2 | J108: 10 | K108: 68448071 | L108: 20365995 | M108: 814042 | P108: 3.3609 | Q108: RENTA VARIABLE | R108: 67869004 | S108: 20183490 | T108: GITC | U108: 8247269000 | V108: 3281203000 | W108: 4966066000 | X108: 0.2241953 | Y108: =+MID(Tabla_Consulta_desde_Reporte_de_Valorización_de_Instrumentos6[[#This Row],[CODIGO_SBS]],7,1) -> 2 | Z108: =Tabla_Consulta_desde_Reporte_de_Valorización_de_Instrumentos6[[#This Row],[CODIGO_SBS]]&"-"&RIGHT(Tabla_Consulta_desde_Reporte_de_Valorización_de_Instrumentos6[[#This Row],[PORTAFOLIO]],1) -> 3021012171A1-3 | AA108: Equity directo - Local | AB108: Capital | AC108: =Tabla_Consulta_desde_Reporte_de_Valorización_de_Instrumentos6[[#This Row],[VALOR_UNITARIO]]*Tabla_Consulta_desde_Reporte_de_Valorización_de_Instrumentos6[[#This Row],[CANTIDAD]] -> 8140420 | AD108: Inretail Peru Corp | AE108: =_xlfn.IFNA(_xlfn.XLOOKUP(Tabla_Consulta_desde_Reporte_de_Valorización_de_Instrumentos6[[#This Row],[Emisor2]],'Parametria 2'!G:G,'Parametria 2'!F:F,_xlfn.XLOOKUP(Tabla_Consulta_desde_Reporte_de_Valorización_de_Instrumentos6[[#This Row],[Emisor2]],'Valorización de Instrumentos_of'!H:H,'Valorización de Instrumentos_of'!H:H)),_xlfn.XLOOKUP(Tabla_Consulta_desde_Reporte_de_Valorización_de_Instrumentos6[[#This Row],[TITULO]],'Parametria 2'!K:K,'Parametria 2'!L:L)) -> Inretail Peru Corp
A109: 31/12/2025 | B109: 30 | C109: IN-FONDO1 | D109: ACC | E109: 3021012171A1 | F109: PAL1801171A1 | G109: INRETC1 | H109: 2101 | I109: 2 | J109: 10 | K109: 15939422 | L109: 4742605.1 | M109: 189565 | P109: 3.3609 | Q109: RENTA VARIABLE | R109: 15804575 | S109: 4700105.5 | T109: GITC | U109: 8247269000 | V109: 3281203000 | W109: 4966066000 | X109: 0.2241953 | Y109: =+MID(Tabla_Consulta_desde_Reporte_de_Valorización_de_Instrumentos6[[#This Row],[CODIGO_SBS]],7,1) -> 2 | Z109: =Tabla_Consulta_desde_Reporte_de_Valorización_de_Instrumentos6[[#This Row],[CODIGO_SBS]]&"-"&RIGHT(Tabla_Consulta_desde_Reporte_de_Valorización_de_Instrumentos6[[#This Row],[PORTAFOLIO]],1) -> 3021012171A1-1 | AA109: Equity directo - Local | AB109: Capital | AC109: =Tabla_Consulta_desde_Reporte_de_Valorización_de_Instrumentos6[[#This Row],[VALOR_UNITARIO]]*Tabla_Consulta_desde_Reporte_de_Valorización_de_Instrumentos6[[#This Row],[CANTIDAD]] -> 1895650 | AD109: Inretail Peru Corp | AE109: =_xlfn.IFNA(_xlfn.XLOOKUP(Tabla_Consulta_desde_Reporte_de_Valorización_de_Instrumentos6[[#This Row],[Emisor2]],'Parametria 2'!G:G,'Parametria 2'!F:F,_xlfn.XLOOKUP(Tabla_Consulta_desde_Reporte_de_Valorización_de_Instrumentos6[[#This Row],[Emisor2]],'Valorización de Instrumentos_of'!H:H,'Valorización de Instrumentos_of'!H:H)),_xlfn.XLOOKUP(Tabla_Consulta_desde_Reporte_de_Valorización_de_Instrumentos6[[#This Row],[TITULO]],'Parametria 2'!K:K,'Parametria 2'!L:L)) -> Inretail Peru Corp
A110: 31/12/2025 | B110: 30 | C110: IN-FONDO2 | D110: ACC | E110: 3021012171A1 | F110: PAL1801171A1 | G110: INRETC1 | H110: 2101 | I110: 2 | J110: 10 | K110: 3.8849045e+08 | L110: 1.155912e+08 | M110: 4620255 | P110: 3.3609 | Q110: RENTA VARIABLE | R110: 3.8520384e+08 | S110: 1.1455536e+08 | T110: GITC | U110: 8247269000 | V110: 3281203000 | W110: 4966066000 | X110: 0.2241953 | Y110: =+MID(Tabla_Consulta_desde_Reporte_de_Valorización_de_Instrumentos6[[#This Row],[CODIGO_SBS]],7,1) -> 2 | Z110: =Tabla_Consulta_desde_Reporte_de_Valorización_de_Instrumentos6[[#This Row],[CODIGO_SBS]]&"-"&RIGHT(Tabla_Consulta_desde_Reporte_de_Valorización_de_Instrumentos6[[#This Row],[PORTAFOLIO]],1) -> 3021012171A1-2 | AA110: Equity directo - Local | AB110: Capital | AC110: =Tabla_Consulta_desde_Reporte_de_Valorización_de_Instrumentos6[[#This Row],[VALOR_UNITARIO]]*Tabla_Consulta_desde_Reporte_de_Valorización_de_Instrumentos6[[#This Row],[CANTIDAD]] -> 46202550 | AD110: Inretail Peru Corp | AE110: =_xlfn.IFNA(_xlfn.XLOOKUP(Tabla_Consulta_desde_Reporte_de_Valorización_de_Instrumentos6[[#This Row],[Emisor2]],'Parametria 2'!G:G,'Parametria 2'!F:F,_xlfn.XLOOKUP(Tabla_Consulta_desde_Reporte_de_Valorización_de_Instrumentos6[[#This Row],[Emisor2]],'Valorización de Instrumentos_of'!H:H,'Valorización de Instrumentos_of'!H:H)),_xlfn.XLOOKUP(Tabla_Consulta_desde_Reporte_de_Valorización_de_Instrumentos6[[#This Row],[TITULO]],'Parametria 2'!K:K,'Parametria 2'!L:L)) -> Inretail Peru Corp
A111: 31/12/2025 | B111: 27 | C111: IN-FONDO2 | D111: TCDC | E111: 2721171IRSM1 | F111: CVL800707107 | G111: TITIRSM1 | H111: 2117 | I111: 1 | J111: 10000 | K111: 27463685 | L111: 27463685 | M111: 2500 | N111: 49150 | O111: 3128 | P111: 1 | Q111: RENTA FIJA | R111: 27415349 | S111: 27415349 | T111: GITC | U111: 5958165000 | V111: 3039391000 | W111: 2918774000 | X111: 19.334703 | Y111: =+MID(Tabla_Consulta_desde_Reporte_de_Valorización_de_Instrumentos6[[#This Row],[CODIGO_SBS]],7,1) -> 1 | Z111: =Tabla_Consulta_desde_Reporte_de_Valorización_de_Instrumentos6[[#This Row],[CODIGO_SBS]]&"-"&RIGHT(Tabla_Consulta_desde_Reporte_de_Valorización_de_Instrumentos6[[#This Row],[PORTAFOLIO]],1) -> 2721171IRSM1-2 | AA111: Titularización - Renta fija - Internacional | AB111: Deuda | AC111: =Tabla_Consulta_desde_Reporte_de_Valorización_de_Instrumentos6[[#This Row],[VALOR_UNITARIO]]*Tabla_Consulta_desde_Reporte_de_Valorización_de_Instrumentos6[[#This Row],[CANTIDAD]] -> 25000000 | AD111: InRetail Shopping Malls | AE111: =_xlfn.IFNA(_xlfn.XLOOKUP(Tabla_Consulta_desde_Reporte_de_Valorización_de_Instrumentos6[[#This Row],[Emisor2]],'Parametria 2'!G:G,'Parametria 2'!F:F,_xlfn.XLOOKUP(Tabla_Consulta_desde_Reporte_de_Valorización_de_Instrumentos6[[#This Row],[Emisor2]],'Valorización de Instrumentos_of'!H:H,'Valorización de Instrumentos_of'!H:H)),_xlfn.XLOOKUP(Tabla_Consulta_desde_Reporte_de_Valorización_de_Instrumentos6[[#This Row],[TITULO]],'Parametria 2'!K:K,'Parametria 2'!L:L)) -> InRetail Shopping Malls
A112: 31/12/2025 | B112: 25 | C112: IN-FONDO1 | D112: OSF | E112: 2500021V2F13 | F112: US05971V2F13 | G112: BCP2029 | H112: 0002 | I112: 1 | J112: 1000 | K112: 2019528.5 | L112: 2019528.5 | M112: 1839 | N112: 47129 | O112: 1107 | P112: 1 | Q112: RENTA FIJA | R112: 2017652.2 | S112: 2017652.2 | T112: CCOR | U112: 187469765000 | V112: 164938084000 | W112: 22531681000 | X112: 1.020278 | Y112: =+MID(Tabla_Consulta_desde_Reporte_de_Valorización_de_Instrumentos6[[#This Row],[CODIGO_SBS]],7,1) -> 1 | Z112: =Tabla_Consulta_desde_Reporte_de_Valorización_de_Instrumentos6[[#This Row],[CODIGO_SBS]]&"-"&RIGHT(Tabla_Consulta_desde_Reporte_de_Valorización_de_Instrumentos6[[#This Row],[PORTAFOLIO]],1) -> 2500021V2F13-1 | AA112: Deuda corporativa directa - Internacional | AB112: Deuda | AC112: =Tabla_Consulta_desde_Reporte_de_Valorización_de_Instrumentos6[[#This Row],[VALOR_UNITARIO]]*Tabla_Consulta_desde_Reporte_de_Valorización_de_Instrumentos6[[#This Row],[CANTIDAD]] -> 1839000 | AD112: Banco de Crédito del Perú | AE112: =_xlfn.IFNA(_xlfn.XLOOKUP(Tabla_Consulta_desde_Reporte_de_Valorización_de_Instrumentos6[[#This Row],[Emisor2]],'Parametria 2'!G:G,'Parametria 2'!F:F,_xlfn.XLOOKUP(Tabla_Consulta_desde_Reporte_de_Valorización_de_Instrumentos6[[#This Row],[Emisor2]],'Valorización de Instrumentos_of'!H:H,'Valorización de Instrumentos_of'!H:H)),_xlfn.XLOOKUP(Tabla_Consulta_desde_Reporte_de_Valorización_de_Instrumentos6[[#This Row],[TITULO]],'Parametria 2'!K:K,'Parametria 2'!L:L)) -> Banco de Crédito del Perú
A113: 31/12/2025 | B113: 25 | C113: IN-FONDO2 | D113: OSF | E113: 2500021V2F13 | F113: US05971V2F13 | G113: BCP2029 | H113: 0002 | I113: 1 | J113: 1000 | K113: 1.6449548e+08 | L113: 1.6449548e+08 | M113: 149791 | N113: 47129 | O113: 1107 | P113: 1 | Q113: RENTA FIJA | R113: 1.6434265e+08 | S113: 1.6434265e+08 | T113: CCOR | U113: 187469765000 | V113: 164938084000 | W113: 22531681000 | X113: 1.020278 | Y113: =+MID(Tabla_Consulta_desde_Reporte_de_Valorización_de_Instrumentos6[[#This Row],[CODIGO_SBS]],7,1) -> 1 | Z113: =Tabla_Consulta_desde_Reporte_de_Valorización_de_Instrumentos6[[#This Row],[CODIGO_SBS]]&"-"&RIGHT(Tabla_Consulta_desde_Reporte_de_Valorización_de_Instrumentos6[[#This Row],[PORTAFOLIO]],1) -> 2500021V2F13-2 | AA113: Deuda corporativa directa - Internacional | AB113: Deuda | AC113: =Tabla_Consulta_desde_Reporte_de_Valorización_de_Instrumentos6[[#This Row],[VALOR_UNITARIO]]*Tabla_Consulta_desde_Reporte_de_Valorización_de_Instrumentos6[[#This Row],[CANTIDAD]] -> 149791000 | AD113: Banco de Crédito del Perú | AE113: =_xlfn.IFNA(_xlfn.XLOOKUP(Tabla_Consulta_desde_Reporte_de_Valorización_de_Instrumentos6[[#This Row],[Emisor2]],'Parametria 2'!G:G,'Parametria 2'!F:F,_xlfn.XLOOKUP(Tabla_Consulta_desde_Reporte_de_Valorización_de_Instrumentos6[[#This Row],[Emisor2]],'Valorización de Instrumentos_of'!H:H,'Valorización de Instrumentos_of'!H:H)),_xlfn.XLOOKUP(Tabla_Consulta_desde_Reporte_de_Valorización_de_Instrumentos6[[#This Row],[TITULO]],'Parametria 2'!K:K,'Parametria 2'!L:L)) -> Banco de Crédito del Perú
A114: 31/12/2025 | B114: 27 | C114: IN-FONDO1 | D114: TCDC | E114: 2721171IRSM3 | F114: CVL800700S24 | G114: INROCT32 | H114: 2117 | I114: 1 | J114: 10000 | K114: 62097323 | L114: 62097323 | M114: 6000 | N114: 48507 | O114: 2485 | P114: 1 | Q114: RENTA FIJA | R114: 61970910 | S114: 61970910 | T114: GITC | U114: 5958165000 | V114: 3039391000 | W114: 2918774000 | X114: 21.068811 | Y114: =+MID(Tabla_Consulta_desde_Reporte_de_Valorización_de_Instrumentos6[[#This Row],[CODIGO_SBS]],7,1) -> 1 | Z114: =Tabla_Consulta_desde_Reporte_de_Valorización_de_Instrumentos6[[#This Row],[CODIGO_SBS]]&"-"&RIGHT(Tabla_Consulta_desde_Reporte_de_Valorización_de_Instrumentos6[[#This Row],[PORTAFOLIO]],1) -> 2721171IRSM3-1 | AA114: Titularización - Renta fija - Internacional | AB114: Deuda | AC114: =Tabla_Consulta_desde_Reporte_de_Valorización_de_Instrumentos6[[#This Row],[VALOR_UNITARIO]]*Tabla_Consulta_desde_Reporte_de_Valorización_de_Instrumentos6[[#This Row],[CANTIDAD]] -> 60000000 | AD114: TITIRSM1 - InRetail | AE114: =_xlfn.IFNA(_xlfn.XLOOKUP(Tabla_Consulta_desde_Reporte_de_Valorización_de_Instrumentos6[[#This Row],[Emisor2]],'Parametria 2'!G:G,'Parametria 2'!F:F,_xlfn.XLOOKUP(Tabla_Consulta_desde_Reporte_de_Valorización_de_Instrumentos6[[#This Row],[Emisor2]],'Valorización de Instrumentos_of'!H:H,'Valorización de Instrumentos_of'!H:H)),_xlfn.XLOOKUP(Tabla_Consulta_desde_Reporte_de_Valorización_de_Instrumentos6[[#This Row],[TITULO]],'Parametria 2'!K:K,'Parametria 2'!L:L)) -> InRetail Shopping Malls
A115: 31/12/2025 | B115: 27 | C115: IN-FONDO1 | D115: TCDC | E115: 27211723AE14 | F115: USP56243AE14 | G115: INR2032 | H115: 2117 | I115: 2 | J115: 1000 | K115: 20899788 | L115: 6218509.4 | M115: 6100 | N115: 48503 | O115: 2481 | P115: 3.3609 | Q115: RENTA FIJA | R115: 20895306 | S115: 6214032.7 | T115: GITC | U115: 5958165000 | V115: 3039391000 | W115: 2918774000 | X115: 0.733889 | Y115: =+MID(Tabla_Consulta_desde_Reporte_de_Valorización_de_Instrumentos6[[#This Row],[CODIGO_SBS]],7,1) -> 2 | Z115: =Tabla_Consulta_desde_Reporte_de_Valorización_de_Instrumentos6[[#This Row],[CODIGO_SBS]]&"-"&RIGHT(Tabla_Consulta_desde_Reporte_de_Valorización_de_Instrumentos6[[#This Row],[PORTAFOLIO]],1) -> 27211723AE14-1 | AA115: Titularización - Renta fija - Internacional | AB115: Deuda | AC115: =Tabla_Consulta_desde_Reporte_de_Valorización_de_Instrumentos6[[#This Row],[VALOR_UNITARIO]]*Tabla_Consulta_desde_Reporte_de_Valorización_de_Instrumentos6[[#This Row],[CANTIDAD]] -> 6100000 | AD115: InRetail Shopping Malls | AE115: =_xlfn.IFNA(_xlfn.XLOOKUP(Tabla_Consulta_desde_Reporte_de_Valorización_de_Instrumentos6[[#This Row],[Emisor2]],'Parametria 2'!G:G,'Parametria 2'!F:F,_xlfn.XLOOKUP(Tabla_Consulta_desde_Reporte_de_Valorización_de_Instrumentos6[[#This Row],[Emisor2]],'Valorización de Instrumentos_of'!H:H,'Valorización de Instrumentos_of'!H:H)),_xlfn.XLOOKUP(Tabla_Consulta_desde_Reporte_de_Valorización_de_Instrumentos6[[#This Row],[TITULO]],'Parametria 2'!K:K,'Parametria 2'!L:L)) -> InRetail Shopping Malls
A116: 31/12/2025 | B116: 21 | C116: IN-FONDO1 | D116: BSF | E116: 21000325AG03 | F116: USP13435AG03 | G116: BINTPE 6.397 04 | H116: 0003 | I116: 2 | J116: 1000 | K116: 32575042 | L116: 9692356.9 | M116: 9200 | N116: 49429 | O116: 3407 | P116: 3.3609 | Q116: RENTA FIJA | R116: 32503185 | S116: 9666087.3 | T116: GITC | U116: 71698610000 | V116: 64045988000 | W116: 7652622000 | X116: 2.855389 | Y116: =+MID(Tabla_Consulta_desde_Reporte_de_Valorización_de_Instrumentos6[[#This Row],[CODIGO_SBS]],7,1) -> 2 | Z116: =Tabla_Consulta_desde_Reporte_de_Valorización_de_Instrumentos6[[#This Row],[CODIGO_SBS]]&"-"&RIGHT(Tabla_Consulta_desde_Reporte_de_Valorización_de_Instrumentos6[[#This Row],[PORTAFOLIO]],1) -> 21000325AG03-1 | AA116: Deuda corporativa directa - Internacional | AB116: Deuda | AC116: =Tabla_Consulta_desde_Reporte_de_Valorización_de_Instrumentos6[[#This Row],[VALOR_UNITARIO]]*Tabla_Consulta_desde_Reporte_de_Valorización_de_Instrumentos6[[#This Row],[CANTIDAD]] -> 9200000 | AD116: Banco Internacional del Perú | AE116: =_xlfn.IFNA(_xlfn.XLOOKUP(Tabla_Consulta_desde_Reporte_de_Valorización_de_Instrumentos6[[#This Row],[Emisor2]],'Parametria 2'!G:G,'Parametria 2'!F:F,_xlfn.XLOOKUP(Tabla_Consulta_desde_Reporte_de_Valorización_de_Instrumentos6[[#This Row],[Emisor2]],'Valorización de Instrumentos_of'!H:H,'Valorización de Instrumentos_of'!H:H)),_xlfn.XLOOKUP(Tabla_Consulta_desde_Reporte_de_Valorización_de_Instrumentos6[[#This Row],[TITULO]],'Parametria 2'!K:K,'Parametria 2'!L:L)) -> Interbank
A117: 31/12/2025 | B117: 21 | C117: IN-FONDO2 | D117: BSF | E117: 21000325AG03 | F117: USP13435AG03 | G117: BINTPE 6.397 04 | H117: 0003 | I117: 2 | J117: 1000 | K117: 78590830 | L117: 23383865 | M117: 22196 | N117: 49429 | O117: 3407 | P117: 3.3609 | Q117: RENTA FIJA | R117: 78417467 | S117: 23320486 | T117: GITC | U117: 71698610000 | V117: 64045988000 | W117: 7652622000 | X117: 2.855389 | Y117: =+MID(Tabla_Consulta_desde_Reporte_de_Valorización_de_Instrumentos6[[#This Row],[CODIGO_SBS]],7,1) -> 2 | Z117: =Tabla_Consulta_desde_Reporte_de_Valorización_de_Instrumentos6[[#This Row],[CODIGO_SBS]]&"-"&RIGHT(Tabla_Consulta_desde_Reporte_de_Valorización_de_Instrumentos6[[#This Row],[PORTAFOLIO]],1) -> 21000325AG03-2 | AA117: Deuda corporativa directa - Internacional | AB117: Deuda | AC117: =Tabla_Consulta_desde_Reporte_de_Valorización_de_Instrumentos6[[#This Row],[VALOR_UNITARIO]]*Tabla_Consulta_desde_Reporte_de_Valorización_de_Instrumentos6[[#This Row],[CANTIDAD]] -> 22196000 | AD117: Banco Internacional del Perú | AE117: =_xlfn.IFNA(_xlfn.XLOOKUP(Tabla_Consulta_desde_Reporte_de_Valorización_de_Instrumentos6[[#This Row],[Emisor2]],'Parametria 2'!G:G,'Parametria 2'!F:F,_xlfn.XLOOKUP(Tabla_Consulta_desde_Reporte_de_Valorización_de_Instrumentos6[[#This Row],[Emisor2]],'Valorización de Instrumentos_of'!H:H,'Valorización de Instrumentos_of'!H:H)),_xlfn.XLOOKUP(Tabla_Consulta_desde_Reporte_de_Valorización_de_Instrumentos6[[#This Row],[TITULO]],'Parametria 2'!K:K,'Parametria 2'!L:L)) -> Interbank
A118: 31/12/2025 | B118: 25 | C118: IN-FONDO1 | D118: OSF | E118: 25000310A109 | F118: CVL14800A109 | G118: IBKSNO2026 | H118: 0003 | I118: 1 | J118: 10000 | K118: 76040317 | L118: 76040317 | M118: 7500 | N118: 46296 | O118: 274 | P118: 1 | Q118: RENTA FIJA | R118: 76060055 | S118: 76060055 | T118: GITC | U118: 71698610000 | V118: 64045988000 | W118: 7652622000 | X118: -2.6316852 | Y118: =+MID(Tabla_Consulta_desde_Reporte_de_Valorización_de_Instrumentos6[[#This Row],[CODIGO_SBS]],7,1) -> 1 | Z118: =Tabla_Consulta_desde_Reporte_de_Valorización_de_Instrumentos6[[#This Row],[CODIGO_SBS]]&"-"&RIGHT(Tabla_Consulta_desde_Reporte_de_Valorización_de_Instrumentos6[[#This Row],[PORTAFOLIO]],1) -> 25000310A109-1 | AA118: Deuda corporativa directa - Internacional | AB118: Deuda | AC118: =Tabla_Consulta_desde_Reporte_de_Valorización_de_Instrumentos6[[#This Row],[VALOR_UNITARIO]]*Tabla_Consulta_desde_Reporte_de_Valorización_de_Instrumentos6[[#This Row],[CANTIDAD]] -> 75000000 | AD118: Banco Internacional del Perú | AE118: =_xlfn.IFNA(_xlfn.XLOOKUP(Tabla_Consulta_desde_Reporte_de_Valorización_de_Instrumentos6[[#This Row],[Emisor2]],'Parametria 2'!G:G,'Parametria 2'!F:F,_xlfn.XLOOKUP(Tabla_Consulta_desde_Reporte_de_Valorización_de_Instrumentos6[[#This Row],[Emisor2]],'Valorización de Instrumentos_of'!H:H,'Valorización de Instrumentos_of'!H:H)),_xlfn.XLOOKUP(Tabla_Consulta_desde_Reporte_de_Valorización_de_Instrumentos6[[#This Row],[TITULO]],'Parametria 2'!K:K,'Parametria 2'!L:L)) -> Interbank
A119: 31/12/2025 | B119: 25 | C119: IN-FONDO2 | D119: OSF | E119: 25000310A109 | F119: CVL14800A109 | G119: IBKSNO2026 | H119: 0003 | I119: 1 | J119: 10000 | K119: 55762899 | L119: 55762899 | M119: 5500 | N119: 46296 | O119: 274 | P119: 1 | Q119: RENTA FIJA | R119: 55777374 | S119: 55777374 | T119: GITC | U119: 71698610000 | V119: 64045988000 | W119: 7652622000 | X119: -2.6316852 | Y119: =+MID(Tabla_Consulta_desde_Reporte_de_Valorización_de_Instrumentos6[[#This Row],[CODIGO_SBS]],7,1) -> 1 | Z119: =Tabla_Consulta_desde_Reporte_de_Valorización_de_Instrumentos6[[#This Row],[CODIGO_SBS]]&"-"&RIGHT(Tabla_Consulta_desde_Reporte_de_Valorización_de_Instrumentos6[[#This Row],[PORTAFOLIO]],1) -> 25000310A109-2 | AA119: Deuda corporativa directa - Internacional | AB119: Deuda | AC119: =Tabla_Consulta_desde_Reporte_de_Valorización_de_Instrumentos6[[#This Row],[VALOR_UNITARIO]]*Tabla_Consulta_desde_Reporte_de_Valorización_de_Instrumentos6[[#This Row],[CANTIDAD]] -> 55000000 | AD119: Banco Internacional del Perú | AE119: =_xlfn.IFNA(_xlfn.XLOOKUP(Tabla_Consulta_desde_Reporte_de_Valorización_de_Instrumentos6[[#This Row],[Emisor2]],'Parametria 2'!G:G,'Parametria 2'!F:F,_xlfn.XLOOKUP(Tabla_Consulta_desde_Reporte_de_Valorización_de_Instrumentos6[[#This Row],[Emisor2]],'Valorización de Instrumentos_of'!H:H,'Valorización de Instrumentos_of'!H:H)),_xlfn.XLOOKUP(Tabla_Consulta_desde_Reporte_de_Valorización_de_Instrumentos6[[#This Row],[TITULO]],'Parametria 2'!K:K,'Parametria 2'!L:L)) -> Interbank
A120: 31/12/2025 | B120: 63 | C120: IN-FONDO0 | D120: CDLP | E120: 63000312501E | F120: PEP14800Q065 | G120: INTER2CD1E | H120: 0003 | I120: 1 | J120: 1000 | K120: 14540644 | L120: 14540644 | M120: 15000 | N120: 46276 | O120: 254 | P120: 1 | Q120: RENTA FIJA | R120: 14542966 | S120: 14542966 | T120: GITC | U120: 71698610000 | V120: 64045988000 | W120: 7652622000 | X120: -0.1548145 | Y120: =+MID(Tabla_Consulta_desde_Reporte_de_Valorización_de_Instrumentos6[[#This Row],[CODIGO_SBS]],7,1) -> 1 | Z120: =Tabla_Consulta_desde_Reporte_de_Valorización_de_Instrumentos6[[#This Row],[CODIGO_SBS]]&"-"&RIGHT(Tabla_Consulta_desde_Reporte_de_Valorización_de_Instrumentos6[[#This Row],[PORTAFOLIO]],1) -> 63000312501E-0 | AA120: Deuda corporativa directa - Local | AB120: Deuda | AC120: =Tabla_Consulta_desde_Reporte_de_Valorización_de_Instrumentos6[[#This Row],[VALOR_UNITARIO]]*Tabla_Consulta_desde_Reporte_de_Valorización_de_Instrumentos6[[#This Row],[CANTIDAD]] -> 15000000 | AD120: #N/A | AE120: =_xlfn.IFNA(_xlfn.XLOOKUP(Tabla_Consulta_desde_Reporte_de_Valorización_de_Instrumentos6[[#This Row],[Emisor2]],'Parametria 2'!G:G,'Parametria 2'!F:F,_xlfn.XLOOKUP(Tabla_Consulta_desde_Reporte_de_Valorización_de_Instrumentos6[[#This Row],[Emisor2]],'Valorización de Instrumentos_of'!H:H,'Valorización de Instrumentos_of'!H:H)),_xlfn.XLOOKUP(Tabla_Consulta_desde_Reporte_de_Valorización_de_Instrumentos6[[#This Row],[TITULO]],'Parametria 2'!K:K,'Parametria 2'!L:L)) -> Interbank
A121: 31/12/2025 | B121: 27 | C121: IN-FONDO1 | D121: TCDC | E121: 274325396355 | F121: XS0511096355 | G121: HUASCA 5.2 04/ | H121: 4325 | I121: 3 | J121: 1000 | K121: 312930.39 | L121: 312930.39 | M121: 1379 | N121: 46844 | O121: 822 | P121: 1 | Q121: RENTA FIJA | R121: 312797.49 | S121: 312797.49 | U121: 0 | V121: 0 | W121: 0 | X121: 0.0963742 | Y121: =+MID(Tabla_Consulta_desde_Reporte_de_Valorización_de_Instrumentos6[[#This Row],[CODIGO_SBS]],7,1) -> 3 | Z121: =Tabla_Consulta_desde_Reporte_de_Valorización_de_Instrumentos6[[#This Row],[CODIGO_SBS]]&"-"&RIGHT(Tabla_Consulta_desde_Reporte_de_Valorización_de_Instrumentos6[[#This Row],[PORTAFOLIO]],1) -> 274325396355-1 | AA121: Titularización - Renta fija - Internacional | AB121: Deuda | AC121: =Tabla_Consulta_desde_Reporte_de_Valorización_de_Instrumentos6[[#This Row],[VALOR_UNITARIO]]*Tabla_Consulta_desde_Reporte_de_Valorización_de_Instrumentos6[[#This Row],[CANTIDAD]] -> 1379000 | AD121: Huascacocha Finance Limited | AE121: =_xlfn.IFNA(_xlfn.XLOOKUP(Tabla_Consulta_desde_Reporte_de_Valorización_de_Instrumentos6[[#This Row],[Emisor2]],'Parametria 2'!G:G,'Parametria 2'!F:F,_xlfn.XLOOKUP(Tabla_Consulta_desde_Reporte_de_Valorización_de_Instrumentos6[[#This Row],[Emisor2]],'Valorización de Instrumentos_of'!H:H,'Valorización de Instrumentos_of'!H:H)),_xlfn.XLOOKUP(Tabla_Consulta_desde_Reporte_de_Valorización_de_Instrumentos6[[#This Row],[TITULO]],'Parametria 2'!K:K,'Parametria 2'!L:L)) -> Huascacocha Finance Limited
A122: 31/12/2025 | B122: 27 | C122: IN-FONDO2 | D122: TCDC | E122: 274325396355 | F122: XS0511096355 | G122: HUASCA 5.2 04/ | H122: 4325 | I122: 3 | J122: 1000 | K122: 3574985.7 | L122: 3574985.7 | M122: 15754 | N122: 46844 | O122: 822 | P122: 1 | Q122: RENTA FIJA | R122: 3573467.4 | S122: 3573467.4 | U122: 0 | V122: 0 | W122: 0 | X122: 0.0963742 | Y122: =+MID(Tabla_Consulta_desde_Reporte_de_Valorización_de_Instrumentos6[[#This Row],[CODIGO_SBS]],7,1) -> 3 | Z122: =Tabla_Consulta_desde_Reporte_de_Valorización_de_Instrumentos6[[#This Row],[CODIGO_SBS]]&"-"&RIGHT(Tabla_Consulta_desde_Reporte_de_Valorización_de_Instrumentos6[[#This Row],[PORTAFOLIO]],1) -> 274325396355-2 | AA122: Titularización - Renta fija - Internacional | AB122: Deuda | AC122: =Tabla_Consulta_desde_Reporte_de_Valorización_de_Instrumentos6[[#This Row],[VALOR_UNITARIO]]*Tabla_Consulta_desde_Reporte_de_Valorización_de_Instrumentos6[[#This Row],[CANTIDAD]] -> 15754000 | AD122: Huascacocha Finance Limited | AE122: =_xlfn.IFNA(_xlfn.XLOOKUP(Tabla_Consulta_desde_Reporte_de_Valorización_de_Instrumentos6[[#This Row],[Emisor2]],'Parametria 2'!G:G,'Parametria 2'!F:F,_xlfn.XLOOKUP(Tabla_Consulta_desde_Reporte_de_Valorización_de_Instrumentos6[[#This Row],[Emisor2]],'Valorización de Instrumentos_of'!H:H,'Valorización de Instrumentos_of'!H:H)),_xlfn.XLOOKUP(Tabla_Consulta_desde_Reporte_de_Valorización_de_Instrumentos6[[#This Row],[TITULO]],'Parametria 2'!K:K,'Parametria 2'!L:L)) -> Huascacocha Finance Limited
A123: 31/12/2025 | B123: 27 | C123: IN-FONDO1 | D123: TCDC | E123: 274325395894 | F123: XS0511095894 | G123: HUASCA 5.2 04/0 | H123: 4325 | I123: 3 | J123: 1000 | K123: 483453.35 | L123: 483453.35 | M123: 2131 | N123: 46844 | O123: 822 | P123: 1 | Q123: RENTA FIJA | R123: 483247.58 | S123: 483247.58 | U123: 0 | V123: 0 | W123: 0 | X123: 0.0965604 | Y123: =+MID(Tabla_Consulta_desde_Reporte_de_Valorización_de_Instrumentos6[[#This Row],[CODIGO_SBS]],7,1) -> 3 | Z123: =Tabla_Consulta_desde_Reporte_de_Valorización_de_Instrumentos6[[#This Row],[CODIGO_SBS]]&"-"&RIGHT(Tabla_Consulta_desde_Reporte_de_Valorización_de_Instrumentos6[[#This Row],[PORTAFOLIO]],1) -> 274325395894-1 | AA123: Titularización - Renta fija - Internacional | AB123: Deuda | AC123: =Tabla_Consulta_desde_Reporte_de_Valorización_de_Instrumentos6[[#This Row],[VALOR_UNITARIO]]*Tabla_Consulta_desde_Reporte_de_Valorización_de_Instrumentos6[[#This Row],[CANTIDAD]] -> 2131000 | AD123: Huascacocha Finance Limited | AE123: =_xlfn.IFNA(_xlfn.XLOOKUP(Tabla_Consulta_desde_Reporte_de_Valorización_de_Instrumentos6[[#This Row],[Emisor2]],'Parametria 2'!G:G,'Parametria 2'!F:F,_xlfn.XLOOKUP(Tabla_Consulta_desde_Reporte_de_Valorización_de_Instrumentos6[[#This Row],[Emisor2]],'Valorización de Instrumentos_of'!H:H,'Valorización de Instrumentos_of'!H:H)),_xlfn.XLOOKUP(Tabla_Consulta_desde_Reporte_de_Valorización_de_Instrumentos6[[#This Row],[TITULO]],'Parametria 2'!K:K,'Parametria 2'!L:L)) -> Huascacocha Finance Limited
A124: 31/12/2025 | B124: 27 | C124: IN-FONDO2 | D124: TCDC | E124: 274325395894 | F124: XS0511095894 | G124: HUASCA 5.2 04/0 | H124: 4325 | I124: 3 | J124: 1000 | K124: 5524662.6 | L124: 5524662.6 | M124: 24352 | N124: 46844 | O124: 822 | P124: 1 | Q124: RENTA FIJA | R124: 5522311.2 | S124: 5522311.2 | U124: 0 | V124: 0 | W124: 0 | X124: 0.0965604 | Y124: =+MID(Tabla_Consulta_desde_Reporte_de_Valorización_de_Instrumentos6[[#This Row],[CODIGO_SBS]],7,1) -> 3 | Z124: =Tabla_Consulta_desde_Reporte_de_Valorización_de_Instrumentos6[[#This Row],[CODIGO_SBS]]&"-"&RIGHT(Tabla_Consulta_desde_Reporte_de_Valorización_de_Instrumentos6[[#This Row],[PORTAFOLIO]],1) -> 274325395894-2 | AA124: Titularización - Renta fija - Internacional | AB124: Deuda | AC124: =Tabla_Consulta_desde_Reporte_de_Valorización_de_Instrumentos6[[#This Row],[VALOR_UNITARIO]]*Tabla_Consulta_desde_Reporte_de_Valorización_de_Instrumentos6[[#This Row],[CANTIDAD]] -> 24352000 | AD124: Huascacocha Finance Limited | AE124: =_xlfn.IFNA(_xlfn.XLOOKUP(Tabla_Consulta_desde_Reporte_de_Valorización_de_Instrumentos6[[#This Row],[Emisor2]],'Parametria 2'!G:G,'Parametria 2'!F:F,_xlfn.XLOOKUP(Tabla_Consulta_desde_Reporte_de_Valorización_de_Instrumentos6[[#This Row],[Emisor2]],'Valorización de Instrumentos_of'!H:H,'Valorización de Instrumentos_of'!H:H)),_xlfn.XLOOKUP(Tabla_Consulta_desde_Reporte_de_Valorización_de_Instrumentos6[[#This Row],[TITULO]],'Parametria 2'!K:K,'Parametria 2'!L:L)) -> Huascacocha Finance Limited
A125: 31/12/2025 | B125: 27 | C125: IN-FONDO2 | D125: TCDC | E125: 2702021ADP1A | F125: CVL80050A019 | G125: BTADP1EU | H125: 0202 | I125: 1 | J125: 100 | K125: 206963.99 | L125: 206963.99 | M125: 247109 | N125: 46153 | O125: 131 | P125: 1 | Q125: RENTA FIJA | R125: 206965.75 | S125: 206965.75 | T125: CCOR | U125: 0 | V125: 0 | W125: 0 | X125: -7.1e-06 | Y125: =+MID(Tabla_Consulta_desde_Reporte_de_Valorización_de_Instrumentos6[[#This Row],[CODIGO_SBS]],7,1) -> 1 | Z125: =Tabla_Consulta_desde_Reporte_de_Valorización_de_Instrumentos6[[#This Row],[CODIGO_SBS]]&"-"&RIGHT(Tabla_Consulta_desde_Reporte_de_Valorización_de_Instrumentos6[[#This Row],[PORTAFOLIO]],1) -> 2702021ADP1A-2 | AA125: Titularización - Renta fija - Local | AB125: Deuda | AC125: =Tabla_Consulta_desde_Reporte_de_Valorización_de_Instrumentos6[[#This Row],[VALOR_UNITARIO]]*Tabla_Consulta_desde_Reporte_de_Valorización_de_Instrumentos6[[#This Row],[CANTIDAD]] -> 24710900 | AD125: ADP | AE125: =_xlfn.IFNA(_xlfn.XLOOKUP(Tabla_Consulta_desde_Reporte_de_Valorización_de_Instrumentos6[[#This Row],[Emisor2]],'Parametria 2'!G:G,'Parametria 2'!F:F,_xlfn.XLOOKUP(Tabla_Consulta_desde_Reporte_de_Valorización_de_Instrumentos6[[#This Row],[Emisor2]],'Valorización de Instrumentos_of'!H:H,'Valorización de Instrumentos_of'!H:H)),_xlfn.XLOOKUP(Tabla_Consulta_desde_Reporte_de_Valorización_de_Instrumentos6[[#This Row],[TITULO]],'Parametria 2'!K:K,'Parametria 2'!L:L)) -> ADP
A126: 31/12/2025 | B126: 27 | C126: IN-FONDO1 | D126: TCDC | E126: 2702011INS3U | F126: CVL800702P33 | G126: COLPE1P3E | H126: 0201 | I126: 1 | J126: 975 | K126: 24515266 | L126: 24515266 | M126: 30700 | N126: 50273 | O126: 4251 | P126: 1 | Q126: RENTA FIJA | R126: 24466296 | S126: 24466296 | T126: GITC | U126: 0 | V126: 0 | W126: 0 | X126: 1.5951143 | Y126: =+MID(Tabla_Consulta_desde_Reporte_de_Valorización_de_Instrumentos6[[#This Row],[CODIGO_SBS]],7,1) -> 1 | Z126: =Tabla_Consulta_desde_Reporte_de_Valorización_de_Instrumentos6[[#This Row],[CODIGO_SBS]]&"-"&RIGHT(Tabla_Consulta_desde_Reporte_de_Valorización_de_Instrumentos6[[#This Row],[PORTAFOLIO]],1) -> 2702011INS3U-1 | AA126: Titularización - Renta fija - Local | AB126: Deuda | AC126: =Tabla_Consulta_desde_Reporte_de_Valorización_de_Instrumentos6[[#This Row],[VALOR_UNITARIO]]*Tabla_Consulta_desde_Reporte_de_Valorización_de_Instrumentos6[[#This Row],[CANTIDAD]] -> 29932500 | AD126: Internacional de Titulos Soc. Titulizadora | AE126: =_xlfn.IFNA(_xlfn.XLOOKUP(Tabla_Consulta_desde_Reporte_de_Valorización_de_Instrumentos6[[#This Row],[Emisor2]],'Parametria 2'!G:G,'Parametria 2'!F:F,_xlfn.XLOOKUP(Tabla_Consulta_desde_Reporte_de_Valorización_de_Instrumentos6[[#This Row],[Emisor2]],'Valorización de Instrumentos_of'!H:H,'Valorización de Instrumentos_of'!H:H)),_xlfn.XLOOKUP(Tabla_Consulta_desde_Reporte_de_Valorización_de_Instrumentos6[[#This Row],[TITULO]],'Parametria 2'!K:K,'Parametria 2'!L:L)) -> Colegios Peruanos
A127: 31/12/2025 | B127: 27 | C127: IN-FONDO1 | D127: TCDC | E127: 2702011IS11A | F127: PEP80070F166 | G127: SINT1TCP1A | H127: 0201 | I127: 1 | J127: 1000 | K127: 54897680 | L127: 54897680 | M127: 59500 | N127: 49197 | O127: 3175 | P127: 1 | Q127: RENTA FIJA | R127: 54851467 | S127: 54851467 | T127: GITC | U127: 0 | V127: 0 | W127: 0 | X127: 0.7766832 | Y127: =+MID(Tabla_Consulta_desde_Reporte_de_Valorización_de_Instrumentos6[[#This Row],[CODIGO_SBS]],7,1) -> 1 | Z127: =Tabla_Consulta_desde_Reporte_de_Valorización_de_Instrumentos6[[#This Row],[CODIGO_SBS]]&"-"&RIGHT(Tabla_Consulta_desde_Reporte_de_Valorización_de_Instrumentos6[[#This Row],[PORTAFOLIO]],1) -> 2702011IS11A-1 | AA127: Titularización - Renta fija - Local | AB127: Deuda | AC127: =Tabla_Consulta_desde_Reporte_de_Valorización_de_Instrumentos6[[#This Row],[VALOR_UNITARIO]]*Tabla_Consulta_desde_Reporte_de_Valorización_de_Instrumentos6[[#This Row],[CANTIDAD]] -> 59500000 | AD127: Colegios Peruanos - Internacional de Titulos Soc. Titulizadora | AE127: =_xlfn.IFNA(_xlfn.XLOOKUP(Tabla_Consulta_desde_Reporte_de_Valorización_de_Instrumentos6[[#This Row],[Emisor2]],'Parametria 2'!G:G,'Parametria 2'!F:F,_xlfn.XLOOKUP(Tabla_Consulta_desde_Reporte_de_Valorización_de_Instrumentos6[[#This Row],[Emisor2]],'Valorización de Instrumentos_of'!H:H,'Valorización de Instrumentos_of'!H:H)),_xlfn.XLOOKUP(Tabla_Consulta_desde_Reporte_de_Valorización_de_Instrumentos6[[#This Row],[TITULO]],'Parametria 2'!K:K,'Parametria 2'!L:L)) -> Scotia Titulizadora
A128: 31/12/2025 | B128: 27 | C128: IN-FONDO2 | D128: TCDC | E128: 2702011IS11A | F128: PEP80070F166 | G128: SINT1TCP1A | H128: 0201 | I128: 1 | J128: 1000 | K128: 43825879 | L128: 43825879 | M128: 47500 | N128: 49197 | O128: 3175 | P128: 1 | Q128: RENTA FIJA | R128: 43788987 | S128: 43788987 | T128: GITC | U128: 0 | V128: 0 | W128: 0 | X128: 0.7766832 | Y128: =+MID(Tabla_Consulta_desde_Reporte_de_Valorización_de_Instrumentos6[[#This Row],[CODIGO_SBS]],7,1) -> 1 | Z128: =Tabla_Consulta_desde_Reporte_de_Valorización_de_Instrumentos6[[#This Row],[CODIGO_SBS]]&"-"&RIGHT(Tabla_Consulta_desde_Reporte_de_Valorización_de_Instrumentos6[[#This Row],[PORTAFOLIO]],1) -> 2702011IS11A-2 | AA128: Titularización - Renta fija - Local | AB128: Deuda | AC128: =Tabla_Consulta_desde_Reporte_de_Valorización_de_Instrumentos6[[#This Row],[VALOR_UNITARIO]]*Tabla_Consulta_desde_Reporte_de_Valorización_de_Instrumentos6[[#This Row],[CANTIDAD]] -> 47500000 | AD128: Internacional de Titulos Soc. Titulizadora | AE128: =_xlfn.IFNA(_xlfn.XLOOKUP(Tabla_Consulta_desde_Reporte_de_Valorización_de_Instrumentos6[[#This Row],[Emisor2]],'Parametria 2'!G:G,'Parametria 2'!F:F,_xlfn.XLOOKUP(Tabla_Consulta_desde_Reporte_de_Valorización_de_Instrumentos6[[#This Row],[Emisor2]],'Valorización de Instrumentos_of'!H:H,'Valorización de Instrumentos_of'!H:H)),_xlfn.XLOOKUP(Tabla_Consulta_desde_Reporte_de_Valorización_de_Instrumentos6[[#This Row],[TITULO]],'Parametria 2'!K:K,'Parametria 2'!L:L)) -> Colegios Peruanos
...

Sheet Parametria 2
A1: Emisor2 | C1: Nombre (G&P) | F1: Nombre (G&P) | G1: Emisor2 | O1: Emisor | P1: AUM
A2: Gobierno Central | C2: Gobierno Central | F2: Aenza | G2: Graña y Montero S.A.A. | K2: MIBAN5CD1A | L2: MiBanco | O2: Banbif | P2: =SUMIF('Valorización de Instrumentos'!AE:AE,'Parametria 2'!O2,'Valorización de Instrumentos'!K:K) -> 1.442558e+08
A3: Gobierno de Chile | C3: Carlyle Peru | F3: Alicorp | G3: Alicorp S.A. | K3: COMPA3CD3B | L3: Compartamos Banco | O3: Banco de la Nación | P3: =SUMIF('Valorización de Instrumentos'!AE:AE,'Parametria 2'!O3,'Valorización de Instrumentos'!K:K) -> 5479726.5
A4: Gobierno de Brasil | C4: Macro Infraestructura | F4: Alicorp | G4: Alicorp | K4: COMPF3CD3A | L4: Compartamos Banco | O4: Jockey Plaza | P4: =SUMIF('Valorización de Instrumentos'!AE:AE,'Parametria 2'!O4,'Valorización de Instrumentos'!K:K) -> 57157116
A5: Gobierno de Colombia | C5: BD Senior Loans | F5: Auna | G5: AUNA SA | K5: INTER2CD1E | L5: Interbank | O5: Primax | P5: =SUMIF('Valorización de Instrumentos'!AE:AE,'Parametria 2'!O5,'Valorización de Instrumentos'!K:K) -> 51254539
A6: Gobierno de México | C6: Sigma - Leasing Operativo | F6: BBVA | G6: Banco Continental | K6: INTER2CD1D | L6: Interbank | O6: Hermes | P6: =SUMIF('Valorización de Instrumentos'!AE:AE,'Parametria 2'!O6,'Valorización de Instrumentos'!K:K) -> 6957636.3
A7: Grupo Nutresa S.A. | C7: Van Eck - El Dorado Peru | F7: Banco de Crédito del Perú | G7: Banco de Crédito del Perú | K7: ECSCP2CP3C | L7: Santander Consumer Bank | O7: Inca Rail | P7: =SUMIF('Valorización de Instrumentos'!AE:AE,'Parametria 2'!O7,'Valorización de Instrumentos'!K:K) -> 30547552
A8: Nexa Resources | C8: Kandeo - II Private Equity | F8: Buenaventura | G8: Buenaventura ADR | K8: ECSCP3CP2A | L8: Santander Consumer Bank | O8: Intursa | P8: =SUMIF('Valorización de Instrumentos'!AE:AE,'Parametria 2'!O8,'Valorización de Instrumentos'!K:K) -> 1.1668228e+08
A9: Grupo Financiero Banorte | C9: Macrocapitales - Fortaleza | F9: Casa Andina | G9: Casa Andina (Scotia Sociedad Titulizadora) | K9: ECSCP3CP1A | L9: Santander Consumer Bank | O9: Tecsup | P9: =SUMIF('Valorización de Instrumentos'!AE:AE,'Parametria 2'!O9,'Valorización de Instrumentos'!K:K) -> 1764204.3
A10: BBVA Bancomer | C10: W Capital - Fondo Inmobiliario | F10: Colegios Peruanos | G10: Colegios Peruanos - Internacional de Títulos Soc. Titulizadora | K10: ECSCP2CP3D | L10: Santander Consumer Bank | O10: Site del Perú | P10: =SUMIF('Valorización de Instrumentos'!AE:AE,'Parametria 2'!O10,'Valorización de Instrumentos'!K:K) -> 2.2178046e+08
A11: Grupo Aval Acciones y Valores | C11: Sura Credicorp Infraestructura | F11: Credicorp | G11: Credicorp LTD. | K11: ECSCP3CP1B | L11: Santander Consumer Bank | O11: Integratel | P11: =SUMIF('Valorización de Instrumentos'!AE:AE,'Parametria 2'!O11,'Valorización de Instrumentos'!K:K) -> 1.3204671e+08
A12: Banco Davivienda S.A. | C12: AC Capitales - Inmobiliario II | F12: Engie | G12: Energía del Sur S.A. | K12: PLUZ6PC1A | L12: Pluz Energía | O12: Pluz Energía | P12: =SUMIF('Valorización de Instrumentos'!AE:AE,'Parametria 2'!O12,'Valorización de Instrumentos'!K:K) -> 94112875
A13: Banco de Crédito e Inversiones | C13: AC Capitales - Infraestructura II | F13: Ferreycorp | G13: Ferreyros S.A.A. | K13: LUSUR4CP3C | L13: Luz del Sur | O13: Luz del Sur | P13: =SUMIF('Valorización de Instrumentos'!AE:AE,'Parametria 2'!O13,'Valorización de Instrumentos'!K:K) -> 1.9380167e+08
... A21: Jockey Plaza | C21: Sigma- Infraestructura | F21: Intursa | G21: Inversiones Nacionales de Turismo S.A. | K21: SANTC6CD1A | L21: Santander Peru | O21: Casa Andina | P21: =SUMIF('Valorización de Instrumentos'!AE:AE,'Parametria 2'!O21,'Valorización de Instrumentos'!K:K) -> 28177240
A22: Primax | C22: AXA World Funds - US Dynamic High Yield | F22: Jockey Plaza | G22: Jockey Plaza | K22: SANTC6CD1B | L22: Santander Peru | M22: CD | O22: Ferreycorp | P22: =SUMIF('Valorización de Instrumentos'!AE:AE,'Parametria 2'!O22,'Valorización de Instrumentos'!K:K) -> 5.3654005e+08
A23: Hermes | C23: Vontobel - Credit Opportunities | F23: Lima Expresa | G23: Línea Amarilla S.A.C. | K23: CSCOT5CD2G | L23: Santander Consumer Bank | M23: corporate bond | O23: Puerto Chancay | P23: =SUMIF('Valorización de Instrumentos'!AE:AE,'Parametria 2'!O23,'Valorización de Instrumentos'!K:K) -> 54821451
A24: Inca Rail | C24: Vontobel - Emerging Markets Corporate | F24: Minsur | G24: Minsur S.A. | K24: ZCOF5DCP1A | L24: COFIDE | O24: Alicorp | P24: =SUMIF('Valorización de Instrumentos'!AE:AE,'Parametria 2'!O24,'Valorización de Instrumentos'!K:K) -> 3.5181291e+08
A25: Hunt Oil | C25: Vontobel - Emerging Markets Debt | F25: Minsur | G25: MINSUR | K25: SCOF4DCP4A | L25: COFIDE | O25: Buenaventura | P25: =SUMIF('Valorización de Instrumentos'!AE:AE,'Parametria 2'!O25,'Valorización de Instrumentos'!K:K) -> 1.2204285e+09
A26: Inversiones Nacionales de Turismo S.A. | C26: Barings - Emerging Markets Local Debt Fund | F26: Nexa Resources Perú | G26: Nexa US | K26: GNB3CD2A | L26: Banco GNB | O26: Unacem | P26: =SUMIF('Valorización de Instrumentos'!AE:AE,'Parametria 2'!O26,'Valorización de Instrumentos'!K:K) -> 1.2397963e+08
A27: Tecsup | C27: Barings - Emerging Markets Sovereign Debt Fund | F27: Nexa Resources Perú | G27: Nexa Perú (Milpo) | K27: GNB3CD2B | L27: Banco GNB | O27: BBVA | P27: =SUMIF('Valorización de Instrumentos'!AE:AE,'Parametria 2'!O27,'Valorización de Instrumentos'!K:K) -> 65938505
A28: Site del Perú | C28: Arcano Fund - European Income Fund, ESG Selection | F28: Nexa Resources Perú | G28: Nexa US | K28: GNB3CD1D | L28: Banco GNB | O28: Pacasmayo | P28: =SUMIF('Valorización de Instrumentos'!AE:AE,'Parametria 2'!O28,'Valorización de Instrumentos'!K:K) -> 2.509615e+08
A29: Alicorp | C29: Arcano Fund - European Income Fund - ESG Selection | F29: Orygen | G29: Orazen | K29: HBM | L29: Hudbay | O29: Credicorp | P29: =SUMIF('Valorización de Instrumentos'!AE:AE,'Parametria 2'!O29,'Valorización de Instrumentos'!K:K) -> 1.4509467e+09
A30: Buenaventura | C30: JP Morgan - Korea Equity Fund | F30: Pacasmayo | G30: Cementos Pacasmayo-CM | O30: Orygen | P30: =SUMIF('Valorización de Instrumentos'!AE:AE,'Parametria 2'!O30,'Valorización de Instrumentos'!K:K) -> 2.9127666e+08
A31: Telefónica del Perú | C31: Pinebridge - Asia Ex-Japan Small Caps | F31: Pluz Energía | G31: Pluz Energía Perú S.A.A | O31: Engie | P31: =SUMIF('Valorización de Instrumentos'!AE:AE,'Parametria 2'!O31,'Valorización de Instrumentos'!K:K) -> 2.2032392e+08
A32: Pluz Energía Perú S.A.A | C32: BlackRock - iShares Korea | F32: Primax | G32: Primax | O32: Aenza | P32: =SUMIF('Valorización de Instrumentos'!AE:AE,'Parametria 2'!O32,'Valorización de Instrumentos'!K:K) -> 59060165
A33: Orazen | C33: BlackRock - iShares Taiwan | F33: Puerto Chancay | G33: Puerto Chancay A | O33: Nexa Resources Perú | P33: =SUMIF('Valorización de Instrumentos'!AE:AE,'Parametria 2'!O33,'Valorización de Instrumentos'!K:K) -> 2.7926475e+08
A34: Luz del Sur | C34: BlackRock - iShares PHLX Semiconductor ETF | F34: Puerto Chancay | G34: Puerto Chancay B | O34: Volcan | P34: =SUMIF('Valorización de Instrumentos'!AE:AE,'Parametria 2'!O34,'Valorización de Instrumentos'!K:K) -> 87650779
A35: MINSUR | C35: BlackRock - iShares - Tips ETF | F35: Rutas de Lima | G35: Rutas de Lima | O35: El Comercio | P35: =SUMIF('Valorización de Instrumentos'!AE:AE,'Parametria 2'!O35,'Valorización de Instrumentos'!K:K) -> 1864743.2
A36: #N/A | C36: BlackRock - iShares Convertible Bond ETF | F36: Santander Consumer | G36: No encontrado | O36: Minsur | P36: =SUMIF('Valorización de Instrumentos'!AE:AE,'Parametria 2'!O36,'Valorización de Instrumentos'!K:K) -> 1.050478e+09
A37: Fondo Mi Vivienda | C37: BlackRock - iShares Euro Stoxx Banks 30-15 UCITS | F37: Tecsup | G37: Tecsup | O37: Compartamos Banco | P37: =SUMIF('Valorización de Instrumentos'!AE:AE,'Parametria 2'!O37,'Valorización de Instrumentos'!K:K) -> 32286040
A38: Intercorp Perú | C38: Nomura - US High Yield Bond Fund | F38: Unacem | G38: Unión Andina de Cementos | O38: Banco BCI Peru | P38: =SUMIF('Valorización de Instrumentos'!AE:AE,'Parametria 2'!O38,'Valorización de Instrumentos'!K:K) -> 51216372
A39: InRetail Shopping Malls | C39: Fidelity - European Dynamic Growth | F39: Volcan | G39: Volcan A | O39: Santander Peru | P39: =SUMIF('Valorización de Instrumentos'!AE:AE,'Parametria 2'!O39,'Valorización de Instrumentos'!K:K) -> 51901086
A40: TITIRSM1 - InRetail | C40: Robeco - Chinese Equities | F40: Volcan | G40: Volcan B | O40: COFIDE | P40: =SUMIF('Valorización de Instrumentos'!AE:AE,'Parametria 2'!O40,'Valorización de Instrumentos'!K:K) -> 44789536
A41: Colegios Peruanos - Internacional de Titulos Soc. Titulizadora | C41: Eastspring - Japan Dynamic Fund | F41: Banbif | G41: Banco Interamericano de Finanzas | O41: Banco GNB | P41: =SUMIF('Valorización de Instrumentos'!AE:AE,'Parametria 2'!O41,'Valorización de Instrumentos'!K:K) -> 53566020
A42: Casa Andina (Scotia Sociedad Titulizadora) | C42: Groupama - Avenir Euro (Mid Small Caps) | F42: Scotia Titulizadora | G42: Colegios Peruanos - Internacional de Titulos Soc. Titulizadora | O42: MiBanco | P42: =SUMIF('Valorización de Instrumentos'!AE:AE,'Parametria 2'!O42,'Valorización de Instrumentos'!K:K) -> 19578970
A43: Inretail Peru Corp | C43: Pimco - US High Yield Bond | F43: Colegios Peruanos | G43: Internacional de Titulos Soc. Titulizadora | O43: InRetail Consumer | P43: =SUMIF('Valorización de Instrumentos'!AE:AE,'Parametria 2'!O43,'Valorización de Instrumentos'!K:K) -> 1.6916334e+08
A44: Ferreyros S.A.A. | C44: PIMCO - Asia High Yield Bond Fund | F44: Cerro Verde | G44: Sociedad Minera Cerro Verde S.A.A.
A45: Puerto Chancay A | C45: Pimco - GIS Income Fund | F45: Pluz Energía | G45: Edelnor S.A.A.
A46: Puerto Chancay B | C46: Pimco - Emerging Markets Local Bond Fund | F46: Orygen | G46: Edegel S.A.A.
A47: Alicorp S.A. | C47: Man GLG - Continental European Growth | F47: Interbank | G47: Banco Internacional del Perú
A48: Sociedad Minera Cerro Verde S.A.A. | C48: Janus Henderson - Horizon Euroland Fund | F48: Alicorp | G48: Alicorp
A49: Unión Andina de Cementos | C49: Santander Consumer | F49: Integratel | G49: Telefónica del Perú
A50: Banco Continental | C50: Pluz Energía Perú S.A.A | F50: Hochschild | G50: Hocshild Minning Corp.
A51: Cementos Pacasmayo-CM | C51: Luz del Sur | F51: InRetail Shopping Malls | G51: InRetail Shopping Malls
A52: Credicorp LTD. | C52: Lazard Capital Fi | F52: InRetail Shopping Malls | G52: TITIRSM1 - InRetail
A53: Edegel S.A.A. | C53: Krane - CSI China Internet Fund | F53: InRetail Consumer | G53: SINT1INR1U - InRetail
A54: Edelnor S.A.A. | C54: Moneda - Deuda Latam LCC | F54: Inretail Peru Corp | G54: Inretail Peru Corp
A55: Energía del Sur S.A. | C55: BlueBay - Financial Capital Bond - E
A56: Graña y Montero S.A.A. | C56: Invesco - Power Shares QQQ | F56: Gobierno Central | G56: Gobierno Central
A57: Intergroup | C57: Schroder - International Selection Fund China A | F57: Gobierno de Chile | G57: Gobierno de Chile
A58: Nexa Perú (Milpo) | C58: Global X - Copper Miners ETF | F58: Gobierno de Brasil | G58: Gobierno de Brasil
A59: Volcan B | C59: Global X - Silvers Miners ETF | F59: Gobierno de Colombia | G59: Gobierno de Colombia
A60: Volcan A | C60: Global X - Uranium Miners ETF | F60: Gobierno de México | G60: Gobierno de México
A61: El Comercio | C61: Global X - Argentina ETF | F61: Nutresa | G61: Nutresa
A62: Minsur S.A. | C62: Baillie Gifford & Co Ltd - Overseas Growth Funds ICVC - Pacific Fund | F62: Nexa Resources | G62: Nexa Resources
A63: Fossal SA | C63: Joh Berenberg - European Focus Fund | F63: Banorte | G63: Banorte
A64: Buenaventura ADR | C64: SKYY US - First Trust Cloud Computing ETF | F64: BBVA Bancomer | G64: BBVA Bancomer
A65: Cementos Pacasmayo-ADR | C65: Liontrust - Liontrust European Dynamic Fund S | F65: Aval | G65: Aval
A66: AUNA SA | C66: Moneda - Latam High Yield | F66: Banco Davivienda S.A. | G66: Banco Davivienda S.A.
A67: Aclara Resources Inc. | C67: Moneda - CLOs | F67: Banco de Crédito e Inversiones | G67: Banco de Crédito e Inversiones
... A125: Krane - CSI China Internet Fund | C125: Emp. Públicas Medellin | F125: Macrocapitales - Fortaleza | G125: Macrocapitales - Fortaleza
A126: Moneda - Deuda Latam LCC | C126: #N/A | F126: W Capital - Fondo Inmobiliario | G126: W Capital - Fondo Inmobiliario
A127: BlueBay - Financial Capital Bond - E | C127: BIF | F127: Sura Credicorp Infraestructura | G127: Sura Credicorp Infraestructura
A128: Invesco - Power Shares QQQ | F128: AC Capitales - Inmobiliario II | G128: AC Capitales - Inmobiliario II
A129: Schroder - International Selection Fund China A | F129: AC Capitales - Infraestructura II | G129: AC Capitales - Infraestructura II
A130: Global X - Uranium Miners ETF | F130: AC Capitales - Infraestructura | G130: AC Capitales - Infraestructura
A131: Global X - Argentina ETF | F131: BCP Fondo Inmobiliario | G131: BCP Fondo Inmobiliario
A132: Global X - Silvers Miners ETF | F132: Enfoca - Descubridor 1 | G132: Enfoca - Descubridor 1
A133: Global X - Copper Miners ETF | F133: Enfoca - Descubridor 2 | G133: Enfoca - Descubridor 2
A134: Baillie Gifford & Co Ltd - Overseas Growth Funds ICVC - Pacific Fund | F134: Faro Capital - Fondo de Inversión Retail | G134: Faro Capital - Fondo de Inversión Retail
A135: Joh Berenberg - European Focus Fund | F135: LarraínVial Colliers - Fibra III | G135: LarraínVial Colliers - Fibra III
A136: SKYY US - First Trust Cloud Computing ETF | F136: LarraínVial Colliers - Fibra II | G136: LarraínVial Colliers - Fibra II
A137: Liontrust - Liontrust European Dynamic Fund S | F137: Sigma- Infraestructura | G137: Sigma- Infraestructura
A138: Moneda - Latam High Yield | F138: AXA World Funds - US Dynamic High Yield | G138: AXA World Funds - US Dynamic High Yield
A139: Neuberger Berman - CLO Income Fund | F139: Vontobel - Credit Opportunities | G139: Vontobel - Credit Opportunities
... A197: Empresas Públicas Medellin | F197: Goldman Sachs - India Equity Portfolio | G197: Goldman Sachs - India Equity Portfolio
F198: JP Morgan - Japan Equity Fund - C | G198: JP Morgan - Japan Equity Fund - C
F199: Lazard - Japanese Strategic Equity | G199: Lazard - Japanese Strategic Equity
F200: Pictet Chinese LC Debt | G200: Pictet Chinese LC Debt
F201: Schroders - Asian Opportunities | G201: Schroders - Asian Opportunities
F202: State Street - S&P 500 ETF | G202: State Street - S&P 500 ETF
F203: State Street - S&P Metals & Mining ETF | G203: State Street - S&P Metals & Mining ETF
F204: State Street - Technology Select Sector | G204: State Street - Technology Select Sector
F205: UBS - China Opportunity - A3 | G205: UBS - China Opportunity - A3
F206: VanEck Semiconductor ETF | G206: VanEck Semiconductor ETF
F207: VanEck - Gold Miners ETF | G207: VanEck - Gold Miners ETF
F208: VanEck - JPM EM LC Bond ETF | G208: VanEck - JPM EM LC Bond ETF
F209: Vanguard - Emerging Markets Bond Fund - I Retail | G209: Vanguard - Emerging Markets Bond Fund - I Retail
... F246: Emp. Públicas Medellin | G246: Emp. Públicas Medellin

Sheet Valorización de Instrumentos_of
A1: Fecha Valoración | B1: 20251231
B3: FechaValoracion | C3: TIPO_TITULO | D3: PORTAFOLIO | E3: GRUPO | F3: CODIGO_SBS | G3: CODIGO_ISIN | H3: Nombre (G&P) | I3: TITULO | J3: EMISOR | K3: Moneda | L3: VALOR_UNITARIO | M3: VALOR_VECTOR_LOCAL | N3: VALOR_VECTOR_ORIGEN | O3: CANTIDAD | P3: FECHA_VENCIMIENTO | Q3: DIAS_VENTIMIENTO | R3: TIPO_CAMBIO | S3: TIPO_RENTA | T3: VALOR_VECTOR_LOCAL_T-1 | U3: VALOR_VECTOR_ORIGEN_T-1 | V3: GRUPO_ECONOMICO | W3: ACTIVO_DEL_EMISOR | X3: PASIVO_DEL_EMISOR | Y3: PASTRIMONIO_DEL_EMISOR | Z3: DIFERENCIA | AA3: Column1 | AB3: Asset Class
B4: 31/12/2025 | C4: 01 | D4: IN-FONDO2 | E4: BGC | F4: 011000112G32 | G4: PEP01000C5E9 | H4: =+INDEX(Parametria!$V:$V,MATCH(Tabla_Consulta_desde_Reporte_de_Valorización_de_Instrumentos[[#This Row],[CODIGO_SBS]],Parametria!$B:$B,0)) -> Gobierno Central | I4: SB12AGO32 | J4: 1000 | K4: 1 | L4: 1000 | M4: 611420.9 | N4: 611420.9 | O4: 554 | P4: 48438 | Q4: 2416 | R4: 1 | S4: RENTA FIJA | T4: 610528.12 | U4: 610528.12 | W4: 0 | X4: 0 | Y4: 0 | Z4: 1.6115024 | AA4: =+MID(Tabla_Consulta_desde_Reporte_de_Valorización_de_Instrumentos[[#This Row],[CODIGO_SBS]],7,1) -> 1 | AB4: =_xlfn.XLOOKUP(Tabla_Consulta_desde_Reporte_de_Valorización_de_Instrumentos[[#This Row],[CODIGO_SBS]],G_P!A:A,G_P!E:E) -> Renta Fija
B5: 31/12/2025 | C5: 01 | D5: IN-FONDO2 | E5: BGC | F5: 011000112B29 | G5: PEP01000C5F6 | H5: =+INDEX(Parametria!$V:$V,MATCH(Tabla_Consulta_desde_Reporte_de_Valorización_de_Instrumentos[[#This Row],[CODIGO_SBS]],Parametria!$B:$B,0)) -> Gobierno Central | I5: SB12B29 | J5: 1000 | K5: 1 | L5: 1000 | M5: 9639755.9 | N5: 9639755.9 | O5: 9000 | P5: 47161 | Q5: 1139 | R5: 1 | S5: RENTA FIJA | T5: 9638055.6 | U5: 9638055.6 | W5: 0 | X5: 0 | Y5: 0 | Z5: 0.1889171 | AA5: =+MID(Tabla_Consulta_desde_Reporte_de_Valorización_de_Instrumentos[[#This Row],[CODIGO_SBS]],7,1) -> 1 | AB5: =_xlfn.XLOOKUP(Tabla_Consulta_desde_Reporte_de_Valorización_de_Instrumentos[[#This Row],[CODIGO_SBS]],G_P!A:A,G_P!E:E) -> Renta Fija
B6: 31/12/2025 | C6: 01 | D6: IN-FONDO2 | E6: BGC | F6: 011000112F55 | G6: PEP01000C4S2 | H6: =+INDEX(Parametria!$V:$V,MATCH(Tabla_Consulta_desde_Reporte_de_Valorización_de_Instrumentos[[#This Row],[CODIGO_SBS]],Parametria!$B:$B,0)) -> Gobierno Central | I6: SB12FEB55 | J6: 1000 | K6: 1 | L6: 1000 | M6: 1.2615385e+08 | N6: 1.2615385e+08 | O6: 113000 | P6: 56657 | Q6: 10635 | R6: 1 | S6: RENTA FIJA | T6: 1.2613327e+08 | U6: 1.2613327e+08 | W6: 0 | X6: 0 | Y6: 0 | Z6: 0.1821469 | AA6: =+MID(Tabla_Consulta_desde_Reporte_de_Valorización_de_Instrumentos[[#This Row],[CODIGO_SBS]],7,1) -> 1 | AB6: =_xlfn.XLOOKUP(Tabla_Consulta_desde_Reporte_de_Valorización_de_Instrumentos[[#This Row],[CODIGO_SBS]],G_P!A:A,G_P!E:E) -> Renta Fija
B7: 31/12/2025 | C7: 01 | D7: IN-FONDO2 | E7: BGC | F7: 011000112G40 | G7: PEP01000C5H2 | H7: =+INDEX(Parametria!$V:$V,MATCH(Tabla_Consulta_desde_Reporte_de_Valorización_de_Instrumentos[[#This Row],[CODIGO_SBS]],Parametria!$B:$B,0)) -> Gobierno Central | I7: SB12AGO40 | J7: 1000 | K7: 1 | L7: 1000 | M7: 2.2746707e+08 | N7: 2.2746707e+08 | O7: 249953 | P7: 51360 | Q7: 5338 | R7: 1 | S7: RENTA FIJA | T7: 2.2708451e+08 | U7: 2.2708451e+08 | W7: 0 | X7: 0 | Y7: 0 | Z7: 1.5305237 | AA7: =+MID(Tabla_Consulta_desde_Reporte_de_Valorización_de_Instrumentos[[#This Row],[CODIGO_SBS]],7,1) -> 1 | AB7: =_xlfn.XLOOKUP(Tabla_Consulta_desde_Reporte_de_Valorización_de_Instrumentos[[#This Row],[CODIGO_SBS]],G_P!A:A,G_P!E:E) -> Renta Fija
B8: 31/12/2025 | C8: 01 | D8: IN-FONDO2 | E8: BGC | F8: 011000112G35 | G8: PEP01000C5K6 | H8: =+INDEX(Parametria!$V:$V,MATCH(Tabla_Consulta_desde_Reporte_de_Valorización_de_Instrumentos[[#This Row],[CODIGO_SBS]],Parametria!$B:$B,0)) -> Gobierno Central | I8: SB12G35 | J8: 1000 | K8: 1 | L8: 1000 | M8: 6.542607e+08 | N8: 6.542607e+08 | O8: 585950 | P8: 49533 | Q8: 3511 | R8: 1 | S8: RENTA FIJA | T8: 7.7959909e+08 | U8: 7.7959909e+08 | W8: 0 | X8: 0 | Y8: 0 | Z8: 5.9619947 | AA8: =+MID(Tabla_Consulta_desde_Reporte_de_Valorización_de_Instrumentos[[#This Row],[CODIGO_SBS]],7,1) -> 1 | AB8: =_xlfn.XLOOKUP(Tabla_Consulta_desde_Reporte_de_Valorización_de_Instrumentos[[#This Row],[CODIGO_SBS]],G_P!A:A,G_P!E:E) -> Renta Fija
B9: 31/12/2025 | C9: 01 | D9: IN-FONDO2 | E9: BGC | F9: 011000112G33 | G9: PEP01000C5I0 | H9: =+INDEX(Parametria!$V:$V,MATCH(Tabla_Consulta_desde_Reporte_de_Valorización_de_Instrumentos[[#This Row],[CODIGO_SBS]],Parametria!$B:$B,0)) -> Gobierno Central | I9: SB12AGO33 | J9: 1000 | K9: 1 | L9: 1000 | M9: 1.3456725e+09 | N9: 1.3456725e+09 | O9: 1150077 | P9: 48803 | Q9: 2781 | R9: 1 | S9: RENTA FIJA | T9: 1.3424106e+09 | U9: 1.3424106e+09 | W9: 0 | X9: 0 | Y9: 0 | Z9: 2.8362001 | AA9: =+MID(Tabla_Consulta_desde_Reporte_de_Valorización_de_Instrumentos[[#This Row],[CODIGO_SBS]],7,1) -> 1 | AB9: =_xlfn.XLOOKUP(Tabla_Consulta_desde_Reporte_de_Valorización_de_Instrumentos[[#This Row],[CODIGO_SBS]],G_P!A:A,G_P!E:E) -> Renta Fija
B10: 31/12/2025 | C10: 01 | D10: IN-FONDO2 | E10: BGC | F10: 011000112G34 | G10: PEP01000C5G4 | H10: =+INDEX(Parametria!$V:$V,MATCH(Tabla_Consulta_desde_Reporte_de_Valorización_de_Instrumentos[[#This Row],[CODIGO_SBS]],Parametria!$B:$B,0)) -> Gobierno Central | I10: SB12AGO34 | J10: 1000 | K10: 1 | L10: 1000 | M10: 1.3833716e+09 | N10: 1.3833716e+09 | O10: 1357066 | P10: 49168 | Q10: 3146 | R10: 1 | S10: RENTA FIJA | T10: 1.3766394e+09 | U10: 1.3766394e+09 | W10: 0 | X10: 0 | Y10: 0 | Z10: 4.9609047 | AA10: =+MID(Tabla_Consulta_desde_Reporte_de_Valorización_de_Instrumentos[[#This Row],[CODIGO_SBS]],7,1) -> 1 | AB10: =_xlfn.XLOOKUP(Tabla_Consulta_desde_Reporte_de_Valorización_de_Instrumentos[[#This Row],[CODIGO_SBS]],G_P!A:A,G_P!E:E) -> Renta Fija
B11: 31/12/2025 | C11: 01 | D11: IN-FONDO2 | E11: BGC | F11: 011000112G39 | G11: PEP01000C5J8 | H11: =+INDEX(Parametria!$V:$V,MATCH(Tabla_Consulta_desde_Reporte_de_Valorización_de_Instrumentos[[#This Row],[CODIGO_SBS]],Parametria!$B:$B,0)) -> Gobierno Central | I11: SB12G39 | J11: 1000 | K11: 1 | L11: 1000 | M11: 2.0210548e+09 | N11: 2.0210548e+09 | O11: 1801364 | P11: 50994 | Q11: 4972 | R11: 1 | S11: RENTA FIJA | T11: 1.7538822e+09 | U11: 1.7538822e+09 | W11: 0 | X11: 0 | Y11: 0 | Z11: 4.3828539 | AA11: =+MID(Tabla_Consulta_desde_Reporte_de_Valorización_de_Instrumentos[[#This Row],[CODIGO_SBS]],7,1) -> 1 | AB11: =_xlfn.XLOOKUP(Tabla_Consulta_desde_Reporte_de_Valorización_de_Instrumentos[[#This Row],[CODIGO_SBS]],G_P!A:A,G_P!E:E) -> Renta Fija
B12: 31/12/2025 | C12: 01 | D12: IN-FONDO2 | E12: BGC | F12: 011000112G37 | G12: PEP01000C2Z1 | H12: =+INDEX(Parametria!$V:$V,MATCH(Tabla_Consulta_desde_Reporte_de_Valorización_de_Instrumentos[[#This Row],[CODIGO_SBS]],Parametria!$B:$B,0)) -> Gobierno Central | I12: SOBAGO2037 | J12: 1000 | K12: 1 | L12: 1000 | M12: 1.7105274e+09 | N12: 1.7105274e+09 | O12: 1594708 | P12: 50264 | Q12: 4242 | R12: 1 | S12: RENTA FIJA | T12: 1.7024112e+09 | U12: 1.7024112e+09 | W12: 0 | X12: 0 | Y12: 0 | Z12: 5.0895012 | AA12: =+MID(Tabla_Consulta_desde_Reporte_de_Valorización_de_Instrumentos[[#This Row],[CODIGO_SBS]],7,1) -> 1 | AB12: =_xlfn.XLOOKUP(Tabla_Consulta_desde_Reporte_de_Valorización_de_Instrumentos[[#This Row],[CODIGO_SBS]],G_P!A:A,G_P!E:E) -> Renta Fija
B13: 31/12/2025 | C13: 01 | D13: IN-FONDO1 | E13: BGC | F13: 011000112F55 | G13: PEP01000C4S2 | H13: =+INDEX(Parametria!$V:$V,MATCH(Tabla_Consulta_desde_Reporte_de_Valorización_de_Instrumentos[[#This Row],[CODIGO_SBS]],Parametria!$B:$B,0)) -> Gobierno Central | I13: SB12FEB55 | J13: 1000 | K13: 1 | L13: 1000 | M13: 47670526 | N13: 47670526 | O13: 42700 | P13: 56657 | Q13: 10635 | R13: 1 | S13: RENTA FIJA | T13: 47662749 | U13: 47662749 | W13: 0 | X13: 0 | Y13: 0 | Z13: 0.1821469 | AA13: =+MID(Tabla_Consulta_desde_Reporte_de_Valorización_de_Instrumentos[[#This Row],[CODIGO_SBS]],7,1) -> 1 | AB13: =_xlfn.XLOOKUP(Tabla_Consulta_desde_Reporte_de_Valorización_de_Instrumentos[[#This Row],[CODIGO_SBS]],G_P!A:A,G_P!E:E) -> Renta Fija
B14: 31/12/2025 | C14: 01 | D14: IN-FONDO1 | E14: BGC | F14: 011000112G32 | G14: PEP01000C5E9 | H14: =+INDEX(Parametria!$V:$V,MATCH(Tabla_Consulta_desde_Reporte_de_Valorización_de_Instrumentos[[#This Row],[CODIGO_SBS]],Parametria!$B:$B,0)) -> Gobierno Central | I14: SB12AGO32 | J14: 1000 | K14: 1 | L14: 1000 | M14: 73619932 | N14: 73619932 | O14: 66706 | P14: 48438 | Q14: 2416 | R14: 1 | S14: RENTA FIJA | T14: 73512435 | U14: 73512435 | W14: 0 | X14: 0 | Y14: 0 | Z14: 1.6115024 | AA14: =+MID(Tabla_Consulta_desde_Reporte_de_Valorización_de_Instrumentos[[#This Row],[CODIGO_SBS]],7,1) -> 1 | AB14: =_xlfn.XLOOKUP(Tabla_Consulta_desde_Reporte_de_Valorización_de_Instrumentos[[#This Row],[CODIGO_SBS]],G_P!A:A,G_P!E:E) -> Renta Fija
B15: 31/12/2025 | C15: 01 | D15: IN-FONDO1 | E15: BGC | F15: 011000112G33 | G15: PEP01000C5I0 | H15: =+INDEX(Parametria!$V:$V,MATCH(Tabla_Consulta_desde_Reporte_de_Valorización_de_Instrumentos[[#This Row],[CODIGO_SBS]],Parametria!$B:$B,0)) -> Gobierno Central | I15: SB12AGO33 | J15: 1000 | K15: 1 | L15: 1000 | M15: 1.7522759e+08 | N15: 1.7522759e+08 | O15: 149758 | P15: 48803 | Q15: 2781 | R15: 1 | S15: RENTA FIJA | T15: 1.7480285e+08 | U15: 1.7480285e+08 | W15: 0 | X15: 0 | Y15: 0 | Z15: 2.8362001 | AA15: =+MID(Tabla_Consulta_desde_Reporte_de_Valorización_de_Instrumentos[[#This Row],[CODIGO_SBS]],7,1) -> 1 | AB15: =_xlfn.XLOOKUP(Tabla_Consulta_desde_Reporte_de_Valorización_de_Instrumentos[[#This Row],[CODIGO_SBS]],G_P!A:A,G_P!E:E) -> Renta Fija
... B38: 31/12/2025 | C38: 15 | D38: IN-FONDO2 | E38: OSX | F38: 1551192KAB72 | G38: USP1401KAB72 | H38: =+INDEX(Parametria!$V:$V,MATCH(Tabla_Consulta_desde_Reporte_de_Valorización_de_Instrumentos[[#This Row],[CODIGO_SBS]],Parametria!$B:$B,0)) -> Banorte | I38: BANORT 6 5/8 P | J38: 5119 | K38: 2 | L38: 1000 | M38: 70418822 | N38: 20952370 | O38: 21047 | P38: 51525 | Q38: 5503 | R38: 3.3609 | S38: RENTA FIJA | T38: 70393714 | U38: 20934311 | W38: 2191378000000 | X38: 1948764000000 | Y38: 242614000000 | Z38: 0.858056 | AA38: =+MID(Tabla_Consulta_desde_Reporte_de_Valorización_de_Instrumentos[[#This Row],[CODIGO_SBS]],7,1) -> 2 | AB38: =_xlfn.XLOOKUP(Tabla_Consulta_desde_Reporte_de_Valorización_de_Instrumentos[[#This Row],[CODIGO_SBS]],G_P!A:A,G_P!E:E) -> Renta Fija
B39: 31/12/2025 | C39: 15 | D39: IN-FONDO2 | E39: OSX | F39: 1552782BAB48 | G39: USP1S81BAB48 | H39: =+INDEX(Parametria!$V:$V,MATCH(Tabla_Consulta_desde_Reporte_de_Valorización_de_Instrumentos[[#This Row],[CODIGO_SBS]],Parametria!$B:$B,0)) -> BBVA Bancomer | I39: BBVASM 2039 | J39: 5278 | K39: 2 | L39: 1000 | M39: 43414811 | N39: 12917615 | O39: 11500 | P39: 50778 | Q39: 4756 | R39: 3.3609 | S39: RENTA FIJA | T39: 43397300 | U39: 12905876 | V39: GBBV | W39: 2808249000000 | X39: 2500434000000 | Y39: 307815000000 | Z39: 1.020707 | AA39: =+MID(Tabla_Consulta_desde_Reporte_de_Valorización_de_Instrumentos[[#This Row],[CODIGO_SBS]],7,1) -> 2 | AB39: =_xlfn.XLOOKUP(Tabla_Consulta_desde_Reporte_de_Valorización_de_Instrumentos[[#This Row],[CODIGO_SBS]],G_P!A:A,G_P!E:E) -> Renta Fija
B40: 31/12/2025 | C40: 15 | D40: IN-FONDO2 | E40: OSX | F40: 15527829AN67 | G40: USP16259AN67 | H40: =+INDEX(Parametria!$V:$V,MATCH(Tabla_Consulta_desde_Reporte_de_Valorización_de_Instrumentos[[#This Row],[CODIGO_SBS]],Parametria!$B:$B,0)) -> BBVA Bancomer | I40: BBVA 2034 | J40: 5278 | K40: 2 | L40: 1000 | M40: 20520073 | N40: 6105529.2 | O40: 6000 | P40: 49200 | Q40: 3178 | R40: 3.3609 | S40: RENTA FIJA | T40: 20477463 | U40: 6089770.8 | V40: GBBV | W40: 2808249000000 | X40: 2500434000000 | Y40: 307815000000 | Z40: 2.626388 | AA40: =+MID(Tabla_Consulta_desde_Reporte_de_Valorización_de_Instrumentos[[#This Row],[CODIGO_SBS]],7,1) -> 2 | AB40: =_xlfn.XLOOKUP(Tabla_Consulta_desde_Reporte_de_Valorización_de_Instrumentos[[#This Row],[CODIGO_SBS]],G_P!A:A,G_P!E:E) -> Renta Fija
B41: 31/12/2025 | C41: 15 | D41: IN-FONDO2 | E41: OSX | F41: 1552782BAA64 | G41: USP1S81BAA64 | H41: =+INDEX(Parametria!$V:$V,MATCH(Tabla_Consulta_desde_Reporte_de_Valorización_de_Instrumentos[[#This Row],[CODIGO_SBS]],Parametria!$B:$B,0)) -> BBVA Bancomer | I41: BBVASM 2038 | J41: 5278 | K41: 2 | L41: 1000 | M41: 24965834 | N41: 7428317.9 | O41: 6700 | P41: 50585 | Q41: 4563 | R41: 3.3609 | S41: RENTA FIJA | T41: 24969594 | U41: 7425680.7 | V41: GBBV | W41: 2808249000000 | X41: 2500434000000 | Y41: 307815000000 | Z41: 0.393611 | AA41: =+MID(Tabla_Consulta_desde_Reporte_de_Valorización_de_Instrumentos[[#This Row],[CODIGO_SBS]],7,1) -> 2 | AB41: =_xlfn.XLOOKUP(Tabla_Consulta_desde_Reporte_de_Valorización_de_Instrumentos[[#This Row],[CODIGO_SBS]],G_P!A:A,G_P!E:E) -> Renta Fija
B42: 31/12/2025 | C42: 15 | D42: IN-FONDO2 | E42: OSX | F42: 15527829AM84 | G42: USP16259AM84 | H42: =+INDEX(Parametria!$V:$V,MATCH(Tabla_Consulta_desde_Reporte_de_Valorización_de_Instrumentos[[#This Row],[CODIGO_SBS]],Parametria!$B:$B,0)) -> BBVA Bancomer | I42: BBVA 2033 | J42: 5278 | K42: 2 | L42: 1000 | M42: 8467700 | N42: 2519474 | O42: 2500 | P42: 48597 | Q42: 2575 | R42: 3.3609 | S42: RENTA FIJA | T42: 8454457.9 | U42: 2514262.2 | V42: GBBV | W42: 2808249000000 | X42: 2500434000000 | Y42: 307815000000 | Z42: 2.084722 | AA42: =+MID(Tabla_Consulta_desde_Reporte_de_Valorización_de_Instrumentos[[#This Row],[CODIGO_SBS]],7,1) -> 2 | AB42: =_xlfn.XLOOKUP(Tabla_Consulta_desde_Reporte_de_Valorización_de_Instrumentos[[#This Row],[CODIGO_SBS]],G_P!A:A,G_P!E:E) -> Renta Fija
B43: 31/12/2025 | C43: 15 | D43: IN-FONDO1 | E43: OSX | F43: 1552782BAB48 | G43: USP1S81BAB48 | H43: =+INDEX(Parametria!$V:$V,MATCH(Tabla_Consulta_desde_Reporte_de_Valorización_de_Instrumentos[[#This Row],[CODIGO_SBS]],Parametria!$B:$B,0)) -> BBVA Bancomer | I43: BBVASM 2039 | J43: 5278 | K43: 2 | L43: 1000 | M43: 48322572 | N43: 14377867 | O43: 12800 | P43: 50778 | Q43: 4756 | R43: 3.3609 | S43: RENTA FIJA | T43: 48303082 | U43: 14364802 | V43: GBBV | W43: 2808249000000 | X43: 2500434000000 | Y43: 307815000000 | Z43: 1.020707 | AA43: =+MID(Tabla_Consulta_desde_Reporte_de_Valorización_de_Instrumentos[[#This Row],[CODIGO_SBS]],7,1) -> 2 | AB43: =_xlfn.XLOOKUP(Tabla_Consulta_desde_Reporte_de_Valorización_de_Instrumentos[[#This Row],[CODIGO_SBS]],G_P!A:A,G_P!E:E) -> Renta Fija
B44: 31/12/2025 | C44: 15 | D44: IN-FONDO1 | E44: OSX | F44: 15527829AN67 | G44: USP16259AN67 | H44: =+INDEX(Parametria!$V:$V,MATCH(Tabla_Consulta_desde_Reporte_de_Valorización_de_Instrumentos[[#This Row],[CODIGO_SBS]],Parametria!$B:$B,0)) -> BBVA Bancomer | I44: BBVA 2034 | J44: 5278 | K44: 2 | L44: 1000 | M44: 16416058 | N44: 4884423.3 | O44: 4800 | P44: 49200 | Q44: 3178 | R44: 3.3609 | S44: RENTA FIJA | T44: 16381971 | U44: 4871816.7 | V44: GBBV | W44: 2808249000000 | X44: 2500434000000 | Y44: 307815000000 | Z44: 2.626388 | AA44: =+MID(Tabla_Consulta_desde_Reporte_de_Valorización_de_Instrumentos[[#This Row],[CODIGO_SBS]],7,1) -> 2 | AB44: =_xlfn.XLOOKUP(Tabla_Consulta_desde_Reporte_de_Valorización_de_Instrumentos[[#This Row],[CODIGO_SBS]],G_P!A:A,G_P!E:E) -> Renta Fija
B45: 31/12/2025 | C45: 15 | D45: IN-FONDO1 | E45: OSX | F45: 1552782BAA64 | G45: USP1S81BAA64 | H45: =+INDEX(Parametria!$V:$V,MATCH(Tabla_Consulta_desde_Reporte_de_Valorización_de_Instrumentos[[#This Row],[CODIGO_SBS]],Parametria!$B:$B,0)) -> BBVA Bancomer | I45: BBVASM 2038 | J45: 5278 | K45: 2 | L45: 1000 | M45: 30555199 | N45: 9091374.2 | O45: 8200 | P45: 50585 | Q45: 4563 | R45: 3.3609 | S45: RENTA FIJA | T45: 30559802 | U45: 9088146.6 | V45: GBBV | W45: 2808249000000 | X45: 2500434000000 | Y45: 307815000000 | Z45: 0.393611 | AA45: =+MID(Tabla_Consulta_desde_Reporte_de_Valorización_de_Instrumentos[[#This Row],[CODIGO_SBS]],7,1) -> 2 | AB45: =_xlfn.XLOOKUP(Tabla_Consulta_desde_Reporte_de_Valorización_de_Instrumentos[[#This Row],[CODIGO_SBS]],G_P!A:A,G_P!E:E) -> Renta Fija
B46: 31/12/2025 | C46: 15 | D46: IN-FONDO1 | E46: OSX | F46: 1552782GAA15 | G46: USP2000GAA15 | H46: =+INDEX(Parametria!$V:$V,MATCH(Tabla_Consulta_desde_Reporte_de_Valorización_de_Instrumentos[[#This Row],[CODIGO_SBS]],Parametria!$B:$B,0)) -> BBVA Bancomer | I46: BBVASM 2035 | J46: 5278 | K46: 2 | L46: 1000 | M46: 5456578.7 | N46: 1623546.9 | O46: 1500 | P46: 49351 | Q46: 3329 | R46: 3.3609 | S46: RENTA FIJA | T46: 5469811.8 | U46: 1626661.5 | V46: GBBV | W46: 2808249000000 | X46: 2500434000000 | Y46: 307815000000 | Z46: -2.076389 | AA46: =+MID(Tabla_Consulta_desde_Reporte_de_Valorización_de_Instrumentos[[#This Row],[CODIGO_SBS]],7,1) -> 2 | AB46: =_xlfn.XLOOKUP(Tabla_Consulta_desde_Reporte_de_Valorización_de_Instrumentos[[#This Row],[CODIGO_SBS]],G_P!A:A,G_P!E:E) -> Renta Fija
B47: 31/12/2025 | C47: 15 | D47: IN-FONDO2 | E47: OSX | F47: 15528725AC15 | G47: USG42045AC15 | H47: =+INDEX(Parametria!$V:$V,MATCH(Tabla_Consulta_desde_Reporte_de_Valorización_de_Instrumentos[[#This Row],[CODIGO_SBS]],Parametria!$B:$B,0)) -> Aval | I47: AVALCB 4 3/8 02 | J47: 5287 | K47: 2 | L47: 1000 | M47: 3807145.4 | N47: 1132775.6 | O47: 1184 | P47: 47518 | Q47: 1496 | R47: 3.3609 | S47: RENTA FIJA | T47: 3808533.4 | U47: 1132615.7 | V47: GAVA | W47: 316615576000000 | X47: 284936353000000 | Y47: 3.1679223e+13 | Z47: 0.135055 | AA47: =+MID(Tabla_Consulta_desde_Reporte_de_Valorización_de_Instrumentos[[#This Row],[CODIGO_SBS]],7,1) -> 2 | AB47: =_xlfn.XLOOKUP(Tabla_Consulta_desde_Reporte_de_Valorización_de_Instrumentos[[#This Row],[CODIGO_SBS]],G_P!A:A,G_P!E:E) -> Renta Fija
B48: 31/12/2025 | C48: 15 | D48: IN-FONDO2 | E48: OSX | F48: 15532427PD99 | G48: USP0R137PD99 | H48: =+INDEX(Parametria!$V:$V,MATCH(Tabla_Consulta_desde_Reporte_de_Valorización_de_Instrumentos[[#This Row],[CODIGO_SBS]],Parametria!$B:$B,0)) -> Banco Davivienda S.A. | I48: DAVIVI2035 | J48: 5324 | K48: 2 | L48: 1000 | M48: 24307961 | N48: 7232574.9 | O48: 6933 | P48: 48397 | Q48: 2375 | R48: 3.3609 | S48: RENTA FIJA | T48: 25268959 | U48: 7514708.6 | W48: 177149615000000 | X48: 161267686000000 | Y48: 15881929000000 | Z48: -40.694306 | AA48: =+MID(Tabla_Consulta_desde_Reporte_de_Valorización_de_Instrumentos[[#This Row],[CODIGO_SBS]],7,1) -> 2 | AB48: =_xlfn.XLOOKUP(Tabla_Consulta_desde_Reporte_de_Valorización_de_Instrumentos[[#This Row],[CODIGO_SBS]],G_P!A:A,G_P!E:E) -> Renta Fija
B49: 31/12/2025 | C49: 15 | D49: IN-FONDO1 | E49: OSX | F49: 15532427PD99 | G49: USP0R137PD99 | H49: =+INDEX(Parametria!$V:$V,MATCH(Tabla_Consulta_desde_Reporte_de_Valorización_de_Instrumentos[[#This Row],[CODIGO_SBS]],Parametria!$B:$B,0)) -> Banco Davivienda S.A. | I49: DAVIVI2035 | J49: 5324 | K49: 2 | L49: 1000 | M49: 41207481 | N49: 12260847 | O49: 11753 | P49: 48397 | Q49: 2375 | R49: 3.3609 | S49: RENTA FIJA | T49: 42836589 | U49: 12739127 | W49: 177149615000000 | X49: 161267686000000 | Y49: 15881929000000 | Z49: -40.694306 | AA49: =+MID(Tabla_Consulta_desde_Reporte_de_Valorización_de_Instrumentos[[#This Row],[CODIGO_SBS]],7,1) -> 2 | AB49: =_xlfn.XLOOKUP(Tabla_Consulta_desde_Reporte_de_Valorización_de_Instrumentos[[#This Row],[CODIGO_SBS]],G_P!A:A,G_P!E:E) -> Renta Fija
B50: 31/12/2025 | C50: 15 | D50: IN-FONDO1 | E50: OSX | F50: 15515123CH47 | G50: USP32133CH47 | H50: =+INDEX(Parametria!$V:$V,MATCH(Tabla_Consulta_desde_Reporte_de_Valorización_de_Instrumentos[[#This Row],[CODIGO_SBS]],Parametria!$B:$B,0)) -> Banco de Crédito e Inversiones | I50: BCICI 7 1/2 PE | J50: 5151 | K50: 2 | L50: 1000 | M50: 17937711 | N50: 5337175 | O50: 4920 | P50: 73121 | Q50: 27099 | R50: 3.3609 | S50: RENTA FIJA | T50: 17939891 | U50: 5335125 | W50: 0 | X50: 0 | Y50: 0 | Z50: 0.416667 | AA50: =+MID(Tabla_Consulta_desde_Reporte_de_Valorización_de_Instrumentos[[#This Row],[CODIGO_SBS]],7,1) -> 2 | AB50: =_xlfn.XLOOKUP(Tabla_Consulta_desde_Reporte_de_Valorización_de_Instrumentos[[#This Row],[CODIGO_SBS]],G_P!A:A,G_P!E:E) -> Renta Fija
B51: 31/12/2025 | C51: 15 | D51: IN-FONDO1 | E51: OSX | F51: 1551112LAN29 | G51: US05968LAN29 | H51: =+INDEX(Parametria!$V:$V,MATCH(Tabla_Consulta_desde_Reporte_de_Valorización_de_Instrumentos[[#This Row],[CODIGO_SBS]],Parametria!$B:$B,0)) -> Bancolombia | I51: BCOLO 2034 | J51: 5111 | K51: 2 | L51: 1000 | M51: 60957859 | N51: 18137362 | O51: 16900 | P51: 49302 | Q51: 3280 | R51: 3.3609 | S51: RENTA FIJA | T51: 60992718 | U51: 18138559 | W51: 338596669000000 | X51: 301098538000000 | Y51: 37498131000000 | Z51: -0.070833 | AA51: =+MID(Tabla_Consulta_desde_Reporte_de_Valorización_de_Instrumentos[[#This Row],[CODIGO_SBS]],7,1) -> 2 | AB51: =_xlfn.XLOOKUP(Tabla_Consulta_desde_Reporte_de_Valorización_de_Instrumentos[[#This Row],[CODIGO_SBS]],G_P!A:A,G_P!E:E) -> Renta Fija
B52: 31/12/2025 | C52: 15 | D52: IN-FONDO2 | E52: OSX | F52: 1551112LAN29 | G52: US05968LAN29 | H52: =+INDEX(Parametria!$V:$V,MATCH(Tabla_Consulta_desde_Reporte_de_Valorización_de_Instrumentos[[#This Row],[CODIGO_SBS]],Parametria!$B:$B,0)) -> Bancolombia | I52: BCOLO 2034 | J52: 5111 | K52: 2 | L52: 1000 | M52: 48614794 | N52: 14464814 | O52: 13478 | P52: 49302 | Q52: 3280 | R52: 3.3609 | S52: RENTA FIJA | T52: 48642595 | U52: 14465769 | W52: 338596669000000 | X52: 301098538000000 | Y52: 37498131000000 | Z52: -0.070833 | AA52: =+MID(Tabla_Consulta_desde_Reporte_de_Valorización_de_Instrumentos[[#This Row],[CODIGO_SBS]],7,1) -> 2 | AB52: =_xlfn.XLOOKUP(Tabla_Consulta_desde_Reporte_de_Valorización_de_Instrumentos[[#This Row],[CODIGO_SBS]],G_P!A:A,G_P!E:E) -> Renta Fija
B53: 31/12/2025 | C53: 18 | D53: IN-FONDO2 | E53: BNP | F53: 182096345816 | G53: XS0799645816 | H53: =+INDEX(Parametria!$V:$V,MATCH(Tabla_Consulta_desde_Reporte_de_Valorización_de_Instrumentos[[#This Row],[CODIGO_SBS]],Parametria!$B:$B,0)) -> Línea Amarilla | I53: IVPRB 6.45 06/3 | J53: 2096 | K53: 3 | L53: 1000 | M53: 2.4281781e+08 | N53: 2.4281781e+08 | O53: 212084 | P53: 50221 | Q53: 4199 | R53: 1 | S53: RENTA FIJA | T53: 2.4241488e+08 | U53: 2.4241488e+08 | W53: 4252869000 | X53: 3246804000 | Y53: 1006065000 | Z53: 1.899852 | AA53: =+MID(Tabla_Consulta_desde_Reporte_de_Valorización_de_Instrumentos[[#This Row],[CODIGO_SBS]],7,1) -> 3 | AB53: =_xlfn.XLOOKUP(Tabla_Consulta_desde_Reporte_de_Valorización_de_Instrumentos[[#This Row],[CODIGO_SBS]],G_P!A:A,G_P!E:E) -> #N/A
B54: 31/12/2025 | C54: 18 | D54: IN-FONDO1 | E54: BNP | F54: 182096345816 | G54: XS0799645816 | H54: =+INDEX(Parametria!$V:$V,MATCH(Tabla_Consulta_desde_Reporte_de_Valorización_de_Instrumentos[[#This Row],[CODIGO_SBS]],Parametria!$B:$B,0)) -> Línea Amarilla | I54: IVPRB 6.45 06/3 | J54: 2096 | K54: 3 | L54: 1000 | M54: 21246157 | N54: 21246157 | O54: 18557 | P54: 50221 | Q54: 4199 | R54: 1 | S54: RENTA FIJA | T54: 21210902 | U54: 21210902 | W54: 4252869000 | X54: 3246804000 | Y54: 1006065000 | Z54: 1.899852 | AA54: =+MID(Tabla_Consulta_desde_Reporte_de_Valorización_de_Instrumentos[[#This Row],[CODIGO_SBS]],7,1) -> 3 | AB54: =_xlfn.XLOOKUP(Tabla_Consulta_desde_Reporte_de_Valorización_de_Instrumentos[[#This Row],[CODIGO_SBS]],G_P!A:A,G_P!E:E) -> #N/A
B55: 31/12/2025 | C55: 21 | D55: IN-FONDO1 | E55: BSF | F55: 21003811902A | G55: PEP12100D292 | H55: =+INDEX(Parametria!$V:$V,MATCH(Tabla_Consulta_desde_Reporte_de_Valorización_de_Instrumentos[[#This Row],[CODIGO_SBS]],Parametria!$B:$B,0)) -> BIF | I55: BIF3BS2A | J55: 0038 | K55: 1 | L55: 1000 | M55: 20536162 | N55: 20536162 | O55: 20000 | P55: 47177 | Q55: 1155 | R55: 1 | S55: RENTA FIJA | T55: 20535736 | U55: 20535736 | V55: GFIE | W55: 22149047000 | X55: 20355021000 | Y55: 1794026000 | Z55: 0.0212816 | AA55: =+MID(Tabla_Consulta_desde_Reporte_de_Valorización_de_Instrumentos[[#This Row],[CODIGO_SBS]],7,1) -> 1 | AB55: =_xlfn.XLOOKUP(Tabla_Consulta_desde_Reporte_de_Valorización_de_Instrumentos[[#This Row],[CODIGO_SBS]],G_P!A:A,G_P!E:E) -> Renta Fija
B56: 31/12/2025 | C56: 21 | D56: IN-FONDO2 | E56: BSF | F56: 21003811902A | G56: PEP12100D292 | H56: =+INDEX(Parametria!$V:$V,MATCH(Tabla_Consulta_desde_Reporte_de_Valorización_de_Instrumentos[[#This Row],[CODIGO_SBS]],Parametria!$B:$B,0)) -> BIF | I56: BIF3BS2A | J56: 0038 | K56: 1 | L56: 1000 | M56: 5134040.5 | N56: 5134040.5 | O56: 5000 | P56: 47177 | Q56: 1155 | R56: 1 | S56: RENTA FIJA | T56: 5133934 | U56: 5133934 | V56: GFIE | W56: 22149047000 | X56: 20355021000 | Y56: 1794026000 | Z56: 0.0212816 | AA56: =+MID(Tabla_Consulta_desde_Reporte_de_Valorización_de_Instrumentos[[#This Row],[CODIGO_SBS]],7,1) -> 1 | AB56: =_xlfn.XLOOKUP(Tabla_Consulta_desde_Reporte_de_Valorización_de_Instrumentos[[#This Row],[CODIGO_SBS]],G_P!A:A,G_P!E:E) -> Renta Fija
B57: 31/12/2025 | C57: 21 | D57: IN-FONDO2 | E57: BSF | F57: 21001811601A | G57: PEP12030D010 | H57: =+INDEX(Parametria!$V:$V,MATCH(Tabla_Consulta_desde_Reporte_de_Valorización_de_Instrumentos[[#This Row],[CODIGO_SBS]],Parametria!$B:$B,0)) -> Banco de la Nación | I57: BN1BS1A | J57: 0018 | K57: 1 | L57: 1000 | M57: 5479726.5 | N57: 5479726.5 | O57: 5176 | P57: 48182 | Q57: 2160 | R57: 1 | S57: RENTA FIJA | T57: 5482093.3 | U57: 5482093.3 | W57: 47334882000 | X57: 43945418000 | Y57: 3389464000 | Z57: -0.4572594 | AA57: =+MID(Tabla_Consulta_desde_Reporte_de_Valorización_de_Instrumentos[[#This Row],[CODIGO_SBS]],7,1) -> 1 | AB57: =_xlfn.XLOOKUP(Tabla_Consulta_desde_Reporte_de_Valorización_de_Instrumentos[[#This Row],[CODIGO_SBS]],G_P!A:A,G_P!E:E) -> Renta Fija
B58: 31/12/2025 | C58: 21 | D58: IN-FONDO2 | E58: BSF | F58: 2100022V2J35 | G58: US05971V2J35 | H58: =+INDEX(Parametria!$V:$V,MATCH(Tabla_Consulta_desde_Reporte_de_Valorización_de_Instrumentos[[#This Row],[CODIGO_SBS]],Parametria!$B:$B,0)) -> Banco de Crédito del Perú | I58: BCP2035 | J58: 0002 | K58: 2 | L58: 1000 | M58: 26964501 | N58: 8023000 | O58: 7500 | P58: 49520 | Q58: 3498 | R58: 3.3609 | S58: RENTA FIJA | T58: 26969103 | U58: 8020312.5 | V58: CCOR | W58: 187469765000 | X58: 164938084000 | Y58: 22531681000 | Z58: 0.358333 | AA58: =+MID(Tabla_Consulta_desde_Reporte_de_Valorización_de_Instrumentos[[#This Row],[CODIGO_SBS]],7,1) -> 2 | AB58: =_xlfn.XLOOKUP(Tabla_Consulta_desde_Reporte_de_Valorización_de_Instrumentos[[#This Row],[CODIGO_SBS]],G_P!A:A,G_P!E:E) -> Renta Fija
B59: 31/12/2025 | C59: 21 | D59: IN-FONDO2 | E59: BSF | F59: 2100022V2H78 | G59: US05971V2H78 | H59: =+INDEX(Parametria!$V:$V,MATCH(Tabla_Consulta_desde_Reporte_de_Valorización_de_Instrumentos[[#This Row],[CODIGO_SBS]],Parametria!$B:$B,0)) -> Banco de Crédito del Perú | I59: BCP 5.8 03/10/2 | J59: 0002 | K59: 2 | L59: 1000 | M59: 1.0032226e+08 | N59: 29849819 | O59: 28895 | P59: 49378 | Q59: 3356 | R59: 3.3609 | S59: RENTA FIJA | T59: 1.0034169e+08 | U59: 29840509 | V59: CCOR | W59: 187469765000 | X59: 164938084000 | Y59: 22531681000 | Z59: 0.322222 | AA59: =+MID(Tabla_Consulta_desde_Reporte_de_Valorización_de_Instrumentos[[#This Row],[CODIGO_SBS]],7,1) -> 2 | AB59: =_xlfn.XLOOKUP(Tabla_Consulta_desde_Reporte_de_Valorización_de_Instrumentos[[#This Row],[CODIGO_SBS]],G_P!A:A,G_P!E:E) -> Renta Fija
B60: 31/12/2025 | C60: 21 | D60: IN-FONDO1 | E60: BSF | F60: 2100022V2H78 | G60: US05971V2H78 | H60: =+INDEX(Parametria!$V:$V,MATCH(Tabla_Consulta_desde_Reporte_de_Valorización_de_Instrumentos[[#This Row],[CODIGO_SBS]],Parametria!$B:$B,0)) -> Banco de Crédito del Perú | I60: BCP 5.8 03/10/2 | J60: 0002 | K60: 2 | L60: 1000 | M60: 50270495 | N60: 14957451 | O60: 14479 | P60: 49378 | Q60: 3356 | R60: 3.3609 | S60: RENTA FIJA | T60: 50280235 | U60: 14952785 | V60: CCOR | W60: 187469765000 | X60: 164938084000 | Y60: 22531681000 | Z60: 0.322222 | AA60: =+MID(Tabla_Consulta_desde_Reporte_de_Valorización_de_Instrumentos[[#This Row],[CODIGO_SBS]],7,1) -> 2 | AB60: =_xlfn.XLOOKUP(Tabla_Consulta_desde_Reporte_de_Valorización_de_Instrumentos[[#This Row],[CODIGO_SBS]],G_P!A:A,G_P!E:E) -> Renta Fija
B61: 31/12/2025 | C61: 21 | D61: IN-FONDO1 | E61: BSF | F61: 2100022V2J35 | G61: US05971V2J35 | H61: =+INDEX(Parametria!$V:$V,MATCH(Tabla_Consulta_desde_Reporte_de_Valorización_de_Instrumentos[[#This Row],[CODIGO_SBS]],Parametria!$B:$B,0)) -> Banco de Crédito del Perú | I61: BCP2035 | J61: 0002 | K61: 2 | L61: 1000 | M61: 6913698 | N61: 2057097.2 | O61: 1923 | P61: 49520 | Q61: 3498 | R61: 3.3609 | S61: RENTA FIJA | T61: 6914878 | U61: 2056408.1 | V61: CCOR | W61: 187469765000 | X61: 164938084000 | Y61: 22531681000 | Z61: 0.358333 | AA61: =+MID(Tabla_Consulta_desde_Reporte_de_Valorización_de_Instrumentos[[#This Row],[CODIGO_SBS]],7,1) -> 2 | AB61: =_xlfn.XLOOKUP(Tabla_Consulta_desde_Reporte_de_Valorización_de_Instrumentos[[#This Row],[CODIGO_SBS]],G_P!A:A,G_P!E:E) -> Renta Fija
B62: 31/12/2025 | C62: 21 | D62: IN-FONDO1 | E62: BSF | F62: 21000325AG03 | G62: USP13435AG03 | H62: =+INDEX(Parametria!$V:$V,MATCH(Tabla_Consulta_desde_Reporte_de_Valorización_de_Instrumentos[[#This Row],[CODIGO_SBS]],Parametria!$B:$B,0)) -> Interbank | I62: BINTPE 6.397 04 | J62: 0003 | K62: 2 | L62: 1000 | M62: 32575042 | N62: 9692356.9 | O62: 9200 | P62: 49429 | Q62: 3407 | R62: 3.3609 | S62: RENTA FIJA | T62: 32503185 | U62: 9666087.3 | V62: GITC | W62: 71698610000 | X62: 64045988000 | Y62: 7652622000 | Z62: 2.855389 | AA62: =+MID(Tabla_Consulta_desde_Reporte_de_Valorización_de_Instrumentos[[#This Row],[CODIGO_SBS]],7,1) -> 2 | AB62: =_xlfn.XLOOKUP(Tabla_Consulta_desde_Reporte_de_Valorización_de_Instrumentos[[#This Row],[CODIGO_SBS]],G_P!A:A,G_P!E:E) -> Renta Fija
B63: 31/12/2025 | C63: 21 | D63: IN-FONDO2 | E63: BSF | F63: 21000325AG03 | G63: USP13435AG03 | H63: =+INDEX(Parametria!$V:$V,MATCH(Tabla_Consulta_desde_Reporte_de_Valorización_de_Instrumentos[[#This Row],[CODIGO_SBS]],Parametria!$B:$B,0)) -> Interbank | I63: BINTPE 6.397 04 | J63: 0003 | K63: 2 | L63: 1000 | M63: 78590830 | N63: 23383865 | O63: 22196 | P63: 49429 | Q63: 3407 | R63: 3.3609 | S63: RENTA FIJA | T63: 78417467 | U63: 23320486 | V63: GITC | W63: 71698610000 | X63: 64045988000 | Y63: 7652622000 | Z63: 2.855389 | AA63: =+MID(Tabla_Consulta_desde_Reporte_de_Valorización_de_Instrumentos[[#This Row],[CODIGO_SBS]],7,1) -> 2 | AB63: =_xlfn.XLOOKUP(Tabla_Consulta_desde_Reporte_de_Valorización_de_Instrumentos[[#This Row],[CODIGO_SBS]],G_P!A:A,G_P!E:E) -> Renta Fija
B64: 31/12/2025 | C64: 22 | D64: IN-FONDO2 | E64: BEP | F64: 22211619AA48 | G64: USP82169AA48 | H64: =+INDEX(Parametria!$V:$V,MATCH(Tabla_Consulta_desde_Reporte_de_Valorización_de_Instrumentos[[#This Row],[CODIGO_SBS]],Parametria!$B:$B,0)) -> Rutas de Lima | I64: RUTLI 2036 | J64: 2116 | K64: 1 | L64: 1000 | M64: 64445851 | N64: 64445851 | O64: 222932 | P64: 49856 | Q64: 3834 | R64: 1 | S64: RENTA FIJA | T64: 66842370 | U64: 66842370 | W64: 2816710241 | X64: 1846667545 | Y64: 970042696 | Z64: -10.75 | AA64: =+MID(Tabla_Consulta_desde_Reporte_de_Valorización_de_Instrumentos[[#This Row],[CODIGO_SBS]],7,1) -> 1 | AB64: =_xlfn.XLOOKUP(Tabla_Consulta_desde_Reporte_de_Valorización_de_Instrumentos[[#This Row],[CODIGO_SBS]],G_P!A:A,G_P!E:E) -> Renta Fija
B65: 31/12/2025 | C65: 22 | D65: IN-FONDO1 | E65: BEP | F65: 22211619AA48 | G65: USP82169AA48 | H65: =+INDEX(Parametria!$V:$V,MATCH(Tabla_Consulta_desde_Reporte_de_Valorización_de_Instrumentos[[#This Row],[CODIGO_SBS]],Parametria!$B:$B,0)) -> Rutas de Lima | I65: RUTLI 2036 | J65: 2116 | K65: 1 | L65: 1000 | M65: 16219869 | N65: 16219869 | O65: 56108 | P65: 49856 | Q65: 3834 | R65: 1 | S65: RENTA FIJA | T65: 16823030 | U65: 16823030 | W65: 2816710241 | X65: 1846667545 | Y65: 970042696 | Z65: -10.75 | AA65: =+MID(Tabla_Consulta_desde_Reporte_de_Valorización_de_Instrumentos[[#This Row],[CODIGO_SBS]],7,1) -> 1 | AB65: =_xlfn.XLOOKUP(Tabla_Consulta_desde_Reporte_de_Valorización_de_Instrumentos[[#This Row],[CODIGO_SBS]],G_P!A:A,G_P!E:E) -> Renta Fija
B66: 31/12/2025 | C66: 22 | D66: IN-FONDO1 | E66: BEP | F66: 22212511603A | G66: PEP71320M030 | H66: =+INDEX(Parametria!$V:$V,MATCH(Tabla_Consulta_desde_Reporte_de_Valorización_de_Instrumentos[[#This Row],[CODIGO_SBS]],Parametria!$B:$B,0)) -> Jockey Plaza | I66: JPLAZ1BC3A | J66: 2125 | K66: 1 | L66: 1000 | M66: 16444915 | N66: 16444915 | O66: 15000 | P66: 48051 | Q66: 2029 | R66: 1 | S66: RENTA FIJA | T66: 16439629 | U66: 16439629 | V66: GACU | W66: 1960115000 | X66: 1305903000 | Y66: 654212000 | Z66: 0.3524507 | AA66: =+MID(Tabla_Consulta_desde_Reporte_de_Valorización_de_Instrumentos[[#This Row],[CODIGO_SBS]],7,1) -> 1 | AB66: =_xlfn.XLOOKUP(Tabla_Consulta_desde_Reporte_de_Valorización_de_Instrumentos[[#This Row],[CODIGO_SBS]],G_P!A:A,G_P!E:E) -> Renta Fija
B67: 31/12/2025 | C67: 22 | D67: IN-FONDO1 | E67: BEP | F67: 22212521501A | G67: PEP71320M014 | H67: =+INDEX(Parametria!$V:$V,MATCH(Tabla_Consulta_desde_Reporte_de_Valorización_de_Instrumentos[[#This Row],[CODIGO_SBS]],Parametria!$B:$B,0)) -> Jockey Plaza | I67: JPLAZ1BC1A | J67: 2125 | K67: 2 | L67: 1000 | M67: 10015025 | N67: 2979864.1 | O67: 2893 | P67: 47839 | Q67: 1817 | R67: 3.3609 | S67: RENTA FIJA | T67: 10013982 | U67: 2978047.4 | V67: GACU | W67: 1960115000 | X67: 1305903000 | Y67: 654212000 | Z67: 0.6279485 | AA67: =+MID(Tabla_Consulta_desde_Reporte_de_Valorización_de_Instrumentos[[#This Row],[CODIGO_SBS]],7,1) -> 2 | AB67: =_xlfn.XLOOKUP(Tabla_Consulta_desde_Reporte_de_Valorización_de_Instrumentos[[#This Row],[CODIGO_SBS]],G_P!A:A,G_P!E:E) -> Renta Fija
B68: 31/12/2025 | C68: 22 | D68: IN-FONDO2 | E68: BEP | F68: 22212511603A | G68: PEP71320M030 | H68: =+INDEX(Parametria!$V:$V,MATCH(Tabla_Consulta_desde_Reporte_de_Valorización_de_Instrumentos[[#This Row],[CODIGO_SBS]],Parametria!$B:$B,0)) -> Jockey Plaza | I68: JPLAZ1BC3A | J68: 2125 | K68: 1 | L68: 1000 | M68: 30697175 | N68: 30697175 | O68: 28000 | P68: 48051 | Q68: 2029 | R68: 1 | S68: RENTA FIJA | T68: 30687307 | U68: 30687307 | V68: GACU | W68: 1960115000 | X68: 1305903000 | Y68: 654212000 | Z68: 0.3524507 | AA68: =+MID(Tabla_Consulta_desde_Reporte_de_Valorización_de_Instrumentos[[#This Row],[CODIGO_SBS]],7,1) -> 1 | AB68: =_xlfn.XLOOKUP(Tabla_Consulta_desde_Reporte_de_Valorización_de_Instrumentos[[#This Row],[CODIGO_SBS]],G_P!A:A,G_P!E:E) -> Renta Fija
B69: 31/12/2025 | C69: 22 | D69: IN-FONDO2 | E69: BEP | F69: 22582511603A | G69: PEP73125M031 | H69: =+INDEX(Parametria!$V:$V,MATCH(Tabla_Consulta_desde_Reporte_de_Valorización_de_Instrumentos[[#This Row],[CODIGO_SBS]],Parametria!$B:$B,0)) -> Primax | I69: PRIMX1BC3A | J69: 5825 | K69: 1 | L69: 1000 | M69: 19793767 | N69: 19793767 | O69: 17486 | P69: 49955 | Q69: 3933 | R69: 1 | S69: RENTA FIJA | T69: 19756725 | U69: 19756725 | V69: CCOR | W69: 5024202000 | X69: 4179076000 | Y69: 845126000 | Z69: 2.1183804 | AA69: =+MID(Tabla_Consulta_desde_Reporte_de_Valorización_de_Instrumentos[[#This Row],[CODIGO_SBS]],7,1) -> 1 | AB69: =_xlfn.XLOOKUP(Tabla_Consulta_desde_Reporte_de_Valorización_de_Instrumentos[[#This Row],[CODIGO_SBS]],G_P!A:A,G_P!E:E) -> Renta Fija
B70: 31/12/2025 | C70: 22 | D70: IN-FONDO2 | E70: BEP | F70: 22582511801A | G70: PEP73125M049 | H70: =+INDEX(Parametria!$V:$V,MATCH(Tabla_Consulta_desde_Reporte_de_Valorización_de_Instrumentos[[#This Row],[CODIGO_SBS]],Parametria!$B:$B,0)) -> Primax | I70: PRIMX2BC1A | J70: 5825 | K70: 1 | L70: 10000 | M70: 11228744 | N70: 11228744 | O70: 1037 | P70: 46957 | Q70: 935 | R70: 1 | S70: RENTA FIJA | T70: 11231176 | U70: 11231176 | V70: CCOR | W70: 5024202000 | X70: 4179076000 | Y70: 845126000 | Z70: -2.3456718 | AA70: =+MID(Tabla_Consulta_desde_Reporte_de_Valorización_de_Instrumentos[[#This Row],[CODIGO_SBS]],7,1) -> 1 | AB70: =_xlfn.XLOOKUP(Tabla_Consulta_desde_Reporte_de_Valorización_de_Instrumentos[[#This Row],[CODIGO_SBS]],G_P!A:A,G_P!E:E) -> Renta Fija
B71: 31/12/2025 | C71: 22 | D71: IN-FONDO1 | E71: BEP | F71: 22582511801A | G71: PEP73125M049 | H71: =+INDEX(Parametria!$V:$V,MATCH(Tabla_Consulta_desde_Reporte_de_Valorización_de_Instrumentos[[#This Row],[CODIGO_SBS]],Parametria!$B:$B,0)) -> Primax | I71: PRIMX2BC1A | J71: 5825 | K71: 1 | L71: 10000 | M71: 6323612.7 | N71: 6323612.7 | O71: 584 | P71: 46957 | Q71: 935 | R71: 1 | S71: RENTA FIJA | T71: 6324982.6 | U71: 6324982.6 | V71: CCOR | W71: 5024202000 | X71: 4179076000 | Y71: 845126000 | Z71: -2.3456718 | AA71: =+MID(Tabla_Consulta_desde_Reporte_de_Valorización_de_Instrumentos[[#This Row],[CODIGO_SBS]],7,1) -> 1 | AB71: =_xlfn.XLOOKUP(Tabla_Consulta_desde_Reporte_de_Valorización_de_Instrumentos[[#This Row],[CODIGO_SBS]],G_P!A:A,G_P!E:E) -> Renta Fija
B72: 31/12/2025 | C72: 22 | D72: IN-FONDO1 | E72: BEP | F72: 22582511802A | G72: PEP73125M056 | H72: =+INDEX(Parametria!$V:$V,MATCH(Tabla_Consulta_desde_Reporte_de_Valorización_de_Instrumentos[[#This Row],[CODIGO_SBS]],Parametria!$B:$B,0)) -> Primax | I72: PRIMX2BC2A | J72: 5825 | K72: 1 | L72: 10000 | M72: 7682536.7 | N72: 7682536.7 | O72: 700 | P72: 50609 | Q72: 4587 | R72: 1 | S72: RENTA FIJA | T72: 7684712.4 | U72: 7684712.4 | V72: CCOR | W72: 5024202000 | X72: 4179076000 | Y72: 845126000 | Z72: -3.1082553 | AA72: =+MID(Tabla_Consulta_desde_Reporte_de_Valorización_de_Instrumentos[[#This Row],[CODIGO_SBS]],7,1) -> 1 | AB72: =_xlfn.XLOOKUP(Tabla_Consulta_desde_Reporte_de_Valorización_de_Instrumentos[[#This Row],[CODIGO_SBS]],G_P!A:A,G_P!E:E) -> Renta Fija
B73: 31/12/2025 | C73: 22 | D73: IN-FONDO1 | E73: BEP | F73: 22582511603A | G73: PEP73125M031 | H73: =+INDEX(Parametria!$V:$V,MATCH(Tabla_Consulta_desde_Reporte_de_Valorización_de_Instrumentos[[#This Row],[CODIGO_SBS]],Parametria!$B:$B,0)) -> Primax | I73: PRIMX1BC3A | J73: 5825 | K73: 1 | L73: 1000 | M73: 6225878.9 | N73: 6225878.9 | O73: 5500 | P73: 49955 | Q73: 3933 | R73: 1 | S73: RENTA FIJA | T73: 6214227.8 | U73: 6214227.8 | V73: CCOR | W73: 5024202000 | X73: 4179076000 | Y73: 845126000 | Z73: 2.1183804 | AA73: =+MID(Tabla_Consulta_desde_Reporte_de_Valorización_de_Instrumentos[[#This Row],[CODIGO_SBS]],7,1) -> 1 | AB73: =_xlfn.XLOOKUP(Tabla_Consulta_desde_Reporte_de_Valorización_de_Instrumentos[[#This Row],[CODIGO_SBS]],G_P!A:A,G_P!E:E) -> Renta Fija
B74: 31/12/2025 | C74: 22 | D74: IN-FONDO1 | E74: BEP | F74: 22582811701A | G74: PEP73668M014 | H74: =+INDEX(Parametria!$V:$V,MATCH(Tabla_Consulta_desde_Reporte_de_Valorización_de_Instrumentos[[#This Row],[CODIGO_SBS]],Parametria!$B:$B,0)) -> Hermes | I74: HERME1BC1A | J74: 5828 | K74: 1 | L74: 1000 | M74: 6957636.3 | N74: 6957636.3 | O74: 12749 | P74: 47545 | Q74: 1523 | R74: 1 | S74: RENTA FIJA | T74: 6957489.8 | U74: 6957489.8 | W74: 1625198000 | X74: 791660000 | Y74: 833538000 | Z74: 0.0114911 | AA74: =+MID(Tabla_Consulta_desde_Reporte_de_Valorización_de_Instrumentos[[#This Row],[CODIGO_SBS]],7,1) -> 1 | AB74: =_xlfn.XLOOKUP(Tabla_Consulta_desde_Reporte_de_Valorización_de_Instrumentos[[#This Row],[CODIGO_SBS]],G_P!A:A,G_P!E:E) -> Renta Fija
