Workbook
Name IQ_CH: 110000
Name IQ_CQ: 5000
Name IQ_CY: 10000
Name IQ_DAILY: 500000
Name IQ_FH: 100000
Name IQ_FQ: 500
Name IQ_FY: 1000
Name IQ_LTM: 2000
Name IQ_MONTH: 15000
Name IQ_NTM: 6000
Name IQ_WEEK: 50000
Name IQ_YTD: 3000
Name repCO2: '[1]Manual Ant'!#REF!

Sheet ANALISIS BD
A1: Cod. OriginadorBU | B1: SBS | C1: ISIN | D1: Weight | E1: Fondo | F1: assetclass | G1: Strategy | H1: Afp | I1: AUM | J1: Tipo | K1: Q | L1: Nombre | M1: Fecha | N1: codEmisor | O1: Precio | P1: Inversión | Q1: Sector | R1: País | S1: ISSUER_CNTRY_DOMICILE | T1: IVA_INDUSTRY | U1: RATING | V1: IVA_RATING_TREND | W1: E | X1: S | Y1: G | Z1: EW | AA1: SW | AB1: GW | AC1: CONTROVERSIES | AD1: CO2 Tn | AE1: CO2/Sales | AF1: CARBON_EMISSIONS_SCORE | AG1: CARBON_EMISSIONS_EXP_SCORE | AH1: CORP_GOVERNANCE_SCORE | AI1: FUND_ESG_COVERAGE | AJ1: FUND_ESG_LEADERS_PCT | AK1: FUND_ESG_AVERAGE_PCT | AL1: FUND_ESG_LAGGARDS_PCT | AM1: FUND_ESG_QUALITY_SCORE | AN1: FUND_CARBON_SCOPE_12_INTEN_3Y_TREND_M_IMPROV | AO1: FUND_CARBON_SCOPE_12_INTEN_3Y_TREND_M_WORSE | AP1: GOVERNANCE_PILLAR_QUARTILE | AQ1: GOVERNANCE_PCTL_GLOBAL | AR1: INDUSTRY_ADJUSTED_SCORE | AS1: CO2/EVIC | AT1: FUND_ESG_QUALITY_SCORE_PCTL_GLOBAL | AU1: FUND_GOV_GLOBAL_LEADERS_PCT | AV1: FUND_GOV_GLOBAL_AVERAGE_PCT | AW1: FUND_GOV_GLOBAL_LAGGARDS_PCT | AX1: FUND_FINANCED_CARBON_EMISSIONS | AY1: ITR | AZ1: Cobertura | BA1: Weight_Ingresado | BB1: Weight_Cubierto | BC1: Weight_N | BD1: trend*Wn | BE1: E*Wn | BF1: S*Wn | BG1: G*Wn | BH1: ESG*Wn | BI1: Controversia*Wn | BJ1: CO2/Sales*Wn | BK1: CO2/EVIC*Wn | BL1: CO2*Wn | BM1: Gov*Wn
B2: 12535622BA92 | C2: USP58072BA92 | D2: 0.0013603332 | E2: Multifondos | F2: RFIC | G2: BU | H2: Ex_Integra | I2: 7.7424621e+10 | J2: 3.4075 | K2: 31330 | M2: 46174 | N2: 5356 | O2: 986.57053 | P2: 1.0532329e+08 | AI2: rt | AJ2: rt | AK2: rt | AL2: rt | AM2: rt | AN2: rt | AO2: rt | AT2: rt | AU2: rt | AV2: rt | AW2: rt | AX2: rt | AZ2: NoCov | BA2: 0.62163188 | BB2: 0.14542962 | BC2: 0.0093538937
B3: 15515123CH47 | C3: USP32133CH47 | D3: 0.0012602963 | E3: F1 | F3: RFIC | G3: BU | H3: Ex_Integra | I3: 1.3660104e+10 | J3: 3.4075 | K3: 4675.0074 | M3: 46174 | N3: 5151 | O3: 1080.7083 | P3: 17215779 | AI3: rt | AJ3: rt | AK3: rt | AL3: rt | AM3: rt | AN3: rt | AO3: rt | AT3: rt | AU3: rt | AV3: rt | AW3: rt | AX3: rt | AZ3: NoCov | BA3: 0.57964491 | BB3: 0.30151641 | BC3: 0.0041798599
B4: 2100022V2H78 | C4: US05971V2H78 | D4: 0.00084844162 | E4: Multifondos | F4: RFLC | G4: BU | H4: Habitat | I4: 2.2785495e+10 | J4: 3.4075 | K4: 5532.97 | M4: 46174 | N4: 0002 | O4: 1025.3833 | P4: 19332162 | AI4: rt | AJ4: rt | AK4: rt | AL4: rt | AM4: rt | AN4: rt | AO4: rt | AT4: rt | AU4: rt | AV4: rt | AW4: rt | AX4: rt | AZ4: NoCov | BA4: 0.65823103 | BB4: 0.11726488 | BC4: 0.0072352577
A5: 509401 | B5: 59509428AJ82 | C5: US279158AJ82 | D5: 0.00096096238 | E5: F1 | F5: RFIC | G5: BU | H5: Habitat | I5: 1.8939189e+09 | J5: 3.4075 | K5: 644.13118 | L5: Ecopetrol S.A. | M5: 46174 | N5: 5094 | O5: 829.19671 | P5: 1819984.8 | Q5: Energy | R5: Colombia | S5: CO | T5: Integrated Oil & Gas | U5: A | V5: 1 | W5: 4.9145451 | X5: 8.1681979 | Y5: 4.609375 | Z5: 41 | AA5: 26 | AB5: 33 | AC5: 4 | AD5: 12677105 | AE5: 418.89 | AF5: 5.9190111 | AG5: 7.4017041 | AH5: 5.9 | AI5: rt | AJ5: rt | AK5: rt | AL5: rt | AM5: rt | AN5: rt | AO5: rt | AP5: 2 | AQ5: 39 | AR5: 6.51 | AS5: 226.35 | AT5: rt | AU5: rt | AV5: rt | AW5: rt | AX5: rt | AY5: Strongly Misaligned | AZ5: Cov | BA5: 0.63778762 | BB5: 0.36085898 | BC5: 0.0026629859 | BD5: 0.0026629859 | BE5: 0.013087364 | BF5: 0.021751796 | BG5: 0.0122747 | BH5: 0.017336038 | BI5: 0.010651943 | BJ5: 1.1154982 | BK5: 0.60276685 | BL5: 33758.951 | BM5: 0.0053259717
B6: 1254342KAB22 | C6: USP4R21KAB22 | D6: 0.0023538246 | E6: Multifondos | F6: RFIC | G6: BU | H6: Ex_Integra | I6: 7.7424621e+10 | J6: 3.4075 | K6: 47705 | M6: 46174 | N6: 5434 | O6: 1121.1234 | P6: 1.8224398e+08 | AI6: rt | AJ6: rt | AK6: rt | AL6: rt | AM6: rt | AN6: rt | AO6: rt | AT6: rt | AU6: rt | AV6: rt | AW6: rt | AX6: rt | AZ6: NoCov | BA6: 0.62163188 | BB6: 0.14542962 | BC6: 0.016185317
B7: 12535622BA92 | C7: USP58072BA92 | D7: 0.0032170875 | E7: Multifondos | F7: RFIC | G7: BU | H7: Prima | I7: 3.2738708e+10 | J7: 3.4075 | K7: 31330 | M7: 46174 | N7: 5356 | O7: 986.57053 | P7: 1.0532329e+08 | AI7: rt | AJ7: rt | AK7: rt | AL7: rt | AM7: rt | AN7: rt | AO7: rt | AT7: rt | AU7: rt | AV7: rt | AW7: rt | AX7: rt | AZ7: NoCov | BA7: 0.62127201 | BB7: 0.1558531 | BC7: 0.020641794
B8: 1551192MAD04 | C8: USP1400MAD04 | D8: 0.0024271404 | E8: Multifondos | F8: RFIC | G8: BU | H8: Profuturo | I8: 2.1900418e+10 | J8: 3.4075 | K8: 15093.95 | M8: 46174 | N8: 5119 | O8: 1033.4953 | P8: 53155388 | AI8: rt | AJ8: rt | AK8: rt | AL8: rt | AM8: rt | AN8: rt | AO8: rt | AT8: rt | AU8: rt | AV8: rt | AW8: rt | AX8: rt | AZ8: NoCov | BA8: 0.58409167 | BB8: 0.15915074 | BC8: 0.015250576
B9: 1551112LAN29 | C9: US05968LAN29 | D9: 0.00034459576 | E9: Multifondos | F9: RFIC | G9: BU | H9: Ex_Integra | I9: 7.7424621e+10 | J9: 3.4075 | K9: 7319 | M9: 46174 | N9: 5111 | O9: 1069.7971 | P9: 26680196 | AI9: rt | AJ9: rt | AK9: rt | AL9: rt | AM9: rt | AN9: rt | AO9: rt | AT9: rt | AU9: rt | AV9: rt | AW9: rt | AX9: rt | AZ9: NoCov | BA9: 0.62163188 | BB9: 0.14542962 | BC9: 0.0023695019
B10: 15515123CH47 | C10: USP32133CH47 | D10: 0.00354492 | E10: F1 | F10: RFIC | G10: BU | H10: Profuturo | I10: 4.856457e+09 | J10: 3.4075 | K10: 4675 | M10: 46174 | N10: 5151 | O10: 1080.7083 | P10: 17215751 | AI10: rt | AJ10: rt | AK10: rt | AL10: rt | AM10: rt | AN10: rt | AO10: rt | AT10: rt | AU10: rt | AV10: rt | AW10: rt | AX10: rt | AZ10: NoCov | BA10: 0.58036121 | BB10: 0.33866066 | BC10: 0.010467469
B11: 1551512PAC05 | C11: US05890PAC05 | D11: 0.0038776307 | E11: F1 | F11: RFIC | G11: BU | H11: Ex_Integra | I11: 1.3660104e+10 | J11: 3.4075 | K11: 14039 | M11: 46174 | N11: 5151 | O11: 1107.2569 | P11: 52968839 | AI11: rt | AJ11: rt | AK11: rt | AL11: rt | AM11: rt | AN11: rt | AO11: rt | AT11: rt | AU11: rt | AV11: rt | AW11: rt | AX11: rt | AZ11: NoCov | BA11: 0.57964491 | BB11: 0.30151641 | BC11: 0.01286043
B12: 15515123CH47 | C12: USP32133CH47 | D12: 3.9640842e-09 | E12: F1 | F12: RFIC | G12: BU | H12: Prima | I12: 6.909728e+09 | J12: 3.4075 | K12: 0.0074380562 | M12: 46174 | N12: 5151 | O12: 1080.7083 | P12: 27.390743 | AI12: rt | AJ12: rt | AK12: rt | AL12: rt | AM12: rt | AN12: rt | AO12: rt | AT12: rt | AU12: rt | AV12: rt | AW12: rt | AX12: rt | AZ12: NoCov | BA12: 0.56320494 | BB12: 0.28214925 | BC12: 1.40496e-08
B13: 2100022V2J35 | C13: US05971V2J35 | D13: 0.00092579384 | E13: Multifondos | F13: RFLC | G13: BU | H13: Habitat | I13: 2.2785495e+10 | J13: 3.4075 | K13: 5839.83 | M13: 46174 | N13: 0002 | O13: 1060.0752 | P13: 21094671 | AI13: rt | AJ13: rt | AK13: rt | AL13: rt | AM13: rt | AN13: rt | AO13: rt | AT13: rt | AU13: rt | AV13: rt | AW13: rt | AX13: rt | AZ13: NoCov | BA13: 0.65823103 | BB13: 0.11726488 | BC13: 0.0078948945
B14: 1551192MAD04 | C14: USP1400MAD04 | D14: 0.0028494034 | E14: Multifondos | F14: RFIC | G14: BU | H14: Ex_Integra | I14: 7.7424621e+10 | J14: 3.4075 | K14: 62645.32 | M14: 46174 | N14: 5119 | O14: 1033.4953 | P14: 2.2061397e+08 | AI14: rt | AJ14: rt | AK14: rt | AL14: rt | AM14: rt | AN14: rt | AO14: rt | AT14: rt | AU14: rt | AV14: rt | AW14: rt | AX14: rt | AZ14: NoCov | BA14: 0.62163188 | BB14: 0.14542962 | BC14: 0.019593005
B15: 15515123CH47 | C15: USP32133CH47 | D15: 0.00022235535 | E15: Multifondos | F15: RFIC | G15: BU | H15: Ex_Integra | I15: 7.7424621e+10 | J15: 3.4075 | K15: 4675.0074 | M15: 46174 | N15: 5151 | O15: 1080.7083 | P15: 17215779 | AI15: rt | AJ15: rt | AK15: rt | AL15: rt | AM15: rt | AN15: rt | AO15: rt | AT15: rt | AU15: rt | AV15: rt | AW15: rt | AX15: rt | AZ15: NoCov | BA15: 0.62163188 | BB15: 0.14542962 | BC15: 0.001528955
B16: 1254342KAB22 | C16: USP4R21KAB22 | D16: 0.005566621 | E16: Multifondos | F16: RFIC | G16: BU | H16: Prima | I16: 3.2738708e+10 | J16: 3.4075 | K16: 47705 | M16: 46174 | N16: 5434 | O16: 1121.1234 | P16: 1.8224398e+08 | AI16: rt | AJ16: rt | AK16: rt | AL16: rt | AM16: rt | AN16: rt | AO16: rt | AT16: rt | AU16: rt | AV16: rt | AW16: rt | AX16: rt | AZ16: NoCov | BA16: 0.62127201 | BB16: 0.1558531 | BC16: 0.035717102
B17: 1551192MAD04 | C17: USP1400MAD04 | D17: 0.0086965016 | E17: F1 | F17: RFIC | G17: BU | H17: Ex_Integra | I17: 1.3660104e+10 | J17: 3.4075 | K17: 33732.94 | M17: 46174 | N17: 5119 | O17: 1033.4953 | P17: 1.1879511e+08 | AI17: rt | AJ17: rt | AK17: rt | AL17: rt | AM17: rt | AN17: rt | AO17: rt | AT17: rt | AU17: rt | AV17: rt | AW17: rt | AX17: rt | AZ17: NoCov | BA17: 0.57964491 | BB17: 0.30151641 | BC17: 0.028842549
... B20: 1254342KAB22 | C20: USP4R21KAB22 | D20: 0.002263091 | E20: Multifondos | F20: RFIC | G20: BU | H20: Integra | I20: 3.9311487e+10 | J20: 3.4075 | K20: 23288 | M20: 46174 | N20: 5434 | O20: 1121.1234 | P20: 88965470 | AI20: rt | AJ20: rt | AK20: rt | AL20: rt | AM20: rt | AN20: rt | AO20: rt | AT20: rt | AU20: rt | AV20: rt | AW20: rt | AX20: rt | AZ20: NoCov | BA20: 0.59538531 | BB20: 0.13474712 | BC20: 0.016795097
A21: 527801 | B21: 15527829AM84 | C21: USP16259AM84 | D21: 0.00060143115 | E21: Multifondos | F21: RFIC | G21: BU | H21: Ex_Integra | I21: 7.7424621e+10 | J21: 3.4075 | K21: 13622 | L21: BBVA Mexico, S.A., Institucion de Banca Multiple, Grupo Financiero BBVA Mexico | M21: 46174 | N21: 5278 | O21: 1003.2017 | P21: 46565578 | Q21: Financials | R21: Mexico | S21: MX | T21: Banks | U21: AA | V21: 0 | W21: 8.4489927 | X21: 5.8658712 | Y21: 4.8984375 | Z21: 13 | AA21: 54 | AB21: 33 | AC21: 4 | AD21: 249742 | AE21: 2.68 | AF21: 10 | AG21: 2.085084 | AH21: 7.5 | AI21: rt | AJ21: rt | AK21: rt | AL21: rt | AM21: rt | AN21: rt | AO21: rt | AP21: 4 | AQ21: 75 | AR21: 8.27 | AS21: 0.77 | AT21: rt | AU21: rt | AV21: rt | AW21: rt | AX21: rt | AY21: 1.5°C Aligned | AZ21: Cov | BA21: 0.62163188 | BB21: 0.47620225 | BC21: 0.0012629742 | BD21: 0 | BE21: 0.01067086 | BF21: 0.0074084437 | BG21: 0.0061866 | BH21: 0.010444796 | BI21: 0.0050518967 | BJ21: 0.0033847708 | BK21: 0.00097249011 | BL21: 315.41769 | BM21: 0.0050518967
B22: 1551192MAD04 | C22: USP1400MAD04 | D22: 0.0020033656 | E22: F2 | F22: RFIC | G22: BU | H22: Ex_Integra | I22: 5.0823903e+10 | J22: 3.4075 | K22: 28912.38 | M22: 46174 | N22: 5119 | O22: 1033.4953 | P22: 1.0181886e+08 | AI22: rt | AJ22: rt | AK22: rt | AL22: rt | AM22: rt | AN22: rt | AO22: rt | AT22: rt | AU22: rt | AV22: rt | AW22: rt | AX22: rt | AZ22: NoCov | BA22: 0.60589742 | BB22: 0.14204353 | BC22: 0.014103885
B23: 2100022V2K08 | C23: US05971V2K08 | D23: 0.0012592095 | E23: Multifondos | F23: RFLC | G23: BU | H23: Habitat | I23: 2.2785495e+10 | J23: 3.4075 | K23: 8157.37 | M23: 46174 | N23: 0002 | O23: 1032.2156 | P23: 28691712 | AI23: rt | AJ23: rt | AK23: rt | AL23: rt | AM23: rt | AN23: rt | AO23: rt | AT23: rt | AU23: rt | AV23: rt | AW23: rt | AX23: rt | AZ23: NoCov | BA23: 0.65823103 | BB23: 0.11726488 | BC23: 0.010738164
A24: 527801 | B24: 15527829AN67 | C24: USP16259AN67 | D24: 0.0011411929 | E24: Multifondos | F24: RFIC | G24: BU | H24: Ex_Integra | I24: 7.7424621e+10 | J24: 3.4075 | K24: 25841.48 | L24: BBVA Mexico, S.A., Institucion de Banca Multiple, Grupo Financiero BBVA Mexico | M24: 46174 | N24: 5278 | O24: 1003.425 | P24: 88356431 | Q24: Financials | R24: Mexico | S24: MX | T24: Banks | U24: AA | V24: 0 | W24: 8.4489927 | X24: 5.8658712 | Y24: 4.8984375 | Z24: 13 | AA24: 54 | AB24: 33 | AC24: 4 | AD24: 249742 | AE24: 2.68 | AF24: 10 | AG24: 2.085084 | AH24: 7.5 | AI24: rt | AJ24: rt | AK24: rt | AL24: rt | AM24: rt | AN24: rt | AO24: rt | AP24: 4 | AQ24: 75 | AR24: 8.27 | AS24: 0.77 | AT24: rt | AU24: rt | AV24: rt | AW24: rt | AX24: rt | AY24: 1.5°C Aligned | AZ24: Cov | BA24: 0.62163188 | BB24: 0.47620225 | BC24: 0.0023964459 | BD24: 0 | BE24: 0.020247554 | BF24: 0.014057243 | BG24: 0.011738841 | BH24: 0.019818608 | BI24: 0.0095857837 | BJ24: 0.0064224751 | BK24: 0.0018452634 | BL24: 598.4932 | BM24: 0.0095857837
B25: 1552782BAB48 | C25: USP1S81BAB48 | D25: 0.00072717208 | E25: Multifondos | F25: RFIC | G25: BU | H25: Profuturo | I25: 2.1900418e+10 | J25: 3.4075 | K25: 4217.9 | M25: 46174 | N25: 5278 | O25: 1108.0451 | P25: 15925372 | AI25: rt | AJ25: rt | AK25: rt | AL25: rt | AM25: rt | AN25: rt | AO25: rt | AT25: rt | AU25: rt | AV25: rt | AW25: rt | AX25: rt | AZ25: NoCov | BA25: 0.58409167 | BB25: 0.15915074 | BC25: 0.0045690776
B26: 1552782GAA15 | C26: USP2000GAA15 | D26: 0.00085934127 | E26: F1 | F26: RFIC | G26: BU | H26: Ex_Integra | I26: 1.3660104e+10 | J26: 3.4075 | K26: 3233 | M26: 46174 | N26: 5278 | O26: 1065.5605 | P26: 11738691 | AI26: rt | AJ26: rt | AK26: rt | AL26: rt | AM26: rt | AN26: rt | AO26: rt | AT26: rt | AU26: rt | AV26: rt | AW26: rt | AX26: rt | AZ26: NoCov | BA26: 0.57964491 | BB26: 0.30151641 | BC26: 0.0028500647
A27: 527801 | B27: 1552782BAA64 | C27: USP1S81BAA64 | D27: 0.00016144479 | E27: Multifondos | F27: RFIC | G27: BU | H27: Ex_Integra | I27: 7.7424621e+10 | J27: 3.4075 | K27: 3398 | L27: BBVA Mexico, S.A., Institucion de Banca Multiple, Grupo Financiero BBVA Mexico | M27: 46174 | N27: 5278 | O27: 1079.5528 | P27: 12499802 | Q27: Financials | R27: Mexico | S27: MX | T27: Banks | U27: AA | V27: 0 | W27: 8.4489927 | X27: 5.8658712 | Y27: 4.8984375 | Z27: 13 | AA27: 54 | AB27: 33 | AC27: 4 | AD27: 249742 | AE27: 2.68 | AF27: 10 | AG27: 2.085084 | AH27: 7.5 | AI27: rt | AJ27: rt | AK27: rt | AL27: rt | AM27: rt | AN27: rt | AO27: rt | AP27: 4 | AQ27: 75 | AR27: 8.27 | AS27: 0.77 | AT27: rt | AU27: rt | AV27: rt | AW27: rt | AX27: rt | AY27: 1.5°C Aligned | AZ27: Cov | BA27: 0.62163188 | BB27: 0.47620225 | BC27: 0.00033902567 | BD27: 0 | BE27: 0.0028644254 | BF27: 0.0019886809 | BG27: 0.0016606961 | BH27: 0.0028037423 | BI27: 0.0013561027 | BJ27: 0.0009085888 | BK27: 0.00026104977 | BL27: 84.668949 | BM27: 0.0013561027
B28: 1552782BAB48 | C28: USP1S81BAB48 | D28: 0.001226819 | E28: Multifondos | F28: RFIC | G28: BU | H28: Ex_Integra | I28: 7.7424621e+10 | J28: 3.4075 | K28: 25157.43 | M28: 46174 | N28: 5278 | O28: 1108.0451 | P28: 94985998 | AI28: rt | AJ28: rt | AK28: rt | AL28: rt | AM28: rt | AN28: rt | AO28: rt | AT28: rt | AU28: rt | AV28: rt | AW28: rt | AX28: rt | AZ28: NoCov | BA28: 0.62163188 | BB28: 0.14542962 | BC28: 0.0084358262
B29: 1551112LAN29 | C29: US05968LAN29 | D29: 0.00081494348 | E29: Multifondos | F29: RFIC | G29: BU | H29: Prima | I29: 3.2738708e+10 | J29: 3.4075 | K29: 7319 | M29: 46174 | N29: 5111 | O29: 1069.7971 | P29: 26680196 | AI29: rt | AJ29: rt | AK29: rt | AL29: rt | AM29: rt | AN29: rt | AO29: rt | AT29: rt | AU29: rt | AV29: rt | AW29: rt | AX29: rt | AZ29: NoCov | BA29: 0.62127201 | BB29: 0.1558531 | BC29: 0.0052289207
B30: 1552782GAA15 | C30: USP2000GAA15 | D30: 0.00033919805 | E30: Multifondos | F30: RFIC | G30: BU | H30: Ex_Integra | I30: 7.7424621e+10 | J30: 3.4075 | K30: 7233 | M30: 46174 | N30: 5278 | O30: 1065.5605 | P30: 26262280 | AI30: rt | AJ30: rt | AK30: rt | AL30: rt | AM30: rt | AN30: rt | AO30: rt | AT30: rt | AU30: rt | AV30: rt | AW30: rt | AX30: rt | AZ30: NoCov | BA30: 0.62163188 | BB30: 0.14542962 | BC30: 0.0023323862
B31: 1551112LAN29 | C31: US05968LAN29 | D31: 0.0027798442 | E31: Multifondos | F31: RFIC | G31: BU | H31: Integra | I31: 3.9311487e+10 | J31: 3.4075 | K31: 29978 | M31: 46174 | N31: 5111 | O31: 1069.7971 | P31: 1.0927981e+08 | AI31: rt | AJ31: rt | AK31: rt | AL31: rt | AM31: rt | AN31: rt | AO31: rt | AT31: rt | AU31: rt | AV31: rt | AW31: rt | AX31: rt | AZ31: NoCov | BA31: 0.59538531 | BB31: 0.13474712 | BC31: 0.020630082
B32: 1551512PAC05 | C32: US05890PAC05 | D32: 0.0076658356 | E32: F1 | F32: RFIC | G32: BU | H32: Prima | I32: 6.909728e+09 | J32: 3.4075 | K32: 14039 | M32: 46174 | N32: 5151 | O32: 1107.2569 | P32: 52968839 | AI32: rt | AJ32: rt | AK32: rt | AL32: rt | AM32: rt | AN32: rt | AO32: rt | AT32: rt | AU32: rt | AV32: rt | AW32: rt | AX32: rt | AZ32: NoCov | BA32: 0.56320494 | BB32: 0.28214925 | BC32: 0.027169434
B33: 1551192MAD04 | C33: USP1400MAD04 | D33: 0.005115003 | E33: Multifondos | F33: RFIC | G33: BU | H33: Prima | I33: 3.2738708e+10 | J33: 3.4075 | K33: 47551.37 | M33: 46174 | N33: 5119 | O33: 1033.4953 | P33: 1.6745859e+08 | AI33: rt | AJ33: rt | AK33: rt | AL33: rt | AM33: rt | AN33: rt | AO33: rt | AT33: rt | AU33: rt | AV33: rt | AW33: rt | AX33: rt | AZ33: NoCov | BA33: 0.62127201 | BB33: 0.1558531 | BC33: 0.032819386
B34: 1552782GAA15 | C34: USP2000GAA15 | D34: 0.0011223262 | E34: F3 | F34: RFIC | G34: BU | H34: Ex_Integra | I34: 1.2940613e+10 | J34: 3.4075 | K34: 4000 | M34: 46174 | N34: 5278 | O34: 1065.5605 | P34: 14523589 | AI34: rt | AJ34: rt | AK34: rt | AL34: rt | AM34: rt | AN34: rt | AO34: rt | AT34: rt | AU34: rt | AV34: rt | AW34: rt | AX34: rt | AZ34: NoCov | BA34: 0.8040057 | BB34: 0.070219065 | BC34: 0.015983212
B35: 15532427PD99 | C35: USP0R137PD99 | D35: 0.0035958357 | E35: Multifondos | F35: RFIC | G35: BU | H35: Ex_Integra | I35: 7.7424621e+10 | J35: 3.4075 | K35: 75813.31 | M35: 46174 | N35: 5324 | O35: 1077.6993 | P35: 2.7840621e+08 | AI35: rt | AJ35: rt | AK35: rt | AL35: rt | AM35: rt | AN35: rt | AO35: rt | AT35: rt | AU35: rt | AV35: rt | AW35: rt | AX35: rt | AZ35: NoCov | BA35: 0.62163188 | BB35: 0.14542962 | BC35: 0.024725607
B36: 21000325AF20 | C36: USP13435AF20 | D36: 2.7940878e-05 | E36: Multifondos | F36: RFLC | G36: BU | H36: Habitat | I36: 2.2785495e+10 | J36: 3.4075 | K36: 172.01 | M36: 46174 | N36: 0003 | O36: 1086.1979 | P36: 636646.75 | AI36: rt | AJ36: rt | AK36: rt | AL36: rt | AM36: rt | AN36: rt | AO36: rt | AT36: rt | AU36: rt | AV36: rt | AW36: rt | AX36: rt | AZ36: NoCov | BA36: 0.65823103 | BB36: 0.11726488 | BC36: 0.0002382715
A37: 509401 | B37: 59509428AJ82 | C37: US279158AJ82 | D37: 0.00064020052 | E37: F2 | F37: RFIC | G37: BU | H37: Habitat | I37: 1.4820338e+10 | J37: 3.4075 | K37: 3358 | L37: Ecopetrol S.A. | M37: 46174 | N37: 5094 | O37: 829.19671 | P37: 9487988 | Q37: Energy | R37: Colombia | S37: CO | T37: Integrated Oil & Gas | U37: A | V37: 1 | W37: 4.9145451 | X37: 8.1681979 | Y37: 4.609375 | Z37: 41 | AA37: 26 | AB37: 33 | AC37: 4 | AD37: 12677105 | AE37: 418.89 | AF37: 5.9190111 | AG37: 7.4017041 | AH37: 5.9 | AI37: rt | AJ37: rt | AK37: rt | AL37: rt | AM37: rt | AN37: rt | AO37: rt | AP37: 2 | AQ37: 39 | AR37: 6.51 | AS37: 226.35 | AT37: rt | AU37: rt | AV37: rt | AW37: rt | AX37: rt | AY37: Strongly Misaligned | AZ37: Cov | BA37: 0.61054168 | BB37: 0.49055401 | BC37: 0.0013050561 | BD37: 0.0013050561 | BE37: 0.0064137571 | BF37: 0.010659957 | BG37: 0.0060154931 | BH37: 0.0084959154 | BI37: 0.0052202245 | BJ37: 0.54667496 | BK37: 0.29539945 | BL37: 16544.334 | BM37: 0.0026101122
A38: 209601 | B38: 182096345816 | C38: XS0799645816 | D38: 0.0046054666 | E38: Multifondos | F38: RFLC | G38: BU | H38: Ex_Integra | I38: 7.7424621e+10 | J38: 1 | K38: 303359 | M38: 46174 | N38: 2096 | O38: 1175.4275 | P38: 3.5657651e+08 | Q38: Industrials | R38: Peru | AI38: rt | AJ38: rt | AK38: rt | AL38: rt | AM38: rt | AN38: rt | AO38: rt | AT38: rt | AU38: rt | AV38: rt | AW38: rt | AX38: rt | AZ38: NoCov | BA38: 0.62163188 | BB38: 0.14542962 | BC38: 0.031668009
A39: 527801 | B39: 15527829AM84 | C39: USP16259AM84 | D39: 0.00091621412 | E39: F2 | F39: RFIC | G39: BU | H39: Ex_Integra | I39: 5.0823903e+10 | J39: 3.4075 | K39: 13622 | L39: BBVA Mexico, S.A., Institucion de Banca Multiple, Grupo Financiero BBVA Mexico | M39: 46174 | N39: 5278 | O39: 1003.2017 | P39: 46565578 | Q39: Financials | R39: Mexico | S39: MX | T39: Banks | U39: AA | V39: 0 | W39: 8.4489927 | X39: 5.8658712 | Y39: 4.8984375 | Z39: 13 | AA39: 54 | AB39: 33 | AC39: 4 | AD39: 249742 | AE39: 2.68 | AF39: 10 | AG39: 2.085084 | AH39: 7.5 | AI39: rt | AJ39: rt | AK39: rt | AL39: rt | AM39: rt | AN39: rt | AO39: rt | AP39: 4 | AQ39: 75 | AR39: 8.27 | AS39: 0.77 | AT39: rt | AU39: rt | AV39: rt | AW39: rt | AX39: rt | AY39: 1.5°C Aligned | AZ39: Cov | BA39: 0.60589742 | BB39: 0.46385389 | BC39: 0.0019752214 | BD39: 0 | BE39: 0.016688631 | BF39: 0.011586394 | BG39: 0.0096754984 | BH39: 0.016335081 | BI39: 0.0079008855 | BJ39: 0.0052935933 | BK39: 0.0015209205 | BL39: 493.29574 | BM39: 0.0079008855
A40: 209601 | B40: 182096345816 | C40: XS0799645816 | D40: 0.0075675691 | E40: Multifondos | F40: RFLC | G40: BU | H40: Profuturo | I40: 2.1900418e+10 | J40: 1 | K40: 140998 | M40: 46174 | N40: 2096 | O40: 1175.4275 | P40: 1.6573292e+08 | Q40: Industrials | R40: Peru | AI40: rt | AJ40: rt | AK40: rt | AL40: rt | AM40: rt | AN40: rt | AO40: rt | AT40: rt | AU40: rt | AV40: rt | AW40: rt | AX40: rt | AZ40: NoCov | BA40: 0.58409167 | BB40: 0.15915074 | BC40: 0.047549695
B41: 1551192MAD04 | C41: USP1400MAD04 | D41: 0.010945302 | E41: F1 | F41: RFIC | G41: BU | H41: Profuturo | I41: 4.856457e+09 | J41: 3.4075 | K41: 15093.95 | M41: 46174 | N41: 5119 | O41: 1033.4953 | P41: 53155388 | AI41: rt | AJ41: rt | AK41: rt | AL41: rt | AM41: rt | AN41: rt | AO41: rt | AT41: rt | AU41: rt | AV41: rt | AW41: rt | AX41: rt | AZ41: NoCov | BA41: 0.58036121 | BB41: 0.33866066 | BC41: 0.032319378
B42: 1552782BAB48 | C42: USP1S81BAB48 | D42: 0.0032792162 | E42: F1 | F42: RFIC | G42: BU | H42: Profuturo | I42: 4.856457e+09 | J42: 3.4075 | K42: 4217.9 | M42: 46174 | N42: 5278 | O42: 1108.0451 | P42: 15925372 | AI42: rt | AJ42: rt | AK42: rt | AL42: rt | AM42: rt | AN42: rt | AO42: rt | AT42: rt | AU42: rt | AV42: rt | AW42: rt | AX42: rt | AZ42: NoCov | BA42: 0.58036121 | BB42: 0.33866066 | BC42: 0.0096828968
A43: 000201 | B43: 2100022V2D64 | C43: US05971V2D64 | D43: 0.00017540145 | E43: Multifondos | F43: RFLC | G43: BU | H43: Ex_Integra | I43: 7.7424621e+10 | J43: 3.4075 | K43: 3974 | L43: Banco de Credito del Peru | M43: 46174 | N43: 0002 | O43: 1002.879 | P43: 13580391 | Q43: Financials | R43: Peru | S43: PE | T43: Banks | U43: BBB | V43: 0 | W43: 4.3727436 | X43: 4.8090464 | Y43: 4.1667969 | Z43: 13 | AA43: 54 | AB43: 33 | AC43: 0 | AD43: 12369.54 | AE43: 2.06 | AF43: 9.0531244 | AG43: 1.7266014 | AH43: 4.3 | AI43: rt | AJ43: rt | AK43: rt | AL43: rt | AM43: rt | AN43: rt | AO43: rt | AP43: 4 | AQ43: 12 | AR43: 5.55 | AS43: 0.44 | AT43: rt | AU43: rt | AV43: rt | AW43: rt | AX43: rt | AY43: Misaligned | AZ43: Cov | BA43: 0.62163188 | BB43: 0.47620225 | BC43: 0.00036833393 | BD43: 0 | BE43: 0.0016106298 | BF43: 0.001771335 | BG43: 0.0015347727 | BH43: 0.0020442533 | BI43: 0 | BJ43: 0.0007587679 | BK43: 0.00016206693 | BL43: 4.5561213 | BM43: 0.0014733357
B44: 2100022V2H78 | C44: US05971V2H78 | D44: 0.00049479706 | E44: Multifondos | F44: RFLC | G44: BU | H44: Ex_Integra | I44: 7.7424621e+10 | J44: 3.4075 | K44: 10964.38 | M44: 46174 | N44: 0002 | O44: 1025.3833 | P44: 38309475 | AI44: rt | AJ44: rt | AK44: rt | AL44: rt | AM44: rt | AN44: rt | AO44: rt | AT44: rt | AU44: rt | AV44: rt | AW44: rt | AX44: rt | AZ44: NoCov | BA44: 0.62163188 | BB44: 0.14542962 | BC44: 0.0034023127
B45: 1551192MAD04 | C45: USP1400MAD04 | D45: 0.0094996108 | E45: F1 | F45: RFIC | G45: BU | H45: Prima | I45: 6.909728e+09 | J45: 3.4075 | K45: 18638.99 | M45: 46174 | N45: 5119 | O45: 1033.4953 | P45: 65639726 | AI45: rt | AJ45: rt | AK45: rt | AL45: rt | AM45: rt | AN45: rt | AO45: rt | AT45: rt | AU45: rt | AV45: rt | AW45: rt | AX45: rt | AZ45: NoCov | BA45: 0.56320494 | BB45: 0.28214925 | BC45: 0.033668743
B46: 15515123CH47 | C46: USP32133CH47 | D46: 8.3664706e-10 | E46: Multifondos | F46: RFIC | G46: BU | H46: Prima | I46: 3.2738708e+10 | J46: 3.4075 | K46: 0.0074380562 | M46: 46174 | N46: 5151 | O46: 1080.7083 | P46: 27.390743 | AI46: rt | AJ46: rt | AK46: rt | AL46: rt | AM46: rt | AN46: rt | AO46: rt | AT46: rt | AU46: rt | AV46: rt | AW46: rt | AX46: rt | AZ46: NoCov | BA46: 0.62127201 | BB46: 0.1558531 | BC46: 5.3681773e-09
B47: 2100022V2J35 | C47: US05971V2J35 | D47: 0.0015081522 | E47: Multifondos | F47: RFLC | G47: BU | H47: Ex_Integra | I47: 7.7424621e+10 | J47: 3.4075 | K47: 32325.98 | M47: 46174 | N47: 0002 | O47: 1060.0752 | P47: 1.1676811e+08 | AI47: rt | AJ47: rt | AK47: rt | AL47: rt | AM47: rt | AN47: rt | AO47: rt | AT47: rt | AU47: rt | AV47: rt | AW47: rt | AX47: rt | AZ47: NoCov | BA47: 0.62163188 | BB47: 0.14542962 | BC47: 0.010370323
B48: 21000325AG03 | C48: USP13435AG03 | D48: 0.0015029254 | E48: Multifondos | F48: RFLC | G48: BU | H48: Habitat | I48: 2.2785495e+10 | J48: 3.4075 | K48: 9643.49 | M48: 46174 | N48: 0003 | O48: 1042.1394 | P48: 34244900 | AI48: rt | AJ48: rt | AK48: rt | AL48: rt | AM48: rt | AN48: rt | AO48: rt | AT48: rt | AU48: rt | AV48: rt | AW48: rt | AX48: rt | AZ48: NoCov | BA48: 0.65823103 | BB48: 0.11726488 | BC48: 0.012816501
A49: 509401 | B49: 59509428AQ26 | C49: US279158AQ26 | D49: 0.00097788329 | E49: F1 | F49: RFIC | G49: BU | H49: Habitat | I49: 1.8939189e+09 | J49: 3.4075 | K49: 669.06018 | L49: Ecopetrol S.A. | M49: 46174 | N49: 5094 | O49: 812.35778 | P49: 1852031.6 | Q49: Energy | R49: Colombia | S49: CO | T49: Integrated Oil & Gas | U49: A | V49: 1 | W49: 4.9145451 | X49: 8.1681979 | Y49: 4.609375 | Z49: 41 | AA49: 26 | AB49: 33 | AC49: 4 | AD49: 12677105 | AE49: 418.89 | AF49: 5.9190111 | AG49: 7.4017041 | AH49: 5.9 | AI49: rt | AJ49: rt | AK49: rt | AL49: rt | AM49: rt | AN49: rt | AO49: rt | AP49: 2 | AQ49: 39 | AR49: 6.51 | AS49: 226.35 | AT49: rt | AU49: rt | AV49: rt | AW49: rt | AX49: rt | AY49: Strongly Misaligned | AZ49: Cov | BA49: 0.63778762 | BB49: 0.36085898 | BC49: 0.0027098765 | BD49: 0.0027098765 | BE49: 0.01331781 | BF49: 0.022134808 | BG49: 0.012490837 | BH49: 0.017641296 | BI49: 0.010839506 | BJ49: 1.1351402 | BK49: 0.61338055 | BL49: 34353.389 | BM49: 0.005419753
A50: 527801 | B50: 15527829AN67 | C50: USP16259AN67 | D50: 0.0042372013 | E50: F1 | F50: RFIC | G50: BU | H50: Ex_Integra | I50: 1.3660104e+10 | J50: 3.4075 | K50: 16928.26 | L50: BBVA Mexico, S.A., Institucion de Banca Multiple, Grupo Financiero BBVA Mexico | M50: 46174 | N50: 5278 | O50: 1003.425 | P50: 57880610 | Q50: Financials | R50: Mexico | S50: MX | T50: Banks | U50: AA | V50: 0 | W50: 8.4489927 | X50: 5.8658712 | Y50: 4.8984375 | Z50: 13 | AA50: 54 | AB50: 33 | AC50: 4 | AD50: 249742 | AE50: 2.68 | AF50: 10 | AG50: 2.085084 | AH50: 7.5 | AI50: rt | AJ50: rt | AK50: rt | AL50: rt | AM50: rt | AN50: rt | AO50: rt | AP50: 4 | AQ50: 75 | AR50: 8.27 | AS50: 0.77 | AT50: rt | AU50: rt | AV50: rt | AW50: rt | AX50: rt | AY50: 1.5°C Aligned | AZ50: Cov | BA50: 0.57964491 | BB50: 0.27812851 | BC50: 0.015234689 | BD50: 0 | BE50: 0.12871778 | BF50: 0.089364723 | BG50: 0.074626172 | BH50: 0.12599088 | BI50: 0.060938756 | BJ50: 0.040828967 | BK50: 0.011730711 | BL50: 3804.7417 | BM50: 0.060938756
B51: 2100022V2H78 | C51: US05971V2H78 | D51: 2.3931007e-08 | E51: Multifondos | F51: RFLC | G51: BU | H51: Profuturo | I51: 2.1900418e+10 | J51: 3.4075 | K51: 0.15 | M51: 46174 | N51: 0002 | O51: 1025.3833 | P51: 524.09906 | AI51: rt | AJ51: rt | AK51: rt | AL51: rt | AM51: rt | AN51: rt | AO51: rt | AT51: rt | AU51: rt | AV51: rt | AW51: rt | AX51: rt | AZ51: NoCov | BA51: 0.58409167 | BB51: 0.15915074 | BC51: 1.5036693e-07
A52: 527801 | B52: 15527829AN67 | C52: USP16259AN67 | D52: 0.00026422014 | E52: F3 | F52: RFIC | G52: BU | H52: Ex_Integra | I52: 1.2940613e+10 | J52: 3.4075 | K52: 1000 | L52: BBVA Mexico, S.A., Institucion de Banca Multiple, Grupo Financiero BBVA Mexico | M52: 46174 | N52: 5278 | O52: 1003.425 | P52: 3419170.7 | Q52: Financials | R52: Mexico | S52: MX | T52: Banks | U52: AA | V52: 0 | W52: 8.4489927 | X52: 5.8658712 | Y52: 4.8984375 | Z52: 13 | AA52: 54 | AB52: 33 | AC52: 4 | AD52: 249742 | AE52: 2.68 | AF52: 10 | AG52: 2.085084 | AH52: 7.5 | AI52: rt | AJ52: rt | AK52: rt | AL52: rt | AM52: rt | AN52: rt | AO52: rt | AP52: 4 | AQ52: 75 | AR52: 8.27 | AS52: 0.77 | AT52: rt | AU52: rt | AV52: rt | AW52: rt | AX52: rt | AY52: 1.5°C Aligned | AZ52: Cov | BA52: 0.8040057 | BB52: 0.73378663 | BC52: 0.00036007762 | BD52: 0 | BE52: 0.0030422932 | BF52: 0.0021121689 | BG52: 0.0017638177 | BH52: 0.0029778419 | BI52: 0.0014403105 | BJ52: 0.00096500802 | BK52: 0.00027725977 | BL52: 89.926505 | BM52: 0.0014403105
B53: 2100022V2K08 | C53: US05971V2K08 | D53: 0.0018044174 | E53: Multifondos | F53: RFLC | G53: BU | H53: Ex_Integra | I53: 7.7424621e+10 | J53: 3.4075 | K53: 39720.05 | M53: 46174 | N53: 0002 | O53: 1032.2156 | P53: 1.3970633e+08 | AI53: rt | AJ53: rt | AK53: rt | AL53: rt | AM53: rt | AN53: rt | AO53: rt | AT53: rt | AU53: rt | AV53: rt | AW53: rt | AX53: rt | AZ53: NoCov | BA53: 0.62163188 | BB53: 0.14542962 | BC53: 0.012407495
A54: 511901 | B54: 1551192KAB72 | C54: USP1401KAB72 | D54: 0.0023296279 | E54: Multifondos | F54: RFIC | G54: BU | H54: Integra | I54: 3.9311487e+10 | J54: 3.4075 | K54: 27820 | L54: BANCO MERCANTIL DEL NORTE S.A. | M54: 46174 | N54: 5119 | O54: 966.07986 | P54: 91581134 | Q54: Financials | R54: Mexico | S54: KY | T54: Banks | U54: AA | V54: 0 | W54: 7.1886191 | X54: 6.016652 | Y54: 4.8828125 | Z54: 13 | AA54: 54 | AB54: 33 | AC54: 1 | AD54: 64594.9 | AE54: 2.21 | AF54: 10 | AG54: 2.052 | AH54: 5.6 | AI54: rt | AJ54: rt | AK54: rt | AL54: rt | AM54: rt | AN54: rt | AO54: rt | AP54: 4 | AQ54: 33 | AR54: 8.6 | AS54: 1.26 | AT54: rt | AU54: rt | AV54: rt | AW54: rt | AX54: rt | AY54: Misaligned | AZ54: Cov | BA54: 0.59538531 | BB54: 0.46063819 | BC54: 0.005057392 | BD54: 0 | BE54: 0.036355665 | BF54: 0.030428567 | BG54: 0.024694297 | BH54: 0.043493571 | BI54: 0.005057392 | BJ54: 0.011176836 | BK54: 0.0063723139 | BL54: 326.68173 | BM54: 0.020229568
B55: 2100022V2J35 | C55: US05971V2J35 | D55: 2.4740668e-08 | E55: Multifondos | F55: RFLC | G55: BU | H55: Profuturo | I55: 2.1900418e+10 | J55: 3.4075 | K55: 0.15 | M55: 46174 | N55: 0002 | O55: 1060.0752 | P55: 541.83096 | AI55: rt | AJ55: rt | AK55: rt | AL55: rt | AM55: rt | AN55: rt | AO55: rt | AT55: rt | AU55: rt | AV55: rt | AW55: rt | AX55: rt | AZ55: NoCov | BA55: 0.58409167 | BB55: 0.15915074 | BC55: 1.5545431e-07
B56: 21000325AF20 | C56: USP13435AF20 | D56: 8.2227946e-06 | E56: Multifondos | F56: RFLC | G56: BU | H56: Ex_Integra | I56: 7.7424621e+10 | J56: 3.4075 | K56: 172.01 | M56: 46174 | N56: 0003 | O56: 1086.1979 | P56: 636646.75 | AI56: rt | AJ56: rt | AK56: rt | AL56: rt | AM56: rt | AN56: rt | AO56: rt | AT56: rt | AU56: rt | AV56: rt | AW56: rt | AX56: rt | AZ56: NoCov | BA56: 0.62163188 | BB56: 0.14542962 | BC56: 5.65414e-05
B57: 21001112601A | C57: PEP11600D110 | D57: 0.001330535 | E57: Multifondos | F57: RFLC | G57: BU | H57: Habitat | I57: 2.2785495e+10 | J57: 1 | K57: 29161 | M57: 46174 | N57: 0011 | O57: 1039.6385 | P57: 30316898 | AI57: rt | AJ57: rt | AK57: rt | AL57: rt | AM57: rt | AN57: rt | AO57: rt | AT57: rt | AU57: rt | AV57: rt | AW57: rt | AX57: rt | AZ57: NoCov | BA57: 0.65823103 | BB57: 0.11726488 | BC57: 0.011346407
B58: 21000325AG03 | C58: USP13435AG03 | D58: 0.00044229987 | E58: Multifondos | F58: RFLC | G58: BU | H58: Ex_Integra | I58: 7.7424621e+10 | J58: 3.4075 | K58: 9643.49 | M58: 46174 | N58: 0003 | O58: 1042.1394 | P58: 34244900 | AI58: rt | AJ58: rt | AK58: rt | AL58: rt | AM58: rt | AN58: rt | AO58: rt | AT58: rt | AU58: rt | AV58: rt | AW58: rt | AX58: rt | AZ58: NoCov | BA58: 0.62163188 | BB58: 0.14542962 | BC58: 0.0030413327
B59: 21001112601A | C59: PEP11600D110 | D59: 0.00086552596 | E59: Multifondos | F59: RFLC | G59: BU | H59: Ex_Integra | I59: 7.7424621e+10 | J59: 1 | K59: 64458 | M59: 46174 | N59: 0011 | O59: 1039.6385 | P59: 67013019 | AI59: rt | AJ59: rt | AK59: rt | AL59: rt | AM59: rt | AN59: rt | AO59: rt | AT59: rt | AU59: rt | AV59: rt | AW59: rt | AX59: rt | AZ59: NoCov | BA59: 0.62163188 | BB59: 0.14542962 | BC59: 0.0059515106
A60: 527801 | B60: 15527829AN67 | C60: USP16259AN67 | D60: 0.00053236072 | E60: F2 | F60: RFIC | G60: BU | H60: Ex_Integra | I60: 5.0823903e+10 | J60: 3.4075 | K60: 7913.22 | L60: BBVA Mexico, S.A., Institucion de Banca Multiple, Grupo Financiero BBVA Mexico | M60: 46174 | N60: 5278 | O60: 1003.425 | P60: 27056650 | Q60: Financials | R60: Mexico | S60: MX | T60: Banks | U60: AA | V60: 0 | W60: 8.4489927 | X60: 5.8658712 | Y60: 4.8984375 | Z60: 13 | AA60: 54 | AB60: 33 | AC60: 4 | AD60: 249742 | AE60: 2.68 | AF60: 10 | AG60: 2.085084 | AH60: 7.5 | AI60: rt | AJ60: rt | AK60: rt | AL60: rt | AM60: rt | AN60: rt | AO60: rt | AP60: 4 | AQ60: 75 | AR60: 8.27 | AS60: 0.77 | AT60: rt | AU60: rt | AV60: rt | AW60: rt | AX60: rt | AY60: 1.5°C Aligned | AZ60: Cov | BA60: 0.60589742 | BB60: 0.46385389 | BC60: 0.0011476905 | BD60: 0 | BE60: 0.0096968289 | BF60: 0.0067322048 | BG60: 0.0056218903 | BH60: 0.0094914007 | BI60: 0.0045907621 | BJ60: 0.0030758106 | BK60: 0.00088372171 | BL60: 286.62653 | BM60: 0.0045907621
B61: 1551512PAC05 | C61: US05890PAC05 | D61: 0.001617927 | E61: Multifondos | F61: RFIC | G61: BU | H61: Prima | I61: 3.2738708e+10 | J61: 3.4075 | K61: 14039 | M61: 46174 | N61: 5151 | O61: 1107.2569 | P61: 52968839 | AI61: rt | AJ61: rt | AK61: rt | AL61: rt | AM61: rt | AN61: rt | AO61: rt | AT61: rt | AU61: rt | AV61: rt | AW61: rt | AX61: rt | AZ61: NoCov | BA61: 0.62127201 | BB61: 0.1558531 | BC61: 0.010381103
B62: 21001120AH74 | C62: USP07760AH74 | D62: 0.00014925257 | E62: Multifondos | F62: RFLC | G62: BU | H62: Ex_Integra | I62: 7.7424621e+10 | J62: 3.4075 | K62: 3295.83 | M62: 46174 | N62: 0011 | O62: 1028.9641 | P62: 11555823 | AI62: rt | AJ62: rt | AK62: rt | AL62: rt | AM62: rt | AN62: rt | AO62: rt | AT62: rt | AU62: rt | AV62: rt | AW62: rt | AX62: rt | AZ62: NoCov | BA62: 0.62163188 | BB62: 0.14542962 | BC62: 0.0010262872
B63: 59509428AW93 | C63: US279158AW93 | D63: 0.0010645114 | E63: F2 | F63: RFIC | G63: BU | H63: Ex_Integra | I63: 5.0823903e+10 | J63: 3.4075 | K63: 14707.64 | M63: 46174 | N63: 5094 | O63: 1079.5419 | P63: 54102627 | AI63: rt | AJ63: rt | AK63: rt | AL63: rt | AM63: rt | AN63: rt | AO63: rt | AT63: rt | AU63: rt | AV63: rt | AW63: rt | AX63: rt | AZ63: NoCov | BA63: 0.60589742 | BB63: 0.14204353 | BC63: 0.0074942621
B64: 21001120AH74 | C64: USP07760AH74 | D64: 0.00050715699 | E64: Multifondos | F64: RFLC | G64: BU | H64: Habitat | I64: 2.2785495e+10 | J64: 3.4075 | K64: 3295.83 | M64: 46174 | N64: 0011 | O64: 1028.9641 | P64: 11555823 | AI64: rt | AJ64: rt | AK64: rt | AL64: rt | AM64: rt | AN64: rt | AO64: rt | AT64: rt | AU64: rt | AV64: rt | AW64: rt | AX64: rt | AZ64: NoCov | BA64: 0.65823103 | BB64: 0.11726488 | BC64: 0.004324884
A65: 527801 | B65: 15527829AM84 | C65: USP16259AM84 | D65: 0.0014223401 | E65: Multifondos | F65: RFIC | G65: BU | H65: Prima | I65: 3.2738708e+10 | J65: 3.4075 | K65: 13622 | L65: BBVA Mexico, S.A., Institucion de Banca Multiple, Grupo Financiero BBVA Mexico | M65: 46174 | N65: 5278 | O65: 1003.2017 | P65: 46565578 | Q65: Financials | R65: Mexico | S65: MX | T65: Banks | U65: AA | V65: 0 | W65: 8.4489927 | X65: 5.8658712 | Y65: 4.8984375 | Z65: 13 | AA65: 54 | AB65: 33 | AC65: 4 | AD65: 249742 | AE65: 2.68 | AF65: 10 | AG65: 2.085084 | AH65: 7.5 | AI65: rt | AJ65: rt | AK65: rt | AL65: rt | AM65: rt | AN65: rt | AO65: rt | AP65: 4 | AQ65: 75 | AR65: 8.27 | AS65: 0.77 | AT65: rt | AU65: rt | AV65: rt | AW65: rt | AX65: rt | AY65: 1.5°C Aligned | AZ65: Cov | BA65: 0.62127201 | BB65: 0.46541892 | BC65: 0.0030560428 | BD65: 0 | BE65: 0.025820484 | BF65: 0.017926354 | BG65: 0.014969835 | BH65: 0.025273474 | BI65: 0.012224171 | BJ65: 0.0081901948 | BK65: 0.002353153 | BL65: 763.22225 | BM65: 0.012224171
A66: 001801 | B66: 21001811601A | C66: PEP12030D010 | D66: 0.00024353816 | E66: Multifondos | F66: RFLC | G66: BU | H66: Ex_Integra | I66: 7.7424621e+10 | J66: 1 | K66: 18240 | L66: Banco de la Nacion | M66: 46174 | N66: 0018 | O66: 1033.7637 | P66: 18855849 | Q66: Financials | R66: Peru | S66: PE | AI66: rt | AJ66: rt | AK66: rt | AL66: rt | AM66: rt | AN66: rt | AO66: rt | AT66: rt | AU66: rt | AV66: rt | AW66: rt | AX66: rt | AZ66: NoCov | BA66: 0.62163188 | BB66: 0.14542962 | BC66: 0.0016746118
B67: 21015122401A | C67: PEP66450D098 | D67: 0.0001369058 | E67: Multifondos | F67: RFLC | G67: BU | H67: Ex_Integra | I67: 7.7424621e+10 | J67: 3.4075 | K67: 3001.51 | M67: 46174 | N67: 0151 | O67: 1036.3949 | P67: 10599880 | AI67: rt | AJ67: rt | AK67: rt | AL67: rt | AM67: rt | AN67: rt | AO67: rt | AT67: rt | AU67: rt | AV67: rt | AW67: rt | AX67: rt | AZ67: NoCov | BA67: 0.62163188 | BB67: 0.14542962 | BC67: 0.00094138868
A68: 015401 | B68: 21015422002A | C68: PEP66950D014 | D68: 0.0012821282 | E68: Multifondos | F68: RFLC | G68: BU | H68: Profuturo | I68: 2.1900418e+10 | J68: 3.4075 | K68: 8600 | L68: Pacifico Compania de Seguros y Reaseguros | M68: 46174 | N68: 0154 | O68: 958.18536 | P68: 28079143 | Q68: Financials | R68: Peru | S68: PE | T68: Life & Health Insurance | AI68: rt | AJ68: rt | AK68: rt | AL68: rt | AM68: rt | AN68: rt | AO68: rt | AT68: rt | AU68: rt | AV68: rt | AW68: rt | AX68: rt | AZ68: NoCov | BA68: 0.58409167 | BB68: 0.15915074 | BC68: 0.0080560618
B69: 1551192MAD04 | C69: USP1400MAD04 | D69: 0.003287243 | E69: Multifondos | F69: RFIC | G69: BU | H69: Integra | I69: 3.9311487e+10 | J69: 3.4075 | K69: 36695 | M69: 46174 | N69: 5119 | O69: 1033.4953 | P69: 1.2922641e+08 | AI69: rt | AJ69: rt | AK69: rt | AL69: rt | AM69: rt | AN69: rt | AO69: rt | AT69: rt | AU69: rt | AV69: rt | AW69: rt | AX69: rt | AZ69: NoCov | BA69: 0.59538531 | BB69: 0.13474712 | BC69: 0.024395645
A70: 015401 | B70: 21015422002A | C70: PEP66950D014 | D70: 0.0012314982 | E70: Multifondos | F70: RFLC | G70: BU | H70: Ex_Integra | I70: 7.7424621e+10 | J70: 3.4075 | K70: 29203 | L70: Pacifico Compania de Seguros y Reaseguros | M70: 46174 | N70: 0154 | O70: 958.18536 | P70: 95348280 | Q70: Financials | R70: Peru | S70: PE | T70: Life & Health Insurance | AI70: rt | AJ70: rt | AK70: rt | AL70: rt | AM70: rt | AN70: rt | AO70: rt | AT70: rt | AU70: rt | AV70: rt | AW70: rt | AX70: rt | AZ70: NoCov | BA70: 0.62163188 | BB70: 0.14542962 | BC70: 0.0084680009
B71: 59509428AW93 | C71: US279158AW93 | D71: 0.0015824572 | E71: F1 | F71: RFIC | G71: BU | H71: Ex_Integra | I71: 1.3660104e+10 | J71: 3.4075 | K71: 5876.39 | M71: 46174 | N71: 5094 | O71: 1079.5419 | P71: 21616530 | AI71: rt | AJ71: rt | AK71: rt | AL71: rt | AM71: rt | AN71: rt | AO71: rt | AT71: rt | AU71: rt | AV71: rt | AW71: rt | AX71: rt | AZ71: NoCov | BA71: 0.57964491 | BB71: 0.30151641 | BC71: 0.0052483287
B72: 2220082PAB78 | C72: USP6680PAB78 | D72: 0.0035354495 | E72: Multifondos | F72: RFLC | G72: BU | H72: Profuturo | I72: 2.1900418e+10 | J72: 3.4075 | K72: 21456.475 | M72: 46174 | N72: 2008 | O72: 1059.0167 | P72: 77427821 | AI72: rt | AJ72: rt | AK72: rt | AL72: rt | AM72: rt | AN72: rt | AO72: rt | AT72: rt | AU72: rt | AV72: rt | AW72: rt | AX72: rt | AZ72: NoCov | BA72: 0.58409167 | BB72: 0.15915074 | BC72: 0.022214471
A73: 527801 | B73: 15527829AN67 | C73: USP16259AN67 | D73: 0.0026988369 | E73: Multifondos | F73: RFIC | G73: BU | H73: Prima | I73: 3.2738708e+10 | J73: 3.4075 | K73: 25841.48 | L73: BBVA Mexico, S.A., Institucion de Banca Multiple, Grupo Financiero BBVA Mexico | M73: 46174 | N73: 5278 | O73: 1003.425 | P73: 88356431 | Q73: Financials | R73: Mexico | S73: MX | T73: Banks | U73: AA | V73: 0 | W73: 8.4489927 | X73: 5.8658712 | Y73: 4.8984375 | Z73: 13 | AA73: 54 | AB73: 33 | AC73: 4 | AD73: 249742 | AE73: 2.68 | AF73: 10 | AG73: 2.085084 | AH73: 7.5 | AI73: rt | AJ73: rt | AK73: rt | AL73: rt | AM73: rt | AN73: rt | AO73: rt | AP73: 4 | AQ73: 75 | AR73: 8.27 | AS73: 0.77 | AT73: rt | AU73: rt | AV73: rt | AW73: rt | AX73: rt | AY73: 1.5°C Aligned | AZ73: Cov | BA73: 0.62127201 | BB73: 0.46541892 | BC73: 0.0057987262 | BD73: 0 | BE73: 0.048993396 | BF73: 0.034014581 | BG73: 0.028404698 | BH73: 0.047955466 | BI73: 0.023194905 | BJ73: 0.015540586 | BK73: 0.0044650192 | BL73: 1448.1855 | BM73: 0.023194905
B74: 21015422302B | C74: PEP66950D030 | D74: 7.0089126e-05 | E74: Multifondos | F74: RFLC | G74: BU | H74: Ex_Integra | I74: 7.7424621e+10 | J74: 3.4075 | K74: 1504 | M74: 46174 | N74: 0154 | O74: 1058.8783 | P74: 5426624 | AI74: rt | AJ74: rt | AK74: rt | AL74: rt | AM74: rt | AN74: rt | AO74: rt | AT74: rt | AU74: rt | AV74: rt | AW74: rt | AX74: rt | AZ74: NoCov | BA74: 0.62163188 | BB74: 0.14542962 | BC74: 0.00048194531
B75: 1552782BAB48 | C75: USP1S81BAB48 | D75: 0.0011657978 | E75: F1 | F75: RFIC | G75: BU | H75: Ex_Integra | I75: 1.3660104e+10 | J75: 3.4075 | K75: 4217.9 | M75: 46174 | N75: 5278 | O75: 1108.0451 | P75: 15925372 | AI75: rt | AJ75: rt | AK75: rt | AL75: rt | AM75: rt | AN75: rt | AO75: rt | AT75: rt | AU75: rt | AV75: rt | AW75: rt | AX75: rt | AZ75: NoCov | BA75: 0.57964491 | BB75: 0.30151641 | BC75: 0.0038664491
B76: 1551192MAD04 | C76: USP1400MAD04 | D76: 0.0044983709 | E76: F2 | F76: RFIC | G76: BU | H76: Prima | I76: 2.2634608e+10 | J76: 3.4075 | K76: 28912.38 | M76: 46174 | N76: 5119 | O76: 1033.4953 | P76: 1.0181886e+08 | AI76: rt | AJ76: rt | AK76: rt | AL76: rt | AM76: rt | AN76: rt | AO76: rt | AT76: rt | AU76: rt | AV76: rt | AW76: rt | AX76: rt | AZ76: NoCov | BA76: 0.61894322 | BB76: 0.1389632 | BC76: 0.03237095
A77: 001801 | B77: 21001811601A | C77: PEP12030D010 | D77: 0.0008275374 | E77: Multifondos | F77: RFLC | G77: BU | H77: Habitat | I77: 2.2785495e+10 | J77: 1 | K77: 18240 | L77: Banco de la Nacion | M77: 46174 | N77: 0018 | O77: 1033.7637 | P77: 18855849 | Q77: Financials | R77: Peru | S77: PE | AI77: rt | AJ77: rt | AK77: rt | AL77: rt | AM77: rt | AN77: rt | AO77: rt | AT77: rt | AU77: rt | AV77: rt | AW77: rt | AX77: rt | AZ77: NoCov | BA77: 0.65823103 | BB77: 0.11726488 | BC77: 0.0070569928
B78: 2220082PAB78 | C78: USP6680PAB78 | D78: 0.003348622 | E78: Multifondos | F78: RFLC | G78: BU | H78: Ex_Integra | I78: 7.7424621e+10 | J78: 3.4075 | K78: 71846.655 | M78: 46174 | N78: 2008 | O78: 1059.0167 | P78: 2.5926579e+08 | AI78: rt | AJ78: rt | AK78: rt | AL78: rt | AM78: rt | AN78: rt | AO78: rt | AT78: rt | AU78: rt | AV78: rt | AW78: rt | AX78: rt | AZ78: NoCov | BA78: 0.62163188 | BB78: 0.14542962 | BC78: 0.023025721
A79: 509401 | B79: 59509428AJ82 | C79: US279158AJ82 | D79: 9.8906039e-08 | E79: F1 | F79: RFIC | G79: BU | H79: Profuturo | I79: 4.856457e+09 | J79: 3.4075 | K79: 0.17 | L79: Ecopetrol S.A. | M79: 46174 | N79: 5094 | O79: 829.19671 | P79: 480.33293 | Q79: Energy | R79: Colombia | S79: CO | T79: Integrated Oil & Gas | U79: A | V79: 1 | W79: 4.9145451 | X79: 8.1681979 | Y79: 4.609375 | Z79: 41 | AA79: 26 | AB79: 33 | AC79: 4 | AD79: 12677105 | AE79: 418.89 | AF79: 5.9190111 | AG79: 7.4017041 | AH79: 5.9 | AI79: rt | AJ79: rt | AK79: rt | AL79: rt | AM79: rt | AN79: rt | AO79: rt | AP79: 2 | AQ79: 39 | AR79: 6.51 | AS79: 226.35 | AT79: rt | AU79: rt | AV79: rt | AW79: rt | AX79: rt | AY79: Strongly Misaligned | AZ79: Cov | BA79: 0.58036121 | BB79: 0.24170055 | BC79: 4.0920899e-07 | BD79: 4.0920899e-07 | BE79: 2.011076e-06 | BF79: 3.3425e-06 | BG79: 1.8861977e-06 | BH79: 2.6639505e-06 | BI79: 1.636836e-06 | BJ79: 0.00017141356 | BK79: 9.2624456e-05 | BL79: 5.1875854 | BM79: 8.1841799e-07
A80: 509401 | B80: 59509428AE95 | C80: US279158AE95 | D80: 0.013145951 | E80: F1 | F80: RFIC | G80: BU | H80: Habitat | I80: 1.8939189e+09 | J80: 3.4075 | K80: 7245.11 | L80: Ecopetrol S.A. | M80: 46174 | N80: 5094 | O80: 1008.4922 | P80: 24897366 | Q80: Energy | R80: Colombia | S80: CO | T80: Integrated Oil & Gas | U80: A | V80: 1 | W80: 4.9145451 | X80: 8.1681979 | Y80: 4.609375 | Z80: 41 | AA80: 26 | AB80: 33 | AC80: 4 | AD80: 12677105 | AE80: 418.89 | AF80: 5.9190111 | AG80: 7.4017041 | AH80: 5.9 | AI80: rt | AJ80: rt | AK80: rt | AL80: rt | AM80: rt | AN80: rt | AO80: rt | AP80: 2 | AQ80: 39 | AR80: 6.51 | AS80: 226.35 | AT80: rt | AU80: rt | AV80: rt | AW80: rt | AX80: rt | AY80: Strongly Misaligned | AZ80: Cov | BA80: 0.63778762 | BB80: 0.36085898 | BC80: 0.036429608 | BD80: 0.036429608 | BE80: 0.17903495 | BF80: 0.29756425 | BG80: 0.16791773 | BH80: 0.23715675 | BI80: 0.14571843 | BJ80: 15.259999 | BK80: 8.2458418 | BL80: 461821.97 | BM80: 0.072859217
A81: 200901 | B81: 22200911502A | C81: PEP70252M275 | D81: 1.3378285e-07 | E81: Multifondos | F81: RFLC | G81: BU | H81: Ex_Integra | I81: 7.7424621e+10 | J81: 1 | K81: 2 | L81: Luz del Sur S.A.A. | M81: 46174 | N81: 2009 | O81: 5179.0431 | P81: 10358.086 | Q81: Utilities | R81: Peru | S81: PE | T81: Utilities | AI81: rt | AJ81: rt | AK81: rt | AL81: rt | AM81: rt | AN81: rt | AO81: rt | AT81: rt | AU81: rt | AV81: rt | AW81: rt | AX81: rt | AZ81: NoCov | BA81: 0.62163188 | BB81: 0.14542962 | BC81: 9.1991469e-07
B82: 2220091VAC83 | C82: USP6411VAC83 | D82: 0.013066595 | E82: Multifondos | F82: RFLC | G82: BU | H82: Profuturo | I82: 2.1900418e+10 | J82: 1 | K82: 277613.39 | M82: 46174 | N82: 2009 | O82: 1030.8 | P82: 2.8616388e+08 | AI82: rt | AJ82: rt | AK82: rt | AL82: rt | AM82: rt | AN82: rt | AO82: rt | AT82: rt | AU82: rt | AV82: rt | AW82: rt | AX82: rt | AZ82: NoCov | BA82: 0.58409167 | BB82: 0.15915074 | BC82: 0.082102005
A83: 509401 | B83: 59509428AQ26 | C83: US279158AQ26 | D83: 3.1058245e-08 | E83: F2 | F83: RFIC | G83: BU | H83: Profuturo | I83: 1.3368958e+10 | J83: 3.4075 | K83: 0.15 | L83: Ecopetrol S.A. | M83: 46174 | N83: 5094 | O83: 812.35778 | P83: 415.21637 | Q83: Energy | R83: Colombia | S83: CO | T83: Integrated Oil & Gas | U83: A | V83: 1 | W83: 4.9145451 | X83: 8.1681979 | Y83: 4.609375 | Z83: 41 | AA83: 26 | AB83: 33 | AC83: 4 | AD83: 12677105 | AE83: 418.89 | AF83: 5.9190111 | AG83: 7.4017041 | AH83: 5.9 | AI83: rt | AJ83: rt | AK83: rt | AL83: rt | AM83: rt | AN83: rt | AO83: rt | AP83: 2 | AQ83: 39 | AR83: 6.51 | AS83: 226.35 | AT83: rt | AU83: rt | AV83: rt | AW83: rt | AX83: rt | AY83: Strongly Misaligned | AZ83: Cov | BA83: 0.57866161 | BB83: 0.40695246 | BC83: 7.63191e-08 | BD83: 7.63191e-08 | BE83: 3.7507365e-07 | BF83: 6.2338951e-07 | BG83: 3.5178335e-07 | BH83: 4.9683734e-07 | BI83: 3.052764e-07 | BJ83: 3.1969308e-05 | BK83: 1.7274828e-05 | BL83: 0.96750524 | BM83: 1.526382e-07
A84: 200901 | B84: 22200911807A | C84: PEP70252M317 | D84: 1.3898972e-07 | E84: Multifondos | F84: RFLC | G84: BU | H84: Ex_Integra | I84: 7.7424621e+10 | J84: 1 | K84: 2 | L84: Luz del Sur S.A.A. | M84: 46174 | N84: 2009 | O84: 5380.6131 | P84: 10761.226 | Q84: Utilities | R84: Peru | S84: PE | T84: Utilities | AI84: rt | AJ84: rt | AK84: rt | AL84: rt | AM84: rt | AN84: rt | AO84: rt | AT84: rt | AU84: rt | AV84: rt | AW84: rt | AX84: rt | AZ84: NoCov | BA84: 0.62163188 | BB84: 0.14542962 | BC84: 9.5571806e-07
B85: 1552782BAB48 | C85: USP1S81BAB48 | D85: 0.0015555885 | E85: F2 | F85: RFIC | G85: BU | H85: Ex_Integra | I85: 5.0823903e+10 | J85: 3.4075 | K85: 20939.65 | M85: 46174 | N85: 5278 | O85: 1108.0451 | P85: 79061079 | AI85: rt | AJ85: rt | AK85: rt | AL85: rt | AM85: rt | AN85: rt | AO85: rt | AT85: rt | AU85: rt | AV85: rt | AW85: rt | AX85: rt | AZ85: NoCov | BA85: 0.60589742 | BB85: 0.14204353 | BC85: 0.010951491
B86: 21015122401A | C86: PEP66450D098 | D86: 0.00046520296 | E86: Multifondos | F86: RFLC | G86: BU | H86: Habitat | I86: 2.2785495e+10 | J86: 3.4075 | K86: 3001.51 | M86: 46174 | N86: 0151 | O86: 1036.3949 | P86: 10599880 | AI86: rt | AJ86: rt | AK86: rt | AL86: rt | AM86: rt | AN86: rt | AO86: rt | AT86: rt | AU86: rt | AV86: rt | AW86: rt | AX86: rt | AZ86: NoCov | BA86: 0.65823103 | BB86: 0.11726488 | BC86: 0.0039671124
B87: 1552782GAA15 | C87: USP2000GAA15 | D87: 0.0016988644 | E87: F1 | F87: RFIC | G87: BU | H87: Prima | I87: 6.909728e+09 | J87: 3.4075 | K87: 3233 | M87: 46174 | N87: 5278 | O87: 1065.5605 | P87: 11738691 | AI87: rt | AJ87: rt | AK87: rt | AL87: rt | AM87: rt | AN87: rt | AO87: rt | AT87: rt | AU87: rt | AV87: rt | AW87: rt | AX87: rt | AZ87: NoCov | BA87: 0.56320494 | BB87: 0.28214925 | BC87: 0.0060211551
B88: 2220091VAC83 | C88: USP6411VAC83 | D88: 0.0067468031 | E88: Multifondos | F88: RFLC | G88: BU | H88: Ex_Integra | I88: 7.7424621e+10 | J88: 1 | K88: 506760.45 | M88: 46174 | N88: 2009 | O88: 1030.8 | P88: 5.2236867e+08 | AI88: rt | AJ88: rt | AK88: rt | AL88: rt | AM88: rt | AN88: rt | AO88: rt | AT88: rt | AU88: rt | AV88: rt | AW88: rt | AX88: rt | AZ88: NoCov | BA88: 0.62163188 | BB88: 0.14542962 | BC88: 0.04639222
A89: 509401 | B89: 59509428AS81 | C89: US279158AS81 | D89: 4.5086628e-07 | E89: F1 | F89: RFIC | G89: BU | H89: Habitat | I89: 1.8939189e+09 | J89: 3.4075 | K89: 0.22 | L89: Ecopetrol S.A. | M89: 46174 | N89: 5094 | O89: 1139.0705 | P89: 853.90416 | Q89: Energy | R89: Colombia | S89: CO | T89: Integrated Oil & Gas | U89: A | V89: 1 | W89: 4.9145451 | X89: 8.1681979 | Y89: 4.609375 | Z89: 41 | AA89: 26 | AB89: 33 | AC89: 4 | AD89: 12677105 | AE89: 418.89 | AF89: 5.9190111 | AG89: 7.4017041 | AH89: 5.9 | AI89: rt | AJ89: rt | AK89: rt | AL89: rt | AM89: rt | AN89: rt | AO89: rt | AP89: 2 | AQ89: 39 | AR89: 6.51 | AS89: 226.35 | AT89: rt | AU89: rt | AV89: rt | AW89: rt | AX89: rt | AY89: Strongly Misaligned | AZ89: Cov | BA89: 0.63778762 | BB89: 0.36085898 | BC89: 1.2494251e-06 | BD89: 1.2494251e-06 | BE89: 6.1403561e-06 | BF89: 1.0205552e-05 | BG89: 5.759069e-06 | BH89: 8.1337576e-06 | BI89: 4.9977005e-06 | BJ89: 0.00052337169 | BK89: 0.00028280738 | BL89: 15.839094 | BM89: 2.4988503e-06
A90: 527801 | B90: 1552782BAA64 | C90: USP1S81BAA64 | D90: 0.00038180498 | E90: Multifondos | F90: RFIC | G90: BU | H90: Prima | I90: 3.2738708e+10 | J90: 3.4075 | K90: 3398 | L90: BBVA Mexico, S.A., Institucion de Banca Multiple, Grupo Financiero BBVA Mexico | M90: 46174 | N90: 5278 | O90: 1079.5528 | P90: 12499802 | Q90: Financials | R90: Mexico | S90: MX | T90: Banks | U90: AA | V90: 0 | W90: 8.4489927 | X90: 5.8658712 | Y90: 4.8984375 | Z90: 13 | AA90: 54 | AB90: 33 | AC90: 4 | AD90: 249742 | AE90: 2.68 | AF90: 10 | AG90: 2.085084 | AH90: 7.5 | AI90: rt | AJ90: rt | AK90: rt | AL90: rt | AM90: rt | AN90: rt | AO90: rt | AP90: 4 | AQ90: 75 | AR90: 8.27 | AS90: 0.77 | AT90: rt | AU90: rt | AV90: rt | AW90: rt | AX90: rt | AY90: 1.5°C Aligned | AZ90: Cov | BA90: 0.62127201 | BB90: 0.46541892 | BC90: 0.00082034693 | BD90: 0 | BE90: 0.0069311052 | BF90: 0.0048120494 | BG90: 0.0040184182 | BH90: 0.0067842691 | BI90: 0.0032813877 | BJ90: 0.0021985298 | BK90: 0.00063166714 | BL90: 204.87508 | BM90: 0.0032813877
A91: 527801 | B91: 1552782BAA64 | C91: USP1S81BAA64 | D91: 0.00091505904 | E91: F1 | F91: RFIC | G91: BU | H91: Ex_Integra | I91: 1.3660104e+10 | J91: 3.4075 | K91: 3398 | L91: BBVA Mexico, S.A., Institucion de Banca Multiple, Grupo Financiero BBVA Mexico | M91: 46174 | N91: 5278 | O91: 1079.5528 | P91: 12499802 | Q91: Financials | R91: Mexico | S91: MX | T91: Banks | U91: AA | V91: 0 | W91: 8.4489927 | X91: 5.8658712 | Y91: 4.8984375 | Z91: 13 | AA91: 54 | AB91: 33 | AC91: 4 | AD91: 249742 | AE91: 2.68 | AF91: 10 | AG91: 2.085084 | AH91: 7.5 | AI91: rt | AJ91: rt | AK91: rt | AL91: rt | AM91: rt | AN91: rt | AO91: rt | AP91: 4 | AQ91: 75 | AR91: 8.27 | AS91: 0.77 | AT91: rt | AU91: rt | AV91: rt | AW91: rt | AX91: rt | AY91: 1.5°C Aligned | AZ91: Cov | BA91: 0.57964491 | BB91: 0.27812851 | BC91: 0.0032900584 | BD91: 0 | BE91: 0.02779768 | BF91: 0.019299059 | BG91: 0.016116146 | BH91: 0.027208783 | BI91: 0.013160234 | BJ91: 0.0088173566 | BK91: 0.002533345 | BL91: 821.66577 | BM91: 0.013160234
B92: 2220111KEA71 | C92: USP0161KEA71 | D92: 0.0050009157 | E92: Multifondos | F92: RFLC | G92: BU | H92: Ex_Integra | I92: 7.7424621e+10 | J92: 1 | K92: 369250.87 | M92: 46174 | N92: 2011 | O92: 1048.5933 | P92: 3.87194e+08 | AI92: rt | AJ92: rt | AK92: rt | AL92: rt | AM92: rt | AN92: rt | AO92: rt | AT92: rt | AU92: rt | AV92: rt | AW92: rt | AX92: rt | AZ92: NoCov | BA92: 0.62163188 | BB92: 0.14542962 | BC92: 0.034387187
A93: 015401 | B93: 21015422002A | C93: PEP66950D014 | D93: 0.0029522789 | E93: Multifondos | F93: RFLC | G93: BU | H93: Habitat | I93: 2.2785495e+10 | J93: 3.4075 | K93: 20603 | L93: Pacifico Compania de Seguros y Reaseguros | M93: 46174 | N93: 0154 | O93: 958.18536 | P93: 67269137 | Q93: Financials | R93: Peru | S93: PE | T93: Life & Health Insurance | AI93: rt | AJ93: rt | AK93: rt | AL93: rt | AM93: rt | AN93: rt | AO93: rt | AT93: rt | AU93: rt | AV93: rt | AW93: rt | AX93: rt | AZ93: NoCov | BA93: 0.65823103 | BB93: 0.11726488 | BC93: 0.025176157
B94: 2220292FAB50 | C94: USP0091FAB50 | D94: 0.0032019403 | E94: Multifondos | F94: RFLC | G94: BU | H94: Ex_Integra | I94: 7.7424621e+10 | J94: 3.4075 | K94: 71603.5 | M94: 46174 | N94: 2029 | O94: 1016.0667 | P94: 2.4790902e+08 | AI94: rt | AJ94: rt | AK94: rt | AL94: rt | AM94: rt | AN94: rt | AO94: rt | AT94: rt | AU94: rt | AV94: rt | AW94: rt | AX94: rt | AZ94: NoCov | BA94: 0.62163188 | BB94: 0.14542962 | BC94: 0.022017112
B95: 2220111KEA71 | C95: USP0161KEA71 | D95: 0.0085408893 | E95: Multifondos | F95: RFLC | G95: BU | H95: Profuturo | I95: 2.1900418e+10 | J95: 1 | K95: 178380.92 | M95: 46174 | N95: 2011 | O95: 1048.5933 | P95: 1.8704904e+08 | AI95: rt | AJ95: rt | AK95: rt | AL95: rt | AM95: rt | AN95: rt | AO95: rt | AT95: rt | AU95: rt | AV95: rt | AW95: rt | AX95: rt | AZ95: NoCov | BA95: 0.58409167 | BB95: 0.15915074 | BC95: 0.053665408
A96: 203001 | B96: 22203011211A | C96: PEP70101M506 | D96: 9.4036398e-07 | E96: Multifondos | F96: RFLC | G96: BU | H96: Ex_Integra | I96: 7.7424621e+10 | J96: 1 | K96: 14 | L96: Pluz Energia Peru, S.A.A. | M96: 46174 | N96: 2030 | O96: 5200.5231 | P96: 72807.324 | Q96: Utilities | R96: Peru | S96: PE | AI96: rt | AJ96: rt | AK96: rt | AL96: rt | AM96: rt | AN96: rt | AO96: rt | AT96: rt | AU96: rt | AV96: rt | AW96: rt | AX96: rt | AZ96: NoCov | BA96: 0.62163188 | BB96: 0.14542962 | BC96: 6.4661102e-06
B97: 1551112LAN29 | C97: US05968LAN29 | D97: 0.00093214153 | E97: F1 | F97: RFIC | G97: BU | H97: Ex_Integra | I97: 1.3660104e+10 | J97: 3.4075 | K97: 3493 | M97: 46174 | N97: 5111 | O97: 1069.7971 | P97: 12733150 | AI97: rt | AJ97: rt | AK97: rt | AL97: rt | AM97: rt | AN97: rt | AO97: rt | AT97: rt | AU97: rt | AV97: rt | AW97: rt | AX97: rt | AZ97: NoCov | BA97: 0.57964491 | BB97: 0.30151641 | BC97: 0.0030915118
B98: 1551112LAN29 | C98: US05968LAN29 | D98: 0.00027441903 | E98: F2 | F98: RFIC | G98: BU | H98: Ex_Integra | I98: 5.0823903e+10 | J98: 3.4075 | K98: 3826 | M98: 46174 | N98: 5111 | O98: 1069.7971 | P98: 13947046 | AI98: rt | AJ98: rt | AK98: rt | AL98: rt | AM98: rt | AN98: rt | AO98: rt | AT98: rt | AU98: rt | AV98: rt | AW98: rt | AX98: rt | AZ98: NoCov | BA98: 0.60589742 | BB98: 0.14204353 | BC98: 0.0019319361
B99: 1551192MAF51 | C99: USP1400MAF51 | D99: 0.00052205618 | E99: Multifondos | F99: RFIC | G99: BU | H99: Integra | I99: 3.9311487e+10 | J99: 3.4075 | K99: 6000 | M99: 46174 | N99: 5119 | O99: 1003.8056 | P99: 20522805 | AI99: rt | AJ99: rt | AK99: rt | AL99: rt | AM99: rt | AN99: rt | AO99: rt | AT99: rt | AU99: rt | AV99: rt | AW99: rt | AX99: rt | AZ99: NoCov | BA99: 0.59538531 | BB99: 0.13474712 | BC99: 0.0038743401
B100: 1552782BAB48 | C100: USP1S81BAB48 | D100: 0.0024149114 | E100: Multifondos | F100: RFIC | G100: BU | H100: Prima | I100: 3.2738708e+10 | J100: 3.4075 | K100: 20939.53 | M100: 46174 | N100: 5278 | O100: 1108.0451 | P100: 79060626 | AI100: rt | AJ100: rt | AK100: rt | AL100: rt | AM100: rt | AN100: rt | AO100: rt | AT100: rt | AU100: rt | AV100: rt | AW100: rt | AX100: rt | AZ100: NoCov | BA100: 0.62127201 | BB100: 0.1558531 | BC100: 0.015494793
A101: 203001 | B101: 22203011312A | C101: PEP70101M530 | D101: 2.5594864e-07 | E101: Multifondos | F101: RFLC | G101: BU | H101: Ex_Integra | I101: 7.7424621e+10 | J101: 1 | K101: 4 | L101: Pluz Energia Peru, S.A.A. | M101: 46174 | N101: 2030 | O101: 4954.1816 | P101: 19816.726 | Q101: Utilities | R101: Peru | S101: PE | AI101: rt | AJ101: rt | AK101: rt | AL101: rt | AM101: rt | AN101: rt | AO101: rt | AT101: rt | AU101: rt | AV101: rt | AW101: rt | AX101: rt | AZ101: NoCov | BA101: 0.62163188 | BB101: 0.14542962 | BC101: 1.7599484e-06
A102: 203001 | B102: 22203012105A | C102: PEP70101M720 | D102: 2.622088e-07 | E102: Multifondos | F102: RFLC | G102: BU | H102: Ex_Integra | I102: 7.7424621e+10 | J102: 1 | K102: 20 | L102: Pluz Energia Peru, S.A.A. | M102: 46174 | N102: 2030 | O102: 1015.0708 | P102: 20301.417 | Q102: Utilities | R102: Peru | S102: PE | AI102: rt | AJ102: rt | AK102: rt | AL102: rt | AM102: rt | AN102: rt | AO102: rt | AT102: rt | AU102: rt | AV102: rt | AW102: rt | AX102: rt | AZ102: NoCov | BA102: 0.62163188 | BB102: 0.14542962 | BC102: 1.8029944e-06
...

Sheet BD1_S
A1: SBS | B1: ISIN | C1: Weight | D1: Fondo | E1: assetclass | F1: Strategy | G1: Afp | H1: AUM | I1: Tipo | J1: Q | K1: Nombre | L1: Fecha | M1: codEmisor | N1: Precio | O1: Inversión | P1: Cov? | R1: NUEVA COBERTURA
A2: 15515123CH47 | B2: USP32133CH47 | C2: 0.0012602963 | D2: F1 | E2: RFIC | F2: BU | G2: Ex_Integra | H2: 1.3660104e+10 | I2: 3.6555 | J2: 4675.0074 | L2: 46174 | M2: 5151 | N2: 1080.7083 | O2: 18468754 | P2: =+IFERROR(IF(OR(B2="PEP795509FD5",B2="CVL79560FI39",B2="CVL79590GA30")=FALSE,IF(F2="SOB","Cov",INDEX('ANALISIS BD'!AZ:AZ,MATCH(BD1_S!B2,'ANALISIS BD'!C:C,0))),"NoCov"),"NoCov") -> NoCov | R2: Integra | V2: Ex_Integra
A3: 15515123CH47 | B3: USP32133CH47 | C3: 0.0032138989 | D3: F1 | E3: RFIC | F3: BU | G3: Integra | H3: 7.9289969e+09 | I3: 3.6555 | J3: 6920 | L3: 46174 | M3: 5151 | N3: 1080.7083 | O3: 27337663 | P3: =+IFERROR(IF(OR(B3="PEP795509FD5",B3="CVL79560FI39",B3="CVL79590GA30")=FALSE,IF(F3="SOB","Cov",INDEX('ANALISIS BD'!AZ:AZ,MATCH(BD1_S!B3,'ANALISIS BD'!C:C,0))),"NoCov"),"NoCov") -> NoCov | R3: F1 | V3: F1
A4: 15515123CH47 | B4: USP32133CH47 | C4: 3.9640842e-09 | D4: F1 | E4: RFIC | F4: BU | G4: Prima | H4: 6.909728e+09 | I4: 3.6555 | J4: 0.0074380562 | L4: 46174 | M4: 5151 | N4: 1080.7083 | O4: 29.384259 | P4: =+IFERROR(IF(OR(B4="PEP795509FD5",B4="CVL79560FI39",B4="CVL79590GA30")=FALSE,IF(F4="SOB","Cov",INDEX('ANALISIS BD'!AZ:AZ,MATCH(BD1_S!B4,'ANALISIS BD'!C:C,0))),"NoCov"),"NoCov") -> NoCov | S4: Cov | T4: =+SUMIFS($C:$C,$D:$D,$R$3,$G:$G,$R$2,$P:$P,S4) -> 0.7151317 | W4: Cov | X4: =+SUMIFS($C:$C,$D:$D,$R$3,$G:$G,$V$2,$P:$P,W4) -> 0.67478395
A5: 011000112B29 | B5: PEP01000C5F6 | C5: 0.00024750793 | D5: Multifondos | E5: RFLG | F5: SOB | G5: Ex_Integra | H5: 7.7424621e+10 | I5: 1 | J5: 17821 | K5: Gobierno Central | L5: 46174 | M5: 1000 | N5: 1075.3161 | O5: 19163208 | P5: =+IFERROR(IF(OR(B5="PEP795509FD5",B5="CVL79560FI39",B5="CVL79590GA30")=FALSE,IF(F5="SOB","Cov",INDEX('ANALISIS BD'!AZ:AZ,MATCH(BD1_S!B5,'ANALISIS BD'!C:C,0))),"NoCov"),"NoCov") -> Cov | S5: NoCov | T5: =+SUMIFS($C:$C,$D:$D,$R$3,$G:$G,$R$2,$P:$P,S5) -> 0.2702173 | W5: NoCov | X5: =+SUMIFS($C:$C,$D:$D,$R$3,$G:$G,$V$2,$P:$P,W5) -> 0.30151641
A6: 5270772F2269 | B6: LU0727122698 | C6: 0.0012256398 | D6: F1 | E6: RFIG | F6: TD | G6: Ex_Integra | H6: 1.3660104e+10 | I6: 3.6555 | J6: 144383.99 | K6: Franklin Templeton - Global Convertibles | L6: 46174 | M6: 7077 | N6: 34.03 | O6: 17960887 | P6: =+IFERROR(IF(OR(B6="PEP795509FD5",B6="CVL79560FI39",B6="CVL79590GA30")=FALSE,IF(F6="SOB","Cov",INDEX('ANALISIS BD'!AZ:AZ,MATCH(BD1_S!B6,'ANALISIS BD'!C:C,0))),"NoCov"),"NoCov") -> Cov | S6: Total | T6: =+T4+T5 -> 0.985349 | W6: Total | X6: =+X4+X5 -> 0.97630036
A7: 011000112B29 | B7: PEP01000C5F6 | C7: 0.00024550127 | D7: Multifondos | E7: RFLG | F7: SOB | G7: Profuturo | H7: 2.1900418e+10 | I7: 1 | J7: 5000 | K7: Gobierno Central | L7: 46174 | M7: 1000 | N7: 1075.3161 | O7: 5376580.4 | P7: =+IFERROR(IF(OR(B7="PEP795509FD5",B7="CVL79560FI39",B7="CVL79590GA30")=FALSE,IF(F7="SOB","Cov",INDEX('ANALISIS BD'!AZ:AZ,MATCH(BD1_S!B7,'ANALISIS BD'!C:C,0))),"NoCov"),"NoCov") -> Cov
A8: 011000112F42 | B8: PEP01000C4L7 | C8: 0.002826684 | D8: Multifondos | E8: RFLG | F8: SOB | G8: Ex_Integra | H8: 7.7424621e+10 | I8: 1 | J8: 208404 | K8: Gobierno Central | L8: 46174 | M8: 1000 | N8: 1050.1475 | O8: 2.1885493e+08 | P8: =+IFERROR(IF(OR(B8="PEP795509FD5",B8="CVL79560FI39",B8="CVL79590GA30")=FALSE,IF(F8="SOB","Cov",INDEX('ANALISIS BD'!AZ:AZ,MATCH(BD1_S!B8,'ANALISIS BD'!C:C,0))),"NoCov"),"NoCov") -> Cov | R8: F2 | V8: F2
A9: 011000112F42 | B9: PEP01000C4L7 | C9: 0.0041587425 | D9: Multifondos | E9: RFLG | F9: SOB | G9: Habitat | H9: 2.2785495e+10 | I9: 1 | J9: 90234 | K9: Gobierno Central | L9: 46174 | M9: 1000 | N9: 1050.1475 | O9: 94759007 | P9: =+IFERROR(IF(OR(B9="PEP795509FD5",B9="CVL79560FI39",B9="CVL79590GA30")=FALSE,IF(F9="SOB","Cov",INDEX('ANALISIS BD'!AZ:AZ,MATCH(BD1_S!B9,'ANALISIS BD'!C:C,0))),"NoCov"),"NoCov") -> Cov | S9: Cov | T9: =+SUMIFS($C:$C,$D:$D,$R$8,$G:$G,$R$2,$P:$P,S9) -> 0.70685114 | W9: Cov | X9: =+SUMIFS($C:$C,$D:$D,$R$8,$G:$G,$V$2,$P:$P,W9) -> 0.69051509
A10: 011000112F55 | B10: PEP01000C4S2 | C10: 0.0012107429 | D10: Multifondos | E10: RFLG | F10: SOB | G10: Ex_Integra | H10: 7.7424621e+10 | I10: 1 | J10: 88895 | K10: Gobierno Central | L10: 46174 | M10: 1000 | N10: 1054.5172 | O10: 93741307 | P10: =+IFERROR(IF(OR(B10="PEP795509FD5",B10="CVL79560FI39",B10="CVL79590GA30")=FALSE,IF(F10="SOB","Cov",INDEX('ANALISIS BD'!AZ:AZ,MATCH(BD1_S!B10,'ANALISIS BD'!C:C,0))),"NoCov"),"NoCov") -> Cov | S10: NoCov | T10: =+SUMIFS($C:$C,$D:$D,$R$8,$G:$G,$R$2,$P:$P,S10) -> 0.10561105 | W10: NoCov | X10: =+SUMIFS($C:$C,$D:$D,$R$8,$G:$G,$V$2,$P:$P,W10) -> 0.14204353
A11: 15515123CH47 | B11: USP32133CH47 | C11: 0.00354492 | D11: F1 | E11: RFIC | F11: BU | G11: Profuturo | H11: 4.856457e+09 | I11: 3.6555 | J11: 4675 | L11: 46174 | M11: 5151 | N11: 1080.7083 | O11: 18468725 | P11: =+IFERROR(IF(OR(B11="PEP795509FD5",B11="CVL79560FI39",B11="CVL79590GA30")=FALSE,IF(F11="SOB","Cov",INDEX('ANALISIS BD'!AZ:AZ,MATCH(BD1_S!B11,'ANALISIS BD'!C:C,0))),"NoCov"),"NoCov") -> NoCov | S11: Total | T11: =+T9+T10 -> 0.81246219 | W11: Total | X11: =+X9+X10 -> 0.83255862
A12: 0840002CNC19 | B12: US91282CNC19 | C12: 0.00065509686 | D12: F2 | E12: RFIG | F12: SOB | G12: Ex_Integra | H12: 5.0823903e+10 | I12: 3.6555 | J12: 98506.37 | K12: Gobierno de los Estados Unidos | L12: 46174 | M12: 4000 | N12: 99.191249 | O12: 35717780 | P12: =+IFERROR(IF(OR(B12="PEP795509FD5",B12="CVL79560FI39",B12="CVL79590GA30")=FALSE,IF(F12="SOB","Cov",INDEX('ANALISIS BD'!AZ:AZ,MATCH(BD1_S!B12,'ANALISIS BD'!C:C,0))),"NoCov"),"NoCov") -> Cov
A13: 0840038TF238 | B13: BRSTNCNTF238 | C13: 0.026580201 | D13: F1 | E13: RFIG | F13: SOB | G13: Habitat | H13: 1.8939189e+09 | I13: 0.6528844 | J13: 95257.93 | K13: Gobierno de Brasil | L13: 46174 | M13: 4003 | N13: 801.5185 | O13: 49848372 | P13: =+IFERROR(IF(OR(B13="PEP795509FD5",B13="CVL79560FI39",B13="CVL79590GA30")=FALSE,IF(F13="SOB","Cov",INDEX('ANALISIS BD'!AZ:AZ,MATCH(BD1_S!B13,'ANALISIS BD'!C:C,0))),"NoCov"),"NoCov") -> Cov | R13: F3 | V13: F3
A14: 5271112EG102 | B14: US46435G1022 | C14: 0.002125755 | D14: F1 | E14: RFIG | F14: TD | G14: Ex_Integra | H14: 1.3660104e+10 | I14: 3.6555 | J14: 70000 | K14: BlackRock - iShares Convertible Bond ETF | L14: 46174 | M14: 7111 | N14: 121.74 | O14: 31151440 | P14: =+IFERROR(IF(OR(B14="PEP795509FD5",B14="CVL79560FI39",B14="CVL79590GA30")=FALSE,IF(F14="SOB","Cov",INDEX('ANALISIS BD'!AZ:AZ,MATCH(BD1_S!B14,'ANALISIS BD'!C:C,0))),"NoCov"),"NoCov") -> Cov | S14: Cov | T14: =+SUMIFS($C:$C,$D:$D,$R$13,$G:$G,$R$2,$P:$P,S14) -> 0.77818039 | W14: Cov | X14: =+SUMIFS($C:$C,$D:$D,$R$13,$G:$G,$V$2,$P:$P,W14) -> 0.78545601
A15: 011000112B29 | B15: PEP01000C5F6 | C15: 0.00042111092 | D15: Multifondos | E15: RFLG | F15: SOB | G15: Prima | H15: 3.2738708e+10 | I15: 1 | J15: 12821 | K15: Gobierno Central | L15: 46174 | M15: 1000 | N15: 1075.3161 | O15: 13786627 | P15: =+IFERROR(IF(OR(B15="PEP795509FD5",B15="CVL79560FI39",B15="CVL79590GA30")=FALSE,IF(F15="SOB","Cov",INDEX('ANALISIS BD'!AZ:AZ,MATCH(BD1_S!B15,'ANALISIS BD'!C:C,0))),"NoCov"),"NoCov") -> Cov | S15: NoCov | T15: =+SUMIFS($C:$C,$D:$D,$R$13,$G:$G,$R$2,$P:$P,S15) -> 0.060288595 | W15: NoCov | X15: =+SUMIFS($C:$C,$D:$D,$R$13,$G:$G,$V$2,$P:$P,W15) -> 0.070219065
A16: 011000112G32 | B16: PEP01000C5E9 | C16: 0.0057924386 | D16: Multifondos | E16: RFLG | F16: SOB | G16: Ex_Integra | H16: 7.7424621e+10 | I16: 1 | J16: 405241.28 | K16: Gobierno Central | L16: 46174 | M16: 1000 | N16: 1106.6922 | O16: 4.4847736e+08 | P16: =+IFERROR(IF(OR(B16="PEP795509FD5",B16="CVL79560FI39",B16="CVL79590GA30")=FALSE,IF(F16="SOB","Cov",INDEX('ANALISIS BD'!AZ:AZ,MATCH(BD1_S!B16,'ANALISIS BD'!C:C,0))),"NoCov"),"NoCov") -> Cov | S16: Total | T16: =+T14+T15 -> 0.83846899 | W16: Total | X16: =+X14+X15 -> 0.85567508
A17: 011000112B29 | B17: PEP01000C5F6 | C17: 0.00024618363 | D17: Multifondos | E17: RFLG | F17: SOB | G17: Integra | H17: 3.9311487e+10 | I17: 1 | J17: 9000 | K17: Gobierno Central | L17: 46174 | M17: 1000 | N17: 1075.3161 | O17: 9677844.6 | P17: =+IFERROR(IF(OR(B17="PEP795509FD5",B17="CVL79560FI39",B17="CVL79590GA30")=FALSE,IF(F17="SOB","Cov",INDEX('ANALISIS BD'!AZ:AZ,MATCH(BD1_S!B17,'ANALISIS BD'!C:C,0))),"NoCov"),"NoCov") -> Cov
A18: 011000112G32 | B18: PEP01000C5E9 | C18: 0.0048649347 | D18: Multifondos | E18: RFLG | F18: SOB | G18: Profuturo | H18: 2.1900418e+10 | I18: 1 | J18: 96272.57 | K18: Gobierno Central | L18: 46174 | M18: 1000 | N18: 1106.6922 | O18: 1.065441e+08 | P18: =+IFERROR(IF(OR(B18="PEP795509FD5",B18="CVL79560FI39",B18="CVL79590GA30")=FALSE,IF(F18="SOB","Cov",INDEX('ANALISIS BD'!AZ:AZ,MATCH(BD1_S!B18,'ANALISIS BD'!C:C,0))),"NoCov"),"NoCov") -> Cov | R18: Multifondos | V18: Multifondos
A19: 084003411726 | B19: XS3344411726 | C19: 0.0033272413 | D19: F1 | E19: RFIG | F19: SOB | G19: Ex_Integra | H19: 1.3660104e+10 | I19: 4.4023187 | J19: 11425.27 | K19: Gobierno de Brasil | L19: 46174 | M19: 4003 | N19: 1022.28 | O19: 51418312 | P19: =+IFERROR(IF(OR(B19="PEP795509FD5",B19="CVL79560FI39",B19="CVL79590GA30")=FALSE,IF(F19="SOB","Cov",INDEX('ANALISIS BD'!AZ:AZ,MATCH(BD1_S!B19,'ANALISIS BD'!C:C,0))),"NoCov"),"NoCov") -> Cov | S19: Cov | T19: =+SUMIFS($C:$C,$D:$D,$R$18,$G:$G,$R$2,$P:$P,S19) -> 0.71491802 | W19: Cov | X19: =+SUMIFS($C:$C,$D:$D,$R$18,$G:$G,$V$2,$P:$P,W19) -> 0.70360789
A20: 011000112G33 | B20: PEP01000C5I0 | C20: 0.019381297 | D20: Multifondos | E20: RFLG | F20: SOB | G20: Ex_Integra | H20: 7.7424621e+10 | I20: 1 | J20: 1307394.5 | K20: Gobierno Central | L20: 46174 | M20: 1000 | N20: 1147.7711 | O20: 1.5005896e+09 | P20: =+IFERROR(IF(OR(B20="PEP795509FD5",B20="CVL79560FI39",B20="CVL79590GA30")=FALSE,IF(F20="SOB","Cov",INDEX('ANALISIS BD'!AZ:AZ,MATCH(BD1_S!B20,'ANALISIS BD'!C:C,0))),"NoCov"),"NoCov") -> Cov | S20: NoCov | T20: =+SUMIFS($C:$C,$D:$D,$R$18,$G:$G,$R$2,$P:$P,S20) -> 0.13474712 | W20: NoCov | X20: =+SUMIFS($C:$C,$D:$D,$R$18,$G:$G,$V$2,$P:$P,W20) -> 0.14542962
A21: 011000112F55 | B21: PEP01000C4S2 | C21: 0.0020174463 | D21: Multifondos | E21: RFLG | F21: SOB | G21: Habitat | H21: 2.2785495e+10 | I21: 1 | J21: 43592 | K21: Gobierno Central | L21: 46174 | M21: 1000 | N21: 1054.5172 | O21: 45968514 | P21: =+IFERROR(IF(OR(B21="PEP795509FD5",B21="CVL79560FI39",B21="CVL79590GA30")=FALSE,IF(F21="SOB","Cov",INDEX('ANALISIS BD'!AZ:AZ,MATCH(BD1_S!B21,'ANALISIS BD'!C:C,0))),"NoCov"),"NoCov") -> Cov | S21: Total | T21: =+T19+T20 -> 0.84966514 | W21: Total | X21: =+X19+X20 -> 0.84903751
A22: 5270772F2269 | B22: LU0727122698 | C22: 0.0088400657 | D22: F1 | E22: RFIG | F22: TD | G22: Habitat | H22: 1.8939189e+09 | I22: 3.6555 | J22: 144383.99 | K22: Franklin Templeton - Global Convertibles | L22: 46174 | M22: 7077 | N22: 34.03 | O22: 17960887 | P22: =+IFERROR(IF(OR(B22="PEP795509FD5",B22="CVL79560FI39",B22="CVL79590GA30")=FALSE,IF(F22="SOB","Cov",INDEX('ANALISIS BD'!AZ:AZ,MATCH(BD1_S!B22,'ANALISIS BD'!C:C,0))),"NoCov"),"NoCov") -> Cov
A23: 1551512PAC05 | B23: US05890PAC05 | C23: 0.0038776307 | D23: F1 | E23: RFIC | F23: BU | G23: Ex_Integra | H23: 1.3660104e+10 | I23: 3.6555 | J23: 14039 | L23: 46174 | M23: 5151 | N23: 1107.2569 | O23: 56823944 | P23: =+IFERROR(IF(OR(B23="PEP795509FD5",B23="CVL79560FI39",B23="CVL79590GA30")=FALSE,IF(F23="SOB","Cov",INDEX('ANALISIS BD'!AZ:AZ,MATCH(BD1_S!B23,'ANALISIS BD'!C:C,0))),"NoCov"),"NoCov") -> NoCov
A24: 011000112G34 | B24: PEP01000C5G4 | C24: 0.023844341 | D24: Multifondos | E24: RFLG | F24: SOB | G24: Ex_Integra | H24: 7.7424621e+10 | I24: 1 | J24: 1851516.5 | K24: Gobierno Central | L24: 46174 | M24: 1000 | N24: 997.09565 | O24: 1.8461391e+09 | P24: =+IFERROR(IF(OR(B24="PEP795509FD5",B24="CVL79560FI39",B24="CVL79590GA30")=FALSE,IF(F24="SOB","Cov",INDEX('ANALISIS BD'!AZ:AZ,MATCH(BD1_S!B24,'ANALISIS BD'!C:C,0))),"NoCov"),"NoCov") -> Cov
A25: 5271112EG102 | B25: US46435G1022 | C25: 0.005979263 | D25: F1 | E25: RFIG | F25: TD | G25: Profuturo | H25: 4.856457e+09 | I25: 3.6555 | J25: 70000 | K25: BlackRock - iShares Convertible Bond ETF | L25: 46174 | M25: 7111 | N25: 121.74 | O25: 31151440 | P25: =+IFERROR(IF(OR(B25="PEP795509FD5",B25="CVL79560FI39",B25="CVL79590GA30")=FALSE,IF(F25="SOB","Cov",INDEX('ANALISIS BD'!AZ:AZ,MATCH(BD1_S!B25,'ANALISIS BD'!C:C,0))),"NoCov"),"NoCov") -> Cov
A26: 011000112F42 | B26: PEP01000C4L7 | C26: 0.0037904956 | D26: Multifondos | E26: RFLG | F26: SOB | G26: Prima | H26: 3.2738708e+10 | I26: 1 | J26: 118170 | K26: Gobierno Central | L26: 46174 | M26: 1000 | N26: 1050.1475 | O26: 1.2409593e+08 | P26: =+IFERROR(IF(OR(B26="PEP795509FD5",B26="CVL79560FI39",B26="CVL79590GA30")=FALSE,IF(F26="SOB","Cov",INDEX('ANALISIS BD'!AZ:AZ,MATCH(BD1_S!B26,'ANALISIS BD'!C:C,0))),"NoCov"),"NoCov") -> Cov
A27: 5273932EA359 | B27: US78464A3591 | C27: 0.0091805964 | D27: F2 | E27: RFIG | F27: TD | G27: Ex_Integra | H27: 5.0823903e+10 | I27: 3.6555 | J27: 1270000 | K27: SSGA - Bloomberg Barclays Convertible Securities | L27: 46174 | M27: 7393 | N27: 107.82 | O27: 5.0055273e+08 | P27: =+IFERROR(IF(OR(B27="PEP795509FD5",B27="CVL79560FI39",B27="CVL79590GA30")=FALSE,IF(F27="SOB","Cov",INDEX('ANALISIS BD'!AZ:AZ,MATCH(BD1_S!B27,'ANALISIS BD'!C:C,0))),"NoCov"),"NoCov") -> Cov
A28: 0840002CNC19 | B28: US91282CNC19 | C28: 0.001470959 | D28: F2 | E28: RFIG | F28: SOB | G28: Prima | H28: 2.2634608e+10 | I28: 3.6555 | J28: 98506.37 | K28: Gobierno de los Estados Unidos | L28: 46174 | M28: 4000 | N28: 99.191249 | O28: 35717780 | P28: =+IFERROR(IF(OR(B28="PEP795509FD5",B28="CVL79560FI39",B28="CVL79590GA30")=FALSE,IF(F28="SOB","Cov",INDEX('ANALISIS BD'!AZ:AZ,MATCH(BD1_S!B28,'ANALISIS BD'!C:C,0))),"NoCov"),"NoCov") -> Cov
A29: 011000112G35 | B29: PEP01000C5K6 | C29: 0.029283838 | D29: Multifondos | E29: RFLG | F29: SOB | G29: Ex_Integra | H29: 7.7424621e+10 | I29: 1 | J29: 2102557.4 | K29: Gobierno Central | L29: 46174 | M29: 1000 | N29: 1078.3487 | O29: 2.26729e+09 | P29: =+IFERROR(IF(OR(B29="PEP795509FD5",B29="CVL79560FI39",B29="CVL79590GA30")=FALSE,IF(F29="SOB","Cov",INDEX('ANALISIS BD'!AZ:AZ,MATCH(BD1_S!B29,'ANALISIS BD'!C:C,0))),"NoCov"),"NoCov") -> Cov
A30: 011000112G37 | B30: PEP01000C2Z1 | C30: 0.042283942 | D30: Multifondos | E30: RFLG | F30: SOB | G30: Ex_Integra | H30: 7.7424621e+10 | I30: 1 | J30: 3116234.9 | K30: Gobierno Central | L30: 46174 | M30: 1000 | N30: 1050.5685 | O30: 3.2738182e+09 | P30: =+IFERROR(IF(OR(B30="PEP795509FD5",B30="CVL79560FI39",B30="CVL79590GA30")=FALSE,IF(F30="SOB","Cov",INDEX('ANALISIS BD'!AZ:AZ,MATCH(BD1_S!B30,'ANALISIS BD'!C:C,0))),"NoCov"),"NoCov") -> Cov
A31: 011000112G33 | B31: PEP01000C5I0 | C31: 0.020749837 | D31: Multifondos | E31: RFLG | F31: SOB | G31: Profuturo | H31: 2.1900418e+10 | I31: 1 | J31: 395923.98 | K31: Gobierno Central | L31: 46174 | M31: 1000 | N31: 1147.7711 | O31: 4.5443009e+08 | P31: =+IFERROR(IF(OR(B31="PEP795509FD5",B31="CVL79560FI39",B31="CVL79590GA30")=FALSE,IF(F31="SOB","Cov",INDEX('ANALISIS BD'!AZ:AZ,MATCH(BD1_S!B31,'ANALISIS BD'!C:C,0))),"NoCov"),"NoCov") -> Cov
A32: 1551192MAD04 | B32: USP1400MAD04 | C32: 0.0086965016 | D32: F1 | E32: RFIC | F32: BU | G32: Ex_Integra | H32: 1.3660104e+10 | I32: 3.6555 | J32: 33732.94 | L32: 46174 | M32: 5119 | N32: 1033.4953 | O32: 1.274411e+08 | P32: =+IFERROR(IF(OR(B32="PEP795509FD5",B32="CVL79560FI39",B32="CVL79590GA30")=FALSE,IF(F32="SOB","Cov",INDEX('ANALISIS BD'!AZ:AZ,MATCH(BD1_S!B32,'ANALISIS BD'!C:C,0))),"NoCov"),"NoCov") -> NoCov
A33: 011000112F55 | B33: PEP01000C4S2 | C33: 0.0041765993 | D33: Multifondos | E33: RFLG | F33: SOB | G33: Integra | H33: 3.9311487e+10 | I33: 1 | J33: 155700 | K33: Gobierno Central | L33: 46174 | M33: 1000 | N33: 1054.5172 | O33: 1.6418833e+08 | P33: =+IFERROR(IF(OR(B33="PEP795509FD5",B33="CVL79560FI39",B33="CVL79590GA30")=FALSE,IF(F33="SOB","Cov",INDEX('ANALISIS BD'!AZ:AZ,MATCH(BD1_S!B33,'ANALISIS BD'!C:C,0))),"NoCov"),"NoCov") -> Cov
A34: 084003411726 | B34: XS3344411726 | C34: 0.00089427335 | D34: F2 | E34: RFIG | F34: SOB | G34: Ex_Integra | H34: 5.0823903e+10 | I34: 4.4023187 | J34: 11425.27 | K34: Gobierno de Brasil | L34: 46174 | M34: 4003 | N34: 1022.28 | O34: 51418312 | P34: =+IFERROR(IF(OR(B34="PEP795509FD5",B34="CVL79560FI39",B34="CVL79590GA30")=FALSE,IF(F34="SOB","Cov",INDEX('ANALISIS BD'!AZ:AZ,MATCH(BD1_S!B34,'ANALISIS BD'!C:C,0))),"NoCov"),"NoCov") -> Cov
A35: 011000112G32 | B35: PEP01000C5E9 | C35: 0.014696076 | D35: Multifondos | E35: RFLG | F35: SOB | G35: Habitat | H35: 2.2785495e+10 | I35: 1 | J35: 302574.98 | K35: Gobierno Central | L35: 46174 | M35: 1000 | N35: 1106.6922 | O35: 3.3485737e+08 | P35: =+IFERROR(IF(OR(B35="PEP795509FD5",B35="CVL79560FI39",B35="CVL79590GA30")=FALSE,IF(F35="SOB","Cov",INDEX('ANALISIS BD'!AZ:AZ,MATCH(BD1_S!B35,'ANALISIS BD'!C:C,0))),"NoCov"),"NoCov") -> Cov
A36: 5273932EA359 | B36: US78464A3591 | C36: 0.0051941226 | D36: F2 | E36: RFIG | F36: TD | G36: Prima | H36: 2.2634608e+10 | I36: 3.6555 | J36: 320000 | K36: SSGA - Bloomberg Barclays Convertible Securities | L36: 46174 | M36: 7393 | N36: 107.82 | O36: 1.2612352e+08 | P36: =+IFERROR(IF(OR(B36="PEP795509FD5",B36="CVL79560FI39",B36="CVL79590GA30")=FALSE,IF(F36="SOB","Cov",INDEX('ANALISIS BD'!AZ:AZ,MATCH(BD1_S!B36,'ANALISIS BD'!C:C,0))),"NoCov"),"NoCov") -> Cov
A37: 011000112G39 | B37: PEP01000C5J8 | C37: 0.036737902 | D37: Multifondos | E37: RFLG | F37: SOB | G37: Ex_Integra | H37: 7.7424621e+10 | I37: 1 | J37: 2582158.4 | K37: Gobierno Central | L37: 46174 | M37: 1000 | N37: 1101.5661 | O37: 2.8444181e+09 | P37: =+IFERROR(IF(OR(B37="PEP795509FD5",B37="CVL79560FI39",B37="CVL79590GA30")=FALSE,IF(F37="SOB","Cov",INDEX('ANALISIS BD'!AZ:AZ,MATCH(BD1_S!B37,'ANALISIS BD'!C:C,0))),"NoCov"),"NoCov") -> Cov
A38: 011000112F55 | B38: PEP01000C4S2 | C38: 0.0014592144 | D38: Multifondos | E38: RFLG | F38: SOB | G38: Prima | H38: 3.2738708e+10 | I38: 1 | J38: 45303 | K38: Gobierno Central | L38: 46174 | M38: 1000 | N38: 1054.5172 | O38: 47772793 | P38: =+IFERROR(IF(OR(B38="PEP795509FD5",B38="CVL79560FI39",B38="CVL79590GA30")=FALSE,IF(F38="SOB","Cov",INDEX('ANALISIS BD'!AZ:AZ,MATCH(BD1_S!B38,'ANALISIS BD'!C:C,0))),"NoCov"),"NoCov") -> Cov
A39: 011000112G40 | B39: PEP01000C5H2 | C39: 0.022941055 | D39: Multifondos | E39: RFLG | F39: SOB | G39: Ex_Integra | H39: 7.7424621e+10 | I39: 1 | J39: 1992704.5 | K39: Gobierno Central | L39: 46174 | M39: 1000 | N39: 891.35269 | O39: 1.7762025e+09 | P39: =+IFERROR(IF(OR(B39="PEP795509FD5",B39="CVL79560FI39",B39="CVL79590GA30")=FALSE,IF(F39="SOB","Cov",INDEX('ANALISIS BD'!AZ:AZ,MATCH(BD1_S!B39,'ANALISIS BD'!C:C,0))),"NoCov"),"NoCov") -> Cov
A40: 0840038TF238 | B40: BRSTNCNTF238 | C40: 0.053773139 | D40: F1 | E40: RFIG | F40: SOB | G40: Profuturo | H40: 4.856457e+09 | I40: 0.6528844 | J40: 494158.69 | K40: Gobierno de Brasil | L40: 46174 | M40: 4003 | N40: 801.5185 | O40: 2.5859271e+08 | P40: =+IFERROR(IF(OR(B40="PEP795509FD5",B40="CVL79560FI39",B40="CVL79590GA30")=FALSE,IF(F40="SOB","Cov",INDEX('ANALISIS BD'!AZ:AZ,MATCH(BD1_S!B40,'ANALISIS BD'!C:C,0))),"NoCov"),"NoCov") -> Cov
A41: 5273932EA359 | B41: US78464A3591 | C41: 0.0044857743 | D41: F3 | E41: RFIG | F41: TD | G41: Ex_Integra | H41: 1.2940613e+10 | I41: 3.6555 | J41: 158000 | K41: SSGA - Bloomberg Barclays Convertible Securities | L41: 46174 | M41: 7393 | N41: 107.82 | O41: 62273490 | P41: =+IFERROR(IF(OR(B41="PEP795509FD5",B41="CVL79560FI39",B41="CVL79590GA30")=FALSE,IF(F41="SOB","Cov",INDEX('ANALISIS BD'!AZ:AZ,MATCH(BD1_S!B41,'ANALISIS BD'!C:C,0))),"NoCov"),"NoCov") -> Cov
A42: 0110001PEB40 | B42: US715638DC30 | C42: 7.4784212e-05 | D42: Multifondos | E42: RFLG | F42: SOB | G42: Ex_Integra | H42: 7.7424621e+10 | I42: 1 | J42: 6480 | K42: Gobierno Central | L42: 46174 | M42: 1000 | N42: 893.54 | O42: 5790139.2 | P42: =+IFERROR(IF(OR(B42="PEP795509FD5",B42="CVL79560FI39",B42="CVL79590GA30")=FALSE,IF(F42="SOB","Cov",INDEX('ANALISIS BD'!AZ:AZ,MATCH(BD1_S!B42,'ANALISIS BD'!C:C,0))),"NoCov"),"NoCov") -> Cov
A43: 59509428AJ82 | B43: US279158AJ82 | C43: 0.00096096238 | D43: F1 | E43: RFIC | F43: BU | G43: Habitat | H43: 1.8939189e+09 | I43: 3.6555 | J43: 644.13118 | K43: Ecopetrol | L43: 46174 | M43: 5094 | N43: 829.19671 | O43: 1952444.4 | P43: =+IFERROR(IF(OR(B43="PEP795509FD5",B43="CVL79560FI39",B43="CVL79590GA30")=FALSE,IF(F43="SOB","Cov",INDEX('ANALISIS BD'!AZ:AZ,MATCH(BD1_S!B43,'ANALISIS BD'!C:C,0))),"NoCov"),"NoCov") -> Cov
A44: 1551192MAD04 | B44: USP1400MAD04 | C44: 0.0020033656 | D44: F2 | E44: RFIC | F44: BU | G44: Ex_Integra | H44: 5.0823903e+10 | I44: 3.6555 | J44: 28912.38 | L44: 46174 | M44: 5119 | N44: 1033.4953 | O44: 1.092293e+08 | P44: =+IFERROR(IF(OR(B44="PEP795509FD5",B44="CVL79560FI39",B44="CVL79590GA30")=FALSE,IF(F44="SOB","Cov",INDEX('ANALISIS BD'!AZ:AZ,MATCH(BD1_S!B44,'ANALISIS BD'!C:C,0))),"NoCov"),"NoCov") -> NoCov
A45: 011000112G33 | B45: PEP01000C5I0 | C45: 0.029027019 | D45: Multifondos | E45: RFLG | F45: SOB | G45: Habitat | H45: 2.2785495e+10 | I45: 1 | J45: 576242.97 | K45: Gobierno Central | L45: 46174 | M45: 1000 | N45: 1147.7711 | O45: 6.6139501e+08 | P45: =+IFERROR(IF(OR(B45="PEP795509FD5",B45="CVL79560FI39",B45="CVL79590GA30")=FALSE,IF(F45="SOB","Cov",INDEX('ANALISIS BD'!AZ:AZ,MATCH(BD1_S!B45,'ANALISIS BD'!C:C,0))),"NoCov"),"NoCov") -> Cov
A46: 5271112E8513 | B46: US4642885135 | C46: 0.01789922 | D46: F1 | E46: RFIG | F46: TD | G46: Profuturo | H46: 4.856457e+09 | I46: 3.6555 | J46: 319000 | K46: BlackRock - iShares iBoxx High Yield Corporate Bond | L46: 46174 | M46: 7111 | N46: 79.97 | O46: 93253377 | P46: =+IFERROR(IF(OR(B46="PEP795509FD5",B46="CVL79560FI39",B46="CVL79590GA30")=FALSE,IF(F46="SOB","Cov",INDEX('ANALISIS BD'!AZ:AZ,MATCH(BD1_S!B46,'ANALISIS BD'!C:C,0))),"NoCov"),"NoCov") -> Cov
A47: 01100028DQ26 | B47: US715638DQ26 | C47: 3.8683629e-07 | D47: Multifondos | E47: RFLG | F47: SOB | G47: Ex_Integra | H47: 7.7424621e+10 | I47: 3.6555 | J47: 16 | K47: Gobierno Central | L47: 46174 | M47: 1000 | N47: 549.35167 | O47: 32130.48 | P47: =+IFERROR(IF(OR(B47="PEP795509FD5",B47="CVL79560FI39",B47="CVL79590GA30")=FALSE,IF(F47="SOB","Cov",INDEX('ANALISIS BD'!AZ:AZ,MATCH(BD1_S!B47,'ANALISIS BD'!C:C,0))),"NoCov"),"NoCov") -> Cov
A48: 011000112G34 | B48: PEP01000C5G4 | C48: 0.014812652 | D48: Multifondos | E48: RFLG | F48: SOB | G48: Profuturo | H48: 2.1900418e+10 | I48: 1 | J48: 325348.18 | K48: Gobierno Central | L48: 46174 | M48: 1000 | N48: 997.09565 | O48: 3.2440326e+08 | P48: =+IFERROR(IF(OR(B48="PEP795509FD5",B48="CVL79560FI39",B48="CVL79590GA30")=FALSE,IF(F48="SOB","Cov",INDEX('ANALISIS BD'!AZ:AZ,MATCH(BD1_S!B48,'ANALISIS BD'!C:C,0))),"NoCov"),"NoCov") -> Cov
A49: 0840052BAZ31 | B49: US91087BAZ31 | C49: 0.0031969026 | D49: F1 | E49: RFIG | F49: SOB | G49: Ex_Integra | H49: 1.3660104e+10 | I49: 3.6555 | J49: 12734.86 | K49: Gobierno de Mexico | L49: 46174 | M49: 4005 | N49: 1006.36 | O49: 46848353 | P49: =+IFERROR(IF(OR(B49="PEP795509FD5",B49="CVL79560FI39",B49="CVL79590GA30")=FALSE,IF(F49="SOB","Cov",INDEX('ANALISIS BD'!AZ:AZ,MATCH(BD1_S!B49,'ANALISIS BD'!C:C,0))),"NoCov"),"NoCov") -> Cov
A50: 0840052BAZ31 | B50: US91087BAZ31 | C50: 0.0015642023 | D50: F2 | E50: RFIG | F50: SOB | G50: Ex_Integra | H50: 5.0823903e+10 | I50: 3.6555 | J50: 23183.11 | K50: Gobierno de Mexico | L50: 46174 | M50: 4005 | N50: 1006.36 | O50: 85284842 | P50: =+IFERROR(IF(OR(B50="PEP795509FD5",B50="CVL79560FI39",B50="CVL79590GA30")=FALSE,IF(F50="SOB","Cov",INDEX('ANALISIS BD'!AZ:AZ,MATCH(BD1_S!B50,'ANALISIS BD'!C:C,0))),"NoCov"),"NoCov") -> Cov
A51: 011000112G32 | B51: PEP01000C5E9 | C51: 0.00021613227 | D51: Multifondos | E51: RFLG | F51: SOB | G51: Prima | H51: 3.2738708e+10 | I51: 1 | J51: 6393.73 | K51: Gobierno Central | L51: 46174 | M51: 1000 | N51: 1106.6922 | O51: 7075891.1 | P51: =+IFERROR(IF(OR(B51="PEP795509FD5",B51="CVL79560FI39",B51="CVL79590GA30")=FALSE,IF(F51="SOB","Cov",INDEX('ANALISIS BD'!AZ:AZ,MATCH(BD1_S!B51,'ANALISIS BD'!C:C,0))),"NoCov"),"NoCov") -> Cov
A52: 084003411726 | B52: XS3344411726 | C52: 0.0065777499 | D52: F1 | E52: RFIG | F52: SOB | G52: Prima | H52: 6.909728e+09 | I52: 4.4023187 | J52: 11425.27 | K52: Gobierno de Brasil | L52: 46174 | M52: 4003 | N52: 1022.28 | O52: 51418312 | P52: =+IFERROR(IF(OR(B52="PEP795509FD5",B52="CVL79560FI39",B52="CVL79590GA30")=FALSE,IF(F52="SOB","Cov",INDEX('ANALISIS BD'!AZ:AZ,MATCH(BD1_S!B52,'ANALISIS BD'!C:C,0))),"NoCov"),"NoCov") -> Cov
A53: 01100028DR09 | B53: US715638DR09 | C53: 1.0018341e-07 | D53: Multifondos | E53: RFLG | F53: SOB | G53: Ex_Integra | H53: 7.7424621e+10 | I53: 3.6555 | J53: 4 | K53: Gobierno Central | L53: 46174 | M53: 1000 | N53: 569.0875 | O53: 8321.1974 | P53: =+IFERROR(IF(OR(B53="PEP795509FD5",B53="CVL79560FI39",B53="CVL79590GA30")=FALSE,IF(F53="SOB","Cov",INDEX('ANALISIS BD'!AZ:AZ,MATCH(BD1_S!B53,'ANALISIS BD'!C:C,0))),"NoCov"),"NoCov") -> Cov
A54: 011000312F54 | B54: PEP01000C4T0 | C54: 0.00023109555 | D54: Multifondos | E54: RFLG | F54: SOB | G54: Ex_Integra | H54: 7.7424621e+10 | I54: 1 | J54: 13013 | K54: Gobierno Central | L54: 46174 | M54: 1000 | N54: 1374.9701 | O54: 17892485 | P54: =+IFERROR(IF(OR(B54="PEP795509FD5",B54="CVL79560FI39",B54="CVL79590GA30")=FALSE,IF(F54="SOB","Cov",INDEX('ANALISIS BD'!AZ:AZ,MATCH(BD1_S!B54,'ANALISIS BD'!C:C,0))),"NoCov"),"NoCov") -> Cov
A55: 0840038TF1P8 | B55: BRSTNCNTF1P8 | C55: 0.021202806 | D55: F1 | E55: RFIG | F55: SOB | G55: Habitat | H55: 1.8939189e+09 | I55: 0.6528844 | J55: 62000 | K55: Gobierno de Brasil | L55: 46174 | M55: 4003 | N55: 982.3315 | O55: 39763633 | P55: =+IFERROR(IF(OR(B55="PEP795509FD5",B55="CVL79560FI39",B55="CVL79590GA30")=FALSE,IF(F55="SOB","Cov",INDEX('ANALISIS BD'!AZ:AZ,MATCH(BD1_S!B55,'ANALISIS BD'!C:C,0))),"NoCov"),"NoCov") -> Cov
A56: 011000112G33 | B56: PEP01000C5I0 | C56: 0.011752587 | D56: Multifondos | E56: RFLG | F56: SOB | G56: Prima | H56: 3.2738708e+10 | I56: 1 | J56: 335227.57 | K56: Gobierno Central | L56: 46174 | M56: 1000 | N56: 1147.7711 | O56: 3.8476451e+08 | P56: =+IFERROR(IF(OR(B56="PEP795509FD5",B56="CVL79560FI39",B56="CVL79590GA30")=FALSE,IF(F56="SOB","Cov",INDEX('ANALISIS BD'!AZ:AZ,MATCH(BD1_S!B56,'ANALISIS BD'!C:C,0))),"NoCov"),"NoCov") -> Cov
A57: 1552782GAA15 | B57: USP2000GAA15 | C57: 0.00085934127 | D57: F1 | E57: RFIC | F57: BU | G57: Ex_Integra | H57: 1.3660104e+10 | I57: 3.6555 | J57: 3233 | L57: 46174 | M57: 5278 | N57: 1065.5605 | O57: 12593040 | P57: =+IFERROR(IF(OR(B57="PEP795509FD5",B57="CVL79560FI39",B57="CVL79590GA30")=FALSE,IF(F57="SOB","Cov",INDEX('ANALISIS BD'!AZ:AZ,MATCH(BD1_S!B57,'ANALISIS BD'!C:C,0))),"NoCov"),"NoCov") -> NoCov
A58: 0840002CNC19 | B58: US91282CNC19 | C58: 0.00043002574 | D58: Multifondos | E58: RFIG | F58: SOB | G58: Ex_Integra | H58: 7.7424621e+10 | I58: 3.6555 | J58: 98506.37 | K58: Gobierno de los Estados Unidos | L58: 46174 | M58: 4000 | N58: 99.191249 | O58: 35717780 | P58: =+IFERROR(IF(OR(B58="PEP795509FD5",B58="CVL79560FI39",B58="CVL79590GA30")=FALSE,IF(F58="SOB","Cov",INDEX('ANALISIS BD'!AZ:AZ,MATCH(BD1_S!B58,'ANALISIS BD'!C:C,0))),"NoCov"),"NoCov") -> Cov
A59: 0840038TF2K7 | B59: BRSTNCNTF2K7 | C59: 0.0083708121 | D59: F1 | E59: RFIG | F59: SOB | G59: Profuturo | H59: 4.856457e+09 | I59: 0.6528844 | J59: 79000 | K59: Gobierno de Brasil | L59: 46174 | M59: 4003 | N59: 780.468 | O59: 40254875 | P59: =+IFERROR(IF(OR(B59="PEP795509FD5",B59="CVL79560FI39",B59="CVL79590GA30")=FALSE,IF(F59="SOB","Cov",INDEX('ANALISIS BD'!AZ:AZ,MATCH(BD1_S!B59,'ANALISIS BD'!C:C,0))),"NoCov"),"NoCov") -> Cov
A60: 59509428AJ82 | B60: US279158AJ82 | C60: 0.00064020052 | D60: F2 | E60: RFIC | F60: BU | G60: Habitat | H60: 1.4820338e+10 | I60: 3.6555 | J60: 3358 | K60: Ecopetrol | L60: 46174 | M60: 5094 | N60: 829.19671 | O60: 10178530 | P60: =+IFERROR(IF(OR(B60="PEP795509FD5",B60="CVL79560FI39",B60="CVL79590GA30")=FALSE,IF(F60="SOB","Cov",INDEX('ANALISIS BD'!AZ:AZ,MATCH(BD1_S!B60,'ANALISIS BD'!C:C,0))),"NoCov"),"NoCov") -> Cov
A61: 5274494F4261 | B61: FR0010642611 | C61: 0.0013261362 | D61: F1 | E61: RFIG | F61: TD | G61: Ex_Integra | H61: 1.3660104e+10 | I61: 4.4023187 | J61: 239.59679 | K61: Lazard - Convertible Europe Fund | L61: 46174 | M61: 7449 | N61: 19429.39 | O61: 20493760 | P61: =+IFERROR(IF(OR(B61="PEP795509FD5",B61="CVL79560FI39",B61="CVL79590GA30")=FALSE,IF(F61="SOB","Cov",INDEX('ANALISIS BD'!AZ:AZ,MATCH(BD1_S!B61,'ANALISIS BD'!C:C,0))),"NoCov"),"NoCov") -> Cov
A62: 084003411726 | B62: XS3344411726 | C62: 0.0011740571 | D62: Multifondos | E62: RFIG | F62: SOB | G62: Ex_Integra | H62: 7.7424621e+10 | I62: 4.4023187 | J62: 22850.54 | K62: Gobierno de Brasil | L62: 46174 | M62: 4003 | N62: 1022.28 | O62: 1.0283662e+08 | P62: =+IFERROR(IF(OR(B62="PEP795509FD5",B62="CVL79560FI39",B62="CVL79590GA30")=FALSE,IF(F62="SOB","Cov",INDEX('ANALISIS BD'!AZ:AZ,MATCH(BD1_S!B62,'ANALISIS BD'!C:C,0))),"NoCov"),"NoCov") -> Cov
A63: 011000112G35 | B63: PEP01000C5K6 | C63: 0.021210865 | D63: Multifondos | E63: RFLG | F63: SOB | G63: Profuturo | H63: 2.1900418e+10 | I63: 1 | J63: 430776.06 | K63: Gobierno Central | L63: 46174 | M63: 1000 | N63: 1078.3487 | O63: 4.645268e+08 | P63: =+IFERROR(IF(OR(B63="PEP795509FD5",B63="CVL79560FI39",B63="CVL79590GA30")=FALSE,IF(F63="SOB","Cov",INDEX('ANALISIS BD'!AZ:AZ,MATCH(BD1_S!B63,'ANALISIS BD'!C:C,0))),"NoCov"),"NoCov") -> Cov
A64: 5274494F4261 | B64: FR0010642611 | C64: 0.00071285977 | D64: F2 | E64: RFIG | F64: TD | G64: Ex_Integra | H64: 5.0823903e+10 | I64: 4.4023187 | J64: 479.19358 | K64: Lazard - Convertible Europe Fund | L64: 46174 | M64: 7449 | N64: 19429.39 | O64: 40987519 | P64: =+IFERROR(IF(OR(B64="PEP795509FD5",B64="CVL79560FI39",B64="CVL79590GA30")=FALSE,IF(F64="SOB","Cov",INDEX('ANALISIS BD'!AZ:AZ,MATCH(BD1_S!B64,'ANALISIS BD'!C:C,0))),"NoCov"),"NoCov") -> Cov
A65: 5273932EA359 | B65: US78464A3591 | C65: 0.0055206593 | D65: F3 | E65: RFIG | F65: TD | G65: Prima | H65: 3.1943719e+09 | I65: 3.6555 | J65: 48000 | K65: SSGA - Bloomberg Barclays Convertible Securities | L65: 46174 | M65: 7393 | N65: 107.82 | O65: 18918528 | P65: =+IFERROR(IF(OR(B65="PEP795509FD5",B65="CVL79560FI39",B65="CVL79590GA30")=FALSE,IF(F65="SOB","Cov",INDEX('ANALISIS BD'!AZ:AZ,MATCH(BD1_S!B65,'ANALISIS BD'!C:C,0))),"NoCov"),"NoCov") -> Cov
A66: 011000112G34 | B66: PEP01000C5G4 | C66: 0.018365152 | D66: Multifondos | E66: RFLG | F66: SOB | G66: Habitat | H66: 2.2785495e+10 | I66: 1 | J66: 419677.97 | K66: Gobierno Central | L66: 46174 | M66: 1000 | N66: 997.09565 | O66: 4.1845908e+08 | P66: =+IFERROR(IF(OR(B66="PEP795509FD5",B66="CVL79560FI39",B66="CVL79590GA30")=FALSE,IF(F66="SOB","Cov",INDEX('ANALISIS BD'!AZ:AZ,MATCH(BD1_S!B66,'ANALISIS BD'!C:C,0))),"NoCov"),"NoCov") -> Cov
A67: 0840038TF1P8 | B67: BRSTNCNTF1P8 | C67: 0.0031727735 | D67: Multifondos | E67: RFIG | F67: SOB | G67: Ex_Integra | H67: 7.7424621e+10 | I67: 0.6528844 | J67: 379275.8 | K67: Gobierno de Brasil | L67: 46174 | M67: 4003 | N67: 982.3315 | O67: 2.4324812e+08 | P67: =+IFERROR(IF(OR(B67="PEP795509FD5",B67="CVL79560FI39",B67="CVL79590GA30")=FALSE,IF(F67="SOB","Cov",INDEX('ANALISIS BD'!AZ:AZ,MATCH(BD1_S!B67,'ANALISIS BD'!C:C,0))),"NoCov"),"NoCov") -> Cov
A68: 5273932EA359 | B68: US78464A3591 | C68: 0.02355053 | D68: F2 | E68: RFIG | F68: TD | G68: Habitat | H68: 1.4820338e+10 | I68: 3.6555 | J68: 950000 | K68: SSGA - Bloomberg Barclays Convertible Securities | L68: 46174 | M68: 7393 | N68: 107.82 | O68: 3.7442921e+08 | P68: =+IFERROR(IF(OR(B68="PEP795509FD5",B68="CVL79560FI39",B68="CVL79590GA30")=FALSE,IF(F68="SOB","Cov",INDEX('ANALISIS BD'!AZ:AZ,MATCH(BD1_S!B68,'ANALISIS BD'!C:C,0))),"NoCov"),"NoCov") -> Cov
A69: 1552782GAA15 | B69: USP2000GAA15 | C69: 0.0011223262 | D69: F3 | E69: RFIC | F69: BU | G69: Ex_Integra | H69: 1.2940613e+10 | I69: 3.6555 | J69: 4000 | L69: 46174 | M69: 5278 | N69: 1065.5605 | O69: 15580625 | P69: =+IFERROR(IF(OR(B69="PEP795509FD5",B69="CVL79560FI39",B69="CVL79590GA30")=FALSE,IF(F69="SOB","Cov",INDEX('ANALISIS BD'!AZ:AZ,MATCH(BD1_S!B69,'ANALISIS BD'!C:C,0))),"NoCov"),"NoCov") -> NoCov
A70: 0840038TF204 | B70: BRSTNCNTF204 | C70: 0.0044098791 | D70: Multifondos | E70: RFIG | F70: SOB | G70: Ex_Integra | H70: 7.7424621e+10 | I70: 0.6528844 | J70: 596082 | K70: Gobierno de Brasil | L70: 46174 | M70: 4003 | N70: 868.75 | O70: 3.3809373e+08 | P70: =+IFERROR(IF(OR(B70="PEP795509FD5",B70="CVL79560FI39",B70="CVL79590GA30")=FALSE,IF(F70="SOB","Cov",INDEX('ANALISIS BD'!AZ:AZ,MATCH(BD1_S!B70,'ANALISIS BD'!C:C,0))),"NoCov"),"NoCov") -> Cov
A71: 011000112G37 | B71: PEP01000C2Z1 | C71: 0.033845295 | D71: Multifondos | E71: RFLG | F71: SOB | G71: Profuturo | H71: 2.1900418e+10 | I71: 1 | J71: 705547.63 | K71: Gobierno Central | L71: 46174 | M71: 1000 | N71: 1050.5685 | O71: 7.4122611e+08 | P71: =+IFERROR(IF(OR(B71="PEP795509FD5",B71="CVL79560FI39",B71="CVL79590GA30")=FALSE,IF(F71="SOB","Cov",INDEX('ANALISIS BD'!AZ:AZ,MATCH(BD1_S!B71,'ANALISIS BD'!C:C,0))),"NoCov"),"NoCov") -> Cov
A72: 0840052QBB32 | B72: US91086QBB32 | C72: 0.00048362372 | D72: F2 | E72: RFIG | F72: SOB | G72: Ex_Integra | H72: 5.0823903e+10 | I72: 3.6555 | J72: 4392.2 | K72: Gobierno de México | L72: 46174 | M72: 4005 | N72: 1642.3194 | O72: 26368567 | P72: =+IFERROR(IF(OR(B72="PEP795509FD5",B72="CVL79560FI39",B72="CVL79590GA30")=FALSE,IF(F72="SOB","Cov",INDEX('ANALISIS BD'!AZ:AZ,MATCH(BD1_S!B72,'ANALISIS BD'!C:C,0))),"NoCov"),"NoCov") -> Cov
A73: 1551512PAC05 | B73: US05890PAC05 | C73: 0.0076658356 | D73: F1 | E73: RFIC | F73: BU | G73: Prima | H73: 6.909728e+09 | I73: 3.6555 | J73: 14039 | L73: 46174 | M73: 5151 | N73: 1107.2569 | O73: 56823944 | P73: =+IFERROR(IF(OR(B73="PEP795509FD5",B73="CVL79560FI39",B73="CVL79590GA30")=FALSE,IF(F73="SOB","Cov",INDEX('ANALISIS BD'!AZ:AZ,MATCH(BD1_S!B73,'ANALISIS BD'!C:C,0))),"NoCov"),"NoCov") -> NoCov
A74: 1551192MAD04 | B74: USP1400MAD04 | C74: 0.010945302 | D74: F1 | E74: RFIC | F74: BU | G74: Profuturo | H74: 4.856457e+09 | I74: 3.6555 | J74: 15093.95 | L74: 46174 | M74: 5119 | N74: 1033.4953 | O74: 57024071 | P74: =+IFERROR(IF(OR(B74="PEP795509FD5",B74="CVL79560FI39",B74="CVL79590GA30")=FALSE,IF(F74="SOB","Cov",INDEX('ANALISIS BD'!AZ:AZ,MATCH(BD1_S!B74,'ANALISIS BD'!C:C,0))),"NoCov"),"NoCov") -> NoCov
A75: 0840038TF212 | B75: BRSTNCNTF212 | C75: 0.0023474105 | D75: Multifondos | E75: RFIG | F75: SOB | G75: Ex_Integra | H75: 7.7424621e+10 | I75: 0.6528844 | J75: 332665.71 | K75: Gobierno de Brasil | L75: 46174 | M75: 4003 | N75: 828.6195 | O75: 1.7996974e+08 | P75: =+IFERROR(IF(OR(B75="PEP795509FD5",B75="CVL79560FI39",B75="CVL79590GA30")=FALSE,IF(F75="SOB","Cov",INDEX('ANALISIS BD'!AZ:AZ,MATCH(BD1_S!B75,'ANALISIS BD'!C:C,0))),"NoCov"),"NoCov") -> Cov
A76: 5274492F8555 | B76: FR0013185550 | C76: 0.00060234568 | D76: F1 | E76: RFIG | F76: TD | G76: Ex_Integra | H76: 1.3660104e+10 | I76: 3.6555 | J76: 1266.75 | K76: Lazard - Convertible Global Fund | L76: 46174 | M76: 7449 | N76: 1906.22 | O76: 8826951.1 | P76: =+IFERROR(IF(OR(B76="PEP795509FD5",B76="CVL79560FI39",B76="CVL79590GA30")=FALSE,IF(F76="SOB","Cov",INDEX('ANALISIS BD'!AZ:AZ,MATCH(BD1_S!B76,'ANALISIS BD'!C:C,0))),"NoCov"),"NoCov") -> Cov
A77: 011000112G35 | B77: PEP01000C5K6 | C77: 0.02860031 | D77: Multifondos | E77: RFLG | F77: SOB | G77: Habitat | H77: 2.2785495e+10 | I77: 1 | J77: 604324.21 | K77: Gobierno Central | L77: 46174 | M77: 1000 | N77: 1078.3487 | O77: 6.5167222e+08 | P77: =+IFERROR(IF(OR(B77="PEP795509FD5",B77="CVL79560FI39",B77="CVL79590GA30")=FALSE,IF(F77="SOB","Cov",INDEX('ANALISIS BD'!AZ:AZ,MATCH(BD1_S!B77,'ANALISIS BD'!C:C,0))),"NoCov"),"NoCov") -> Cov
A78: 0840038TF238 | B78: BRSTNCNTF238 | C78: 0.0076775817 | D78: Multifondos | E78: RFIG | F78: SOB | G78: Ex_Integra | H78: 7.7424621e+10 | I78: 0.6528844 | J78: 1124825.2 | K78: Gobierno de Brasil | L78: 46174 | M78: 4003 | N78: 801.5185 | O78: 5.8861982e+08 | P78: =+IFERROR(IF(OR(B78="PEP795509FD5",B78="CVL79560FI39",B78="CVL79590GA30")=FALSE,IF(F78="SOB","Cov",INDEX('ANALISIS BD'!AZ:AZ,MATCH(BD1_S!B78,'ANALISIS BD'!C:C,0))),"NoCov"),"NoCov") -> Cov
A79: 011000112G31 | B79: PEP01000C4G7 | C79: 0.0065248853 | D79: Multifondos | E79: RFLG | F79: SOB | G79: Integra | H79: 3.9311487e+10 | I79: 1 | J79: 220000 | K79: Gobierno Central | L79: 46174 | M79: 1000 | N79: 1165.9225 | O79: 2.5650294e+08 | P79: =+IFERROR(IF(OR(B79="PEP795509FD5",B79="CVL79560FI39",B79="CVL79590GA30")=FALSE,IF(F79="SOB","Cov",INDEX('ANALISIS BD'!AZ:AZ,MATCH(BD1_S!B79,'ANALISIS BD'!C:C,0))),"NoCov"),"NoCov") -> Cov
A80: 0840052QBB32 | B80: US91086QBB32 | C80: 0.0017993747 | D80: F1 | E80: RFIG | F80: SOB | G80: Ex_Integra | H80: 1.3660104e+10 | I80: 3.6555 | J80: 4392.2 | K80: Gobierno de México | L80: 46174 | M80: 4005 | N80: 1642.3194 | O80: 26368567 | P80: =+IFERROR(IF(OR(B80="PEP795509FD5",B80="CVL79560FI39",B80="CVL79590GA30")=FALSE,IF(F80="SOB","Cov",INDEX('ANALISIS BD'!AZ:AZ,MATCH(BD1_S!B80,'ANALISIS BD'!C:C,0))),"NoCov"),"NoCov") -> Cov
A81: 011000112G34 | B81: PEP01000C5G4 | C81: 0.033699458 | D81: Multifondos | E81: RFLG | F81: SOB | G81: Prima | H81: 3.2738708e+10 | I81: 1 | J81: 1106490.4 | K81: Gobierno Central | L81: 46174 | M81: 1000 | N81: 997.09565 | O81: 1.1032767e+09 | P81: =+IFERROR(IF(OR(B81="PEP795509FD5",B81="CVL79560FI39",B81="CVL79590GA30")=FALSE,IF(F81="SOB","Cov",INDEX('ANALISIS BD'!AZ:AZ,MATCH(BD1_S!B81,'ANALISIS BD'!C:C,0))),"NoCov"),"NoCov") -> Cov
A82: 1551192MAD04 | B82: USP1400MAD04 | C82: 0.0094996108 | D82: F1 | E82: RFIC | F82: BU | G82: Prima | H82: 6.909728e+09 | I82: 3.6555 | J82: 18638.99 | L82: 46174 | M82: 5119 | N82: 1033.4953 | O82: 70417027 | P82: =+IFERROR(IF(OR(B82="PEP795509FD5",B82="CVL79560FI39",B82="CVL79590GA30")=FALSE,IF(F82="SOB","Cov",INDEX('ANALISIS BD'!AZ:AZ,MATCH(BD1_S!B82,'ANALISIS BD'!C:C,0))),"NoCov"),"NoCov") -> NoCov
A83: 15527829AM84 | B83: USP16259AM84 | C83: 0.00091621412 | D83: F2 | E83: RFIC | F83: BU | G83: Ex_Integra | H83: 5.0823903e+10 | I83: 3.6555 | J83: 13622 | K83: BBVA Bancomer | L83: 46174 | M83: 5278 | N83: 1003.2017 | O83: 49954650 | P83: =+IFERROR(IF(OR(B83="PEP795509FD5",B83="CVL79560FI39",B83="CVL79590GA30")=FALSE,IF(F83="SOB","Cov",INDEX('ANALISIS BD'!AZ:AZ,MATCH(BD1_S!B83,'ANALISIS BD'!C:C,0))),"NoCov"),"NoCov") -> Cov
A84: 0840038TF2K7 | B84: BRSTNCNTF2K7 | C84: 0.00052505893 | D84: Multifondos | E84: RFIG | F84: SOB | G84: Ex_Integra | H84: 7.7424621e+10 | I84: 0.6528844 | J84: 79000 | K84: Gobierno de Brasil | L84: 46174 | M84: 4003 | N84: 780.468 | O84: 40254875 | P84: =+IFERROR(IF(OR(B84="PEP795509FD5",B84="CVL79560FI39",B84="CVL79590GA30")=FALSE,IF(F84="SOB","Cov",INDEX('ANALISIS BD'!AZ:AZ,MATCH(BD1_S!B84,'ANALISIS BD'!C:C,0))),"NoCov"),"NoCov") -> Cov
A85: 011000112G32 | B85: PEP01000C5E9 | C85: 0.013745436 | D85: Multifondos | E85: RFLG | F85: SOB | G85: Integra | H85: 3.9311487e+10 | I85: 1 | J85: 488260 | K85: Gobierno Central | L85: 46174 | M85: 1000 | N85: 1106.6922 | O85: 5.4035353e+08 | P85: =+IFERROR(IF(OR(B85="PEP795509FD5",B85="CVL79560FI39",B85="CVL79590GA30")=FALSE,IF(F85="SOB","Cov",INDEX('ANALISIS BD'!AZ:AZ,MATCH(BD1_S!B85,'ANALISIS BD'!C:C,0))),"NoCov"),"NoCov") -> Cov
A86: 1552782BAB48 | B86: USP1S81BAB48 | C86: 0.0032792162 | D86: F1 | E86: RFIC | F86: BU | G86: Profuturo | H86: 4.856457e+09 | I86: 3.6555 | J86: 4217.9 | L86: 46174 | M86: 5278 | N86: 1108.0451 | O86: 17084431 | P86: =+IFERROR(IF(OR(B86="PEP795509FD5",B86="CVL79560FI39",B86="CVL79590GA30")=FALSE,IF(F86="SOB","Cov",INDEX('ANALISIS BD'!AZ:AZ,MATCH(BD1_S!B86,'ANALISIS BD'!C:C,0))),"NoCov"),"NoCov") -> NoCov
A87: 084004F02914 | B87: COL17CT02914 | C87: 1.1617835e-09 | D87: Multifondos | E87: RFIG | F87: SOB | G87: Ex_Integra | H87: 7.7424621e+10 | I87: 0.0010088 | J87: 1 | K87: Gobierno de Colombia | L87: 46174 | M87: 4004 | N87: 90877.6 | O87: 91.677323 | P87: =+IFERROR(IF(OR(B87="PEP795509FD5",B87="CVL79560FI39",B87="CVL79590GA30")=FALSE,IF(F87="SOB","Cov",INDEX('ANALISIS BD'!AZ:AZ,MATCH(BD1_S!B87,'ANALISIS BD'!C:C,0))),"NoCov"),"NoCov") -> Cov
A88: 5277292FB100 | B88: KYG6963B1005 | C88: 0.00084631234 | D88: F2 | E88: RFIG | F88: TD | G88: Ex_Integra | H88: 5.0823903e+10 | I88: 3.6555 | J88: 6647.47 | K88: Pearl Diver Capital LLC - Floating Rate Global Income | L88: 46174 | M88: 7729 | N88: 1898.919 | O88: 46143402 | P88: =+IFERROR(IF(OR(B88="PEP795509FD5",B88="CVL79560FI39",B88="CVL79590GA30")=FALSE,IF(F88="SOB","Cov",INDEX('ANALISIS BD'!AZ:AZ,MATCH(BD1_S!B88,'ANALISIS BD'!C:C,0))),"NoCov"),"NoCov") -> NoCov
A89: 011000112G37 | B89: PEP01000C2Z1 | C89: 0.011861026 | D89: Multifondos | E89: RFLG | F89: SOB | G89: Habitat | H89: 2.2785495e+10 | I89: 1 | J89: 257250.57 | K89: Gobierno Central | L89: 46174 | M89: 1000 | N89: 1050.5685 | O89: 2.7025934e+08 | P89: =+IFERROR(IF(OR(B89="PEP795509FD5",B89="CVL79560FI39",B89="CVL79590GA30")=FALSE,IF(F89="SOB","Cov",INDEX('ANALISIS BD'!AZ:AZ,MATCH(BD1_S!B89,'ANALISIS BD'!C:C,0))),"NoCov"),"NoCov") -> Cov
A90: 084004F03748 | B90: COL17CT03748 | C90: 0.0059432272 | D90: Multifondos | E90: RFIG | F90: SOB | G90: Ex_Integra | H90: 7.7424621e+10 | I90: 0.0010088 | J90: 6237768.6 | K90: Gobierno de Colombia | L90: 46174 | M90: 4004 | N90: 74528.9 | O90: 4.689851e+08 | P90: =+IFERROR(IF(OR(B90="PEP795509FD5",B90="CVL79560FI39",B90="CVL79590GA30")=FALSE,IF(F90="SOB","Cov",INDEX('ANALISIS BD'!AZ:AZ,MATCH(BD1_S!B90,'ANALISIS BD'!C:C,0))),"NoCov"),"NoCov") -> Cov
A91: 0840038TF204 | B91: BRSTNCNTF204 | C91: 0.035348514 | D91: F1 | E91: RFIG | F91: SOB | G91: Habitat | H91: 1.8939189e+09 | I91: 0.6528844 | J91: 116878 | K91: Gobierno de Brasil | L91: 46174 | M91: 4003 | N91: 868.75 | O91: 66292421 | P91: =+IFERROR(IF(OR(B91="PEP795509FD5",B91="CVL79560FI39",B91="CVL79590GA30")=FALSE,IF(F91="SOB","Cov",INDEX('ANALISIS BD'!AZ:AZ,MATCH(BD1_S!B91,'ANALISIS BD'!C:C,0))),"NoCov"),"NoCov") -> Cov
A92: 011000112G35 | B92: PEP01000C5K6 | C92: 0.03515994 | D92: Multifondos | E92: RFLG | F92: SOB | G92: Prima | H92: 3.2738708e+10 | I92: 1 | J92: 1067457.1 | K92: Gobierno Central | L92: 46174 | M92: 1000 | N92: 1078.3487 | O92: 1.151091e+09 | P92: =+IFERROR(IF(OR(B92="PEP795509FD5",B92="CVL79560FI39",B92="CVL79590GA30")=FALSE,IF(F92="SOB","Cov",INDEX('ANALISIS BD'!AZ:AZ,MATCH(BD1_S!B92,'ANALISIS BD'!C:C,0))),"NoCov"),"NoCov") -> Cov
A93: 01100028DQ26 | B93: US715638DQ26 | C93: 5.8930249e-07 | D93: F2 | E93: RFLG | F93: SOB | G93: Ex_Integra | H93: 5.0823903e+10 | I93: 3.6555 | J93: 16 | K93: Gobierno Central | L93: 46174 | M93: 1000 | N93: 549.35167 | O93: 32130.48 | P93: =+IFERROR(IF(OR(B93="PEP795509FD5",B93="CVL79560FI39",B93="CVL79590GA30")=FALSE,IF(F93="SOB","Cov",INDEX('ANALISIS BD'!AZ:AZ,MATCH(BD1_S!B93,'ANALISIS BD'!C:C,0))),"NoCov"),"NoCov") -> Cov
A94: 084004F03771 | B94: COL17CT03771 | C94: 0.0019398996 | D94: Multifondos | E94: RFIG | F94: SOB | G94: Ex_Integra | H94: 7.7424621e+10 | I94: 0.0010088 | J94: 1800000 | K94: Gobierno de Colombia | L94: 46174 | M94: 4004 | N94: 84302.1 | O94: 1.5307913e+08 | P94: =+IFERROR(IF(OR(B94="PEP795509FD5",B94="CVL79560FI39",B94="CVL79590GA30")=FALSE,IF(F94="SOB","Cov",INDEX('ANALISIS BD'!AZ:AZ,MATCH(BD1_S!B94,'ANALISIS BD'!C:C,0))),"NoCov"),"NoCov") -> Cov
A95: 011000112G39 | B95: PEP01000C5J8 | C95: 0.04159989 | D95: Multifondos | E95: RFLG | F95: SOB | G95: Profuturo | H95: 2.1900418e+10 | I95: 1 | J95: 827054.3 | K95: Gobierno Central | L95: 46174 | M95: 1000 | N95: 1101.5661 | O95: 9.1105496e+08 | P95: =+IFERROR(IF(OR(B95="PEP795509FD5",B95="CVL79560FI39",B95="CVL79590GA30")=FALSE,IF(F95="SOB","Cov",INDEX('ANALISIS BD'!AZ:AZ,MATCH(BD1_S!B95,'ANALISIS BD'!C:C,0))),"NoCov"),"NoCov") -> Cov
A96: 084003411726 | B96: XS3344411726 | C96: 0.0020080075 | D96: F2 | E96: RFIG | F96: SOB | G96: Prima | H96: 2.2634608e+10 | I96: 4.4023187 | J96: 11425.27 | K96: Gobierno de Brasil | L96: 46174 | M96: 4003 | N96: 1022.28 | O96: 51418312 | P96: =+IFERROR(IF(OR(B96="PEP795509FD5",B96="CVL79560FI39",B96="CVL79590GA30")=FALSE,IF(F96="SOB","Cov",INDEX('ANALISIS BD'!AZ:AZ,MATCH(BD1_S!B96,'ANALISIS BD'!C:C,0))),"NoCov"),"NoCov") -> Cov
A97: 15527829AN67 | B97: USP16259AN67 | C97: 0.0042372013 | D97: F1 | E97: RFIC | F97: BU | G97: Ex_Integra | H97: 1.3660104e+10 | I97: 3.6555 | J97: 16928.26 | K97: BBVA Bancomer | L97: 46174 | M97: 5278 | N97: 1003.425 | O97: 62093198 | P97: =+IFERROR(IF(OR(B97="PEP795509FD5",B97="CVL79560FI39",B97="CVL79590GA30")=FALSE,IF(F97="SOB","Cov",INDEX('ANALISIS BD'!AZ:AZ,MATCH(BD1_S!B97,'ANALISIS BD'!C:C,0))),"NoCov"),"NoCov") -> Cov
A98: 5273982F6385 | B98: LU1883863851 | C98: 1.0997111e-08 | D98: F1 | E98: RFIG | F98: TD | G98: Ex_Integra | H98: 1.3660104e+10 | I98: 3.6555 | J98: 1.884 | K98: Amundi / Pioneer - US High Yield | L98: 46174 | M98: 7398 | N98: 23.4 | O98: 161.15491 | P98: =+IFERROR(IF(OR(B98="PEP795509FD5",B98="CVL79560FI39",B98="CVL79590GA30")=FALSE,IF(F98="SOB","Cov",INDEX('ANALISIS BD'!AZ:AZ,MATCH(BD1_S!B98,'ANALISIS BD'!C:C,0))),"NoCov"),"NoCov") -> NoCov
... A122: 0840038TF1P8 | B122: BRSTNCNTF1P8 | C122: 0.0017623665 | D122: Multifondos | E122: RFIG | F122: SOB | G122: Habitat | H122: 2.2785495e+10 | I122: 0.6528844 | J122: 62000 | K122: Gobierno de Brasil | L122: 46174 | M122: 4003 | N122: 982.3315 | O122: 39763633 | P122: =+IFERROR(IF(OR(B122="PEP795509FD5",B122="CVL79560FI39",B122="CVL79590GA30")=FALSE,IF(F122="SOB","Cov",INDEX('ANALISIS BD'!AZ:AZ,MATCH(BD1_S!B122,'ANALISIS BD'!C:C,0))),"NoCov"),"NoCov") -> Cov
A123: 59509428AW93 | B123: US279158AW93 | C123: 0.0010645114 | D123: F2 | E123: RFIC | F123: BU | G123: Ex_Integra | H123: 5.0823903e+10 | I123: 3.6555 | J123: 14707.64 | L123: 46174 | M123: 5094 | N123: 1079.5419 | O123: 58040250 | P123: =+IFERROR(IF(OR(B123="PEP795509FD5",B123="CVL79560FI39",B123="CVL79590GA30")=FALSE,IF(F123="SOB","Cov",INDEX('ANALISIS BD'!AZ:AZ,MATCH(BD1_S!B123,'ANALISIS BD'!C:C,0))),"NoCov"),"NoCov") -> NoCov
...
