Workbook

Sheet BD
A1: Corte | B1: AFP | C1: Fondo | D1: Portafolio | E1: SBS | F1: ISIN | G1: Estrategia | H1: Universo | I1: Categoria | J1: Tipo_Dato | K1: Pais | L1: Nombre_Original | M1: Emisor | N1: PERDIO_HUELLA | O1: CO2-H | P1: Weight | Q1: Inv_MM_USD | R1: Huella | S1: Intensidad | T1: Huella_Verif | U1: Intensidad_Verif
A2: 202606 | B2: Ex_Integra | C2: F2 | D2: IN-FONDO2 | E2: 0840002CNC19 | F2: US91282CNC19 | G2: SOB | H2: Soberanos | I2: GOB | K2: EEUU | L2: Gobierno de los Estados Unidos | M2: Gobierno de los Estados Unidos | N2: FALSE | O2: 202.59174 | P2: 0.00067661643 | Q2: 9.4581485 | R2: 1916.1428 | S2: 0.1370769 | T2: =O2*Q2 | U2: =O2*P2
A3: 202606 | B3: Ex_Integra | C3: F1 | D3: IN-FONDO1 | E3: 084003411726 | F3: XS3344411726 | G3: SOB | H3: Soberanos | I3: GOB | K3: Brasil | L3: Gobierno de Brasil | M3: Gobierno de Brasil | N3: FALSE | O3: 274.39828 | P3: 0.0033728351 | Q3: 12.498937 | R3: 3429.6869 | S3: 0.92550015 | T3: =O3*Q3 | U3: =O3*P3
A4: 202606 | B4: Ex_Integra | C4: F2 | D4: IN-FONDO2 | E4: 084003411726 | F4: XS3344411726 | G4: SOB | H4: Soberanos | I4: GOB | K4: Brasil | L4: Gobierno de Brasil | M4: Gobierno de Brasil | N4: FALSE | O4: 274.39828 | P4: 0.00090969042 | Q4: 12.716196 | R4: 3489.3023 | S4: 0.24961749 | T4: =O4*Q4 | U4: =O4*P4
A5: 202606 | B5: Ex_Integra | C5: F1 | D5: IN-FONDO1 | E5: 0840052BAZ31 | F5: US91087BAZ31 | G5: SOB | H5: Soberanos | I5: GOB | K5: México | L5: Gobierno de Mexico | M5: Gobierno de México | N5: FALSE | O5: 204.30315 | P5: 0.0032830534 | Q5: 12.166227 | R5: 2485.5985 | S5: 0.67073815 | T5: =O5*Q5 | U5: =O5*P5
A6: 202606 | B6: Ex_Integra | C6: F2 | D6: IN-FONDO2 | E6: 0840052BAZ31 | F6: US91087BAZ31 | G6: SOB | H6: Soberanos | I6: GOB | K6: México | L6: Gobierno de Mexico | M6: Gobierno de México | N6: FALSE | O6: 204.30315 | P6: 0.001611959 | Q6: 22.532925 | R6: 4603.5475 | S6: 0.32932829 | T6: =O6*Q6 | U6: =O6*P6
A7: 202606 | B7: Ex_Integra | C7: F2 | D7: IN-FONDO2 | E7: 0840052QBB32 | F7: US91086QBB32 | G7: SOB | H7: Soberanos | I7: GOB | K7: México | L7: Gobierno de México | M7: Gobierno de México | N7: FALSE | O7: 204.30315 | P7: 0.0004994821 | Q7: 6.9820591 | R7: 1426.4567 | S7: 0.10204577 | T7: =O7*Q7 | U7: =O7*P7
A8: 202606 | B8: Ex_Integra | C8: F1 | D8: IN-FONDO1 | E8: 0840052QBB32 | F8: US91086QBB32 | G8: SOB | H8: Soberanos | I8: GOB | K8: México | L8: Gobierno de México | M8: Gobierno de México | N8: FALSE | O8: 204.30315 | P8: 0.0018519166 | Q8: 6.8627692 | R8: 1402.0854 | S8: 0.37835238 | T8: =O8*Q8 | U8: =O8*P8
A9: 202606 | B9: Ex_Integra | C9: F2 | D9: IN-FONDO2 | E9: 01100028DQ26 | F9: US715638DQ26 | G9: SOB | H9: Soberanos | I9: GOB | K9: Perú | L9: Gobierno Central | M9: Gobierno Central | N9: FALSE | O9: 170.41984 | P9: 6.0940321e-07 | Q9: 0.008518602 | R9: 1.4517388 | S9: 0.0001038544 | T9: =O9*Q9 | U9: =O9*P9
A10: 202606 | B10: Ex_Integra | C10: F1 | D10: IN-FONDO1 | E10: 01100028DR09 | F10: US715638DR09 | G10: SOB | H10: Soberanos | I10: GOB | K10: Perú | L10: Gobierno Central | M10: Gobierno Central | N10: FALSE | O10: 170.41984 | P10: 5.8572117e-07 | Q10: 0.0021705455 | R10: 0.36990402 | S10: 9.9818508e-05 | T10: =O10*Q10 | U10: =O10*P10
A11: 202606 | B11: Ex_Integra | C11: F1 | D11: IN-FONDO1 | E11: 0840038TF238 | F11: BRSTNCNTF238 | G11: SOB | H11: Soberanos | I11: GOB | K11: Brasil | L11: Gobierno de Brasil | M11: Gobierno de Brasil | N11: FALSE | O11: 274.39828 | P11: 0.046997124 | Q11: 174.16034 | R11: 47789.298 | S11: 12.89593 | T11: =O11*Q11 | U11: =O11*P11
A12: 202606 | B12: Ex_Integra | C12: F1 | D12: IN-FONDO1 | E12: 0840038TF2K7 | F12: BRSTNCNTF2K7 | G12: SOB | H12: Soberanos | I12: GOB | K12: Brasil | L12: Gobierno de Brasil | M12: Gobierno de Brasil | N12: FALSE | O12: 274.39828 | P12: 0.0032273003 | Q12: 11.959619 | R12: 3281.699 | S12: 0.88556565 | T12: =O12*Q12 | U12: =O12*P12
A13: 202606 | B13: Ex_Integra | C13: F1 | D13: IN-FONDO1 | E13: 0840038TF212 | F13: BRSTNCNTF212 | G13: SOB | H13: Soberanos | I13: GOB | K13: Brasil | L13: Gobierno de Brasil | M13: Gobierno de Brasil | N13: FALSE | O13: 274.39828 | P13: 0.012042696 | Q13: 44.627413 | R13: 12245.685 | S13: 3.3044951 | T13: =O13*Q13 | U13: =O13*P13
... A63: 202606 | B63: Ex_Integra | C63: F2 | D63: IN-FONDO2 | E63: 011000312F54 | F63: PEP01000C4T0 | G63: SOB | H63: Soberanos | I63: GOB | K63: Perú | L63: Gobierno Central | M63: Gobierno Central | N63: FALSE | O63: 170.41984 | P63: 0.00036317378 | Q63: 5.07666 | R63: 865.16358 | S63: 0.061892018 | T63: =O63*Q63 | U63: =O63*P63
A64: 202606 | B64: Ex_Integra | C64: F3 | D64: IN-FONDO3 | E64: 2220082PAB78 | F64: USP6680PAB78 | G64: BU | H64: Sector | I64: Materials | J64: MSCI | M64: nan | N64: FALSE | O64: 32.13 | P64: 0.00058775142 | Q64: 2.0937595 | R64: 67.272492 | S64: 0.018884453 | T64: =O64*Q64 | U64: =O64*P64
A65: 202606 | B65: Ex_Integra | C65: F1 | D65: IN-FONDO1 | E65: 2220082PAB78 | F65: USP6680PAB78 | G65: BU | H65: Sector | I65: Materials | J65: MSCI | M65: nan | N65: FALSE | O65: 32.13 | P65: 0.010670635 | Q65: 39.542876 | R65: 1270.5126 | S65: 0.34284751 | T65: =O65*Q65 | U65: =O65*P65
A66: 202606 | B66: Ex_Integra | C66: F2 | D66: IN-FONDO2 | E66: 2220082PAB78 | F66: USP6680PAB78 | G66: BU | H66: Sector | I66: Materials | J66: MSCI | M66: nan | N66: FALSE | O66: 32.13 | P66: 0.0022021118 | Q66: 30.782434 | R66: 989.0396 | S66: 0.070753852 | T66: =O66*Q66 | U66: =O66*P66
A67: 202606 | B67: Ex_Integra | C67: F3 | D67: IN-FONDO3 | E67: 2259582AAA36 | F67: USP6432AAA36 | G67: BU | H67: Sector | I67: Materials | J67: MSCI | M67: nan | N67: FALSE | O67: 116.89 | P67: 0.00028132429 | Q67: 1.0021675 | R67: 117.14336 | S67: 0.032883996 | T67: =O67*Q67 | U67: =O67*P67
A68: 202606 | B68: Ex_Integra | C68: F1 | D68: IN-FONDO1 | E68: 2259582AAA36 | F68: USP6432AAA36 | G68: BU | H68: Sector | I68: Materials | J68: MSCI | M68: nan | N68: FALSE | O68: 116.89 | P68: 0.0019779426 | Q68: 7.3297924 | R68: 856.77943 | S68: 0.23120172 | T68: =O68*Q68 | U68: =O68*P68
A69: 202606 | B69: Ex_Integra | C69: F2 | D69: IN-FONDO2 | E69: 2259582AAA36 | F69: USP6432AAA36 | G69: BU | H69: Sector | I69: Materials | J69: MSCI | M69: nan | N69: FALSE | O69: 116.89 | P69: 0.00097475393 | Q69: 13.625693 | R69: 1592.7072 | S69: 0.11393899 | T69: =O69*Q69 | U69: =O69*P69
A70: 202606 | B70: Ex_Integra | C70: F2 | D70: IN-FONDO2 | E70: 22204327AE63 | F70: USP98047AE63 | G70: BU | H70: Sector | I70: Materials | J70: MSCI | M70: nan | N70: FALSE | O70: 113.85 | P70: 0.0046521504 | Q70: 65.030537 | R70: 7403.7266 | S70: 0.52964733 | T70: =O70*Q70 | U70: =O70*P70
A71: 202606 | B71: Ex_Integra | C71: F1 | D71: IN-FONDO1 | E71: 22204327AE63 | F71: USP98047AE63 | G71: BU | H71: Sector | I71: Materials | J71: MSCI | M71: nan | N71: FALSE | O71: 113.85 | P71: 0.008378714 | Q71: 31.049553 | R71: 3534.9916 | S71: 0.95391659 | T71: =O71*Q71 | U71: =O71*P71
A72: 202606 | B72: Ex_Integra | C72: F3 | D72: IN-FONDO3 | E72: 395953O13172 | F72: HK1208013172 | G72: BU | H72: Sector | I72: Materials | J72: MSCI | M72: nan | N72: FALSE | O72: 46.98 | P72: 0.00012567153 | Q72: 0.44768239 | R72: 21.032119 | S72: 0.0059040486 | T72: =O72*Q72 | U72: =O72*P72
A73: 202606 | B73: Ex_Integra | C73: F2 | D73: IN-FONDO2 | E73: 302043100001 | F73: PEP648011109 | G73: BU | H73: Sector | I73: Materials | J73: MSCI | L73: Volcan* | M73: Volcan | N73: FALSE | O73: 113.85 | P73: 2.3743506e-08 | Q73: 0.00033190091 | R73: 0.037786919 | S73: 2.7031982e-06 | T73: =O73*Q73 | U73: =O73*P73
A74: 202606 | B74: Ex_Integra | C74: F2 | D74: IN-FONDO2 | E74: 302043100002 | F74: PEP648014202 | G74: BU | H74: Sector | I74: Materials | J74: MSCI | L74: Volcan* | M74: Volcan | N74: FALSE | O74: 113.85 | P74: 0.001278807 | Q74: 17.875927 | R74: 2035.1743 | S74: 0.14559217 | T74: =O74*Q74 | U74: =O74*P74
A75: 202606 | B75: Ex_Integra | C75: F1 | D75: IN-FONDO1 | E75: 302043100002 | F75: PEP648014202 | G75: BU | H75: Sector | I75: Materials | J75: MSCI | L75: Volcan* | M75: Volcan | N75: FALSE | O75: 113.85 | P75: 0.0012103985 | Q75: 4.4854533 | R75: 510.66886 | S75: 0.13780386 | T75: =O75*Q75 | U75: =O75*P75
A76: 202606 | B76: Ex_Integra | C76: F3 | D76: IN-FONDO3 | E76: 302043100002 | F76: PEP648014202 | G76: BU | H76: Sector | I76: Materials | J76: MSCI | L76: Volcan* | M76: Volcan | N76: FALSE | O76: 113.85 | P76: 0.007065566 | Q76: 25.169817 | R76: 2865.5837 | S76: 0.80441469 | T76: =O76*Q76 | U76: =O76*P76
A77: 202606 | B77: Ex_Integra | C77: F3 | D77: IN-FONDO3 | E77: 302845100002 | F77: PEP620001003 | G77: BU | H77: Sector | I77: Materials | J77: MSCI | L77: Nexa Resources Perú | M77: Nexa Resources Perú | N77: FALSE | O77: 167.61 | P77: 0.0028773301 | Q77: 10.249975 | R77: 1717.9982 | S77: 0.48226929 | T77: =O77*Q77 | U77: =O77*P77
A78: 202606 | B78: Ex_Integra | C78: F1 | D78: IN-FONDO1 | E78: 302845100002 | F78: PEP620001003 | G78: BU | H78: Sector | I78: Materials | J78: MSCI | L78: Nexa Resources Perú | M78: Nexa Resources Perú | N78: FALSE | O78: 167.61 | P78: 5.6109197e-06 | Q78: 0.020792755 | R78: 3.4850737 | S78: 0.00094044626 | T78: =O78*Q78 | U78: =O78*P78
A79: 202606 | B79: Ex_Integra | C79: F2 | D79: IN-FONDO2 | E79: 302845100002 | F79: PEP620001003 | G79: BU | H79: Sector | I79: Materials | J79: MSCI | L79: Nexa Resources Perú | M79: Nexa Resources Perú | N79: FALSE | O79: 167.61 | P79: 0.00040533812 | Q79: 5.6660583 | R79: 949.68802 | S79: 0.067938722 | T79: =O79*Q79 | U79: =O79*P79
A80: 202606 | B80: Ex_Integra | C80: F2 | D80: IN-FONDO2 | E80: 312039100001 | F80: PEP622005002 | G80: BU | H80: Sector | I80: Materials | J80: MSCI | L80: Minsur | M80: Minsur | N80: FALSE | O80: 116.89 | P80: 0.030090232 | Q80: 420.61923 | R80: 49166.182 | S80: 3.5172472 | T80: =O80*Q80 | U80: =O80*P80
A81: 202606 | B81: Ex_Integra | C81: F3 | D81: IN-FONDO3 | E81: 312039100001 | F81: PEP622005002 | G81: BU | H81: Sector | I81: Materials | J81: MSCI | L81: Minsur | M81: Minsur | N81: FALSE | O81: 116.89 | P81: 0.054646863 | Q81: 194.66969 | R81: 22754.94 | S81: 6.3876718 | T81: =O81*Q81 | U81: =O81*P81
A82: 202606 | B82: Ex_Integra | C82: F1 | D82: IN-FONDO1 | E82: 312039100001 | F82: PEP622005002 | G82: BU | H82: Sector | I82: Materials | J82: MSCI | L82: Minsur | M82: Minsur | N82: FALSE | O82: 116.89 | P82: 0.009829985 | Q82: 36.427623 | R82: 4258.0249 | S82: 1.1490269 | T82: =O82*Q82 | U82: =O82*P82
A83: 202606 | B83: Ex_Integra | C83: F1 | D83: IN-FONDO1 | E83: 395833228291 | F83: LU1701428291 | G83: BU | H83: Sector | I83: Materials | J83: MSCI | L83: Nexa Resources | M83: Nexa Resources | N83: FALSE | O83: 206.9 | P83: 0.00021937034 | Q83: 0.81293511 | R83: 168.19627 | S83: 0.045387722 | T83: =O83*Q83 | U83: =O83*P83
A84: 202606 | B84: Ex_Integra | C84: F3 | D84: IN-FONDO3 | E84: 395833228291 | F84: LU1701428291 | G84: BU | H84: Sector | I84: Materials | J84: MSCI | L84: Nexa Resources | M84: Nexa Resources | N84: FALSE | O84: 206.9 | P84: 0.0088783088 | Q84: 31.62739 | R84: 6543.7069 | S84: 1.8369221 | T84: =O84*Q84 | U84: =O84*P84
A85: 202606 | B85: Ex_Integra | C85: F2 | D85: IN-FONDO2 | E85: 395833228291 | F85: LU1701428291 | G85: BU | H85: Sector | I85: Materials | J85: MSCI | L85: Nexa Resources | M85: Nexa Resources | N85: FALSE | O85: 206.9 | P85: 0.0032966427 | Q85: 46.08244 | R85: 9534.4569 | S85: 0.68207537 | T85: =O85*Q85 | U85: =O85*P85
A86: 202606 | B86: Ex_Integra | C86: F2 | D86: IN-FONDO2 | E86: 3920836W5029 | F86: GB00B1FW5029 | G86: BU | H86: Sector | I86: Materials | J86: MSCI | M86: nan | N86: FALSE | O86: 31.79 | P86: 0.0073822023 | Q86: 103.19283 | R86: 3280.5002 | S86: 0.23468021 | T86: =O86*Q86 | U86: =O86*P86
A87: 202606 | B87: Ex_Integra | C87: F1 | D87: IN-FONDO1 | E87: 3920836W5029 | F87: GB00B1FW5029 | G87: BU | H87: Sector | I87: Materials | J87: MSCI | M87: nan | N87: FALSE | O87: 31.79 | P87: 0.0014060737 | Q87: 5.2105798 | R87: 165.64433 | S87: 0.044699082 | T87: =O87*Q87 | U87: =O87*P87
A88: 202606 | B88: Ex_Integra | C88: F3 | D88: IN-FONDO3 | E88: 3920836W5029 | F88: GB00B1FW5029 | G88: BU | H88: Sector | I88: Materials | J88: MSCI | M88: nan | N88: FALSE | O88: 31.79 | P88: 0.015761449 | Q88: 56.147349 | R88: 1784.9242 | S88: 0.50105648 | T88: =O88*Q88 | U88: =O88*P88
A89: 202606 | B89: Ex_Integra | C89: F1 | D89: IN-FONDO1 | E89: 3220082A1040 | F89: US2044481040 | G89: BU | H89: Sector | I89: Materials | J89: MSCI | L89: Buenaventura* | M89: Buenaventura | N89: FALSE | O89: 32.13 | P89: 0.0038732375 | Q89: 14.353311 | R89: 461.1719 | S89: 0.12444712 | T89: =O89*Q89 | U89: =O89*P89
A90: 202606 | B90: Ex_Integra | C90: F3 | D90: IN-FONDO3 | E90: 3220082A1040 | F90: US2044481040 | G90: BU | H90: Sector | I90: Materials | J90: MSCI | L90: Buenaventura* | M90: Buenaventura | N90: FALSE | O90: 32.13 | P90: 0.053958466 | Q90: 192.2174 | R90: 6175.945 | S90: 1.7336855 | T90: =O90*Q90 | U90: =O90*P90
A91: 202606 | B91: Ex_Integra | C91: F2 | D91: IN-FONDO2 | E91: 3220082A1040 | F91: US2044481040 | G91: BU | H91: Sector | I91: Materials | J91: MSCI | L91: Buenaventura* | M91: Buenaventura | N91: FALSE | O91: 32.13 | P91: 0.037742459 | Q91: 527.58663 | R91: 16951.359 | S91: 1.2126652 | T91: =O91*Q91 | U91: =O91*P91
A92: 202606 | B92: Ex_Integra | C92: F1 | D92: IN-FONDO1 | E92: 5953042VAC78 | F92: USP4R53VAC78 | G92: BU | H92: Sector | I92: Utilities | J92: MSCI | M92: nan | N92: FALSE | O92: 23.88 | P92: 0.0021143498 | Q92: 7.8352854 | R92: 187.10661 | S92: 0.050490673 | T92: =O92*Q92 | U92: =O92*P92
A93: 202606 | B93: Ex_Integra | C93: F2 | D93: IN-FONDO2 | E93: 5953042VAC78 | F93: USP4R53VAC78 | G93: BU | H93: Sector | I93: Utilities | J93: MSCI | M93: nan | N93: FALSE | O93: 23.88 | P93: 0.00027226699 | Q93: 3.8059106 | R93: 90.885144 | S93: 0.0065017357 | T93: =O93*Q93 | U93: =O93*P93
A94: 202606 | B94: Ex_Integra | C94: F2 | D94: IN-FONDO2 | E94: 59529429BR86 | F94: USP30179BR86 | G94: BU | H94: Sector | I94: Utilities | J94: MSCI | L94: Comisión Federal de Electricidad | M94: Comisión Federal de Electricidad | N94: FALSE | O94: 898.1 | P94: 1.1939129e-08 | Q94: 0.00016689227 | R94: 0.14988595 | S94: 1.0722532e-05 | T94: =O94*Q94 | U94: =O94*P94
A95: 202606 | B95: Ex_Integra | C95: F2 | D95: IN-FONDO2 | E95: 22205821204A | F95: PEP70310M131 | G95: BU | H95: Sector | I95: Utilities | J95: MSCI | L95: Red de Energía del Perú | M95: Red de Energía del Perú | N95: FALSE | O95: 26.11 | P95: 6.2599846e-06 | Q95: 0.087505803 | R95: 2.2847765 | S95: 0.0001634482 | T95: =O95*Q95 | U95: =O95*P95
A96: 202606 | B96: Ex_Integra | C96: F1 | D96: IN-FONDO1 | E96: 22205821204A | F96: PEP70310M131 | G96: BU | H96: Sector | I96: Utilities | J96: MSCI | L96: Red de Energía del Perú | M96: Red de Energía del Perú | N96: FALSE | O96: 26.11 | P96: 1.5473319e-05 | Q96: 0.0573405 | R96: 1.4971604 | S96: 0.00040400837 | T96: =O96*Q96 | U96: =O96*P96
A97: 202606 | B97: Ex_Integra | C97: F1 | D97: IN-FONDO1 | E97: 595132FRAZ03 | F97: USP9379RAZ03 | G97: BU | H97: Sector | I97: Utilities | J97: MSCI | L97: Emp. Públicas Medellin | M97: Emp. Públicas Medellin | N97: FALSE | O97: 32.63 | P97: 0.0131096 | Q97: 48.581109 | R97: 1585.2016 | S97: 0.42776625 | T97: =O97*Q97 | U97: =O97*P97
A98: 202606 | B98: Ex_Integra | C98: F2 | D98: IN-FONDO2 | E98: 595132FRAZ03 | F98: USP9379RAZ03 | G98: BU | H98: Sector | I98: Utilities | J98: MSCI | L98: Emp. Públicas Medellin | M98: Emp. Públicas Medellin | N98: FALSE | O98: 32.63 | P98: 0.0042139532 | Q98: 58.905154 | R98: 1922.0752 | S98: 0.13750129 | T98: =O98*Q98 | U98: =O98*P98
A99: 202606 | B99: Ex_Integra | C99: F1 | D99: IN-FONDO1 | E99: 15515123CH47 | F99: USP32133CH47 | G99: BU | H99: Sector | I99: Otros | J99: MSCI | M99: nan | N99: FALSE | O99: 0.11 | P99: 0.0012887125 | Q99: 4.7756669 | R99: 0.52532336 | S99: 0.00014175838 | T99: =O99*Q99 | U99: =O99*P99
A100: 202606 | B100: Ex_Integra | C100: F1 | D100: IN-FONDO1 | E100: 1551512PAC05 | F100: US05890PAC05 | G100: BU | H100: Sector | I100: Otros | J100: MSCI | M100: nan | N100: FALSE | O100: 0.11 | P100: 0.0039598518 | Q100: 14.674284 | R100: 1.6141712 | S100: 0.0004355837 | T100: =O100*Q100 | U100: =O100*P100
A101: 202606 | B101: Ex_Integra | C101: F1 | D101: IN-FONDO1 | E101: 1551192MAD04 | F101: USP1400MAD04 | G101: BU | H101: Sector | I101: Otros | J101: MSCI | M101: nan | N101: FALSE | O101: 1.26 | P101: 0.0088869519 | Q101: 32.932963 | R101: 41.495534 | S101: 0.011197559 | T101: =O101*Q101 | U101: =O101*P101
A102: 202606 | B102: Ex_Integra | C102: F2 | D102: IN-FONDO2 | E102: 1551192MAD04 | F102: USP1400MAD04 | G102: BU | H102: Sector | I102: Otros | J102: MSCI | M102: nan | N102: FALSE | O102: 1.26 | P102: 0.002054381 | Q102: 28.717365 | R102: 36.183879 | S102: 0.0025885201 | T102: =O102*Q102 | U102: =O102*P102
A103: 202606 | B103: Ex_Integra | C103: F1 | D103: IN-FONDO1 | E103: 1552782GAA15 | F103: USP2000GAA15 | G103: BU | H103: Sector | I103: Otros | J103: MSCI | M103: nan | N103: FALSE | O103: 0.77 | P103: 0.00087879106 | Q103: 3.256594 | R103: 2.5075773 | S103: 0.00067666912 | T103: =O103*Q103 | U103: =O103*P103
A104: 202606 | B104: Ex_Integra | C104: F3 | D104: IN-FONDO3 | E104: 1552782GAA15 | F104: USP2000GAA15 | G104: BU | H104: Sector | I104: Otros | J104: MSCI | M104: nan | N104: FALSE | O104: 0.77 | P104: 0.0011848834 | Q104: 4.2209354 | R104: 3.2501202 | S104: 0.00091236019 | T104: =O104*Q104 | U104: =O104*P104
A105: 202606 | B105: Ex_Integra | C105: F2 | D105: IN-FONDO2 | E105: 15527829AM84 | F105: USP16259AM84 | G105: BU | H105: Sector | I105: Otros | J105: MSCI | L105: BBVA Bancomer | M105: BBVA Bancomer | N105: FALSE | O105: 0.77 | P105: 0.00094025979 | Q105: 13.143513 | R105: 10.120505 | S105: 0.00072400004 | T105: =O105*Q105 | U105: =O105*P105
A106: 202606 | B106: Ex_Integra | C106: F1 | D106: IN-FONDO1 | E106: 15527829AN67 | F106: USP16259AN67 | G106: BU | H106: Sector | I106: Otros | J106: MSCI | L106: BBVA Bancomer | M106: BBVA Bancomer | N106: FALSE | O106: 0.77 | P106: 0.0043266562 | Q106: 16.033575 | R106: 12.345853 | S106: 0.0033315253 | T106: =O106*Q106 | U106: =O106*P106
A107: 202606 | B107: Ex_Integra | C107: F3 | D107: IN-FONDO3 | E107: 15527829AN67 | F107: USP16259AN67 | G107: BU | H107: Sector | I107: Otros | J107: MSCI | L107: BBVA Bancomer | M107: BBVA Bancomer | N107: FALSE | O107: 0.77 | P107: 0.00027853242 | Q107: 0.992222 | R107: 0.76401094 | S107: 0.00021446996 | T107: =O107*Q107 | U107: =O107*P107
A108: 202606 | B108: Ex_Integra | C108: F2 | D108: IN-FONDO2 | E108: 15527829AN67 | F108: USP16259AN67 | G108: BU | H108: Sector | I108: Otros | J108: MSCI | L108: BBVA Bancomer | M108: BBVA Bancomer | N108: FALSE | O108: 0.77 | P108: 0.00054549632 | Q108: 7.6252733 | R108: 5.8714604 | S108: 0.00042003216 | T108: =O108*Q108 | U108: =O108*P108
A109: 202606 | B109: Ex_Integra | C109: F2 | D109: IN-FONDO2 | E109: 59509428AW93 | F109: US279158AW93 | G109: BU | H109: Sector | I109: Otros | J109: MSCI | M109: nan | N109: FALSE | O109: 226.35 | P109: 0.0010953931 | Q109: 15.312059 | R109: 3465.8845 | S109: 0.24794222 | T109: =O109*Q109 | U109: =O109*P109
A110: 202606 | B110: Ex_Integra | C110: F1 | D110: IN-FONDO1 | E110: 59509428AW93 | F110: US279158AW93 | G110: BU | H110: Sector | I110: Otros | J110: MSCI | M110: nan | N110: FALSE | O110: 226.35 | P110: 0.0016227032 | Q110: 6.0133582 | R110: 1361.1236 | S110: 0.36729887 | T110: =O110*Q110 | U110: =O110*P110
A111: 202606 | B111: Ex_Integra | C111: F1 | D111: IN-FONDO1 | E111: 1552782BAB48 | F111: USP1S81BAB48 | G111: BU | H111: Sector | I111: Otros | J111: MSCI | M111: nan | N111: FALSE | O111: 0.77 | P111: 0.0011906972 | Q111: 4.4124452 | R111: 3.3975828 | S111: 0.00091683688 | T111: =O111*Q111 | U111: =O111*P111
A112: 202606 | B112: Ex_Integra | C112: F2 | D112: IN-FONDO2 | E112: 1552782BAB48 | F112: USP1S81BAB48 | G112: BU | H112: Sector | I112: Otros | J112: MSCI | M112: nan | N112: FALSE | O112: 0.77 | P112: 0.0015943562 | Q112: 22.286863 | R112: 17.160885 | S112: 0.0012276543 | T112: =O112*Q112 | U112: =O112*P112
A113: 202606 | B113: Ex_Integra | C113: F1 | D113: IN-FONDO1 | E113: 1552782BAA64 | F113: USP1S81BAA64 | G113: BU | H113: Sector | I113: Otros | J113: MSCI | L113: BBVA Bancomer | M113: BBVA Bancomer | N113: FALSE | O113: 0.77 | P113: 0.00097482992 | Q113: 3.6124915 | R113: 2.7816184 | S113: 0.00075061904 | T113: =O113*Q113 | U113: =O113*P113
A114: 202606 | B114: Ex_Integra | C114: F1 | D114: IN-FONDO1 | E114: 1551112LAN29 | F114: US05968LAN29 | G114: BU | H114: Sector | I114: Otros | J114: MSCI | M114: nan | N114: FALSE | O114: 0.6 | P114: 0.00095394357 | Q114: 3.5350916 | R114: 2.1210549 | S114: 0.00057236614 | T114: =O114*Q114 | U114: =O114*P114
A115: 202606 | B115: Ex_Integra | C115: F2 | D115: IN-FONDO2 | E115: 1551112LAN29 | F115: US05968LAN29 | G115: BU | H115: Sector | I115: Otros | J115: MSCI | M115: nan | N115: FALSE | O115: 0.6 | P115: 0.00028181726 | Q115: 3.9394099 | R115: 2.3636459 | S115: 0.00016909035 | T115: =O115*Q115 | U115: =O115*P115
A116: 202606 | B116: Ex_Integra | C116: F2 | D116: IN-FONDO2 | E116: 59509428AJ82 | F116: US279158AJ82 | G116: BU | H116: Sector | I116: Otros | J116: MSCI | L116: Ecopetrol | M116: Ecopetrol | N116: FALSE | O116: 226.35 | P116: 0.00019396169 | Q116: 2.7113124 | R116: 613.70556 | S116: 0.043903229 | T116: =O116*Q116 | U116: =O116*P116
A117: 202606 | B117: Ex_Integra | C117: F1 | D117: IN-FONDO1 | E117: 59509428AJ82 | F117: US279158AJ82 | G117: BU | H117: Sector | I117: Otros | J117: MSCI | L117: Ecopetrol | M117: Ecopetrol | N117: FALSE | O117: 226.35 | P117: 0.0018495288 | Q117: 6.8539207 | R117: 1551.3849 | S117: 0.41864084 | T117: =O117*Q117 | U117: =O117*P117
A118: 202606 | B118: Ex_Integra | C118: F2 | D118: IN-FONDO2 | E118: 59509428AQ26 | F118: US279158AQ26 | G118: BU | H118: Sector | I118: Otros | J118: MSCI | L118: Ecopetrol | M118: Ecopetrol | N118: FALSE | O118: 226.35 | P118: 0.0015394832 | Q118: 21.519815 | R118: 4871.0101 | S118: 0.34846201 | T118: =O118*Q118 | U118: =O118*P118
A119: 202606 | B119: Ex_Integra | C119: F1 | D119: IN-FONDO1 | E119: 59509428AQ26 | F119: US279158AQ26 | G119: BU | H119: Sector | I119: Otros | J119: MSCI | L119: Ecopetrol | M119: Ecopetrol | N119: FALSE | O119: 226.35 | P119: 0.00095448814 | Q119: 3.5371096 | R119: 800.62476 | S119: 0.21604839 | T119: =O119*Q119 | U119: =O119*P119
A120: 202606 | B120: Ex_Integra | C120: F2 | D120: IN-FONDO2 | E120: 59509428AE95 | F120: US279158AE95 | G120: BU | H120: Sector | I120: Otros | J120: MSCI | L120: Ecopetrol | M120: Ecopetrol | N120: FALSE | O120: 226.35 | P120: 0.00069125132 | Q120: 9.6627238 | R120: 2187.1575 | S120: 0.15646474 | T120: =O120*Q120 | U120: =O120*P120
A121: 202606 | B121: Ex_Integra | C121: F1 | D121: IN-FONDO1 | E121: 59509428AE95 | F121: US279158AE95 | G121: BU | H121: Sector | I121: Otros | J121: MSCI | L121: Ecopetrol | M121: Ecopetrol | N121: FALSE | O121: 226.35 | P121: 0.0036825872 | Q121: 13.646806 | R121: 3088.9546 | S121: 0.83355362 | T121: =O121*Q121 | U121: =O121*P121
A122: 202606 | B122: Ex_Integra | C122: F2 | D122: IN-FONDO2 | E122: 59509428AS81 | F122: US279158AS81 | G122: BU | H122: Sector | I122: Otros | J122: MSCI | L122: Ecopetrol | M122: Ecopetrol | N122: FALSE | O122: 226.35 | P122: 3.4673481e-08 | Q122: 0.00048468662 | R122: 0.10970882 | S122: 7.8483423e-06 | T122: =O122*Q122 | U122: =O122*P122
A123: 202606 | B123: Ex_Integra | C123: F1 | D123: IN-FONDO1 | E123: 59509428AS81 | F123: US279158AS81 | G123: BU | H123: Sector | I123: Otros | J123: MSCI | L123: Ecopetrol | M123: Ecopetrol | N123: FALSE | O123: 226.35 | P123: 0.0016026238 | Q123: 5.9389486 | R123: 1344.281 | S123: 0.3627539 | T123: =O123*Q123 | U123: =O123*P123
A124: 202606 | B124: Ex_Integra | C124: F1 | D124: IN-FONDO1 | E124: 59509428AV11 | F124: US279158AV11 | G124: BU | H124: Sector | I124: Otros | J124: MSCI | M124: nan | N124: FALSE | O124: 226.35 | P124: 0.0019937232 | Q124: 7.3882715 | R124: 1672.3353 | S124: 0.45127925 | T124: =O124*Q124 | U124: =O124*P124
A125: 202606 | B125: Ex_Integra | C125: F2 | D125: IN-FONDO2 | E125: 12535622BA92 | F125: USP58072BA92 | G125: BU | H125: Sector | I125: Otros | J125: MSCI | M125: nan | N125: FALSE | O125: 336.19 | P125: 0.0015549655 | Q125: 21.736236 | R125: 7307.5052 | S125: 0.52276384 | T125: =O125*Q125 | U125: =O125*P125
A126: 202606 | B126: Ex_Integra | C126: F1 | D126: IN-FONDO1 | E126: 12535622BA92 | F126: USP58072BA92 | G126: BU | H126: Sector | I126: Otros | J126: MSCI | M126: nan | N126: FALSE | O126: 336.19 | P126: 0.0021389047 | Q126: 7.92628 | R126: 2664.7361 | S126: 0.71907837 | T126: =O126*Q126 | U126: =O126*P126
A127: 202606 | B127: Ex_Integra | C127: F1 | D127: IN-FONDO1 | E127: 2100022V2D64 | F127: US05971V2D64 | G127: BU | H127: Sector | I127: Otros | J127: MSCI | L127: BCP | M127: BCP | N127: FALSE | O127: 0.44 | P127: 0.00050591034 | Q127: 1.8747853 | R127: 0.82490552 | S127: 0.00022260055 | T127: =O127*Q127 | U127: =O127*P127
A128: 202606 | B128: Ex_Integra | C128: F3 | D128: IN-FONDO3 | E128: 2100022V2D64 | F128: US05971V2D64 | G128: BU | H128: Sector | I128: Otros | J128: MSCI | L128: BCP | M128: BCP | N128: FALSE | O128: 0.44 | P128: 0.00055858862 | Q128: 1.9898722 | R128: 0.87554377 | S128: 0.00024577899 | T128: =O128*Q128 | U128: =O128*P128
A129: 202606 | B129: Ex_Integra | C129: F2 | D129: IN-FONDO2 | E129: 2100022V2H78 | F129: US05971V2H78 | G129: BU | H129: Sector | I129: Otros | J129: MSCI | M129: nan | N129: FALSE | O129: 0.44 | P129: 0.00077234824 | Q129: 10.796345 | R129: 4.7503918 | S129: 0.00033983323 | T129: =O129*Q129 | U129: =O129*P129
A130: 202606 | B130: Ex_Integra | C130: F2 | D130: IN-FONDO2 | E130: 2100022V2K08 | F130: US05971V2K08 | G130: BU | H130: Sector | I130: Otros | J130: MSCI | M130: nan | N130: FALSE | O130: 0.44 | P130: 0.002465275 | Q130: 34.461087 | R130: 15.162878 | S130: 0.001084721 | T130: =O130*Q130 | U130: =O130*P130
A131: 202606 | B131: Ex_Integra | C131: F1 | D131: IN-FONDO1 | E131: 2100022V2K08 | F131: US05971V2K08 | G131: BU | H131: Sector | I131: Otros | J131: MSCI | M131: nan | N131: FALSE | O131: 0.44 | P131: 0.0013184287 | Q131: 4.8857881 | R131: 2.1497468 | S131: 0.00058010862 | T131: =O131*Q131 | U131: =O131*P131
A132: 202606 | B132: Ex_Integra | C132: F1 | D132: IN-FONDO1 | E132: 2100022V2J35 | F132: US05971V2J35 | G132: BU | H132: Sector | I132: Otros | J132: MSCI | M132: nan | N132: FALSE | O132: 0.44 | P132: 0.0041819299 | Q132: 15.497253 | R132: 6.8187914 | S132: 0.0018400492 | T132: =O132*Q132 | U132: =O132*P132
A133: 202606 | B133: Ex_Integra | C133: F2 | D133: IN-FONDO2 | E133: 2100022V2J35 | F133: US05971V2J35 | G133: BU | H133: Sector | I133: Otros | J133: MSCI | M133: nan | N133: FALSE | O133: 0.44 | P133: 0.0012254904 | Q133: 17.130636 | R133: 7.5374799 | S133: 0.00053921576 | T133: =O133*Q133 | U133: =O133*P133
A134: 202606 | B134: Ex_Integra | C134: F1 | D134: IN-FONDO1 | E134: 21000325AG03 | F134: USP13435AG03 | G134: BU | H134: Sector | I134: Otros | J134: MSCI | M134: nan | N134: FALSE | O134: 0.48 | P134: 0.00087420033 | Q134: 3.2395818 | R134: 1.5549993 | S134: 0.00041961616 | T134: =O134*Q134 | U134: =O134*P134
A135: 202606 | B135: Ex_Integra | C135: F2 | D135: IN-FONDO2 | E135: 21000325AG03 | F135: USP13435AG03 | G135: BU | H135: Sector | I135: Otros | J135: MSCI | M135: nan | N135: FALSE | O135: 0.48 | P135: 0.00045506927 | Q135: 6.36123 | R135: 3.0533904 | S135: 0.00021843325 | T135: =O135*Q135 | U135: =O135*P135
A136: 202606 | B136: Ex_Integra | C136: F1 | D136: IN-FONDO1 | E136: 21000325AF20 | F136: USP13435AF20 | G136: BU | H136: Sector | I136: Otros | J136: MSCI | M136: nan | N136: FALSE | O136: 0.48 | P136: 4.7768291e-05 | Q136: 0.1770181 | R136: 0.08496869 | S136: 2.292878e-05 | T136: =O136*Q136 | U136: =O136*P136
A137: 202606 | B137: Ex_Integra | C137: F2 | D137: IN-FONDO2 | E137: 1254342KAB22 | F137: USP4R21KAB22 | G137: BU | H137: Sector | I137: Otros | J137: MSCI | M137: nan | N137: FALSE | O137: 4.3 | P137: 0.0023431021 | Q137: 32.75328 | R137: 140.8391 | S137: 0.010075339 | T137: =O137*Q137 | U137: =O137*P137
A138: 202606 | B138: Ex_Integra | C138: F1 | D138: IN-FONDO1 | E138: 1254342KAB22 | F138: USP4R21KAB22 | G138: BU | H138: Sector | I138: Otros | J138: MSCI | M138: nan | N138: FALSE | O138: 4.3 | P138: 0.004949764 | Q138: 18.342667 | R138: 78.873466 | S138: 0.021283985 | T138: =O138*Q138 | U138: =O138*P138
A139: 202606 | B139: Ex_Integra | C139: F2 | D139: IN-FONDO2 | E139: 27211826AB16 | F139: USP56236AB16 | G139: BU | H139: Sector | I139: Otros | J139: MSCI | L139: InRetail Consumer | M139: InRetail Consumer | N139: FALSE | O139: 23.09 | P139: 4.020473e-05 | Q139: 0.56200572 | R139: 12.976712 | S139: 0.00092832721 | T139: =O139*Q139 | U139: =O139*P139
A140: 202606 | B140: Ex_Integra | C140: F1 | D140: IN-FONDO1 | E140: 2220292FAB50 | F140: USP0091FAB50 | G140: BU | H140: Sector | I140: Otros | J140: MSCI | M140: nan | N140: FALSE | O140: 140.61 | P140: 0.0099470922 | Q140: 36.861595 | R140: 5183.1089 | S140: 1.3986606 | T140: =O140*Q140 | U140: =O140*P140
A141: 202606 | B141: Ex_Integra | C141: F2 | D141: IN-FONDO2 | E141: 2220292FAB50 | F141: USP0091FAB50 | G141: BU | H141: Sector | I141: Otros | J141: MSCI | M141: nan | N141: FALSE | O141: 140.61 | P141: 0.0023303574 | Q141: 32.575127 | R141: 4580.3886 | S141: 0.32767155 | T141: =O141*Q141 | U141: =O141*P141
A142: 202606 | B142: Ex_Integra | C142: F2 | D142: IN-FONDO2 | E142: 25210529AF09 | F142: USP42009AF09 | G142: BU | H142: Sector | I142: Otros | J142: MSCI | M142: nan | N142: FALSE | O142: 0.31 | P142: 0.00035512434 | Q142: 4.9641401 | R142: 1.5388834 | S142: 0.00011008855 | T142: =O142*Q142 | U142: =O142*P142
A143: 202606 | B143: Ex_Integra | C143: F1 | D143: IN-FONDO1 | E143: 25210529AF09 | F143: USP42009AF09 | G143: BU | H143: Sector | I143: Otros | J143: MSCI | M143: nan | N143: FALSE | O143: 0.31 | P143: 0.0010954535 | Q143: 4.0594941 | R143: 1.2584432 | S143: 0.00033959058 | T143: =O143*Q143 | U143: =O143*P143
A144: 202606 | B144: Ex_Integra | C144: F2 | D144: IN-FONDO2 | E144: 27211723AE14 | F144: USP56243AE14 | G144: BU | H144: Sector | I144: Otros | J144: MSCI | M144: nan | N144: FALSE | O144: 23.09 | P144: 0.0008369107 | Q144: 11.698838 | R144: 270.12616 | S144: 0.019324268 | T144: =O144*Q144 | U144: =O144*P144
A145: 202606 | B145: Ex_Integra | C145: F1 | D145: IN-FONDO1 | E145: 27211723AE14 | F145: USP56243AE14 | G145: BU | H145: Sector | I145: Otros | J145: MSCI | M145: nan | N145: FALSE | O145: 23.09 | P145: 0.00029657289 | Q145: 1.0990297 | R145: 25.376596 | S145: 0.006847868 | T145: =O145*Q145 | U145: =O145*P145
A146: 202606 | B146: Ex_Integra | C146: F3 | D146: IN-FONDO3 | E146: 2220892BAE13 | F146: USP7721BAE13 | G146: BU | H146: Sector | I146: Otros | J146: MSCI | L146: Perú LNG | M146: Perú LNG | N146: FALSE | O146: 968.15 | P146: 3.7627554e-19 | Q146: 1.3404144e-15 | R146: 1.2977222e-12 | S146: 3.6429117e-16 | T146: =O146*Q146 | U146: =O146*P146
A147: 202606 | B147: Ex_Integra | C147: F1 | D147: IN-FONDO1 | E147: 2220111KEA71 | F147: USP0161KEA71 | G147: BU | H147: Sector | I147: Otros | J147: MSCI | M147: nan | N147: FALSE | O147: 35.74 | P147: 0.017546729 | Q147: 65.02407 | R147: 2323.9603 | S147: 0.62712009 | T147: =O147*Q147 | U147: =O147*P147
A148: 202606 | B148: Ex_Integra | C148: F2 | D148: IN-FONDO2 | E148: 2220111KEA71 | F148: USP0161KEA71 | G148: BU | H148: Sector | I148: Otros | J148: MSCI | M148: nan | N148: FALSE | O148: 35.74 | P148: 0.0030615054 | Q148: 42.795551 | R148: 1529.513 | S148: 0.1094182 | T148: =O148*Q148 | U148: =O148*P148
A149: 202606 | B149: Ex_Integra | C149: F2 | D149: IN-FONDO2 | E149: 22210611802U | F149: PEP70215M017 | G149: BU | H149: Sector | I149: Otros | J149: MSCI | L149: Calidda* | M149: Calidda | N149: FALSE | O149: 23.88 | P149: 1.8059143e-06 | Q149: 0.025244148 | R149: 0.60283026 | S149: 4.3125233e-05 | T149: =O149*Q149 | U149: =O149*P149
...

Sheet Huella Soberanos
C1: Corte | D1: Perú | E1: Brasil | F1: Colombia | G1: México | H1: Chile | I1: Sudáfrica | J1: Total | K1: Variación %
C2: Dic25 | D2: =SUMIFS('BD'!$R$2:$R$6977,'BD'!$H$2:$H$6977,"Soberanos",'BD'!$B$2:$B$6977,"Integra",'BD'!$K$2:$K$6977,D$1,'BD'!$A$2:$A$6977,"202512") | E2: =SUMIFS('BD'!$R$2:$R$6977,'BD'!$H$2:$H$6977,"Soberanos",'BD'!$B$2:$B$6977,"Integra",'BD'!$K$2:$K$6977,E$1,'BD'!$A$2:$A$6977,"202512") | F2: =SUMIFS('BD'!$R$2:$R$6977,'BD'!$H$2:$H$6977,"Soberanos",'BD'!$B$2:$B$6977,"Integra",'BD'!$K$2:$K$6977,F$1,'BD'!$A$2:$A$6977,"202512") | G2: =SUMIFS('BD'!$R$2:$R$6977,'BD'!$H$2:$H$6977,"Soberanos",'BD'!$B$2:$B$6977,"Integra",'BD'!$K$2:$K$6977,G$1,'BD'!$A$2:$A$6977,"202512") | H2: =SUMIFS('BD'!$R$2:$R$6977,'BD'!$H$2:$H$6977,"Soberanos",'BD'!$B$2:$B$6977,"Integra",'BD'!$K$2:$K$6977,H$1,'BD'!$A$2:$A$6977,"202512") | I2: =SUMIFS('BD'!$R$2:$R$6977,'BD'!$H$2:$H$6977,"Soberanos",'BD'!$B$2:$B$6977,"Integra",'BD'!$K$2:$K$6977,I$1,'BD'!$A$2:$A$6977,"202512") | J2: =SUM(D2:I2)
C3: Jun26 | D3: =SUMIFS('BD'!$R$2:$R$6977,'BD'!$H$2:$H$6977,"Soberanos",'BD'!$B$2:$B$6977,"Integra",'BD'!$K$2:$K$6977,D$1,'BD'!$A$2:$A$6977,"202606") | E3: =SUMIFS('BD'!$R$2:$R$6977,'BD'!$H$2:$H$6977,"Soberanos",'BD'!$B$2:$B$6977,"Integra",'BD'!$K$2:$K$6977,E$1,'BD'!$A$2:$A$6977,"202606") | F3: =SUMIFS('BD'!$R$2:$R$6977,'BD'!$H$2:$H$6977,"Soberanos",'BD'!$B$2:$B$6977,"Integra",'BD'!$K$2:$K$6977,F$1,'BD'!$A$2:$A$6977,"202606") | G3: =SUMIFS('BD'!$R$2:$R$6977,'BD'!$H$2:$H$6977,"Soberanos",'BD'!$B$2:$B$6977,"Integra",'BD'!$K$2:$K$6977,G$1,'BD'!$A$2:$A$6977,"202606") | H3: =SUMIFS('BD'!$R$2:$R$6977,'BD'!$H$2:$H$6977,"Soberanos",'BD'!$B$2:$B$6977,"Integra",'BD'!$K$2:$K$6977,H$1,'BD'!$A$2:$A$6977,"202606") | I3: =SUMIFS('BD'!$R$2:$R$6977,'BD'!$H$2:$H$6977,"Soberanos",'BD'!$B$2:$B$6977,"Integra",'BD'!$K$2:$K$6977,I$1,'BD'!$A$2:$A$6977,"202606") | J3: =SUM(D3:I3) | K3: =IFERROR(J3/J2-1,"")

Sheet Intensidad Soberanos
C1: Corte | D1: Perú | E1: Brasil | F1: Colombia | G1: México | H1: Chile | I1: Sudáfrica | J1: Total | K1: Variación %
C2: Dic25 | D2: =SUMIFS('BD'!$S$2:$S$6977,'BD'!$H$2:$H$6977,"Soberanos",'BD'!$B$2:$B$6977,"Integra",'BD'!$K$2:$K$6977,D$1,'BD'!$A$2:$A$6977,"202512") | E2: =SUMIFS('BD'!$S$2:$S$6977,'BD'!$H$2:$H$6977,"Soberanos",'BD'!$B$2:$B$6977,"Integra",'BD'!$K$2:$K$6977,E$1,'BD'!$A$2:$A$6977,"202512") | F2: =SUMIFS('BD'!$S$2:$S$6977,'BD'!$H$2:$H$6977,"Soberanos",'BD'!$B$2:$B$6977,"Integra",'BD'!$K$2:$K$6977,F$1,'BD'!$A$2:$A$6977,"202512") | G2: =SUMIFS('BD'!$S$2:$S$6977,'BD'!$H$2:$H$6977,"Soberanos",'BD'!$B$2:$B$6977,"Integra",'BD'!$K$2:$K$6977,G$1,'BD'!$A$2:$A$6977,"202512") | H2: =SUMIFS('BD'!$S$2:$S$6977,'BD'!$H$2:$H$6977,"Soberanos",'BD'!$B$2:$B$6977,"Integra",'BD'!$K$2:$K$6977,H$1,'BD'!$A$2:$A$6977,"202512") | I2: =SUMIFS('BD'!$S$2:$S$6977,'BD'!$H$2:$H$6977,"Soberanos",'BD'!$B$2:$B$6977,"Integra",'BD'!$K$2:$K$6977,I$1,'BD'!$A$2:$A$6977,"202512") | J2: =SUM(D2:I2)
C3: Jun26 | D3: =SUMIFS('BD'!$S$2:$S$6977,'BD'!$H$2:$H$6977,"Soberanos",'BD'!$B$2:$B$6977,"Integra",'BD'!$K$2:$K$6977,D$1,'BD'!$A$2:$A$6977,"202606") | E3: =SUMIFS('BD'!$S$2:$S$6977,'BD'!$H$2:$H$6977,"Soberanos",'BD'!$B$2:$B$6977,"Integra",'BD'!$K$2:$K$6977,E$1,'BD'!$A$2:$A$6977,"202606") | F3: =SUMIFS('BD'!$S$2:$S$6977,'BD'!$H$2:$H$6977,"Soberanos",'BD'!$B$2:$B$6977,"Integra",'BD'!$K$2:$K$6977,F$1,'BD'!$A$2:$A$6977,"202606") | G3: =SUMIFS('BD'!$S$2:$S$6977,'BD'!$H$2:$H$6977,"Soberanos",'BD'!$B$2:$B$6977,"Integra",'BD'!$K$2:$K$6977,G$1,'BD'!$A$2:$A$6977,"202606") | H3: =SUMIFS('BD'!$S$2:$S$6977,'BD'!$H$2:$H$6977,"Soberanos",'BD'!$B$2:$B$6977,"Integra",'BD'!$K$2:$K$6977,H$1,'BD'!$A$2:$A$6977,"202606") | I3: =SUMIFS('BD'!$S$2:$S$6977,'BD'!$H$2:$H$6977,"Soberanos",'BD'!$B$2:$B$6977,"Integra",'BD'!$K$2:$K$6977,I$1,'BD'!$A$2:$A$6977,"202606") | J3: =SUM(D3:I3) | K3: =IFERROR(J3/J2-1,"")

Sheet Huella por Sector
C1: Corte | D1: Materials | E1: Utilities | F1: Otros | G1: RF | H1: RV | I1: Proxies | J1: Alts | K1: Total | L1: Variación %
C2: Dic25 | D2: =SUMIFS('BD'!$R$2:$R$6977,'BD'!$H$2:$H$6977,"Sector",'BD'!$B$2:$B$6977,"Integra",'BD'!$I$2:$I$6977,D$1,'BD'!$J$2:$J$6977,"MSCI",'BD'!$A$2:$A$6977,"202512") | E2: =SUMIFS('BD'!$R$2:$R$6977,'BD'!$H$2:$H$6977,"Sector",'BD'!$B$2:$B$6977,"Integra",'BD'!$I$2:$I$6977,E$1,'BD'!$J$2:$J$6977,"MSCI",'BD'!$A$2:$A$6977,"202512") | F2: =SUMIFS('BD'!$R$2:$R$6977,'BD'!$H$2:$H$6977,"Sector",'BD'!$B$2:$B$6977,"Integra",'BD'!$I$2:$I$6977,F$1,'BD'!$J$2:$J$6977,"MSCI",'BD'!$A$2:$A$6977,"202512") | G2: =SUMIFS('BD'!$R$2:$R$6977,'BD'!$H$2:$H$6977,"Sector",'BD'!$B$2:$B$6977,"Integra",'BD'!$I$2:$I$6977,G$1,'BD'!$J$2:$J$6977,"MSCI",'BD'!$A$2:$A$6977,"202512") | H2: =SUMIFS('BD'!$R$2:$R$6977,'BD'!$H$2:$H$6977,"Sector",'BD'!$B$2:$B$6977,"Integra",'BD'!$I$2:$I$6977,H$1,'BD'!$J$2:$J$6977,"MSCI",'BD'!$A$2:$A$6977,"202512") | I2: =SUMIFS('BD'!$R$2:$R$6977,'BD'!$H$2:$H$6977,"Sector",'BD'!$B$2:$B$6977,"Integra",'BD'!$I$2:$I$6977,I$1,'BD'!$J$2:$J$6977,"Proxies",'BD'!$A$2:$A$6977,"202512") | J2: =SUMIFS('BD'!$R$2:$R$6977,'BD'!$H$2:$H$6977,"Sector",'BD'!$B$2:$B$6977,"Integra",'BD'!$I$2:$I$6977,J$1,'BD'!$J$2:$J$6977,"Proxies",'BD'!$A$2:$A$6977,"202512") | K2: =SUM(D2:J2)
C3: Jun26 | D3: =SUMIFS('BD'!$R$2:$R$6977,'BD'!$H$2:$H$6977,"Sector",'BD'!$B$2:$B$6977,"Integra",'BD'!$I$2:$I$6977,D$1,'BD'!$J$2:$J$6977,"MSCI",'BD'!$A$2:$A$6977,"202606") | E3: =SUMIFS('BD'!$R$2:$R$6977,'BD'!$H$2:$H$6977,"Sector",'BD'!$B$2:$B$6977,"Integra",'BD'!$I$2:$I$6977,E$1,'BD'!$J$2:$J$6977,"MSCI",'BD'!$A$2:$A$6977,"202606") | F3: =SUMIFS('BD'!$R$2:$R$6977,'BD'!$H$2:$H$6977,"Sector",'BD'!$B$2:$B$6977,"Integra",'BD'!$I$2:$I$6977,F$1,'BD'!$J$2:$J$6977,"MSCI",'BD'!$A$2:$A$6977,"202606") | G3: =SUMIFS('BD'!$R$2:$R$6977,'BD'!$H$2:$H$6977,"Sector",'BD'!$B$2:$B$6977,"Integra",'BD'!$I$2:$I$6977,G$1,'BD'!$J$2:$J$6977,"MSCI",'BD'!$A$2:$A$6977,"202606") | H3: =SUMIFS('BD'!$R$2:$R$6977,'BD'!$H$2:$H$6977,"Sector",'BD'!$B$2:$B$6977,"Integra",'BD'!$I$2:$I$6977,H$1,'BD'!$J$2:$J$6977,"MSCI",'BD'!$A$2:$A$6977,"202606") | I3: =SUMIFS('BD'!$R$2:$R$6977,'BD'!$H$2:$H$6977,"Sector",'BD'!$B$2:$B$6977,"Integra",'BD'!$I$2:$I$6977,I$1,'BD'!$J$2:$J$6977,"Proxies",'BD'!$A$2:$A$6977,"202606") | J3: =SUMIFS('BD'!$R$2:$R$6977,'BD'!$H$2:$H$6977,"Sector",'BD'!$B$2:$B$6977,"Integra",'BD'!$I$2:$I$6977,J$1,'BD'!$J$2:$J$6977,"Proxies",'BD'!$A$2:$A$6977,"202606") | K3: =SUM(D3:J3) | L3: =IFERROR(K3/K2-1,"")

Sheet Intensidad por Sector
C1: Corte | D1: Materials | E1: Utilities | F1: Otros | G1: RF | H1: RV | I1: Proxies | J1: Alts | K1: Total | L1: Variación %
C2: Dic25 | D2: =SUMIFS('BD'!$S$2:$S$6977,'BD'!$H$2:$H$6977,"Sector",'BD'!$B$2:$B$6977,"Integra",'BD'!$I$2:$I$6977,D$1,'BD'!$J$2:$J$6977,"MSCI",'BD'!$A$2:$A$6977,"202512") | E2: =SUMIFS('BD'!$S$2:$S$6977,'BD'!$H$2:$H$6977,"Sector",'BD'!$B$2:$B$6977,"Integra",'BD'!$I$2:$I$6977,E$1,'BD'!$J$2:$J$6977,"MSCI",'BD'!$A$2:$A$6977,"202512") | F2: =SUMIFS('BD'!$S$2:$S$6977,'BD'!$H$2:$H$6977,"Sector",'BD'!$B$2:$B$6977,"Integra",'BD'!$I$2:$I$6977,F$1,'BD'!$J$2:$J$6977,"MSCI",'BD'!$A$2:$A$6977,"202512") | G2: =SUMIFS('BD'!$S$2:$S$6977,'BD'!$H$2:$H$6977,"Sector",'BD'!$B$2:$B$6977,"Integra",'BD'!$I$2:$I$6977,G$1,'BD'!$J$2:$J$6977,"MSCI",'BD'!$A$2:$A$6977,"202512") | H2: =SUMIFS('BD'!$S$2:$S$6977,'BD'!$H$2:$H$6977,"Sector",'BD'!$B$2:$B$6977,"Integra",'BD'!$I$2:$I$6977,H$1,'BD'!$J$2:$J$6977,"MSCI",'BD'!$A$2:$A$6977,"202512") | I2: =SUMIFS('BD'!$S$2:$S$6977,'BD'!$H$2:$H$6977,"Sector",'BD'!$B$2:$B$6977,"Integra",'BD'!$I$2:$I$6977,I$1,'BD'!$J$2:$J$6977,"Proxies",'BD'!$A$2:$A$6977,"202512") | J2: =SUMIFS('BD'!$S$2:$S$6977,'BD'!$H$2:$H$6977,"Sector",'BD'!$B$2:$B$6977,"Integra",'BD'!$I$2:$I$6977,J$1,'BD'!$J$2:$J$6977,"Proxies",'BD'!$A$2:$A$6977,"202512") | K2: =SUM(D2:J2)
C3: Jun26 | D3: =SUMIFS('BD'!$S$2:$S$6977,'BD'!$H$2:$H$6977,"Sector",'BD'!$B$2:$B$6977,"Integra",'BD'!$I$2:$I$6977,D$1,'BD'!$J$2:$J$6977,"MSCI",'BD'!$A$2:$A$6977,"202606") | E3: =SUMIFS('BD'!$S$2:$S$6977,'BD'!$H$2:$H$6977,"Sector",'BD'!$B$2:$B$6977,"Integra",'BD'!$I$2:$I$6977,E$1,'BD'!$J$2:$J$6977,"MSCI",'BD'!$A$2:$A$6977,"202606") | F3: =SUMIFS('BD'!$S$2:$S$6977,'BD'!$H$2:$H$6977,"Sector",'BD'!$B$2:$B$6977,"Integra",'BD'!$I$2:$I$6977,F$1,'BD'!$J$2:$J$6977,"MSCI",'BD'!$A$2:$A$6977,"202606") | G3: =SUMIFS('BD'!$S$2:$S$6977,'BD'!$H$2:$H$6977,"Sector",'BD'!$B$2:$B$6977,"Integra",'BD'!$I$2:$I$6977,G$1,'BD'!$J$2:$J$6977,"MSCI",'BD'!$A$2:$A$6977,"202606") | H3: =SUMIFS('BD'!$S$2:$S$6977,'BD'!$H$2:$H$6977,"Sector",'BD'!$B$2:$B$6977,"Integra",'BD'!$I$2:$I$6977,H$1,'BD'!$J$2:$J$6977,"MSCI",'BD'!$A$2:$A$6977,"202606") | I3: =SUMIFS('BD'!$S$2:$S$6977,'BD'!$H$2:$H$6977,"Sector",'BD'!$B$2:$B$6977,"Integra",'BD'!$I$2:$I$6977,I$1,'BD'!$J$2:$J$6977,"Proxies",'BD'!$A$2:$A$6977,"202606") | J3: =SUMIFS('BD'!$S$2:$S$6977,'BD'!$H$2:$H$6977,"Sector",'BD'!$B$2:$B$6977,"Integra",'BD'!$I$2:$I$6977,J$1,'BD'!$J$2:$J$6977,"Proxies",'BD'!$A$2:$A$6977,"202606") | K3: =SUM(D3:J3) | L3: =IFERROR(K3/K2-1,"")

Sheet Intensidad FFMM
A1: Corte | B1: Corte_Rol | C1: AFP | D1: Tipo_Fila | E1: Bloque | F1: Gestion | G1: Instrumento | H1: SubCategoria | I1: Benchmark_Tipo | J1: Benchmark_Nombre | K1: Metrica | L1: Valor | N1: Instrumento | O1: Intensidad | P1: Benchmark
A2: 202512 | B2: Comparación | C2: Ex_Integra | D2: Benchmark | I2: Escalar_Portafolio | J2: Total_Integra | K2: Intensidad | L2: 75.896051 | N2: BlackRock - iShares Korea (Equities) | O2: =SUMIFS($L$2:$L$426,$G$2:$G$426,"BlackRock - iShares Korea",$E$2:$E$426,"Equities",$D$2:$D$426,"Instrumento",$C$2:$C$426,"Integra",$A$2:$A$426,"202606") | P2: 50.676744
A3: 202512 | B3: Comparación | C3: Ex_Integra | D3: Benchmark | I3: Escalar_Portafolio | J3: F1_Integra | K3: Intensidad | L3: 37.747666 | N3: Global X - Copper Miners ETF (Equities) | O3: =SUMIFS($L$2:$L$426,$G$2:$G$426,"Global X - Copper Miners ETF",$E$2:$E$426,"Equities",$D$2:$D$426,"Instrumento",$C$2:$C$426,"Integra",$A$2:$A$426,"202606") | P3: 50.676744
A4: 202512 | B4: Comparación | C4: Ex_Integra | D4: Benchmark | I4: Escalar_Portafolio | J4: F2_Integra | K4: Intensidad | L4: 16.583562 | N4: BNP Paribas - Japan Small Caps (Equities) | O4: =SUMIFS($L$2:$L$426,$G$2:$G$426,"BNP Paribas - Japan Small Caps",$E$2:$E$426,"Equities",$D$2:$D$426,"Instrumento",$C$2:$C$426,"Integra",$A$2:$A$426,"202606") | P4: 50.676744
A5: 202512 | B5: Comparación | C5: Ex_Integra | D5: Benchmark | I5: Escalar_Portafolio | J5: F3_Integra | K5: Intensidad | L5: 21.564823 | N5: JP Morgan - Korea Equity Fund (Equities) | O5: =SUMIFS($L$2:$L$426,$G$2:$G$426,"JP Morgan - Korea Equity Fund",$E$2:$E$426,"Equities",$D$2:$D$426,"Instrumento",$C$2:$C$426,"Integra",$A$2:$A$426,"202606") | P5: 50.676744
A6: 202512 | B6: Comparación | C6: Habitat | D6: Benchmark | I6: Escalar_Portafolio | J6: Total_Integra | K6: Intensidad | L6: 63.150033 | N6: BlackRock - iShares PHLX Semiconductor ETF (Equities) | O6: =SUMIFS($L$2:$L$426,$G$2:$G$426,"BlackRock - iShares PHLX Semiconductor ETF",$E$2:$E$426,"Equities",$D$2:$D$426,"Instrumento",$C$2:$C$426,"Integra",$A$2:$A$426,"202606") | P6: 50.676744
A7: 202512 | B7: Comparación | C7: Habitat | D7: Benchmark | I7: Escalar_Portafolio | J7: F1_Integra | K7: Intensidad | L7: 27.245936 | N7: BlackRock - iShares PHLX Semiconductor ETF (Equities) | O7: =SUMIFS($L$2:$L$426,$G$2:$G$426,"BlackRock - iShares PHLX Semiconductor ETF",$E$2:$E$426,"Equities",$D$2:$D$426,"Instrumento",$C$2:$C$426,"Integra",$A$2:$A$426,"202606") | P7: 50.676744
A8: 202512 | B8: Comparación | C8: Habitat | D8: Benchmark | I8: Escalar_Portafolio | J8: F2_Integra | K8: Intensidad | L8: 13.075085 | N8: BlackRock - iShares Korea (Equities) | O8: =SUMIFS($L$2:$L$426,$G$2:$G$426,"BlackRock - iShares Korea",$E$2:$E$426,"Equities",$D$2:$D$426,"Instrumento",$C$2:$C$426,"Integra",$A$2:$A$426,"202606") | P8: 50.676744
A9: 202512 | B9: Comparación | C9: Habitat | D9: Benchmark | I9: Escalar_Portafolio | J9: F3_Integra | K9: Intensidad | L9: 22.829012 | N9: Global X - Copper Miners ETF (Equities) | O9: =SUMIFS($L$2:$L$426,$G$2:$G$426,"Global X - Copper Miners ETF",$E$2:$E$426,"Equities",$D$2:$D$426,"Instrumento",$C$2:$C$426,"Integra",$A$2:$A$426,"202606") | P9: 50.676744
A10: 202512 | B10: Comparación | C10: Integra | D10: Benchmark | I10: Escalar_Portafolio | J10: Total_Integra | K10: Intensidad | L10: 65.224844 | N10: BNP Paribas - Japan Small Caps (Equities) | O10: =SUMIFS($L$2:$L$426,$G$2:$G$426,"BNP Paribas - Japan Small Caps",$E$2:$E$426,"Equities",$D$2:$D$426,"Instrumento",$C$2:$C$426,"Integra",$A$2:$A$426,"202606") | P10: 50.676744
A11: 202512 | B11: Comparación | C11: Integra | D11: Benchmark | I11: Escalar_Portafolio | J11: F1_Integra | K11: Intensidad | L11: 28.069357 | N11: JP Morgan - Korea Equity Fund (Equities) | O11: =SUMIFS($L$2:$L$426,$G$2:$G$426,"JP Morgan - Korea Equity Fund",$E$2:$E$426,"Equities",$D$2:$D$426,"Instrumento",$C$2:$C$426,"Integra",$A$2:$A$426,"202606") | P11: 50.676744
A12: 202512 | B12: Comparación | C12: Integra | D12: Benchmark | I12: Escalar_Portafolio | J12: F2_Integra | K12: Intensidad | L12: 14.076505 | N12: Moneda - Latam High Yield (Fixed Income) | O12: =SUMIFS($L$2:$L$426,$G$2:$G$426,"Moneda - Latam High Yield",$E$2:$E$426,"Fixed Income",$D$2:$D$426,"Instrumento",$C$2:$C$426,"Integra",$A$2:$A$426,"202606") | P12: 50.676744
A13: 202512 | B13: Comparación | C13: Integra | D13: Benchmark | I13: Escalar_Portafolio | J13: F3_Integra | K13: Intensidad | L13: 23.078982 | N13: Vontobel - Emerging Markets Debt (Fixed Income) | O13: =SUMIFS($L$2:$L$426,$G$2:$G$426,"Vontobel - Emerging Markets Debt",$E$2:$E$426,"Fixed Income",$D$2:$D$426,"Instrumento",$C$2:$C$426,"Integra",$A$2:$A$426,"202606") | P13: 50.676744
A14: 202512 | B14: Comparación | C14: Prima | D14: Benchmark | I14: Escalar_Portafolio | J14: Total_Integra | K14: Intensidad | L14: 79.277836 | N14: Pimco - Emerging Markets Local Bond Fund (Fixed Income) | O14: =SUMIFS($L$2:$L$426,$G$2:$G$426,"Pimco - Emerging Markets Local Bond Fund",$E$2:$E$426,"Fixed Income",$D$2:$D$426,"Instrumento",$C$2:$C$426,"Integra",$A$2:$A$426,"202606") | P14: 50.676744
A15: 202512 | B15: Comparación | C15: Prima | D15: Benchmark | I15: Escalar_Portafolio | J15: F1_Integra | K15: Intensidad | L15: 43.397454 | N15: Moneda - Deuda Latam LCC (Fixed Income) | O15: =SUMIFS($L$2:$L$426,$G$2:$G$426,"Moneda - Deuda Latam LCC",$E$2:$E$426,"Fixed Income",$D$2:$D$426,"Instrumento",$C$2:$C$426,"Integra",$A$2:$A$426,"202606") | P15: 50.676744
A16: 202512 | B16: Comparación | C16: Prima | D16: Benchmark | I16: Escalar_Portafolio | J16: F2_Integra | K16: Intensidad | L16: 16.71005 | N16: Vontobel - Credit Opportunities (Fixed Income) | O16: =SUMIFS($L$2:$L$426,$G$2:$G$426,"Vontobel - Credit Opportunities",$E$2:$E$426,"Fixed Income",$D$2:$D$426,"Instrumento",$C$2:$C$426,"Integra",$A$2:$A$426,"202606") | P16: 50.676744
A17: 202512 | B17: Comparación | C17: Prima | D17: Benchmark | I17: Escalar_Portafolio | J17: F3_Integra | K17: Intensidad | L17: 19.170332 | N17: Vontobel - Credit Opportunities (Fixed Income) | O17: =SUMIFS($L$2:$L$426,$G$2:$G$426,"Vontobel - Credit Opportunities",$E$2:$E$426,"Fixed Income",$D$2:$D$426,"Instrumento",$C$2:$C$426,"Integra",$A$2:$A$426,"202606") | P17: 50.676744
A18: 202512 | B18: Comparación | C18: Profuturo | D18: Benchmark | I18: Escalar_Portafolio | J18: Total_Integra | K18: Intensidad | L18: 75.984063 | N18: Moneda - Latam High Yield (Fixed Income) | O18: =SUMIFS($L$2:$L$426,$G$2:$G$426,"Moneda - Latam High Yield",$E$2:$E$426,"Fixed Income",$D$2:$D$426,"Instrumento",$C$2:$C$426,"Integra",$A$2:$A$426,"202606") | P18: 50.676744
A19: 202512 | B19: Comparación | C19: Profuturo | D19: Benchmark | I19: Escalar_Portafolio | J19: F1_Integra | K19: Intensidad | L19: 34.14988 | N19: Pimco - Emerging Markets Local Bond Fund (Fixed Income) | O19: =SUMIFS($L$2:$L$426,$G$2:$G$426,"Pimco - Emerging Markets Local Bond Fund",$E$2:$E$426,"Fixed Income",$D$2:$D$426,"Instrumento",$C$2:$C$426,"Integra",$A$2:$A$426,"202606") | P19: 50.676744
A20: 202512 | B20: Comparación | C20: Profuturo | D20: Benchmark | I20: Escalar_Portafolio | J20: F2_Integra | K20: Intensidad | L20: 19.999563 | N20: Moneda - Deuda Latam LCC (Fixed Income) | O20: =SUMIFS($L$2:$L$426,$G$2:$G$426,"Moneda - Deuda Latam LCC",$E$2:$E$426,"Fixed Income",$D$2:$D$426,"Instrumento",$C$2:$C$426,"Integra",$A$2:$A$426,"202606") | P20: 50.676744
A21: 202512 | B21: Comparación | C21: Profuturo | D21: Benchmark | I21: Escalar_Portafolio | J21: F3_Integra | K21: Intensidad | L21: 21.83462 | N21: Vontobel - Emerging Markets Debt (Fixed Income) | O21: =SUMIFS($L$2:$L$426,$G$2:$G$426,"Vontobel - Emerging Markets Debt",$E$2:$E$426,"Fixed Income",$D$2:$D$426,"Instrumento",$C$2:$C$426,"Integra",$A$2:$A$426,"202606") | P21: 50.676744
A22: 202512 | B22: Comparación | C22: Ex_Integra | D22: Benchmark | E22: Equities | H22: DM | I22: Comparables_Subcat_Ajustado (x Weight del instrumento) | K22: Intensidad | L22: 63.45775
A23: 202512 | B23: Comparación | C23: Ex_Integra | D23: Benchmark | E23: Equities | H23: EM | I23: Comparables_Subcat_Ajustado (x Weight del instrumento) | K23: Intensidad | L23: 71.066596
A24: 202512 | B24: Comparación | C24: Ex_Integra | D24: Benchmark | E24: Equities | H24: Metales Preciosos | I24: Comparables_Subcat_Ajustado (x Weight del instrumento) | K24: Intensidad | L24: 78.727754
A25: 202512 | B25: Comparación | C25: Ex_Integra | D25: Benchmark | E25: Equities | H25: Peru | I25: Comparables_Subcat_Ajustado (x Weight del instrumento) | K25: Intensidad | L25: 31.332475
A26: 202512 | B26: Comparación | C26: Ex_Integra | D26: Benchmark | E26: Equities | H26: DM | I26: Comparables_Subcat_SinAjustar | K26: Intensidad | L26: 1.095698
A27: 202512 | B27: Comparación | C27: Ex_Integra | D27: Benchmark | E27: Equities | H27: EM | I27: Comparables_Subcat_SinAjustar | K27: Intensidad | L27: 0.861977
A28: 202512 | B28: Comparación | C28: Ex_Integra | D28: Benchmark | E28: Equities | H28: Metales Preciosos | I28: Comparables_Subcat_SinAjustar | K28: Intensidad | L28: 11.295997
A29: 202512 | B29: Comparación | C29: Ex_Integra | D29: Benchmark | E29: Equities | H29: Peru | I29: Comparables_Subcat_SinAjustar | K29: Intensidad | L29: 1.337515
A30: 202512 | B30: Comparación | C30: Habitat | D30: Benchmark | E30: Equities | H30: DM | I30: Comparables_Subcat_Ajustado (x Weight del instrumento) | K30: Intensidad | L30: 63.45775
A31: 202512 | B31: Comparación | C31: Habitat | D31: Benchmark | E31: Equities | H31: EM | I31: Comparables_Subcat_Ajustado (x Weight del instrumento) | K31: Intensidad | L31: 71.066596
A32: 202512 | B32: Comparación | C32: Habitat | D32: Benchmark | E32: Equities | H32: Metales Preciosos | I32: Comparables_Subcat_Ajustado (x Weight del instrumento) | K32: Intensidad | L32: 78.727754
A33: 202512 | B33: Comparación | C33: Habitat | D33: Benchmark | E33: Equities | H33: Peru | I33: Comparables_Subcat_Ajustado (x Weight del instrumento) | K33: Intensidad | L33: 31.332475
... A101: 202512 | B101: Comparación | C101: Profuturo | D101: Benchmark | E101: Fixed Income | H101: IG | I101: Comparables_Subcat_SinAjustar | K101: Intensidad | L101: 0.187061
A102: 202512 | B102: Comparación | C102: Ex_Integra | D102: Instrumento | E102: Equities | F102: Active | G102: BNP Paribas - Japan Small Caps | H102: DM | K102: Intensidad | L102: 1.621033
A103: 202512 | B103: Comparación | C103: Ex_Integra | D103: Instrumento | E103: Equities | F103: Active | G103: BNP Paribas - Japan Small Caps | H103: DM | K103: Weight | L103: 0.013354
A104: 202512 | B104: Comparación | C104: Habitat | D104: Instrumento | E104: Equities | F104: Active | G104: BNP Paribas - Japan Small Caps | H104: DM | K104: Intensidad | L104: 4.450315
A105: 202512 | B105: Comparación | C105: Habitat | D105: Instrumento | E105: Equities | F105: Active | G105: BNP Paribas - Japan Small Caps | H105: DM | K105: Weight | L105: 0.036662
A106: 202512 | B106: Comparación | C106: Integra | D106: Instrumento | E106: Equities | F106: Active | G106: BNP Paribas - Japan Small Caps | H106: DM | K106: Intensidad | L106: 3.044707
A107: 202512 | B107: Comparación | C107: Integra | D107: Instrumento | E107: Equities | F107: Active | G107: BNP Paribas - Japan Small Caps | H107: DM | K107: Weight | L107: 0.025083
A108: 202512 | B108: Comparación | C108: Integra | D108: Instrumento | E108: Equities | F108: Passive | G108: BlackRock - iShares Korea | H108: EM | K108: Intensidad | L108: 2.909986
A109: 202512 | B109: Comparación | C109: Integra | D109: Instrumento | E109: Equities | F109: Passive | G109: BlackRock - iShares Korea | H109: EM | K109: Weight | L109: 0.02893
A110: 202512 | B110: Comparación | C110: Ex_Integra | D110: Instrumento | E110: Equities | F110: Passive | G110: BlackRock - iShares MSCI Brazil | H110: EM | K110: Intensidad | L110: 4.029573
A111: 202512 | B111: Comparación | C111: Ex_Integra | D111: Instrumento | E111: Equities | F111: Passive | G111: BlackRock - iShares MSCI Brazil | H111: EM | K111: Weight | L111: 0.043945
A112: 202512 | B112: Comparación | C112: Habitat | D112: Instrumento | E112: Equities | F112: Passive | G112: BlackRock - iShares MSCI Brazil | H112: EM | K112: Intensidad | L112: 2.67897
A113: 202512 | B113: Comparación | C113: Habitat | D113: Instrumento | E113: Equities | F113: Passive | G113: BlackRock - iShares MSCI Brazil | H113: EM | K113: Weight | L113: 0.029216
... A201: 202512 | B201: Comparación | C201: Profuturo | D201: Instrumento | E201: Fixed Income | F201: Active | G201: Vontobel - Emerging Markets Debt | H201: EM | K201: Weight | L201: 0.033504
A202: 202606 | B202: Actual | C202: Ex_Integra | D202: Benchmark | I202: Escalar_Portafolio | J202: Total_Integra | K202: Intensidad | L202: 74.299564
A203: 202606 | B203: Actual | C203: Ex_Integra | D203: Benchmark | I203: Escalar_Portafolio | J203: F1_Integra | K203: Intensidad | L203: 38.489404
A204: 202606 | B204: Actual | C204: Ex_Integra | D204: Benchmark | I204: Escalar_Portafolio | J204: F2_Integra | K204: Intensidad | L204: 16.969317
A205: 202606 | B205: Actual | C205: Ex_Integra | D205: Benchmark | I205: Escalar_Portafolio | J205: F3_Integra | K205: Intensidad | L205: 18.840842
A206: 202606 | B206: Actual | C206: Habitat | D206: Benchmark | I206: Escalar_Portafolio | J206: Total_Integra | K206: Intensidad | L206: 88.616171
A207: 202606 | B207: Actual | C207: Habitat | D207: Benchmark | I207: Escalar_Portafolio | J207: F1_Integra | K207: Intensidad | L207: 46.311571
A208: 202606 | B208: Actual | C208: Habitat | D208: Benchmark | I208: Escalar_Portafolio | J208: F2_Integra | K208: Intensidad | L208: 23.78561
A209: 202606 | B209: Actual | C209: Habitat | D209: Benchmark | I209: Escalar_Portafolio | J209: F3_Integra | K209: Intensidad | L209: 18.51899
A210: 202606 | B210: Actual | C210: Integra | D210: Benchmark | I210: Escalar_Portafolio | J210: Total_Integra | K210: Intensidad | L210: 50.676744
A211: 202606 | B211: Actual | C211: Integra | D211: Benchmark | I211: Escalar_Portafolio | J211: F1_Integra | K211: Intensidad | L211: 22.661121
A212: 202606 | B212: Actual | C212: Integra | D212: Benchmark | I212: Escalar_Portafolio | J212: F2_Integra | K212: Intensidad | L212: 11.408378
A213: 202606 | B213: Actual | C213: Integra | D213: Benchmark | I213: Escalar_Portafolio | J213: F3_Integra | K213: Intensidad | L213: 16.607245
... A221: 202606 | B221: Actual | C221: Profuturo | D221: Benchmark | I221: Escalar_Portafolio | J221: F3_Integra | K221: Intensidad | L221: 19.516585
A222: 202606 | B222: Actual | D222: Benchmark | I222: FFMM (x Weight del instrumento) | J222: iShares Core S&P 500 ETF | K222: Intensidad | L222: 22.272457
A223: 202606 | B223: Actual | D223: Benchmark | I223: FFMM (x Weight del instrumento) | J223: iShares US Real Estate ETF | K223: Intensidad | L223: 6.7584659
A224: 202606 | B224: Actual | D224: Benchmark | I224: FFMM (x Weight del instrumento) | J224: iShares MSCI Eurozone ETF | K224: Intensidad | L224: 43.232015
A225: 202606 | B225: Actual | D225: Benchmark | I225: FFMM (x Weight del instrumento) | J225: iShares Latin America 40 ETF | K225: Intensidad | L225: 109.30923
A226: 202606 | B226: Actual | D226: Benchmark | I226: FFMM (x Weight del instrumento) | J226: iShares Global Energy ETF | K226: Intensidad | L226: 208.759
A227: 202606 | B227: Actual | D227: Benchmark | I227: FFMM (x Weight del instrumento) | J227: iShares Global Financials ETF | K227: Intensidad | L227: 3.533892
A228: 202606 | B228: Actual | D228: Benchmark | I228: FFMM (x Weight del instrumento) | J228: iShares Global Healthcare ETF | K228: Intensidad | L228: 2.7511171
A229: 202606 | B229: Actual | D229: Benchmark | I229: FFMM (x Weight del instrumento) | J229: iShares Global Tech ETF | K229: Intensidad | L229: 7.9125586
A230: 202606 | B230: Actual | D230: Benchmark | I230: FFMM (x Weight del instrumento) | J230: iShares Global Comm Services ETF | K230: Intensidad | L230: 3.9668277
A231: 202606 | B231: Actual | D231: Benchmark | I231: FFMM (x Weight del instrumento) | J231: iShares Global Consumer Discretionary ETF | K231: Intensidad | L231: 11.680975
A232: 202606 | B232: Actual | D232: Benchmark | I232: FFMM (x Weight del instrumento) | J232: iShares Global Consumer Staples ETF | K232: Intensidad | L232: 20.599526
A233: 202606 | B233: Actual | D233: Benchmark | I233: FFMM (x Weight del instrumento) | J233: iShares Global Industrials ETF | K233: Intensidad | L233: 29.22582
... A246: 202606 | B246: Actual | D246: Benchmark | I246: FFMM (x Weight del instrumento) | J246: iShares ? High Yield Corp Bond UCITS ETF EUR D | K246: Intensidad | L246: 99.280223
A247: 202606 | B247: Actual | C247: Ex_Integra | D247: Benchmark | E247: Equities | H247: Commodities | I247: Comparables_Subcat_Ajustado (x Weight del instrumento) | K247: Intensidad | L247: 110.64883
A248: 202606 | B248: Actual | C248: Ex_Integra | D248: Benchmark | E248: Equities | H248: DM | I248: Comparables_Subcat_Ajustado (x Weight del instrumento) | K248: Intensidad | L248: 46.196599
A249: 202606 | B249: Actual | C249: Ex_Integra | D249: Benchmark | E249: Equities | H249: EM | I249: Comparables_Subcat_Ajustado (x Weight del instrumento) | K249: Intensidad | L249: 63.629768
A250: 202606 | B250: Actual | C250: Ex_Integra | D250: Benchmark | E250: Equities | H250: Peru | I250: Comparables_Subcat_Ajustado (x Weight del instrumento) | K250: Intensidad | L250: 20.496116
A251: 202606 | B251: Actual | C251: Ex_Integra | D251: Benchmark | E251: Equities | H251: Commodities | I251: Comparables_Subcat_SinAjustar | K251: Intensidad | L251: 3.634762
A252: 202606 | B252: Actual | C252: Ex_Integra | D252: Benchmark | E252: Equities | H252: DM | I252: Comparables_Subcat_SinAjustar | K252: Intensidad | L252: 0.474217
A253: 202606 | B253: Actual | C253: Ex_Integra | D253: Benchmark | E253: Equities | H253: EM | I253: Comparables_Subcat_SinAjustar | K253: Intensidad | L253: 1.409431
A254: 202606 | B254: Actual | C254: Ex_Integra | D254: Benchmark | E254: Equities | H254: Peru | I254: Comparables_Subcat_SinAjustar | K254: Intensidad | L254: 3.317613
A255: 202606 | B255: Actual | C255: Habitat | D255: Benchmark | E255: Equities | H255: Commodities | I255: Comparables_Subcat_Ajustado (x Weight del instrumento) | K255: Intensidad | L255: 110.64883
A256: 202606 | B256: Actual | C256: Habitat | D256: Benchmark | E256: Equities | H256: DM | I256: Comparables_Subcat_Ajustado (x Weight del instrumento) | K256: Intensidad | L256: 46.196599
A257: 202606 | B257: Actual | C257: Habitat | D257: Benchmark | E257: Equities | H257: EM | I257: Comparables_Subcat_Ajustado (x Weight del instrumento) | K257: Intensidad | L257: 63.629768
A258: 202606 | B258: Actual | C258: Habitat | D258: Benchmark | E258: Equities | H258: Peru | I258: Comparables_Subcat_Ajustado (x Weight del instrumento) | K258: Intensidad | L258: 20.496116
... A326: 202606 | B326: Actual | C326: Profuturo | D326: Benchmark | E326: Fixed Income | H326: IG | I326: Comparables_Subcat_SinAjustar | K326: Intensidad | L326: 0.233551
A327: 202606 | B327: Actual | C327: Habitat | D327: Instrumento | E327: Equities | F327: Active | G327: BNP Paribas - Japan Small Caps | H327: DM | K327: Intensidad | L327: 3.189379
A328: 202606 | B328: Actual | C328: Habitat | D328: Instrumento | E328: Equities | F328: Active | G328: BNP Paribas - Japan Small Caps | H328: DM | K328: Weight | L328: 0.030021
A329: 202606 | B329: Actual | C329: Integra | D329: Instrumento | E329: Equities | F329: Active | G329: BNP Paribas - Japan Small Caps | H329: DM | K329: Intensidad | L329: 3.252364
A330: 202606 | B330: Actual | C330: Integra | D330: Instrumento | E330: Equities | F330: Active | G330: BNP Paribas - Japan Small Caps | H330: DM | K330: Weight | L330: 0.030614
A331: 202606 | B331: Actual | C331: Habitat | D331: Instrumento | E331: Equities | F331: Passive | G331: BlackRock - iShares Core S&P 500 | H331: DM | K331: Intensidad | L331: 1.525922
A332: 202606 | B332: Actual | C332: Habitat | D332: Instrumento | E332: Equities | F332: Passive | G332: BlackRock - iShares Core S&P 500 | H332: DM | K332: Weight | L332: 0.069895
A333: 202606 | B333: Actual | C333: Ex_Integra | D333: Instrumento | E333: Equities | F333: Passive | G333: BlackRock - iShares Korea | H333: EM | K333: Intensidad | L333: 8.283403
A334: 202606 | B334: Actual | C334: Ex_Integra | D334: Instrumento | E334: Equities | F334: Passive | G334: BlackRock - iShares Korea | H334: EM | K334: Weight | L334: 0.142106
A335: 202606 | B335: Actual | C335: Habitat | D335: Instrumento | E335: Equities | F335: Passive | G335: BlackRock - iShares Korea | H335: EM | K335: Intensidad | L335: 5.389704
A336: 202606 | B336: Actual | C336: Habitat | D336: Instrumento | E336: Equities | F336: Passive | G336: BlackRock - iShares Korea | H336: EM | K336: Weight | L336: 0.092463
A337: 202606 | B337: Actual | C337: Integra | D337: Instrumento | E337: Equities | F337: Passive | G337: BlackRock - iShares Korea | H337: EM | K337: Intensidad | L337: 8.9528
A338: 202606 | B338: Actual | C338: Integra | D338: Instrumento | E338: Equities | F338: Passive | G338: BlackRock - iShares Korea | H338: EM | K338: Weight | L338: 0.15359
... A426: 202606 | B426: Actual | C426: Profuturo | D426: Instrumento | E426: Fixed Income | F426: Active | G426: Vontobel - Emerging Markets Debt | H426: EM | K426: Weight | L426: 0.031912

Sheet Intensidad y Benchmarks
A1: Corte | B1: Corte_Rol | C1: AFP | D1: Segmento | E1: Categoria | F1: Tipo_Dato | G1: Pais | H1: Emisor | I1: Benchmark_Nombre | J1: Metrica | K1: Valor | M1: Serie | N1: Intensidad
A2: 202512 | B2: Comparación | C2: Habitat | D2: AFP_Categoria | E2: Materials | F2: MSCI | J2: Intensidad | K2: 21.110172 | M2: Integra | N2: =SUMIFS($K$2:$K$77,$D$2:$D$77,"AFP_Categoria",$C$2:$C$77,"Integra",$A$2:$A$77,"202606")
A3: 202512 | B3: Comparación | C3: Habitat | D3: AFP_Categoria | E3: Utilities | F3: MSCI | J3: Intensidad | K3: 0.592175 | M3: Prima | N3: =SUMIFS($K$2:$K$77,$D$2:$D$77,"AFP_Categoria",$C$2:$C$77,"Prima",$A$2:$A$77,"202606")
A4: 202512 | B4: Comparación | C4: Habitat | D4: AFP_Categoria | E4: Otros | F4: MSCI | J4: Intensidad | K4: 14.30549 | M4: Profuturo | N4: =SUMIFS($K$2:$K$77,$D$2:$D$77,"AFP_Categoria",$C$2:$C$77,"Profuturo",$A$2:$A$77,"202606")
A5: 202512 | B5: Comparación | C5: Habitat | D5: AFP_Categoria | E5: RF | F5: MSCI | J5: Intensidad | K5: 21.719801 | M5: Habitat | N5: =SUMIFS($K$2:$K$77,$D$2:$D$77,"AFP_Categoria",$C$2:$C$77,"Habitat",$A$2:$A$77,"202606")
A6: 202512 | B6: Comparación | C6: Habitat | D6: AFP_Categoria | E6: RV | F6: MSCI | J6: Intensidad | K6: 27.500445 | M6: ACWI | N6: =SUMIFS($K$2:$K$77,$D$2:$D$77,"Benchmark_Mercado",$I$2:$I$77,"ACWI",$A$2:$A$77,"202606")
A7: 202512 | B7: Comparación | C7: Habitat | D7: AFP_Categoria | E7: Proxies | F7: Proxies | J7: Intensidad | K7: 58.113863 | M7: ILF | N7: =SUMIFS($K$2:$K$77,$D$2:$D$77,"Benchmark_Mercado",$I$2:$I$77,"ILF",$A$2:$A$77,"202606")
A8: 202512 | B8: Comparación | C8: Habitat | D8: AFP_Categoria | E8: Alts | F8: Proxies | J8: Intensidad | K8: 18.714894 | M8: CEMB | N8: =SUMIFS($K$2:$K$77,$D$2:$D$77,"Benchmark_Mercado",$I$2:$I$77,"CEMB",$A$2:$A$77,"202606")
A9: 202512 | B9: Comparación | C9: Integra | D9: AFP_Categoria | E9: Materials | F9: MSCI | J9: Intensidad | K9: 27.233583 | M9: EMB | N9: =SUMIFS($K$2:$K$77,$D$2:$D$77,"Benchmark_Mercado",$I$2:$I$77,"EMB",$A$2:$A$77,"202606")
A10: 202512 | B10: Comparación | C10: Integra | D10: AFP_Categoria | E10: Utilities | F10: MSCI | J10: Intensidad | K10: 0.360136 | M10: Gobierno Central | N10: =SUMIFS($K$2:$K$77,$D$2:$D$77,"Soberano_GOB",$H$2:$H$77,"Gobierno Central",$A$2:$A$77,"202606")
A11: 202512 | B11: Comparación | C11: Integra | D11: AFP_Categoria | E11: Otros | F11: MSCI | J11: Intensidad | K11: 14.065582 | M11: Gobierno de Brasil | N11: =SUMIFS($K$2:$K$77,$D$2:$D$77,"Soberano_GOB",$H$2:$H$77,"Gobierno de Brasil",$A$2:$A$77,"202606")
A12: 202512 | B12: Comparación | C12: Integra | D12: AFP_Categoria | E12: RF | F12: MSCI | J12: Intensidad | K12: 23.202345 | M12: Gobierno de Colombia | N12: =SUMIFS($K$2:$K$77,$D$2:$D$77,"Soberano_GOB",$H$2:$H$77,"Gobierno de Colombia",$A$2:$A$77,"202606")
A13: 202512 | B13: Comparación | C13: Integra | D13: AFP_Categoria | E13: RV | F13: MSCI | J13: Intensidad | K13: 36.157902 | M13: Gobierno de Sudáfrica | N13: =SUMIFS($K$2:$K$77,$D$2:$D$77,"Soberano_GOB",$H$2:$H$77,"Gobierno de Sudáfrica",$A$2:$A$77,"202606")
A14: 202512 | B14: Comparación | C14: Integra | D14: AFP_Categoria | E14: Proxies | F14: Proxies | J14: Intensidad | K14: 40.601161 | M14: Gobierno de Mexico | N14: =SUMIFS($K$2:$K$77,$D$2:$D$77,"Soberano_GOB",$H$2:$H$77,"Gobierno de Mexico",$A$2:$A$77,"202606")
A15: 202512 | B15: Comparación | C15: Integra | D15: AFP_Categoria | E15: Alts | F15: Proxies | J15: Intensidad | K15: 17.58301 | M15: Gobierno de México | N15: =SUMIFS($K$2:$K$77,$D$2:$D$77,"Soberano_GOB",$H$2:$H$77,"Gobierno de México",$A$2:$A$77,"202606")
A16: 202512 | B16: Comparación | C16: Prima | D16: AFP_Categoria | E16: Materials | F16: MSCI | J16: Intensidad | K16: 36.738399 | M16: Gobierno de Chile | N16: =SUMIFS($K$2:$K$77,$D$2:$D$77,"Soberano_GOB",$H$2:$H$77,"Gobierno de Chile",$A$2:$A$77,"202606")
A17: 202512 | B17: Comparación | C17: Prima | D17: AFP_Categoria | E17: Utilities | F17: MSCI | J17: Intensidad | K17: 1.083011
A18: 202512 | B18: Comparación | C18: Prima | D18: AFP_Categoria | E18: Otros | F18: MSCI | J18: Intensidad | K18: 19.918916
A19: 202512 | B19: Comparación | C19: Prima | D19: AFP_Categoria | E19: RF | F19: MSCI | J19: Intensidad | K19: 40.486087
A20: 202512 | B20: Comparación | C20: Prima | D20: AFP_Categoria | E20: RV | F20: MSCI | J20: Intensidad | K20: 30.214588
A21: 202512 | B21: Comparación | C21: Prima | D21: AFP_Categoria | E21: Proxies | F21: Proxies | J21: Intensidad | K21: 43.735007
A22: 202512 | B22: Comparación | C22: Prima | D22: AFP_Categoria | E22: Alts | F22: Proxies | J22: Intensidad | K22: 10.062701
A23: 202512 | B23: Comparación | C23: Profuturo | D23: AFP_Categoria | E23: Materials | F23: MSCI | J23: Intensidad | K23: 17.533109
A24: 202512 | B24: Comparación | C24: Profuturo | D24: AFP_Categoria | E24: Utilities | F24: MSCI | J24: Intensidad | K24: 0.292189
A25: 202512 | B25: Comparación | C25: Profuturo | D25: AFP_Categoria | E25: Otros | F25: MSCI | J25: Intensidad | K25: 8.948961
A26: 202512 | B26: Comparación | C26: Profuturo | D26: AFP_Categoria | E26: RF | F26: MSCI | J26: Intensidad | K26: 28.365067
A27: 202512 | B27: Comparación | C27: Profuturo | D27: AFP_Categoria | E27: RV | F27: MSCI | J27: Intensidad | K27: 31.010547
A28: 202512 | B28: Comparación | C28: Profuturo | D28: AFP_Categoria | E28: Proxies | F28: Proxies | J28: Intensidad | K28: 48.881664
A29: 202512 | B29: Comparación | C29: Profuturo | D29: AFP_Categoria | E29: Alts | F29: Proxies | J29: Intensidad | K29: 13.582613
A30: 202512 | B30: Comparación | D30: Benchmark_Mercado | I30: ACWI | J30: Intensidad | K30: 39.567477
A31: 202512 | B31: Comparación | D31: Benchmark_Mercado | I31: ILF | J31: Intensidad | K31: 145.75332
A32: 202512 | B32: Comparación | D32: Benchmark_Mercado | I32: CEMB | J32: Intensidad | K32: 202.57506
A33: 202512 | B33: Comparación | D33: Benchmark_Mercado | I33: EMB | J33: Intensidad | K33: 388.10196
A34: 202512 | B34: Comparación | C34: Integra | D34: Soberano_GOB | G34: Perú | H34: Gobierno Central | J34: Intensidad | K34: 97.22459
A35: 202512 | B35: Comparación | C35: Integra | D35: Soberano_GOB | G35: Brasil | H35: Gobierno de Brasil | J35: Intensidad | K35: 14.223795
A36: 202512 | B36: Comparación | C36: Integra | D36: Soberano_GOB | G36: México | H36: Gobierno de México | J36: Intensidad | K36: 3.037226
A37: 202512 | B37: Comparación | C37: Integra | D37: Soberano_GOB | G37: Chile | H37: Gobierno de Chile | J37: Intensidad | K37: 4.951348
A38: 202512 | B38: Comparación | C38: Integra | D38: Soberano_GOB | G38: Colombia | H38: Gobierno de Colombia | J38: Intensidad | K38: 4.696621
A39: 202606 | B39: Actual | C39: Habitat | D39: AFP_Categoria | E39: Materials | F39: MSCI | J39: Intensidad | K39: 20.38687
A40: 202606 | B40: Actual | C40: Habitat | D40: AFP_Categoria | E40: Utilities | F40: MSCI | J40: Intensidad | K40: 0.638379
A41: 202606 | B41: Actual | C41: Habitat | D41: AFP_Categoria | E41: Otros | F41: MSCI | J41: Intensidad | K41: 10.665688
A42: 202606 | B42: Actual | C42: Habitat | D42: AFP_Categoria | E42: RF | F42: MSCI | J42: Intensidad | K42: 51.684975
A43: 202606 | B43: Actual | C43: Habitat | D43: AFP_Categoria | E43: RV | F43: MSCI | J43: Intensidad | K43: 23.294834
A44: 202606 | B44: Actual | C44: Habitat | D44: AFP_Categoria | E44: Proxies | F44: Proxies | J44: Intensidad | K44: 43.583984
A45: 202606 | B45: Actual | C45: Habitat | D45: AFP_Categoria | E45: Alts | F45: Proxies | J45: Intensidad | K45: 16.85958
A46: 202606 | B46: Actual | C46: Integra | D46: AFP_Categoria | E46: Materials | F46: MSCI | J46: Intensidad | K46: 22.923856
A47: 202606 | B47: Actual | C47: Integra | D47: AFP_Categoria | E47: Utilities | F47: MSCI | J47: Intensidad | K47: 0.428393
A48: 202606 | B48: Actual | C48: Integra | D48: AFP_Categoria | E48: Otros | F48: MSCI | J48: Intensidad | K48: 9.228149
A49: 202606 | B49: Actual | C49: Integra | D49: AFP_Categoria | E49: RF | F49: MSCI | J49: Intensidad | K49: 13.115297
A50: 202606 | B50: Actual | C50: Integra | D50: AFP_Categoria | E50: RV | F50: MSCI | J50: Intensidad | K50: 26.231119
... A66: 202606 | B66: Actual | C66: Profuturo | D66: AFP_Categoria | E66: Alts | F66: Proxies | J66: Intensidad | K66: 10.55566
A67: 202606 | B67: Actual | D67: Benchmark_Mercado | I67: ACWI | J67: Intensidad | K67: 33.985581
A68: 202606 | B68: Actual | D68: Benchmark_Mercado | I68: ILF | J68: Intensidad | K68: 109.30923
A69: 202606 | B69: Actual | D69: Benchmark_Mercado | I69: CEMB | J69: Intensidad | K69: 186.25221
A70: 202606 | B70: Actual | D70: Benchmark_Mercado | I70: EMB | J70: Intensidad | K70: 388.10196
A71: 202606 | B71: Actual | C71: Integra | D71: Soberano_GOB | G71: Perú | H71: Gobierno Central | J71: Intensidad | K71: 81.922696
A72: 202606 | B72: Actual | C72: Integra | D72: Soberano_GOB | G72: Brasil | H72: Gobierno de Brasil | J72: Intensidad | K72: 27.364061
A73: 202606 | B73: Actual | C73: Integra | D73: Soberano_GOB | G73: Colombia | H73: Gobierno de Colombia | J73: Intensidad | K73: 9.641955
A74: 202606 | B74: Actual | C74: Integra | D74: Soberano_GOB | G74: Sudáfrica | H74: Gobierno de Sudáfrica | J74: Intensidad | K74: 9.213352
A75: 202606 | B75: Actual | C75: Integra | D75: Soberano_GOB | G75: México | H75: Gobierno de Mexico | J75: Intensidad | K75: 3.330972
A76: 202606 | B76: Actual | C76: Integra | D76: Soberano_GOB | G76: México | H76: Gobierno de México | J76: Intensidad | K76: 2.749931
A77: 202606 | B77: Actual | C77: Integra | D77: Soberano_GOB | G77: Chile | H77: Gobierno de Chile | J77: Intensidad | K77: 1.310432

Sheet Mayores contribuyentes
A1: Corte | B1: Corte_Rol | C1: AFP | D1: Emisor | E1: Metrica | F1: Valor | H1: Emisor | I1: Intensidad | J1: Huella
A2: 202512 | B2: Comparación | C2: Ex_Integra | D2: AXA - World Funds Framligton Digital Economy | E2: Huella | F2: 0.096157 | H2: Minsur | I2: =SUMIFS('BD'!$S$2:$S$6977,'BD'!$H$2:$H$6977,"Mayores",'BD'!$B$2:$B$6977,"Integra",'BD'!$M$2:$M$6977,"Minsur",'BD'!$A$2:$A$6977,"202606") | J2: =SUMIFS('BD'!$R$2:$R$6977,'BD'!$H$2:$H$6977,"Mayores",'BD'!$B$2:$B$6977,"Integra",'BD'!$M$2:$M$6977,"Minsur",'BD'!$A$2:$A$6977,"202606")
A3: 202512 | B3: Comparación | C3: Ex_Integra | D3: AXA - World Funds Framligton Digital Economy | E3: Intensidad | F3: 2.7e-05 | H3: BlackRock - iShares Korea | I3: =SUMIFS('BD'!$S$2:$S$6977,'BD'!$H$2:$H$6977,"Mayores",'BD'!$B$2:$B$6977,"Integra",'BD'!$M$2:$M$6977,"BlackRock - iShares Korea",'BD'!$A$2:$A$6977,"202606") | J3: =SUMIFS('BD'!$R$2:$R$6977,'BD'!$H$2:$H$6977,"Mayores",'BD'!$B$2:$B$6977,"Integra",'BD'!$M$2:$M$6977,"BlackRock - iShares Korea",'BD'!$A$2:$A$6977,"202606")
A4: 202512 | B4: Comparación | C4: Ex_Integra | D4: AXA - World Funds Framligton Digital Economy | E4: Inv MM$ | F4: 0.070143 | H4: Vontobel - Emerging Markets Debt | I4: =SUMIFS('BD'!$S$2:$S$6977,'BD'!$H$2:$H$6977,"Mayores",'BD'!$B$2:$B$6977,"Integra",'BD'!$M$2:$M$6977,"Vontobel - Emerging Markets Debt",'BD'!$A$2:$A$6977,"202606") | J4: =SUMIFS('BD'!$R$2:$R$6977,'BD'!$H$2:$H$6977,"Mayores",'BD'!$B$2:$B$6977,"Integra",'BD'!$M$2:$M$6977,"Vontobel - Emerging Markets Debt",'BD'!$A$2:$A$6977,"202606")
A5: 202512 | B5: Comparación | C5: Ex_Integra | D5: AXA World Funds - US Dynamic High Yield | E5: Huella | F5: 0.117442 | H5: Nexa Resources Perú | I5: =SUMIFS('BD'!$S$2:$S$6977,'BD'!$H$2:$H$6977,"Mayores",'BD'!$B$2:$B$6977,"Integra",'BD'!$M$2:$M$6977,"Nexa Resources Perú",'BD'!$A$2:$A$6977,"202606") | J5: =SUMIFS('BD'!$R$2:$R$6977,'BD'!$H$2:$H$6977,"Mayores",'BD'!$B$2:$B$6977,"Integra",'BD'!$M$2:$M$6977,"Nexa Resources Perú",'BD'!$A$2:$A$6977,"202606")
A6: 202512 | B6: Comparación | C6: Ex_Integra | D6: AXA World Funds - US Dynamic High Yield | E6: Intensidad | F6: 3.2e-05 | H6: Ecopetrol | I6: =SUMIFS('BD'!$S$2:$S$6977,'BD'!$H$2:$H$6977,"Mayores",'BD'!$B$2:$B$6977,"Integra",'BD'!$M$2:$M$6977,"Ecopetrol",'BD'!$A$2:$A$6977,"202606") | J6: =SUMIFS('BD'!$R$2:$R$6977,'BD'!$H$2:$H$6977,"Mayores",'BD'!$B$2:$B$6977,"Integra",'BD'!$M$2:$M$6977,"Ecopetrol",'BD'!$A$2:$A$6977,"202606")
A7: 202512 | B7: Comparación | C7: Ex_Integra | D7: AXA World Funds - US Dynamic High Yield | E7: Inv MM$ | F7: 0.001041 | H7: Global X - Copper Miners ETF | I7: =SUMIFS('BD'!$S$2:$S$6977,'BD'!$H$2:$H$6977,"Mayores",'BD'!$B$2:$B$6977,"Integra",'BD'!$M$2:$M$6977,"Global X - Copper Miners ETF",'BD'!$A$2:$A$6977,"202606") | J7: =SUMIFS('BD'!$R$2:$R$6977,'BD'!$H$2:$H$6977,"Mayores",'BD'!$B$2:$B$6977,"Integra",'BD'!$M$2:$M$6977,"Global X - Copper Miners ETF",'BD'!$A$2:$A$6977,"202606")
A8: 202512 | B8: Comparación | C8: Ex_Integra | D8: Aberdeen - Select Emerging Markets Bond | E8: Huella | F8: 2.6e-05 | H8: Pimco - Emerging Markets Local Bond Fund | I8: =SUMIFS('BD'!$S$2:$S$6977,'BD'!$H$2:$H$6977,"Mayores",'BD'!$B$2:$B$6977,"Integra",'BD'!$M$2:$M$6977,"Pimco - Emerging Markets Local Bond Fund",'BD'!$A$2:$A$6977,"202606") | J8: =SUMIFS('BD'!$R$2:$R$6977,'BD'!$H$2:$H$6977,"Mayores",'BD'!$B$2:$B$6977,"Integra",'BD'!$M$2:$M$6977,"Pimco - Emerging Markets Local Bond Fund",'BD'!$A$2:$A$6977,"202606")
A9: 202512 | B9: Comparación | C9: Ex_Integra | D9: Aberdeen - Select Emerging Markets Bond | E9: Intensidad | F9: 0 | H9: BNP Paribas - Japan Small Caps | I9: =SUMIFS('BD'!$S$2:$S$6977,'BD'!$H$2:$H$6977,"Mayores",'BD'!$B$2:$B$6977,"Integra",'BD'!$M$2:$M$6977,"BNP Paribas - Japan Small Caps",'BD'!$A$2:$A$6977,"202606") | J9: =SUMIFS('BD'!$R$2:$R$6977,'BD'!$H$2:$H$6977,"Mayores",'BD'!$B$2:$B$6977,"Integra",'BD'!$M$2:$M$6977,"BNP Paribas - Japan Small Caps",'BD'!$A$2:$A$6977,"202606")
A10: 202512 | B10: Comparación | C10: Ex_Integra | D10: Aberdeen - Select Emerging Markets Bond | E10: Inv MM$ | F10: 0 | H10: Buenaventura | I10: =SUMIFS('BD'!$S$2:$S$6977,'BD'!$H$2:$H$6977,"Mayores",'BD'!$B$2:$B$6977,"Integra",'BD'!$M$2:$M$6977,"Buenaventura",'BD'!$A$2:$A$6977,"202606") | J10: =SUMIFS('BD'!$R$2:$R$6977,'BD'!$H$2:$H$6977,"Mayores",'BD'!$B$2:$B$6977,"Integra",'BD'!$M$2:$M$6977,"Buenaventura",'BD'!$A$2:$A$6977,"202606")
A11: 202512 | B11: Comparación | C11: Ex_Integra | D11: Aegon High Yield Global Bond Fund | E11: Huella | F11: 2598.6648 | H11: nan | I11: =SUMIFS('BD'!$S$2:$S$6977,'BD'!$H$2:$H$6977,"Mayores",'BD'!$B$2:$B$6977,"Integra",'BD'!$M$2:$M$6977,"nan",'BD'!$A$2:$A$6977,"202606") | J11: =SUMIFS('BD'!$R$2:$R$6977,'BD'!$H$2:$H$6977,"Mayores",'BD'!$B$2:$B$6977,"Integra",'BD'!$M$2:$M$6977,"nan",'BD'!$A$2:$A$6977,"202606")
A12: 202512 | B12: Comparación | C12: Ex_Integra | D12: Aegon High Yield Global Bond Fund | E12: Intensidad | F12: 0.461637 | H12: Vontobel - Credit Opportunities | I12: =SUMIFS('BD'!$S$2:$S$6977,'BD'!$H$2:$H$6977,"Mayores",'BD'!$B$2:$B$6977,"Integra",'BD'!$M$2:$M$6977,"Vontobel - Credit Opportunities",'BD'!$A$2:$A$6977,"202606") | J12: =SUMIFS('BD'!$R$2:$R$6977,'BD'!$H$2:$H$6977,"Mayores",'BD'!$B$2:$B$6977,"Integra",'BD'!$M$2:$M$6977,"Vontobel - Credit Opportunities",'BD'!$A$2:$A$6977,"202606")
A13: 202512 | B13: Comparación | C13: Ex_Integra | D13: Aegon High Yield Global Bond Fund | E13: Inv MM$ | F13: 38.74936 | H13: Aenza | I13: =SUMIFS('BD'!$S$2:$S$6977,'BD'!$H$2:$H$6977,"Mayores",'BD'!$B$2:$B$6977,"Integra",'BD'!$M$2:$M$6977,"Aenza",'BD'!$A$2:$A$6977,"202606") | J13: =SUMIFS('BD'!$R$2:$R$6977,'BD'!$H$2:$H$6977,"Mayores",'BD'!$B$2:$B$6977,"Integra",'BD'!$M$2:$M$6977,"Aenza",'BD'!$A$2:$A$6977,"202606")
A14: 202512 | B14: Comparación | C14: Ex_Integra | D14: Aenza | E14: Huella | F14: 7988.2834 | H14: JP Morgan - Korea Equity Fund | I14: =SUMIFS('BD'!$S$2:$S$6977,'BD'!$H$2:$H$6977,"Mayores",'BD'!$B$2:$B$6977,"Integra",'BD'!$M$2:$M$6977,"JP Morgan - Korea Equity Fund",'BD'!$A$2:$A$6977,"202606") | J14: =SUMIFS('BD'!$R$2:$R$6977,'BD'!$H$2:$H$6977,"Mayores",'BD'!$B$2:$B$6977,"Integra",'BD'!$M$2:$M$6977,"JP Morgan - Korea Equity Fund",'BD'!$A$2:$A$6977,"202606")
A15: 202512 | B15: Comparación | C15: Ex_Integra | D15: Aenza | E15: Intensidad | F15: 1.651909 | H15: BlackRock - iShares PHLX Semiconductor ETF | I15: =SUMIFS('BD'!$S$2:$S$6977,'BD'!$H$2:$H$6977,"Mayores",'BD'!$B$2:$B$6977,"Integra",'BD'!$M$2:$M$6977,"BlackRock - iShares PHLX Semiconductor ETF",'BD'!$A$2:$A$6977,"202606") | J15: =SUMIFS('BD'!$R$2:$R$6977,'BD'!$H$2:$H$6977,"Mayores",'BD'!$B$2:$B$6977,"Integra",'BD'!$M$2:$M$6977,"BlackRock - iShares PHLX Semiconductor ETF",'BD'!$A$2:$A$6977,"202606")
A16: 202512 | B16: Comparación | C16: Ex_Integra | D16: Aenza | E16: Inv MM$ | F16: 62.281954 | H16: WisdomTree - Japan Hedged Equity | I16: =SUMIFS('BD'!$S$2:$S$6977,'BD'!$H$2:$H$6977,"Mayores",'BD'!$B$2:$B$6977,"Integra",'BD'!$M$2:$M$6977,"WisdomTree - Japan Hedged Equity",'BD'!$A$2:$A$6977,"202606") | J16: =SUMIFS('BD'!$R$2:$R$6977,'BD'!$H$2:$H$6977,"Mayores",'BD'!$B$2:$B$6977,"Integra",'BD'!$M$2:$M$6977,"WisdomTree - Japan Hedged Equity",'BD'!$A$2:$A$6977,"202606")
A17: 202512 | B17: Comparación | C17: Ex_Integra | D17: Alicorp | E17: Huella | F17: 74.450437
A18: 202512 | B18: Comparación | C18: Ex_Integra | D18: Alicorp | E18: Intensidad | F18: 0.018426
A19: 202512 | B19: Comparación | C19: Ex_Integra | D19: Alicorp | E19: Inv MM$ | F19: 2.034165
A20: 202512 | B20: Comparación | C20: Ex_Integra | D20: Alliance Bernstein - Emerging Markets Growth | E20: Huella | F20: 348.61454
A21: 202512 | B21: Comparación | C21: Ex_Integra | D21: Alliance Bernstein - Emerging Markets Growth | E21: Intensidad | F21: 0.091332
A22: 202512 | B22: Comparación | C22: Ex_Integra | D22: Alliance Bernstein - Emerging Markets Growth | E22: Inv MM$ | F22: 3.849484
A23: 202512 | B23: Comparación | C23: Ex_Integra | D23: Allianz - Artificial Intelligence | E23: Huella | F23: 34.740787
A24: 202512 | B24: Comparación | C24: Ex_Integra | D24: Allianz - Artificial Intelligence | E24: Intensidad | F24: 0.009767
A25: 202512 | B25: Comparación | C25: Ex_Integra | D25: Allianz - Artificial Intelligence | E25: Inv MM$ | F25: 4.297153
A26: 202512 | B26: Comparación | C26: Ex_Integra | D26: Allianz - China-A | E26: Huella | F26: 59.193733
A27: 202512 | B27: Comparación | C27: Ex_Integra | D27: Allianz - China-A | E27: Intensidad | F27: 0.014008
A28: 202512 | B28: Comparación | C28: Ex_Integra | D28: Allianz - China-A | E28: Inv MM$ | F28: 1.652254
... A2719: 202606 | B2719: Actual | C2719: Profuturo | D2719: WisdomTree - Cloud Computing | E2719: Inv MM$ | F2719: 30.863486

Sheet Auditoría
A1: Hoja | B1: Objeto(s) en HISTORICO | C1: Metrica(s) | D1: Corte Actual (default) | E1: Corte Comparación (default) | F1: AFP default dashboard | G1: Nota / fórmula
A2: Huella Soberanos | B2: Soberanos | C2: Huella | D2: 202606 | E2: 202512 | F2: Integra | G2: País se obtiene mapeando Emisor con PAIS_POR_EMISOR_SOBERANO. También existen en HISTORICO '% Huella', '% AUM' e 'Intensidad implícita' para este objeto, no incluidas aquí.
A3: Intensidad Soberanos | B3: Soberanos | C3: Intensidad | D3: 202606 | E3: 202512 | F3: Integra | G3: Intensidad = CO2-H x Weight (no Huella x Weight).
A4: Huella por Sector | B4: Sector_MSCI_Proxies | C4: Huella | D4: 202606 | E4: 202512 | F4: Integra | G4: Tipo_Dato distingue MSCI (dato directo) vs Proxies. 'Proxies' consolida RF+RV+BU proxy sin distinguir origen.
A5: Intensidad por Sector | B5: Sector_MSCI_Proxies | C5: Intensidad | D5: 202606 | E5: 202512 | F5: Integra | G5: Igual a la hoja anterior, métrica Intensidad.
A6: Intensidad FFMM | B6: TopSubCat_Asset | C6: Intensidad, Weight | D6: 202606 | E6: No aplica (el chart solo usa el corte actual) | F6: Integra | G6: Los benchmarks 'Comparables_Subcat_Ajustado' y 'FFMM' son valores base que el dashboard multiplica por el Weight PROPIO de cada instrumento antes de graficar; esa multiplicación no viene precalculada aquí. Los benchmarks FFMM reflejan solo el corte actual (misma limitación que el dashboard).
A7: Intensidad y Benchmarks | B7: Sector_MSCI_Proxies, Comparables, Soberanos | C7: Intensidad | D7: 202606 | E7: No aplica (el chart solo usa el corte actual) | F7: Integra, Prima, Profuturo, Habitat (según segmento) | G7: Combina 3 fuentes distintas identificadas por la columna Segmento.
A8: Mayores contribuyentes | B8: Contrib_Variacion_Intensidad | C8: Huella, Intensidad, Inv MM$, PERDIO_HUELLA | D8: 202606 | E8: No aplica (el chart solo usa el corte actual) | F8: Integra | G8: El dashboard muestra solo el Top 15 por Intensidad; aquí va el universo BU+TD sin Proxy completo. PERDIO_HUELLA=1 marca emisores con dato de respaldo de la hoja 'Perdieron Huella' (símbolo ◇ en el dashboard).
