Workbook
Name IQ_CH: 110000
Name IQ_CQ: 5000
Name IQ_CY: 10000
Name IQ_DAILY: 500000
Name IQ_FH: 100000
Name IQ_FQ: 500
Name IQ_FY: 1000
Name IQ_LTM: 2000
Name IQ_MONTH: 15000
Name IQ_NTM: 6000
Name IQ_WEEK: 50000
Name IQ_YTD: 3000

Sheet guia
A1: Fecha Reporte
A2: =TEXT(EDATE(TODAY(),1),"yyyymm") -> 202608 | B2: =TEXT(EDATE(TODAY(),0),"yyyymm") -> 202607

Sheet 202606
A1: FUND_SHARE_CLASS_ID | B1: FUND_NAME | C1: Client_ID | D1: Security_Status | E1: FUND_ISIN | F1: FUND_TICKER | G1: FUND_FINANCED_CARBON_EMISSIONS | H1: FUND_CARBON_EMISSIONS_SCOPE_3_TOT_EVIC_INTEN | I1: FUND_ISIN
A2: 40056077 | B2: iShares Core S&P 500 ETF | C2: US4642872000 | D2: Matched | E2: US4642872000 | F2: IVV | G2: 22.272457 | H2: 177.58506 | I2: US4642872000
A3: 40056109 | B3: iShares US Real Estate ETF | C3: US4642877397 | D3: Matched | E3: US4642877397 | F3: IYR | G3: 6.7584659 | H3: 39.940379 | I3: US4642877397
A4: 40056868 | B4: iShares MSCI Eurozone ETF | C4: US4642866085 | D4: Matched | E4: US4642866085 | F4: EZU | G4: 43.232015 | H4: 396.91306 | I4: US4642866085
A5: 40068873 | B5: iShares Latin America 40 ETF | C5: US4642873909 | D5: Matched | E5: US4642873909 | F5: ILF | G5: 109.30923 | H5: 743.38134 | I5: US4642873909
A6: 40073950 | B6: iShares Global Energy ETF | C6: US4642873412 | D6: Matched | E6: US4642873412 | F6: IXC | G6: 208.759 | H6: 2220.5207 | I6: US4642873412
A7: 40073951 | B7: iShares Global Financials ETF | C7: US4642873339 | D7: Matched | E7: US4642873339 | F7: IXG | G7: 3.533892 | H7: 54.296142 | I7: US4642873339
A8: 40073952 | B8: iShares Global Healthcare ETF | C8: US4642873255 | D8: Matched | E8: US4642873255 | F8: IXJ | G8: 2.7511171 | H8: 89.510659 | I8: US4642873255
A9: 40073953 | B9: iShares Global Tech ETF | C9: US4642872919 | D9: Matched | E9: US4642872919 | F9: IXN | G9: 7.9125586 | H9: 72.088831 | I9: US4642872919
A10: 40073954 | B10: iShares Global Comm Services ETF | C10: US4642872752 | D10: Matched | E10: US4642872752 | F10: IXP | G10: 3.9668277 | H10: 36.215903 | I10: US4642872752
A11: 40111267 | B11: iShares Global Consumer Discretionary ETF | C11: US4642887453 | D11: Matched | E11: US4642887453 | F11: RXI | G11: 11.680975 | H11: 322.22907 | I11: US4642887453
A12: 40111270 | B12: iShares Global Consumer Staples ETF | C12: US4642887370 | D12: Matched | E12: US4642887370 | F12: KXI | G12: 20.599526 | H12: 283.85097 | I12: US4642887370
A13: 40111272 | B13: iShares Global Industrials ETF | C13: US4642887297 | D13: Matched | E13: US4642887297 | F13: EXI | G13: 29.22582 | H13: 600.13717 | I13: US4642887297
... A26: 68060932 | B26: iShares ? High Yield Corp Bond UCITS ETF EUR D | C26: IE00B66F4759 | D26: Matched | E26: IE00B66F4759 | F26: IHYG | G26: 99.280223 | H26: 741.44553 | I26: IE00B66F4759

Sheet 202607
A1: FUND_SHARE_CLASS_ID | B1: FUND_NAME | C1: Client_ID | D1: Security_Status | E1: FUND_ISIN | F1: FUND_TICKER | G1: FUND_FINANCED_CARBON_EMISSIONS | H1: FUND_CARBON_EMISSIONS_SCOPE_3_TOT_EVIC_INTEN | I1: FUND_ISIN
A2: 40056077 | B2: iShares Core S&P 500 ETF | C2: US4642872000 | D2: Matched | E2: US4642872000 | F2: IVV | G2: 22.272457 | H2: 177.58506 | I2: US4642872000
A3: 40056109 | B3: iShares US Real Estate ETF | C3: US4642877397 | D3: Matched | E3: US4642877397 | F3: IYR | G3: 6.7584659 | H3: 39.940379 | I3: US4642877397
A4: 40056868 | B4: iShares MSCI Eurozone ETF | C4: US4642866085 | D4: Matched | E4: US4642866085 | F4: EZU | G4: 43.232015 | H4: 396.91306 | I4: US4642866085
A5: 40068873 | B5: iShares Latin America 40 ETF | C5: US4642873909 | D5: Matched | E5: US4642873909 | F5: ILF | G5: 109.30923 | H5: 743.38134 | I5: US4642873909
A6: 40073950 | B6: iShares Global Energy ETF | C6: US4642873412 | D6: Matched | E6: US4642873412 | F6: IXC | G6: 208.759 | H6: 2220.5207 | I6: US4642873412
A7: 40073951 | B7: iShares Global Financials ETF | C7: US4642873339 | D7: Matched | E7: US4642873339 | F7: IXG | G7: 3.533892 | H7: 54.296142 | I7: US4642873339
A8: 40073952 | B8: iShares Global Healthcare ETF | C8: US4642873255 | D8: Matched | E8: US4642873255 | F8: IXJ | G8: 2.7511171 | H8: 89.510659 | I8: US4642873255
A9: 40073953 | B9: iShares Global Tech ETF | C9: US4642872919 | D9: Matched | E9: US4642872919 | F9: IXN | G9: 7.9125586 | H9: 72.088831 | I9: US4642872919
A10: 40073954 | B10: iShares Global Comm Services ETF | C10: US4642872752 | D10: Matched | E10: US4642872752 | F10: IXP | G10: 3.9668277 | H10: 36.215903 | I10: US4642872752
A11: 40111267 | B11: iShares Global Consumer Discretionary ETF | C11: US4642887453 | D11: Matched | E11: US4642887453 | F11: RXI | G11: 11.680975 | H11: 322.22907 | I11: US4642887453
A12: 40111270 | B12: iShares Global Consumer Staples ETF | C12: US4642887370 | D12: Matched | E12: US4642887370 | F12: KXI | G12: 20.599526 | H12: 283.85097 | I12: US4642887370
A13: 40111272 | B13: iShares Global Industrials ETF | C13: US4642887297 | D13: Matched | E13: US4642887297 | F13: EXI | G13: 29.22582 | H13: 600.13717 | I13: US4642887297
... A26: 68060932 | B26: iShares ? High Yield Corp Bond UCITS ETF EUR D | C26: IE00B66F4759 | D26: Matched | E26: IE00B66F4759 | F26: IHYG | G26: 99.280223 | H26: 741.44553 | I26: IE00B66F4759

Sheet Reporte ASG Mensual
A1: SBS | B1: ISIN | C1: Fondo | D1: Afp | E1: Emisor | F1: Cobertura | G1: Nombre | H1: Proxy | I1: Proxy
A2: 12535622BA92 | B2: USP58072BA92 | C2: Multifondos | D2: Ex_Integra | E2: Inversiones CMPC | F2: NoCov | G2: iShares Global Materials ETF | H2: US4642886950 | I2: 46174
A3: 15515123CH47 | B3: USP32133CH47 | C3: F1 | D3: Ex_Integra | E3: Banco de Crédito e Inversiones | F3: NoCov | G3: iShares Global Financials ETF | H3: US4642873339 | I3: 46174
A4: 2100022V2H78 | B4: US05971V2H78 | C4: Multifondos | D4: Habitat | E4: Banco de Crédito del Perú | F4: NoCov | G4: iShares Global Financials ETF | H4: US4642873339 | I4: 46174
A5: 1254342KAB22 | B5: USP4R21KAB22 | C5: Multifondos | D5: Ex_Integra | E5: Grupo Nutresa S.A. | F5: NoCov | G5: iShares Global Consumer Discretionary ETF | H5: US4642887453 | I5: 46174
A6: 12535622BA92 | B6: USP58072BA92 | C6: Multifondos | D6: Prima | E6: Inversiones CMPC | F6: NoCov | G6: iShares Global Materials ETF | H6: US4642886950 | I6: 46174
A7: 1551192MAD04 | B7: USP1400MAD04 | C7: Multifondos | D7: Profuturo | E7: Grupo Financiero Banorte | F7: NoCov | G7: iShares Global Financials ETF | H7: US4642873339 | I7: 46174
A8: 1551112LAN29 | B8: US05968LAN29 | C8: Multifondos | D8: Ex_Integra | E8: Banco de Colombia | F8: NoCov | G8: iShares Global Financials ETF | H8: US4642873339 | I8: 46174
A9: 15515123CH47 | B9: USP32133CH47 | C9: F1 | D9: Profuturo | E9: Banco de Crédito e Inversiones | F9: NoCov | G9: iShares Global Financials ETF | H9: US4642873339 | I9: 46174
A10: 1551512PAC05 | B10: US05890PAC05 | C10: F1 | D10: Ex_Integra | E10: Banco de Crédito e Inversiones | F10: NoCov | G10: iShares Global Financials ETF | H10: US4642873339 | I10: 46174
A11: 15515123CH47 | B11: USP32133CH47 | C11: F1 | D11: Prima | E11: Banco de Crédito e Inversiones | F11: NoCov | G11: iShares Global Financials ETF | H11: US4642873339 | I11: 46174
A12: 2100022V2J35 | B12: US05971V2J35 | C12: Multifondos | D12: Habitat | E12: Banco de Crédito del Perú | F12: NoCov | G12: iShares Global Financials ETF | H12: US4642873339 | I12: 46174
A13: 1551192MAD04 | B13: USP1400MAD04 | C13: Multifondos | D13: Ex_Integra | E13: Grupo Financiero Banorte | F13: NoCov | G13: iShares Global Financials ETF | H13: US4642873339 | I13: 46174
... A914: 5277012F9LZQ | B914: IE000NG9LZQX | C914: F1 | D914: Prima | E914: Moneda - Latam High Yield | F914: NoCov | G914: iShares Latin America 40 ETF | H914: US4642873909 | I914: 46174
A915: 4974252S2BDC | C915: F2 | D915: Profuturo | E915: BD Capital - Senior Loans 2 | F915: NoCov | G915: iShares iBoxx $ High Yield Corporate Bond ETF | H915: US4642885135 | I915: 46174
A916: 4974252S2BDC | C916: F1 | D916: Profuturo | E916: BD Capital - Senior Loans 2 | F916: NoCov | G916: iShares iBoxx $ High Yield Corporate Bond ETF | H916: US4642885135 | I916: 46174
A917: 5270582R1157 | B917: KYG6201R1157 | C917: Multifondos | D917: Ex_Integra | E917: Moneda - CLOs | F917: NoCov | G917: iShares iBoxx $ High Yield Corporate Bond ETF | H917: US4642885135 | I917: 46174
A918: 4974252SCBDC | B918: CVL79590GA30 | C918: F1 | D918: Profuturo | E918: BD Capital - Senior Loans C | F918: NoCov | G918: iShares MSCI Peru and Global Exposure ETF | H918: US4642898427 | I918: 46174
A919: 4974252SCBDC | B919: CVL79590GA30 | C919: F2 | D919: Profuturo | E919: BD Capital - Senior Loans C | F919: NoCov | G919: iShares MSCI Peru and Global Exposure ETF | H919: US4642898427 | I919: 46174
A920: 5275262COMP2 | B920: CL0002633205 | C920: F2 | D920: Habitat | E920: FIGLHYI CI - Compass Latam HY | F920: NoCov | G920: iShares Latin America 40 ETF | H920: US4642873909 | I920: 46174
A921: 5275262COMP2 | B921: CL0002633205 | C921: F1 | D921: Habitat | E921: FIGLHYI CI - Compass Latam HY | F921: NoCov | G921: iShares Latin America 40 ETF | H921: US4642873909 | I921: 46174
A922: 4911102LINAE | C922: F2 | D922: Profuturo | E922: Fond. de Inversión Activa Financiamiento Estructurado Peru II | F922: NoCov | G922: iShares MSCI Peru and Global Exposure ETF | H922: US4642898427 | I922: 46174
A923: 5272092MACSM | B923: LU0721876877 | C923: Multifondos | D923: Ex_Integra | E923: Matthews Asia Funds - China Innov Fd I Acc USD | F923: NoCov | G923: iShares MSCI ACWI ETF | H923: US4642882579 | I923: 46174
A924: 4911102LINAE | C924: F1 | D924: Profuturo | E924: Fond. de Inversión Activa Financiamiento Estructurado Peru II | F924: NoCov | G924: iShares MSCI Peru and Global Exposure ETF | H924: US4642898427 | I924: 46174
A925: 5273662CORP1 | B925: LU1569037366 | C925: Multifondos | D925: Ex_Integra | E925: Credicorp Capital Latin American Corporate Debt S | F925: NoCov | G925: iShares Latin America 40 ETF | H925: US4642873909 | I925: 46174
A926: 4974252S2BDC | C926: F2 | D926: Ex_Integra | E926: BD Capital - Senior Loans 2 | F926: NoCov | G926: iShares iBoxx $ High Yield Corporate Bond ETF | H926: US4642885135 | I926: 46174
A927: 4975141HMCPS | C927: F1 | D927: Profuturo | E927: Fondo HMC II (PEN) | F927: NoCov | G927: iShares MSCI Peru and Global Exposure ETF | H927: US4642898427 | I927: 46174
A928: 5273982F6385 | B928: LU1883863851 | C928: Multifondos | D928: Ex_Integra | E928: Amundi Funds US High Yield Bond - I2 U C | F928: NoCov | G928: iShares iBoxx $ High Yield Corporate Bond ETF | H928: US4642885135 | I928: 46174
A929: 4974252S2BDC | C929: F1 | D929: Ex_Integra | E929: BD Capital - Senior Loans 2 | F929: NoCov | G929: iShares iBoxx $ High Yield Corporate Bond ETF | H929: US4642885135 | I929: 46174
A930: 4975141HMCPS | C930: F2 | D930: Profuturo | E930: Fondo HMC II (PEN) | F930: NoCov | G930: iShares MSCI Peru and Global Exposure ETF | H930: US4642898427 | I930: 46174
A931: 4974252SCBDC | B931: CVL79590GA30 | C931: F2 | D931: Ex_Integra | E931: BD Capital - Senior Loans C | F931: NoCov | G931: iShares MSCI Peru and Global Exposure ETF | H931: US4642898427 | I931: 46174
A932: 4974252S2BDC | C932: F2 | D932: Prima | E932: BD Capital - Senior Loans 2 | F932: NoCov | G932: iShares iBoxx $ High Yield Corporate Bond ETF | H932: US4642885135 | I932: 46174
A933: 5277192F9LZQ | B933: IE000NG9LZQ6 | C933: F2 | D933: Habitat | E933: Moneda - Latam High Yield | F933: NoCov | G933: iShares Latin America 40 ETF | H933: US4642873909 | I933: 46174
A934: 4974252S2BDC | C934: F1 | D934: Prima | E934: BD Capital - Senior Loans 2 | F934: NoCov | G934: iShares iBoxx $ High Yield Corporate Bond ETF | H934: US4642885135 | I934: 46174
A935: 5274302F65N6 | B935: IE00BD065N65 | C935: Multifondos | D935: Ex_Integra | E935: Veritas Asian C USD | F935: NoCov | G935: iShares MSCI All Country Asia ex Japan ETF | H935: US4642881829 | I935: 46174
A936: 5277192F9LZQ | B936: IE000NG9LZQ6 | C936: F1 | D936: Habitat | E936: Moneda - Latam High Yield | F936: NoCov | G936: iShares Latin America 40 ETF | H936: US4642873909 | I936: 46174
A937: 5274542F8758 | B937: LU1617687584 | C937: Multifondos | D937: Ex_Integra | E937: Oaktree (Lux.) III - Global Credit Fund I USD acc | F937: NoCov | G937: iShares US & Intl High Yield Corp Bond ETF | H937: US4642861789 | I937: 46174
A938: 491105206SI1 | B938: PEP795509FD5 | C938: F2 | D938: Profuturo | E938: Sigma - Leasing Operativo | F938: NoCov | G938: iShares MSCI Peru and Global Exposure ETF | H938: US4642898427 | I938: 46174
A939: 5274742F1585 | B939: LU0648315850 | C939: Multifondos | D939: Ex_Integra | E939: LarrainVial AM SICAV - Latin American Corp Dbt I | F939: NoCov | G939: iShares Latin America 40 ETF | H939: US4642873909 | I939: 46174
A940: 5274742F8681 | B940: LU2600586817 | C940: Multifondos | D940: Ex_Integra | E940: LarrainVial AM SICAV - Gavekal Latam LC Debt I | F940: NoCov | G940: iShares Latin America 40 ETF | H940: US4642873909 | I940: 46174
A941: 5274822F3552 | B941: CL0002535525 | C941: F1 | D941: Profuturo | E941: Moneda - Deuda Latam LCC | F941: NoCov | G941: iShares Latin America 40 ETF | H941: US4642873909 | I941: 46174
A942: 4974252SCBDC | B942: CVL79590GA30 | C942: F1 | D942: Ex_Integra | E942: BD Capital - Senior Loans C | F942: NoCov | G942: iShares MSCI Peru and Global Exposure ETF | H942: US4642898427 | I942: 46174
A943: 5274822F3552 | B943: CL0002535525 | C943: Multifondos | D943: Ex_Integra | E943: Moneda - Deuda Latam LCC | F943: NoCov | G943: iShares Latin America 40 ETF | H943: US4642873909 | I943: 46174
A944: 4974252SCBDC | B944: CVL79590GA30 | C944: F1 | D944: Prima | E944: BD Capital - Senior Loans C | F944: NoCov | G944: iShares MSCI Peru and Global Exposure ETF | H944: US4642898427 | I944: 46174
A945: 4911102LINAE | C945: F1 | D945: Ex_Integra | E945: Fond. de Inversión Activa Financiamiento Estructurado Peru II | F945: NoCov | G945: iShares MSCI Peru and Global Exposure ETF | H945: US4642898427 | I945: 46174
A946: 5274972DI16R | B946: LU0939496179 | C946: Multifondos | D946: Ex_Integra | E946: LarrainVial AM SICAV - Latin American Equity I | F946: NoCov | G946: iShares Latin America 40 ETF | H946: US4642873909 | I946: 46174
A947: 4974252SCBDC | B947: CVL79590GA30 | C947: F2 | D947: Prima | E947: BD Capital - Senior Loans C | F947: NoCov | G947: iShares MSCI Peru and Global Exposure ETF | H947: US4642898427 | I947: 46174
A948: 52751946750L | B948: LU1959967503 | C948: Multifondos | D948: Ex_Integra | E948: Berenberg European Small Cap I | F948: NoCov | G948: iShares MSCI ACWI ETF | H948: US4642882579 | I948: 46174
A949: 5275194F2546 | B949: LU1966825462 | C949: Multifondos | D949: Ex_Integra | E949: Joh Berenberg - European Focus Fund | F949: NoCov | G949: iShares MSCI ACWI ETF | H949: US4642882579 | I949: 46174
A950: 5274822F3552 | B950: CL0002535525 | C950: F2 | D950: Profuturo | E950: Moneda - Deuda Latam LCC | F950: NoCov | G950: iShares Latin America 40 ETF | H950: US4642873909 | I950: 46174
A951: 5275262COMP2 | B951: CL0002633205 | C951: Multifondos | D951: Ex_Integra | E951: FIGLHYI CI - Compass Latam HY | F951: NoCov | G951: iShares Latin America 40 ETF | H951: US4642873909 | I951: 46174
A952: 4911102LINAE | C952: F2 | D952: Ex_Integra | E952: Fond. de Inversión Activa Financiamiento Estructurado Peru II | F952: NoCov | G952: iShares MSCI Peru and Global Exposure ETF | H952: US4642898427 | I952: 46174
A953: 4975141HMCPS | C953: F2 | D953: Ex_Integra | E953: Fondo HMC II (PEN) | F953: NoCov | G953: iShares MSCI Peru and Global Exposure ETF | H953: US4642898427 | I953: 46174
A954: 5277012F9LZQ | B954: IE000NG9LZQX | C954: Multifondos | D954: Ex_Integra | E954: Moneda - Latam High Yield | F954: NoCov | G954: iShares Latin America 40 ETF | H954: US4642873909 | I954: 46174
A955: 491105206SI1 | B955: PEP795509FD5 | C955: F2 | D955: Prima | E955: Sigma - Leasing Operativo | F955: NoCov | G955: iShares MSCI Peru and Global Exposure ETF | H955: US4642898427 | I955: 46174
A956: 5277132F2733 | B956: LU2301227331 | C956: Multifondos | D956: Ex_Integra | E956: Moneda Luxembourg SICAV Latin America Small Cap I | F956: NoCov | G956: iShares Latin America 40 ETF | H956: US4642873909 | I956: 46174
A957: 5277192F9LZQ | B957: IE000NG9LZQ6 | C957: Multifondos | D957: Ex_Integra | E957: Moneda - Latam High Yield | F957: NoCov | G957: iShares Latin America 40 ETF | H957: US4642873909 | I957: 46174
A958: 491105206SI1 | B958: PEP795509FD5 | C958: Multifondos | D958: Profuturo | E958: Sigma - Leasing Operativo | F958: NoCov | G958: iShares MSCI Peru and Global Exposure ETF | H958: US4642898427 | I958: 46174
A959: 491105206SI1 | B959: PEP795509FD5 | C959: F3 | D959: Prima | E959: Sigma - Leasing Operativo | F959: NoCov | G959: iShares MSCI Peru and Global Exposure ETF | H959: US4642898427 | I959: 46174
A960: 5277292FB100 | B960: KYG6963B1005 | C960: Multifondos | D960: Ex_Integra | E960: Pearl Diver Capital LLC - Floating Rate Global Income | F960: NoCov | G960: iShares iBoxx $ High Yield Corporate Bond ETF | H960: US4642885135 | I960: 46174
A961: 5277462F5710 | B961: LI0229057109 | C961: Multifondos | D961: Ex_Integra | E961: Solitaire Global Bond Fund - USD | F961: NoCov | G961: iShares US & Intl High Yield Corp Bond ETF | H961: US4642861789 | I961: 46174
A962: 4974252SCBDC | B962: CVL79590GA30 | C962: Multifondos | D962: Profuturo | E962: BD Capital - Senior Loans C | F962: NoCov | G962: iShares MSCI Peru and Global Exposure ETF | H962: US4642898427 | I962: 46174
A963: 4975141HMCPS | C963: F3 | D963: Ex_Integra | E963: Fondo HMC II (PEN) | F963: NoCov | G963: iShares MSCI Peru and Global Exposure ETF | H963: US4642898427 | I963: 46174
A964: 4975141HMCPS | C964: F1 | D964: Ex_Integra | E964: Fondo HMC II (PEN) | F964: NoCov | G964: iShares MSCI Peru and Global Exposure ETF | H964: US4642898427 | I964: 46174
A965: 5274822F3552 | B965: CL0002535525 | C965: F1 | D965: Prima | E965: Moneda - Deuda Latam LCC | F965: NoCov | G965: iShares Latin America 40 ETF | H965: US4642873909 | I965: 46174
A966: 491105206SI1 | B966: PEP795509FD5 | C966: F3 | D966: Ex_Integra | E966: Sigma - Leasing Operativo | F966: NoCov | G966: iShares MSCI Peru and Global Exposure ETF | H966: US4642898427 | I966: 46174
A967: 491105206SI1 | B967: PEP795509FD5 | C967: F2 | D967: Ex_Integra | E967: Sigma - Leasing Operativo | F967: NoCov | G967: iShares MSCI Peru and Global Exposure ETF | H967: US4642898427 | I967: 46174
A968: 5274822F3552 | B968: CL0002535525 | C968: F1 | D968: Ex_Integra | E968: Moneda - Deuda Latam LCC | F968: NoCov | G968: iShares Latin America 40 ETF | H968: US4642873909 | I968: 46174
A969: 5274822F3552 | B969: CL0002535525 | C969: F2 | D969: Ex_Integra | E969: Moneda - Deuda Latam LCC | F969: NoCov | G969: iShares Latin America 40 ETF | H969: US4642873909 | I969: 46174
A970: 5274822F3552 | B970: CL0002535525 | C970: F2 | D970: Prima | E970: Moneda - Deuda Latam LCC | F970: NoCov | G970: iShares Latin America 40 ETF | H970: US4642873909 | I970: 46174
A971: 491105206SI1 | B971: PEP795509FD5 | C971: Multifondos | D971: Prima | E971: Sigma - Leasing Operativo | F971: NoCov | G971: iShares MSCI Peru and Global Exposure ETF | H971: US4642898427 | I971: 46174
A972: 4911141MIND1 | B972: CVL79560FI39 | C972: Multifondos | D972: Prima | E972: Macrocapitales SAFI S.A. | F972: NoCov | G972: iShares MSCI Peru and Global Exposure ETF | H972: US4642898427 | I972: 46174
A973: 4974252SCBDC | B973: CVL79590GA30 | C973: Multifondos | D973: Prima | E973: BD Capital - Senior Loans C | F973: NoCov | G973: iShares MSCI Peru and Global Exposure ETF | H973: US4642898427 | I973: 46174
A974: 5274742F8681 | B974: LU2600586817 | C974: F3 | D974: Ex_Integra | E974: LarrainVial AM SICAV - Gavekal Latam LC Debt I | F974: NoCov | G974: iShares Latin America 40 ETF | H974: US4642873909 | I974: 46174
A975: 5274742F8681 | B975: LU2600586817 | C975: F2 | D975: Ex_Integra | E975: LarrainVial AM SICAV - Gavekal Latam LC Debt I | F975: NoCov | G975: iShares Latin America 40 ETF | H975: US4642873909 | I975: 46174
A976: 5274742F8681 | B976: LU2600586817 | C976: F1 | D976: Profuturo | E976: LarrainVial AM SICAV - Gavekal Latam LC Debt I | F976: NoCov | G976: iShares Latin America 40 ETF | H976: US4642873909 | I976: 46174
A977: 5274742F8681 | B977: LU2600586817 | C977: F1 | D977: Ex_Integra | E977: LarrainVial AM SICAV - Gavekal Latam LC Debt I | F977: NoCov | G977: iShares Latin America 40 ETF | H977: US4642873909 | I977: 46174
A978: 4911011FCDS1 | C978: F1 | D978: Ex_Integra | E978: Fondo Credicorp Deuda Soles | F978: NoCov | G978: iShares MSCI Peru and Global Exposure ETF | H978: US4642898427 | I978: 46174
A979: 4911011FCDS1 | C979: F2 | D979: Profuturo | E979: Fondo Credicorp Deuda Soles | F979: NoCov | G979: iShares MSCI Peru and Global Exposure ETF | H979: US4642898427 | I979: 46174
A980: 4911011FCDS1 | C980: F2 | D980: Ex_Integra | E980: Fondo Credicorp Deuda Soles | F980: NoCov | G980: iShares MSCI Peru and Global Exposure ETF | H980: US4642898427 | I980: 46174
A981: 4911011FCDS2 | C981: F2 | D981: Ex_Integra | E981: Fondo Credicorp Deuda Soles II | F981: NoCov | G981: iShares MSCI Peru and Global Exposure ETF | H981: US4642898427 | I981: 46174
A982: 4911011FCDS2 | C982: F1 | D982: Ex_Integra | E982: Fondo Credicorp Deuda Soles II | F982: NoCov | G982: iShares MSCI Peru and Global Exposure ETF | H982: US4642898427 | I982: 46174
A983: 4975142HMCPD | C983: F1 | D983: Ex_Integra | E983: Fondo HMC II (USD) | F983: NoCov | G983: iShares MSCI Peru and Global Exposure ETF | H983: US4642898427 | I983: 46174
A984: 4975142HMCPD | C984: F2 | D984: Ex_Integra | E984: Fondo HMC II (USD) | F984: NoCov | G984: iShares MSCI Peru and Global Exposure ETF | H984: US4642898427 | I984: 46174
A985: 4975142HMCPD | C985: F3 | D985: Ex_Integra | E985: Fondo HMC II (USD) | F985: NoCov | G985: iShares MSCI Peru and Global Exposure ETF | H985: US4642898427 | I985: 46174
A986: 4911141MIND1 | B986: CVL79560FI39 | C986: F2 | D986: Ex_Integra | E986: Macrocapitales SAFI S.A. | F986: NoCov | G986: iShares MSCI Peru and Global Exposure ETF | H986: US4642898427 | I986: 46174
A987: 4911011FCDS1 | C987: F1 | D987: Profuturo | E987: Fondo Credicorp Deuda Soles | F987: NoCov | G987: iShares MSCI Peru and Global Exposure ETF | H987: US4642898427 | I987: 46174
A988: 4911011FCDS2 | C988: F1 | D988: Profuturo | E988: Fondo Credicorp Deuda Soles II | F988: NoCov | G988: iShares MSCI Peru and Global Exposure ETF | H988: US4642898427 | I988: 46174
A989: 4911011FCDS2 | C989: F2 | D989: Profuturo | E989: Fondo Credicorp Deuda Soles II | F989: NoCov | G989: iShares MSCI Peru and Global Exposure ETF | H989: US4642898427 | I989: 46174
A990: 4975142HMCPD | C990: F1 | D990: Profuturo | E990: Fondo HMC II (USD) | F990: NoCov | G990: iShares MSCI Peru and Global Exposure ETF | H990: US4642898427 | I990: 46174
A991: 5275194F2546 | B991: LU1966825462 | C991: F1 | D991: Ex_Integra | E991: Joh Berenberg - European Focus Fund | F991: NoCov | G991: iShares MSCI ACWI ETF | H991: US4642882579 | I991: 46174
A992: 5275194F2546 | B992: LU1966825462 | C992: F3 | D992: Ex_Integra | E992: Joh Berenberg - European Focus Fund | F992: NoCov | G992: iShares MSCI ACWI ETF | H992: US4642882579 | I992: 46174
A993: 5275194F2546 | B993: LU1966825462 | C993: F2 | D993: Ex_Integra | E993: Joh Berenberg - European Focus Fund | F993: NoCov | G993: iShares MSCI ACWI ETF | H993: US4642882579 | I993: 46174
A994: 4975142HMCPD | C994: F2 | D994: Profuturo | E994: Fondo HMC II (USD) | F994: NoCov | G994: iShares MSCI Peru and Global Exposure ETF | H994: US4642898427 | I994: 46174
A995: 5274742F8681 | B995: LU2600586817 | C995: F2 | D995: Prima | E995: LarrainVial AM SICAV - Gavekal Latam LC Debt I | F995: NoCov | G995: iShares Latin America 40 ETF | H995: US4642873909 | I995: 46174
A996: 5274742F8681 | B996: LU2600586817 | C996: F3 | D996: Prima | E996: LarrainVial AM SICAV - Gavekal Latam LC Debt I | F996: NoCov | G996: iShares Latin America 40 ETF | H996: US4642873909 | I996: 46174
A997: 5274742F8681 | B997: LU2600586817 | C997: Multifondos | D997: Profuturo | E997: LarrainVial AM SICAV - Gavekal Latam LC Debt I | F997: NoCov | G997: iShares Latin America 40 ETF | H997: US4642873909 | I997: 46174
A998: 5273662CORP1 | B998: LU1569037366 | C998: Multifondos | D998: Prima | E998: Credicorp Capital Latin American Corporate Debt S | F998: NoCov | G998: iShares Latin America 40 ETF | H998: US4642873909 | I998: 46174
A999: 52751946750L | B999: LU1959967503 | C999: F3 | D999: Ex_Integra | E999: Berenberg European Small Cap I | F999: NoCov | G999: iShares MSCI ACWI ETF | H999: US4642882579 | I999: 46174
A1000: 5274822F3552 | B1000: CL0002535525 | C1000: Multifondos | D1000: Profuturo | E1000: Moneda - Deuda Latam LCC | F1000: NoCov | G1000: iShares Latin America 40 ETF | H1000: US4642873909 | I1000: 46174
...

Sheet 202608
A1: FUND_SHARE_CLASS_ID | B1: FUND_NAME | C1: Client_ID | D1: Security_Status | E1: FUND_ISIN | F1: FUND_ID | G1: FUND_TICKER | H1: FUND_FINANCED_CARBON_EMISSIONS | I1: FUND_FINANCED_CARBON_EMISSIONS_COVERAGE | J1: FUND_CARBON_EMISSIONS_SCOPE_3_DOWN_EVIC_INTEN | K1: FUND_CARBON_EMISSIONS_SCOPE_3_DOWN_EVIC_INTEN_COV | L1: FUND_CARBON_EMISSIONS_SCOPE_3_TOT_EVIC_INTEN | M1: FUND_CARBON_EMISSIONS_SCOPE_3_TOT_EVIC_INTEN_COV | N1: FUND_CARBON_EMISSIONS_SCOPE_3_UPST_EVIC_INTEN | O1: FUND_CARBON_EMISSIONS_SCOPE_3_UPST_EVIC_INTEN_COV | P1: FUND_FOSS_FUEL_SECT_EXP_PCT | Q1: FUND_FOSSIL_FUEL_REVENUES_PCT | R1: FUND_GREEN_REVENUES_PCT | S1: FUND_GREEN_FFB_REV_RATIO | T1: FUND_OIL_GAS_ANY_TIE | U1: FUND_EXP_TO_OG_REV_REFINING | V1: FUND_THERMAL_COAL_ANY_TIE | W1: FUND_WEIGHTED_AVG_CARBON_INTEN | X1: FUND_WEIGHTED_AVG_CARBON_INTEN_COVERAGE | Y1: FUND_CARBON_EMISSIONS_SCOPE_3_DOWN_SALES_INTEN | Z1: FUND_CARBON_EMISSIONS_SCOPE_3_DOWN_SALES_INTEN_COV | AA1: FUND_CARBON_EMISSIONS_SCOPE_3_TOTAL_SALES_INTEN | AB1: FUND_CARBON_EMISSIONS_SCOPE_3_TOTAL_SALES_INTEN_COV | AC1: FUND_CARBON_EMISSIONS_SCOPE_3_UPST_INTEN_PROF | AD1: FUND_CARBON_EMISSIONS_SCOPE_3_UPST_INTEN_PROF_COV | AE1: FUND_WEIGHTED_AVG_SOV_CARBON_INTEN | AF1: FUND_WEIGHTED_AVG_SOV_CARBON_INTEN_COVERAGE | AG1: FUND_OVERSHOOT_GLOBAL_BUDGET_TCRE | AH1: FUND_IMPLIED_TEMP_RISE_OVERSHOOT | AI1: FUND_IMPLIED_TEMP_RISE_BUDGET | AJ1: FUND_ITR_1.5_ALIGN_PCT | AK1: FUND_ITR_2.0_ALIGN_PCT | AL1: FUND_ITR_BAND | AM1: FUND_IMPLIED_TEMP_RISE_COVERAGE | AN1: FUND_ITR_MISALIGN_PCT | AO1: FUND_ITR_STRONG_MISALIGN_PCT | AP1: FUND_IMPLIED_TEMP_RISE | AQ1: FUND_PERC_LOW_CARB_VALUE_COV | AR1: FUND_CBN_LCT_MGMT_SCORE_QUART_1 | AS1: FUND_CARBON_EMISSIONS_CLEANER_ENERGY_SOURCES | AT1: FUND_PERC_LOW_CARB_VALUE | AU1: FUND_HAS_SBTI_APPROVED_TARGET | AV1: FUND_HAS_SBTI_APPROVED_TARGET_COV | AW1: FUND_AFFORD_HOUSING_INVOLV_PCT | AX1: FUND_ALT_ENERGY_INVOLV_PCT | AY1: FUND_CONNECTIVITY_MAX_REV_INVOLV_PCT | AZ1: FUND_EDU_SERVICES_INVOLV_PCT | BA1: FUND_ENERGY_EFF_INVOLV_PCT | BB1: FUND_CLEAN_TECH_INVOLV_PCT | BC1: FUND_GREEN_BLDG_INVOLV_PCT | BD1: FUND_HEALTHCARE_INVOLV_PCT | BE1: FUND_NUTRI_FOOD_INVOLV_PCT | BF1: FUND_POLL_PREV_INVOLV_PCT | BG1: FUND_AFFORD_HOUSING_PCT | BH1: FUND_ALT_ENERGY_PCT | BI1: FUND_CONNECTIVITY_MAX_REV_PCT | BJ1: FUND_EDU_SERVICES_PCT | BK1: FUND_ENERGY_EFF_PCT | BL1: FUND_CLEAN_TECH_PCT | BM1: FUND_GREEN_BLDG_PCT | BN1: FUND_HEALTHCARE_PCT | BO1: FUND_NUTRI_FOOD_PCT | BP1: FUND_POLL_PREV_PCT | BQ1: FUND_SOCIAL_FIN_PCT | BR1: FUND_SANITARY_PROD_PCT | BS1: FUND_SOCIAL_IMPACT_PCT | BT1: FUND_SUST_AG_MAX_REV_PCT | BU1: FUND_SUSTAINABLE_IMPACT_PCT | BV1: FUND_SUST_WATER_PCT | BW1: FUND_SOCIAL_FIN_INVOLV_PCT | BX1: FUND_SANITARY_PROD_INVOLV_PCT | BY1: FUND_SOCIAL_IMPACT_INVOLV_PCT | BZ1: FUND_SUST_AG_MAX_REV_INVOLV_PCT | CA1: FUND_SUSTAINABLE_IMPACT_INVOLV_PCT | CB1: FUND_SUST_WATER_INVOLV_PCT | CC1: FUND_EXP_TO_POLLUT_PREVEN_PCT | CD1: FUND_CT_SUST_AG_MAX_REV | CE1: FUND_EXP_TO_SUST_WATER_PCT | CF1: FUND_OVERSHOOT_GLOBAL_BUDGET_TCRE_SIMULATED | CG1: FUND_CARBON_SCOPE_12_INTEN_3Y_TREND_M_IMPROV | CH1: FUND_WATER_FRESH_WD_INTEN_3Y_TREND_M_IMPROV | CI1: FUND_CARBON_SCOPE_12_INTEN_3Y_TREND_M_NON_DETER | CJ1: FUND_WATER_FRESH_WD_INTEN_3Y_TREND_M_NON_DETER | CK1: FUND_CARBON_SCOPE_12_INTEN_3Y_TREND_M_STABLE | CL1: FUND_WATER_FRESH_WD_INTEN_3Y_TREND_M_STABLE | CM1: FUND_CARBON_SCOPE_12_INTEN_3Y_TREND_M_WORSE | CN1: FUND_WATER_FRESH_WD_INTEN_3Y_TREND_M_WORSE | CO1: FUND_ACCOUNTING_FLAG_PCT | CP1: FUND_BOARD_FLAG_PCT | CQ1: FUND_BOARD_INDEP_0_25PCT | CR1: FUND_BOARD_INDEP_25_50PCT | CS1: FUND_BOARD_INDEP_50_75PCT | CT1: FUND_BOARD_INDEP_75_100PCT | CU1: FUND_CONTROLLING_SHAREHOLDER_PCT | CV1: FUND_CONTROLLING_SHAREHOLDER_CONCERNS_PCT | CW1: FUND_CROSS_SHAREHOLDINGS_PCT | CX1: FUND_MAJORITY_VOTING_PCT | CY1: FUND_ENTRENCHED_BOARD_PCT | CZ1: FUND_EXEC_PAY_NONDISCLOSURE_PCT | DA1: FUND_FEMALE_DIRECTORS_30_PCT | DB1: FUND_GOV_GLOBAL_AVERAGE_PCT | DC1: FUND_GOV_GLOBAL_LAGGARDS_PCT | DD1: FUND_GOV_GLOBAL_LEADERS_PCT | DE1: FUND_GM_EVENT_EVENT_TYPE | DF1: FUND_GOV_METRICS_RESEARCHED_COVERAGE | DG1: FUND_HUMAN_CAPITAL_DEV_MGMT_SCORE | DH1: FUND_HUMAN_CAPITAL_DEV_MGMT_SCORE_COVERAGE | DI1: FUND_INDEPENDENT_BOARD_MAJORITY | DJ1: FUND_LACK_INDEP_MAJORITY_PCT | DK1: FUND_LACK_INTERNAL_PAY_EQUITY_PCT | DL1: FUND_LCT_CAT_ASSET_STRAND_PCT | DM1: FUND_LCT_CAT_NEUTRAL_PCT | DN1: FUND_LCT_CAT_OPERAT_TRANSITION_PCT | DO1: FUND_LCT_CAT_PRODUCT_TRANSITION_PCT | DP1: FUND_LCT_CAT_SOLUTIONS_PCT | DQ1: FUND_LOW_CARBON_TRANSITION | DR1: FUND_LOW_CARBON_TRANS_SCORE_COVERAGE | DS1: FUND_NEGATIVE_DIRECTOR_VOTES_PCT | DT1: FUND_CLASSIFIED_BOARD_PCT | DU1: FUND_NO_FEMALE_DIRECTORS_PCT | DV1: FUND_NO_PAY_PERF_LINK_PCT | DW1: FUND_ONE_SHARE_ONE_VOTE_PCT | DX1: FUND_OVERBOARDING_PCT | DY1: FUND_OWNERSHIP_FLAG_PCT | DZ1: FUND_PAY_FLAG_PCT | EA1: FUND_PAY_LINKED_TO_SUSTAINABILITY | EB1: FUND_POISON_PILL_PCT | EC1: FUND_WASTE_MGMT_THEME_WEIGHT | ED1: FUND_PROD_CARB_FTPRNT_MGMT_SCORE | EE1: FUND_PROD_CARB_FTPRNT_MGMT_SCORE_COVERAGE | EF1: FUND_VOTE_AGAINST_PAY_PRACTICES_PCT | EG1: FUND_THREE_FEMALE_DIRECTORS_PCT | EH1: FUND_TOXIC_EMISS_WSTE_MGMT_SCORE | EI1: FUND_TOXIC_EMISS_WSTE_MGMT_SCORE_COVERAGE | EJ1: FUND_WATER_STRESS_EXP_SCORE_HIGH_PCT | EK1: FUND_WATER_STRESS_EXP_SCORE_LOW_PCT | EL1: FUND_WATER_STRESS_EXP_SCORE_MODERATE_PCT | EM1: FUND_WATER_STRESS_HIGH_RISK_BUS_PCT | EN1: FUND_WATER_STRESS_HIGH_RISK_GEO_PCT | EO1: FUND_WEIGHTED_AVG_WATER_FRESH_WD_INTEN | EP1: FUND_WEIGHTED_AVG_WATER_FRESH_WD_INTEN_COVERAGE | EQ1: FUND_WEIGHTED_AVG_WATER_WD_INTEN | ER1: FUND_WEIGHTED_AVG_WATER_WD_INTEN_COVERAGE | ES1: FUND_COMBINED_CEO_CHAIR | ET1: FUND_DIVERSITY_WORKF_POLICY_M | EU1: FUND_HUMAN_RIGHT_POLICY_M_YES | EV1: FUND_MONITOR_EMP_SATISFACTION_M | EW1: FUND_MONITOR_HUMAN_RIGHTS_POLICY_M | EX1: FUND_NON_COMP_BENEFITS_M | EY1: FUND_PAY_CONTROVERSY | EZ1: FUND_PHILANTHROPIC_INVEST_ALIGN_M | FA1: FUND_LABOR_POLICY_INTL_RECOG_M | FB1: FUND_PRIV_DATA_SECURITY_PROCESS_M | FC1: FUND_DIVERSITY_PROGRAMS_M | FD1: FUND_CBN_RENEW_ENER_USE_M | FE1: FUND_SDG01_ACHIEVE_SIGNAL | FF1: FUND_SDG01_ALIGN_PCT | FG1: FUND_SDG01_ANY_ALIGN_PCT | FH1: FUND_SDG01_ANY_MISALIGN_PCT | FI1: FUND_SDG01_MISALIGN_PCT | FJ1: FUND_SDG01_NEUTRAL_PCT | FK1: FUND_SDG01_STRONG_ALIGN_PCT | FL1: FUND_SDG01_STRONG_MISALIGN_PCT | FM1: FUND_SDG02_ACHIEVE_SIGNAL | FN1: FUND_SDG02_ALIGN_PCT | FO1: FUND_SDG02_ANY_ALIGN_PCT | FP1: FUND_SDG02_ANY_MISALIGN_PCT | FQ1: FUND_SDG02_MISALIGN_PCT | FR1: FUND_SDG02_NEUTRAL_PCT | FS1: FUND_SDG02_STRONG_ALIGN_PCT | FT1: FUND_SDG02_STRONG_MISALIGN_PCT | FU1: FUND_SDG03_ACHIEVE_SIGNAL | FV1: FUND_SDG03_ALIGN_PCT | FW1: FUND_SDG03_ANY_ALIGN_PCT | FX1: FUND_SDG03_ANY_MISALIGN_PCT | FY1: FUND_SDG03_MISALIGN_PCT | FZ1: FUND_SDG03_NEUTRAL_PCT | GA1: FUND_SDG03_STRONG_ALIGN_PCT | GB1: FUND_SDG03_STRONG_MISALIGN_PCT | GC1: FUND_SDG04_ACHIEVE_SIGNAL | GD1: FUND_SDG04_ALIGN_PCT | GE1: FUND_SDG04_ANY_ALIGN_PCT | GF1: FUND_SDG04_ANY_MISALIGN_PCT | GG1: FUND_SDG04_MISALIGN_PCT | GH1: FUND_SDG04_NEUTRAL_PCT | GI1: FUND_SDG04_STRONG_ALIGN_PCT | GJ1: FUND_SDG04_STRONG_MISALIGN_PCT | GK1: FUND_SDG05_ACHIEVE_SIGNAL | GL1: FUND_SDG05_ALIGN_PCT | GM1: FUND_SDG05_ANY_ALIGN_PCT | GN1: FUND_SDG05_ANY_MISALIGN_PCT | GO1: FUND_SDG05_MISALIGN_PCT | GP1: FUND_SDG05_NEUTRAL_PCT | GQ1: FUND_SDG05_STRONG_ALIGN_PCT | GR1: FUND_SDG05_STRONG_MISALIGN_PCT | GS1: FUND_SDG06_ACHIEVE_SIGNAL | GT1: FUND_SDG06_ALIGN_PCT | GU1: FUND_SDG06_ANY_ALIGN_PCT | GV1: FUND_SDG06_ANY_MISALIGN_PCT | GW1: FUND_SDG06_MISALIGN_PCT | GX1: FUND_SDG06_NEUTRAL_PCT | GY1: FUND_SDG06_STRONG_ALIGN_PCT | GZ1: FUND_SDG06_STRONG_MISALIGN_PCT | HA1: FUND_SDG07_ACHIEVE_SIGNAL | HB1: FUND_SDG07_ALIGN_PCT | HC1: FUND_SDG07_ANY_ALIGN_PCT | HD1: FUND_SDG07_ANY_MISALIGN_PCT | HE1: FUND_SDG07_MISALIGN_PCT | HF1: FUND_SDG07_NEUTRAL_PCT | HG1: FUND_SDG07_STRONG_ALIGN_PCT | HH1: FUND_SDG07_STRONG_MISALIGN_PCT | HI1: FUND_SDG08_ACHIEVE_SIGNAL | HJ1: FUND_SDG08_ALIGN_PCT | HK1: FUND_SDG08_ANY_ALIGN_PCT | HL1: FUND_SDG08_ANY_MISALIGN_PCT | HM1: FUND_SDG08_MISALIGN_PCT | HN1: FUND_SDG08_NEUTRAL_PCT | HO1: FUND_SDG08_STRONG_ALIGN_PCT | HP1: FUND_SDG08_STRONG_MISALIGN_PCT | HQ1: FUND_SDG09_ACHIEVE_SIGNAL | HR1: FUND_SDG09_ALIGN_PCT | HS1: FUND_SDG09_ANY_ALIGN_PCT | HT1: FUND_SDG09_ANY_MISALIGN_PCT | HU1: FUND_SDG09_MISALIGN_PCT | HV1: FUND_SDG09_NEUTRAL_PCT | HW1: FUND_SDG09_STRONG_ALIGN_PCT | HX1: FUND_SDG09_STRONG_MISALIGN_PCT | HY1: FUND_SDG10_ACHIEVE_SIGNAL | HZ1: FUND_SDG10_ALIGN_PCT | IA1: FUND_SDG10_ANY_ALIGN_PCT | IB1: FUND_SDG10_ANY_MISALIGN_PCT | IC1: FUND_SDG10_MISALIGN_PCT | ID1: FUND_SDG10_NEUTRAL_PCT | IE1: FUND_SDG10_STRONG_ALIGN_PCT | IF1: FUND_SDG10_STRONG_MISALIGN_PCT | IG1: FUND_SDG11_ACHIEVE_SIGNAL | IH1: FUND_SDG11_ALIGN_PCT | II1: FUND_SDG11_ANY_ALIGN_PCT | IJ1: FUND_SDG11_ANY_MISALIGN_PCT | IK1: FUND_SDG11_MISALIGN_PCT | IL1: FUND_SDG11_NEUTRAL_PCT | IM1: FUND_SDG11_STRONG_ALIGN_PCT | IN1: FUND_SDG11_STRONG_MISALIGN_PCT | IO1: FUND_SDG12_ACHIEVE_SIGNAL | IP1: FUND_SDG12_ALIGN_PCT | IQ1: FUND_SDG12_ANY_ALIGN_PCT | IR1: FUND_SDG12_ANY_MISALIGN_PCT | IS1: FUND_SDG12_MISALIGN_PCT | IT1: FUND_SDG12_NEUTRAL_PCT | IU1: FUND_SDG12_STRONG_ALIGN_PCT | IV1: FUND_SDG12_STRONG_MISALIGN_PCT | IW1: FUND_SDG13_ACHIEVE_SIGNAL | IX1: FUND_SDG13_ALIGN_PCT | IY1: FUND_SDG13_ANY_ALIGN_PCT | IZ1: FUND_SDG13_ANY_MISALIGN_PCT | JA1: FUND_SDG13_MISALIGN_PCT | JB1: FUND_SDG13_NEUTRAL_PCT | JC1: FUND_SDG13_STRONG_ALIGN_PCT | JD1: FUND_SDG13_STRONG_MISALIGN_PCT | JE1: FUND_SDG14_ACHIEVE_SIGNAL | JF1: FUND_SDG14_ALIGN_PCT | JG1: FUND_SDG14_ANY_ALIGN_PCT | JH1: FUND_SDG14_ANY_MISALIGN_PCT | JI1: FUND_SDG14_MISALIGN_PCT | JJ1: FUND_SDG14_NEUTRAL_PCT | JK1: FUND_SDG14_STRONG_ALIGN_PCT | JL1: FUND_SDG14_STRONG_MISALIGN_PCT | JM1: FUND_SDG15_ACHIEVE_SIGNAL | JN1: FUND_SDG15_ALIGN_PCT | JO1: FUND_SDG15_ANY_ALIGN_PCT | JP1: FUND_SDG15_ANY_MISALIGN_PCT | JQ1: FUND_SDG15_MISALIGN_PCT | JR1: FUND_SDG15_NEUTRAL_PCT | JS1: FUND_SDG15_STRONG_ALIGN_PCT | JT1: FUND_SDG15_STRONG_MISALIGN_PCT | JU1: FUND_SDG16_ACHIEVE_SIGNAL | JV1: FUND_SDG16_ALIGN_PCT | JW1: FUND_SDG16_ANY_ALIGN_PCT | JX1: FUND_SDG16_ANY_MISALIGN_PCT | JY1: FUND_SDG16_MISALIGN_PCT | JZ1: FUND_SDG16_NEUTRAL_PCT | KA1: FUND_SDG16_STRONG_ALIGN_PCT | KB1: FUND_SDG16_STRONG_MISALIGN_PCT | KC1: FUND_SDG17_ACHIEVE_SIGNAL | KD1: FUND_SDG17_ALIGN_PCT | KE1: FUND_SDG17_ANY_ALIGN_PCT | KF1: FUND_SDG17_ANY_MISALIGN_PCT | KG1: FUND_SDG17_MISALIGN_PCT | KH1: FUND_SDG17_NEUTRAL_PCT | KI1: FUND_SDG17_STRONG_ALIGN_PCT | KJ1: FUND_SDG17_STRONG_MISALIGN_PCT | KK1: FUND_SDG_COVERAGE | KL1: FUND_ESG_SCORE_ADJUSTMENT | KM1: FUND_ESG_SCORE_ADJUSTMENT_PCT | KN1: FUND_ESG_TREND_NEGATIVE_PCT | KO1: FUND_ASSET_CLASS | KP1: FUND_ASSET_UNIVERSE | KQ1: FUND_DOMICILE | KR1: FUND_ESG_AVERAGE_PCT | KS1: FUND_ESG_COVERAGE | KT1: FUND_ESG_COVERAGE_OVERALL | KU1: FUND_ESG_ENV_SCORE_AVG_PEER | KV1: FUND_ESG_GOV_SCORE_AVG_PEER | KW1: FUND_ESG_LAGGARDS_PCT | KX1: FUND_ESG_LEADERS_PCT | KY1: FUND_ESG_POLICY | KZ1: FUND_ESG_QUALITY_SCORE | LA1: FUND_ESG_QUALITY_SCORE_PCTL_GLOBAL | LB1: FUND_ESG_QUALITY_SCORE_AVG_PEER | LC1: FUND_ESG_QUALITY_SCORE_PCTL_PEER | LD1: FUND_ESG_RATING | LE1: ESG_RATING_A | LF1: ESG_RATING_AA | LG1: ESG_RATING_AAA | LH1: ESG_RATING_B | LI1: ESG_RATING_BB | LJ1: ESG_RATING_BBB | LK1: ESG_RATING_CCC | LL1: ESG_RATING_NoValue | LM1: FUND_ESG_SOCIAL_SCORE_AVG_PEER | LN1: FUND_ESG_TREND_NONE_PCT | LO1: FUND_ESG_TREND_POSITIVE_PCT | LP1: FUND_ESG_TREND_STABLE_PCT | LQ1: ESG_ENVIRONMENTAL_SCORE | LR1: FUND_ENVIRONMENTAL_WEIGHT | LS1: FUND_GEO_FOCUS | LT1: ESG_GOVERNANCE_SCORE | LU1: FUND_GOVERNANCE_WEIGHT | LV1: FUND_HOLDINGS_COUNT | LW1: FUND_HOLDING_FUNDS_COUNT | LX1: FUND_HOLDINGS_MATCHED | LY1: FUND_IN_UNIVERSE | LZ1: FUND_INVESTMENT_STRATEGY | MA1: FUND_LATEST_HOLDINGS_DATE | MB1: FUND_LIPPER_GLOBAL_CLASS | MC1: FUND_LIPPER_GLOBAL_CLASS_SIZE | MD1: FUND_MANAGER | ME1: FUND_OVERVIEW_NAME | MF1: ESG_SOCIAL_SCORE | MG1: FUND_SOCIAL_WEIGHT | MH1: FUND_NAV_USD | MI1: FUND_WEIGHTED_AVG_ESG_SCORE | MJ1: FUND_WEIGHTED_AVG_SCORE_PCTL_GLOBAL | MK1: FUND_WEIGHTED_AVG_SCORE_PCTL_PEER | ML1: FUND_WEIGHTED_AVG_KEY_ISSUE_SCORE | MM1: FUND_OF_FUNDS | MN1: FUND_AE_TIE_PCT | MO1: FUND_AE_HIGH_RESTRICT_PCT | MP1: FUND_AE_LEAST_RESTRICT_PCT | MQ1: FUND_AE_MODER_RESTRICT_PCT | MR1: FUND_ALC_TIE_PCT | MS1: FUND_ALC_HIGH_RESTRICT_PCT | MT1: FUND_ALC_LEAST_RESTRICT_PCT | MU1: FUND_ALC_MODER_RESTRICT_PCT | MV1: FUND_ANI_TIE_PCT | MW1: FUND_ANI_HIGH_RESTRICT_PCT | MX1: FUND_ANI_MODER_RESTRICT_PCT | MY1: FUND_WEAP_BIO_CHEM_TIE_PCT | MZ1: FUND_CANNA_TIE_PCT | NA1: FUND_CANNA_HIGH_RESTRICT_PCT | NB1: FUND_CANNA_MODER_RESTRICT_PCT | NC1: FUND_CATHOLIC_VALUES_FAIL_PCT | ND1: FUND_PROD_CIV_ARMS_AUTO_PCT | NE1: FUND_FIREARM_REV_PCT10_PCT | NF1: FUND_FIREARM_TIE_PCT | NG1: FUND_FIREARM_HIGH_RESTRICT_PCT | NH1: FUND_FIREARM_MODER_RESTRICT_PCT | NI1: FUND_PROD_CIV_ARMS_PCT | NJ1: FUND_PROD_CIV_ARMS_AMMO_PCT | NK1: FUND_PROD_CIV_ARMS_SEMI_PCT | NL1: FUND_FIREARM_RETAILER_PCT | NM1: FUND_CM_TIE_PCT | NN1: FUND_CM_HIGH_RESTRICT_PCT | NO1: FUND_CM_MODER_RESTRICT_PCT | NP1: FUND_CONTR_WEAP_TIE_PCT | NQ1: FUND_CONTR_CONTROVERSIAL_WORKPLACE_M | NR1: FUND_CONTR_CONV_WEAP_TIE_PCT | NS1: FUND_CONV_WEAP_HIGH_RESTRICT_PCT | NT1: FUND_CONV_WEAP_LEAST_RESTRICT_PCT | NU1: FUND_CONV_WEAP_MODER_RESTRICT_PCT | NV1: FUND_PRED_LEND_DIRECT_PCT | NW1: FUND_FIREARM_LEAST_RESTRICT_PCT | NX1: FUND_FOSSIL_FUEL_RESERVES_PCT | NY1: FUND_GAM_TIE_PCT | NZ1: FUND_GAM_HIGH_RESTRICT_PCT | OA1: FUND_GAM_LEAST_RESTRICT_PCT | OB1: FUND_GAM_MODER_RESTRICT_PCT | OC1: FUND_GMO_TIE_PCT | OD1: FUND_GMO_HIGH_RESTRICT_PCT | OE1: FUND_GMO_LEAST_RESTRICT_PCT | OF1: FUND_GMO_MODER_RESTRICT_PCT | OG1: FUND_UNGC_COMPLIANCE_VIOLATION_PCT | OH1: FUND_UNGC_COMPLIANCE_VIOLATION_WATCH_LIST_PCT | OI1: FUND_CONTR_HEALTH_SAFETY_M | OJ1: FUND_HIGH_IMPACT_FOSSIL_FUEL_RESERVES_PCT | OK1: FUND_HR_COMPLIANCE_VIOLATION_PCT | OL1: FUND_HR_NORMS_VIOLATION_WATCH_LIST_PCT | OM1: FUND_ISLAMIC_NON_COMPLIANT_PCT | ON1: FUND_LABOR_COMPLIANCE_VIOLATION_PCT | OO1: FUND_LABOR_NORMS_VIOLATION_WATCH_LIST_PCT | OP1: FUND_LM_TIE_PCT | OQ1: FUND_LM_HIGH_RESTRICT_PCT | OR1: FUND_LM_MODER_RESTRICT_PCT | OS1: FUND_NATURAL_GAS_RESERVES | OT1: FUND_NUC_TIE_PCT | OU1: FUND_NUC_HIGH_RESTRICT_PCT | OV1: FUND_NUC_LEAST_RESTRICT_PCT | OW1: FUND_NUC_MODER_RESTRICT_PCT | OX1: FUND_WEAP_NUC_TIE_PCT | OY1: FUND_WEAP_NUC_HIGH_RESTRICT_PCT | OZ1: FUND_WEAP_NUC_LEAST_RESTRICT_PCT | PA1: FUND_WEAP_NUC_MODER_RESTRICT_PCT | PB1: FUND_PALM_TIE_PCT | PC1: FUND_PALM_HIGH_RESTRICT_PCT | PD1: FUND_PALM_MODER_RESTRICT_PCT | PE1: FUND_CONTR_PRODUCT_SAFE_M | PF1: FUND_VERY_SEVERE_CONTROVERSY_PCT | PG1: FUND_VERY_SEVERE_CUST_CONTROVERSY_PCT | PH1: FUND_VERY_SEVERE_ENV_CONTROVERSY_PCT | PI1: FUND_VERY_SEVERE_GOV_CONTROVERSY_PCT | PJ1: FUND_VERY_SEVERE_HR_CONTROVERSY_PCT | PK1: FUND_VERY_SEVERE_LR_CONTROVERSY_PCT | PL1: FUND_CHILD_LABOR_CONTROVERSY_PCT | PM1: FUND_SEVERE_CONTROVERSY_PCT | PN1: FUND_CUSTOMER_CONTROVERSY_PCT | PO1: FUND_ENVIRONMENT_CONTROVERSY_PCT | PP1: FUND_GOVERNANCE_CONTROVERSY_PCT | PQ1: FUND_HUMAN_RIGHTS_CONTROVERSY_PCT | PR1: FUND_LABOR_RIGHTS_CONTROVERSY_PCT | PS1: FUND_REV_EXP_AE | PT1: FUND_REV_EXP_ALC | PU1: FUND_REV_EXP_CONV_WEAP | PV1: FUND_REV_EXP_FIREARM | PW1: FUND_REV_EXP_GAM | PX1: FUND_REV_EXP_GMO | PY1: FUND_REV_EXP_NUC | PZ1: FUND_REV_EXP_TOB | QA1: FUND_SRI_EXCLUSION_CRITERIA_PCT | QB1: FUND_THERMAL_COAL_TIE_PCT | QC1: FUND_THERMAL_COAL_HIGH_RESTRICT_PCT | QD1: FUND_THERMAL_COAL_LEAST_RESTRICT_PCT | QE1: FUND_THERMAL_COAL_MODER_RESTRICT_PCT | QF1: FUND_THERMAL_COAL_RESERVES | QG1: FUND_TOB_TIE_PCT | QH1: FUND_TOB_HIGH_RESTRICT_PCT | QI1: FUND_TOB_LEAST_RESTRICT_PCT | QJ1: FUND_TOB_MODER_RESTRICT_PCT | QK1: FUND_WEAP_GTIE_PCT
A2: 40056077 | B2: iShares Core S&P 500 ETF | C2: US4642872000 | D2: Matched | E2: US4642872000 | F2: 35557136 | G2: IVV | H2: 22.262271 | I2: 99.540277 | J2: 124.59092 | K2: 99.540277 | L2: 178.49342 | M2: 99.540277 | N2: 53.902503 | O2: 99.540277 | P2: 11.5163 | Q2: 2.9126284 | R2: 13.262482 | S2: 4.553441 | T2: 11.42105 | U2: 1.6185507 | V2: 3.5443457 | W2: 91.559741 | X2: 99.651031 | Y2: 401.63503 | Z2: 99.651031 | AA2: 649.75138 | AB2: 99.651031 | AC2: 248.1162 | AD2: 99.651031 | AE2: 202.59174 | AF2: 0.04533778 | AG2: 2006.2231 | AH2: 5004.9451 | AI2: 1467.4775 | AJ2: 29.361012 | AK2: 19.647897 | AL2: Misaligned | AM2: 99.540277 | AN2: 30.349614 | AO2: 20.18398 | AP2: 3 | AQ2: 93.363195 | AR2: 63.006747 | AS2: 97.40707 | AT2: 5.3719495 | AU2: 58.404463 | AV2: 99.651031 | AW2: 0.83228747 | AX2: 4.6116199 | AY2: 1.1348104 | AZ2: 0 | BA2: 22.154424 | BB2: 25.719233 | BC2: 1.3940016 | BD2: 1.8498827 | BE2: 1.1811373 | BF2: 1.9954151 | BG2: 0.08031326 | BH2: 0.3022154 | BI2: 0.00248368 | BJ2: 0 | BK2: 9.048343 | BL2: 9.649701 | BM2: 0.15104092 | BN2: 0.75797205 | BO2: 0.11900751 | BP2: 0.07289786 | BQ2: 0.01661208 | BR2: 0.0910415 | BS2: 1.0674301 | BT2: 0.02537893 | BU2: 10.716943 | BV2: 0.04982493 | BW2: 1.3642226 | BX2: 1.7123996 | BY2: 7.0243966 | BZ2: 0.14846587 | CA2: 29.442336 | CB2: 2.4576861 | CC2: 0.1565869 | CD2: 0.03093161 | CE2: 0.05441826 | CG2: 60.150693 | CH2: 9.369657 | CI2: 2.527135 | CJ2: 74.289303 | CK2: 24.54936 | CL2: 10.636609 | CM2: 12.449204 | CN2: 3.7570639 | CO2: 24.452926 | CP2: 17.510465 | CQ2: 0 | CR2: 2.075361 | CS2: 18.29978 | CT2: 79.139878 | CU2: 13.25255 | CV2: 10.339601 | CW2: 0.00249868 | CX2: 96.321925 | CY2: 37.110499 | CZ2: 0.88565437 | DA2: 74.972256 | DB2: 67.95532 | DC2: 14.389952 | DD2: 17.215523 | DE2: 59.133978 | DF2: 99.567862 | DG2: 6.0266269 | DH2: 99.542502 | DI2: 97.600179 | DJ2: 2.0762128 | DK2: 42.814634 | DL2: 2.3079087 | DM2: 64.535322 | DN2: 3.4020655 | DO2: 12.587792 | DP2: 16.70895 | DQ2: 6.2655873 | DR2: 99.542037 | DS2: 41.847165 | DT2: 8.7063544 | DU2: 0 | DV2: 2.2246617 | DW2: 17.519226 | DX2: 59.766137 | DY2: 18.349265 | DZ2: 4.197354 | EA2: 54.630049 | EB2: 0.00090404 | EC2: 3.3415771 | ED2: 6.0104202 | EE2: 12.300468 | EF2: 23.537997 | EG2: 83.441485 | EH2: 4.1759165 | EI2: 17.341882 | EJ2: 5.9723861 | EK2: 57.233529 | EL2: 36.086382 | EM2: 5.010186 | EN2: 1.4397442 | EO2: 14517.367 | EP2: 42.499425 | EQ2: 11650.364 | ER2: 79.714661 | ES2: 41.393955 | ET2: 22.034211 | EU2: 3.8223222 | EV2: 54.722224 | EW2: 2.7616949 | EX2: 56.063876 | EY2: 2.1322092 | EZ2: 3.5897889 | FA2: 86.440979 | FB2: 99.006649 | FC2: 19.865094 | FD2: 95.431218 | FE2: Not Aligned | FF2: 4.5348937 | FG2: 4.5348937 | FH2: 22.379252 | FI2: 22.366971 | FJ2: 72.628357 | FK2: 0 | FL2: 0.01228063 | FM2: Aligned | FN2: 0.74422636 | FO2: 0.75550857 | FP2: 0.70448902 | FQ2: 0.70448902 | FR2: 98.082505 | FS2: 0.01128221 | FT2: 0 | FU2: Not Aligned | FV2: 7.0016584 | FW2: 7.0016584 | FX2: 8.2896599 | FY2: 7.6555599 | FZ2: 84.251184 | GA2: 0 | GB2: 0.63410002 | GC2: Not Aligned | GD2: 0 | GE2: 0 | GF2: 4.7488111 | GG2: 4.7488111 | GH2: 94.793691 | GI2: 0 | GJ2: 0 | GK2: Aligned | GL2: 40.464802 | GM2: 40.464802 | GN2: 0 | GO2: 0 | GP2: 59.0777 | GQ2: 0 | GR2: 0 | GS2: Aligned | GT2: 6.1748387 | GU2: 6.3402778 | GV2: 1.5505548 | GW2: 1.5505548 | GX2: 91.65167 | GY2: 0.16543911 | GZ2: 0 | HA2: Not Aligned | HB2: 34.220229 | HC2: 34.220229 | HD2: 3.9003752 | HE2: 0.20695611 | HF2: 61.421898 | HG2: 0 | HH2: 3.693419 | HI2: Not Aligned | HJ2: 10.505439 | HK2: 10.505439 | HL2: 11.456134 | HM2: 11.456134 | HN2: 77.58093 | HO2: 0 | HP2: 0 | HQ2: Not Aligned | HR2: 12.649946 | HS2: 12.966646 | HT2: 24.447247 | HU2: 24.434966 | HV2: 62.128609 | HW2: 0.31670057 | HX2: 0.01228063 | HY2: Aligned | HZ2: 14.155453 | IA2: 14.155453 | IB2: 12.457654 | IC2: 12.457654 | ID2: 72.929395 | IE2: 0 | IF2: 0 | IG2: Not Aligned | IH2: 3.3361389 | II2: 3.3361389 | IJ2: 16.968877 | IK2: 16.968877 | IL2: 79.237486 | IM2: 0 | IN2: 0 | IO2: Not Aligned | IP2: 19.210096 | IQ2: 29.247867 | IR2: 5.9704107 | IS2: 2.2769917 | IT2: 64.324225 | IU2: 10.03777 | IV2: 3.693419 | IW2: Not Aligned | IX2: 41.621683 | IY2: 41.621683 | IZ2: 3.9146701 | JA2: 0.22125109 | JB2: 54.00615 | JC2: 0 | JD2: 3.693419 | JE2: Not Aligned | JF2: 0.04343151 | JG2: 0.04343151 | JH2: 5.8108689 | JI2: 5.730296 | JJ2: 93.688202 | JK2: 0 | JL2: 0.08057294 | JM2: Not Aligned | JN2: 0 | JO2: 0 | JP2: 6.8104924 | JQ2: 6.8104924 | JR2: 92.73201 | JS2: 0 | JT2: 0 | JU2: Aligned | JV2: 10.32258 | JW2: 10.32258 | JX2: 9.6991626 | JY2: 9.6991626 | JZ2: 79.52076 | KA2: 0 | KB2: 0 | KC2: Not Aligned | KD2: 0.89998073 | KE2: 0.89998073 | KF2: 23.661159 | KG2: 23.661159 | KH2: 74.981363 | KI2: 0 | KJ2: 0 | KK2: 99.542502 | KL2: 0.17699742 | KM2: 2.7240137 | KN2: 6.0527457 | KO2: Equity | KP2: Exchange Traded Funds | KQ2: USA | KR2: 54.468621 | KS2: 99.710181 | KT2: 99.58784 | KU2: 5.7830404 | KV2: 5.6110777 | KW2: 2.9448919 | KX2: 42.174328 | KZ2: 6.49767 | LA2: 48.106397 | LB2: 6.5045186 | LC2: 53.241343 | LD2: A | LE2: 19.508835 | LF2: 33.389758 | LG2: 8.7845694 | LH2: 2.9130421 | LI2: 6.1195495 | LJ2: 28.840237 | LK2: 0.03184977 | LL2: 0.41215977 | LM2: 4.7866754 | LN2: 0.41215977 | LO2: 11.721651 | LP2: 81.813443 | LQ2: 5.817533 | LR2: 19.249343 | LS2: United States of America | LT2: 5.4837464 | LU2: 38.021967 | LV2: 507 | LW2: 2 | LX2: 505 | LY2: T | LZ2: The Fund seeks investment results that correspond generally to the price and yield performance of the S&P 500 Index which is composed of large-capitalization U.S. equities. The underlying Index included approximately 86.44% of the market capitalization of all publicly traded U.S. equity securities. | MA2: 46203 | MB2: Equity US | MC2: 3841 | MD2: BlackRock Fund Advisors | ME2: iShares Core S&P 500 ETF | MF2: 4.7459526 | MG2: 42.316531 | MH2: 888128937468 | MI2: 6.49767 | MJ2: 48.106397 | MK2: 53.241343 | ML2: 5.2347632 | MM2: T | MN2: 4.6608215 | MO2: 0.08157136 | MP2: 0 | MQ2: 0 | MR2: 10.733805 | MS2: 4.4327096 | MT2: 0.04652663 | MU2: 0.04652663 | MV2: 13.77476 | MW2: 13.750798 | MX2: 12.799997 | MY2: 0 | MZ2: 0.18580698 | NA2: 0 | NB2: 0 | NC2: 10.360527 | ND2: 0 | NE2: 0 | NF2: 0.7677892 | NG2: 0 | NH2: 0 | NI2: 0 | NJ2: 0 | NK2: 0 | NL2: 0.7677892 | NM2: 0.42373178 | NN2: 0.42373178 | NO2: 0 | NP2: 0.56281245 | NQ2: 0.51309086 | NR2: 7.884528 | NS2: 3.9146884 | NT2: 1.1047578 | NU2: 1.1884259 | NV2: 0.00310939 | NW2: 0 | NX2: 4.6880442 | NY2: 1.9112859 | NZ2: 0.54803574 | OA2: 0.0481241 | OB2: 0.0929534 | OC2: 0.2740503 | OD2: 0.2740503 | OE2: 0.08756191 | OF2: 0.08756191 | OG2: 0 | OH2: 18.314384 | OI2: 13.00933 | OJ2: 4.5482646 | OK2: 0 | OL2: 10.298796 | OM2: 67.853558 | ON2: 0 | OO2: 5.7706043 | OP2: 0 | OQ2: 0 | OR2: 0 | OS2: 2.1063156 | OT2: 4.4648894 | OU2: 2.9017545 | OV2: 1.4830917 | OW2: 1.4830917 | OX2: 1.92137 | OY2: 1.3184209 | OZ2: 1.054537 | PA2: 1.054537 | PB2: 0.07937483 | PC2: 0.02236473 | PD2: 0 | PE2: 22.25739 | PF2: 0.01228063 | PG2: 0.01228063 | PH2: 0 | PI2: 0 | PJ2: 0 | PK2: 0 | PL2: 0 | PM2: 30.868916 | PN2: 14.497737 | PO2: 3.3491184 | PP2: 8.6543611 | PQ2: 4.6159579 | PR2: 5.7706043 | PS2: 0.04524958 | PT2: 0.21778455 | PU2: 0.82108312 | PV2: 0.00760111 | PW2: 0.08792909 | PX2: 0.04817268 | PY2: 0.37316327 | PZ2: 0.67112148 | QA2: 11.681092 | QB2: 0.00020424 | QC2: 0 | QD2: 0 | QE2: 0 | QF2: 1.8377065 | QG2: 5.4285893 | QH2: 0.66714791 | QI2: 0.62181939 | QJ2: 0.62181939 | QK2: 7.884528
A3: 40056109 | B3: iShares US Real Estate ETF | C3: US4642877397 | D3: Matched | E3: US4642877397 | F3: 35557182 | G3: IYR | H3: 6.7813414 | I3: 99.464999 | J3: 10.78743 | K3: 99.464999 | L3: 40.1148 | M3: 99.464999 | N3: 29.32737 | O3: 99.464999 | P3: 2.3917048 | Q3: 0.02296265 | R3: 15.262255 | S3: 664.65566 | T3: 2.3917048 | U3: 0 | V3: 1.2757026 | W3: 70.969563 | X3: 99.464999 | Y3: 26.371452 | Z3: 99.464999 | AA3: 255.32308 | AB3: 99.464999 | AC3: 228.9528 | AD3: 99.464999 | AE3: 202.59174 | AF3: 0.05487671 | AG3: 249.27856 | AH3: 622.06956 | AI3: 239.61816 | AJ3: 11.501023 | AK3: 23.333947 | AL3: Misaligned | AM3: 99.464999 | AN3: 37.693075 | AO3: 26.936954 | AP3: 2.6 | AQ3: 52.444705 | AR3: 69.042538 | AS3: 96.161092 | AT3: 0.8770182 | AU3: 64.536829 | AV3: 99.464999 | AW3: 34.239168 | AX3: 8.7238175 | AY3: 3.8540077 | AZ3: 0 | BA3: 28.297057 | BB3: 75.293151 | BC3: 65.610131 | BD3: 0 | BE3: 0.18200036 | BF3: 0 | BG3: 4.2651555 | BH3: 0.01221334 | BI3: 0.0489459 | BJ3: 0 | BK3: 6.5359206 | BL3: 15.249325 | BM3: 7.6640448 | BN3: 0 | BO3: 0.0001092 | BP3: 0 | BQ3: 0 | BR3: 0 | BS3: 4.3142106 | BT3: 1.0371462 | BU3: 19.554551 | BV3: 0 | BW3: 0 | BX3: 0 | BY3: 38.275177 | BZ3: 1.2757026 | CA3: 77.309955 | CB3: 0 | CC3: 0 | CD3: 1.0371462 | CE3: 0 | CG3: 59.85162 | CH3: 2.0614041 | CI3: 2.3341047 | CJ3: 80.12486 | CK3: 33.855668 | CL3: 0 | CM3: 3.4236068 | CN3: 2.5391051 | CO3: 21.453443 | CP3: 3.492807 | CQ3: 0 | CR3: 0 | CS3: 13.165426 | CT3: 86.299573 | CU3: 2.020504 | CV3: 1.6780034 | CW3: 0 | CX3: 94.218688 | CY3: 38.326877 | CZ3: 5.6197112 | DA3: 89.028978 | DB3: 74.022148 | DC3: 2.1369043 | DD3: 23.305947 | DE3: 67.049134 | DF3: 99.464999 | DG3: 5.8858399 | DH3: 99.464999 | DI3: 99.464999 | DJ3: 0 | DK3: 59.599919 | DL3: 0 | DM3: 93.635987 | DN3: 0 | DO3: 1.2757026 | DP3: 4.5533091 | DQ3: 6.3988804 | DR3: 99.464999 | DS3: 37.911976 | DT3: 2.9342059 | DU3: 0 | DV3: 11.132222 | DW3: 87.848176 | DX3: 28.432457 | DY3: 14.184328 | DZ3: 0.85460171 | EA3: 77.922256 | EB3: 0 | EC3: 0 | EE3: 0 | EF3: 41.584483 | EG3: 92.693485 | EI3: 0 | EJ3: 1.2757026 | EK3: 24.267649 | EL3: 73.921648 | EM3: 1.2757026 | EN3: 0 | EO3: 1347.3211 | EP3: 20.10614 | EQ3: 33683.612 | ER3: 77.312555 | ES3: 10.267921 | ET3: 27.385855 | EU3: 0 | EV3: 70.255941 | EW3: 0 | EX3: 45.870092 | EY3: 0 | EZ3: 0 | FA3: 80.556861 | FB3: 91.055482 | FC3: 26.696353 | FD3: 90.18878 | FE3: Aligned | FF3: 18.285837 | FG3: 18.285837 | FH3: 0 | FI3: 0 | FJ3: 81.179162 | FK3: 0 | FL3: 0 | FM3: Aligned | FN3: 1.2757026 | FO3: 1.2757026 | FP3: 0 | FQ3: 0 | FR3: 98.189296 | FS3: 0 | FT3: 0 | FU3: Not Aligned | FV3: 0 | FW3: 0 | FX3: 0 | FY3: 0 | FZ3: 99.464999 | GA3: 0 | GB3: 0 | GC3: Not Aligned | GD3: 0 | GE3: 0 | GF3: 0 | GG3: 0 | GH3: 99.464999 | GI3: 0 | GJ3: 0 | GK3: Aligned | GL3: 48.202096 | GM3: 48.202096 | GN3: 0 | GO3: 0 | GP3: 51.262903 | GQ3: 0 | GR3: 0 | GS3: Aligned | GT3: 1.2757026 | GU3: 1.2757026 | GV3: 0 | GW3: 0 | GX3: 98.189296 | GY3: 0 | GZ3: 0 | HA3: Aligned | HB3: 26.901454 | HC3: 26.901454 | HD3: 0 | HE3: 0 | HF3: 72.563545 | HG3: 0 | HH3: 0 | HI3: Aligned | HJ3: 22.191044 | HK3: 22.191044 | HL3: 0 | HM3: 0 | HN3: 77.273955 | HO3: 0 | HP3: 0 | HQ3: Aligned | HR3: 17.611935 | HS3: 17.611935 | HT3: 0 | HU3: 0 | HV3: 81.853064 | HW3: 0 | HX3: 0 | HY3: Aligned | HZ3: 38.624877 | IA3: 38.624877 | IB3: 0 | IC3: 0 | ID3: 60.840122 | IE3: 0 | IF3: 0 | IG3: Aligned | IH3: 44.203788 | II3: 44.203788 | IJ3: 0 | IK3: 0 | IL3: 55.261211 | IM3: 0 | IN3: 0 | IO3: Aligned | IP3: 53.960008 | IQ3: 64.082828 | IR3: 0 | IS3: 0 | IT3: 35.382171 | IU3: 10.12282 | IV3: 0 | IW3: Aligned | IX3: 9.9347199 | IY3: 9.9347199 | IZ3: 0 | JA3: 0 | JB3: 89.530279 | JC3: 0 | JD3: 0 | JE3: Not Aligned | JF3: 0 | JG3: 0 | JH3: 0 | JI3: 0 | JJ3: 99.464999 | JK3: 0 | JL3: 0 | JM3: Not Aligned | JN3: 0 | JO3: 0 | JP3: 0 | JQ3: 0 | JR3: 99.464999 | JS3: 0 | JT3: 0 | JU3: Aligned | JV3: 18.927638 | JW3: 18.927638 | JX3: 0 | JY3: 0 | JZ3: 80.537361 | KA3: 0 | KB3: 0 | KC3: Not Aligned | KD3: 0 | KE3: 0 | KF3: 0 | KG3: 0 | KH3: 99.464999 | KI3: 0 | KJ3: 0 | KK3: 99.464999 | KL3: -0.87668178 | KM3: -13.559527 | KN3: 20.922042 | KO3: Equity | KP3: Exchange Traded Funds | KQ3: USA | KR3: 56.037189 | KS3: 99.626625 | KT3: 99.519876 | KU3: 5.558891 | KV3: 6.6866488 | KW3: 4.001908 | KX3: 39.480779 | KZ3: 6.4654303 | LA3: 46.637606 | LB3: 6.1489286 | LC3: 67.857143 | LD3: A | LE3: 18.858714 | LF3: 18.886638 | LG3: 20.594141 | LH3: 3.2720065 | LI3: 13.018426 | LJ3: 24.160048 | LK3: 0.72990146 | LL3: 0.48012436 | LM3: 4.6302256 | LN3: 0.48012436 | LO3: 11.364423 | LP3: 67.233411 | LQ3: 5.6982897 | LR3: 26.040201 | LS3: United States of America | LT3: 6.693641 | LU3: 44.456618 | LV3: 64 | LW3: 1 | LX3: 62 | LY3: T | LZ3: The Fund seeks investment results that correspond generally to the price and yield performance, before fees and expenses, of the Dow Jones US Real Estate Index. Uses a representative sampling strategy. Component firms include hotel and resort firms and REIT's. | MA3: 46203 | MB3: Equity Sector Real Estate US | MC3: 168 | MD3: BlackRock Fund Advisors | ME3: iShares US Real Estate ETF | MF3: 4.8140946 | MG3: 29.023056 | MH3: 4672414947 | MI3: 6.4654303 | MJ3: 46.637606 | MK3: 67.857143 | ML3: 5.8850655 | MM3: T | MN3: 0 | MO3: 0 | MP3: 0 | MQ3: 0 | MR3: 5.01351 | MS3: 1.1160022 | MT3: 0 | MU3: 0 | MV3: 0 | MW3: 0 | MX3: 0 | MY3: 0 | MZ3: 0 | NA3: 0 | NB3: 0 | NC3: 3.0762061 | ND3: 0 | NE3: 0 | NF3: 0 | NG3: 0 | NH3: 0 | NI3: 0 | NJ3: 0 | NK3: 0 | NL3: 0 | NM3: 0 | NN3: 0 | NO3: 0 | NP3: 0 | NQ3: 0 | NR3: 0 | NS3: 0 | NT3: 0 | NU3: 0 | NV3: 0 | NW3: 0 | NX3: 1.2757026 | NY3: 3.0762061 | NZ3: 3.0762061 | OA3: 0 | OB3: 3.0762061 | OC3: 0 | OD3: 0 | OE3: 0 | OF3: 0 | OG3: 0 | OH3: 0 | OI3: 0 | OJ3: 1.2757026 | OK3: 0 | OL3: 0 | OM3: 73.345847 | ON3: 0 | OO3: 0 | OP3: 0 | OQ3: 0 | OR3: 0 | OS3: 1.2757026 | OT3: 0 | OU3: 0 | OV3: 0 | OW3: 0 | OX3: 0 | OY3: 0 | OZ3: 0 | PA3: 0 | PB3: 0 | PC3: 0 | PD3: 0 | PE3: 0 | PF3: 0 | PG3: 0 | PH3: 0 | PI3: 0 | PJ3: 0 | PK3: 0 | PL3: 0 | PM3: 0 | PN3: 0 | PO3: 0 | PP3: 0 | PQ3: 0 | PR3: 0 | PS3: 0 | PT3: 0.08521012 | PU3: 0 | PV3: 0 | PW3: 2.1881978 | PX3: 0 | PY3: 0 | PZ3: 0.00021442 | QA3: 3.0762061 | QB3: 0 | QC3: 0 | QD3: 0 | QE3: 0 | QF3: 1.2757026 | QG3: 2.1442043 | QH3: 0 | QI3: 0 | QJ3: 0 | QK3: 0
A4: 40056868 | B4: iShares MSCI Eurozone ETF | C4: US4642866085 | D4: Matched | E4: US4642866085 | F4: 35557352 | G4: EZU | H4: 42.848172 | I4: 99.647304 | J4: 298.24568 | K4: 99.647304 | L4: 397.03327 | M4: 99.647304 | N4: 98.787583 | O4: 99.647304 | P4: 21.899381 | Q4: 2.1173363 | R4: 6.4311664 | S4: 3.0373854 | T4: 21.444886 | U4: 1.3309691 | V4: 5.2234478 | W4: 84.282305 | X4: 99.766802 | Y4: 683.14659 | Z4: 99.675603 | AA4: 942.54645 | AB4: 99.675603 | AC4: 259.39973 | AD4: 99.675603 | AE4: 202.59174 | AF4: 0.01331267 | AG4: 2137.7545 | AH4: 5333.3472 | AI4: 3353.2954 | AJ4: 41.664383 | AK4: 27.647824 | AL4: Misaligned | AM4: 98.858811 | AN4: 15.701743 | AO4: 13.873161 | AP4: 2.2 | AQ4: 86.078239 | AR4: 66.083939 | AS4: 97.828922 | AT4: 10.367572 | AU4: 67.499925 | AV4: 99.766802 | AW4: 0.61169388 | AX4: 10.854791 | AY4: 0.64809352 | AZ4: 0.18909811 | BA4: 21.290387 | BB4: 24.102959 | BC4: 1.9204808 | BD4: 7.1670283 | BE4: 0.79769202 | BF4: 1.9847802 | BG4: 0.22925807 | BH4: 1.4127848 | BI4: 0.02519383 | BJ4: 0.01058949 | BK4: 2.0260011 | BL4: 4.0458346 | BM4: 0.4905564 | BN4: 1.4608867 | BO4: 0.09167867 | BP4: 0.04703539 | BQ4: 0.3307702 | BR4: 0.08323256 | BS4: 2.2316095 | BT4: 0.05543273 | BU4: 6.2583726 | BV4: 0.01402411 | BW4: 7.8395216 | BX4: 2.597674 | BY4: 17.611824 | BZ4: 0.18079819 | CA4: 37.223128 | CB4: 1.5445846 | CC4: 0.14295428 | CD4: 0.06238681 | CE4: 0.11061227 | CG4: 74.758652 | CH4: 22.842372 | CI4: 0.15779842 | CJ4: 66.550434 | CK4: 15.97014 | CL4: 5.0442496 | CM4: 8.8802112 | CN4: 2.9122709 | CO4: 0.52459475 | CP4: 11.164188 | CQ4: 0.11819882 | CR4: 4.3640564 | CS4: 48.280417 | CT4: 47.00413 | CU4: 20.384596 | CV4: 11.00929 | CW4: 0.57619424 | CX4: 20.383196 | CY4: 6.2904371 | CZ4: 2.9945701 | DA4: 95.464745 | DB4: 36.213238 | DC4: 5.6416436 | DD4: 57.911921 | DE4: 41.349387 | DF4: 99.766802 | DG4: 6.4506214 | DH4: 99.647304 | DI4: 97.103729 | DJ4: 2.6630734 | DK4: 8.1159189 | DL4: 0.11499885 | DM4: 62.636874 | DN4: 2.9380706 | DO4: 26.542735 | DP4: 7.4146258 | DQ4: 5.8332665 | DR4: 99.647304 | DS4: 30.072199 | DT4: 92.219478 | DU4: 0 | DV4: 0.69779303 | DW4: 31.198188 | DX4: 24.470355 | DY4: 9.9726003 | DZ4: 1.5483845 | EA4: 97.803722 | EB4: 15.086249 | EC4: 3.8722673 | ED4: 6.503237 | EE4: 13.628964 | EF4: 38.873011 | EG4: 97.596224 | EH4: 5.46402 | EI4: 25.109349 | EJ4: 9.1444086 | EK4: 67.140929 | EL4: 23.481465 | EM4: 11.156488 | EN4: 9.9711003 | EO4: 4670.1918 | EP4: 48.738413 | EQ4: 6712.1554 | ER4: 92.826472 | ES4: 7.5725243 | ET4: 69.348406 | EU4: 5.8073419 | EV4: 79.9513 | EW4: 29.831802 | EX4: 42.570474 | EY4: 0.2298977 | EZ4: 3.7113629 | FA4: 99.344607 | FB4: 99.592104 | FC4: 83.376666 | FD4: 98.494215 | FE4: Aligned | FF4: 12.678273 | FG4: 12.678273 | FH4: 1.6879831 | FI4: 1.6879831 | FJ4: 85.309347 | FK4: 0 | FL4: 0 | FM4: Aligned | FN4: 1.3764862 | FO4: 1.3764862 | FP4: 0.42659573 | FQ4: 0.42659573 | FR4: 97.872521 | FS4: 0 | FT4: 0 | FU4: Not Aligned | FV4: 2.4747753 | FW4: 2.4747753 | FX4: 3.3828662 | FY4: 3.3828662 | FZ4: 93.817962 | GA4: 0 | GB4: 0 | GC4: Not Aligned | GD4: 0 | GE4: 0 | GF4: 0 | GG4: 0 | GH4: 99.675603 | GI4: 0 | GJ4: 0 | GK4: Aligned | GL4: 86.97283 | GM4: 86.97283 | GN4: 0 | GO4: 0 | GP4: 12.702773 | GQ4: 0 | GR4: 0 | GS4: Aligned | GT4: 26.199738 | GU4: 26.199738 | GV4: 0.4497955 | GW4: 0.4497955 | GX4: 73.02607 | GY4: 0 | GZ4: 0 | HA4: Not Aligned | HB4: 62.460275 | HC4: 62.562474 | HD4: 5.0415496 | HE4: 0.61649384 | HF4: 32.071579 | HG4: 0.10219898 | HH4: 4.4250558 | HI4: Aligned | HJ4: 36.645933 | HK4: 36.645933 | HL4: 0 | HM4: 0 | HN4: 63.02967 | HO4: 0 | HP4: 0 | HQ4: Aligned | HR4: 38.496415 | HS4: 44.636654 | HT4: 0.34839651 | HU4: 0.34839651 | HV4: 54.690553 | HW4: 6.1402386 | HX4: 0 | HY4: Aligned | HZ4: 79.285407 | IA4: 79.285407 | IB4: 0 | IC4: 0 | ID4: 20.390196 | IE4: 0 | IF4: 0 | IG4: Not Aligned | IH4: 5.9913401 | II4: 5.9913401 | IJ4: 6.602234 | IK4: 6.602234 | IL4: 87.082029 | IM4: 0 | IN4: 0 | IO4: Not Aligned | IP4: 38.066919 | IQ4: 39.02681 | IR4: 5.1592484 | IS4: 0.73419266 | IT4: 55.489545 | IU4: 0.95989042 | IV4: 4.4250558 | IW4: Not Aligned | IX4: 58.288717 | IY4: 58.547115 | IZ4: 4.4250558 | JA4: 0 | JB4: 36.703433 | JC4: 0.25839742 | JD4: 4.4250558 | JE4: Not Aligned | JF4: 0 | JG4: 0 | JH4: 3.5429646 | JI4: 3.4751652 | JJ4: 96.132639 | JK4: 0 | JL4: 0.06779932 | JM4: Not Aligned | JN4: 0 | JO4: 0 | JP4: 4.5876541 | JQ4: 4.5876541 | JR4: 95.087949 | JS4: 0 | JT4: 0 | JU4: Aligned | JV4: 12.135879 | JW4: 12.135879 | JX4: 0 | JY4: 0 | JZ4: 87.539725 | KA4: 0 | KB4: 0 | KC4: Aligned | KD4: 1.8931811 | KE4: 1.8931811 | KF4: 0 | KG4: 0 | KH4: 97.782422 | KI4: 0 | KJ4: 0 | KK4: 99.675603 | KL4: 0.54264146 | KM4: 6.7790323 | KN4: 7.9404206 | KO4: Equity | KP4: Exchange Traded Funds | KQ4: USA | KR4: 24.037972 | KS4: 99.866292 | KT4: 99.688916 | KU4: 6.3939449 | KV4: 6.8008484 | KW4: 0.82619173 | KX4: 74.824752 | KZ4: 8.004704 | LA4: 95.14799 | LB4: 7.9772285 | LC4: 46.996198 | LD4: AA | LE4: 14.075572 | LF4: 35.383846 | LG4: 39.440906 | LH4: 0.7595924 | LI4: 2.2087779 | LJ4: 7.7536225 | LK4: 0.06659933 | LL4: 0.3110841 | LM4: 5.2600118 | LN4: 0.3110841 | LO4: 15.545645 | LP4: 76.202851 | LQ4: 6.5050272 | LR4: 22.079665 | LS4: Europe | LT4: 6.7027449 | LU4: 39.521177 | LV4: 225 | LW4: 1 | LX4: 223 | LY4: T | LZ4: The Fund seeks to track the investment results of an index composed of large- and mid-capitalization equities from developed market countries that use the euro as their official currency. The Fund invests at least 95% of its assets in the securities of its Underlying Index and in depositary receipts in its index. | MA4: 46203 | MB4: Equity Europe | MC4: 1315 | MD4: BlackRock Fund Advisors | ME4: iShares MSCI Eurozone ETF | MF4: 5.4517977 | MG4: 38.088073 | MH4: 9595189883 | MI4: 8.004704 | MJ4: 95.14799 | MK4: 46.996198 | ML4: 6.1810048 | MM4: T | MN4: 3.8285617 | MO4: 0 | MP4: 0 | MQ4: 0 | MR4: 9.8743013 | MS4: 4.2125579 | MT4: 1.6227838 | MU4: 3.402566 | MV4: 17.317527 | MW4: 16.99033 | MX4: 15.448646 | MY4: 0 | MZ4: 0.4306957 | NA4: 0.4306957 | NB4: 0 | NC4: 12.750673 | ND4: 0 | NE4: 0.02829972 | NF4: 0.02829972 | NG4: 0.02829972 | NH4: 0.02829972 | NI4: 0.02829972 | NJ4: 0.02829972 | NK4: 0 | NL4: 0 | NM4: 0 | NN4: 0 | NO4: 0 | NP4: 0 | NQ4: 0.49199508 | NR4: 9.5168048 | NS4: 7.902121 | NT4: 0.78539215 | NU4: 1.3739863 | NV4: 3.2148679 | NW4: 0 | NX4: 6.1719383 | NY4: 2.500675 | NZ4: 0.76409235 | OA4: 0 | OB4: 0 | OC4: 1.3555865 | OD4: 1.3185868 | OE4: 0.70209298 | OF4: 0.70209298 | OG4: 0 | OH4: 11.633884 | OI4: 1.4932851 | OJ4: 4.5107549 | OK4: 0 | OL4: 7.8171218 | OM4: 63.847362 | ON4: 0 | OO4: 3.596264 | OP4: 0 | OQ4: 0 | OR4: 0 | OS4: 6.1719383 | OT4: 11.784682 | OU4: 5.0355496 | OV4: 4.1311587 | OW4: 4.298957 | OX4: 5.0553494 | OY4: 4.3708563 | OZ4: 3.4685653 | PA4: 3.4685653 | PB4: 0.03699963 | PC4: 0 | PD4: 0 | PE4: 5.0496495 | PF4: 0 | PG4: 0 | PH4: 0 | PI4: 0 | PJ4: 0 | PK4: 0 | PL4: 0 | PM4: 17.122929 | PN4: 5.2160478 | PO4: 2.6844732 | PP4: 2.1073789 | PQ4: 6.5224348 | PR4: 3.596264 | PS4: 0.01894125 | PT4: 1.7297724 | PU4: 1.3742556 | PV4: 0.00424213 | PW4: 0.02325527 | PX4: 0.15267826 | PY4: 0.20001918 | PZ4: 0.04384657 | QA4: 19.494305 | QB4: 0.99229007 | QC4: 0 | QD4: 0 | QE4: 0 | QF4: 1.4805852 | QG4: 4.7569524 | QH4: 0 | QI4: 0 | QJ4: 0 | QK4: 10.218898
A5: 40068873 | B5: iShares Latin America 40 ETF | C5: US4642873909 | D5: Matched | E5: US4642873909 | F5: 35560680 | G5: ILF | H5: 111.51934 | I5: 98.928005 | J5: 635.90783 | K5: 98.928005 | L5: 747.51033 | M5: 98.928005 | N5: 111.6025 | O5: 98.928005 | P5: 33.393733 | Q5: 9.6972177 | R5: 1.6430035 | S5: 0.16943041 | T5: 33.393733 | U5: 9.3261997 | V5: 0 | W5: 222.02592 | X5: 98.928005 | Y5: 1639.3641 | Z5: 98.928005 | AA5: 1901.9427 | AB5: 98.928005 | AC5: 262.57919 | AD5: 98.928005 | AE5: 202.59174 | AF5: 0.08614577 | AG5: 8101.2884 | AH5: 20244.44 | AI5: 3403.8604 | AJ5: 16.265519 | AK5: 25.678972 | AL5: Strongly Misaligned | AM5: 98.179209 | AN5: 26.476968 | AO5: 29.757751 | AP5: 4 | AQ5: 43.99278 | AR5: 50.145949 | AS5: 85.829671 | AT5: 8.355491 | AU5: 24.494778 | AV5: 98.928005 | AW5: 0 | AX5: 1.6849916 | AY5: 0 | AZ5: 0 | BA5: 7.2398638 | BB5: 14.232229 | BC5: 0.74879626 | BD5: 0 | BE5: 8.9578552 | BF5: 3.7128814 | BG5: 0 | BH5: 0.00690847 | BI5: 0 | BJ5: 0 | BK5: 0.16030581 | BL5: 1.2972207 | BM5: 0.15552498 | BN5: 0 | BO5: 0.59564748 | BP5: 0.17360305 | BQ5: 0.88784436 | BR5: 0.01314095 | BS5: 1.4966328 | BT5: 0.08462238 | BU5: 2.7938535 | BV5: 0.71625601 | BW5: 23.041685 | BX5: 6.9370653 | BY5: 31.99954 | BZ5: 0.36349818 | CA5: 43.606982 | CB5: 2.1671891 | CC5: 0.17551752 | CD5: 0.08462238 | CE5: 0.72976524 | CG5: 84.756276 | CH5: 19.108604 | CI5: 0 | CJ5: 53.738531 | CK5: 13.348133 | CL5: 14.963425 | CM5: 0.82359588 | CN5: 9.1533542 | CO5: 0.60929695 | CP5: 25.278574 | CQ5: 1.6437918 | CR5: 38.774106 | CS5: 23.088085 | CT5: 35.422023 | CU5: 69.296854 | CV5: 36.641317 | CW5: 4.2184789 | CX5: 17.089015 | CY5: 35.752621 | CZ5: 96.611317 | DA5: 21.689592 | DB5: 59.502202 | DC5: 39.425803 | DD5: 0 | DE5: 41.231694 | DF5: 98.928005 | DG5: 4.8276059 | DH5: 98.928005 | DI5: 58.510107 | DJ5: 40.417898 | DK5: 2.3166884 | DL5: 10.495548 | DM5: 56.586817 | DN5: 10.508547 | DO5: 21.337093 | DP5: 0 | DQ5: 5.0220344 | DR5: 98.928005 | DS5: 24.466978 | DT5: 61.739591 | DU5: 7.9416603 | DV5: 0 | DW5: 68.985155 | DX5: 18.467508 | DY5: 33.794931 | DZ5: 38.149009 | EA5: 65.853171 | EB5: 1.8824906 | EC5: 5.2422048 | ED5: 5.5617253 | EE5: 10.723946 | EF5: 1.8824906 | EG5: 55.301424 | EH5: 4.4562765 | EI5: 37.222114 | EJ5: 16.938815 | EK5: 46.385968 | EL5: 35.603222 | EM5: 29.94415 | EN5: 30.517947 | EO5: 2250558.2 | EP5: 62.163289 | EQ5: 1579847.4 | ER5: 88.790956 | ES5: 13.797931 | ET5: 41.555292 | EU5: 31.384343 | EV5: 72.00354 | EW5: 24.758376 | EX5: 26.380868 | EY5: 0 | EZ5: 29.738351 | FA5: 98.928005 | FB5: 97.243014 | FC5: 62.324088 | FD5: 88.753656 | FE5: Aligned | FF5: 17.178614 | FG5: 17.178614 | FH5: 1.8824906 | FI5: 1.8824906 | FJ5: 79.866901 | FK5: 0 | FL5: 0 | FM5: Not Aligned | FN5: 1.0802946 | FO5: 1.0802946 | FP5: 8.404558 | FQ5: 8.404558 | FR5: 89.443153 | FS5: 0 | FT5: 0 | FU5: Not Aligned | FV5: 0 | FW5: 0 | FX5: 8.404558 | FY5: 0 | FZ5: 90.523447 | GA5: 0 | GB5: 8.404558 | GC5: Not Aligned | GD5: 0 | GE5: 0 | GF5: 0 | GG5: 0 | GH5: 98.928005 | GI5: 0 | GJ5: 0 | GK5: Aligned | GL5: 46.848066 | GM5: 46.848066 | GN5: 0 | GO5: 0 | GP5: 52.07994 | GQ5: 0 | GR5: 0 | GS5: Not Aligned | GT5: 9.0888546 | GU5: 11.256044 | GV5: 8.404558 | GW5: 0 | GX5: 79.267404 | GY5: 2.1671891 | GZ5: 8.404558 | HA5: Not Aligned | HB5: 39.436003 | HC5: 41.318493 | HD5: 10.859046 | HE5: 0 | HF5: 46.750466 | HG5: 1.8824906 | HH5: 10.859046 | HI5: Not Aligned | HJ5: 24.838476 | HK5: 24.838476 | HL5: 8.404558 | HM5: 0 | HN5: 65.684972 | HO5: 0 | HP5: 8.404558 | HQ5: Aligned | HR5: 36.628017 | HS5: 36.628017 | HT5: 8.404558 | HU5: 8.404558 | HV5: 53.895431 | HW5: 0 | HX5: 0 | HY5: Aligned | HZ5: 68.06826 | IA5: 68.06826 | IB5: 0 | IC5: 0 | ID5: 30.859746 | IE5: 0 | IF5: 0 | IG5: Not Aligned | IH5: 1.5650922 | II5: 1.5650922 | IJ5: 10.287049 | IK5: 1.8824906 | IL5: 87.075865 | IM5: 0 | IN5: 8.404558 | IO5: Not Aligned | IP5: 12.425838 | IQ5: 14.593027 | IR5: 19.263604 | IS5: 0 | IT5: 65.071375 | IU5: 2.1671891 | IV5: 19.263604 | IW5: Not Aligned | IX5: 39.671602 | IY5: 41.554092 | IZ5: 10.859046 | JA5: 0 | JB5: 46.514867 | JC5: 1.8824906 | JD5: 10.859046 | JE5: Not Aligned | JF5: 2.1671891 | JG5: 2.1671891 | JH5: 8.9633552 | JI5: 0.55879721 | JJ5: 87.797461 | JK5: 0 | JL5: 8.404558 | JM5: Not Aligned | JN5: 0 | JO5: 0 | JP5: 10.845846 | JQ5: 2.4412878 | JR5: 88.08216 | JS5: 0 | JT5: 8.404558 | JU5: Aligned | JV5: 15.98572 | JW5: 15.98572 | JX5: 0 | JY5: 0 | JZ5: 82.942285 | KA5: 0 | KB5: 0 | KC5: Aligned | KD5: 13.043035 | KE5: 13.043035 | KF5: 0 | KG5: 0 | KH5: 85.884971 | KI5: 0 | KJ5: 0 | KK5: 98.928005 | KL5: 0.09522928 | KM5: 1.6211919 | KN5: 13.752431 | KO5: Equity | KP5: Exchange Traded Funds | KQ5: USA | KR5: 74.818172 | KS5: 99.406974 | KT5: 99.014151 | KU5: 5.4686989 | KV5: 4.9980013 | KW5: 2.7704861 | KX5: 21.425493 | KZ5: 5.8740288 | LA5: 30.522546 | LB5: 5.8035852 | LC5: 70 | LD5: A | LE5: 33.103681 | LF5: 16.265519 | LG5: 5.1599742 | LH5: 2.1271894 | LI5: 15.519722 | LJ5: 26.194769 | LK5: 0.64329678 | LL5: 0.98584887 | LM5: 5.0878726 | LN5: 0.98584887 | LO5: 18.144109 | LP5: 67.117611 | LQ5: 5.6611884 | LR5: 24.280716 | LS5: Latin America | LT5: 4.8199497 | LU5: 34.758041 | LV5: 44 | LW5: 1 | LX5: 42 | LY5: T | LZ5: The Fund seeks to track the investment results of the S&P Latin America 40 composed of 40 of the largest Latin American equities. The Fund invests, under normal circumstances, at least 90% of its assets in securities of the Underlying Index and in depositary receipts representing securities of the Underlying Index. | MA5: 46203 | MB5: Equity Emerging Markets Latin America | MC5: 70 | MD5: BlackRock Fund Advisors | ME5: iShares Latin America 40 ETF | MF5: 5.0512137 | MG5: 39.975394 | MH5: 3739343853 | MI5: 5.8740288 | MJ5: 30.522546 | MK5: 70 | ML5: 5.1196114 | MM5: T | MN5: 9.3024535 | MO5: 0 | MP5: 0 | MQ5: 0 | MR5: 13.96933 | MS5: 4.390878 | MT5: 2.1295893 | MU5: 2.1295893 | MV5: 0 | MW5: 0 | MX5: 0 | MY5: 0 | MZ5: 0 | NA5: 0 | NB5: 0 | NC5: 13.702231 | ND5: 0 | NE5: 0 | NF5: 0 | NG5: 0 | NH5: 0 | NI5: 0 | NJ5: 0 | NK5: 0 | NL5: 0 | NM5: 0 | NN5: 0 | NO5: 0 | NP5: 0 | NQ5: 8.404558 | NR5: 0 | NS5: 0 | NT5: 0 | NU5: 0 | NV5: 8.802856 | NW5: 0 | NX5: 11.138844 | NY5: 0 | NZ5: 0 | OA5: 0 | OB5: 0 | OC5: 0 | OD5: 0 | OE5: 0 | OF5: 0 | OG5: 8.404558 | OH5: 28.724256 | OI5: 0 | OJ5: 0.55879721 | OK5: 8.404558 | OL5: 18.228709 | OM5: 64.01488 | ON5: 0 | OO5: 16.346218 | OP5: 0 | OQ5: 0 | OR5: 0 | OS5: 11.138844 | OT5: 1.8824906 | OU5: 1.8824906 | OV5: 0 | OW5: 1.8824906 | OX5: 0 | OY5: 0 | OZ5: 0 | PA5: 0 | PB5: 0 | PC5: 0 | PD5: 0 | PE5: 0 | PF5: 8.404558 | PG5: 0 | PH5: 0 | PI5: 0 | PJ5: 8.404558 | PK5: 0 | PL5: 0 | PM5: 28.724256 | PN5: 0 | PO5: 10.845846 | PP5: 9.9367503 | PQ5: 10.287049 | PR5: 16.346218 | PS5: 0.02347452 | PT5: 1.8208565 | PU5: 0 | PV5: 0 | PW5: 0 | PX5: 0 | PY5: 0 | PZ5: 0.06327383 | QA5: 4.0120799 | QB5: 0 | QC5: 0 | QD5: 0 | QE5: 0 | QF5: 0 | QG5: 7.1202644 | QH5: 0 | QI5: 0 | QJ5: 0 | QK5: 0
A6: 40073950 | B6: iShares Global Energy ETF | C6: US4642873412 | D6: Matched | E6: US4642873412 | F6: 35561608 | G6: IXC | H6: 208.84839 | I6: 99.443601 | J6: 2033.1823 | K6: 99.443601 | L6: 2233.8709 | M6: 99.443601 | N6: 200.68855 | O6: 99.443601 | P6: 98.065702 | Q6: 69.573512 | R6: 3.7108798 | S6: 0.05333754 | T6: 98.065702 | U6: 46.209887 | V6: 0 | W6: 445.76752 | X6: 99.443601 | Y6: 3575.0025 | Z6: 99.443601 | AA6: 3900.8496 | AB6: 99.443601 | AC6: 325.84809 | AD6: 99.443601 | AE6: 202.59174 | AF6: 0.04864585 | AG6: 22332.725 | AH6: 55540.444 | AI6: 6533.8424 | AJ6: 0.28469972 | AK6: 10.824289 | AL6: Strongly Misaligned | AM6: 99.443601 | AN6: 18.433882 | AO6: 69.90073 | AP6: 5 | AQ6: 89.95861 | AR6: 47.909252 | AS6: 98.963601 | AT6: 16.442668 | AU6: 0 | AV6: 99.443601 | AW6: 0 | AX6: 14.761585 | AY6: 0 | AZ6: 0 | BA6: 6.8135932 | BB6: 14.761585 | BC6: 0 | BD6: 0 | BE6: 0 | BF6: 2.8687971 | BG6: 0 | BH6: 0.49549496 | BI6: 0 | BJ6: 0 | BK6: 0.15623318 | BL6: 0.66822816 | BM6: 0 | BN6: 0 | BO6: 0 | BP6: 0.00706097 | BQ6: 0 | BR6: 0 | BS6: 0 | BT6: 0 | BU6: 0.66822816 | BV6: 0.00943905 | BW6: 0 | BX6: 0 | BY6: 0 | BZ6: 0 | CA6: 14.761585 | CB6: 4.7441952 | CC6: 0.09661339 | CD6: 0 | CE6: 0.01656256 | CG6: 83.516816 | CH6: 57.378143 | CI6: 0 | CJ6: 39.161861 | CK6: 14.058986 | CL6: 2.4403976 | CM6: 1.8677981 | CN6: 0 | CO6: 50.582149 | CP6: 2.6464974 | CQ6: 0 | CR6: 1.5523985 | CS6: 10.836189 | CT6: 87.055013 | CU6: 8.967491 | CV6: 2.1565978 | CW6: 0.57469943 | CX6: 72.104628 | CY6: 10.893989 | CZ6: 4.8379952 | DA6: 83.502416 | DB6: 58.735441 | DC6: 1.5643985 | DD6: 39.143761 | DE6: 73.950626 | DF6: 99.443601 | DG6: 5.2380321 | DH6: 99.443601 | DI6: 97.891202 | DJ6: 1.5523985 | DK6: 39.76006 | DL6: 57.104343 | DM6: 0 | DN6: 0 | DO6: 42.339258 | DP6: 0 | DQ6: 2.1348271 | DR6: 99.443601 | DS6: 14.767785 | DT6: 19.59158 | DU6: 0 | DV6: 0 | DW6: 14.619285 | DX6: 50.700249 | DY6: 7.6679923 | DZ6: 0.28469972 | EA6: 98.659201 | EB6: 1.039399 | EC6: 10.610334 | EE6: 0 | EF6: 5.5925944 | EG6: 90.568609 | EH6: 3.739635 | EI6: 83.762016 | EJ6: 20.00388 | EK6: 3.4867965 | EL6: 75.952924 | EM6: 10.31309 | EN6: 0 | EO6: 997.89784 | EP6: 87.850312 | EQ6: 3327.1812 | ER6: 69.56673 | ES6: 49.96365 | ET6: 22.593077 | EU6: 86.478714 | EV6: 44.154756 | EW6: 9.2290908 | EX6: 29.74407 | EY6: 0 | EZ6: 87.880412 | FA6: 94.520405 | FB6: 99.443601 | FC6: 29.97937 | FD6: 88.102612 | FE6: Not Aligned | FF6: 0 | FG6: 0 | FH6: 5.1062949 | FI6: 5.1062949 | FJ6: 94.337306 | FK6: 0 | FL6: 0 | FM6: Not Aligned | FN6: 0 | FO6: 0 | FP6: 0 | FQ6: 0 | FR6: 99.443601 | FS6: 0 | FT6: 0 | FU6: Not Aligned | FV6: 0 | FW6: 0 | FX6: 28.784671 | FY6: 28.784671 | FZ6: 70.658929 | GA6: 0 | GB6: 0 | GC6: Not Aligned | GD6: 0 | GE6: 0 | GF6: 0.7049993 | GG6: 0.7049993 | GH6: 98.738601 | GI6: 0 | GJ6: 0 | GK6: Aligned | GL6: 61.870638 | GM6: 61.870638 | GN6: 0 | GO6: 0 | GP6: 37.572962 | GQ6: 0 | GR6: 0 | GS6: Aligned | GT6: 2.2714977 | GU6: 2.2714977 | GV6: 0 | GW6: 0 | GX6: 97.172103 | GY6: 0 | GZ6: 0 | HA6: Not Aligned | HB6: 0 | HC6: 0 | HD6: 98.065702 | HE6: 0 | HF6: 1.3778986 | HG6: 0 | HH6: 98.065702 | HI6: Aligned | HJ6: 10.504789 | HK6: 10.504789 | HL6: 0 | HM6: 0 | HN6: 88.938811 | HO6: 0 | HP6: 0 | HQ6: Aligned | HR6: 17.688882 | HS6: 17.688882 | HT6: 2.1402979 | HU6: 2.1402979 | HV6: 79.61442 | HW6: 0 | HX6: 0 | HY6: Aligned | HZ6: 24.094376 | IA6: 24.094376 | IB6: 0 | IC6: 0 | ID6: 75.349225 | IE6: 0 | IF6: 0 | IG6: Not Aligned | IH6: 0.62089938 | II6: 0.62089938 | IJ6: 47.676552 | IK6: 47.676552 | IL6: 51.146149 | IM6: 0 | IN6: 0 | IO6: Not Aligned | IP6: 0 | IQ6: 0 | IR6: 98.065702 | IS6: 0 | IT6: 1.3778986 | IU6: 0 | IV6: 98.065702 | IW6: Not Aligned | IX6: 0 | IY6: 0 | IZ6: 98.065702 | JA6: 0 | JB6: 1.3778986 | JC6: 0 | JD6: 98.065702 | JE6: Not Aligned | JF6: 0 | JG6: 0 | JH6: 28.891771 | JI6: 28.891771 | JJ6: 70.551829 | JK6: 0 | JL6: 0 | JM6: Not Aligned | JN6: 0 | JO6: 0 | JP6: 53.178547 | JQ6: 53.178547 | JR6: 46.265054 | JS6: 0 | JT6: 0 | JU6: Not Aligned | JV6: 2.7147973 | JW6: 2.7147973 | JX6: 3.003597 | JY6: 3.003597 | JZ6: 93.725206 | KA6: 0 | KB6: 0 | KC6: Aligned | KD6: 18.673181 | KE6: 18.673181 | KF6: 0 | KG6: 0 | KH6: 80.770419 | KI6: 0 | KJ6: 0 | KK6: 99.443601 | KL6: 1.3398147 | KM6: 20.627079 | KN6: 4.5196955 | KO6: Equity | KP6: Exchange Traded Funds | KQ6: USA | KR6: 65.90468 | KS6: 99.810342 | KT6: 99.492246 | KU6: 4.5870463 | KV6: 6.3277361 | KW6: 0.28469972 | KX6: 33.302867 | KZ6: 6.4954164 | LA6: 47.881497 | LB6: 6.3905097 | LC6: 41.706161 | LD6: A | LE6: 34.327712 | LF6: 20.747579 | LG6: 12.555287 | LH6: 0.28469972 | LI6: 27.207073 | LJ6: 4.3698956 | LK6: 0 | LL6: 0.50775359 | LM6: 6.0479823 | LN6: 0.50775359 | LO6: 25.431475 | LP6: 69.541076 | LQ6: 4.9902475 | LR6: 40.924215 | LS6: Global | LT6: 5.911074 | LU6: 33.088325 | LV6: 53 | LW6: 1 | LX6: 51 | LY6: T | LZ6: The Fund seeks to track the investment results of an index composed of global equities in the energy sector. The Fund invests at least 80% of its assets in the component securities of its Index and in investments that have economic characteristics that are substantially identical to the component securities of its Index. | MA6: 46203 | MB6: Equity Theme - Natural Resources | MC6: 211 | MD6: BlackRock Fund Advisors | ME6: iShares Global Energy ETF | MF6: 6.7210025 | MG6: 25.479707 | MH6: 1999341487 | MI6: 6.4954164 | MJ6: 47.881497 | MK6: 41.706161 | ML6: 5.7397304 | MM6: T | MN6: 0 | MO6: 0 | MP6: 0 | MQ6: 0 | MR6: 20.23668 | MS6: 0 | MT6: 0 | MU6: 0 | MV6: 25.127075 | MW6: 24.606175 | MX6: 24.606175 | MY6: 0 | MZ6: 0 | NA6: 0 | NB6: 0 | NC6: 0.22189978 | ND6: 0 | NE6: 0 | NF6: 0 | NG6: 0 | NH6: 0 | NI6: 0 | NJ6: 0 | NK6: 0 | NL6: 0 | NM6: 0 | NN6: 0 | NO6: 0 | NP6: 0 | NQ6: 0 | NR6: 0 | NS6: 0 | NT6: 0 | NU6: 0 | NV6: 0 | NW6: 0 | NX6: 75.428725 | NY6: 0 | NZ6: 0 | OA6: 0 | OB6: 0 | OC6: 0 | OD6: 0 | OE6: 0 | OF6: 0 | OG6: 0 | OH6: 57.165643 | OI6: 3.7085963 | OJ6: 70.584629 | OK6: 0 | OL6: 55.128845 | OM6: 20.08218 | ON6: 0 | OO6: 5.7310943 | OP6: 0 | OQ6: 0 | OR6: 0 | OS6: 63.665436 | OT6: 3.5181965 | OU6: 3.5181965 | OV6: 2.1402979 | OW6: 3.5181965 | OX6: 0 | OY6: 0 | OZ6: 0 | PA6: 0 | PB6: 0 | PC6: 0 | PD6: 0 | PE6: 17.580182 | PF6: 0 | PG6: 0 | PH6: 0 | PI6: 0 | PJ6: 0 | PK6: 0 | PL6: 0 | PM6: 57.165643 | PN6: 0 | PO6: 24.434576 | PP6: 4.9332951 | PQ6: 54.423846 | PR6: 5.7310943 | PS6: 0 | PT6: 0.1059996 | PU6: 0 | PV6: 0 | PW6: 0 | PX6: 0 | PY6: 1.4209186 | PZ6: 0.10869933 | QA6: 3.5181965 | QB6: 0 | QC6: 0 | QD6: 0 | QE6: 0 | QF6: 0 | QG6: 20.509379 | QH6: 0 | QI6: 0 | QJ6: 0 | QK6: 0
A7: 40073951 | B7: iShares Global Financials ETF | C7: US4642873339 | D7: Matched | E7: US4642873339 | F7: 35561610 | G7: IXG | H7: 3.535983 | I7: 99.1368 | J7: 29.413816 | K7: 99.1368 | L7: 54.443367 | M7: 99.1368 | N7: 25.029551 | O7: 99.1368 | P7: 9.5391 | Q7: 0.16487489 | R7: 0.26574463 | S7: 1.6117956 | T7: 9.2497 | U7: 0.03074945 | V7: 6.959 | W7: 12.756098 | X7: 99.1368 | Y7: 172.38631 | Z7: 99.1368 | AA7: 287.48871 | AB7: 99.1368 | AC7: 115.10252 | AD7: 99.1368 | AE7: 202.59174 | AF7: 0.1053027 | AG7: 2877.8546 | AH7: 7150.7432 | AI7: 3888.434 | AJ7: 32.8373 | AK7: 26.6986 | AL7: Misaligned | AM7: 99.1368 | AN7: 31.6315 | AO7: 7.9694 | AP7: 2.3 | AQ7: 88.4346 | AR7: 66.0401 | AS7: 96.7112 | AT7: 2.7423817 | AU7: 17.3295 | AV7: 99.1368 | AW7: 0.4336 | AX7: 0.8563 | AY7: 0.0987 | AZ7: 0 | BA7: 0.5158 | BB7: 1.3599 | BC7: 0.793 | BD7: 0 | BE7: 0 | BF7: 0.2894 | BG7: 0.00047636 | BH7: 0.02535667 | BI7: 0.00018753 | BJ7: 0 | BK7: 0.00284084 | BL7: 0.03032985 | BM7: 0.00025124 | BN7: 0 | BO7: 0 | BP7: 0.0018811 | BQ7: 0.65168381 | BR7: 5.716e-05 | BS7: 0.65240486 | BT7: 0 | BU7: 0.68273471 | BV7: 0 | BW7: 24.7225 | BX7: 0.2858 | BY7: 24.9654 | BZ7: 0 | CA7: 26.0359 | CB7: 0 | CC7: 0.03065027 | CD7: 0 | CE7: 0 | CG7: 73.1445 | CH7: 5.8612 | CI7: 7.1078 | CJ7: 91.4962 | CK7: 12.2962 | CL7: 0.2258 | CM7: 6.5883 | CN7: 0.9605 | CO7: 22.1222 | CP7: 10.7641 | CQ7: 0.1201 | CR7: 4.353 | CS7: 27.4973 | CT7: 67.1664 | CU7: 15.5787 | CV7: 12.4383 | CW7: 3.5497 | CX7: 62.0909 | CY7: 25.0909 | CZ7: 9.177 | DA7: 81.0613 | DB7: 47.81 | DC7: 10.2643 | DD7: 41.0625 | DE7: 51.87 | DF7: 99.1368 | DG7: 6.1663952 | DH7: 99.1368 | DI7: 96.6907 | DJ7: 2.4461 | DK7: 21.0425 | DL7: 0 | DM7: 90.1212 | DN7: 0.0749 | DO7: 8.4249 | DP7: 0.5158 | DQ7: 6.2740924 | DR7: 99.1368 | DS7: 32.112 | DT7: 25.4493 | DU7: 0 | DV7: 0.9708 | DW7: 31.1374 | DX7: 55.4654 | DY7: 14.1562 | DZ7: 0.7109 | EA7: 73.3146 | EB7: 0.9726 | EC7: 0.856954 | EE7: 0 | EF7: 20.095 | EG7: 92.2661 | EH7: 2.3093856 | EI7: 6.1211 | EJ7: 0 | EK7: 98.4821 | EL7: 0.6547 | EM7: 0 | EN7: 3.7816 | EO7: 559.28923 | EP7: 26.13 | EQ7: 238.26341 | ER7: 73.5768 | ES7: 30.4944 | ET7: 41.4891 | EU7: 0 | EV7: 71.6499 | EW7: 4.284 | EX7: 55.6618 | EY7: 0.9038 | EZ7: 0 | FA7: 83.0037 | FB7: 99.1368 | FC7: 47.8496 | FD7: 93.3038 | FE7: Aligned | FF7: 4.7629 | FG7: 4.7629 | FH7: 0.9721 | FI7: 0.9721 | FJ7: 93.4018 | FK7: 0 | FL7: 0 | FM7: Not Aligned | FN7: 0 | FO7: 0 | FP7: 0 | FQ7: 0 | FR7: 99.1368 | FS7: 0 | FT7: 0 | FU7: Not Aligned | FV7: 0 | FW7: 0 | FX7: 6.1211 | FY7: 6.1211 | FZ7: 93.0157 | GA7: 0 | GB7: 0 | GC7: Not Aligned | GD7: 0 | GE7: 0 | GF7: 0 | GG7: 0 | GH7: 99.1368 | GI7: 0 | GJ7: 0 | GK7: Aligned | GL7: 58.6024 | GM7: 58.6024 | GN7: 0 | GO7: 0 | GP7: 40.5344 | GQ7: 0 | GR7: 0 | GS7: Not Aligned | GT7: 0.9473 | GU7: 0.9473 | GV7: 6.1211 | GW7: 6.1211 | GX7: 92.0684 | GY7: 0 | GZ7: 0 | HA7: Aligned | HB7: 64.6851 | HC7: 64.6851 | HD7: 0.2019 | HE7: 0.2019 | HF7: 34.2498 | HG7: 0 | HH7: 0 | HI7: Aligned | HJ7: 37.7038 | HK7: 37.7038 | HL7: 6.1211 | HM7: 6.1211 | HN7: 55.3119 | HO7: 0 | HP7: 0 | HQ7: Aligned | HR7: 36.6059 | HS7: 36.6059 | HT7: 0.6251 | HU7: 0.6251 | HV7: 61.9058 | HW7: 0 | HX7: 0 | HY7: Aligned | HZ7: 34.0332 | IA7: 34.0332 | IB7: 0.4237 | IC7: 0.4237 | ID7: 64.6799 | IE7: 0 | IF7: 0 | IG7: Not Aligned | IH7: 0 | II7: 0 | IJ7: 6.6587 | IK7: 6.6587 | IL7: 92.4781 | IM7: 0 | IN7: 0 | IO7: Not Aligned | IP7: 5.2872 | IQ7: 5.2872 | IR7: 6.323 | IS7: 6.323 | IT7: 87.5266 | IU7: 0 | IV7: 0 | IW7: Aligned | IX7: 65.9751 | IY7: 65.9751 | IZ7: 0.2019 | JA7: 0.2019 | JB7: 32.9598 | JC7: 0 | JD7: 0 | JE7: Not Aligned | JF7: 0 | JG7: 0 | JH7: 6.1211 | JI7: 6.1211 | JJ7: 93.0157 | JK7: 0 | JL7: 0 | JM7: Not Aligned | JN7: 0 | JO7: 0 | JP7: 7.2676 | JQ7: 7.2676 | JR7: 91.8692 | JS7: 0 | JT7: 0 | JU7: Not Aligned | JV7: 9.37 | JW7: 9.37 | JX7: 11.1218 | JY7: 11.1218 | JZ7: 78.645 | KA7: 0 | KB7: 0 | KC7: Not Aligned | KD7: 0 | KE7: 0 | KF7: 10.0419 | KG7: 10.0419 | KH7: 89.0949 | KI7: 0 | KJ7: 0 | KK7: 99.1368 | KL7: 0.58427719 | KM7: 7.821 | KN7: 4.892 | KO7: Equity | KP7: Exchange Traded Funds | KQ7: USA | KR7: 37.440703 | KS7: 99.607817 | KT7: 99.242103 | KU7: 6.3395816 | KV7: 5.9114945 | KW7: 0.3111 | KX7: 61.4903 | KZ7: 7.47062 | LA7: 84.988616 | LB7: 7.2419191 | LC7: 54.123711 | LD7: AA | LE7: 24.495403 | LF7: 34.0525 | LG7: 27.4378 | LH7: 0.3111 | LI7: 7.5795 | LJ7: 5.3658 | LK7: 0 | LL7: 0.7578973 | LM7: 4.9516918 | LN7: 0.7578973 | LO7: 13.0241 | LP7: 81.326003 | LQ7: 7.7815252 | LR7: 11.879264 | LS7: Global | LT7: 5.946511 | LU7: 35.592623 | LV7: 224 | LW7: 1 | LX7: 222 | LY7: T | LZ7: The Fund seeks to track the investment results of the S&P Global 1200 Financials (Sector) Capped Idx composed of global equities in the financials sector. The Fund generally invests at least 90% of its assets in securities of the Underlying Index and in depositary receipts representing securities of the Underlying Index. | MA7: 46203 | MB7: Equity Sector Financials | MC7: 388 | MD7: BlackRock Fund Advisors | ME7: iShares Global Financials ETF | MF7: 4.8817047 | MG7: 51.770216 | MH7: 585764584 | MI7: 7.47062 | MJ7: 84.988616 | MK7: 54.123711 | ML7: 5.6106996 | MM7: T | MN7: 0.4112 | MO7: 0 | MP7: 0 | MQ7: 0 | MR7: 9.4798 | MS7: 0.3405 | MT7: 0 | MU7: 0 | MV7: 6.9652 | MW7: 6.4616 | MX7: 6.1211 | MY7: 0 | MZ7: 0 | NA7: 0 | NB7: 0 | NC7: 0.9676 | ND7: 0 | NE7: 0 | NF7: 0 | NG7: 0 | NH7: 0 | NI7: 0 | NJ7: 0 | NK7: 0 | NL7: 0 | NM7: 0 | NN7: 0 | NO7: 0 | NP7: 0 | NQ7: 0 | NR7: 7.0374 | NS7: 0 | NT7: 0 | NU7: 0 | NV7: 3.7938 | NW7: 0 | NX7: 8.4167 | NY7: 2.5944 | NZ7: 0.9036 | OA7: 0 | OB7: 0 | OC7: 0 | OD7: 0 | OE7: 0 | OF7: 0 | OG7: 0 | OH7: 26.0325 | OI7: 1.095 | OJ7: 7.9662 | OK7: 0 | OL7: 7.2676 | OM7: 98.6148 | ON7: 0 | OO7: 0 | OP7: 0 | OQ7: 0 | OR7: 0 | OS7: 1.6118 | OT7: 6.73 | OU7: 6.1211 | OV7: 0 | OW7: 0 | OX7: 0 | OY7: 0 | OZ7: 0 | PA7: 0 | PB7: 0 | PC7: 0 | PD7: 0 | PE7: 3.0932 | PF7: 0 | PG7: 0 | PH7: 0 | PI7: 0 | PJ7: 0 | PK7: 0 | PL7: 0 | PM7: 26.6896 | PN7: 0.0875 | PO7: 0 | PP7: 19.3345 | PQ7: 7.2676 | PR7: 0 | PS7: 0 | PT7: 0.06453709 | PU7: 0.06059889 | PV7: 0 | PW7: 0.00975443 | PX7: 0 | PY7: 0.00367266 | PZ7: 0.06188513 | QA7: 6.1211 | QB7: 0.0749 | QC7: 0.0749 | QD7: 0 | QE7: 0 | QF7: 6.6696 | QG7: 8.2087 | QH7: 0 | QI7: 0 | QJ7: 0 | QK7: 7.0374
A8: 40073952 | B8: iShares Global Healthcare ETF | C8: US4642873255 | D8: Matched | E8: US4642873255 | F8: 35561612 | G8: IXJ | H8: 2.7524687 | I8: 99.566601 | J8: 32.037658 | K8: 99.566601 | L8: 93.83209 | M8: 99.566601 | N8: 61.794432 | O8: 99.566601 | P8: 4.1226876 | Q8: 0 | R8: 0.05223829 | T8: 4.1226876 | U8: 0 | V8: 0 | W8: 11.407101 | X8: 99.566601 | Y8: 159.55641 | Z8: 99.566601 | AA8: 333.82494 | AB8: 99.566601 | AC8: 174.26841 | AD8: 99.566601 | AE8: 202.59174 | AF8: 0.08080536 | AG8: 112.42189 | AH8: 277.55903 | AI8: 1584.6465 | AJ8: 67.032899 | AK8: 12.400463 | AL8: 2.0°C Aligned | AM8: 99.566601 | AN8: 9.7641707 | AO8: 10.369069 | AP8: 1.7 | AQ8: 93.869118 | AR8: 84.609346 | AS8: 92.527422 | AT8: 2.5147764 | AU8: 70.661088 | AV8: 99.566601 | AW8: 0 | AX8: 0 | AY8: 0 | AZ8: 0 | BA8: 3.9714881 | BB8: 3.9714881 | BC8: 0 | BD8: 24.001928 | BE8: 0.44489867 | BF8: 0 | BG8: 0 | BH8: 0 | BI8: 0 | BJ8: 0 | BK8: 0.0504748 | BL8: 0.0504748 | BM8: 0 | BN8: 11.283618 | BO8: 0.00298082 | BP8: 0 | BQ8: 0 | BR8: 0.09407857 | BS8: 11.380678 | BT8: 0 | BU8: 11.431152 | BV8: 0 | BW8: 0 | BX8: 2.1728935 | BY8: 24.621926 | BZ8: 0 | CA8: 24.621926 | CB8: 0 | CC8: 0 | CD8: 0 | CE8: 0.00176349 | CG8: 71.973684 | CH8: 27.267718 | CI8: 0.1013997 | CJ8: 59.84952 | CK8: 20.951537 | CL8: 7.1303786 | CM8: 6.5399804 | CN8: 4.8013856 | CO8: 27.568017 | CP8: 2.5184925 | CQ8: 0.19319942 | CR8: 4.1672875 | CS8: 31.861104 | CT8: 63.34501 | CU8: 10.14717 | CV8: 7.1100787 | CW8: 0.93019721 | CX8: 69.681591 | CY8: 10.967767 | CZ8: 2.9141913 | DA8: 79.440062 | DB8: 67.007699 | DC8: 3.008691 | DD8: 29.550211 | DE8: 67.402498 | DF8: 99.566601 | DG8: 7.0077171 | DH8: 99.566601 | DI8: 97.902306 | DJ8: 1.664295 | DK8: 36.476291 | DL8: 0 | DM8: 91.853624 | DN8: 0 | DO8: 7.7129769 | DP8: 0 | DQ8: 6.2653087 | DR8: 99.566601 | DS8: 35.631793 | DT8: 25.270124 | DU8: 0 | DV8: 6.3623809 | DW8: 16.72035 | DX8: 45.474464 | DY8: 23.35603 | DZ8: 0.94829715 | EA8: 87.607837 | EB8: 0.37919886 | EC8: 5.9193702 | ED8: 2.9828038 | EE8: 2.9555911 | EF8: 25.877822 | EG8: 86.075442 | EH8: 5.3022657 | EI8: 63.086511 | EJ8: 0 | EK8: 15.680053 | EL8: 81.786655 | EM8: 0 | EN8: 0 | EO8: 436.34744 | EP8: 56.53493 | EQ8: 342.51162 | ER8: 90.894527 | ES8: 57.565127 | ET8: 28.003716 | EU8: 2.7571917 | EV8: 79.588461 | EW8: 11.303066 | EX8: 62.844711 | EY8: 3.7590887 | EZ8: 0 | FA8: 99.465202 | FB8: 99.566601 | FC8: 43.21217 | FD8: 97.486008 | FE8: Not Aligned | FF8: 38.641484 | FG8: 38.641484 | FH8: 6.3920808 | FI8: 6.2906811 | FJ8: 54.533036 | FK8: 0 | FL8: 0.1013997 | FM8: Not Aligned | FN8: 0 | FO8: 0 | FP8: 0 | FQ8: 0 | FR8: 99.566601 | FS8: 0 | FT8: 0 | FU8: Not Aligned | FV8: 66.012202 | FW8: 66.012202 | FX8: 5.6251831 | FY8: 5.5237834 | FZ8: 27.929216 | GA8: 0 | GB8: 0.1013997 | GC8: Not Aligned | GD8: 0 | GE8: 0 | GF8: 0 | GG8: 0 | GH8: 99.566601 | GI8: 0 | GJ8: 0 | GK8: Aligned | GL8: 49.508251 | GM8: 49.508251 | GN8: 0 | GO8: 0 | GP8: 50.05835 | GQ8: 0 | GR8: 0 | GS8: Aligned | GT8: 17.885246 | GU8: 17.885246 | GV8: 0 | GW8: 0 | GX8: 81.681355 | GY8: 0 | GZ8: 0 | HA8: Aligned | HB8: 48.745154 | HC8: 48.745154 | HD8: 0 | HE8: 0 | HF8: 50.821448 | HG8: 0 | HH8: 0 | HI8: Aligned | HJ8: 31.496606 | HK8: 31.496606 | HL8: 0 | HM8: 0 | HN8: 68.069996 | HO8: 0 | HP8: 0 | HQ8: Not Aligned | HR8: 2.4865925 | HS8: 2.4865925 | HT8: 12.617062 | HU8: 12.515662 | HV8: 84.462947 | HW8: 0 | HX8: 0.1013997 | HY8: Aligned | HZ8: 38.974083 | IA8: 38.974083 | IB8: 4.3954868 | IC8: 4.3954868 | ID8: 56.197031 | IE8: 0 | IF8: 0 | IG8: Not Aligned | IH8: 0 | II8: 0 | IJ8: 1.2439963 | IK8: 1.2439963 | IL8: 98.322605 | IM8: 0 | IN8: 0 | IO8: Aligned | IP8: 42.417273 | IQ8: 42.417273 | IR8: 0 | IS8: 0 | IT8: 57.149329 | IU8: 0 | IV8: 0 | IW8: Aligned | IX8: 59.676521 | IY8: 59.676521 | IZ8: 0 | JA8: 0 | JB8: 39.89008 | JC8: 0 | JD8: 0 | JE8: Not Aligned | JF8: 0 | JG8: 0 | JH8: 1.2439963 | JI8: 1.2439963 | JJ8: 98.322605 | JK8: 0 | JL8: 0 | JM8: Not Aligned | JN8: 0 | JO8: 0 | JP8: 1.2439963 | JQ8: 1.2439963 | JR8: 98.322605 | JS8: 0 | JT8: 0 | JU8: Aligned | JV8: 13.49566 | JW8: 13.49566 | JX8: 4.3954868 | JY8: 4.3954868 | JZ8: 81.675455 | KA8: 0 | KB8: 0 | KC8: Aligned | KD8: 0.70539788 | KE8: 0.70539788 | KF8: 0 | KG8: 0 | KH8: 98.861203 | KI8: 0 | KJ8: 0 | KK8: 99.566601 | KL8: -0.19050522 | KM8: -2.7621917 | KN8: 8.4920745 | KO8: Equity | KP8: Exchange Traded Funds | KQ8: USA | KR8: 58.140031 | KS8: 99.843194 | KT8: 99.647407 | KU8: 6.6899117 | KV8: 5.9569073 | KW8: 0.4346987 | KX8: 41.072677 | KZ8: 6.8968861 | LA8: 65.219625 | LB8: 6.2934039 | LC8: 73.446328 | LD8: A | LE8: 32.925607 | LF8: 27.894316 | LG8: 13.17836 | LH8: 0.333299 | LI8: 1.9042943 | LJ8: 23.31013 | LK8: 0.1013997 | LL8: 0.35259334 | LM8: 4.5464041 | LN8: 0.35259334 | LO8: 6.1645815 | LP8: 84.990751 | LQ8: 7.4088519 | LR8: 7.8826098 | LS8: Global | LT8: 6.0559642 | LU8: 36.36201 | LV8: 112 | LW8: 1 | LX8: 110 | LY8: T | LZ8: The Fund seeks investment results that correspond generally to the price and yield performance, before fees and expenses, of companies that Standard & Poor's deems part of the healthcare sector of the economy and important to global markets, as represented by the S&P Global Healthcare Sector Index ("the Index"). The Index is a subset of the Standard & Poor's Global 1200 Index. | MA8: 46203 | MB8: Equity Sector Healthcare | MC8: 531 | MD8: BlackRock Fund Advisors | ME8: iShares Global Healthcare ETF | MF8: 4.6421698 | MG8: 55.402787 | MH8: 3844812651 | MI8: 6.8968861 | MJ8: 65.219625 | MK8: 73.446328 | ML8: 5.3769313 | MM8: T | MN8: 0 | MO8: 0 | MP8: 0 | MQ8: 0 | MR8: 2.2470933 | MS8: 0.44489867 | MT8: 0 | MU8: 0 | MV8: 84.235247 | MW8: 84.235247 | MX8: 84.235247 | MY8: 0 | MZ8: 0 | NA8: 0 | NB8: 0 | NC8: 76.74377 | ND8: 0 | NE8: 0 | NF8: 0 | NG8: 0 | NH8: 0 | NI8: 0 | NJ8: 0 | NK8: 0 | NL8: 0 | NM8: 0 | NN8: 0 | NO8: 0 | NP8: 0 | NQ8: 0 | NR8: 0 | NS8: 0 | NT8: 0 | NU8: 0 | NV8: 0 | NW8: 0 | NX8: 0 | NY8: 0 | NZ8: 0 | OA8: 0 | OB8: 0 | OC8: 0.70539788 | OD8: 0.70539788 | OE8: 0.70539788 | OF8: 0.70539788 | OG8: 0 | OH8: 23.37333 | OI8: 5.5794833 | OJ8: 0 | OK8: 0 | OL8: 6.333781 | OM8: 60.602818 | ON8: 0 | OO8: 1.1839964 | OP8: 0 | OQ8: 0 | OR8: 0 | OS8: 0 | OT8: 0 | OU8: 0 | OV8: 0 | OW8: 0 | OX8: 0 | OY8: 0 | OZ8: 0 | PA8: 0 | PB8: 0 | PC8: 0 | PD8: 0 | PE8: 43.021571 | PF8: 0.1013997 | PG8: 0.1013997 | PH8: 0 | PI8: 0 | PJ8: 0 | PK8: 0 | PL8: 0 | PM8: 45.594663 | PN8: 41.453076 | PO8: 0.70539788 | PP8: 19.576641 | PQ8: 1.2439963 | PR8: 1.1839964 | PS8: 0 | PT8: 0.02577358 | PU8: 0 | PV8: 0 | PW8: 0 | PX8: 0.14100904 | PY8: 0 | PZ8: 0 | QA8: 0.70539788 | QB8: 0 | QC8: 0 | QD8: 0 | QE8: 0 | QF8: 0 | QG8: 0 | QH8: 0 | QI8: 0 | QJ8: 0 | QK8: 0.70539788
A9: 40073953 | B9: iShares Global Tech ETF | C9: US4642872919 | D9: Matched | E9: US4642872919 | F9: 35561614 | G9: IXN | H9: 8.102145 | I9: 99.599778 | J9: 24.751832 | K9: 99.599778 | L9: 71.622675 | M9: 99.599778 | N9: 46.870843 | O9: 99.599778 | P9: 0.78894537 | Q9: 0 | R9: 18.40557 | T9: 0.78894537 | U9: 0 | V9: 0 | W9: 46.523625 | X9: 99.599778 | Y9: 146.79851 | Z9: 99.599778 | AA9: 449.62744 | AB9: 99.599778 | AC9: 302.82827 | AD9: 99.599778 | AE9: 202.59174 | AF9: 0.10899654 | AG9: 348.56694 | AH9: 871.71183 | AI9: 578.90204 | AJ9: 23.204552 | AK9: 19.280021 | AL9: Misaligned | AM9: 99.599778 | AN9: 43.355402 | AO9: 13.759803 | AP9: 2.2 | AQ9: 97.568677 | AR9: 54.621194 | AS9: 98.122868 | AT9: 4.8233163 | AU9: 65.934977 | AV9: 99.599778 | AW9: 0 | AX9: 3.5389063 | AY9: 2.3387416 | AZ9: 0 | BA9: 44.369703 | BB9: 45.730337 | BC9: 0 | BD9: 0.7848461 | BE9: 0 | BF9: 0.8617311 | BG9: 0 | BH9: 0.16569767 | BI9: 0.00227126 | BJ9: 0 | BK9: 16.376264 | BL9: 16.602907 | BM9: 0 | BN9: 0.01406254 | BO9: 0 | BP9: 0.0518184 | BQ9: 0 | BR9: 0.00027035 | BS9: 0.01660415 | BT9: 0 | BU9: 16.619511 | BV9: 0.00912636 | BW9: 0 | BX9: 0.16896688 | BY9: 3.2925546 | BZ9: 0 | CA9: 45.730337 | CB9: 1.6677731 | CC9: 0.0518184 | CD9: 0 | CE9: 0.00912636 | CG9: 44.517275 | CH9: 3.7135722 | CI9: 1.2763498 | CJ9: 58.479138 | CK9: 41.791709 | CL9: 22.619966 | CM9: 12.014445 | CN9: 12.277794 | CO9: 13.708513 | CP9: 8.2094909 | CQ9: 0 | CR9: 2.5140073 | CS9: 18.633748 | CT9: 78.452023 | CU9: 4.0035153 | CV9: 2.8638387 | CW9: 1.3773301 | CX9: 76.295746 | CY9: 29.982623 | CZ9: 3.3408452 | DA9: 68.226328 | DB9: 75.222556 | DC9: 3.3022528 | DD9: 21.074969 | DE9: 42.692032 | DF9: 99.599778 | DG9: 6.4251227 | DH9: 99.599778 | DI9: 97.085771 | DJ9: 2.5140073 | DK9: 29.919736 | DL9: 0 | DM9: 63.931269 | DN9: 0 | DO9: 8.6980952 | DP9: 26.970414 | DQ9: 6.5778954 | DR9: 99.599778 | DS9: 35.991246 | DT9: 23.511192 | DU9: 0 | DV9: 0.42791613 | DW9: 8.5525237 | DX9: 48.628569 | DY9: 5.2303748 | DZ9: 7.7964719 | EA9: 49.903919 | EB9: 3.0279065 | EC9: 1.6585519 | EE9: 0 | EF9: 15.235914 | EG9: 76.158573 | EH9: 3.8304737 | EI9: 0.71136057 | EJ9: 3.1169891 | EK9: 49.915017 | EL9: 46.567773 | EM9: 0.77134882 | EN9: 2.3456403 | EO9: 617.2676 | EP9: 52.546701 | EQ9: 463.32642 | ER9: 92.558658 | ES9: 36.773092 | ET9: 30.066107 | EU9: 0 | EV9: 73.894117 | EW9: 5.3173578 | EX9: 42.29641 | EY9: 0.4862047 | EZ9: 0 | FA9: 95.808022 | FB9: 98.402513 | FC9: 36.68241 | FD9: 96.411803 | FE9: Not Aligned | FF9: 0 | FG9: 0 | FH9: 18.766022 | FI9: 18.766022 | FJ9: 80.833757 | FK9: 0 | FL9: 0 | FM9: Not Aligned | FN9: 0 | FO9: 0 | FP9: 0 | FQ9: 0 | FR9: 99.599778 | FS9: 0 | FT9: 0 | FU9: Not Aligned | FV9: 0 | FW9: 0 | FX9: 0 | FY9: 0 | FZ9: 99.599778 | GA9: 0 | GB9: 0 | GC9: Not Aligned | GD9: 0 | GE9: 0 | GF9: 0 | GG9: 0 | GH9: 99.599778 | GI9: 0 | GJ9: 0 | GK9: Aligned | GL9: 45.341613 | GM9: 45.341613 | GN9: 0 | GO9: 0 | GP9: 54.258165 | GQ9: 0 | GR9: 0 | GS9: Aligned | GT9: 7.3004691 | GU9: 7.3004691 | GV9: 0 | GW9: 0 | GX9: 92.299309 | GY9: 0 | GZ9: 0 | HA9: Aligned | HB9: 31.297466 | HC9: 31.297466 | HD9: 0 | HE9: 0 | HF9: 68.302313 | HG9: 0 | HH9: 0 | HI9: Aligned | HJ9: 9.4768426 | HK9: 9.4768426 | HL9: 0 | HM9: 0 | HN9: 90.122936 | HO9: 0 | HP9: 0 | HQ9: Not Aligned | HR9: 9.7620866 | HS9: 9.7620866 | HT9: 18.766022 | HU9: 18.766022 | HV9: 71.07167 | HW9: 0 | HX9: 0 | HY9: Aligned | HZ9: 25.791645 | IA9: 25.791645 | IB9: 0 | IC9: 0 | ID9: 73.808134 | IE9: 0 | IF9: 0 | IG9: Not Aligned | IH9: 0.27164676 | II9: 0.27164676 | IJ9: 7.4064483 | IK9: 7.4064483 | IL9: 91.921683 | IM9: 0 | IN9: 0 | IO9: Aligned | IP9: 26.826342 | IQ9: 40.734716 | IR9: 0 | IS9: 0 | IT9: 58.865063 | IU9: 13.908374 | IV9: 0 | IW9: Aligned | IX9: 41.985971 | IY9: 41.985971 | IZ9: 0 | JA9: 0 | JB9: 57.613808 | JC9: 0 | JD9: 0 | JE9: Not Aligned | JF9: 0 | JG9: 0 | JH9: 0 | JI9: 0 | JJ9: 99.599778 | JK9: 0 | JL9: 0 | JM9: Not Aligned | JN9: 0 | JO9: 0 | JP9: 0 | JQ9: 0 | JR9: 99.599778 | JS9: 0 | JT9: 0 | JU9: Aligned | JV9: 16.153634 | JW9: 16.153634 | JX9: 0 | JY9: 0 | JZ9: 83.446145 | KA9: 0 | KB9: 0 | KC9: Not Aligned | KD9: 0 | KE9: 0 | KF9: 18.766022 | KG9: 18.766022 | KH9: 80.833757 | KI9: 0 | KJ9: 0 | KK9: 99.599778 | KL9: 0.44449286 | KM9: 6.0228196 | KN9: 5.0073185 | KO9: Equity | KP9: Exchange Traded Funds | KQ9: USA | KR9: 29.311273 | KS9: 99.980885 | KT9: 99.708775 | KU9: 5.2932532 | KV9: 5.538442 | KW9: 1.0112018 | KX9: 69.3863 | KZ9: 7.3801457 | LA9: 82.610506 | LB9: 6.0207147 | LC9: 89.64539 | LD9: AA | LE9: 13.088952 | LF9: 54.036009 | LG9: 15.350291 | LH9: 1.0112018 | LI9: 2.2305628 | LJ9: 13.991758 | LK9: 0 | LL9: 0.29122502 | LM9: 4.8454222 | LN9: 0.29122502 | LO9: 12.04134 | LP9: 82.660117 | LQ9: 5.3029548 | LR9: 20.934946 | LS9: Global | LT9: 6.1223211 | LU9: 39.478125 | LV9: 129 | LW9: 1 | LX9: 128 | LY9: T | LZ9: The Fund seeks to track the investment results of the S%P Global 1200 Information Technology Index composed of global equities in the technology sector. The Fund invests at least 90% of its assets in securities of the Underlying Index and in depositary receipts representing securities of the Underlying Index. | MA9: 46203 | MB9: Equity Sector Information Technology | MC9: 1410 | MD9: BlackRock Fund Advisors | ME9: iShares Global Tech ETF | MF9: 5.6717585 | MG9: 39.295704 | MH9: 9455798439 | MI9: 7.3801457 | MJ9: 82.610506 | MK9: 89.64539 | ML9: 5.7727173 | MM9: T | MN9: 0 | MO9: 0 | MP9: 0 | MQ9: 0 | MR9: 0.11067831 | MS9: 0 | MT9: 0 | MU9: 0 | MV9: 1.0347972 | MW9: 1.0347972 | MX9: 1.0347972 | MY9: 0 | MZ9: 0 | NA9: 0 | NB9: 0 | NC9: 0.71136057 | ND9: 0 | NE9: 0 | NF9: 0 | NG9: 0 | NH9: 0 | NI9: 0 | NJ9: 0 | NK9: 0 | NL9: 0 | NM9: 0 | NN9: 0 | NO9: 0 | NP9: 0 | NQ9: 0 | NR9: 6.8651543 | NS9: 0.81683982 | NT9: 0 | NU9: 0 | NV9: 0 | NW9: 0 | NX9: 0 | NY9: 2.1526781 | NZ9: 0 | OA9: 0 | OB9: 0 | OC9: 0 | OD9: 0 | OE9: 0 | OF9: 0 | OG9: 0 | OH9: 0.34563226 | OI9: 0.34563226 | OJ9: 0 | OK9: 0 | OL9: 0.34563226 | OM9: 43.720831 | ON9: 0 | OO9: 0.34563226 | OP9: 0 | OQ9: 0 | OR9: 0 | OS9: 0 | OT9: 0 | OU9: 0 | OV9: 0 | OW9: 0 | OX9: 0 | OY9: 0 | OZ9: 0 | PA9: 0 | PB9: 0 | PC9: 0 | PD9: 0 | PE9: 8.2199889 | PF9: 0 | PG9: 0 | PH9: 0 | PI9: 0 | PJ9: 0 | PK9: 0 | PL9: 0 | PM9: 4.6395906 | PN9: 0 | PO9: 0 | PP9: 4.2939584 | PQ9: 0 | PR9: 0.34563226 | PS9: 0 | PT9: 1.107e-05 | PU9: 0.13395711 | PV9: 0 | PW9: 0.00962872 | PX9: 0 | PY9: 0 | PZ9: 0 | QA9: 2.9553207 | QB9: 0 | QC9: 0 | QD9: 0 | QE9: 0 | QF9: 0 | QG9: 0 | QH9: 0 | QI9: 0 | QJ9: 0 | QK9: 6.8651543
A10: 40073954 | B10: iShares Global Comm Services ETF | C10: US4642872752 | D10: Matched | E10: US4642872752 | F10: 35561616 | G10: IXP | H10: 3.9577318 | I10: 99.7002 | J10: 5.8405769 | K10: 99.7002 | L10: 35.915389 | M10: 99.7002 | N10: 30.074812 | O10: 99.7002 | P10: 0 | Q10: 0 | R10: 1.8407465 | T10: 0 | U10: 0 | V10: 0 | W10: 14.313043 | X10: 99.7002 | Y10: 32.060596 | Z10: 99.7002 | AA10: 158.1479 | AB10: 99.7002 | AC10: 126.08807 | AD10: 99.7002 | AE10: 202.59174 | AF10: 0.06079764 | AG10: 30.871351 | AH10: 76.730356 | AI10: 542.5068 | AJ10: 65.646634 | AK10: 18.252982 | AL10: 2.0°C Aligned | AM10: 99.7002 | AN10: 15.205785 | AO10: 0.59479941 | AP10: 1.7 | AQ10: 90.41591 | AR10: 84.652415 | AS10: 98.770401 | AT10: 2.3286056 | AU10: 85.323315 | AV10: 99.7002 | AW10: 1.2686987 | AX10: 6.2872937 | AY10: 2.2211978 | AZ10: 0.41329959 | BA10: 26.048774 | BB10: 26.048774 | BC10: 0 | BD10: 0 | BE10: 0.31459969 | BF10: 0 | BG10: 0.00063435 | BH10: 0.048043 | BI10: 0.14715761 | BJ10: 0.02843501 | BK10: 0.84633264 | BL10: 0.89437565 | BM10: 0 | BN10: 0 | BO10: 0.00091234 | BP10: 0 | BQ10: 0 | BR10: 0 | BS10: 0.17713931 | BT10: 0 | BU10: 1.071515 | BV10: 0 | BW10: 0 | BX10: 0 | BY10: 4.2177958 | BZ10: 0 | CA10: 26.776673 | CB10: 0 | CC10: 0 | CD10: 0 | CE10: 0 | CG10: 40.01296 | CH10: 3.5778964 | CI10: 2.031398 | CJ10: 83.399217 | CK10: 22.830477 | CL10: 6.3280937 | CM10: 34.825365 | CN10: 5.2325948 | CO10: 9.8935901 | CP10: 52.655347 | CQ10: 0 | CR10: 7.7593923 | CS10: 43.041457 | CT10: 48.899351 | CU10: 58.674841 | CV10: 27.072673 | CW10: 2.5951974 | CX10: 71.486129 | CY10: 41.783258 | CZ10: 5.9271941 | DA10: 38.695361 | DB10: 35.471465 | DC10: 47.970552 | DD10: 16.258184 | DE10: 53.534946 | DF10: 99.7002 | DG10: 5.8626659 | DH10: 99.7002 | DI10: 91.940808 | DJ10: 7.7593923 | DK10: 14.952385 | DL10: 0 | DM10: 99.7002 | DN10: 0 | DO10: 0 | DP10: 0 | DQ10: 6.5323311 | DR10: 99.7002 | DS10: 62.789837 | DT10: 16.288784 | DU10: 0 | DV10: 5.964794 | DW10: 56.724843 | DX10: 65.670134 | DY10: 47.537852 | DZ10: 6.1805938 | EA10: 60.669339 | EB10: 0.96189904 | EC10: 0 | ED10: 0.1875 | EE10: 4.0681959 | EF10: 47.782552 | EG10: 43.858056 | EI10: 0 | EJ10: 0 | EK10: 95.632004 | EL10: 4.0681959 | EM10: 0 | EN10: 0.45859954 | EO10: 103.82752 | EP10: 18.052282 | EQ10: 88.010914 | ER10: 81.134319 | ES10: 40.33146 | ET10: 12.332588 | EU10: 0.56369944 | EV10: 41.837058 | EW10: 3.8018962 | EX10: 75.073825 | EY10: 2.8600971 | EZ10: 4.5390955 | FA10: 72.143928 | FB10: 99.7002 | FC10: 25.289575 | FD10: 98.628701 | FE10: Not Aligned | FF10: 2.8793971 | FG10: 2.8793971 | FH10: 41.980958 | FI10: 41.980958 | FJ10: 54.839845 | FK10: 0 | FL10: 0 | FM10: Not Aligned | FN10: 0 | FO10: 0 | FP10: 0 | FQ10: 0 | FR10: 99.7002 | FS10: 0 | FT10: 0 | FU10: Not Aligned | FV10: 0 | FW10: 0 | FX10: 0 | FY10: 0 | FZ10: 99.7002 | GA10: 0 | GB10: 0 | GC10: Not Aligned | GD10: 0 | GE10: 0 | GF10: 0 | GG10: 0 | GH10: 99.7002 | GI10: 0 | GJ10: 0 | GK10: Aligned | GL10: 26.197474 | GM10: 26.197474 | GN10: 0 | GO10: 0 | GP10: 73.502727 | GQ10: 0 | GR10: 0 | GS10: Aligned | GT10: 0.998199 | GU10: 0.998199 | GV10: 0 | GW10: 0 | GX10: 98.702001 | GY10: 0 | GZ10: 0 | HA10: Aligned | HB10: 10.856189 | HC10: 10.856189 | HD10: 0 | HE10: 0 | HF10: 88.844011 | HG10: 0 | HH10: 0 | HI10: Not Aligned | HJ10: 15.662484 | HK10: 15.662484 | HL10: 24.923075 | HM10: 24.923075 | HN10: 59.114641 | HO10: 0 | HP10: 0 | HQ10: Not Aligned | HR10: 3.6578964 | HS10: 3.6578964 | HT10: 45.316855 | HU10: 45.316855 | HV10: 50.725449 | HW10: 0 | HX10: 0 | HY10: Not Aligned | HZ10: 21.783178 | IA10: 21.783178 | IB10: 40.662659 | IC10: 40.662659 | ID10: 37.254363 | IE10: 0 | IF10: 0 | IG10: Not Aligned | IH10: 0 | II10: 0 | IJ10: 39.99526 | IK10: 39.99526 | IL10: 59.70494 | IM10: 0 | IN10: 0 | IO10: Aligned | IP10: 8.0861919 | IQ10: 8.0861919 | IR10: 0 | IS10: 0 | IT10: 91.614008 | IU10: 0 | IV10: 0 | IW10: Aligned | IX10: 13.448287 | IY10: 13.448287 | IZ10: 0 | JA10: 0 | JB10: 86.251914 | JC10: 0 | JD10: 0 | JE10: Not Aligned | JF10: 0 | JG10: 0 | JH10: 0 | JI10: 0 | JJ10: 99.7002 | JK10: 0 | JL10: 0 | JM10: Not Aligned | JN10: 0 | JO10: 0 | JP10: 0 | JQ10: 0 | JR10: 99.7002 | JS10: 0 | JT10: 0 | JU10: Not Aligned | JV10: 6.991293 | JW10: 6.991293 | JX10: 23.741276 | JY10: 23.741276 | JZ10: 68.967631 | KA10: 0 | KB10: 0 | KC10: Not Aligned | KD10: 0 | KE10: 0 | KF10: 39.99526 | KG10: 39.99526 | KH10: 59.70494 | KI10: 0 | KJ10: 0 | KK10: 99.7002 | KL10: -0.59035183 | KM10: -10.882789 | KN10: 4.1022959 | KO10: Equity | KP10: Exchange Traded Funds | KQ10: USA | KR10: 60.298837 | KS10: 99.962461 | KT10: 99.760998 | KU10: 7.0239202 | KV10: 4.9643115 | KW10: 19.273681 | KX10: 20.18848 | KZ10: 5.4246372 | LA10: 22.283152 | LB10: 5.6885136 | LC10: 43.902439 | LD10: BBB | LE10: 16.430281 | LF10: 13.581886 | LG10: 6.6065934 | LH10: 18.929281 | LI10: 6.974993 | LJ10: 36.893563 | LK10: 0.34439966 | LL10: 0.23900205 | LM10: 4.4711039 | LN10: 0.23900205 | LO10: 12.493188 | LP10: 83.165515 | LQ10: 8.2151488 | LR10: 7.5738658 | LS10: Global | LT10: 4.150296 | LU10: 40.898765 | LV10: 67 | LW10: 1 | LX10: 65 | LY10: T | LZ10: The Fund seeks to track the investment results of the S&P Global 1200 Communication Services Sector Index, a subset of the S&P Global 1200, composed of global equity securities of companies in the communication services sector. The Underlying Index may include large-, mid- or small-capitalization companies. | MA10: 46203 | MB10: Equity Sector Communication Services | MC10: 82 | MD10: BlackRock Fund Advisors | ME10: iShares Global Comm Services ETF | MF10: 4.1612027 | MG10: 51.288367 | MH10: 518793862 | MI10: 5.4246372 | MJ10: 22.283152 | MK10: 43.902439 | ML10: 4.4645073 | MM10: T | MN10: 17.064883 | MO10: 1.1817988 | MP10: 0 | MQ10: 0 | MR10: 13.537886 | MS10: 0 | MT10: 0 | MU10: 0 | MV10: 4.5390955 | MW10: 4.5390955 | MX10: 0 | MY10: 0 | MZ10: 0 | NA10: 0 | NB10: 0 | NC10: 0 | ND10: 0 | NE10: 0 | NF10: 0 | NG10: 0 | NH10: 0 | NI10: 0 | NJ10: 0 | NK10: 0 | NL10: 0 | NM10: 0 | NN10: 0 | NO10: 0 | NP10: 0 | NQ10: 0 | NR10: 0.37569962 | NS10: 0 | NT10: 0 | NU10: 0 | NV10: 0 | NW10: 0 | NX10: 0 | NY10: 10.854589 | NZ10: 5.5070945 | OA10: 0 | OB10: 0 | OC10: 0 | OD10: 0 | OE10: 0 | OF10: 0 | OG10: 0 | OH10: 1.5261985 | OI10: 29.56487 | OJ10: 0 | OK10: 0 | OL10: 1.5261985 | OM10: 97.714802 | ON10: 0 | OO10: 1.5261985 | OP10: 0 | OQ10: 0 | OR10: 0 | OS10: 0 | OT10: 0 | OU10: 0 | OV10: 0 | OW10: 0 | OX10: 0 | OY10: 0 | OZ10: 0 | PA10: 0 | PB10: 0 | PC10: 0 | PD10: 0 | PE10: 41.241759 | PF10: 0 | PG10: 0 | PH10: 0 | PI10: 0 | PJ10: 0 | PK10: 0 | PL10: 0 | PM10: 45.616054 | PN10: 42.295458 | PO10: 0 | PP10: 18.392782 | PQ10: 0 | PR10: 1.5261985 | PS10: 0.10017008 | PT10: 0.13985319 | PU10: 0.01874741 | PV10: 0 | PW10: 0.21167639 | PX10: 0 | PY10: 0 | PZ10: 0.01432543 | QA10: 3.2038968 | QB10: 0 | QC10: 0 | QD10: 0 | QE10: 0 | QF10: 0 | QG10: 9.3731906 | QH10: 0 | QI10: 0 | QJ10: 0 | QK10: 0.37569962
A11: 40111267 | B11: iShares Global Consumer Discretionary ETF | C11: US4642887453 | D11: Matched | E11: US4642887453 | F11: 35594106 | G11: RXI | H11: 11.691397 | I11: 99.628101 | J11: 190.93993 | K11: 99.628101 | L11: 304.96492 | M11: 99.628101 | N11: 114.02499 | O11: 99.628101 | P11: 4.7034812 | Q11: 0 | R11: 11.869232 | T11: 4.7034812 | U11: 0 | V11: 3.1206875 | W11: 45.131706 | X11: 99.628101 | Y11: 294.60078 | Z11: 99.628101 | AA11: 560.65308 | AB11: 99.628101 | AC11: 266.05213 | AD11: 99.628101 | AE11: 202.59174 | AF11: 0.06381604 | AG11: 1579.5282 | AH11: 3944.3192 | AI11: 2387.9104 | AJ11: 7.4484702 | AK11: 28.767585 | AL11: Misaligned | AM11: 99.628101 | AN11: 22.151311 | AO11: 41.260735 | AP11: 2.3 | AQ11: 84.112564 | AR11: 66.445534 | AS11: 98.051208 | AT11: 6.2713904 | AU11: 49.812801 | AV11: 99.628101 | AW11: 1.8710925 | AX11: 1.4044944 | AY11: 0 | AZ11: 0.1507994 | BA11: 4.5668817 | BB11: 6.258475 | BC11: 1.6569934 | BD11: 0 | BE11: 0.97899608 | BF11: 0.55729777 | BG11: 0.03611488 | BH11: 0.0222664 | BI11: 0 | BJ11: 0.13891641 | BK11: 0.59880188 | BL11: 0.9897057 | BM11: 0.34928446 | BN11: 0 | BO11: 0.04082164 | BP11: 0.00398116 | BQ11: 0 | BR11: 0.02997023 | BS11: 0.24582315 | BT11: 0.00805485 | BU11: 1.2355288 | BV11: 0.00731695 | BW11: 0 | BX11: 2.8726885 | BY11: 5.0426798 | BZ11: 0.03459986 | CA11: 8.9733641 | CB11: 0.9261963 | CC11: 0.00398116 | CD11: 0.00805485 | CE11: 0.00731695 | CG11: 73.034508 | CH11: 4.2625829 | CI11: 1.0293959 | CJ11: 88.594246 | CK11: 18.669625 | CL11: 3.0926876 | CM11: 6.8945724 | CN11: 2.3156907 | CO11: 12.923248 | CP11: 33.589166 | CQ11: 0.11459954 | CR11: 17.60363 | CS11: 31.416174 | CT11: 50.493698 | CU11: 23.480406 | CV11: 20.860017 | CW11: 7.1035716 | CX11: 60.582558 | CY11: 33.156667 | CZ11: 10.828757 | DA11: 75.458198 | DB11: 60.479058 | DC11: 21.750013 | DD11: 17.39903 | DE11: 67.342931 | DF11: 99.628101 | DG11: 5.4523849 | DH11: 99.628101 | DI11: 82.44457 | DJ11: 17.183531 | DK11: 37.50365 | DL11: 0 | DM11: 73.879904 | DN11: 5.0482798 | DO11: 12.946348 | DP11: 7.753569 | DQ11: 6.2336927 | DR11: 99.628101 | DS11: 44.96972 | DT11: 28.645585 | DU11: 0 | DV11: 0.67009732 | DW11: 21.777613 | DX11: 45.176319 | DY11: 21.001416 | DZ11: 1.4224943 | EA11: 43.160827 | EB11: 1.0620957 | EC11: 1.7695529 | ED11: 5.8929138 | EE11: 74.868701 | EF11: 22.673409 | EG11: 78.479186 | EH11: 4.4565563 | EI11: 3.6400854 | EJ11: 3.8574846 | EK11: 64.266343 | EL11: 31.504274 | EM11: 7.2916708 | EN11: 0.82869668 | EO11: 1178.8154 | EP11: 31.697573 | EQ11: 2624.07 | ER11: 53.558686 | ES11: 26.797093 | ET11: 24.144803 | EU11: 0.91039636 | EV11: 44.226323 | EW11: 13.622546 | EX11: 55.00318 | EY11: 7.753569 | EZ11: 0 | FA11: 89.97594 | FB11: 99.254603 | FC11: 30.11428 | FD11: 96.420214 | FE11: Not Aligned | FF11: 2.6704893 | FG11: 2.6704893 | FH11: 14.743641 | FI11: 14.743641 | FJ11: 82.213971 | FK11: 0 | FL11: 0 | FM11: Not Aligned | FN11: 0.249099 | FO11: 0.249099 | FP11: 5.8014768 | FQ11: 5.8014768 | FR11: 93.577526 | FS11: 0 | FT11: 0 | FU11: Not Aligned | FV11: 0 | FW11: 0 | FX11: 15.277039 | FY11: 15.277039 | FZ11: 84.351063 | GA11: 0 | GB11: 0 | GC11: Not Aligned | GD11: 0.1507994 | GE11: 0.1507994 | GF11: 19.95672 | GG11: 19.95672 | GH11: 79.520582 | GI11: 0 | GJ11: 0 | GK11: Aligned | GL11: 33.320867 | GM11: 33.320867 | GN11: 0 | GO11: 0 | GP11: 66.307235 | GQ11: 0 | GR11: 0 | GS11: Aligned | GT11: 3.6462854 | GU11: 3.6462854 | GV11: 0.14219943 | GW11: 0.14219943 | GX11: 95.839617 | GY11: 0 | GZ11: 0 | HA11: Not Aligned | HB11: 37.314251 | HC11: 37.314251 | HD11: 0.03459986 | HE11: 0 | HF11: 62.279251 | HG11: 0 | HH11: 0.03459986 | HI11: Not Aligned | HJ11: 3.4555862 | HK11: 3.6063856 | HL11: 18.747725 | HM11: 18.747725 | HN11: 77.273991 | HO11: 0.1507994 | HP11: 0 | HQ11: Not Aligned | HR11: 6.9812721 | HS11: 6.9812721 | HT11: 18.904124 | HU11: 18.904124 | HV11: 73.742705 | HW11: 0 | HX11: 0 | HY11: Not Aligned | HZ11: 17.170331 | IA11: 17.170331 | IB11: 18.551626 | IC11: 18.551626 | ID11: 63.906144 | IE11: 0 | IF11: 0 | IG11: Aligned | IH11: 9.7683609 | II11: 9.7683609 | IJ11: 3.6184855 | IK11: 3.6184855 | IL11: 86.241255 | IM11: 0 | IN11: 0 | IO11: Not Aligned | IP11: 22.998908 | IQ11: 31.360975 | IR11: 0.28159887 | IS11: 0.24699901 | IT11: 67.985528 | IU11: 8.3620666 | IV11: 0.03459986 | IW11: Not Aligned | IX11: 50.735397 | IY11: 50.735397 | IZ11: 0.03459986 | JA11: 0 | JB11: 48.858105 | JC11: 0 | JD11: 0.03459986 | JE11: Not Aligned | JF11: 0 | JG11: 0 | JH11: 0.9494962 | JI11: 0.9494962 | JJ11: 98.678605 | JK11: 0 | JL11: 0 | JM11: Not Aligned | JN11: 0 | JO11: 0 | JP11: 3.1546874 | JQ11: 3.1546874 | JR11: 96.473414 | JS11: 0 | JT11: 0 | JU11: Not Aligned | JV11: 3.7653849 | JW11: 3.7653849 | JX11: 5.1967792 | JY11: 5.1967792 | JZ11: 90.665937 | KA11: 0 | KB11: 0 | KC11: Not Aligned | KD11: 0 | KE11: 0 | KF11: 15.621838 | KG11: 15.621838 | KH11: 84.006264 | KI11: 0 | KJ11: 0 | KK11: 99.628101 | KL11: -0.14303191 | KM11: -2.2901908 | KN11: 10.894356 | KO11: Equity | KP11: Exchange Traded Funds | KQ11: USA | KR11: 62.846965 | KS11: 99.894993 | KT11: 99.691918 | KU11: 6.1224397 | KV11: 5.3933208 | KW11: 2.6270895 | KX11: 34.217863 | KZ11: 6.2454145 | LA11: 38.800811 | LB11: 6.0552896 | LC11: 55.729167 | LD11: A | LE11: 16.65885 | LF11: 24.583602 | LG11: 9.6342615 | LH11: 2.2832909 | LI11: 6.1046756 | LJ11: 40.08344 | LK11: 0.34379862 | LL11: 0.30808247 | LM11: 4.104254 | LN11: 0.30808247 | LO11: 11.231255 | LP11: 77.566306 | LQ11: 6.4280522 | LR11: 19.797161 | LS11: Global | LT11: 5.4303665 | LU11: 34.609934 | LV11: 135 | LW11: 1 | LX11: 133 | LY11: T | LZ11: The Fund seeks the investment results of the S&P Global 1200 Consumer Sector Discretionary Capped Index that are composed of global equities in the consumer discretionary sector. The Underlying Index is designed to measure the performance of large-capitalization stocks from major global markets, as determined by SPDJI. | MA11: 46203 | MB11: Equity Sector Consumer Discretionary | MC11: 192 | MD11: BlackRock Fund Advisors | ME11: iShares Global Consumer Discretionary ETF | MF11: 3.9870591 | MG11: 45.284823 | MH11: 251662158 | MI11: 6.2454145 | MJ11: 38.800811 | MK11: 55.729167 | ML11: 4.9728713 | MM11: T | MN11: 15.763737 | MO11: 0.14219943 | MP11: 0 | MQ11: 0 | MR11: 44.363623 | MS11: 18.831925 | MT11: 0 | MU11: 2.2076912 | MV11: 4.9373803 | MW11: 2.4307903 | MX11: 2.2885908 | MY11: 0 | MZ11: 0 | NA11: 0 | NB11: 0 | NC11: 6.4220743 | ND11: 0 | NE11: 0 | NF11: 2.0562918 | NG11: 1.9514922 | NH11: 0 | NI11: 1.9514922 | NJ11: 0 | NK11: 0 | NL11: 0.10479958 | NM11: 0 | NN11: 0 | NO11: 0 | NP11: 0 | NQ11: 0 | NR11: 2.2320911 | NS11: 0.7724969 | NT11: 0 | NU11: 0 | NV11: 0 | NW11: 0 | NX11: 0 | NY11: 10.540058 | NZ11: 6.5116739 | OA11: 0.69489721 | OB11: 1.3498946 | OC11: 0 | OD11: 0 | OE11: 0 | OF11: 0 | OG11: 0 | OH11: 29.868781 | OI11: 22.168211 | OJ11: 0 | OK11: 0 | OL11: 27.739589 | OM11: 86.744953 | ON11: 0 | OO11: 23.028108 | OP11: 0 | OQ11: 0 | OR11: 0 | OS11: 0 | OT11: 0.81559674 | OU11: 0 | OV11: 0 | OW11: 0 | OX11: 0 | OY11: 0 | OZ11: 0 | PA11: 0 | PB11: 0 | PC11: 0 | PD11: 0 | PE11: 10.627157 | PF11: 0 | PG11: 0 | PH11: 0 | PI11: 0 | PJ11: 0 | PK11: 0 | PL11: 0 | PM11: 39.484842 | PN11: 8.3059668 | PO11: 2.0616918 | PP11: 1.3775945 | PQ11: 4.7114812 | PR11: 23.028108 | PS11: 0.15353933 | PT11: 0.67289913 | PU11: 0.00895352 | PV11: 0.00259871 | PW11: 1.1976631 | PX11: 0 | PY11: 0 | PZ11: 0.08157562 | QA11: 23.410806 | QB11: 0 | QC11: 0 | QD11: 0 | QE11: 0 | QF11: 0 | QG11: 14.472642 | QH11: 0 | QI11: 0 | QJ11: 0 | QK11: 2.2320911
A12: 40111270 | B12: iShares Global Consumer Staples ETF | C12: US4642887370 | D12: Matched | E12: US4642887370 | F12: 35594112 | G12: KXI | H12: 20.553825 | I12: 99.418299 | J12: 87.101723 | K12: 99.418299 | L12: 280.69175 | M12: 99.418299 | N12: 193.59003 | O12: 99.418299 | P12: 23.873924 | Q12: 0 | R12: 0.25703715 | T12: 22.888723 | U12: 0 | V12: 0.98520099 | W12: 32.593771 | X12: 99.418299 | Y12: 116.28673 | Z12: 99.418299 | AA12: 517.65185 | AB12: 99.418299 | AC12: 401.36522 | AD12: 99.418299 | AE12: 202.59174 | AF12: 0.07581338 | AG12: 1767.9622 | AH12: 4416.1834 | AI12: 1841.9389 | AJ12: 26.775527 | AK12: 21.443121 | AL12: Misaligned | AM12: 99.418299 | AN12: 34.812635 | AO12: 16.387016 | AP12: 2.6 | AQ12: 92.426392 | AR12: 59.97746 | AS12: 99.418299 | AT12: 2.6020673 | AU12: 81.806882 | AV12: 99.418299 | AW12: 0 | AX12: 0 | AY12: 0 | AZ12: 0 | BA12: 2.4227024 | BB12: 5.1978052 | BC12: 0.90920091 | BD12: 0.16420016 | BE12: 25.363925 | BF12: 0.56320056 | BG12: 0 | BH12: 0 | BI12: 0 | BJ12: 0 | BK12: 0.00568748 | BL12: 0.2382462 | BM12: 0.00885453 | BN12: 0.01121487 | BO12: 3.1745556 | BP12: 0.00191488 | BQ12: 0 | BR12: 1.8835073 | BS12: 5.0692778 | BT12: 0.22178931 | BU12: 5.1220376 | BV12: 0 | BW12: 0 | BX12: 22.274122 | BY12: 29.53923 | BZ12: 1.9161019 | CA12: 29.53923 | CB12: 0 | CC12: 0.00191488 | CD12: 0.22846702 | CE12: 0 | CG12: 70.810071 | CH12: 28.611329 | CI12: 0 | CJ12: 57.148357 | CK12: 26.012826 | CL12: 12.646313 | CM12: 2.5954026 | CN12: 0 | CO12: 34.556835 | CP12: 2.8261028 | CQ12: 0.30580031 | CR12: 3.3683034 | CS12: 35.114635 | CT12: 60.629561 | CU12: 22.070322 | CV12: 17.895018 | CW12: 1.3747014 | CX12: 62.009762 | CY12: 19.49822 | CZ12: 9.6280096 | DA12: 83.227683 | DB12: 58.790159 | DC12: 4.0710041 | DD12: 36.557137 | DE12: 85.348785 | DF12: 99.418299 | DG12: 5.6663392 | DH12: 99.418299 | DI12: 95.949296 | DJ12: 3.4690035 | DK12: 40.12964 | DL12: 0 | DM12: 77.181077 | DN12: 3.8536038 | DO12: 18.383618 | DP12: 0 | DQ12: 5.8590508 | DR12: 99.418299 | DS12: 18.568319 | DT12: 11.731912 | DU12: 0 | DV12: 5.6519056 | DW12: 14.227114 | DX12: 49.288549 | DY12: 17.257517 | DZ12: 1.6636017 | EA12: 87.687188 | EB12: 1.8899019 | EC12: 9.6744677 | ED12: 6.9663267 | EE12: 85.294185 | EF12: 20.943521 | EG12: 96.196396 | EI12: 0 | EJ12: 43.573744 | EK12: 31.592632 | EL12: 24.251924 | EM12: 46.872047 | EN12: 1.5394016 | EO12: 1216.8042 | EP12: 46.204246 | EQ12: 1777.6724 | ER12: 95.351795 | ES12: 15.059815 | ET12: 23.623124 | EU12: 1.3715014 | EV12: 61.439961 | EW12: 30.34493 | EX12: 46.702947 | EY12: 0 | EZ12: 0.38630039 | FA12: 95.637296 | FB12: 99.418299 | FC12: 58.424058 | FD12: 91.358191 | FE12: Aligned | FF12: 34.508935 | FG12: 34.508935 | FH12: 3.2608033 | FI12: 3.2608033 | FJ12: 61.648562 | FK12: 0 | FL12: 0 | FM12: Aligned | FN12: 21.141121 | FO12: 21.742222 | FP12: 0 | FQ12: 0 | FR12: 77.676078 | FS12: 0.6011006 | FT12: 0 | FU12: Not Aligned | FV12: 16.296916 | FW12: 16.296916 | FX12: 15.438315 | FY12: 2.6857027 | FZ12: 67.683068 | GA12: 0 | GB12: 12.752613 | GC12: Not Aligned | GD12: 0 | GE12: 0 | GF12: 9.8132098 | GG12: 9.8132098 | GH12: 89.60509 | GI12: 0 | GJ12: 0 | GK12: Aligned | GL12: 42.602643 | GM12: 42.602643 | GN12: 0 | GO12: 0 | GP12: 56.815657 | GQ12: 0 | GR12: 0 | GS12: Aligned | GT12: 30.848931 | GU12: 32.695233 | GV12: 0 | GW12: 0 | GX12: 66.723067 | GY12: 1.8463018 | GZ12: 0 | HA12: Not Aligned | HB12: 34.329234 | HC12: 34.329234 | HD12: 2.8157028 | HE12: 0 | HF12: 62.273362 | HG12: 0 | HH12: 2.8157028 | HI12: Aligned | HJ12: 2.9360029 | HK12: 2.9360029 | HL12: 0 | HM12: 0 | HN12: 96.482296 | HO12: 0 | HP12: 0 | HQ12: Aligned | HR12: 9.006709 | HS12: 9.006709 | HT12: 2.6108026 | HU12: 2.6108026 | HV12: 87.800788 | HW12: 0 | HX12: 0 | HY12: Aligned | HZ12: 26.772827 | IA12: 26.772827 | IB12: 0 | IC12: 0 | ID12: 72.645473 | IE12: 0 | IF12: 0 | IG12: Not Aligned | IH12: 0 | II12: 0 | IJ12: 0 | IK12: 0 | IL12: 99.418299 | IM12: 0 | IN12: 0 | IO12: Not Aligned | IP12: 8.7581087 | IQ12: 8.980009 | IR12: 11.785112 | IS12: 8.969409 | IT12: 78.653179 | IU12: 0.22190022 | IV12: 2.8157028 | IW12: Not Aligned | IX12: 40.905641 | IY12: 40.905641 | IZ12: 2.8157028 | JA12: 0 | JB12: 55.696956 | JC12: 0 | JD12: 2.8157028 | JE12: Not Aligned | JF12: 0 | JG12: 0 | JH12: 39.330539 | JI12: 39.330539 | JJ12: 60.08776 | JK12: 0 | JL12: 0 | JM12: Not Aligned | JN12: 0 | JO12: 0 | JP12: 40.39574 | JQ12: 40.39574 | JR12: 59.022559 | JS12: 0 | JT12: 0 | JU12: Not Aligned | JV12: 7.4432074 | JW12: 7.4432074 | JX12: 9.6723097 | JY12: 9.6723097 | JZ12: 82.302782 | KA12: 0 | KB12: 0 | KC12: Aligned | KD12: 0.38630039 | KE12: 0.38630039 | KF12: 0.19070019 | KG12: 0.19070019 | KH12: 98.841299 | KI12: 0 | KJ12: 0 | KK12: 99.418299 | KL12: 0.6022121 | KM12: 8.4188084 | KN12: 7.1641072 | KO12: Equity | KP12: Exchange Traded Funds | KQ12: USA | KR12: 48.635362 | KS12: 99.77024 | KT12: 99.494113 | KU12: 4.8345536 | KV12: 5.7163084 | KW12: 0 | KX12: 50.858751 | KZ12: 7.153175 | LA12: 75.583074 | LB12: 6.0895126 | LC12: 84.536082 | LD12: AA | LE12: 21.330935 | LF12: 36.039136 | LG12: 14.819615 | LH12: 0 | LI12: 2.2626023 | LJ12: 25.041825 | LK12: 0 | LL12: 0.50588721 | LM12: 4.7266461 | LN12: 0.50588721 | LO12: 15.582916 | LP12: 76.74709 | LQ12: 5.1147654 | LR12: 28.572807 | LS12: Global | LT12: 6.3545148 | LU12: 33.428012 | LV12: 96 | LW12: 1 | LX12: 93 | LY12: T | LZ12: The Fund seeks the investment results of the S&P Global 1200 Consumer Staples Sector Capped Index composed of global equities in the consumer staples sector. The Underlying Index is a subset of the S&P Global 1200, which is designed to measure the performance of large-capitalization stocks from major global markets. | MA12: 46203 | MB12: Equity Sector Consumer Staples | MC12: 97 | MD12: BlackRock Fund Advisors | ME12: iShares Global Consumer Staples ETF | MF12: 4.5179797 | MG12: 37.493294 | MH12: 1010230361 | MI12: 7.153175 | MJ12: 75.583074 | MK12: 84.536082 | ML12: 5.3064038 | MM12: T | MN12: 10.866711 | MO12: 0 | MP12: 0 | MQ12: 0 | MR12: 50.24225 | MS12: 17.545718 | MT12: 6.8469068 | MU12: 6.8469068 | MV12: 64.432364 | MW12: 64.432364 | MX12: 54.312354 | MY12: 0 | MZ12: 7.3159073 | NA12: 0.84790085 | NB12: 0 | NC12: 23.885724 | ND12: 0 | NE12: 0 | NF12: 8.5822086 | NG12: 0 | NH12: 0 | NI12: 0 | NJ12: 0 | NK12: 0 | NL12: 8.5822086 | NM12: 0 | NN12: 0 | NO12: 0 | NP12: 0 | NQ12: 0.42990043 | NR12: 0 | NS12: 0 | NT12: 0 | NU12: 0 | NV12: 0 | NW12: 0 | NX12: 0 | NY12: 0.6028006 | NZ12: 0.6028006 | OA12: 0 | OB12: 0 | OC12: 7.5495076 | OD12: 7.5495076 | OE12: 0 | OF12: 0 | OG12: 0 | OH12: 51.407051 | OI12: 8.3354083 | OJ12: 0 | OK12: 0 | OL12: 11.397611 | OM12: 79.058379 | ON12: 0 | OO12: 11.397611 | OP12: 0 | OQ12: 0 | OR12: 0 | OS12: 0 | OT12: 0 | OU12: 0 | OV12: 0 | OW12: 0 | OX12: 0 | OY12: 0 | OZ12: 0 | PA12: 0 | PB12: 1.3715014 | PC12: 0.38630039 | PD12: 0 | PE12: 1.5655016 | PF12: 0 | PG12: 0 | PH12: 0 | PI12: 0 | PJ12: 0 | PK12: 0 | PL12: 0 | PM12: 55.201355 | PN12: 3.7943038 | PO12: 40.00944 | PP12: 7.7456077 | PQ12: 0 | PR12: 11.397611 | PS12: 0.08523064 | PT12: 7.637446 | PU12: 0 | PV12: 0.08496386 | PW12: 0 | PX12: 0.03228195 | PY12: 0 | PZ12: 13.123794 | QA12: 19.59952 | QB12: 0 | QC12: 0 | QD12: 0 | QE12: 0 | QF12: 0 | QG12: 43.476143 | QH12: 15.568316 | QI12: 12.752613 | QJ12: 12.752613 | QK12: 0
A13: 40111272 | B13: iShares Global Industrials ETF | C13: US4642887297 | D13: Matched | E13: US4642887297 | F13: 35594116 | G13: EXI | H13: 29.001318 | I13: 98.753194 | J13: 463.55173 | K13: 98.753194 | L13: 559.00543 | M13: 98.753194 | N13: 95.453698 | O13: 98.753194 | P13: 30.216951 | Q13: 0.31869328 | R13: 6.8396594 | S13: 21.461574 | T13: 29.91325 | U13: 0.04756362 | V13: 8.9129446 | W13: 70.189471 | X13: 99.437897 | Y13: 1619.0343 | Z13: 99.437897 | AA13: 1903.2467 | AB13: 99.437897 | AC13: 284.21302 | AD13: 99.437897 | AE13: 202.59174 | AF13: 0.07341427 | AG13: 3963.9804 | AH13: 9896.7917 | AI13: 2090.7297 | AJ13: 14.842574 | AK13: 14.05607 | AL13: Strongly Misaligned | AM13: 98.753194 | AN13: 23.91962 | AO13: 45.93493 | AP13: 3.5 | AQ13: 88.683643 | AR13: 46.541933 | AS13: 98.190491 | AT13: 12.879069 | AU13: 52.290562 | AV13: 99.437897 | AW13: 0.29600149 | AX13: 17.839589 | AY13: 0 | AZ13: 0.22530113 | BA13: 29.365347 | BB13: 34.302672 | BC13: 2.4699124 | BD13: 2.4243121 | BE13: 2.1051105 | BF13: 10.598553 | BG13: 0.00087149 | BH13: 0.76048499 | BI13: 0 | BJ13: 0.00917474 | BK13: 2.2765896 | BL13: 3.7435283 | BM13: 0.12841474 | BN13: 0.22195741 | BO13: 0.1797259 | BP13: 0.33383793 | BQ13: 0.0003077 | BR13: 0.12251338 | BS13: 0.53536837 | BT13: 0.001849 | BU13: 4.2788967 | BV13: 0.2423521 | BW13: 0.61540308 | BX13: 3.2991165 | BY13: 8.1028405 | BZ13: 0.47410237 | CA13: 34.935275 | CB13: 13.829669 | CC13: 0.51408511 | CD13: 0.001849 | CE13: 0.3019675 | CG13: 70.650153 | CH13: 22.348012 | CI13: 2.2228111 | CJ13: 67.014435 | CK13: 22.285511 | CL13: 5.7794289 | CM13: 4.4383222 | CN13: 1.8925095 | CO13: 28.776244 | CP13: 9.2251461 | CQ13: 0 | CR13: 8.5739429 | CS13: 21.470307 | CT13: 68.867844 | CU13: 5.2637263 | CV13: 3.4906174 | CW13: 3.8496193 | CX13: 56.01388 | CY13: 12.558563 | CZ13: 7.4649373 | DA13: 74.686073 | DB13: 58.422192 | DC13: 5.3383267 | DD13: 35.151576 | DE13: 71.000755 | DF13: 98.912095 | DG13: 5.608686 | DH13: 98.753194 | DI13: 91.354657 | DJ13: 8.2421412 | DK13: 39.116796 | DL13: 0 | DM13: 36.659083 | DN13: 6.5180326 | DO13: 51.656858 | DP13: 3.9192196 | DQ13: 5.1981336 | DR13: 98.753194 | DS13: 25.690128 | DT13: 23.760219 | DU13: 0 | DV13: 2.0840104 | DW13: 14.730674 | DX13: 42.410612 | DY13: 13.079965 | DZ13: 2.7218136 | EA13: 80.678603 | EB13: 0.32910165 | EC13: 5.9516598 | EE13: 0 | EF13: 18.698593 | EG13: 84.236021 | EH13: 4.8529391 | EI13: 44.276421 | EJ13: 2.4416122 | EK13: 45.595128 | EL13: 50.716454 | EM13: 2.7667138 | EN13: 0.56520282 | EO13: 296.6047 | EP13: 48.00084 | EQ13: 477.08157 | ER13: 89.182546 | ES13: 29.767149 | ET13: 32.282861 | EU13: 6.2192311 | EV13: 58.353292 | EW13: 7.3611368 | EX13: 38.449192 | EY13: 0 | EZ13: 5.0266251 | FA13: 97.473687 | FB13: 98.445492 | FC13: 51.856659 | FD13: 95.030275 | FE13: Aligned | FF13: 5.9836299 | FG13: 5.9836299 | FH13: 1.3371067 | FI13: 1.3371067 | FJ13: 91.432457 | FK13: 0 | FL13: 0 | FM13: Aligned | FN13: 0.78470392 | FO13: 0.78470392 | FP13: 0 | FQ13: 0 | FR13: 97.96849 | FS13: 0 | FT13: 0 | FU13: Not Aligned | FV13: 0.51350257 | FW13: 0.51350257 | FX13: 6.2798314 | FY13: 6.2798314 | FZ13: 91.95986 | GA13: 0 | GB13: 0 | GC13: Not Aligned | GD13: 0 | GE13: 0 | GF13: 0 | GG13: 0 | GH13: 98.753194 | GI13: 0 | GJ13: 0 | GK13: Aligned | GL13: 51.777159 | GM13: 51.777159 | GN13: 0 | GO13: 0 | GP13: 46.976035 | GQ13: 0 | GR13: 0 | GS13: Aligned | GT13: 16.527983 | GU13: 16.527983 | GV13: 0 | GW13: 0 | GX13: 82.225211 | GY13: 0 | GZ13: 0 | HA13: Aligned | HB13: 44.855424 | HC13: 45.132426 | HD13: 0.58910295 | HE13: 0.58910295 | HF13: 53.031665 | HG13: 0.27700139 | HH13: 0 | HI13: Aligned | HJ13: 18.261591 | HK13: 18.261591 | HL13: 1.1017055 | HM13: 1.1017055 | HN13: 79.389897 | HO13: 0 | HP13: 0 | HQ13: Aligned | HR13: 40.383102 | HS13: 48.01954 | HT13: 2.6930135 | HU13: 2.6930135 | HV13: 48.04064 | HW13: 7.6364382 | HX13: 0 | HY13: Aligned | HZ13: 41.562408 | IA13: 41.562408 | IB13: 0.67280336 | IC13: 0.67280336 | ID13: 56.517983 | IE13: 0 | IF13: 0 | IG13: Not Aligned | IH13: 7.2705364 | II13: 7.2705364 | IJ13: 10.115551 | IK13: 10.115551 | IL13: 81.367107 | IM13: 0 | IN13: 0 | IO13: Aligned | IP13: 26.573433 | IQ13: 29.186946 | IR13: 1.3485068 | IS13: 1.3485068 | IT13: 68.217741 | IU13: 2.6135131 | IV13: 0 | IW13: Aligned | IX13: 46.639333 | IY13: 46.916335 | IZ13: 1.3485068 | JA13: 1.3485068 | JB13: 50.488352 | JC13: 0.27700139 | JD13: 0 | JE13: Not Aligned | JF13: 0.2797014 | JG13: 0.2797014 | JH13: 5.3116266 | JI13: 5.3116266 | JJ13: 93.161866 | JK13: 0 | JL13: 0 | JM13: Not Aligned | JN13: 0 | JO13: 0 | JP13: 4.3262216 | JQ13: 4.3262216 | JR13: 94.426972 | JS13: 0 | JT13: 0 | JU13: Aligned | JV13: 15.240176 | JW13: 15.240176 | JX13: 1.0907054 | JY13: 1.0907054 | JZ13: 82.422312 | KA13: 0 | KB13: 0 | KC13: Aligned | KD13: 2.3330117 | KE13: 2.3330117 | KF13: 0 | KG13: 0 | KH13: 96.420182 | KI13: 0 | KJ13: 0 | KK13: 98.753194 | KL13: -0.2680537 | KM13: -3.8374192 | KN13: 12.825264 | KO13: Equity | KP13: Exchange Traded Funds | KQ13: USA | KR13: 50.761068 | KS13: 99.101557 | KT13: 98.826608 | KU13: 4.8992252 | KV13: 5.8849326 | KW13: 1.6490082 | KX13: 46.416532 | KZ13: 6.9852598 | LA13: 69.08735 | LB13: 6.0332309 | LC13: 86.046512 | LD13: A | LE13: 29.489461 | LF13: 26.04563 | LG13: 20.370902 | LH13: 1.610608 | LI13: 5.0950255 | LJ13: 16.176581 | LK13: 0.03840019 | LL13: 1.173392 | LM13: 4.8044443 | LN13: 1.173392 | LO13: 10.636853 | LP13: 75.364491 | LQ13: 5.6271314 | LR13: 22.58871 | LS13: Global | LT13: 6.5924077 | LU13: 43.029385 | LV13: 219 | LW13: 1 | LX13: 217 | LY13: T | LZ13: The Fund seeks investment results that correspond to the S&P Global 1200 Industrials (Sector) Capped Idx. It is a subset of the Standard & Poor's Global 1200 Index, whose components include manufacturers and distributors of capital goods, providers of commercial services and supplies, and transportation service providers. | MA13: 46203 | MB13: Equity Sector Industrials | MC13: 215 | MD13: BlackRock Fund Advisors | ME13: iShares Global Industrials ETF | MF13: 4.950477 | MG13: 33.208513 | MH13: 1435181442 | MI13: 6.9852598 | MJ13: 69.08735 | MK13: 86.046512 | ML13: 5.8200406 | MM13: T | MN13: 2.3320117 | MO13: 0 | MP13: 0 | MQ13: 0 | MR13: 9.3366467 | MS13: 1.3529068 | MT13: 0 | MU13: 0 | MV13: 8.7603438 | MW13: 8.5374427 | MX13: 6.4957325 | MY13: 0 | MZ13: 0 | NA13: 0 | NB13: 0 | NC13: 24.632023 | ND13: 0 | NE13: 0 | NF13: 0 | NG13: 0 | NH13: 0 | NI13: 0 | NJ13: 0 | NK13: 0 | NL13: 0 | NM13: 2.6771134 | NN13: 2.6771134 | NO13: 0 | NP13: 3.7633188 | NQ13: 3.192716 | NR13: 36.300981 | NS13: 33.898769 | NT13: 8.7133435 | NU13: 11.413357 | NV13: 0 | NW13: 0 | NX13: 5.1304256 | NY13: 0.54470272 | NZ13: 0.16150081 | OA13: 0 | OB13: 0 | OC13: 0 | OD13: 0 | OE13: 0 | OF13: 0 | OG13: 0 | OH13: 11.226156 | OI13: 8.6424432 | OJ13: 4.3795219 | OK13: 0 | OL13: 11.226156 | OM13: 70.242151 | ON13: 0 | OO13: 4.01002 | OP13: 0.20960105 | OQ13: 0.20960105 | OR13: 0.20960105 | OS13: 5.1304256 | OT13: 24.563423 | OU13: 0.75030375 | OV13: 0 | OW13: 0 | OX13: 18.436192 | OY13: 13.888469 | OZ13: 9.3046465 | PA13: 10.02135 | PB13: 0 | PC13: 0 | PD13: 0 | PE13: 12.446362 | PF13: 0 | PG13: 0 | PH13: 0 | PI13: 0 | PJ13: 0 | PK13: 0 | PL13: 0 | PM13: 15.568878 | PN13: 4.3427217 | PO13: 0 | PP13: 0 | PQ13: 7.2161361 | PR13: 4.01002 | PS13: 0.00049315 | PT13: 0.04944189 | PU13: 7.2019842 | PV13: 0 | PW13: 0.0001615 | PX13: 0 | PY13: 0.48673892 | PZ13: 0.00434879 | QA13: 31.303956 | QB13: 3.2971165 | QC13: 0 | QD13: 0 | QE13: 0 | QF13: 4.1566208 | QG13: 4.6598233 | QH13: 0 | QI13: 0 | QJ13: 0 | QK13: 36.300981
A14: 40111273 | B14: iShares Global Utilities ETF | C14: US4642887115 | D14: Matched | E14: US4642887115 | F14: 35594118 | G14: JXI | H14: 250.58497 | I14: 99.466599 | J14: 142.43575 | K14: 99.466599 | L14: 233.45193 | M14: 99.466599 | N14: 91.016178 | O14: 99.466599 | P14: 95.042095 | Q14: 18.660905 | R14: 15.797774 | S14: 0.84657062 | T14: 93.962894 | U14: 0.13915916 | V14: 61.691962 | W14: 1290.8658 | X14: 99.466599 | Y14: 549.41774 | Z14: 99.466599 | AA14: 964.5647 | AB14: 99.466599 | AC14: 415.14654 | AD14: 99.466599 | AE14: 202.59174 | AF14: 0.08115398 | AG14: 1811.9505 | AH14: 4516.2751 | AI14: 4098.4107 | AJ14: 30.854431 | AK14: 14.551815 | AL14: 2.0°C Aligned | AM14: 99.466599 | AN14: 19.345319 | AO14: 34.715035 | AP14: 2 | AQ14: 90.618991 | AR14: 26.648727 | AS14: 96.191996 | AT14: 26.058998 | AU14: 32.373532 | AV14: 99.466599 | AW14: 1.6538016 | AX14: 69.90337 | AY14: 0 | AZ14: 0 | BA14: 36.373336 | BB14: 72.353972 | BC14: 0.47620048 | BD14: 0 | BE14: 0 | BF14: 0.45330045 | BG14: 0.0008269 | BH14: 9.595686 | BI14: 0 | BJ14: 0 | BK14: 1.3178375 | BL14: 11.699376 | BM14: 0.00242862 | BN14: 0 | BO14: 0 | BP14: 0.00199452 | BQ14: 0 | BR14: 0 | BS14: 0.0008269 | BT14: 0 | BU14: 11.700203 | BV14: 0.78142927 | BW14: 0 | BX14: 0 | BY14: 1.6538016 | BZ14: 0 | CA14: 72.353972 | CB14: 2.7381027 | CC14: 0.16730175 | CD14: 0 | CE14: 0.91625 | CG14: 84.164184 | CH14: 38.712539 | CI14: 1.2533013 | CJ14: 54.626455 | CK14: 14.049114 | CL14: 1.4532014 | CM14: 0 | CN14: 3.0981031 | CO14: 25.332625 | CP14: 6.6905067 | CQ14: 0 | CR14: 1.1855012 | CS14: 9.4262094 | CT14: 88.854889 | CU14: 4.3934044 | CV14: 1.4098014 | CW14: 0 | CX14: 68.268468 | CY14: 6.8534069 | CZ14: 2.2128022 | DA14: 80.19758 | DB14: 50.823551 | DC14: 1.3977014 | DD14: 47.245347 | DE14: 79.57688 | DF14: 99.466599 | DG14: 6.046322 | DH14: 99.466599 | DI14: 98.281098 | DJ14: 1.1855012 | DK14: 37.395137 | DL14: 1.4308014 | DM14: 21.175321 | DN14: 40.583741 | DO14: 23.310023 | DP14: 12.966713 | DQ14: 5.0177159 | DR14: 99.466599 | DS14: 25.676626 | DT14: 30.647631 | DU14: 0 | DV14: 3.1652032 | DW14: 22.301822 | DX14: 36.078236 | DY14: 4.1408042 | DZ14: 5.8576059 | EA14: 97.318397 | EB14: 0.51490053 | EC14: 12.646251 | EE14: 0 | EF14: 24.571925 | EG14: 97.083197 | EH14: 4.2082441 | EI14: 91.103491 | EJ14: 10.46241 | EK14: 55.156555 | EL14: 33.847634 | EM14: 15.906816 | EN14: 13.872814 | EO14: 730795.34 | EP14: 72.634673 | EQ14: 753892.45 | ER14: 91.730692 | ES14: 38.281638 | ET14: 34.547535 | EU14: 0 | EV14: 71.854172 | EW14: 0 | EX14: 35.618936 | EY14: 0 | EZ14: 0 | FA14: 85.263485 | FB14: 98.738399 | FC14: 32.218532 | FD14: 92.653193 | FE14: Not Aligned | FF14: 0 | FG14: 0 | FH14: 0.51490053 | FI14: 0.51490053 | FJ14: 98.951699 | FK14: 0 | FL14: 0 | FM14: Not Aligned | FN14: 0 | FO14: 0 | FP14: 0 | FQ14: 0 | FR14: 99.466599 | FS14: 0 | FT14: 0 | FU14: Not Aligned | FV14: 0 | FW14: 0 | FX14: 5.047005 | FY14: 5.047005 | FZ14: 94.419594 | GA14: 0 | GB14: 0 | GC14: Not Aligned | GD14: 0 | GE14: 0 | GF14: 0 | GG14: 0 | GH14: 99.466599 | GI14: 0 | GJ14: 0 | GK14: Aligned | GL14: 52.776653 | GM14: 52.776653 | GN14: 0 | GO14: 0 | GP14: 46.689947 | GQ14: 0 | GR14: 0 | GS14: Aligned | GT14: 7.9264079 | GU14: 8.5275085 | GV14: 1.2487013 | GW14: 1.2487013 | GX14: 89.69039 | GY14: 0.6011006 | GZ14: 0 | HA14: Not Aligned | HB14: 18.496118 | HC14: 19.011019 | HD14: 32.045932 | HE14: 6.7352067 | HF14: 48.409648 | HG14: 0.51490053 | HH14: 25.310725 | HI14: Aligned | HJ14: 11.656212 | HK14: 11.656212 | HL14: 1.6142016 | HM14: 1.6142016 | HN14: 86.196186 | HO14: 0 | HP14: 0 | HQ14: Aligned | HR14: 64.308464 | HS14: 66.983467 | HT14: 0 | HU14: 0 | HV14: 32.483133 | HW14: 2.6750027 | HX14: 0 | HY14: Aligned | HZ14: 36.098536 | IA14: 36.098536 | IB14: 0 | IC14: 0 | ID14: 63.368063 | IE14: 0 | IF14: 0 | IG14: Aligned | IH14: 5.7706058 | II14: 5.7706058 | IJ14: 4.3132043 | IK14: 4.3132043 | IL14: 89.382789 | IM14: 0 | IN14: 0 | IO14: Not Aligned | IP14: 18.021818 | IQ14: 18.622919 | IR14: 34.622035 | IS14: 9.3113093 | IT14: 46.221646 | IU14: 0.6011006 | IV14: 25.310725 | IW14: Not Aligned | IX14: 20.862421 | IY14: 21.377321 | IZ14: 29.83153 | JA14: 4.5208045 | JB14: 48.257748 | JC14: 0.51490053 | JD14: 25.310725 | JE14: Not Aligned | JF14: 1.1639012 | JG14: 1.1639012 | JH14: 5.047005 | JI14: 5.047005 | JJ14: 93.255693 | JK14: 0 | JL14: 0 | JM14: Not Aligned | JN14: 0 | JO14: 0 | JP14: 5.5619056 | JQ14: 5.5619056 | JR14: 93.904694 | JS14: 0 | JT14: 0 | JU14: Aligned | JV14: 10.35321 | JW14: 10.35321 | JX14: 0 | JY14: 0 | JZ14: 89.113389 | KA14: 0 | KB14: 0 | KC14: Not Aligned | KD14: 0 | KE14: 0 | KF14: 0 | KG14: 0 | KH14: 99.466599 | KI14: 0 | KJ14: 0 | KK14: 99.466599 | KL14: 1.3190087 | KM14: 17.060217 | KN14: 6.5350065 | KO14: Equity | KP14: Exchange Traded Funds | KQ14: USA | KR14: 27.799582 | KS14: 99.804049 | KT14: 99.547753 | KU14: 6.6026332 | KV14: 6.2236971 | KW14: 0 | KX14: 71.748172 | KZ14: 7.7314886 | LA14: 90.538927 | LB14: 6.8828256 | LC14: 85.714286 | LD14: AA | LE14: 18.444672 | LF14: 53.177653 | LG14: 18.570519 | LH14: 0 | LI14: 2.4592025 | LJ14: 6.8957069 | LK14: 0 | LL14: 0.45224656 | LM14: 5.424105 | LN14: 0.45224656 | LO14: 23.595224 | LP14: 69.417523 | LQ14: 7.2102064 | LR14: 46.762064 | LS14: Global | LT14: 6.7188459 | LU14: 35.664713 | LV14: 68 | LW14: 1 | LX14: 66 | LY14: T | LZ14: The Fund seeks investment results that correspond to the S&P Global Utilities Sector Index that deems to be part of the utilities sector of the economy. The Underlying Index is a subset of the S&P Global 1200, which is designed to measure the performance of large-capitalization stocks from major global markets. | MA14: 46203 | MB14: Equity Sector Utilities | MC14: 98 | MD14: BlackRock Fund Advisors | ME14: iShares Global Utilities ETF | MF14: 5.8099446 | MG14: 17.120977 | MH14: 322841753 | MI14: 7.7314886 | MJ14: 90.538927 | MK14: 85.714286 | ML14: 6.7933404 | MM14: T | MN14: 0 | MO14: 0 | MP14: 0 | MQ14: 0 | MR14: 0.62450062 | MS14: 0 | MT14: 0 | MU14: 0 | MV14: 0 | MW14: 0 | MX14: 0 | MY14: 0 | MZ14: 0 | NA14: 0 | NB14: 0 | NC14: 0 | ND14: 0 | NE14: 0 | NF14: 0 | NG14: 0 | NH14: 0 | NI14: 0 | NJ14: 0 | NK14: 0 | NL14: 0 | NM14: 0 | NN14: 0 | NO14: 0 | NP14: 0 | NQ14: 0 | NR14: 0 | NS14: 0 | NT14: 0 | NU14: 0 | NV14: 0 | NW14: 0 | NX14: 20.584221 | NY14: 0 | NZ14: 0 | OA14: 0 | OB14: 0 | OC14: 0 | OD14: 0 | OE14: 0 | OF14: 0 | OG14: 0 | OH14: 3.947704 | OI14: 0.45610046 | OJ14: 19.503619 | OK14: 0 | OL14: 3.947704 | OM14: 85.429985 | ON14: 0 | OO14: 0 | OP14: 0 | OQ14: 0 | OR14: 0 | OS14: 4.0736041 | OT14: 61.510362 | OU14: 61.054261 | OV14: 56.624757 | OW14: 58.434758 | OX14: 0 | OY14: 0 | OZ14: 0 | PA14: 0 | PB14: 0 | PC14: 0 | PD14: 0 | PE14: 24.628525 | PF14: 0 | PG14: 0 | PH14: 0 | PI14: 0 | PJ14: 0 | PK14: 0 | PL14: 0 | PM14: 3.947704 | PN14: 0 | PO14: 0.51490053 | PP14: 0 | PQ14: 3.947704 | PR14: 0 | PS14: 0 | PT14: 6.245e-05 | PU14: 0 | PV14: 0 | PW14: 0 | PX14: 0 | PY14: 10.12395 | PZ14: 0 | QA14: 61.054261 | QB14: 1.9324019 | QC14: 0 | QD14: 0 | QE14: 0 | QF14: 9.9020099 | QG14: 0 | QH14: 0 | QI14: 0 | QJ14: 0 | QK14: 0
A15: 40111274 | B15: iShares Global Materials ETF | C15: US4642886950 | D15: Matched | E15: US4642886950 | F15: 35594120 | G15: MXI | H15: 207.50298 | I15: 99.7483 | J15: 747.8458 | K15: 99.7483 | L15: 945.34145 | M15: 99.7483 | N15: 197.49565 | O15: 99.7483 | P15: 38.038624 | Q15: 0.61856822 | R15: 3.6322247 | S15: 5.8719873 | T15: 34.447331 | U15: 0.06607025 | V15: 18.839662 | W15: 533.71064 | X15: 99.7483 | Y15: 1976.9594 | Z15: 99.7483 | AA15: 2429.1692 | AB15: 99.7483 | AC15: 452.21032 | AD15: 99.7483 | AE15: 202.59174 | AF15: 0.02705125 | AG15: 9077.5183 | AH15: 22683.305 | AI15: 4509.569 | AJ15: 17.714365 | AK15: 19.085762 | AL15: Strongly Misaligned | AM15: 99.7483 | AN15: 13.175274 | AO15: 49.7729 | AP15: 3.6 | AQ15: 79.572441 | AR15: 75.362149 | AS15: 99.7483 | AT15: 19.995744 | AU15: 38.994322 | AV15: 99.7483 | AW15: 0 | AX15: 5.9177882 | AY15: 0 | AZ15: 0 | BA15: 9.98538 | BB15: 24.651851 | BC15: 0 | BD15: 4.9777901 | BE15: 0.79119842 | BF15: 14.015472 | BG15: 0 | BH15: 0.22812783 | BI15: 0 | BJ15: 0 | BK15: 0.24085966 | BL15: 1.7958193 | BM15: 0 | BN15: 0.24110836 | BO15: 0.00191088 | BP15: 0.70751392 | BQ15: 0 | BR15: 0.20200856 | BS15: 0.44502779 | BT15: 0.31193806 | BU15: 2.2408471 | BV15: 0.30737985 | BW15: 0 | BX15: 6.8308863 | BY15: 8.4406831 | BZ15: 1.3261973 | CA15: 29.398441 | CB15: 13.927772 | CC15: 2.0424988 | CD15: 0.44138694 | CE15: 0.49627042 | CG15: 54.83929 | CH15: 20.960758 | CI15: 0 | CJ15: 21.310857 | CK15: 41.613317 | CL15: 36.639427 | CM15: 3.2956934 | CN15: 20.333359 | CO15: 16.606967 | CP15: 3.0966938 | CQ15: 0 | CR15: 6.2160876 | CS15: 14.379971 | CT15: 79.152242 | CU15: 7.4019852 | CV15: 3.2064936 | CW15: 0.76709846 | CX15: 48.631803 | CY15: 12.707175 | CZ15: 7.506285 | DA15: 81.207338 | DB15: 36.328627 | DC15: 2.2324955 | DD15: 61.187178 | DE15: 61.719177 | DF15: 99.7483 | DG15: 5.3093633 | DH15: 99.7483 | DI15: 93.532213 | DJ15: 6.2160876 | DK15: 37.551325 | DL15: 0 | DM15: 16.499367 | DN15: 32.694035 | DO15: 50.554899 | DP15: 0 | DQ15: 4.6200815 | DR15: 99.7483 | DS15: 15.942868 | DT15: 18.680263 | DU15: 1.6441967 | DV15: 7.2621855 | DW15: 12.112876 | DX15: 29.75674 | DY15: 2.2194955 | DZ15: 2.6049948 | EA15: 87.610825 | EB15: 1.5403969 | EC15: 12.567237 | ED15: 5.5608308 | EE15: 0.98109804 | EF15: 11.889576 | EG15: 87.329825 | EH15: 4.3188342 | EI15: 91.476717 | EJ15: 67.372365 | EK15: 0 | EL15: 32.375935 | EM15: 85.487829 | EN15: 20.940358 | EO15: 31357.44 | EP15: 84.585331 | EQ15: 14823.559 | ER15: 94.017612 | ES15: 21.395457 | ET15: 42.761014 | EU15: 48.708603 | EV15: 73.581553 | EW15: 14.169472 | EX15: 36.058328 | EY15: 0 | EZ15: 46.601907 | FA15: 98.605903 | FB15: 96.680507 | FC15: 68.705063 | FD15: 97.916804 | FE15: Not Aligned | FF15: 2.8252944 | FG15: 2.8252944 | FH15: 6.6778866 | FI15: 3.9535921 | FJ15: 90.24512 | FK15: 0 | FL15: 2.7242946 | FM15: Not Aligned | FN15: 2.1265957 | FO15: 2.1265957 | FP15: 6.5873868 | FQ15: 6.5873868 | FR15: 91.034318 | FS15: 0 | FT15: 0 | FU15: Not Aligned | FV15: 3.1286937 | FW15: 3.1286937 | FX15: 10.960978 | FY15: 9.2209815 | FZ15: 85.658629 | GA15: 0 | GB15: 1.7399965 | GC15: Not Aligned | GD15: 0 | GE15: 0 | GF15: 12.478175 | GG15: 11.782576 | GH15: 87.270125 | GI15: 0 | GJ15: 0.69559861 | GK15: Not Aligned | GL15: 57.196886 | GM15: 57.196886 | GN15: 0.69559861 | GO15: 0 | GP15: 41.855816 | GQ15: 0 | GR15: 0.69559861 | GS15: Not Aligned | GT15: 25.329349 | GU15: 27.653245 | GV15: 4.4563911 | GW15: 2.7163946 | GX15: 67.638665 | GY15: 2.3238953 | GZ15: 1.7399965 | HA15: Aligned | HB15: 20.354659 | HC15: 20.354659 | HD15: 2.9014942 | HE15: 2.9014942 | HF15: 76.492147 | HG15: 0 | HH15: 0 | HI15: Not Aligned | HJ15: 27.070046 | HK15: 27.070046 | HL15: 2.4355951 | HM15: 0 | HN15: 70.24266 | HO15: 0 | HP15: 2.4355951 | HQ15: Aligned | HR15: 18.393063 | HS15: 18.393063 | HT15: 8.9369821 | HU15: 8.9369821 | HV15: 72.418255 | HW15: 0 | HX15: 0 | HY15: Not Aligned | HZ15: 52.253995 | IA15: 52.253995 | IB15: 2.7242946 | IC15: 0 | ID15: 44.77001 | IE15: 0 | IF15: 2.7242946 | IG15: Not Aligned | IH15: 5.1474897 | II15: 5.1474897 | IJ15: 27.598845 | IK15: 23.134554 | IL15: 67.001966 | IM15: 0 | IN15: 4.4642911 | IO15: Not Aligned | IP15: 26.733547 | IQ15: 26.932646 | IR15: 5.7404885 | IS15: 4.000492 | IT15: 67.075166 | IU15: 0.1990996 | IV15: 1.7399965 | IW15: Aligned | IX15: 18.535563 | IY15: 18.535563 | IZ15: 2.4265952 | JA15: 2.4265952 | JB15: 78.786142 | JC15: 0 | JD15: 0 | JE15: Not Aligned | JF15: 0 | JG15: 0 | JH15: 16.941266 | JI15: 13.003774 | JJ15: 82.807034 | JK15: 0 | JL15: 3.9374921 | JM15: Not Aligned | JN15: 0 | JO15: 0 | JP15: 27.553745 | JQ15: 25.813748 | JR15: 72.194556 | JS15: 0 | JT15: 1.7399965 | JU15: Not Aligned | JV15: 6.984386 | JW15: 6.984386 | JX15: 2.7242946 | JY15: 0 | JZ15: 90.03962 | KA15: 0 | KB15: 2.7242946 | KC15: Not Aligned | KD15: 23.854452 | KE15: 23.854452 | KF15: 2.7242946 | KG15: 0 | KH15: 73.169554 | KI15: 0 | KJ15: 2.7242946 | KK15: 99.7483 | KL15: 1.2815628 | KM15: 18.267263 | KN15: 2.2027956 | KO15: Equity | KP15: Exchange Traded Funds | KQ15: USA | KR15: 51.648448 | KS15: 99.939627 | KT15: 99.775352 | KU15: 4.2606225 | KV15: 5.8431178 | KW15: 0.30809938 | KX15: 47.818804 | KZ15: 7.0156253 | LA15: 70.320135 | LB15: 5.5366787 | LC15: 83.673469 | LD15: A | LE15: 31.181489 | LF15: 30.552239 | LG15: 17.266565 | LH15: 0.30809938 | LI15: 3.6112928 | LJ15: 16.855666 | LK15: 0 | LL15: 0.22464825 | LM15: 4.8891948 | LN15: 0.22464825 | LO15: 20.778158 | LP15: 76.794398 | LQ15: 4.8563405 | LR15: 44.90597 | LS15: Global | LT15: 6.8814716 | LU15: 33.147742 | LV15: 95 | LW15: 1 | LX15: 93 | LY15: T | LZ15: The Fund seeks to track the investment results of the S&P Global 1200 Materials (Sector) Capped Idx composed of global equities in the materials sector. The Fund generally invests at least 90% of its assets in securities of the Underlying Index and in depositary receipts representing securities of the Underlying Index. | MA15: 46203 | MB15: Equity Sector Materials | MC15: 147 | MD15: BlackRock Fund Advisors | ME15: iShares Global Materials ETF | MF15: 5.1725592 | MG15: 21.721639 | MH15: 339587757 | MI15: 7.0156253 | MJ15: 70.320135 | MK15: 83.673469 | ML15: 5.5979797 | MM15: T | MN15: 0 | MO15: 0 | MP15: 0 | MQ15: 0 | MR15: 7.4188852 | MS15: 2.1101958 | MT15: 0 | MU15: 0 | MV15: 21.078058 | MW15: 21.078058 | MX15: 21.078058 | MY15: 0 | MZ15: 0 | NA15: 0 | NB15: 0 | NC15: 6.6276867 | ND15: 0 | NE15: 0 | NF15: 0 | NG15: 0 | NH15: 0 | NI15: 0 | NJ15: 0 | NK15: 0 | NL15: 0 | NM15: 0 | NN15: 0 | NO15: 0 | NP15: 0 | NQ15: 9.2955814 | NR15: 1.0956978 | NS15: 0.89189822 | NT15: 0 | NU15: 0 | NV15: 0 | NW15: 0 | NX15: 20.509359 | NY15: 0 | NZ15: 0 | OA15: 0 | OB15: 0 | OC15: 3.4424931 | OD15: 3.4424931 | OE15: 1.8685963 | OF15: 1.8685963 | OG15: 4.4642911 | OH15: 29.85444 | OI15: 12.294975 | OJ15: 17.530565 | OK15: 4.4642911 | OL15: 29.85444 | OM15: 23.313453 | ON15: 0.69559861 | OO15: 21.328357 | OP15: 0 | OQ15: 0 | OR15: 0 | OS15: 8.018484 | OT15: 8.0300839 | OU15: 0 | OV15: 0 | OW15: 0 | OX15: 0 | OY15: 0 | OZ15: 0 | PA15: 0 | PB15: 0 | PC15: 0 | PD15: 0 | PE15: 0 | PF15: 4.4642911 | PG15: 0 | PH15: 0 | PI15: 0 | PJ15: 4.4642911 | PK15: 0.69559861 | PL15: 0 | PM15: 29.85444 | PN15: 1.8685963 | PO15: 7.3877852 | PP15: 0 | PQ15: 22.797454 | PR15: 21.328357 | PS15: 0 | PT15: 0.09918637 | PU15: 0.01765958 | PV15: 0 | PW15: 0 | PX15: 1.0592059 | PY15: 0.37646248 | PZ15: 0.07790153 | QA15: 10.423679 | QB15: 11.427677 | QC15: 0 | QD15: 0 | QE15: 0 | QF15: 13.636373 | QG15: 4.6979906 | QH15: 0 | QI15: 0 | QJ15: 0 | QK15: 1.0956978
A16: 40114659 | B16: iShares iBoxx $ High Yield Corporate Bond ETF | C16: US4642885135 | D16: Matched | E16: US4642885135 | F16: 30093152 | G16: HYG | H16: 94.323512 | I16: 76.768886 | J16: 504.68547 | K16: 76.781441 | L16: 694.59978 | M16: 76.781441 | N16: 189.91432 | O16: 76.781441 | P16: 15.295809 | Q16: 4.8275017 | R16: 3.3902053 | S16: 0.70226911 | T16: 15.124336 | U16: 1.9722645 | V16: 2.688576 | W16: 178.55384 | X16: 77.611906 | Y16: 781.64317 | Z16: 78.715673 | AA16: 1052.9398 | AB16: 78.715673 | AC16: 271.29697 | AD16: 78.715673 | AE16: 202.59174 | AF16: 0.30118517 | AG16: 7779.967 | AH16: 19155.488 | AI16: 3525.2825 | AJ16: 7.1420032 | AK16: 21.180805 | AL16: Strongly Misaligned | AM16: 76.422552 | AN16: 21.572773 | AO16: 26.993366 | AP16: 3.8 | AQ16: 45.087849 | AR16: 18.981243 | AS16: 53.98195 | AT16: 7.0273864 | AU16: 16.659725 | AV16: 77.611906 | AW16: 1.0737764 | AX16: 4.3504036 | AY16: 0.08120329 | AZ16: 0.22308485 | BA16: 10.004344 | BB16: 13.863941 | BC16: 1.4341596 | BD16: 1.5099825 | BE16: 1.9784707 | BF16: 1.8750486 | BG16: 0.02488777 | BH16: 0.57920378 | BI16: 0.00014617 | BJ16: 0.00216392 | BK16: 1.4103993 | BL16: 2.471991 | BM16: 0.21408 | BN16: 0.57563903 | BO16: 0.72441606 | BP16: 0.16052055 | BQ16: 0.00106281 | BR16: 0.0628117 | BS16: 1.3911275 | BT16: 0.04054604 | BU16: 3.8631147 | BV16: 0.0672414 | BW16: 0.18900935 | BX16: 1.4051655 | BY16: 5.7724076 | BZ16: 0.26831955 | CA16: 18.918173 | CB16: 1.5959683 | CC16: 0.23946335 | CD16: 0.04940113 | CE16: 0.09975579 | CG16: 30.246977 | CH16: 4.2057322 | CI16: 25.575049 | CJ16: 27.233688 | CK16: 16.708945 | CL16: 0.57808766 | CM16: 4.960873 | CN16: 0.25616398 | CO16: 11.263842 | CP16: 13.275392 | CQ16: 0.6134584 | CR16: 2.0702354 | CS16: 10.025168 | CT16: 23.698805 | CU16: 18.919867 | CV16: 15.770873 | CW16: 0.90877932 | CX16: 53.437539 | CY16: 16.591176 | CZ16: 7.301321 | DA16: 37.457829 | DB16: 37.354905 | DC16: 15.512717 | DD16: 17.032762 | DE16: 42.612992 | DF16: 77.328143 | DG16: 4.5129115 | DH16: 74.036172 | DI16: 81.688709 | DJ16: 6.3146263 | DK16: 28.900498 | DL16: 5.3434749 | DM16: 48.208944 | DN16: 6.8310394 | DO16: 12.322972 | DP16: 1.3734813 | DQ16: 5.4908767 | DR16: 74.079912 | DS16: 19.877866 | DT16: 13.592433 | DU16: 4.7655866 | DV16: 15.059772 | DW16: 17.475246 | DX16: 23.225633 | DY16: 17.376307 | DZ16: 8.1246127 | EA16: 54.790296 | EB16: 0.62710856 | EC16: 2.5699285 | ED16: 4.3169436 | EE16: 6.7545189 | EF16: 15.918135 | EG16: 42.964508 | EH16: 3.24134 | EI16: 16.26975 | EJ16: 11.067161 | EK16: 39.857261 | EL16: 23.866791 | EM16: 10.625475 | EN16: 1.2515269 | EO16: 9839.5868 | EP16: 13.005179 | EQ16: 20440.783 | ER16: 21.106477 | ES16: 17.767079 | ET16: 13.598511 | EU16: 1.3771678 | EV16: 29.155765 | EW16: 1.2270165 | EX16: 14.124688 | EY16: 0.76201559 | EZ16: 1.1876603 | FA16: 43.738679 | FB16: 53.977167 | FC16: 13.772475 | FD16: 48.69467 | FE16: Not Aligned | FF16: 3.6610225 | FG16: 3.6610225 | FH16: 2.2900322 | FI16: 1.9555544 | FJ16: 68.374958 | FK16: 0 | FL16: 0.33447781 | FM16: Aligned | FN16: 0.48413098 | FO16: 1.3157921 | FP16: 0.29243144 | FQ16: 0.29243144 | FR16: 72.717789 | FS16: 0.8316611 | FT16: 0 | FU16: Aligned | FV16: 2.0943473 | FW16: 2.0943473 | FX16: 1.0442842 | FY16: 1.0442842 | FZ16: 71.187381 | GA16: 0 | GB16: 0 | GC16: Not Aligned | GD16: 0 | GE16: 0 | GF16: 0 | GG16: 0 | GH16: 74.326013 | GI16: 0 | GJ16: 0 | GK16: Aligned | GL16: 21.301564 | GM16: 21.301564 | GN16: 0 | GO16: 0 | GP16: 53.024449 | GQ16: 0 | GR16: 0 | GS16: Aligned | GT16: 2.6979417 | GU16: 2.7458666 | GV16: 0.60827734 | GW16: 0.60827734 | GX16: 70.971869 | GY16: 0.04792488 | GZ16: 0 | HA16: Not Aligned | HB16: 11.883378 | HC16: 12.245156 | HD16: 8.0294604 | HE16: 0 | HF16: 54.051396 | HG16: 0.36177807 | HH16: 8.0294604 | HI16: Not Aligned | HJ16: 3.3258473 | HK16: 3.3258473 | HL16: 0.79160747 | HM16: 0.67164581 | HN16: 70.208558 | HO16: 0 | HP16: 0.11996166 | HQ16: Aligned | HR16: 9.4894256 | HS16: 9.5573773 | HT16: 3.936516 | HU16: 3.936516 | HV16: 60.832119 | HW16: 0.0679517 | HX16: 0 | HY16: Not Aligned | HZ16: 4.795278 | IA16: 4.795278 | IB16: 3.2814097 | IC16: 2.9469319 | ID16: 66.249325 | IE16: 0 | IF16: 0.33447781 | IG16: Not Aligned | IH16: 1.5250275 | II16: 1.5250275 | IJ16: 1.5486413 | IK16: 1.4286796 | IL16: 71.252344 | IM16: 0 | IN16: 0.11996166 | IO16: Not Aligned | IP16: 9.3435587 | IQ16: 10.020286 | IR16: 8.805425 | IS16: 0.77596463 | IT16: 55.500302 | IU16: 0.67672724 | IV16: 8.0294604 | IW16: Not Aligned | IX16: 10.685954 | IY16: 11.162911 | IZ16: 8.0294604 | JA16: 0 | JB16: 55.133642 | JC16: 0.47695721 | JD16: 8.0294604 | JE16: Not Aligned | JF16: 0 | JG16: 0 | JH16: 2.7894075 | JI16: 1.71045 | JJ16: 71.536605 | JK16: 0 | JL16: 1.0789575 | JM16: Not Aligned | JN16: 0 | JO16: 0 | JP16: 2.0500093 | JQ16: 2.0500093 | JR16: 72.276003 | JS16: 0 | JT16: 0 | JU16: Not Aligned | JV16: 3.5677634 | JW16: 3.5677634 | JX16: 1.4478097 | JY16: 1.3278481 | JZ16: 69.31044 | KA16: 0 | KB16: 0.11996166 | KC16: Not Aligned | KD16: 0.96955725 | KE16: 0.96955725 | KF16: 0.99307132 | KG16: 0.87310966 | KH16: 72.363384 | KI16: 0 | KJ16: 0.11996166 | KK16: 74.326013 | KL16: -0.6454861 | KM16: -11.894338 | KN16: 13.186716 | KO16: Bond | KP16: Exchange Traded Funds | KQ16: USA | KR16: 44.176166 | KS16: 75.104494 | KT16: 74.627198 | KU16: 4.7901862 | KV16: 5.8955409 | KW16: 11.684505 | KX16: 18.766527 | KZ16: 5.426835 | LA16: 22.323412 | LB16: 5.5413926 | LC16: 42.821782 | LD16: BBB | LE16: 17.175825 | LF16: 15.149942 | LG16: 3.616585 | LH16: 9.4239649 | LI16: 11.215618 | LJ16: 15.784723 | LK16: 2.26054 | LL16: 25.372802 | LM16: 4.4125782 | LN16: 25.372802 | LO16: 12.976883 | LP16: 48.4636 | LQ16: 4.7722988 | LR16: 15.180986 | LS16: United States of America | LT16: 5.7823951 | LU16: 29.855498 | LV16: 1336 | LW16: 1 | LX16: 1326 | LY16: T | LZ16: The Fund seeks to track the investment results of the Markit iBoxx USD Liquid High Yield Index composed of US dollar-denominated, high yield corporate bonds. The Fund invests at least 90% of its assets in the component securities of the Underlying Index and may invest up to 10% of its assets in certain futures. | MA16: 46203 | MB16: Bond USD High Yield | MC16: 404 | MD16: BlackRock Fund Advisors | ME16: iShares iBoxx $ High Yield Corporate Bond ETF | MF16: 4.2773416 | MG16: 29.590714 | MH16: 17626117386 | MI16: 5.426835 | MJ16: 22.323412 | MK16: 42.821782 | ML16: 4.9801425 | MM16: T | MN16: 5.517539 | MO16: 0.67602979 | MP16: 0 | MQ16: 0 | MR16: 11.878994 | MS16: 0.59741705 | MT16: 0 | MU16: 0 | MV16: 5.0296218 | MW16: 4.695941 | MX16: 3.3915075 | MY16: 0 | MZ16: 0.1189653 | NA16: 0.1189653 | NB16: 0 | NC16: 7.9941893 | ND16: 0 | NE16: 0.1827323 | NF16: 0.39724845 | NG16: 0.1827323 | NH16: 0.1827323 | NI16: 0.1827323 | NJ16: 0.1827323 | NK16: 0 | NL16: 0.39724845 | NM16: 0 | NN16: 0 | NO16: 0 | NP16: 0 | NQ16: 0 | NR16: 3.4959259 | NS16: 2.6606779 | NT16: 0 | NU16: 0.15881967 | NV16: 0.21451615 | NW16: 0 | NX16: 3.3176772 | NY16: 5.9755653 | NZ16: 5.2511125 | OA16: 2.7037206 | OB16: 3.0022299 | OC16: 0.08927379 | OD16: 0.08927379 | OE16: 0 | OF16: 0 | OG16: 0.11996166 | OH16: 3.0824368 | OI16: 0.79838271 | OJ16: 2.9784169 | OK16: 0.11996166 | OL16: 0.62033331 | OM16: 24.926817 | ON16: 0 | OO16: 0.09365778 | OP16: 0 | OQ16: 0 | OR16: 0 | OS16: 0.67184509 | OT16: 1.4419312 | OU16: 1.2165547 | OV16: 1.1351521 | OW16: 1.1351521 | OX16: 0.10382064 | OY16: 0.10382064 | OZ16: 0.10382064 | PA16: 0.10382064 | PB16: 0.10820462 | PC16: 0.10820462 | PD16: 0.10820462 | PE16: 3.087319 | PF16: 0.11996166 | PG16: 0 | PH16: 0 | PI16: 0 | PJ16: 0.11996166 | PK16: 0 | PL16: 0 | PM16: 7.560474 | PN16: 3.664211 | PO16: 0.83225891 | PP16: 2.4436708 | PQ16: 0.52667553 | PR16: 0.09365778 | PS16: 0.04059099 | PT16: 0.26733469 | PU16: 0.21910062 | PV16: 0.02218772 | PW16: 2.25957 | PX16: 0.00088381 | PY16: 0.35580821 | PZ16: 0.18845366 | QA16: 7.5340705 | QB16: 0 | QC16: 0 | QD16: 0 | QE16: 0 | QF16: 0.6114657 | QG16: 6.7663756 | QH16: 0 | QI16: 0 | QJ16: 0 | QK16: 3.6083152
A17: 40118468 | B17: iShares Global Infrastructure ETF | C17: US4642883726 | D17: Matched | E17: US4642883726 | F17: 35655823 | G17: IGF | H17: 138.32673 | I17: 98.477405 | J17: 121.71788 | K17: 98.477405 | L17: 180.13041 | M17: 98.477405 | N17: 58.412529 | O17: 98.477405 | P17: 64.389507 | Q17: 17.238062 | R17: 7.3190324 | S17: 0.42458556 | T17: 64.013508 | U17: 8.4951478 | V17: 27.230118 | W17: 809.97363 | X17: 98.477405 | Y17: 587.94999 | Z17: 98.477405 | AA17: 911.77848 | AB17: 98.477405 | AC17: 323.8275 | AD17: 98.477405 | AE17: 202.59174 | AF17: 0.06439661 | AG17: 1691.4914 | AH17: 4152.1265 | AI17: 2618.9323 | AJ17: 16.74415 | AK17: 22.076634 | AL17: Misaligned | AM17: 98.477405 | AN17: 29.780411 | AO17: 29.87621 | AP17: 2.2 | AQ17: 64.703306 | AR17: 47.766857 | AS17: 97.886006 | AT17: 19.617825 | AU17: 30.869207 | AV17: 98.477405 | AW17: 0 | AX17: 28.374215 | AY17: 0 | AZ17: 0 | BA17: 20.589938 | BB17: 33.147701 | BC17: 1.8961943 | BD17: 0 | BE17: 1.1861964 | BF17: 0 | BG17: 0 | BH17: 4.3615928 | BI17: 0 | BJ17: 0 | BK17: 1.0619427 | BL17: 5.5456377 | BM17: 0.00100735 | BN17: 0 | BO17: 0.00616822 | BP17: 0 | BQ17: 0 | BR17: 0 | BS17: 0.00616822 | BT17: 0 | BU17: 5.5518059 | BV17: 0.12109484 | BW17: 0 | BX17: 0 | BY17: 1.1861964 | BZ17: 0 | CA17: 34.333897 | CB17: 0.3663989 | CC17: 0.01413666 | CD17: 0 | CE17: 0.12131864 | CG17: 72.811782 | CH17: 30.464309 | CI17: 0.5650983 | CJ17: 45.142665 | CK17: 22.322233 | CL17: 7.319578 | CM17: 2.7782917 | CN17: 2.0955937 | CO17: 16.59495 | CP17: 14.295857 | CQ17: 0 | CR17: 5.337884 | CS17: 10.456469 | CT17: 82.496552 | CU17: 20.528438 | CV17: 6.3716809 | CW17: 0 | CX17: 43.31237 | CY17: 12.534262 | CZ17: 14.797856 | DA17: 73.733679 | DB17: 47.046459 | DC17: 6.4834806 | DD17: 44.760966 | DE17: 69.696591 | DF17: 98.290905 | DG17: 5.4454319 | DH17: 98.290905 | DI17: 95.358214 | DJ17: 3.1191906 | DK17: 25.402824 | DL17: 13.106661 | DM17: 47.597157 | DN17: 15.438254 | DO17: 16.350351 | DP17: 5.984982 | DQ17: 4.9423129 | DR17: 98.477405 | DS17: 18.110346 | DT17: 46.033062 | DU17: 0 | DV17: 0 | DW17: 28.859013 | DX17: 23.518929 | DY17: 7.4154777 | DZ17: 5.5819832 | EA17: 94.501717 | EB17: 0.25869922 | EC17: 5.4696876 | EE17: 0 | EF17: 15.677653 | EG17: 85.282444 | EH17: 4.3266407 | EI17: 40.226979 | EJ17: 25.074925 | EK17: 32.037904 | EL17: 41.364576 | EM17: 14.759956 | EN17: 17.969846 | EO17: 431691.81 | EP17: 62.188113 | EQ17: 460453.06 | ER17: 76.917569 | ES17: 26.910119 | ET17: 36.985689 | EU17: 39.805881 | EV17: 59.031223 | EW17: 0.6984979 | EX17: 30.498309 | EY17: 0 | EZ17: 35.271094 | FA17: 78.591064 | FB17: 88.748434 | FC17: 43.40317 | FD17: 96.57361 | FE17: Not Aligned | FF17: 0 | FG17: 0 | FH17: 0.25869922 | FI17: 0.25869922 | FJ17: 97.622207 | FK17: 0 | FL17: 0 | FM17: Not Aligned | FN17: 0 | FO17: 0 | FP17: 0 | FQ17: 0 | FR17: 97.880906 | FS17: 0 | FT17: 0 | FU17: Not Aligned | FV17: 0 | FW17: 0 | FX17: 2.2647932 | FY17: 2.2647932 | FZ17: 95.616113 | GA17: 0 | GB17: 0 | GC17: Not Aligned | GD17: 0 | GE17: 0 | GF17: 0 | GG17: 0 | GH17: 97.880906 | GI17: 0 | GJ17: 0 | GK17: Aligned | GL17: 51.486346 | GM17: 51.486346 | GN17: 0 | GO17: 0 | GP17: 46.394561 | GQ17: 0 | GR17: 0 | GS17: Aligned | GT17: 9.1524725 | GU17: 9.5188714 | GV17: 0 | GW17: 0 | GX17: 88.362035 | GY17: 0.3663989 | GZ17: 0 | HA17: Not Aligned | HB17: 33.3576 | HC17: 33.616299 | HD17: 30.981207 | HE17: 1.3545959 | HF17: 33.2834 | HG17: 0.25869922 | HH17: 29.626611 | HI17: Aligned | HJ17: 21.634635 | HK17: 21.634635 | HL17: 0.99119703 | HM17: 0.99119703 | HN17: 75.255074 | HO17: 0 | HP17: 0 | HQ17: Aligned | HR17: 40.253979 | HS17: 44.044768 | HT17: 2.3132931 | HU17: 2.3132931 | HV17: 51.522845 | HW17: 3.7907886 | HX17: 0 | HY17: Aligned | HZ17: 50.640748 | IA17: 50.640748 | IB17: 0 | IC17: 0 | ID17: 47.240158 | IE17: 0 | IF17: 0 | IG17: Aligned | IH17: 6.0612818 | II17: 6.0612818 | IJ17: 4.8367855 | IK17: 4.8367855 | IL17: 86.982839 | IM17: 0 | IN17: 0 | IO17: Not Aligned | IP17: 16.184451 | IQ17: 16.55085 | IR17: 34.170798 | IS17: 4.5441864 | IT17: 47.159258 | IU17: 0.3663989 | IV17: 29.626611 | IW17: Not Aligned | IX17: 29.113113 | IY17: 29.371812 | IZ17: 30.981207 | JA17: 1.3545959 | JB17: 37.527887 | JC17: 0.25869922 | JD17: 29.626611 | JE17: Not Aligned | JF17: 0.3663989 | JG17: 0.3663989 | JH17: 2.2647932 | JI17: 2.2647932 | JJ17: 95.249714 | JK17: 0 | JL17: 0 | JM17: Not Aligned | JN17: 0 | JO17: 0 | JP17: 8.8085736 | JQ17: 8.8085736 | JR17: 89.072333 | JS17: 0 | JT17: 0 | JU17: Aligned | JV17: 8.8993733 | JW17: 8.8993733 | JX17: 0 | JY17: 0 | JZ17: 88.981533 | KA17: 0 | KB17: 0 | KC17: Aligned | KD17: 30.923107 | KE17: 30.923107 | KF17: 0 | KG17: 0 | KH17: 66.957799 | KI17: 0 | KJ17: 0 | KK17: 97.880906 | KL17: 1.7286184 | KM17: 22.200933 | KN17: 5.2877841 | KO17: Equity | KP17: Exchange Traded Funds | KQ17: USA | KR17: 36.634387 | KS17: 98.218894 | KT17: 97.945303 | KU17: 6.5546049 | KV17: 6.2934086 | KW17: 0.56219831 | KX17: 60.748718 | KZ17: 7.7862419 | LA17: 91.521824 | LB17: 7.2855028 | LC17: 64.918033 | LD17: AA | LE17: 26.109318 | LF17: 26.980219 | LG17: 33.768499 | LH17: 0.56219831 | LI17: 1.9636941 | LJ17: 8.5613743 | LK17: 0 | LL17: 2.054697 | LM17: 5.844143 | LN17: 2.054697 | LO17: 28.050916 | LP17: 64.606603 | LQ17: 7.1694528 | LR17: 34.133887 | LS17: Global | LT17: 6.3576477 | LU17: 37.479465 | LV17: 78 | LW17: 1 | LX17: 76 | LY17: T | LZ17: The Fund seeks investment results that correspond generally to the price and yield performance, before fees and expenses, of the S&P Global Infrastructure Index. The Fund seeks to track the performance of the stocks of large infrastructure companies around the world. | MA17: 46203 | MB17: Equity Theme - Infrastructure | MC17: 305 | MD17: BlackRock Fund Advisors | ME17: iShares Global Infrastructure ETF | MF17: 7.0602712 | MG17: 26.331951 | MH17: 10779330059 | MI17: 7.7862419 | MJ17: 91.521824 | MK17: 64.918033 | ML17: 6.8294571 | MM17: T | MN17: 0 | MO17: 0 | MP17: 0 | MQ17: 0 | MR17: 24.025328 | MS17: 0 | MT17: 0 | MU17: 0 | MV17: 0 | MW17: 0 | MX17: 0 | MY17: 0 | MZ17: 0 | NA17: 0 | NB17: 0 | NC17: 0 | ND17: 0 | NE17: 0 | NF17: 0 | NG17: 0 | NH17: 0 | NI17: 0 | NJ17: 0 | NK17: 0 | NL17: 0 | NM17: 0 | NN17: 0 | NO17: 0 | NP17: 0 | NQ17: 0 | NR17: 0 | NS17: 0 | NT17: 0 | NU17: 0 | NV17: 0 | NW17: 0 | NX17: 15.851752 | NY17: 0 | NZ17: 0 | OA17: 0 | OB17: 0 | OC17: 0 | OD17: 0 | OE17: 0 | OF17: 0 | OG17: 0 | OH17: 3.8455885 | OI17: 0 | OJ17: 15.458254 | OK17: 0 | OL17: 3.8455885 | OM17: 82.281053 | ON17: 0 | OO17: 0 | OP17: 0 | OQ17: 0 | OR17: 0 | OS17: 1.6052952 | OT17: 33.975298 | OU17: 33.898398 | OV17: 32.478903 | OW17: 32.737602 | OX17: 0 | OY17: 0 | OZ17: 0 | PA17: 0 | PB17: 0 | PC17: 0 | PD17: 0 | PE17: 11.950464 | PF17: 0 | PG17: 0 | PH17: 0 | PI17: 0 | PJ17: 0 | PK17: 0 | PL17: 0 | PM17: 3.8455885 | PN17: 0 | PO17: 0.25869922 | PP17: 0 | PQ17: 3.8455885 | PR17: 0 | PS17: 0 | PT17: 0.16346812 | PU17: 0 | PV17: 0 | PW17: 0 | PX17: 0 | PY17: 5.5224164 | PZ17: 0.04380739 | QA17: 33.898398 | QB17: 1.1607965 | QC17: 0 | QD17: 0 | QE17: 0 | QF17: 5.4673836 | QG17: 11.215566 | QH17: 0 | QI17: 0 | QJ17: 0 | QK17: 0
A18: 40119505 | B18: iShares MSCI ACWI ETF | C18: US4642882579 | D18: Matched | E18: US4642882579 | F18: 35665227 | G18: ACWI | H18: 33.99381 | I18: 99.398379 | J18: 187.1819 | K18: 99.398379 | L18: 256.30846 | M18: 99.398379 | N18: 69.12656 | O18: 99.398379 | P18: 13.496738 | Q18: 2.9473546 | R18: 9.6248152 | S18: 3.2655776 | T18: 13.132706 | U18: 1.5958633 | V18: 4.157271 | W18: 114.41789 | X18: 99.580795 | Y18: 510.40769 | Z18: 99.570599 | AA18: 766.57956 | AB18: 99.570599 | AC18: 256.17184 | AD18: 99.570599 | AE18: 202.59174 | AF18: 0.0415832 | AG18: 2456.1081 | AH18: 6118.6264 | AI18: 1915.1656 | AJ18: 28.2326 | AK18: 19.489757 | AL18: Misaligned | AM18: 99.264041 | AN18: 29.521402 | AO18: 22.113839 | AP18: 2.9 | AQ18: 88.541517 | AR18: 60.805486 | AS18: 96.780494 | AT18: 6.1339666 | AU18: 51.588863 | AV18: 99.580795 | AW18: 0.90298105 | AX18: 6.2666923 | AY18: 0.8621 | AZ18: 0.11714565 | BA18: 21.772198 | BB18: 25.706772 | BC18: 1.7540861 | BD18: 2.6470718 | BE18: 1.5551784 | BF18: 2.1875849 | BG18: 0.08354246 | BH18: 0.46256039 | BI18: 0.00845389 | BJ18: 0.01772064 | BK18: 6.0040858 | BL18: 6.8699078 | BM18: 0.230153 | BN18: 1.0041713 | BO18: 0.18004971 | BP18: 0.0745251 | BQ18: 0.15549046 | BR18: 0.11137691 | BS18: 1.5608748 | BT18: 0.03388788 | BU18: 8.419749 | BV18: 0.06469562 | BW18: 4.8666416 | BX18: 2.1151186 | BY18: 11.582925 | BZ18: 0.16862176 | CA18: 33.795719 | CB18: 2.7904053 | CC18: 0.14431983 | CD18: 0.04355121 | CE18: 0.08116189 | CG18: 58.261667 | CH18: 12.281701 | CI18: 2.4526619 | CJ18: 68.032733 | CK18: 26.91781 | CL18: 11.690975 | CM18: 11.964848 | CN18: 5.6002015 | CO18: 18.161473 | CP18: 17.205517 | CQ18: 0.23778967 | CR18: 7.2346431 | CS18: 26.621448 | CT18: 65.406151 | CU18: 17.212613 | CV18: 11.572131 | CW18: 2.0933287 | CX18: 66.735135 | CY18: 27.317425 | CZ18: 7.536803 | DA18: 68.628756 | DB18: 60.009356 | DC18: 12.840542 | DD18: 26.650134 | DE18: 56.94038 | DF18: 99.518923 | DG18: 5.9961059 | DH18: 99.440759 | DI18: 92.790145 | DJ18: 6.8068417 | DK18: 30.260959 | DL18: 2.1954813 | DM18: 66.932643 | DN18: 3.780246 | DO18: 15.335684 | DP18: 11.166819 | DQ18: 6.0463035 | DR18: 99.410873 | DS18: 36.123839 | DT18: 27.668162 | DU18: 0.56803643 | DV18: 1.8131587 | DW18: 22.367122 | DX18: 49.09592 | DY18: 16.598898 | DZ18: 5.2907452 | EA18: 64.238493 | EB18: 1.4039486 | EC18: 3.4709445 | ED18: 6.0500619 | EE18: 11.59532 | EF18: 20.885509 | EG18: 76.171556 | EH18: 4.564196 | EI18: 19.817305 | EJ18: 7.1823673 | EK18: 55.036563 | EL18: 37.110781 | EM18: 7.2615306 | EN18: 4.6406467 | EO18: 41695.61 | EP18: 45.902601 | EQ18: 34648.117 | ER18: 84.07389 | ES18: 32.964205 | ET18: 28.158834 | EU18: 5.5810104 | EV18: 62.752883 | EW18: 7.0283389 | EX18: 48.803455 | EY18: 1.7941675 | EZ18: 5.288746 | FA18: 90.182955 | FB18: 98.985771 | FC18: 38.169489 | FD18: 94.108833 | FE18: Not Aligned | FF18: 7.0989062 | FG18: 7.0989062 | FH18: 14.673392 | FI18: 14.587232 | FJ18: 77.652169 | FK18: 0 | FL18: 0.08616002 | FM18: Aligned | FN18: 1.1479674 | FO18: 1.204741 | FP18: 0.55664172 | FQ18: 0.55664172 | FR18: 97.663084 | FS18: 0.05677367 | FT18: 0 | FU18: Not Aligned | FV18: 6.2760879 | FW18: 6.2760879 | FX18: 6.3570503 | FY18: 5.6970565 | FZ18: 86.791329 | GA18: 0 | GB18: 0.65999376 | GC18: Not Aligned | GD18: 0.01909114 | GE18: 0.01909114 | GF18: 3.5610477 | GG18: 3.5348598 | GH18: 95.844328 | GI18: 0 | GJ18: 0.02618785 | GK18: Not Aligned | GL18: 44.368613 | GM18: 44.368613 | GN18: 0.0415807 | GO18: 0.01539285 | GP18: 55.014274 | GQ18: 0 | GR18: 0.02618785 | GS18: Not Aligned | GT18: 8.7980178 | GU18: 8.9730366 | GV18: 0.96385276 | GW18: 0.9098778 | GX18: 89.487578 | GY18: 0.1750188 | GZ18: 0.05397496 | HA18: Not Aligned | HB18: 35.229254 | HC18: 35.321411 | HD18: 4.7128133 | HE18: 0.38961922 | HF18: 59.390243 | HG18: 0.09215726 | HH18: 4.3231941 | HI18: Not Aligned | HJ18: 16.199083 | HK18: 16.212977 | HL18: 7.1629764 | HM18: 7.0828136 | HN18: 76.048514 | HO18: 0.01389355 | HP18: 0.08016281 | HQ18: Aligned | HR18: 17.739669 | HS18: 18.646748 | HT18: 16.058549 | HU18: 16.058549 | HV18: 64.71917 | HW18: 0.90707913 | HX18: 0 | HY18: Not Aligned | HZ18: 28.424011 | IA18: 28.424011 | IB18: 7.9151274 | IC18: 7.8289674 | ID18: 63.085328 | IE18: 0 | IF18: 0.08616002 | IG18: Not Aligned | IH18: 3.3460474 | II18: 3.3460474 | IJ18: 12.041513 | IK18: 11.903277 | IL18: 84.036907 | IM18: 0 | IN18: 0.13823586 | IO18: Not Aligned | IP18: 20.429221 | IQ18: 27.131011 | IR18: 6.2033217 | IS18: 1.8261527 | IT18: 66.090134 | IU18: 6.7017904 | IV18: 4.377169 | IW18: Not Aligned | IX18: 40.884929 | IY18: 40.985483 | IZ18: 4.7528947 | JA18: 0.42970062 | JB18: 53.68609 | JC18: 0.10055335 | JD18: 4.3231941 | JE18: Not Aligned | JF18: 0.05227575 | JG18: 0.05227575 | JH18: 4.9731924 | JI18: 4.8263606 | JJ18: 94.398999 | JK18: 0 | JL18: 0.14683187 | JM18: Not Aligned | JN18: 0 | JO18: 0 | JP18: 6.3765413 | JQ18: 6.3225663 | JR18: 93.047926 | JS18: 0 | JT18: 0.05397496 | JU18: Not Aligned | JV18: 12.654428 | JW18: 12.654428 | JX18: 6.8818068 | JY18: 6.7956468 | JZ18: 79.888232 | KA18: 0 | KB18: 0.08616002 | KC18: Not Aligned | KD18: 1.8705321 | KE18: 1.8705321 | KF18: 15.546386 | KG18: 15.460226 | KH18: 82.007548 | KI18: 0 | KJ18: 0.08616002 | KK18: 99.424467 | KL18: 0.14423138 | KM18: 2.1052231 | KN18: 6.8690128 | KO18: Equity | KP18: Exchange Traded Funds | KQ18: USA | KR18: 46.389278 | KS18: 99.737017 | KT18: 99.479744 | KU18: 5.9218468 | KV18: 5.9621007 | KW18: 2.9922116 | KX18: 50.098254 | KZ18: 6.8511212 | LA18: 63.119169 | LB18: 6.9150195 | LC18: 37.400434 | LD18: A | LE18: 19.844695 | LF18: 35.190672 | LG18: 14.907583 | LH18: 2.622783 | LI18: 4.9195173 | LJ18: 21.625066 | LK18: 0.36942855 | LL18: 0.52025608 | LM18: 4.9898189 | LN18: 0.52025608 | LO18: 11.966447 | LP18: 80.644284 | LQ18: 5.8653189 | LR18: 20.091946 | LS18: Global | LT18: 5.7990146 | LU18: 37.801436 | LV18: 2226 | LW18: 1 | LX18: 2222 | LY18: T | LZ18: The Fund seeks to track the investment results of an index composed of large- and mid-capitalization developed and emerging market equities. The Fund seeks to track the MSCI ACWI, a free floatadjusted, market capweighted index that measures combined equity performance across developed and emerging markets countries. | MA18: 46203 | MB18: Equity Global | MC18: 5524 | MD18: BlackRock Fund Advisors | ME18: iShares MSCI ACWI ETF | MF18: 4.9290029 | MG18: 41.586362 | MH18: 33203742579 | MI18: 6.8511212 | MJ18: 63.119169 | MK18: 37.400434 | ML18: 5.4487077 | MM18: T | MN18: 3.8286235 | MO18: 0.13233859 | MP18: 0 | MQ18: 0 | MR18: 10.607278 | MS18: 3.5746414 | MT18: 0.2717739 | MU18: 0.40411249 | MV18: 13.804795 | MW18: 13.462553 | MX18: 12.54228 | MY18: 0 | MZ18: 0.27397288 | NA18: 0.03328456 | NB18: 0 | NC18: 10.897644 | ND18: 0 | NE18: 0.0027987 | NF18: 0.61701371 | NG18: 0.12444226 | NH18: 0.0027987 | NI18: 0.12444226 | NJ18: 0.0027987 | NK18: 0 | NL18: 0.49257145 | NM18: 0.31415425 | NN18: 0.30715749 | NO18: 0.01109485 | NP18: 0.41410787 | NQ18: 0.79403156 | NR18: 6.9172904 | NS18: 3.9672592 | NT18: 0.91517537 | NU18: 1.2632139 | NV18: 0.59792256 | NW18: 0 | NX18: 5.4384765 | NY18: 2.1711926 | NZ18: 0.825417 | OA18: 0.04947705 | OB18: 0.12124375 | OC18: 0.4385965 | OD18: 0.4344984 | OE18: 0.1075501 | OF18: 0.11024885 | OG18: 0.14013498 | OH18: 15.842549 | OI18: 9.1342616 | OJ18: 4.926614 | OK18: 0.14013498 | OL18: 9.308181 | OM18: 68.744403 | ON18: 0.02618785 | OO18: 4.9343105 | OP18: 0.02558813 | OQ18: 0.02558813 | OR18: 0.02558813 | OS18: 3.3415495 | OT18: 5.1674024 | OU18: 2.2800421 | OV18: 1.3583697 | OW18: 1.4651202 | OX18: 1.8627357 | OY18: 1.3798598 | OZ18: 0.91207679 | PA18: 0.98654224 | PB18: 0.12644132 | PC18: 0.077564 | PD18: 0.00309856 | PE18: 15.432239 | PF18: 0.14013498 | PG18: 0 | PH18: 0 | PI18: 0 | PJ18: 0.13823586 | PK18: 0.02618785 | PL18: 0 | PM18: 25.736658 | PN18: 10.290825 | PO18: 3.1769259 | PP18: 7.7168194 | PQ18: 4.6576388 | PR18: 4.9343105 | PS18: 0.03162828 | PT18: 0.40259524 | PU18: 0.83412943 | PV18: 0.0053933 | PW18: 0.11712 | PX18: 0.04328039 | PY18: 0.34414586 | PZ18: 0.63577436 | QA18: 10.62437 | QB18: 0.77873866 | QC18: 0.07616464 | QD18: 0.01599257 | QE18: 0.04108092 | QF18: 2.0033704 | QG18: 5.7175471 | QH18: 0.70637224 | QI18: 0.6060188 | QJ18: 0.6060188 | QK18: 6.9988525
A19: 40120602 | B19: iShares MSCI All Country Asia ex Japan ETF | C19: US4642881829 | D19: Matched | E19: US4642881829 | F19: 35818007 | G19: AAXJ | H19: 75.102935 | I19: 99.201751 | J19: 187.75274 | K19: 99.201751 | L19: 284.93022 | M19: 99.201751 | N19: 97.177479 | O19: 99.201751 | P19: 6.4854462 | Q19: 1.3518603 | R19: 3.6058661 | S19: 2.6673362 | T19: 5.1955848 | U19: 0.41119749 | V19: 3.4962452 | W19: 235.5285 | X19: 99.326198 | Y19: 437.85892 | Z19: 99.305092 | AA19: 749.71274 | AB19: 99.305092 | AC19: 311.85394 | AD19: 99.305092 | AE19: 202.59174 | AF19: 0.16802316 | AG19: 3196.7485 | AH19: 7978.1307 | AI19: 1699.2729 | AJ19: 9.4671806 | AK19: 10.246712 | AL19: Strongly Misaligned | AM19: 99.100801 | AN19: 41.641039 | AO19: 37.769364 | AP19: 3.5 | AQ19: 75.038852 | AR19: 36.301992 | AS19: 96.252971 | AT19: 4.7206886 | AU19: 21.701849 | AV19: 99.326198 | AW19: 1.1520744 | AX19: 6.0040878 | AY19: 0.13410337 | AZ19: 0.40410215 | BA19: 31.877776 | BB19: 35.038812 | BC19: 1.5072941 | BD19: 1.3963875 | BE19: 1.3027042 | BF19: 1.6538421 | BG19: 0.00570044 | BH19: 0.4106673 | BI19: 0.00096053 | BJ19: 0.05517605 | BK19: 1.6555849 | BL19: 2.4263109 | BM19: 0.29695339 | BN19: 0.57156186 | BO19: 0.35421275 | BP19: 0.02895778 | BQ19: 0.54078267 | BR19: 0.12441754 | BS19: 1.6528118 | BT19: 0.00272717 | BU19: 4.0791228 | BV19: 0.03142045 | BW19: 11.463997 | BX19: 1.9375797 | BY19: 16.212471 | BZ19: 0.02289813 | CA19: 48.301009 | CB19: 1.2414767 | CC19: 0.03704154 | CD19: 0.00693817 | CE19: 0.04555537 | CG19: 23.11765 | CH19: 10.303062 | CI19: 1.2000609 | CJ19: 39.55721 | CK19: 57.945301 | CL19: 31.389548 | CM19: 17.063186 | CN19: 15.730017 | CO19: 5.1260939 | CP19: 32.895846 | CQ19: 1.2339103 | CR19: 19.145223 | CS19: 44.103384 | CT19: 34.783946 | CU19: 32.102177 | CV19: 20.349764 | CW19: 2.3780202 | CX19: 9.4944592 | CY19: 14.587998 | CZ19: 22.511845 | DA19: 16.29132 | DB19: 74.345238 | DC19: 17.29157 | DD19: 7.6296556 | DE19: 46.53855 | DF19: 99.266464 | DG19: 5.7203918 | DH19: 99.107869 | DI19: 79.101577 | DJ19: 20.224621 | DK19: 5.3052968 | DL19: 1.7187533 | DM19: 81.139013 | DN19: 5.1708947 | DO19: 9.2349138 | DP19: 1.5782783 | DQ19: 5.7632126 | DR19: 98.841853 | DS19: 23.974139 | DT19: 97.475332 | DU19: 1.5118736 | DV19: 1.4625929 | DW19: 30.974694 | DX19: 36.032989 | DY19: 17.242687 | DZ19: 14.92251 | EA19: 66.292963 | EB19: 0 | EC19: 2.4840385 | ED19: 4.1715492 | EE19: 7.6027752 | EF19: 0.07865008 | EG19: 23.495967 | EH19: 5.0870267 | EI19: 11.905234 | EJ19: 5.3734933 | EK19: 35.184166 | EL19: 58.622787 | EM19: 5.5171542 | EN19: 11.871484 | EO19: 2864.9742 | EP19: 59.143371 | EQ19: 40857.699 | ER19: 95.993127 | ES19: 36.262568 | ET19: 21.26768 | EU19: 1.924936 | EV19: 78.91431 | EW19: 6.4973931 | EX19: 25.177485 | EY19: 0 | EZ19: 1.792525 | FA19: 97.138829 | FB19: 96.976452 | FC19: 58.845994 | FD19: 91.236389 | FE19: Not Aligned | FF19: 6.6878458 | FG19: 6.6878458 | FH19: 1.3076821 | FI19: 1.071035 | FJ19: 90.994366 | FK19: 0 | FL19: 0.23664716 | FM19: Aligned | FN19: 0.63945506 | FO19: 0.94728552 | FP19: 0.06819658 | FQ19: 0.06819658 | FR19: 97.974412 | FS19: 0.30783046 | FT19: 0 | FU19: Not Aligned | FV19: 1.587338 | FW19: 1.587338 | FX19: 1.4373054 | FY19: 1.2549169 | FZ19: 95.965251 | GA19: 0 | GB19: 0.18238856 | GC19: Not Aligned | GD19: 0.08213458 | GE19: 0.08213458 | GF19: 1.4107237 | GG19: 1.1740766 | GH19: 97.497036 | GI19: 0 | GJ19: 0.23664716 | GK19: Not Aligned | GL19: 17.955118 | GM19: 17.955118 | GN19: 0.36497623 | GO19: 0.12832907 | GP19: 80.6698 | GQ19: 0 | GR19: 0.23664716 | GS19: Aligned | GT19: 5.7744097 | GU19: 5.9327054 | GV19: 0.22509854 | GW19: 0.22509854 | GX19: 92.83209 | GY19: 0.15829574 | GZ19: 0 | HA19: Not Aligned | HB19: 14.771083 | HC19: 14.964324 | HD19: 3.9083119 | HE19: 0.69032873 | HF19: 80.117258 | HG19: 0.19324027 | HH19: 3.2179832 | HI19: Not Aligned | HJ19: 17.216902 | HK19: 17.245475 | HL19: 0.92896704 | HM19: 0.69231988 | HN19: 80.815452 | HO19: 0.02857288 | HP19: 0.23664716 | HQ19: Aligned | HR19: 16.156918 | HS19: 16.561418 | HT19: 0.38150269 | HU19: 0.38150269 | HV19: 82.046973 | HW19: 0.40450037 | HX19: 0 | HY19: Not Aligned | HZ19: 31.906946 | IA19: 31.906946 | IB19: 0.32913567 | IC19: 0.09248851 | ID19: 66.753812 | IE19: 0 | IF19: 0.23664716 | IG19: Not Aligned | IH19: 1.5363647 | II19: 1.5363647 | IJ19: 3.0045328 | IK19: 2.7793347 | IL19: 94.448996 | IM19: 0 | IN19: 0.2251981 | IO19: Not Aligned | IP19: 16.47341 | IQ19: 18.196942 | IR19: 4.3473586 | IS19: 1.1293754 | IT19: 76.445594 | IU19: 1.723532 | IV19: 3.2179832 | IW19: Not Aligned | IX19: 11.562857 | IY19: 11.793829 | IZ19: 3.9429578 | JA19: 0.72497459 | JB19: 83.253107 | JC19: 0.2309724 | JD19: 3.2179832 | JE19: Not Aligned | JF19: 0.00497785 | JG19: 0.00497785 | JH19: 0.7140233 | JI19: 0.64164532 | JJ19: 98.270893 | JK19: 0 | JL19: 0.07237798 | JM19: Not Aligned | JN19: 0 | JO19: 0 | JP19: 1.0712341 | JQ19: 1.0712341 | JR19: 97.91866 | JS19: 0 | JT19: 0 | JU19: Not Aligned | JV19: 21.551816 | JW19: 21.551816 | JX19: 0.61814985 | JY19: 0.38150269 | JZ19: 76.819928 | KA19: 0 | KB19: 0.23664716 | KC19: Not Aligned | KD19: 0.70476452 | KE19: 0.70476452 | KF19: 0.45099353 | KG19: 0.21434637 | KH19: 97.834136 | KI19: 0 | KJ19: 0.23664716 | KK19: 98.989894 | KL19: -0.03341012 | KM19: -0.48922344 | KN19: 7.2018589 | KO19: Equity | KP19: Exchange Traded Funds | KQ19: USA | KR19: 31.370503 | KS19: 99.504502 | KT19: 99.157917 | KU19: 5.7879026 | KV19: 5.7496344 | KW19: 6.6675362 | KX19: 61.119878 | KZ19: 6.8292145 | LA19: 62.00994 | LB19: 6.9698199 | LC19: 37.78135 | LD19: A | LE19: 15.336638 | LF19: 50.26527 | LG19: 10.854608 | LH19: 4.4974907 | LI19: 5.6682818 | LJ19: 10.365583 | LK19: 2.1700455 | LL19: 0.84208286 | LM19: 5.2743214 | LN19: 0.84208286 | LO19: 13.380172 | LP19: 78.575887 | LQ19: 5.7783587 | LR19: 23.452495 | LS19: Asia Pacific ex Japan | LT19: 5.5525311 | LU19: 36.820951 | LV19: 941 | LW19: 1 | LX19: 939 | LY19: T | LZ19: The Fund seeks investment results that correspond generally to the price and yield performance of the MSCI AC Asia ex Japan Index. The Index is designed to measure equity market performance of China, Hong Kong, India, Indonesia, Malaysia, the Philippines, Singapore, South Korea, Taiwan and Thailand. | MA19: 46203 | MB19: Equity Asia Pacific ex Japan | MC19: 622 | MD19: BlackRock Fund Advisors | ME19: iShares MSCI All Country Asia ex Japan ETF | MF19: 5.3706289 | MG19: 38.884472 | MH19: 3970623868 | MI19: 6.8292145 | MJ19: 62.00994 | MK19: 37.78135 | ML19: 5.5346107 | MM19: T | MN19: 0.8990999 | MO19: 0 | MP19: 0 | MQ19: 0 | MR19: 8.1737351 | MS19: 0.48205536 | MT19: 0.29249869 | MU19: 0.29468895 | MV19: 3.6699723 | MW19: 2.893228 | MX19: 2.6234284 | MY19: 0 | MZ19: 0 | NA19: 0 | NB19: 0 | NC19: 3.2073306 | ND19: 0 | NE19: 0 | NF19: 0 | NG19: 0 | NH19: 0 | NI19: 0 | NJ19: 0 | NK19: 0 | NL19: 0 | NM19: 0.45736518 | NN19: 0.40908 | NO19: 0.09288675 | NP19: 0.6470214 | NQ19: 0.48892478 | NR19: 2.5937604 | NS19: 2.0229001 | NT19: 0.47020805 | NU19: 0.7061583 | NV19: 0.59256368 | NW19: 0 | NX19: 4.1560099 | NY19: 2.9989576 | NZ19: 0.79874638 | OA19: 0.10403714 | OB19: 0.10403714 | OC19: 0.02608395 | OD19: 0.02608395 | OE19: 0 | OF19: 0.02608395 | OG19: 0.23664716 | OH19: 7.3863382 | OI19: 2.8138811 | OJ19: 3.6652931 | OK19: 0.23664716 | OL19: 5.6374191 | OM19: 66.865515 | ON19: 0.23664716 | OO19: 2.7535495 | OP19: 0.23057418 | OQ19: 0.23057418 | OR19: 0.23057418 | OS19: 2.2474013 | OT19: 2.0456987 | OU19: 0.24739932 | OV19: 0.23256532 | OW19: 0.23256532 | OX19: 0.15242187 | OY19: 0.09169206 | OZ19: 0 | PA19: 0.02210167 | PB19: 0.6827624 | PC19: 0.60799504 | PD19: 0.07486692 | PE19: 1.0247409 | PF19: 0.23664716 | PG19: 0 | PH19: 0 | PI19: 0 | PJ19: 0.2251981 | PK19: 0.23664716 | PL19: 0 | PM19: 17.56346 | PN19: 0.08980048 | PO19: 0.34864885 | PP19: 11.834349 | PQ19: 3.1090678 | PR19: 2.7535495 | PS19: 0.0028972 | PT19: 0.33761755 | PU19: 0.4016923 | PV19: 0 | PW19: 0.09122349 | PX19: 0.0013042 | PY19: 0.09120631 | PZ19: 0.12134872 | QA19: 2.6338819 | QB19: 0.83767317 | QC19: 0.56299522 | QD19: 0.13390426 | QE19: 0.36547399 | QF19: 2.1973241 | QG19: 3.9134889 | QH19: 0.19075135 | QI19: 0.18238856 | QJ19: 0.18238856 | QK19: 2.7953634
A20: 40125506 | B20: iShares MSCI Peru and Global Exposure ETF | C20: US4642898427 | D20: Matched | E20: US4642898427 | F20: 35925070 | G20: EPU | H20: 54.427447 | I20: 92.630774 | J20: 92.538197 | K20: 93.662172 | L20: 160.33818 | M20: 93.662172 | N20: 67.799987 | O20: 93.662172 | P20: 0 | Q20: 0 | R20: 0.36605907 | T20: 0 | U20: 0 | V20: 0 | W20: 212.87823 | X20: 92.630774 | Y20: 296.43786 | Z20: 93.662172 | AA20: 583.81625 | AB20: 93.662172 | AC20: 287.37888 | AD20: 93.662172 | AE20: 202.59174 | AF20: 0.05934266 | AG20: 391.20741 | AH20: 983.65606 | AI20: 4095.031 | AJ20: 44.43687 | AK20: 4.4958466 | AL20: 2.0°C Aligned | AM20: 90.43693 | AN20: 35.659093 | AO20: 5.8451204 | AP20: 1.7 | AQ20: 37.338638 | AR20: 57.99968 | AS20: 87.020162 | AT20: 0 | AU20: 7.3072502 | AV20: 92.630774 | AW20: 2.928158 | AX20: 0 | AY20: 0 | AZ20: 2.7175402 | BA20: 1.374264 | BB20: 4.3024221 | BC20: 2.928158 | BD20: 0 | BE20: 4.5023441 | BF20: 0 | BG20: 0.00146408 | BH20: 0 | BI20: 0 | BJ20: 2.4425251 | BK20: 0.02295021 | BL20: 0.36364584 | BM20: 0.34069563 | BN20: 0 | BO20: 0.06881132 | BP20: 0 | BQ20: 2.9437214 | BR20: 0.02858119 | BS20: 5.4851031 | BT20: 0 | BU20: 5.8487489 | BV20: 0 | BW20: 29.43502 | BX20: 4.5023441 | BY20: 39.583063 | BZ20: 0 | CA20: 40.957327 | CB20: 0 | CC20: 0 | CD20: 0 | CE20: 0.00241323 | CG20: 39.977709 | CH20: 8.25648 | CI20: 6.407701 | CJ20: 33.653075 | CK20: 33.803517 | CL20: 25.30693 | CM20: 12.441848 | CN20: 2.5638001 | CO20: 2.8930717 | CP20: 31.792101 | CQ20: 2.3700757 | CR20: 32.965344 | CS20: 41.174942 | CT20: 16.120413 | CU20: 47.421706 | CV20: 27.448295 | CW20: 26.295545 | CX20: 38.030968 | CY20: 28.476494 | CZ20: 55.660892 | DA20: 41.473425 | DB20: 50.94783 | DC20: 29.422025 | DD20: 12.260918 | DE20: 43.117484 | DF20: 90.43693 | DG20: 4.0581707 | DH20: 87.273663 | DI20: 58.326753 | DJ20: 35.335419 | DK20: 29.243895 | DL20: 0 | DM20: 53.985546 | DN20: 3.6901608 | DO20: 32.761223 | DP20: 0 | DQ20: 5.8265673 | DR20: 90.43693 | DS20: 37.662212 | DT20: 50.635552 | DU20: 21.991423 | DV20: 2.4405482 | DW20: 4.5375304 | DX20: 0 | DY20: 27.448295 | DZ20: 49.406931 | EA20: 69.571867 | EB20: 0 | EC20: 4.9268625 | ED20: 4.8999112 | EE20: 4.5023441 | EF20: 0 | EG20: 41.473425 | EH20: 4.3126186 | EI20: 39.020282 | EJ20: 40.092864 | EK20: 39.336859 | EL20: 11.007207 | EM20: 41.484321 | EN20: 80.94873 | EO20: 7250.9697 | EP20: 41.390358 | EQ20: 4654.6174 | ER20: 69.780286 | ES20: 0 | ET20: 61.810494 | EU20: 32.780316 | EV20: 79.579064 | EW20: 0 | EX20: 8.1234319 | EY20: 0 | EZ20: 29.090155 | FA20: 78.488489 | FB20: 73.702556 | FC20: 32.087486 | FD20: 87.020162 | FE20: Aligned | FF20: 29.013085 | FG20: 29.013085 | FH20: 0 | FI20: 0 | FJ20: 58.260578 | FK20: 0 | FL20: 0 | FM20: Not Aligned | FN20: 0 | FO20: 0 | FP20: 0 | FQ20: 0 | FR20: 87.273663 | FS20: 0 | FT20: 0 | FU20: Not Aligned | FV20: 0 | FW20: 0 | FX20: 0 | FY20: 0 | FZ20: 87.273663 | GA20: 0 | GB20: 0 | GC20: Aligned | GD20: 2.7175402 | GE20: 2.7175402 | GF20: 0 | GG20: 0 | GH20: 84.556123 | GI20: 0 | GJ20: 0 | GK20: Aligned | GL20: 43.69336 | GM20: 43.69336 | GN20: 0 | GO20: 0 | GP20: 43.580304 | GQ20: 0 | GR20: 0 | GS20: Aligned | GT20: 2.4405482 | GU20: 2.4405482 | GV20: 0 | GW20: 0 | GX20: 84.833115 | GY20: 0 | GZ20: 0 | HA20: Aligned | HB20: 38.129529 | HC20: 38.129529 | HD20: 0 | HE20: 0 | HF20: 49.144134 | HG20: 0 | HH20: 0 | HI20: Aligned | HJ20: 30.760004 | HK20: 33.477544 | HL20: 0 | HM20: 0 | HN20: 53.79612 | HO20: 2.7175402 | HP20: 0 | HQ20: Aligned | HR20: 29.43502 | HS20: 29.43502 | HT20: 0 | HU20: 0 | HV20: 57.838643 | HW20: 0 | HX20: 0 | HY20: Aligned | HZ20: 40.060776 | IA20: 40.060776 | IB20: 0 | IC20: 0 | ID20: 47.212887 | IE20: 0 | IF20: 0 | IG20: Not Aligned | IH20: 2.928158 | II20: 2.928158 | IJ20: 5.0043483 | IK20: 5.0043483 | IL20: 79.341157 | IM20: 0 | IN20: 0 | IO20: Aligned | IP20: 7.4944772 | IQ20: 7.4944772 | IR20: 0 | IS20: 0 | IT20: 79.779186 | IU20: 0 | IV20: 0 | IW20: Aligned | IX20: 37.413909 | IY20: 37.413909 | IZ20: 0 | JA20: 0 | JB20: 49.859755 | JC20: 0 | JD20: 0 | JE20: Not Aligned | JF20: 0 | JG20: 0 | JH20: 0 | JI20: 0 | JJ20: 87.273663 | JK20: 0 | JL20: 0 | JM20: Not Aligned | JN20: 0 | JO20: 0 | JP20: 5.0043483 | JQ20: 5.0043483 | JR20: 82.269315 | JS20: 0 | JT20: 0 | JU20: Aligned | JV20: 2.0943832 | JW20: 2.0943832 | JX20: 0 | JY20: 0 | JZ20: 85.17928 | KA20: 0 | KB20: 0 | KC20: Aligned | KD20: 27.775967 | KE20: 27.775967 | KF20: 0 | KG20: 0 | KH20: 59.497696 | KI20: 0 | KJ20: 0 | KK20: 87.273663 | KL20: 0.51637489 | KM20: 7.9976809 | KN20: 1.374264 | KO20: Equity | KP20: Exchange Traded Funds | KQ20: USA | KR20: 47.275228 | KS20: 87.409004 | KT20: 87.333006 | KU20: 5.709392 | KV20: 5.3240459 | KW20: 0 | KX20: 40.057777 | KZ20: 6.4565578 | LA20: 46.286373 | LB20: 6.4392858 | LD20: A | LE20: 9.1280059 | LF20: 37.963394 | LG20: 2.0943832 | LH20: 0 | LI20: 21.991423 | LJ20: 16.155799 | LK20: 0 | LL20: 12.666994 | LM20: 5.0481655 | LN20: 12.666994 | LO20: 9.3719449 | LP20: 76.586797 | LQ20: 4.7718245 | LR20: 22.717731 | LS20: Peru | LT20: 5.2701679 | LU20: 30.256332 | LV20: 27 | LW20: 1 | LX20: 26 | LY20: T | LZ20: The Fund seeks to track the investment results of the MSCI All Peru Capped Index, which is a free float-adjusted market capitalization-weighted index designed to measure the performance of the Broad Peru Equity Universe, as defined by MSCI, Inc. targeting a minimum of 25 securities and 20 issuers. | MA20: 46203 | MB20: Equity Emerging Markets Other | MC20: 27 | MD20: BlackRock Fund Advisors | ME20: iShares MSCI Peru and Global Exposure ETF | MF20: 5.1617448 | MG20: 34.358943 | MH20: 523867828 | MI20: 6.4565578 | MJ20: 46.286373 | ML20: 5.0978787 | MM20: T | MN20: 1.374264 | MO20: 0 | MP20: 0 | MQ20: 0 | MR20: 4.5023441 | MS20: 0 | MT20: 0 | MU20: 0 | MV20: 0 | MW20: 0 | MX20: 0 | MY20: 0 | MZ20: 0 | NA20: 0 | NB20: 0 | NC20: 27.326942 | ND20: 0 | NE20: 0 | NF20: 0 | NG20: 0 | NH20: 0 | NI20: 0 | NJ20: 0 | NK20: 0 | NL20: 0 | NM20: 0 | NN20: 0 | NO20: 0 | NP20: 0 | NQ20: 0 | NR20: 0 | NS20: 0 | NT20: 0 | NU20: 0 | NV20: 0 | NW20: 0 | NX20: 0 | NY20: 0 | NZ20: 0 | OA20: 0 | OB20: 0 | OC20: 0 | OD20: 0 | OE20: 0 | OF20: 0 | OG20: 0 | OH20: 30.159038 | OI20: 0 | OJ20: 0 | OK20: 0 | OL20: 30.159038 | OM20: 64.155279 | ON20: 0 | OO20: 21.991423 | OP20: 0 | OQ20: 0 | OR20: 0 | OS20: 0 | OT20: 0 | OU20: 0 | OV20: 0 | OW20: 0 | OX20: 0 | OY20: 0 | OZ20: 0 | PA20: 0 | PB20: 0 | PC20: 0 | PD20: 0 | PE20: 0 | PF20: 0 | PG20: 0 | PH20: 0 | PI20: 0 | PJ20: 0 | PK20: 0 | PL20: 0 | PM20: 30.159038 | PN20: 0 | PO20: 0 | PP20: 0 | PQ20: 8.1676146 | PR20: 21.991423 | PS20: 0.00068713 | PT20: 0.04457321 | PU20: 0 | PV20: 0 | PW20: 0 | PX20: 0 | PY20: 0 | PZ20: 0.00213227 | QA20: 0 | QB20: 0 | QC20: 0 | QD20: 0 | QE20: 0 | QF20: 0 | QG20: 2.1322684 | QH20: 0 | QI20: 0 | QJ20: 0 | QK20: 0
A21: 40183710 | B21: VanEck JP Morgan EM Local Currency Bond ETF | C21: US92189H3003 | D21: Matched | E21: US92189H3003 | F21: 36253628 | G21: EMLC | H21: 10.130047 | I21: 6.7515502 | J21: 44.336342 | K21: 6.7515502 | L21: 58.134837 | M21: 6.7515502 | N21: 13.798495 | O21: 6.7515502 | P21: 0.0140371 | Q21: 0.00731712 | R21: 0.0015619 | S21: 0.2134583 | T21: 0.0140371 | U21: 0 | V21: 0.0140371 | W21: 21.879356 | X21: 6.7515502 | Y21: 516.54066 | Z21: 6.7515502 | AA21: 623.65761 | AB21: 6.7515502 | AC21: 107.11738 | AD21: 6.7515502 | AE21: 680.90445 | AF21: 93.036617 | AG21: 2629.1686 | AH21: 6530.4206 | AI21: 218.67967 | AJ21: 0 | AK21: 0 | AL21: Strongly Misaligned | AM21: 2.7011109 | AN21: 0.23244651 | AO21: 2.4686644 | AP21: 10 | AQ21: 0 | AR21: 6.4485256 | AS21: 6.6093142 | AU21: 0 | AV21: 6.7515502 | AW21: 0 | AX21: 0 | AY21: 0 | AZ21: 0 | BA21: 0 | BB21: 0 | BC21: 0 | BD21: 0 | BE21: 0 | BF21: 0 | BG21: 0 | BH21: 0 | BI21: 0 | BJ21: 0 | BK21: 0 | BL21: 0 | BM21: 0 | BN21: 0 | BO21: 0 | BP21: 0 | BQ21: 0.05980275 | BR21: 0 | BS21: 0.05980275 | BT21: 0 | BU21: 0.05980275 | BV21: 0 | BW21: 2.7532347 | BX21: 0 | BY21: 2.7532347 | BZ21: 0 | CA21: 2.7532347 | CB21: 0 | CC21: 0 | CD21: 0 | CE21: 0 | CG21: 5.2482064 | CH21: 0 | CI21: 0.14223606 | CJ21: 0.01334997 | CK21: 1.3611078 | CL21: 0 | CM21: 0 | CN21: 0 | CO21: 0.0140371 | CP21: 0 | CQ21: 0 | CR21: 0 | CS21: 0 | CT21: 0.0140371 | CU21: 0.0140371 | CV21: 0.0140371 | CW21: 0 | CX21: 0 | CY21: 0 | CZ21: 0 | DA21: 0.0140371 | DB21: 0 | DC21: 0.0140371 | DD21: 0 | DE21: 0.01334997 | DF21: 0.0140371 | DG21: 6.4596011 | DH21: 6.7515502 | DI21: 0.0140371 | DJ21: 0 | DK21: 0 | DL21: 0.01334997 | DM21: 4.936249 | DN21: 0.00068713 | DO21: 1.8012641 | DP21: 0 | DQ21: 5.9644011 | DR21: 6.7515502 | DS21: 0 | DT21: 0 | DU21: 0 | DV21: 0 | DW21: 0 | DX21: 0 | DY21: 0 | DZ21: 0 | EA21: 0 | EB21: 0 | EC21: 0.0017355 | EE21: 0 | EF21: 0 | EG21: 0.0140371 | EH21: 4.8945713 | EI21: 0.01334997 | EJ21: 0.01334997 | EK21: 6.7375131 | EL21: 0.00068713 | EM21: 0.01334997 | EN21: 0.0140371 | EP21: 0 | EQ21: 14542.118 | ER21: 0.01334997 | ES21: 0 | ET21: 4.1143425 | EU21: 0 | EV21: 4.3803602 | EW21: 0 | EX21: 5.496555 | EY21: 0 | EZ21: 0 | FA21: 0 | FB21: 0 | FC21: 1.6643288 | FD21: 6.6093142 | FE21: Not Aligned | FF21: 0 | FG21: 0 | FH21: 0.01334997 | FI21: 0.01334997 | FJ21: 0.00068713 | FK21: 0 | FL21: 0 | FM21: Not Aligned | FN21: 0 | FO21: 0 | FP21: 0 | FQ21: 0 | FR21: 0.0140371 | FS21: 0 | FT21: 0 | FU21: Not Aligned | FV21: 0 | FW21: 0 | FX21: 0 | FY21: 0 | FZ21: 0.0140371 | GA21: 0 | GB21: 0 | GC21: Not Aligned | GD21: 0 | GE21: 0 | GF21: 0 | GG21: 0 | GH21: 0.0140371 | GI21: 0 | GJ21: 0 | GK21: Aligned | GL21: 0.01334997 | GM21: 0.01334997 | GN21: 0 | GO21: 0 | GP21: 0.00068713 | GQ21: 0 | GR21: 0 | GS21: Not Aligned | GT21: 0 | GU21: 0 | GV21: 0 | GW21: 0 | GX21: 0.0140371 | GY21: 0 | GZ21: 0 | HA21: Not Aligned | HB21: 0 | HC21: 0 | HD21: 0.01334997 | HE21: 0 | HF21: 0.00068713 | HG21: 0 | HH21: 0.01334997 | HI21: Not Aligned | HJ21: 0 | HK21: 0 | HL21: 0 | HM21: 0 | HN21: 0.0140371 | HO21: 0 | HP21: 0 | HQ21: Aligned | HR21: 0 | HS21: 0.00068713 | HT21: 0 | HU21: 0 | HV21: 0.01334997 | HW21: 0.00068713 | HX21: 0 | HY21: Not Aligned | HZ21: 0 | IA21: 0 | IB21: 0.01334997 | IC21: 0.01334997 | ID21: 0.00068713 | IE21: 0 | IF21: 0 | IG21: Not Aligned | IH21: 0 | II21: 0 | IJ21: 0 | IK21: 0 | IL21: 0.0140371 | IM21: 0 | IN21: 0 | IO21: Not Aligned | IP21: 0 | IQ21: 0 | IR21: 0.01334997 | IS21: 0 | IT21: 0.00068713 | IU21: 0 | IV21: 0.01334997 | IW21: Not Aligned | IX21: 0 | IY21: 0 | IZ21: 0.01334997 | JA21: 0 | JB21: 0.00068713 | JC21: 0 | JD21: 0.01334997 | JE21: Not Aligned | JF21: 0 | JG21: 0 | JH21: 0 | JI21: 0 | JJ21: 0.0140371 | JK21: 0 | JL21: 0 | JM21: Not Aligned | JN21: 0 | JO21: 0 | JP21: 0 | JQ21: 0 | JR21: 0.0140371 | JS21: 0 | JT21: 0 | JU21: Not Aligned | JV21: 0 | JW21: 0 | JX21: 0.01334997 | JY21: 0.01334997 | JZ21: 0.00068713 | KA21: 0 | KB21: 0 | KC21: Not Aligned | KD21: 0 | KE21: 0 | KF21: 0.01334997 | KG21: 0.01334997 | KH21: 0.00068713 | KI21: 0 | KJ21: 0 | KK21: 0.0140371 | KL21: -0.22355514 | KM21: -4.7191157 | KN21: 5.6570491 | KO21: Bond | KP21: Exchange Traded Funds | KQ21: USA | KR21: 93.178853 | KS21: 98.191244 | KT21: 99.788167 | KU21: 5.0391817 | KV21: 5.2954541 | KW21: 0.0140371 | KX21: 6.5952771 | KZ21: 4.7372253 | LA21: 14.37972 | LB21: 4.5876105 | LC21: 74.693878 | LD21: BBB | LE21: 5.9519264 | LF21: 0.60997577 | LG21: 5.9853013 | LH21: 0.00068713 | LI21: 39.395953 | LJ21: 47.830974 | LK21: 0.01334997 | LL21: 0.21183259 | LM21: 5.8453829 | LN21: 0.21183259 | LO21: 0.95197055 | LP21: 93.179148 | LQ21: 5.1355163 | LR21: 25.220359 | LS21: Global Emerging Markets | LT21: 5.4494555 | LU21: 48.74632 | LV21: 498 | LW21: 0 | LX21: 497 | LY21: T | LZ21: The Fund seeks to replicate as closely as possible the price and yield performance of the JP Morgan GBI-EMG Core Index. It invests at least 80% of its total assets in securities that comprise the Fund's benchmark Index. The Index provides direct exposure to local currency bonds issued by emerging market governments. | MA21: 46203 | MB21: Bond Emerging Markets Global LC | MC21: 245 | MD21: Van Eck Associates Corp | ME21: VanEck JP Morgan EM Local Currency Bond ETF | MF21: 6.1811232 | MG21: 25.821488 | MH21: 4872451315 | MI21: 4.7372253 | MJ21: 14.37972 | MK21: 74.693878 | ML21: 5.5594394 | MN21: 0 | MO21: 0 | MP21: 0 | MQ21: 0 | MR21: 0 | MS21: 0 | MT21: 0 | MU21: 0 | MV21: 0 | MW21: 0 | MX21: 0 | MY21: 0 | MZ21: 0 | NA21: 0 | NB21: 0 | NC21: 0 | ND21: 0 | NE21: 0 | NF21: 0 | NG21: 0 | NH21: 0 | NI21: 0 | NJ21: 0 | NK21: 0 | NL21: 0 | NM21: 0 | NN21: 0 | NO21: 0 | NP21: 0 | NQ21: 0 | NR21: 0 | NS21: 0 | NT21: 0 | NU21: 0 | NV21: 0 | NW21: 0 | NX21: 0 | NY21: 0 | NZ21: 0 | OA21: 0 | OB21: 0 | OC21: 0 | OD21: 0 | OE21: 0 | OF21: 0 | OG21: 0 | OH21: 0 | OI21: 0 | OJ21: 0 | OK21: 0 | OL21: 0 | OM21: 0 | ON21: 0 | OO21: 0 | OP21: 0 | OQ21: 0 | OR21: 0 | OS21: 0 | OT21: 0.01334997 | OU21: 0.01334997 | OV21: 0 | OW21: 0 | OX21: 0 | OY21: 0 | OZ21: 0 | PA21: 0 | PB21: 0 | PC21: 0 | PD21: 0 | PE21: 0 | PF21: 0 | PG21: 0 | PH21: 0 | PI21: 0 | PJ21: 0 | PK21: 0 | PL21: 0 | PM21: 0 | PN21: 0 | PO21: 0 | PP21: 0 | PQ21: 0 | PR21: 0 | PS21: 0 | PT21: 0 | PU21: 0 | PV21: 0 | PW21: 0 | PX21: 0 | PY21: 0.00033909 | PZ21: 0 | QA21: 0.01334997 | QB21: 0 | QC21: 0 | QD21: 0 | QE21: 0 | QF21: 0 | QG21: 0 | QH21: 0 | QI21: 0 | QJ21: 0 | QK21: 0
A22: 40197668 | B22: iShares US & Intl High Yield Corp Bond ETF | C22: US4642861789 | D22: Matched | E22: US4642861789 | F22: 36406711 | G22: GHYG | H22: 91.455063 | I22: 75.707147 | J22: 481.90627 | K22: 75.828429 | L22: 688.21775 | M22: 75.828429 | N22: 206.31148 | O22: 75.828429 | P22: 14.323709 | Q22: 3.8202698 | R22: 3.7854531 | S22: 0.99088633 | T22: 14.11044 | U22: 1.4168776 | V22: 2.6950065 | W22: 158.28905 | X22: 76.57832 | Y22: 685.03608 | Z22: 78.213181 | AA22: 967.45897 | AB22: 78.213181 | AC22: 282.42323 | AD22: 78.213181 | AE22: 202.59174 | AF22: 0.17698796 | AG22: 6754.6865 | AH22: 16681.098 | AI22: 3971.4106 | AJ22: 8.9508931 | AK22: 22.553607 | AL22: Strongly Misaligned | AM22: 75.177624 | AN22: 21.323387 | AO22: 22.928452 | AP22: 3.3 | AQ22: 43.273482 | AR22: 22.296445 | AS22: 56.653629 | AT22: 7.0463719 | AU22: 23.728436 | AV22: 76.57832 | AW22: 0.93456354 | AX22: 5.5230936 | AY22: 0.24626405 | AZ22: 0.16037659 | BA22: 10.853915 | BB22: 15.090497 | BC22: 1.8372317 | BD22: 1.2303204 | BE22: 1.684554 | BF22: 2.6467136 | BG22: 0.01684566 | BH22: 0.72602945 | BI22: 0.01013498 | BJ22: 0.00155565 | BK22: 1.3681334 | BL22: 2.6521159 | BM22: 0.25327025 | BN22: 0.47137262 | BO22: 0.60699246 | BP22: 0.22189429 | BQ22: 0.05225208 | BR22: 0.08620423 | BS22: 1.2453577 | BT22: 0.03646937 | BU22: 3.8974698 | BV22: 0.04631917 | BW22: 0.99795429 | BX22: 1.1795278 | BY22: 5.7968536 | BZ22: 0.30375565 | CA22: 19.948787 | CB22: 1.5999664 | CC22: 0.31020571 | CD22: 0.05889773 | CE22: 0.18840457 | CG22: 32.009927 | CH22: 4.9753736 | CI22: 20.360727 | CJ22: 25.506076 | CK22: 18.481402 | CL22: 0.54512041 | CM22: 5.5586884 | CN22: 0.38834329 | CO22: 11.30505 | CP22: 15.711906 | CQ22: 0.90196833 | CR22: 2.959168 | CS22: 10.734633 | CT22: 23.938005 | CU22: 23.843219 | CV22: 19.122008 | CW22: 1.0105525 | CX22: 43.724916 | CY22: 14.172131 | CZ22: 11.378539 | DA22: 39.872179 | DB22: 36.354992 | DC22: 16.528687 | DD22: 17.456251 | DE22: 39.539227 | DF22: 76.187677 | DG22: 4.755557 | DH22: 71.351483 | DI22: 77.250121 | DJ22: 8.4525659 | DK22: 24.289854 | DL22: 4.1932878 | DM22: 47.351887 | DN22: 6.5702407 | DO22: 13.057094 | DP22: 1.6757553 | DQ22: 5.6035058 | DR22: 72.848264 | DS22: 17.919484 | DT22: 17.162094 | DU22: 5.8367478 | DV22: 12.034943 | DW22: 17.239483 | DX22: 22.648493 | DY22: 14.428294 | DZ22: 9.5769017 | EA22: 55.781556 | EB22: 0.52052401 | EC22: 2.4005625 | ED22: 4.8346866 | EE22: 6.7167193 | EF22: 16.147343 | EG22: 44.053668 | EH22: 3.5523223 | EI22: 14.86053 | EJ22: 9.4495203 | EK22: 40.20333 | EL22: 23.875814 | EM22: 9.6169959 | EN22: 3.8412392 | EO22: 8131.6957 | EP22: 13.477832 | EQ22: 16937.535 | ER22: 21.800417 | ES22: 16.016362 | ET22: 15.314964 | EU22: 1.7475448 | EV22: 32.303584 | EW22: 2.0717975 | EX22: 14.124738 | EY22: 0.6048117 | EZ22: 1.1947256 | FA22: 46.896153 | FB22: 52.680809 | FC22: 18.991327 | FD22: 52.832486 | FE22: Not Aligned | FF22: 3.8087439 | FG22: 3.8087439 | FH22: 1.9038221 | FI22: 1.6885535 | FJ22: 65.724804 | FK22: 0 | FL22: 0.21526857 | FM22: Aligned | FN22: 0.51852428 | FO22: 1.1859268 | FP22: 0.18237338 | FQ22: 0.18237338 | FR22: 70.06907 | FS22: 0.66740255 | FT22: 0 | FU22: Aligned | FV22: 1.8758261 | FW22: 1.8758261 | FX22: 0.94816156 | FY22: 0.94816156 | FZ22: 68.613382 | GA22: 0 | GB22: 0 | GC22: Not Aligned | GD22: 0 | GE22: 0 | GF22: 0 | GG22: 0 | GH22: 71.43737 | GI22: 0 | GJ22: 0 | GK22: Aligned | GL22: 24.331148 | GM22: 24.331148 | GN22: 0 | GO22: 0 | GP22: 47.106223 | GQ22: 0 | GR22: 0 | GS22: Aligned | GT22: 3.5453824 | GU22: 3.7310552 | GV22: 0.40434097 | GW22: 0.40434097 | GX22: 67.301974 | GY22: 0.18567287 | GZ22: 0 | HA22: Not Aligned | HB22: 13.720697 | HC22: 13.97476 | HD22: 6.5196481 | HE22: 0.1684754 | HF22: 50.942962 | HG22: 0.2540629 | HH22: 6.3511727 | HI22: Not Aligned | HJ22: 4.8291949 | HK22: 4.8291949 | HL22: 0.62080935 | HM22: 0.52842284 | HN22: 65.987366 | HO22: 0 | HP22: 0.09238651 | HQ22: Aligned | HR22: 11.401035 | HS22: 11.921159 | HT22: 3.7017595 | HU22: 3.7017595 | HV22: 55.814451 | HW22: 0.52012406 | HX22: 0 | HY22: Not Aligned | HZ22: 9.2778454 | IA22: 9.2778454 | IB22: 2.8871785 | IC22: 2.6719099 | ID22: 59.272346 | IE22: 0 | IF22: 0.21526857 | IG22: Not Aligned | IH22: 2.5399291 | II22: 2.5399291 | IJ22: 1.7204488 | IK22: 1.6280623 | IL22: 67.176992 | IM22: 0 | IN22: 0.09238651 | IO22: Not Aligned | IP22: 10.291897 | IQ22: 11.144273 | IR22: 7.1323587 | IS22: 0.78118594 | IT22: 53.160739 | IU22: 0.8523755 | IV22: 6.3511727 | IW22: Not Aligned | IX22: 13.63091 | IY22: 13.97046 | IZ22: 6.3511727 | JA22: 0 | JB22: 51.115737 | JC22: 0.33955042 | JD22: 6.3511727 | JE22: Not Aligned | JF22: 0.2012706 | JG22: 0.2012706 | JH22: 2.5505276 | JI22: 1.6144643 | JJ22: 68.685572 | JK22: 0 | JL22: 0.93606333 | JM22: Not Aligned | JN22: 0 | JO22: 0 | JP22: 2.136488 | JQ22: 2.136488 | JR22: 69.300882 | JS22: 0 | JT22: 0 | JU22: Not Aligned | JV22: 3.9276265 | JW22: 3.9276265 | JX22: 1.5553729 | JY22: 1.4629864 | JZ22: 65.954371 | KA22: 0 | KB22: 0.09238651 | KC22: Not Aligned | KD22: 1.3848978 | KE22: 1.3848978 | KF22: 1.0013538 | KG22: 0.90896727 | KH22: 69.051119 | KI22: 0 | KJ22: 0.09238651 | KK22: 71.43737 | KL22: -0.51812961 | KM22: -9.2130548 | KN22: 11.760683 | KO22: Bond | KP22: Exchange Traded Funds | KQ22: USA | KR22: 39.68452 | KS22: 73.166537 | KT22: 71.727842 | KU22: 5.1842572 | KV22: 5.7733549 | KW22: 10.693039 | KX22: 21.350283 | KZ22: 5.6238633 | LA22: 25.606675 | LB22: 5.694472 | LC22: 44.055944 | LD22: BBB | LE22: 16.488506 | LF22: 16.198135 | LG22: 5.1521478 | LH22: 8.2098013 | LI22: 9.3320376 | LJ22: 13.863976 | LK22: 2.4832374 | LL22: 28.272158 | LM22: 4.6464172 | LN22: 28.272158 | LO22: 13.240667 | LP22: 46.726492 | LQ22: 5.1067825 | LR22: 14.275746 | LS22: Global | LT22: 5.7705737 | LU22: 28.599504 | LV22: 1735 | LW22: 1 | LX22: 1719 | LY22: T | LZ22: The Fund seeks to track the investment results of the Markit iBoxx Global Developed Markets High Yield Index composed of US dollar, euro, British pound sterling and Canadian dollar-denominated, high yield corporate bonds. The Fund invests at least 90% of its assets in the component securities of the Underlying Index. | MA22: 46203 | MB22: Bond Global High Yield USD | MC22: 143 | MD22: BlackRock Fund Advisors | ME22: iShares US & Intl High Yield Corp Bond ETF | MF22: 4.3782175 | MG22: 28.852591 | MH22: 199005895 | MI22: 5.6238633 | MJ22: 25.606675 | MK22: 44.055944 | ML22: 5.078385 | MM22: T | MN22: 6.0724134 | MO22: 0.50242665 | MP22: 0 | MQ22: 0 | MR22: 11.500121 | MS22: 0.60651146 | MT22: 0.06878996 | MU22: 0.06878996 | MV22: 5.8888402 | MW22: 5.6675725 | MX22: 4.5021427 | MY22: 0 | MZ22: 0.0903868 | NA22: 0.0903868 | NB22: 0 | NC22: 7.3544262 | ND22: 0 | NE22: 0.10358488 | NF22: 0.22646694 | NG22: 0.10358488 | NH22: 0.10358488 | NI22: 0.10358488 | NJ22: 0.10358488 | NK22: 0 | NL22: 0.22646694 | NM22: 0 | NN22: 0 | NO22: 0 | NP22: 0 | NQ22: 0 | NR22: 3.7623507 | NS22: 2.7599971 | NT22: 0 | NU22: 0.14147935 | NV22: 0.12288206 | NW22: 0 | NX22: 3.1308429 | NY22: 6.2916814 | NZ22: 5.1479484 | OA22: 2.3943504 | OB22: 2.7764946 | OC22: 0.43123704 | OD22: 0.43123704 | OE22: 0.36834622 | OF22: 0.36834622 | OG22: 0.09238651 | OH22: 2.9279725 | OI22: 0.81288133 | OJ22: 2.5765238 | OK22: 0.09238651 | OL22: 0.93166397 | OM22: 25.090237 | ON22: 0 | OO22: 0.12988104 | OP22: 0 | OQ22: 0 | OR22: 0 | OS22: 0.78938475 | OT22: 1.3885973 | OU22: 1.0816421 | OV22: 0.67170193 | OW22: 0.67170193 | OX22: 0.05319223 | OY22: 0.05319223 | OZ22: 0.05319223 | PA22: 0.05319223 | PB22: 0.07148956 | PC22: 0.07148956 | PD22: 0.07148956 | PE22: 3.0535542 | PF22: 0.09238651 | PG22: 0 | PH22: 0 | PI22: 0 | PJ22: 0.09238651 | PK22: 0 | PL22: 0 | PM22: 8.1110158 | PN22: 4.5289388 | PO22: 1.0415479 | PP22: 2.0357028 | PQ22: 0.80178293 | PR22: 0.12988104 | PS22: 0.04282155 | PT22: 0.29180876 | PU22: 0.19042765 | PV22: 0.01259015 | PW22: 2.1556815 | PX22: 0.07425503 | PY22: 0.21171469 | PZ22: 0.17734354 | QA22: 6.9632834 | QB22: 0.05739162 | QC22: 0 | QD22: 0 | QE22: 0 | QF22: 0.60631147 | QG22: 6.4492584 | QH22: 0 | QI22: 0 | QJ22: 0 | QK22: 4.2099854
A23: 40203019 | B23: State Street SPDR Blackstone Senior Loan ETF | C23: US78467V6083 | D23: Matched | E23: US78467V6083 | F23: 36499133 | G23: SRLN | H23: 141.84889 | I23: 7.182644 | J23: 865.99964 | K23: 7.182644 | L23: 1079.7669 | M23: 7.182644 | N23: 213.76728 | O23: 7.182644 | P23: 1.6110367 | Q23: 0.66004251 | R23: 0.14769318 | S23: 0.22376313 | T23: 1.5778185 | U23: 0.34642076 | V23: 0.03321825 | W23: 178.83628 | X23: 7.2058286 | Y23: 995.9191 | Z23: 7.340129 | AA23: 1240.618 | AB23: 7.340129 | AC23: 244.69943 | AD23: 7.340129 | AE23: 202.59174 | AF23: 0.98490083 | AG23: 13120.698 | AH23: 32254.145 | AI23: 4724.2501 | AJ23: 0.86893498 | AK23: 2.4453896 | AL23: Strongly Misaligned | AM23: 7.1617973 | AN23: 1.5290139 | AO23: 2.3327788 | AP23: 4.4 | AQ23: 3.6243234 | AR23: 0.92903951 | AS23: 4.8309271 | AT23: 5.5740303 | AU23: 0.76343539 | AV23: 7.2058286 | AW23: 0.24577612 | AX23: 0.21051218 | AY23: 0 | AZ23: 0.00389657 | BA23: 0.42307 | BB23: 0.73684125 | BC23: 0.10072632 | BD23: 0 | BE23: 0.10549963 | BF23: 0.00467588 | BG23: 0.01676056 | BH23: 0.00276797 | BI23: 0 | BJ23: 0.00011183 | BK23: 0.06446669 | BL23: 0.12739457 | BM23: 0.05307336 | BN23: 0 | BO23: 0.03013525 | BP23: 0.0001337 | BQ23: 0.00115763 | BR23: 0.01051688 | BS23: 0.05868215 | BT23: 0 | BU23: 0.18606323 | BV23: 0.00695284 | BW23: 0.08445814 | BX23: 0.09575819 | BY23: 0.53538865 | BZ23: 0 | CA23: 1.2014098 | CB23: 0.10900653 | CC23: 0.00020227 | CD23: 0 | CE23: 0.01242287 | CG23: 2.3449555 | CH23: 0.28902804 | CI23: 3.1315755 | CJ23: 1.7449812 | CK23: 1.3485052 | CL23: 0.01178712 | CM23: 0.38079225 | CN23: 0 | CO23: 1.5372234 | CP23: 1.9326408 | CQ23: 0.00467588 | CR23: 0.47269368 | CS23: 0.82899518 | CT23: 3.2496992 | CU23: 2.1045948 | CV23: 1.7449415 | CW23: 0.02182079 | CX23: 5.2185384 | CY23: 1.5053422 | CZ23: 0.63011504 | DA23: 2.9865257 | DB23: 3.5344808 | DC23: 2.0077074 | DD23: 1.4678377 | DE23: 4.1964681 | DF23: 7.2003734 | DG23: 4.3017883 | DH23: 6.9388162 | DI23: 7.1012295 | DJ23: 0.70648786 | DK23: 2.4968243 | DL23: 1.0505152 | DM23: 4.5265474 | DN23: 0.36549822 | DO23: 1.1981951 | DP23: 0.03536137 | DQ23: 5.1061687 | DR23: 7.1761172 | DS23: 2.2274739 | DT23: 2.0324507 | DU23: 0.35789991 | DV23: 1.483424 | DW23: 1.3872762 | DX23: 2.0708318 | DY23: 1.9146371 | DZ23: 0.70917565 | EA23: 4.0845452 | EB23: 0.08163308 | EC23: 0.23079673 | ED23: 2.540732 | EE23: 0.36851806 | EF23: 1.6807852 | EG23: 3.3129032 | EH23: 2.8957448 | EI23: 1.4774817 | EJ23: 1.0938645 | EK23: 4.056977 | EL23: 2.0293334 | EM23: 0.94861984 | EN23: 0.04013467 | EO23: 16937.495 | EP23: 0.61692436 | EQ23: 8304.8868 | ER23: 1.3723718 | ES23: 1.5365148 | ET23: 1.1490716 | EU23: 0.23769074 | EV23: 2.4476611 | EW23: 0.00185087 | EX23: 1.6152564 | EY23: 0.05464939 | EZ23: 0.23769074 | FA23: 2.4282446 | FB23: 3.8378287 | FC23: 1.1718932 | FD23: 3.8732209 | FE23: Not Aligned | FF23: 0.30724451 | FG23: 0.30724451 | FH23: 0.19102932 | FI23: 0.02182079 | FJ23: 6.449407 | FK23: 0 | FL23: 0.16920853 | FM23: Aligned | FN23: 0.0930306 | FO23: 0.10549963 | FP23: 0.03682258 | FQ23: 0.03682258 | FR23: 6.8053586 | FS23: 0.01246903 | FT23: 0 | FU23: Not Aligned | FV23: 0.03808897 | FW23: 0.03808897 | FX23: 0.08436073 | FY23: 0.08436073 | FZ23: 6.8252312 | GA23: 0 | GB23: 0 | GC23: Not Aligned | GD23: 0 | GE23: 0 | GF23: 0 | GG23: 0 | GH23: 6.9476809 | GI23: 0 | GJ23: 0 | GK23: Aligned | GL23: 1.5721993 | GM23: 1.5721993 | GN23: 0 | GO23: 0 | GP23: 5.3754816 | GQ23: 0 | GR23: 0 | GS23: Aligned | GT23: 0.16774732 | GU23: 0.16774732 | GV23: 0.11748157 | GW23: 0.11748157 | GX23: 6.662452 | GY23: 0 | GZ23: 0 | HA23: Not Aligned | HB23: 0.73820509 | HC23: 0.73820509 | HD23: 1.4456273 | HE23: 0.02766564 | HF23: 4.7638484 | HG23: 0 | HH23: 1.4179617 | HI23: Aligned | HJ23: 0.16453265 | HK23: 0.16453265 | HL23: 0 | HM23: 0 | HN23: 6.7831482 | HO23: 0 | HP23: 0 | HQ23: Aligned | HR23: 0.46865988 | HS23: 0.46865988 | HT23: 0.04373899 | HU23: 0.04373899 | HV23: 6.435282 | HW23: 0 | HX23: 0 | HY23: Not Aligned | HZ23: 0.11553323 | IA23: 0.11553323 | IB23: 0.21294752 | IC23: 0.04373899 | ID23: 6.6192001 | IE23: 0 | IF23: 0.16920853 | IG23: Aligned | IH23: 0.27470814 | II23: 0.27470814 | IJ23: 0.08065899 | IK23: 0.08065899 | IL23: 6.5923137 | IM23: 0 | IN23: 0 | IO23: Not Aligned | IP23: 0.54474035 | IQ23: 0.57464652 | IR23: 1.4571222 | IS23: 0.03916052 | IT23: 4.9159121 | IU23: 0.02990617 | IV23: 1.4179617 | IW23: Not Aligned | IX23: 1.0503203 | IY23: 1.0503203 | IZ23: 1.4179617 | JA23: 0 | JB23: 4.4793989 | JC23: 0 | JD23: 1.4179617 | JE23: Not Aligned | JF23: 0 | JG23: 0 | JH23: 0.16297401 | JI23: 0.12585919 | JJ23: 6.7847069 | JK23: 0 | JL23: 0.03711482 | JM23: Not Aligned | JN23: 0 | JO23: 0 | JP23: 0.13170405 | JQ23: 0.13170405 | JR23: 6.8159768 | JS23: 0 | JT23: 0 | JU23: Aligned | JV23: 0.12965836 | JW23: 0.12965836 | JX23: 0.05211661 | JY23: 0.05211661 | JZ23: 6.7659059 | KA23: 0 | KB23: 0 | KC23: Aligned | KD23: 0.23769074 | KE23: 0.23769074 | KF23: 0.01422248 | KG23: 0.01422248 | KH23: 6.6957676 | KI23: 0 | KJ23: 0 | KK23: 6.9476809 | KL23: -0.03853128 | KM23: -0.70113009 | KN23: 1.1075999 | KO23: Bond | KP23: Exchange Traded Funds | KQ23: USA | KR23: 4.4825193 | KS23: 9.3448354 | KT23: 7.9325817 | KW23: 1.2282385 | KX23: 2.2218239 | KZ23: 5.4955964 | LD23: BBB | LE23: 2.2202417 | LF23: 1.8837965 | LG23: 0.33802734 | LH23: 0.79610897 | LI23: 0.91396711 | LJ23: 1.3483105 | LK23: 0.43212955 | LL23: 92.067418 | LN23: 92.067418 | LO23: 1.6347083 | LP23: 5.1902735 | LQ23: 4.6384082 | LR23: 1.6855722 | LS23: United States of America | LT23: 5.8816667 | LU23: 3.1954812 | LV23: 724 | LW23: 1 | LX23: 321 | LZ23: The Fund seeks to outperform the Morningstar LSTA US Leveraged Loan Index (the Index) by normally investing at least 80% of its net assets (plus any borrowings for investment purposes) in Senior Loans. For purposes of this 80% test, Senior Loans are first lien senior secured floating rate bank loans. | MA23: 46203 | MB23: Loan Participation Funds | MD23: SSGA Funds Management Inc | ME23: State Street SPDR Blackstone Senior Loan ETF | MF23: 4.759608 | MG23: 3.0515283 | MH23: 5200829363 | MI23: 5.4955964 | ML23: 5.1858534 | MM23: T | MN23: 0.07510638 | MO23: 0 | MP23: 0 | MQ23: 0 | MR23: 0.70303858 | MS23: 0 | MT23: 0 | MU23: 0 | MV23: 0.35458783 | MW23: 0.31708335 | MX23: 0.17339734 | MY23: 0 | MZ23: 0 | NA23: 0 | NB23: 0 | NC23: 0.18050857 | ND23: 0 | NE23: 0.01656042 | NF23: 0.14446531 | NG23: 0.01656042 | NH23: 0.00837762 | NI23: 0.00837762 | NJ23: 0.00837762 | NK23: 0 | NL23: 0.14446531 | NM23: 0 | NN23: 0 | NO23: 0 | NP23: 0 | NQ23: 0 | NR23: 0.21411649 | NS23: 0.21411649 | NT23: 0 | NU23: 0 | NV23: 0.22600103 | NW23: 0 | NX23: 0.33617655 | NY23: 0.29604182 | NZ23: 0.19930953 | OA23: 0.053383 | OB23: 0.053383 | OC23: 0.00642934 | OD23: 0.00642934 | OE23: 0 | OF23: 0 | OG23: 0 | OH23: 0.17554045 | OI23: 0.03974501 | OJ23: 0.19960178 | OK23: 0 | OL23: 0.08065899 | OM23: 1.2335564 | ON23: 0 | OO23: 0 | OP23: 0 | OQ23: 0 | OR23: 0 | OS23: 0.20086817 | OT23: 0 | OU23: 0 | OV23: 0 | OW23: 0 | OX23: 0 | OY23: 0 | OZ23: 0 | PA23: 0 | PB23: 0 | PC23: 0 | PD23: 0 | PE23: 0 | PF23: 0 | PG23: 0 | PH23: 0 | PI23: 0 | PJ23: 0 | PK23: 0 | PL23: 0 | PM23: 0.3442619 | PN23: 0.04373899 | PO23: 0.03682258 | PP23: 0.18304134 | PQ23: 0.08065899 | PR23: 0 | PS23: 0.00014671 | PT23: 0.00728315 | PU23: 0.02081832 | PV23: 0.00300358 | PW23: 0.0536215 | PX23: 0.00032082 | PY23: 0 | PZ23: 0.00193395 | QA23: 0.25746583 | QB23: 0 | QC23: 0 | QD23: 0 | QE23: 0 | QF23: 0 | QG23: 0.19093192 | QH23: 0.00165604 | QI23: 0 | QJ23: 0 | QK23: 0.21411649
