Workbook
Name IQ_CH: 110000
Name IQ_CQ: 5000
Name IQ_CY: 10000
Name IQ_DAILY: 500000
Name IQ_FH: 100000
Name IQ_FQ: 500
Name IQ_FY: 1000
Name IQ_LTM: 2000
Name IQ_MONTH: 15000
Name IQ_NTM: 6000
Name IQ_WEEK: 50000
Name IQ_YTD: 3000

Sheet Filtros FI

Sheet Port Bloomberg
A1: Name | B1: Company Name | C1: Short Name | D1: Issuer | E1: ISIN | F1: Ticker | G1: Eqty Ticker | H1: Group | I1: Sector | J1: Subgroup | K1: Cnty of Dom | L1: Cntry (Risk) | M1: Crncy | N1: Amt Iss (P) | O1: Cpn Type | P1: Cpn (P) | Q1: BB Comp (P) | R1: Mty
A2: ABENGO 6 ⅞ 04/30/43 | B2: Atlantica Transmision Sur SA | C2: ATL TRANS SUR | D2: ATL TRANSMISION SUR | E2: USP00173AA51 | F2: ABENGO | G2: AY US | H2: Electric | I2: UTL | J2: Electric-Transmission | K2: PE | L2: PE | M2: USD | N2: 432000 | O2: SINGLE | P2: 6.875 | Q2: BBB- | R2: 04/30/2043
A3: ABRAGF 14 10/22/29 | B3: ABRA Global Finance | C3: ABRA GLOBAL FIN | D3: ABRA GLOBAL FINANCE | E3: USG00912AC21 | F3: ABRAGF | G3: 2058922D LN | H3: Airlines | I3: IND | J3: Airlines | K3: KY | L3: CO | M3: USD | N3: 560672.64 | O3: PIK | P3: 14 | Q3: NR | R3: 10/22/2029
A4: ACUPET 7 ½ 01/13/32 | B4: Acu Petroleo Luxembourg Sarl | C4: ACU PETROLEO LUX | D4: ACU PETROLEO LUXEMBOURG | E4: USL0R80QAA10 | F4: ACUPET | G4: 1469040D BZ | H4: Pipelines | I4: IND | J4: Pipelines | K4: LU | L4: BR | M4: USD | N4: 600000 | O4: SINGLE | P4: 7.5 | Q4: BB+ | R4: 01/13/2032
A5: AEGEBZ 6 ¾ 05/20/29 | B5: Aegea Finance Sarl | C5: AEGEA FINANCE | D5: AEGEA FINANCE SARL | E5: USL01343AA79 | F5: AEGEBZ | G5: 0596570D BZ | H5: Water | I5: UTL | J5: Water | K5: LU | L5: BR | M5: USD | N5: 500000 | O5: SINGLE | P5: 6.75 | Q5: B | R5: 05/20/2029
A6: AEGEBZ 7 ⅝ 01/20/36 | B6: Aegea Finance Sarl | C6: AEGEA FINANCE | D6: AEGEA FINANCE SARL | E6: USL01343AE91 | F6: AEGEBZ | G6: 0596570D BZ | H6: Water | I6: UTL | J6: Water | K6: LU | L6: BR | M6: USD | N6: 750000 | O6: SINGLE | P6: 7.625 | Q6: B | R6: 01/20/2036
A7: AEGEBZ 9 01/20/31 | B7: Aegea Finance Sarl | C7: AEGEA FINANCE | D7: AEGEA FINANCE SARL | E7: USL01343AB52 | F7: AEGEBZ | G7: 0596570D BZ | H7: Water | I7: UTL | J7: Water | K7: LU | L7: BR | M7: USD | N7: 800000 | O7: SINGLE | P7: 9 | Q7: B | R7: 01/20/2031
A8: AEROMX 8 ¼ 11/15/29 | B8: Grupo Aeromexico SAB de CV | C8: GRUPO AEROMEXICO | D8: GRUPO AEROMEXICO SAB | E8: USP4955JAB46 | F8: AEROMX | G8: AERO* MM | H8: Airlines | I8: IND | J8: Airlines | K8: MX | L8: MX | M8: USD | N8: 500000 | O8: SINGLE | P8: 8.25 | Q8: BB- | R8: 11/15/2029
A9: AEROMX 8 ⅝ 11/15/31 | B9: Grupo Aeromexico SAB de CV | C9: GRUPO AEROMEXICO | D9: GRUPO AEROMEXICO SAB | E9: USP4955JAC29 | F9: AEROMX | G9: AERO* MM | H9: Airlines | I9: IND | J9: Airlines | K9: MX | L9: MX | M9: USD | N9: 610000 | O9: SINGLE | P9: 8.625 | Q9: BB- | R9: 11/15/2031
A10: AES 4.72 06/30/40 | B10: Alto Maipo SpA | C10: ALTO MAIPO SPA | D10: ALTO MAIPO SPA | E10: USP0243BAA37 | F10: AES | G10: AESANDES CI | H10: Energy-Alternate Sources | I10: UTL | J10: Energy-Alternate Sources | K10: CL | L10: CL | M10: USD | O10: STEPUP1 | P10: 4 | R10: 06/30/2040
A11: AES 6 ¼ 03/14/32 | B11: AES Andes SA | C11: AES ANDES SA | D11: AES ANDES SA | E11: USP0091LAD84 | F11: AES | G11: AESANDES CI | H11: Electric | I11: UTL | J11: Electric-Generation | K11: CL | L11: CL | M11: USD | N11: 400000 | O11: SINGLE | P11: 6.25 | Q11: BBB- | R11: 03/14/2032
A12: AES 6 ¼ 11/14/34 | B12: AES Andes SA | C12: AES ANDES SA | D12: AES ANDES SA | E12: USP0091LAE67 | F12: AES | G12: AESANDES CI | H12: Electric | I12: UTL | J12: Electric-Generation | K12: CL | L12: CL | M12: USD | N12: 485000 | O12: SINGLE | P12: 6.25 | Q12: BBB- | R12: 11/14/2034
A13: AES 6.3 03/15/29 | B13: AES Andes SA | C13: AES ANDES SA | D13: AES ANDES SA | E13: USP0091LAA46 | F13: AES | G13: AESANDES CI | H13: Electric | I13: UTL | J13: Electric-Generation | K13: CL | L13: CL | M13: USD | N13: 500000 | O13: SINGLE | P13: 6.3 | Q13: BBB- | R13: 03/15/2029
A14: AES 8.15 06/10/55 | B14: AES Andes SA | C14: AES ANDES SA | D14: AES ANDES SA | E14: USP0091LAC02 | F14: AES | G14: AESANDES CI | H14: Electric | I14: UTL | J14: Electric-Generation | K14: CL | L14: CL | M14: USD | N14: 530000 | O14: SINGLE | P14: 8.15 | Q14: BB | R14: 06/10/2055
A15: AGRO 7 ½ 07/29/32 | B15: Adecoagro SA | C15: ADECOAGRO SA | D15: ADECOAGRO SA | E15: USL00849AB20 | F15: AGRO | G15: AGRO US | H15: Agriculture | I15: IND | J15: Agricultural Operations | K15: AR | L15: BR | M15: USD | N15: 500000 | O15: SINGLE | P15: 7.5 | Q15: B+ | R15: 07/29/2032
A16: AGROSU 4.6 01/20/32 | B16: Agrosuper SA | C16: AGROSUPER | D16: AGROSUPER SA | E16: USP01020AK52 | F16: AGROSU | G16: 4627222Z CI | H16: Food | I16: IND | J16: Food-Meat Products | K16: CL | L16: CL | M16: USD | N16: 500000 | O16: SINGLE | P16: 4.6 | Q16: BBB- | R16: 01/20/2032
A17: AICNRA 5 ¾ 06/15/33 | B17: AI Candelaria -spain- SA | C17: AI CANDELARIA | D17: AI CANDELARIA -SPAIN- SA | E17: USE0R75RAB28 | F17: AICNRA | G17: 1666958D SM | H17: Pipelines | I17: IND | J17: Pipelines | K17: ES | L17: CO | M17: USD | N17: 600000 | O17: SINGLE | P17: 5.75 | Q17: B | R17: 06/15/2033
A18: ALFACL 4.55 09/27/51 | B18: Alfa Desarrollo SpA | C18: ALFA DESARROLLO | D18: ALFA DESARROLLO SPA | E18: USP0R60QAA15 | F18: ALFACL | G18: COLBUN CI | H18: Electric | I18: UTL | J18: Electric-Transmission | K18: CL | L18: CL | M18: USD | N18: 1098618 | O18: SINGLE | P18: 4.55 | Q18: BBB- | R18: 09/27/2051
A19: ALPEKA 3 ¼ 02/25/31 | B19: Alpek SAB de CV | C19: ALPEK SA DE CV | D19: ALPEK SA DE CV | E19: USP01703AD22 | F19: ALPEKA | G19: ALPEKA MM | H19: Chemicals | I19: IND | J19: Petrochemicals | K19: MX | L19: MX | M19: USD | N19: 600000 | O19: SINGLE | P19: 3.25 | Q19: BB+ | R19: 02/25/2031
A20: ALPEKA 4 ¼ 09/18/29 | B20: Alpek SAB de CV | C20: ALPEK SA DE CV | D20: ALPEK SA DE CV | E20: USP01703AC49 | F20: ALPEKA | G20: ALPEKA MM | H20: Chemicals | I20: IND | J20: Petrochemicals | K20: MX | L20: MX | M20: USD | N20: 500000 | O20: SINGLE | P20: 4.25 | Q20: BB+ | R20: 09/18/2029
A21: AMXLMM 2 ⅞ 05/07/30 | B21: America Movil SAB de CV | C21: AMERICA MOVIL SA | D21: AMERICA MOVIL SAB DE CV | E21: US02364WBJ36 | F21: AMXLMM | G21: AMXB MM | H21: Telecommunications | I21: IND | J21: Cellular Telecom | K21: MX | L21: MX | M21: USD | N21: 1000000 | O21: SINGLE | P21: 2.875 | Q21: BBB+ | R21: 05/07/2030
A22: AMXLMM 3 ⅝ 04/22/29 | B22: America Movil SAB de CV | C22: AMERICA MOVIL SA | D22: AMERICA MOVIL SAB DE CV | E22: US02364WBH79 | F22: AMXLMM | G22: AMXB MM | H22: Telecommunications | I22: IND | J22: Cellular Telecom | K22: MX | L22: MX | M22: USD | N22: 1000000 | O22: SINGLE | P22: 3.625 | Q22: BBB+ | R22: 04/22/2029
... A36: ARISCN 8 10/31/29 | B36: Aris Mining Corp | C36: ARIS MINING | D36: ARIS MINING CORP | E36: USC04492AA97 | F36: ARISCN | G36: ARIS CN | H36: Mining | I36: IND | J36: Gold Mining | K36: CA | L36: CO | M36: USD | N36: 450000 | O36: SINGLE | P36: 8 | Q36: B+ | R36: 10/31/2029
A37: ATPTOW 7 ⅞ 02/03/30 | B37: ATP Tower Holdings / Andean Telecom Partners Chile SpA / Andean Tower Partners C | C37: ATP TOW/ANDEAN | D37: ATP TOW/ANDEAN TELECOM | E37: USU0489EAA48 | F37: ATPTOW | H37: Engineering&Construction | I37: IND | J37: Building-Heavy Construct | K37: US | L37: CL | M37: USD | N37: 500000 | O37: SINGLE | P37: 7.875 | Q37: BB- | R37: 02/03/2030
A38: AUNA 8 ¾ 11/06/32 | B38: Auna SA / Oncosalud SAC | C38: AUNA SA/ONCOSALU | D38: AUNA SA / ONCOSALUD SAC | E38: USL04168AA59 | F38: AUNA | G38: AUNA US | H38: Healthcare-Services | I38: IND | J38: Medical-Hospitals | K38: LU | L38: PE | M38: USD | N38: 365000 | O38: SINGLE | P38: 8.75 | Q38: B+ | R38: 11/06/2032
A39: AVALCB 4 ⅜ 02/04/30 | B39: Grupo Aval Ltd | C39: GRUPO AVAL LTD | D39: GRUPO AVAL LTD | E39: USG42045AC15 | F39: AVALCB | G39: AVAL CB | H39: Banks | I39: FIN | J39: Commer Banks Non-US | K39: KY | L39: CO | M39: USD | N39: 1000000 | O39: SINGLE | P39: 4.375 | Q39: BB | R39: 02/04/2030
A40: AZUBBZ 9 ⅞ 02/15/31 | B40: Azul Secured Finance LLP | C40: AZUL SECURED FIN | D40: AZUL SECURED FINANCE LLP | E40: USU0551YAK11 | F40: AZUBBZ | G40: 2870534Z BZ | H40: Airlines | I40: IND | J40: Airlines | K40: US | L40: BR | M40: USD | N40: 1375000 | O40: SINGLE | P40: 9.875 | Q40: B- | R40: 02/15/2031
A41: BANBRA 4 ⅞ 01/11/29 | B41: Banco do Brasil SA/Cayman | C41: BANCO BRASL (CI) | D41: BANCO DO BRASIL (CAYMAN) | E41: USP3772WAK82 | F41: BANBRA | G41: BBAS3 BZ | H41: Banks | I41: FOA | J41: Commer Banks Non-US | K41: KY | L41: BR | M41: USD | N41: 500000 | O41: SINGLE | P41: 4.875 | Q41: BB | R41: 01/11/2029
A42: BANBRA 5 ⅝ 10/23/31 | B42: Banco do Brasil SA/Cayman | C42: BANCO BRASL (CI) | D42: BANCO DO BRASIL (CAYMAN) | E42: USP3772WAL65 | F42: BANBRA | G42: BBAS3 BZ | H42: Banks | I42: FOA | J42: Commer Banks Non-US | K42: KY | L42: BR | M42: USD | N42: 500000 | O42: SINGLE | P42: 5.625 | Q42: BB | R42: 10/23/2031
A43: BANBRA 6 03/18/31 | B43: Banco do Brasil SA/Cayman | C43: BANCO BRASL (CI) | D43: BANCO DO BRASIL (CAYMAN) | E43: USP2000TAE57 | F43: BANBRA | G43: BBAS3 BZ | H43: Banks | I43: FOA | J43: Commer Banks Non-US | K43: KY | L43: BR | M43: USD | N43: 750000 | O43: SINGLE | P43: 6 | Q43: BB | R43: 03/18/2031
A44: BANBRA 6 ¼ 04/18/30 | B44: Banco do Brasil SA/Cayman | C44: BANCO BRASL (CI) | D44: BANCO DO BRASIL (CAYMAN) | E44: USP2000TAB19 | F44: BANBRA | G44: BBAS3 BZ | H44: Banks | I44: FOA | J44: Commer Banks Non-US | K44: KY | L44: BR | M44: USD | N44: 750000 | O44: SINGLE | P44: 6.25 | Q44: BB | R44: 04/18/2030
A45: BANCO 7.95 PERP | B45: Banco del Estado de Chile | C45: BANCO DEL ESTADO | D45: BANCO DEL ESTADO -CHILE | E45: USP1027DHQ71 | F45: BANCO | G45: 167579Z CI | H45: Banks | I45: FOA | J45: Regional Banks-Non US | K45: CL | L45: CL | M45: USD | N45: 600000 | O45: SINGLE | P45: 7.95 | Q45: BBB-
A46: BANMEX 6.697 08/07/36 | B46: Banco Nacional de Mexico SA | C46: BANCO NAC DE MEX | D46: BANCO NAC DE MEXICO SA | E46: USP1S8TDFJ81 | F46: BANMEX | G46: BANAMEX MM | H46: Banks | I46: FIN | J46: Commer Banks Non-US | K46: MX | L46: MX | M46: USD | N46: 1300000 | O46: SINGLE | P46: 6.697 | Q46: BB+ | R46: 08/07/2036
A47: BANORT 6 ⅝ PERP | B47: Banco Mercantil del Norte SA/Grand Cayman | C47: BANCO MERC NORTE | D47: BANCO MERCANTIL DE NORTE | E47: USP1401KAB72 | F47: BANORT | G47: BMNA MM | H47: Banks | I47: FIN | J47: Commer Banks Non-US | K47: KY | L47: MX | M47: USD | N47: 550000 | O47: SINGLE | P47: 6.625 | Q47: BB-
A48: BANORT 7 ½ PERP | B48: Banco Mercantil del Norte SA/Grand Cayman | C48: BANCO MERC NORTE | D48: BANCO MERCANTIL DE NORTE | E48: USP1400MAB48 | F48: BANORT | G48: BMNA MM | H48: Banks | I48: FIN | J48: Commer Banks Non-US | K48: KY | L48: MX | M48: USD | N48: 500000 | O48: SINGLE | P48: 7.5 | Q48: BB-
A49: BANORT 8 PERP | B49: Banco Mercantil del Norte SA/Grand Cayman | C49: BANCO MERC NORTE | D49: BANCO MERCANTIL DE NORTE | E49: USP1400MAF51 | F49: BANORT | G49: BMNA MM | H49: Banks | I49: FIN | J49: Commer Banks Non-US | K49: KY | L49: MX | M49: USD | N49: 600000 | O49: SINGLE | P49: 8 | Q49: BB-
A50: BANORT 8 ¾ PERP | B50: Banco Mercantil del Norte SA/Grand Cayman | C50: BANCO MERC NORTE | D50: BANCO MERCANTIL DE NORTE | E50: USP1400MAE86 | F50: BANORT | G50: BMNA MM | H50: Banks | I50: FIN | J50: Commer Banks Non-US | K50: KY | L50: MX | M50: USD | N50: 750000 | O50: SINGLE | P50: 8.75 | Q50: BB-
A51: BANORT 8 ⅜ PERP | B51: Banco Mercantil del Norte SA/Grand Cayman | C51: BANCO MERC NORTE | D51: BANCO MERCANTIL DE NORTE | E51: USP1400MAD04 | F51: BANORT | G51: BMNA MM | H51: Banks | I51: FIN | J51: Commer Banks Non-US | K51: KY | L51: MX | M51: USD | N51: 750000 | O51: SINGLE | P51: 8.375 | Q51: BB-
A52: BANORT 8 ⅜ PERP | B52: Banco Mercantil del Norte SA/Grand Cayman | C52: BANCO MERC NORTE | D52: BANCO MERCANTIL DE NORTE | E52: USP1400MAC21 | F52: BANORT | G52: BMNA MM | H52: Banks | I52: FIN | J52: Commer Banks Non-US | K52: KY | L52: MX | M52: USD | N52: 500000 | O52: SINGLE | P52: 8.375 | Q52: BB-
A53: BANORT 8.45 PERP | B53: Banco Mercantil del Norte SA/Grand Cayman | C53: BANCO MERC NORTE | D53: BANCO MERCANTIL DE NORTE | E53: USP1400MAG35 | F53: BANORT | G53: BMNA MM | H53: Banks | I53: FIN | J53: Commer Banks Non-US | K53: KY | L53: MX | M53: USD | N53: 750000 | O53: SINGLE | P53: 8.45 | Q53: BB-
A54: BBVASM 5 ¼ 09/10/29 | B54: BBVA Mexico SA Institucion De Banca Multiple Grupo Financiero BBVA Mexico/TX | C54: BBVA MEX BANC/TX | D54: BBVA MEX BANCA GRUPO TX | E54: USP1S81BAC21 | F54: BBVASM | G54: 1470Z MM | H54: Banks | I54: FIN | J54: Money Center Banks | K54: US | L54: MX | M54: USD | N54: 600000 | O54: SINGLE | P54: 5.25 | Q54: BBB+ | R54: 09/10/2029
A55: BBVASM 5 ⅞ 09/13/34 | B55: BBVA Mexico SA Institucion De Banca Multiple Grupo Financiero BBVA Mexico/TX | C55: BBVA MEX BANC/TX | D55: BBVA MEX BANCA GRUPO TX | E55: USP16259AN67 | F55: BBVASM | G55: 1470Z MM | H55: Banks | I55: FIN | J55: Money Center Banks | K55: US | L55: MX | M55: USD | N55: 750000 | O55: SINGLE | P55: 5.875 | Q55: BB+ | R55: 09/13/2034
A56: BBVASM 5.4 06/03/31 | B56: BBVA Mexico SA Institucion De Banca Multiple Grupo Financiero BBVA Mexico/TX | C56: BBVA MEX BANC/TX | D56: BBVA MEX BANCA GRUPO TX | E56: USP2000GAB97 | F56: BBVASM | G56: 1470Z MM | H56: Banks | I56: FIN | J56: Money Center Banks | K56: US | L56: MX | M56: USD | N56: 1000000 | O56: SINGLE | P56: 5.4 | Q56: BBB+ | R56: 06/03/2031
A57: BBVASM 7 ⅝ 02/11/35 | B57: BBVA Mexico SA Institucion De Banca Multiple Grupo Financiero BBVA Mexico/TX | C57: BBVA MEX BANC/TX | D57: BBVA MEX BANCA GRUPO TX | E57: USP2000GAA15 | F57: BBVASM | G57: 1470Z MM | H57: Banks | I57: FIN | J57: Money Center Banks | K57: US | L57: MX | M57: USD | N57: 1000000 | O57: SINGLE | P57: 7.625 | Q57: BB+ | R57: 02/11/2035
A58: BBVASM 8 ⅛ 01/08/39 | B58: BBVA Mexico SA Institucion De Banca Multiple Grupo Financiero BBVA Mexico/TX | C58: BBVA MEX BANC/TX | D58: BBVA MEX BANCA GRUPO TX | E58: USP1S81BAB48 | F58: BBVASM | G58: 1470Z MM | H58: Banks | I58: FIN | J58: Money Center Banks | K58: US | L58: MX | M58: USD | N58: 900000 | O58: SINGLE | P58: 8.125 | Q58: BB+ | R58: 01/08/2039
A59: BBVASM 8.45 06/29/38 | B59: BBVA Mexico SA Institucion De Banca Multiple Grupo Financiero BBVA Mexico/TX | C59: BBVA MEX BANC/TX | D59: BBVA MEX BANCA GRUPO TX | E59: USP1S81BAA64 | F59: BBVASM | G59: 1470Z MM | H59: Banks | I59: FIN | J59: Money Center Banks | K59: US | L59: MX | M59: USD | N59: 1000000 | O59: SINGLE | P59: 8.45 | Q59: BB+ | R59: 06/29/2038
A60: BCAJA 7 07/30/29 | B60: Caja de Compensacion de Asignacion Familiar de Los Andes | C60: CAJA LOS ANDES | D60: CAJA ASIGNACION LOS ANDE | E60: USP1913PAS04 | F60: BCAJA | G60: 8181326Z CI | H60: Diversified Finan Serv | I60: FIN | J60: Finance-Other Services | K60: CL | L60: CL | M60: USD | N60: 300000 | O60: SINGLE | P60: 7 | Q60: BBB- | R60: 07/30/2029
A61: BCAPS 3.9 04/27/31 | B61: CAP SA | C61: CAP | D61: CAP SA | E61: USP2316YAA12 | F61: BCAPS | G61: CAP CI | H61: Iron/Steel | I61: IND | J61: Steel-Producers | K61: CL | L61: CL | M61: USD | N61: 300000 | O61: SINGLE | P61: 3.9 | Q61: BB | R61: 04/27/2031
A62: BCICI 2 ⅞ 10/14/31 | B62: Banco de Credito e Inversiones SA | C62: BANC CRED INVERS | D62: BANC CREDITO INVERSIONES | E62: US05890PAB22 | F62: BCICI | G62: BCI CI | H62: Banks | I62: FIN | J62: Commer Banks Non-US | K62: CL | L62: CL | M62: USD | N62: 500000 | O62: SINGLE | P62: 2.875 | Q62: A- | R62: 10/14/2031
A63: BCICI 7 ½ PERP | B63: Banco de Credito e Inversiones SA | C63: BANC CRED INVERS | D63: BANC CREDITO INVERSIONES | E63: USP32133CH47 | F63: BCICI | G63: BCI CI | H63: Banks | I63: FIN | J63: Commer Banks Non-US | K63: CL | L63: CL | M63: USD | N63: 500000 | O63: SINGLE | P63: 7.5 | Q63: BB+
A64: BCICI 8 ¾ PERP | B64: Banco de Credito e Inversiones SA | C64: BANC CRED INVERS | D64: BANC CREDITO INVERSIONES | E64: US05890PAC05 | F64: BCICI | G64: BCI CI | H64: Banks | I64: FIN | J64: Commer Banks Non-US | K64: CL | L64: CL | M64: USD | N64: 500000 | O64: SINGLE | P64: 8.75 | Q64: BB+
A65: BCOCPE 6.2 06/07/34 | B65: Banco BBVA Peru SA | C65: BANCO BBVA PERU | D65: BANCO BBVA PERU SA | E65: USP07760AH74 | F65: BCOCPE | G65: BBVAC1 PE | H65: Banks | I65: FIN | J65: Commer Banks Non-US | K65: PE | L65: PE | M65: USD | N65: 300000 | O65: SINGLE | P65: 6.2 | Q65: BBB- | R65: 06/07/2034
A66: BCOLO 8 ⅝ 12/24/34 | B66: Bancolombia SA | C66: BANCOLOMBIA | D66: BANCOLOMBIA SA | E66: US05968LAN29 | F66: BCOLO | G66: BCOLO CB | H66: Banks | I66: FIN | J66: Commer Banks Non-US | K66: CO | L66: CO | M66: USD | N66: 800000 | O66: SINGLE | P66: 8.625 | Q66: BB- | R66: 12/24/2034
A67: BCP 5.65 01/15/37 | B67: Banco de Credito del Peru S.A. | C67: BANCO DE CREDITO | D67: BANCO DE CREDITO DEL PER | E67: US05971V2K08 | F67: BCP | G67: CREDITC1 PE | H67: Banks | I67: FIN | J67: Commer Banks Non-US | K67: PE | L67: PE | M67: USD | N67: 500000 | O67: SINGLE | P67: 5.65 | Q67: BBB- | R67: 01/15/2037
A68: BCP 5.8 03/10/35 | B68: Banco de Credito del Peru S.A. | C68: BANCO DE CREDITO | D68: BANCO DE CREDITO DEL PER | E68: US05971V2H78 | F68: BCP | G68: CREDITC1 PE | H68: Banks | I68: FIN | J68: Commer Banks Non-US | K68: PE | L68: PE | M68: USD | N68: 600000 | O68: SINGLE | P68: 5.8 | Q68: BBB- | R68: 03/10/2035
A69: BCP 5.85 01/11/29 | B69: Banco de Credito del Peru S.A. | C69: BANCO DE CREDITO | D69: BANCO DE CREDITO DEL PER | E69: US05971V2E48 | F69: BCP | G69: CREDITC1 PE | H69: Banks | I69: FIN | J69: Commer Banks Non-US | K69: PE | L69: PE | M69: USD | N69: 500000 | O69: SINGLE | P69: 5.85 | Q69: BBB | R69: 01/11/2029
A70: BCP 6.45 07/30/35 | B70: Banco de Credito del Peru S.A. | C70: BANCO DE CREDITO | D70: BANCO DE CREDITO DEL PER | E70: US05971V2J35 | F70: BCP | G70: CREDITC1 PE | H70: Banks | I70: FIN | J70: Commer Banks Non-US | K70: PE | L70: PE | M70: USD | N70: 750000 | O70: SINGLE | P70: 6.45 | Q70: BBB- | R70: 07/30/2035
A71: BEEFBZ 4 ⅜ 03/18/31 | B71: Minerva Luxembourg SA | C71: MINERVA LUX SA | D71: MINERVA LUXEMBOURG SA | E71: USL6401PAJ23 | F71: BEEFBZ | G71: BEEF3 BZ | H71: Food | I71: IND | J71: Food-Meat Products | K71: LU | L71: BR | M71: USD | N71: 1400000 | O71: SINGLE | P71: 4.375 | Q71: BB | R71: 03/18/2031
A72: BEEFBZ 7 ½ 04/22/36 | B72: Minerva Luxembourg SA | C72: MINERVA LUX SA | D72: MINERVA LUXEMBOURG SA | E72: USL6401PAP82 | F72: BEEFBZ | G72: BEEF3 BZ | H72: Food | I72: IND | J72: Food-Meat Products | K72: LU | L72: BR | M72: USD | N72: 600000 | O72: SINGLE | P72: 7.5 | Q72: BB | R72: 04/22/2036
A73: BEEFBZ 8 ⅞ 09/13/33 | B73: Minerva Luxembourg SA | C73: MINERVA LUX SA | D73: MINERVA LUXEMBOURG SA | E73: USL6401PAM51 | F73: BEEFBZ | G73: BEEF3 BZ | H73: Food | I73: IND | J73: Food-Meat Products | K73: LU | L73: BR | M73: USD | N73: 1000000 | O73: SINGLE | P73: 8.875 | Q73: BB | R73: 09/13/2033
A74: BFALA 3 ⅜ 01/15/32 | B74: Falabella SA | C74: FALABELLA SA | D74: FALABELLA SA | E74: USP3984LAA81 | F74: BFALA | G74: FALAB CI | H74: Retail | I74: IND | J74: Retail-Regnl Dept Store | K74: CL | L74: CL | M74: USD | N74: 650000 | O74: SINGLE | P74: 3.375 | Q74: BBB- | R74: 01/15/2032
A75: BFFCC 3.068 08/18/50 | B75: Empresa de los Ferrocarriles del Estado | C75: EFE | D75: EMPRESA DE LOS FERROCARR | E75: USP3742RAW09 | F75: BFFCC | G75: 2940894Z CI | H75: Transportation | I75: FOA | J75: Transport-Rail | K75: CL | L75: CL | M75: USD | N75: 500000 | O75: SINGLE | P75: 3.068 | Q75: A- | R75: 08/18/2050
A76: BFFCC 3.83 09/14/61 | B76: Empresa de los Ferrocarriles del Estado | C76: EFE | D76: EMPRESA DE LOS FERROCARR | E76: USP3742RAX81 | F76: BFFCC | G76: 2940894Z CI | H76: Transportation | I76: FOA | J76: Transport-Rail | K76: CL | L76: CL | M76: USD | N76: 500000 | O76: SINGLE | P76: 3.83 | Q76: A- | R76: 09/14/2061
... A94: BNSPE 6.1 10/01/35 | B94: Scotiabank Peru SAA | C94: SCOTIABANK PERU | D94: SCOTIABANK PERU SA | E94: USP8T35JAP76 | F94: BNSPE | G94: SCOTIAC1 PE | H94: Banks | I94: FIN | J94: Commer Banks Non-US | K94: PE | L94: PE | M94: USD | N94: 400000 | O94: SINGLE | P94: 6.1 | Q94: BBB | R94: 10/01/2035
A95: BORLTD 9 ½ 08/07/32 | B95: Boroo Investments Pte Ltd | C95: BOROO INV PT LTD | D95: BOROO INVESTMENTS | E95: USY00601AA55 | F95: BORLTD | H95: Mining | I95: IND | J95: Gold Mining | K95: SG | L95: PE | M95: USD | N95: 300000 | O95: SINGLE | P95: 9.5 | Q95: B+ | R95: 08/07/2032
A96: BORRNO 8 ¾ 01/15/32 | B96: Borr IHC Ltd / Borr Finance LLC | C96: BORR IHC/BORR FI | D96: BORR IHC LTD / BORR FIN | E96: USG1467FAH67 | F96: BORRNO | G96: BORR US | H96: Oil&Gas | I96: IND | J96: Oil&Gas Drilling | K96: US | L96: MX | M96: USD | N96: 1100000 | O96: SINGLE | P96: 8.75 | Q96: B- | R96: 01/15/2032
A97: BORRNO 9 01/15/34 | B97: Borr IHC Ltd / Borr Finance LLC | C97: BORR IHC/BORR FI | D97: BORR IHC LTD / BORR FIN | E97: USG1467FAJ24 | F97: BORRNO | G97: BORR US | H97: Oil&Gas | I97: IND | J97: Oil&Gas Drilling | K97: US | L97: MX | M97: USD | N97: 935000 | O97: SINGLE | P97: 9 | Q97: B- | R97: 01/15/2034
A98: BQUILL 7.35 07/23/31 | B98: Barranquilla Distrito Especial Industrial y Portuario | C98: BARRANQUILLA DIS | D98: BARRANQUILLA | E98: USP3600PAD70 | F98: BQUILL | H98: Municipal | I98: FLA | J98: Municipal-City | K98: CO | L98: CO | M98: USD | N98: 350000 | O98: SINGLE | P98: 7.35 | R98: 07/23/2031
A99: BRADES 5 ⅜ 01/20/31 | B99: Banco Bradesco SA/Cayman Islands | C99: BANCO BRADES CI | D99: BANCO BRADESCO (CAYMAN) | E99: US05947LBD91 | F99: BRADES | G99: BBDC4 BZ | H99: Banks | I99: FIN | J99: Commer Banks Non-US | K99: KY | L99: BR | M99: USD | N99: 750000 | O99: SINGLE | P99: 5.375 | Q99: BB | R99: 01/20/2031
A100: BRADES 6 ½ 01/22/30 | B100: Banco Bradesco SA/Cayman Islands | C100: BANCO BRADES CI | D100: BANCO BRADESCO (CAYMAN) | E100: US05947LBB36 | F100: BRADES | G100: BBDC4 BZ | H100: Banks | I100: FIN | J100: Commer Banks Non-US | K100: KY | L100: BR | M100: USD | N100: 1000000 | O100: SINGLE | P100: 6.5 | Q100: BB | R100: 01/22/2030
A101: BRASKM 12.004 01/23/2081 | B101: Braskem Netherlands Finance BV | C101: BRASKEM NL | D101: BRASKEM NETHERLANDS | E101: USN15516AF97 | F101: BRASKM | G101: BRKM3 BZ | H101: Chemicals | I101: IND | J101: Chemicals-Diversified | K101: NL | L101: BR | M101: USD | N101: 600000 | O101: SINGLE | P101: 12.004 | Q101: DD+ | R101: 01/23/2081
A102: BRASKM 4 ½ 01/31/30 | B102: Braskem Netherlands Finance BV | C102: BRASKEM NL | D102: BRASKEM NETHERLANDS | E102: USN15516AD40 | F102: BRASKM | G102: BRKM3 BZ | H102: Chemicals | I102: IND | J102: Chemicals-Diversified | K102: NL | L102: BR | M102: USD | N102: 1500000 | O102: SINGLE | P102: 4.5 | Q102: DD+ | R102: 01/31/2030
A103: BRASKM 5 ⅞ 01/31/50 | B103: Braskem Netherlands Finance BV | C103: BRASKEM NL | D103: BRASKEM NETHERLANDS | E103: USN15516AE23 | F103: BRASKM | G103: BRKM3 BZ | H103: Chemicals | I103: IND | J103: Chemicals-Diversified | K103: NL | L103: BR | M103: USD | N103: 750000 | O103: SINGLE | P103: 5.875 | Q103: DD+ | R103: 01/31/2050
A104: BRASKM 7 ¼ 02/13/33 | B104: Braskem Netherlands Finance BV | C104: BRASKEM NL | D104: BRASKEM NETHERLANDS | E104: USN15516AG70 | F104: BRASKM | G104: BRKM3 BZ | H104: Chemicals | I104: IND | J104: Chemicals-Diversified | K104: NL | L104: BR | M104: USD | N104: 1000000 | O104: SINGLE | P104: 7.25 | Q104: DD+ | R104: 02/13/2033
A105: BRASKM 7 ⅛ 07/22/41 | B105: Braskem America Finance Co | C105: BRASKEM AMERICA | D105: BRASKEM AMERICA FINANCE | E105: USU1065PAA94 | F105: BRASKM | G105: BRKM3 BZ | H105: Chemicals | I105: IND | J105: Petrochemicals | K105: US | L105: BR | M105: USD | N105: 750000 | O105: SINGLE | P105: 7.125 | Q105: DD+ | R105: 07/22/2041
A106: BRASKM 8 10/15/34 | B106: Braskem Netherlands Finance BV | C106: BRASKEM NL | D106: BRASKEM NETHERLANDS | E106: USN15516AJ10 | F106: BRASKM | G106: BRKM3 BZ | H106: Chemicals | I106: IND | J106: Chemicals-Diversified | K106: NL | L106: BR | M106: USD | N106: 850000 | O106: SINGLE | P106: 8 | Q106: DD+ | R106: 10/15/2034
A107: BRASKM 8 ½ 01/12/31 | B107: Braskem Netherlands Finance BV | C107: BRASKEM NL | D107: BRASKEM NETHERLANDS | E107: USN15516AH53 | F107: BRASKM | G107: BRKM3 BZ | H107: Chemicals | I107: IND | J107: Chemicals-Diversified | K107: NL | L107: BR | M107: USD | N107: 850000 | O107: SINGLE | P107: 8.5 | Q107: DD+ | R107: 01/12/2031
A108: BRFSBZ 4 ⅞ 01/24/30 | B108: BRF SA | C108: BRF SA | D108: BRF SA | E108: USP1905CJX94 | F108: BRFSBZ | G108: BRFS3 BZ | H108: Food | I108: IND | J108: Food-Meat Products | K108: BR | L108: BR | M108: USD | N108: 750000 | O108: SINGLE | P108: 4.875 | Q108: BB | R108: 01/24/2030
A109: BRFSBZ 5 ¾ 09/21/50 | B109: BRF SA | C109: BRF SA | D109: BRF SA | E109: USP1905CAJ91 | F109: BRFSBZ | G109: BRFS3 BZ | H109: Food | I109: IND | J109: Food-Meat Products | K109: BR | L109: BR | M109: USD | N109: 800000 | O109: SINGLE | P109: 5.75 | Q109: BB | R109: 09/21/2050
A110: BSANCI 3.177 10/26/31 | B110: Banco Santander Chile | C110: BANCO SANTAND | D110: BANCO SANTANDER CHILE | E110: US05971WAD56 | F110: BSANCI | G110: BSAN CI | H110: Banks | I110: FIN | J110: Commer Banks Non-US | K110: CL | L110: CL | M110: USD | N110: 500000 | O110: SINGLE | P110: 3.177 | Q110: A- | R110: 10/26/2031
... A128: CDEL 4 ⅞ 11/04/44 | B128: Corp Nacional del Cobre de Chile | C128: CODELCO INC | D128: CODELCO INC | E128: USP3143NAU83 | F128: CDEL | G128: 1006Z CI | H128: Mining | I128: FOA | J128: Non-Ferrous Metals | K128: CL | L128: CL | M128: USD | N128: 980000 | O128: SINGLE | P128: 4.875 | Q128: BBB | R128: 11/04/2044
A129: CDEL 4.85 05/18/48 | B129: Corp Nacional del Cobre de Chile | C129: CODELCO INC | D129: CODELCO INC | E129: XS1798294523 | F129: CDEL | G129: 1006Z CI | H129: Mining | I129: FOA | J129: Non-Ferrous Metals | K129: CL | L129: CL | M129: USD | N129: 600000 | O129: SINGLE | P129: 4.85 | R129: 05/18/2048
A130: CDEL 5 ⅛ 02/02/33 | B130: Corp Nacional del Cobre de Chile | C130: CODELCO INC | D130: CODELCO INC | E130: USP3143NBP89 | F130: CDEL | G130: 1006Z CI | H130: Mining | I130: FOA | J130: Non-Ferrous Metals | K130: CL | L130: CL | M130: USD | N130: 900000 | O130: SINGLE | P130: 5.125 | Q130: BBB | R130: 02/02/2033
A131: CDEL 5 ⅝ 09/21/35 | B131: Corp Nacional del Cobre de Chile | C131: CODELCO INC | D131: CODELCO INC | E131: USP3143NAG99 | F131: CDEL | G131: 1006Z CI | H131: Mining | I131: FOA | J131: Non-Ferrous Metals | K131: CL | L131: CL | M131: USD | N131: 500000 | O131: SINGLE | P131: 5.625 | Q131: BBB | R131: 09/21/2035
A132: CDEL 5 ⅝ 10/18/43 | B132: Corp Nacional del Cobre de Chile | C132: CODELCO INC | D132: CODELCO INC | E132: USP3143NAS38 | F132: CDEL | G132: 1006Z CI | H132: Mining | I132: FOA | J132: Non-Ferrous Metals | K132: CL | L132: CL | M132: USD | N132: 950000 | O132: SINGLE | P132: 5.625 | Q132: BBB | R132: 10/18/2043
A133: CDEL 5.529 01/30/37 | B133: Corp Nacional del Cobre de Chile | C133: CODELCO INC | D133: CODELCO INC | E133: USP3143NBZ61 | F133: CDEL | G133: 1006Z CI | H133: Mining | I133: FOA | J133: Non-Ferrous Metals | K133: CL | L133: CL | M133: USD | N133: 1000000 | O133: SINGLE | P133: 5.529 | Q133: BBB | R133: 01/30/2037
A134: CDEL 5.95 01/08/34 | B134: Corp Nacional del Cobre de Chile | C134: CODELCO INC | D134: CODELCO INC | E134: USP3143NBQ62 | F134: CDEL | G134: 1006Z CI | H134: Mining | I134: FOA | J134: Non-Ferrous Metals | K134: CL | L134: CL | M134: USD | N134: 1300000 | O134: SINGLE | P134: 5.95 | Q134: BBB | R134: 01/08/2034
A135: CDEL 6.15 10/24/36 | B135: Corp Nacional del Cobre de Chile | C135: CODELCO INC | D135: CODELCO INC | E135: USP3143NAH72 | F135: CDEL | G135: 1006Z CI | H135: Mining | I135: FOA | J135: Non-Ferrous Metals | K135: CL | L135: CL | M135: USD | N135: 500000 | O135: SINGLE | P135: 6.15 | Q135: BBB | R135: 10/24/2036
A136: CDEL 6.3 09/08/53 | B136: Corp Nacional del Cobre de Chile | C136: CODELCO INC | D136: CODELCO INC | E136: USP3143NBR46 | F136: CDEL | G136: 1006Z CI | H136: Mining | I136: FOA | J136: Non-Ferrous Metals | K136: CL | L136: CL | M136: USD | N136: 1450000 | O136: SINGLE | P136: 6.3 | Q136: BBB | R136: 09/08/2053
A137: CDEL 6.33 01/13/35 | B137: Corp Nacional del Cobre de Chile | C137: CODELCO INC | D137: CODELCO INC | E137: USP3143NBV57 | F137: CDEL | G137: 1006Z CI | H137: Mining | I137: FOA | J137: Non-Ferrous Metals | K137: CL | L137: CL | M137: USD | N137: 1450000 | O137: SINGLE | P137: 6.33 | Q137: BBB | R137: 01/13/2035
A138: CDEL 6.44 01/26/36 | B138: Corp Nacional del Cobre de Chile | C138: CODELCO INC | D138: CODELCO INC | E138: USP3143NBT02 | F138: CDEL | G138: 1006Z CI | H138: Mining | I138: FOA | J138: Non-Ferrous Metals | K138: CL | L138: CL | M138: USD | N138: 1500000 | O138: SINGLE | P138: 6.44 | Q138: BBB | R138: 01/26/2036
A139: CDEL 6.78 01/13/55 | B139: Corp Nacional del Cobre de Chile | C139: CODELCO INC | D139: CODELCO INC | E139: USP3143NBW31 | F139: CDEL | G139: 1006Z CI | H139: Mining | I139: FOA | J139: Non-Ferrous Metals | K139: CL | L139: CL | M139: USD | N139: 1450000 | O139: SINGLE | P139: 6.78 | Q139: BBB | R139: 01/13/2055
A140: CELARA 4 ¼ 04/30/29 | B140: Celulosa Arauco y Constitucion SA | C140: CELULOSA ARAUCO | D140: CELULOSA ARAUCO CONSTITU | E140: USP2195VAP06 | F140: CELARA | G140: 1029Z CI | H140: Forest Products&Paper | I140: IND | J140: Paper&Related Products | K140: CL | L140: CL | M140: USD | N140: 500000 | O140: SINGLE | P140: 4.25 | Q140: BBB- | R140: 04/30/2029
A141: CELARA 4.2 01/29/30 | B141: Celulosa Arauco y Constitucion SA | C141: CELULOSA ARAUCO | D141: CELULOSA ARAUCO CONSTITU | E141: USP2195VAR61 | F141: CELARA | G141: 1029Z CI | H141: Forest Products&Paper | I141: IND | J141: Paper&Related Products | K141: CL | L141: CL | M141: USD | N141: 500000 | O141: SINGLE | P141: 4.2 | Q141: BBB- | R141: 01/29/2030
... A150: CEMEX 5.2 09/17/30 | B150: Cemex SAB de CV | C150: CEMEX SAB | D150: CEMEX SAB DE CV | E150: USP2253TJQ33 | F150: CEMEX | G150: CEMEXCPO MM | H150: Building Materials | I150: IND | J150: Bldg Prod-Cement/Aggreg | K150: MX | L150: MX | M150: USD | N150: 1000000 | O150: SINGLE | P150: 5.2 | Q150: BBB- | R150: 09/17/2030
A151: CEMEX 7.2 PERP | B151: Cemex SAB de CV | C151: CEMEX SAB | D151: CEMEX SAB DE CV | E151: USP2253TJW01 | F151: CEMEX | G151: CEMEXCPO MM | H151: Building Materials | I151: IND | J151: Bldg Prod-Cement/Aggreg | K151: MX | L151: MX | M151: USD | N151: 1000000 | O151: SINGLE | P151: 7.2 | Q151: BB
A152: CENSUD 5 ¾ 04/15/36 | B152: Cencosud SA | C152: CENCOSUD SA | D152: CENCOSUD SA | E152: USP2205JAX83 | F152: CENSUD | G152: CENCOSUD CI | H152: Food | I152: IND | J152: Food-Retail | K152: CL | L152: CL | M152: USD | N152: 500000 | O152: SINGLE | P152: 5.75 | Q152: BBB- | R152: 04/15/2036
A153: CENSUD 5.95 05/28/31 | B153: Cencosud SA | C153: CENCOSUD SA | D153: CENCOSUD SA | E153: USP2205JAT71 | F153: CENSUD | G153: CENCOSUD CI | H153: Food | I153: IND | J153: Food-Retail | K153: CL | L153: CL | M153: USD | N153: 650000 | O153: SINGLE | P153: 5.95 | Q153: BBB- | R153: 05/28/2031
A154: CENSUD 6 ⅝ 02/12/45 | B154: Cencosud SA | C154: CENCOSUD SA | D154: CENCOSUD SA | E154: USP2205JAL46 | F154: CENSUD | G154: CENCOSUD CI | H154: Food | I154: IND | J154: Food-Retail | K154: CL | L154: CL | M154: USD | N154: 350000 | O154: SINGLE | P154: 6.625 | Q154: BBB- | R154: 02/12/2045
A155: CFELEC 3 ⅞ 07/26/33 | B155: Comision Federal de Electricidad | C155: COMISION FEDERAL | D155: COMISION FEDERAL DE ELEC | E155: USP30179BK34 | F155: CFELEC | G155: 1016Z MM | H155: Electric | I155: FOA | J155: Electric-Distribution | K155: MX | L155: MX | M155: USD | N155: 850000 | O155: SINGLE | P155: 3.875 | Q155: BBB- | R155: 07/26/2033
...

Sheet Port Filtrado
A1: Name | B1: Company Name | C1: Short Name | D1: Issuer | E1: ISIN | F1: Ticker | G1: Eqty Ticker | H1: Group | I1: Sector | J1: Subgroup | K1: Cnty of Dom | L1: Cntry (Risk) | M1: Crncy | N1: Amt Iss (P) | O1: Cpn Type | P1: Cpn (P) | Q1: BB Comp (P) | R1: Mty | S1: EN BD_MATLAB | T1: EN LISTA | U1: AGREGAR
A2: =IF('Port Bloomberg'!A2="","",'Port Bloomberg'!A2) -> ABENGO 6 ⅞ 04/30/43 | B2: =IF('Port Bloomberg'!B2="","",'Port Bloomberg'!B2) -> Atlantica Transmision Sur SA | C2: =IF('Port Bloomberg'!C2="","",'Port Bloomberg'!C2) -> ATL TRANS SUR | D2: =IF('Port Bloomberg'!D2="","",'Port Bloomberg'!D2) -> ATL TRANSMISION SUR | E2: =IF('Port Bloomberg'!E2="","",'Port Bloomberg'!E2) -> USP00173AA51 | F2: =IF('Port Bloomberg'!F2="","",'Port Bloomberg'!F2) -> ABENGO | G2: =IF('Port Bloomberg'!G2="","",'Port Bloomberg'!G2) -> AY US | H2: =IF('Port Bloomberg'!H2="","",'Port Bloomberg'!H2) -> Electric | ... R2: =IF('Port Bloomberg'!R2="","",'Port Bloomberg'!R2) -> 04/30/2043 | S2: =IF(E2="","",IFERROR(IF(MATCH(E2,[1]Instrumentos!$D:$D,0)>0,1,0),0)) -> 1 | T2: =IF(E2="","",IFERROR(IF(MATCH(E2,'Lista de excepciones'!$E:$E,0)>0,1,0),0)) -> 0 | U2: =IF(E2="","",IF(S2+T2=0,"AGREGAR/REVISAR","NO")) -> NO
A3: =IF('Port Bloomberg'!A3="","",'Port Bloomberg'!A3) -> ABRAGF 14 10/22/29 | B3: =IF('Port Bloomberg'!B3="","",'Port Bloomberg'!B3) -> ABRA Global Finance | C3: =IF('Port Bloomberg'!C3="","",'Port Bloomberg'!C3) -> ABRA GLOBAL FIN | D3: =IF('Port Bloomberg'!D3="","",'Port Bloomberg'!D3) -> ABRA GLOBAL FINANCE | E3: =IF('Port Bloomberg'!E3="","",'Port Bloomberg'!E3) -> USG00912AC21 | F3: =IF('Port Bloomberg'!F3="","",'Port Bloomberg'!F3) -> ABRAGF | G3: =IF('Port Bloomberg'!G3="","",'Port Bloomberg'!G3) -> 2058922D LN | H3: =IF('Port Bloomberg'!H3="","",'Port Bloomberg'!H3) -> Airlines | ... R3: =IF('Port Bloomberg'!R3="","",'Port Bloomberg'!R3) -> 10/22/2029 | S3: =IF(E3="","",IFERROR(IF(MATCH(E3,[1]Instrumentos!$D:$D,0)>0,1,0),0)) -> 0 | T3: =IF(E3="","",IFERROR(IF(MATCH(E3,'Lista de excepciones'!$E:$E,0)>0,1,0),0)) -> 1 | U3: =IF(E3="","",IF(S3+T3=0,"AGREGAR/REVISAR","NO")) -> NO
A4: =IF('Port Bloomberg'!A4="","",'Port Bloomberg'!A4) -> ACUPET 7 ½ 01/13/32 | B4: =IF('Port Bloomberg'!B4="","",'Port Bloomberg'!B4) -> Acu Petroleo Luxembourg Sarl | C4: =IF('Port Bloomberg'!C4="","",'Port Bloomberg'!C4) -> ACU PETROLEO LUX | D4: =IF('Port Bloomberg'!D4="","",'Port Bloomberg'!D4) -> ACU PETROLEO LUXEMBOURG | E4: =IF('Port Bloomberg'!E4="","",'Port Bloomberg'!E4) -> USL0R80QAA10 | F4: =IF('Port Bloomberg'!F4="","",'Port Bloomberg'!F4) -> ACUPET | G4: =IF('Port Bloomberg'!G4="","",'Port Bloomberg'!G4) -> 1469040D BZ | H4: =IF('Port Bloomberg'!H4="","",'Port Bloomberg'!H4) -> Pipelines | ... R4: =IF('Port Bloomberg'!R4="","",'Port Bloomberg'!R4) -> 01/13/2032 | S4: =IF(E4="","",IFERROR(IF(MATCH(E4,[1]Instrumentos!$D:$D,0)>0,1,0),0)) -> 0 | T4: =IF(E4="","",IFERROR(IF(MATCH(E4,'Lista de excepciones'!$E:$E,0)>0,1,0),0)) -> 1 | U4: =IF(E4="","",IF(S4+T4=0,"AGREGAR/REVISAR","NO")) -> NO
A5: =IF('Port Bloomberg'!A5="","",'Port Bloomberg'!A5) -> AEGEBZ 6 ¾ 05/20/29 | B5: =IF('Port Bloomberg'!B5="","",'Port Bloomberg'!B5) -> Aegea Finance Sarl | C5: =IF('Port Bloomberg'!C5="","",'Port Bloomberg'!C5) -> AEGEA FINANCE | D5: =IF('Port Bloomberg'!D5="","",'Port Bloomberg'!D5) -> AEGEA FINANCE SARL | E5: =IF('Port Bloomberg'!E5="","",'Port Bloomberg'!E5) -> USL01343AA79 | F5: =IF('Port Bloomberg'!F5="","",'Port Bloomberg'!F5) -> AEGEBZ | G5: =IF('Port Bloomberg'!G5="","",'Port Bloomberg'!G5) -> 0596570D BZ | H5: =IF('Port Bloomberg'!H5="","",'Port Bloomberg'!H5) -> Water | ... R5: =IF('Port Bloomberg'!R5="","",'Port Bloomberg'!R5) -> 05/20/2029 | S5: =IF(E5="","",IFERROR(IF(MATCH(E5,[1]Instrumentos!$D:$D,0)>0,1,0),0)) -> 1 | T5: =IF(E5="","",IFERROR(IF(MATCH(E5,'Lista de excepciones'!$E:$E,0)>0,1,0),0)) -> 0 | U5: =IF(E5="","",IF(S5+T5=0,"AGREGAR/REVISAR","NO")) -> NO
A6: =IF('Port Bloomberg'!A6="","",'Port Bloomberg'!A6) -> AEGEBZ 7 ⅝ 01/20/36 | B6: =IF('Port Bloomberg'!B6="","",'Port Bloomberg'!B6) -> Aegea Finance Sarl | C6: =IF('Port Bloomberg'!C6="","",'Port Bloomberg'!C6) -> AEGEA FINANCE | D6: =IF('Port Bloomberg'!D6="","",'Port Bloomberg'!D6) -> AEGEA FINANCE SARL | E6: =IF('Port Bloomberg'!E6="","",'Port Bloomberg'!E6) -> USL01343AE91 | F6: =IF('Port Bloomberg'!F6="","",'Port Bloomberg'!F6) -> AEGEBZ | G6: =IF('Port Bloomberg'!G6="","",'Port Bloomberg'!G6) -> 0596570D BZ | H6: =IF('Port Bloomberg'!H6="","",'Port Bloomberg'!H6) -> Water | ... R6: =IF('Port Bloomberg'!R6="","",'Port Bloomberg'!R6) -> 01/20/2036 | S6: =IF(E6="","",IFERROR(IF(MATCH(E6,[1]Instrumentos!$D:$D,0)>0,1,0),0)) -> 1 | T6: =IF(E6="","",IFERROR(IF(MATCH(E6,'Lista de excepciones'!$E:$E,0)>0,1,0),0)) -> 0 | U6: =IF(E6="","",IF(S6+T6=0,"AGREGAR/REVISAR","NO")) -> NO
A7: =IF('Port Bloomberg'!A7="","",'Port Bloomberg'!A7) -> AEGEBZ 9 01/20/31 | B7: =IF('Port Bloomberg'!B7="","",'Port Bloomberg'!B7) -> Aegea Finance Sarl | C7: =IF('Port Bloomberg'!C7="","",'Port Bloomberg'!C7) -> AEGEA FINANCE | D7: =IF('Port Bloomberg'!D7="","",'Port Bloomberg'!D7) -> AEGEA FINANCE SARL | E7: =IF('Port Bloomberg'!E7="","",'Port Bloomberg'!E7) -> USL01343AB52 | F7: =IF('Port Bloomberg'!F7="","",'Port Bloomberg'!F7) -> AEGEBZ | G7: =IF('Port Bloomberg'!G7="","",'Port Bloomberg'!G7) -> 0596570D BZ | H7: =IF('Port Bloomberg'!H7="","",'Port Bloomberg'!H7) -> Water | ... R7: =IF('Port Bloomberg'!R7="","",'Port Bloomberg'!R7) -> 01/20/2031 | S7: =IF(E7="","",IFERROR(IF(MATCH(E7,[1]Instrumentos!$D:$D,0)>0,1,0),0)) -> 1 | T7: =IF(E7="","",IFERROR(IF(MATCH(E7,'Lista de excepciones'!$E:$E,0)>0,1,0),0)) -> 0 | U7: =IF(E7="","",IF(S7+T7=0,"AGREGAR/REVISAR","NO")) -> NO
A8: =IF('Port Bloomberg'!A8="","",'Port Bloomberg'!A8) -> AEROMX 8 ¼ 11/15/29 | B8: =IF('Port Bloomberg'!B8="","",'Port Bloomberg'!B8) -> Grupo Aeromexico SAB de CV | C8: =IF('Port Bloomberg'!C8="","",'Port Bloomberg'!C8) -> GRUPO AEROMEXICO | D8: =IF('Port Bloomberg'!D8="","",'Port Bloomberg'!D8) -> GRUPO AEROMEXICO SAB | E8: =IF('Port Bloomberg'!E8="","",'Port Bloomberg'!E8) -> USP4955JAB46 | F8: =IF('Port Bloomberg'!F8="","",'Port Bloomberg'!F8) -> AEROMX | G8: =IF('Port Bloomberg'!G8="","",'Port Bloomberg'!G8) -> AERO* MM | H8: =IF('Port Bloomberg'!H8="","",'Port Bloomberg'!H8) -> Airlines | ... R8: =IF('Port Bloomberg'!R8="","",'Port Bloomberg'!R8) -> 11/15/2029 | S8: =IF(E8="","",IFERROR(IF(MATCH(E8,[1]Instrumentos!$D:$D,0)>0,1,0),0)) -> 0 | T8: =IF(E8="","",IFERROR(IF(MATCH(E8,'Lista de excepciones'!$E:$E,0)>0,1,0),0)) -> 1 | U8: =IF(E8="","",IF(S8+T8=0,"AGREGAR/REVISAR","NO")) -> NO
A9: =IF('Port Bloomberg'!A9="","",'Port Bloomberg'!A9) -> AEROMX 8 ⅝ 11/15/31 | B9: =IF('Port Bloomberg'!B9="","",'Port Bloomberg'!B9) -> Grupo Aeromexico SAB de CV | C9: =IF('Port Bloomberg'!C9="","",'Port Bloomberg'!C9) -> GRUPO AEROMEXICO | D9: =IF('Port Bloomberg'!D9="","",'Port Bloomberg'!D9) -> GRUPO AEROMEXICO SAB | E9: =IF('Port Bloomberg'!E9="","",'Port Bloomberg'!E9) -> USP4955JAC29 | F9: =IF('Port Bloomberg'!F9="","",'Port Bloomberg'!F9) -> AEROMX | G9: =IF('Port Bloomberg'!G9="","",'Port Bloomberg'!G9) -> AERO* MM | H9: =IF('Port Bloomberg'!H9="","",'Port Bloomberg'!H9) -> Airlines | ... R9: =IF('Port Bloomberg'!R9="","",'Port Bloomberg'!R9) -> 11/15/2031 | S9: =IF(E9="","",IFERROR(IF(MATCH(E9,[1]Instrumentos!$D:$D,0)>0,1,0),0)) -> 0 | T9: =IF(E9="","",IFERROR(IF(MATCH(E9,'Lista de excepciones'!$E:$E,0)>0,1,0),0)) -> 1 | U9: =IF(E9="","",IF(S9+T9=0,"AGREGAR/REVISAR","NO")) -> NO
A10: =IF('Port Bloomberg'!A10="","",'Port Bloomberg'!A10) -> AES 4.72 06/30/40 | B10: =IF('Port Bloomberg'!B10="","",'Port Bloomberg'!B10) -> Alto Maipo SpA | C10: =IF('Port Bloomberg'!C10="","",'Port Bloomberg'!C10) -> ALTO MAIPO SPA | D10: =IF('Port Bloomberg'!D10="","",'Port Bloomberg'!D10) -> ALTO MAIPO SPA | E10: =IF('Port Bloomberg'!E10="","",'Port Bloomberg'!E10) -> USP0243BAA37 | F10: =IF('Port Bloomberg'!F10="","",'Port Bloomberg'!F10) -> AES | G10: =IF('Port Bloomberg'!G10="","",'Port Bloomberg'!G10) -> AESANDES CI | H10: =IF('Port Bloomberg'!H10="","",'Port Bloomberg'!H10) -> Energy-Alternate Sources | ... R10: =IF('Port Bloomberg'!R10="","",'Port Bloomberg'!R10) -> 06/30/2040 | S10: =IF(E10="","",IFERROR(IF(MATCH(E10,[1]Instrumentos!$D:$D,0)>0,1,0),0)) -> 0 | T10: =IF(E10="","",IFERROR(IF(MATCH(E10,'Lista de excepciones'!$E:$E,0)>0,1,0),0)) -> 1 | U10: =IF(E10="","",IF(S10+T10=0,"AGREGAR/REVISAR","NO")) -> NO
A11: =IF('Port Bloomberg'!A11="","",'Port Bloomberg'!A11) -> AES 6 ¼ 03/14/32 | B11: =IF('Port Bloomberg'!B11="","",'Port Bloomberg'!B11) -> AES Andes SA | C11: =IF('Port Bloomberg'!C11="","",'Port Bloomberg'!C11) -> AES ANDES SA | D11: =IF('Port Bloomberg'!D11="","",'Port Bloomberg'!D11) -> AES ANDES SA | E11: =IF('Port Bloomberg'!E11="","",'Port Bloomberg'!E11) -> USP0091LAD84 | F11: =IF('Port Bloomberg'!F11="","",'Port Bloomberg'!F11) -> AES | G11: =IF('Port Bloomberg'!G11="","",'Port Bloomberg'!G11) -> AESANDES CI | H11: =IF('Port Bloomberg'!H11="","",'Port Bloomberg'!H11) -> Electric | ... R11: =IF('Port Bloomberg'!R11="","",'Port Bloomberg'!R11) -> 03/14/2032 | S11: =IF(E11="","",IFERROR(IF(MATCH(E11,[1]Instrumentos!$D:$D,0)>0,1,0),0)) -> 1 | T11: =IF(E11="","",IFERROR(IF(MATCH(E11,'Lista de excepciones'!$E:$E,0)>0,1,0),0)) -> 0 | U11: =IF(E11="","",IF(S11+T11=0,"AGREGAR/REVISAR","NO")) -> NO
A12: =IF('Port Bloomberg'!A12="","",'Port Bloomberg'!A12) -> AES 6 ¼ 11/14/34 | B12: =IF('Port Bloomberg'!B12="","",'Port Bloomberg'!B12) -> AES Andes SA | C12: =IF('Port Bloomberg'!C12="","",'Port Bloomberg'!C12) -> AES ANDES SA | D12: =IF('Port Bloomberg'!D12="","",'Port Bloomberg'!D12) -> AES ANDES SA | E12: =IF('Port Bloomberg'!E12="","",'Port Bloomberg'!E12) -> USP0091LAE67 | F12: =IF('Port Bloomberg'!F12="","",'Port Bloomberg'!F12) -> AES | G12: =IF('Port Bloomberg'!G12="","",'Port Bloomberg'!G12) -> AESANDES CI | H12: =IF('Port Bloomberg'!H12="","",'Port Bloomberg'!H12) -> Electric | ... R12: =IF('Port Bloomberg'!R12="","",'Port Bloomberg'!R12) -> 11/14/2034 | S12: =IF(E12="","",IFERROR(IF(MATCH(E12,[1]Instrumentos!$D:$D,0)>0,1,0),0)) -> 1 | T12: =IF(E12="","",IFERROR(IF(MATCH(E12,'Lista de excepciones'!$E:$E,0)>0,1,0),0)) -> 0 | U12: =IF(E12="","",IF(S12+T12=0,"AGREGAR/REVISAR","NO")) -> NO
A13: =IF('Port Bloomberg'!A13="","",'Port Bloomberg'!A13) -> AES 6.3 03/15/29 | B13: =IF('Port Bloomberg'!B13="","",'Port Bloomberg'!B13) -> AES Andes SA | C13: =IF('Port Bloomberg'!C13="","",'Port Bloomberg'!C13) -> AES ANDES SA | D13: =IF('Port Bloomberg'!D13="","",'Port Bloomberg'!D13) -> AES ANDES SA | E13: =IF('Port Bloomberg'!E13="","",'Port Bloomberg'!E13) -> USP0091LAA46 | F13: =IF('Port Bloomberg'!F13="","",'Port Bloomberg'!F13) -> AES | G13: =IF('Port Bloomberg'!G13="","",'Port Bloomberg'!G13) -> AESANDES CI | H13: =IF('Port Bloomberg'!H13="","",'Port Bloomberg'!H13) -> Electric | ... R13: =IF('Port Bloomberg'!R13="","",'Port Bloomberg'!R13) -> 03/15/2029 | S13: =IF(E13="","",IFERROR(IF(MATCH(E13,[1]Instrumentos!$D:$D,0)>0,1,0),0)) -> 1 | T13: =IF(E13="","",IFERROR(IF(MATCH(E13,'Lista de excepciones'!$E:$E,0)>0,1,0),0)) -> 0 | U13: =IF(E13="","",IF(S13+T13=0,"AGREGAR/REVISAR","NO")) -> NO
... A1250: =IF('Port Bloomberg'!A1250="","",'Port Bloomberg'!A1250) | B1250: =IF('Port Bloomberg'!B1250="","",'Port Bloomberg'!B1250) | C1250: =IF('Port Bloomberg'!C1250="","",'Port Bloomberg'!C1250) | D1250: =IF('Port Bloomberg'!D1250="","",'Port Bloomberg'!D1250) | E1250: =IF('Port Bloomberg'!E1250="","",'Port Bloomberg'!E1250) | F1250: =IF('Port Bloomberg'!F1250="","",'Port Bloomberg'!F1250) | G1250: =IF('Port Bloomberg'!G1250="","",'Port Bloomberg'!G1250) | H1250: =IF('Port Bloomberg'!H1250="","",'Port Bloomberg'!H1250) | ... R1250: =IF('Port Bloomberg'!R1250="","",'Port Bloomberg'!R1250) | S1250: =IF(E1250="","",IFERROR(IF(MATCH(E1250,[1]Instrumentos!$D:$D,0)>0,1,0),0)) | T1250: =IF(E1250="","",IFERROR(IF(MATCH(E1250,'Lista de excepciones'!$E:$E,0)>0,1,0),0)) | U1250: =IF(E1250="","",IF(S1250+T1250=0,"AGREGAR/REVISAR","NO"))

Sheet Lista de excepciones
A1: Name | B1: Long Name | C1: Short Name | D1: Issuer | E1: ISIN | F1: Ticker | G1: Eqty Ticker | H1: Group | I1: Subgroup | J1: Sector | K1: Cntry | L1: Cntry (Risk) | M1: Crncy | N1: BB Comp | O1: Comentario
A2: ABRAGF 14 10/22/29 | B2: ABRA Global Finance | C2: ABRA GLOBAL FIN | D2: ABRA GLOBAL FINANCE | E2: USG00912AC21 | F2: ABRAGF | H2: Airlines | I2: IND | J2: Airlines | K2: KY | L2: CO | M2: USD | N2: NR | O2: CCC+
A3: ABRAGF 5 03/02/28 | B3: ABRA Global Finance | C3: ABRA GLOBAL FIN | D3: ABRA GLOBAL FINANCE | E3: USG00912AA64 | F3: ABRAGF | H3: Airlines | I3: IND | J3: Airlines | K3: KY | L3: CO | M3: USD | N3: NR | O3: CCC+
A4: ACUPET 7 ½ 01/13/32 | B4: ACUPET 7 ½ 01/13/32 | C4: ACU PETROLEO LUX | D4: ACU PETROLEO LUXEMBOURG | E4: USL0R80QAA10 | F4: ACUPET | G4: 1469040D BZ | H4: Pipelines | I4: Energy | J4: Pipelines | K4: BR | L4: BR | M4: USD | N4: BB | O4: NO APLICA
A5: AEGEBZ 9 01/20/31 | B5: Aegea Finance Sarl | C5: AEGEA FINANCE | D5: AEGEA FINANCE SARL | E5: USL01343AD19 | F5: AEGEBZ | G5: AEGEBZ | H5: Water | I5: Utilities | J5: Water | K5: LU | L5: BR | M5: USD | N5: BB- | O5: NO APLICA
A6: AEROMX 8 ¼ 11/15/29 | B6: Grupo Aeromexico SAB de CV | C6: GRUPO AEROMEXICO | D6: GRUPO AEROMEXICO SAB | E6: USP4955JAB46 | F6: AEROMX | G6: AEROMX | H6: Airlines | I6: Consumer, Cyclical | J6: Airlines | K6: MX | L6: MX | M6: USD | N6: BB- | O6: HICIERON CALL
A7: AEROMX 8 ⅝ 11/15/31 | B7: Grupo Aeromexico SAB de CV | C7: GRUPO AEROMEXICO | D7: GRUPO AEROMEXICO SAB | E7: USP4955JAC29 | F7: AEROMX | G7: AEROMX | H7: Airlines | I7: Consumer, Cyclical | J7: Airlines | K7: MX | L7: MX | M7: USD | N7: BB- | O7: HICIERON CALL
A8: AES 4.72 06/30/40 | B8: Alto Maipo SpA | C8: ALTO MAIPO SPA | D8: ALTO MAIPO SPA | E8: USP0243BAA37 | F8: AES | G8: AESANDES CI | H8: Energy-Alternate Sources | I8: UTL | J8: Energy-Alternate Sources | K8: CL | L8: CL | M8: USD | O8: CCC+
A9: AMAGGI 5 ¼ 01/28/28 | B9: AMAGGI 5 ¼ 01/28/28 | C9: AMAGGI LUX INT | D9: AMAGGI LUX INTL SARL | E9: USL0183BAA90 | F9: AMAGGI | H9: Agriculture | I9: Agricultural Operations | J9: Consumer, Non-cyclical | K9: BR | L9: BR | M9: USD | N9: BB- | O9: NO APLICA
A10: AMBIBZ 10 ⅞ 02/05/33 | B10: Ambipar Lux Sarl | C10: AMBIPAR LUX SARL | D10: AMBIPAR LUX SARL | E10: USL0183EAB13 | F10: AMBIBZ | H10: Environmental Control | I10: IND | J10: Non-hazardous Waste Disp | K10: LU | L10: BR | M10: USD | N10: BB- | O10: NO APLICA
A11: ANDRGI 9 12/28/29 | B11: Andrade Gutierrez International SA | C11: ANDRADE GUT INT | D11: ANDRADE GUTIER INT SA | E11: USL01795AG50 | F11: ANDRGI | H11: Engineering&Construction | I11: IND | J11: Building-Heavy Construct | K11: LU | L11: BR | M11: USD | N11: NR | O11: NR
A12: ATPTOW 7 ⅞ 02/03/30 | B12: ATP Tower Holdings / Andean Telecom Partners Chile SpA / Andean Tower Partners C | C12: ATP TOW/ANDEAN | D12: ATP TOW/ANDEAN TELECOM | E12: USU0489EAA48 | F12: ATPTOW | H12: Engineering&Construction | I12: IND | J12: Building-Heavy Construct | K12: US | L12: CL | M12: USD | N12: BB- | O12: NO APLICA
A13: AUNA 10 12/18/29 | B13: Auna SA | C13: AUNA SA | D13: AUNA SA | E13: USL0415AAA18 | F13: AUNA | H13: Healthcare-Services | I13: IND | J13: Medical-Hospitals | K13: LU | L13: PE | M13: USD | N13: B+ | O13: NO APLICA - SE REFINANCIÓ
A14: AZUBBZ 9 ⅞ 02/15/31 | B14: Azul Secured Finance LLP | C14: AZUL SECURED FIN | D14: AZUL SECURED FINANCE LLP | E14: USU0551YAK11 | F14: AZUBBZ | G14: 2870534Z BZ | H14: Airlines | I14: IND | J14: Airlines | K14: US | L14: BR | M14: USD | N14: NR | O14: NR
A15: BANVOR 5 ⅞ 04/08/28 | B15: Banco Votorantim SA/Luxembourg | C15: Banco Votorantim SA/Luxembourg | D15: BANCO VOTORANTIM | E15: XS3046422542 | F15: BANVOR | G15: 1009Z BZ | H15: Banks | I15: FIN | J15: Commer Banks Non-US | K15: LU | L15: BR | M15: USD | N15: BB | O15: NO APLICA
A16: BORLTD 9 ½ 08/07/32 | B16: Boroo Investments Pte Ltd | C16: BOROO INV PT LTD | D16: BOROO INVESTMENTS | E16: USY00601AA55 | F16: BORLTD | H16: Mining | I16: IND | J16: Gold Mining | K16: SG | L16: PE | M16: USD | N16: B+ | O16: NO APLICA
A17: BORRNO 10 ⅜ 11/15/30 | B17: Borr IHC Ltd / Borr Finance LLC | C17: BORR IHC/BORR FI | D17: BORR IHC LTD / BORR FIN | E17: USG1467FAB97 | F17: BORRNO | G17: BORR NO | H17: Oil&Gas | I17: Energy | J17: Oil&Gas Drilling | K17: US | L17: MX | M17: USD | N17: B | O17: NO APLICA
A18: BORRNO 10 11/15/28 | B18: Borr IHC Ltd / Borr Finance LLC | C18: BORR IHC/BORR FI | D18: BORR IHC LTD / BORR FIN | E18: USG1467FAA15 | F18: BORRNO | G18: BORR NO | H18: Oil&Gas | I18: Energy | J18: Oil&Gas Drilling | K18: US | L18: MX | M18: USD | N18: B | O18: NO APLICA
A19: BORRNO 8 ¾ 01/15/32 | B19: Borr IHC Ltd / Borr Finance LLC | C19: BORR IHC/BORR FI | D19: BORR IHC LTD / BORR FIN | E19: USG1467FAH67 | F19: BORRNO | G19: BORR US | H19: Oil&Gas | I19: IND | J19: Oil&Gas Drilling | K19: US | L19: MX | M19: USD | N19: B | O19: NO APLICA
A20: BRASKM 12.06 01/23/2081 | B20: Braskem Netherlands Finance BV | C20: BRASKEM NL | D20: BRASKEM NETHERLANDS | E20: USN15516AF97 | F20: BRASKM | G20: BRKM3 BZ | H20: Chemicals | I20: IND | J20: Chemicals-Diversified | K20: NL | L20: BR | M20: USD | N20: C | O20: C
A21: BRASKM 4 ½ 01/31/30 | B21: Braskem Netherlands Finance BV | C21: BRASKEM NL | D21: BRASKEM NETHERLANDS | E21: USN15516AD40 | F21: BRASKM | G21: BRKM3 BZ | H21: Chemicals | I21: IND | J21: Chemicals-Diversified | K21: NL | L21: BR | M21: USD | N21: CC+ | O21: CC+
A22: BRASKM 5 ⅞ 01/31/50 | B22: Braskem Netherlands Finance BV | C22: BRASKEM NL | D22: BRASKEM NETHERLANDS | E22: USN15516AE23 | F22: BRASKM | G22: BRKM3 BZ | H22: Chemicals | I22: IND | J22: Chemicals-Diversified | K22: NL | L22: BR | M22: USD | N22: CC+ | O22: CC+
A23: BRASKM 7 ⅛ 07/22/41 | B23: Braskem America Finance Co | C23: BRASKEM AMERICA | D23: BRASKEM AMERICA FINANCE | E23: USU1065PAA94 | F23: BRASKM | G23: BRKM3 BZ | H23: Chemicals | I23: IND | J23: Petrochemicals | K23: US | L23: BR | M23: USD | N23: CC+ | O23: CC+
A24: BRASKM 7 ¼ 02/13/33 | B24: Braskem Netherlands Finance BV | C24: BRASKEM NL | D24: BRASKEM NETHERLANDS | E24: USN15516AG70 | F24: BRASKM | G24: BRKM3 BZ | H24: Chemicals | I24: IND | J24: Chemicals-Diversified | K24: NL | L24: BR | M24: USD | N24: CC+ | O24: CC+
A25: BRASKM 8 ½ 01/12/31 | B25: Braskem Netherlands Finance BV | C25: BRASKEM NL | D25: BRASKEM NETHERLANDS | E25: USN15516AH53 | F25: BRASKM | G25: BRKM3 BZ | H25: Chemicals | I25: IND | J25: Chemicals-Diversified | K25: NL | L25: BR | M25: USD | N25: CC+ | O25: CC+
A26: BRASKM 8 10/15/34 | B26: Braskem Netherlands Finance BV | C26: BRASKEM NL | D26: BRASKEM NETHERLANDS | E26: USN15516AJ10 | F26: BRASKM | G26: BRKM3 BZ | H26: Chemicals | I26: IND | J26: Chemicals-Diversified | K26: NL | L26: BR | M26: USD | N26: CC+ | O26: CC+
A27: BSMXB 7.525 10/01/28 | B27: Banco Santander Mexico SA Institucion de Banca Multiple Grupo Financiero Santand | C27: SANTANDER MEXICO | D27: BANCO SANTANDER MEXICO | E27: USP1507SAG23 | F27: BSMXB | G27: BSMXB MM | H27: Banks | I27: Financial | J27: Commer Banks Non-US | K27: MX | L27: MX | M27: USD | N27: BBB- | O27: VENCIMIENTO <= 2028
A28: CDEL 4.85 05/18/48 | B28: Corp Nacional del Cobre de Chile | C28: CODELCO INC | D28: CODELCO INC | E28: XS1798294523 | F28: CDEL | G28: 1006Z CI | H28: Mining | I28: FOA | J28: Non-Ferrous Metals | K28: CL | L28: CL | M28: USD | N28: NR | O28: NO RATING
A29: CHIPEC 0 01/25/28 | B29: CHIPEC 0 01/25/28 | C29: CHILE ELEC PEC | D29: CHILE ELEC PEC SPA | E29: USP2550MAA29 | F29: CHIPEC | H29: Electric | I29: Utilities | J29: Electric-Distribution | K29: CL | L29: CL | M29: USD | N29: BBB- | O29: NO APLICA
A30: CHLELC 6.01 01/20/33 | B30: Chile Electricity Lux MPC Sarl | C30: CHILE ELECTR LUX | D30: CHILE ELECTRICITY LUX | E30: USL15669AA91 | F30: CHLELC | H30: Electric | I30: Utilities | J30: Electric-Distribution | K30: LU | L30: CL | M30: USD | N30: A | O30: NO APLICA
A31: CHLMPC 5.58 10/20/35 | B31: Chile Electricity Lux Mpc II Sarl | C31: CL ELECTRICITY | D31: CHILE ELECTRICITY LUX | E31: USL1567LAA19 | F31: CHLMPC | G31: CHLMPC | H31: Electric | I31: Utilities | J31: Electric-Distribution | K31: LU | L31: CL | M31: USD | N31: A- | O31: NO APLICA
A32: CHLMPC 5.672 10/20/35 | B32: Chile Electricity Lux Mpc II Sarl | C32: Chile Electricity Lux Mpc II Sarl | D32: CL ELECTRICITY | E32: USL1567LAB91 | F32: CHLMPC | H32: Electric | I32: FOA | J32: Electric-Distribution | K32: LU | L32: CL | M32: USD | N32: A- | O32: NO APLICA
A33: COSHSA 9 ⅜ 11/07/29 | B33: NewCo Holding USD 20 Sarl | C33: NEWCOL HLDG SARL | D33: NEWCO HOLDING USD SARL | E33: USL67356AA09 | F33: COSHSA | H33: Oil&Gas | I33: Energy | J33: Oil&Gas Drilling | K33: LU | L33: BR | M33: USD | N33: B | O33: NO APLICA
A34: COXMEX 7 ⅛ 01/08/32 | B34: COX Asset Mexico SA de CV | C34: COX ASSET MEX CV | D34: COX ASSET MEXICO SA CV | E34: USP3172AAA45 | F34: COXMEX | G34: COXG SM | H34: Electric | I34: UTL | J34: Electric-Generation | K34: MX | L34: MX | M34: USD | N34: NR | O34: NO APLICA
A35: COXMEX 7 ¾ 05/08/36 | B35: COX Asset Mexico SA de CV | C35: COX ASSET MEX CV | D35: COX ASSET MEXICO SA CV | E35: USP3172AAB28 | F35: COXMEX | G35: COXG SM | H35: Electric | I35: UTL | J35: Electric-Generation | K35: MX | L35: MX | M35: USD | N35: NR | O35: NO APLICA
A36: CSANBZ 8 ¼ PERP | B36: Cosan Overseas Ltd | C36: COSAN OVERSEAS | D36: COSAN OVERSEAS LTD | E36: XS0556373347 | F36: CSANBZ | G36: CSAN3 BZ | H36: Oil&Gas | I36: IND | J36: Oil Refining&Marketing | K36: KY | L36: BR | M36: USD | N36: BB | O36: NO APLICA
A37: CSNABZ 6 ¾ 01/28/28 | B37: CSN Inova Ventures | C37: CSN ISLANDS XI | D37: CSN ISLANDS XI CORP | E37: USG2583XAB76 | F37: CSNABZ | G37: CSNA3 BZ | H37: Iron/Steel | I37: Basic Materials | J37: Steel-Producers | K37: KY | L37: BR | M37: USD | N37: BB- | O37: VENCIMIENTO <= 2028
A38: ECELUP 8 ½ 12/01/32 | B38: Eldorado Intl. Finance GmbH | C38: ELDORADO INTL FI | D38: ELDORADO INTL FIN GMBH | E38: USA18007AC71 | F38: ECELUP | G38: 0113756D BZ | H38: Forest Products&Paper | I38: IND | J38: Paper&Related Products | K38: AT | L38: BR | M38: USD | N38: BB- | O38: NO APLICA
A39: EKT 12 ½ 10/15/31 | B39: Mexico Remittances Funding Fiduciary Estate Management Sarl | C39: MX REMIT FUND | D39: MX REMIT FUND FIDUC EST | E39: USL6364EAB94 | F39: EKT | G39: EKT | H39: Diversified Finan Serv | I39: Financial | J39: Finance-Other Services | K39: LU | L39: MX | M39: USD | N39: BB | O39: NO APLICA
A40: ENELCH 4 ⅞ 06/12/28 | B40: Enel Chile SA | C40: ENEL CHILE SA | D40: ENEL CHILE SA | E40: US29278DAA37 | F40: ENELCH | G40: ENELCHIL CI | H40: Electric | I40: Utilities | J40: Electric-Integrated | K40: CL | L40: CL | M40: USD | N40: BBB | O40: VENCIMIENTO <= 2028
A41: FCFEMM 5 ⅞ 09/23/40 | B41: CFE Fibra E | C41: CFE FIBRA E | D41: CFE FIBRA E | E41: USP24038AA23 | F41: FCFEMM | H41: REITS | I41: Financial | J41: REITS-Diversified | K41: MX | L41: MX | M41: USD | N41: BBB- | O41: NO APLICA
A42: FECCN 7 ⅞ 06/21/28 | B42: Frontera Energy Corp | C42: FRONTERA ENERGY | D42: FRONTERA ENERGY CORP | E42: USC35898AB82 | F42: FECCN | G42: FEC CN | H42: Oil&Gas | I42: Energy | J42: Oil Comp-Explor&Prodtn | K42: CA | L42: CO | M42: USD | N42: B | O42: VENCIMIENTO <= 2028
A43: FIEMEX 7 ¼ 01/31/41 | B43: FIEMEX Energia - Banco Actinver SA Institucion de Banca Multiple | C43: FIEMEX ENERGI-BA | D43: FIEMEX ENERGIA - BANC AC | E43: USP0R12RAA88 | F43: FIEMEX | G43: FIEMEX | H43: Electric | I43: Utilities | J43: Independ Power Producer | K43: MX | L43: MX | M43: USD | N43: BBB- | O43: NO CUADRA SECTOR NI NOMBRE…
A44: FISOMA 7 ⅛ 05/28/36 | B44: Fibra SOMA Trust F/6185 | C44: FIBRA SOMA 6185 | D44: FIBRA SOMA TRUST F/6185 | E44: USP3990QAA96 | F44: FISOMA | G44: SOMA21 MM | H44: REITS | I44: FIN | J44: REITS-Diversified | K44: MX | L44: MX | M44: USD | N44: NR | O44: NO APLICA
A45: FSBIOE 10 12/15/25 | B45: FSBIOE 10 12/15/25 | C45: FS LUX SARL | D45: FS LUXEMBOURG SARL | E45: USL40756AB19 | F45: FSBIOE | H45: Energy-Alternate Sources | I45: Energy | J45: Energy-Alternate Sources | K45: BR | L45: BR | M45: USD | N45: BB- | O45: NO APLICA
A46: FSBIOE 8 ⅛ 02/11/36 | B46: FS Luxembourg Sarl | C46: FS LUX SARL | D46: FS LUXEMBOURG SARL | E46: USL40756AH88 | F46: FSBIOE | G46: 1833273D BZ | H46: Energy-Alternate Sources | I46: IND | J46: Energy-Alternate Sources | K46: LU | L46: BR | M46: USD | N46: NR | O46: NR
A47: FSBIOE 8 ⅝ 06/25/33 | B47: FS Luxembourg Sarl | C47: FS LUX SARL | D47: FS LUXEMBOURG SARL | E47: USL40756AG06 | F47: FSBIOE | G47: 1833273D BZ | H47: Energy-Alternate Sources | I47: IND | J47: Energy-Alternate Sources | K47: LU | L47: BR | M47: USD | N47: BB- | O47: NO APLICA
A48: FSBIOE 8 ⅞ 02/12/31 | B48: FS Luxembourg Sarl | C48: FS LUX SARL | D48: FS LUXEMBOURG SARL | E48: USL40756AE57 | F48: FSBIOE | G48: 1833273D BZ | H48: Energy-Alternate Sources | I48: Energy | J48: Energy-Alternate Sources | K48: LU | L48: BR | M48: USD | N48: BB- | O48: NO APLICA
A49: GNFPSO 5.198 06/15/34 | B49: GNFPSO 5.198 06/15/34 | C49: GUARA NORTE SARL | D49: GUARA NORTE SARL | E49: USL4R02QAA86 | F49: GNFPSO | G49: SBMO NA | H49: Oil&Gas Services | I49: Energy | J49: Oil Field Mach&Equip | K49: BR | L49: BR | M49: USD | N49: BB+ | O49: NO APLICA
A50: GOLLBZ 14 ⅜ 06/06/30 | B50: Gol Finance Inc | C50: GOL FINANCE | D50: GOL FINANCE | E50: USL4441RAL08 | F50: GOLLBZ | G50: GOLL54 BZ | H50: Airlines | I50: IND | J50: Airlines | K50: BR | L50: BR | M50: USD | N50: CCC+ | O50: CCC+
A51: GOLLBZ 9 ½ 12/05/30 | B51: GOL Equity Finance SA | C51: GOL EQUITY FIN | D51: GOL EQUITY FINANCE SA | E51: US379955AC17 | F51: GOLLBZ | G51: GOLL54 BZ | H51: Airlines | I51: IND | J51: Airlines | K51: LU | L51: BR | M51: USD | O51: NR
A52: IENOVA 3 ¾ 01/14/28 | B52: Infraestructura Energetica Nova SAPI de CV | C52: INFRAESTRUCTURA | D52: INFRAESTRUCTURA ENERGETI | E52: USP56145AA66 | F52: IENOVA | G52: SRE US | H52: Electric | I52: Utilities | J52: Electric-Distribution | K52: MX | L52: MX | M52: USD | N52: BBB- | O52: VENCIMIENTO <= 2028
A53: INRCON 3 ¼ 03/22/28 | B53: InRetail Consumer | C53: INRETAIL CONSUME | D53: INRETAIL CONSUMER | E53: USP56236AB16 | F53: INRCON | G53: INRETC1 PE | H53: Retail | I53: Consumer, Cyclical | J53: Retail-Misc/Diversified | K53: PE | L53: PE | M53: USD | N53: BB+ | O53: VENCIMIENTO <= 2028
A54: IOCMXW 5 05/07/28 | B54: Iochpe-Maxion Austria GmbH / Maxion Wheels de Mexico S de RL de CV | C54: IOCHPE-MAX/MAX W | D54: IOCHPE-MAX/MAX WHEELS MX | E54: USA3R74HAA50 | F54: IOCMXW | G54: MYPK3 BZ | H54: Auto Parts&Equipment | I54: Consumer, Cyclical | J54: Auto/Trk Prts&Equip-Orig | K54: AT | L54: BR | M54: USD | N54: BB- | O54: VENCIMIENTO <= 2028
A55: KARAU 10 ½ 05/14/29 | B55: Karoon USA Finance Inc | C55: KAROON USA FIN | D55: KAROON USA FINANCE INC | E55: USU24463AA68 | F55: KARAU | G55: KARAU | H55: Oil&Gas | I55: Energy | J55: Oil Comp-Explor&Prodtn | K55: AU | L55: BR | M55: USD | N55: B+ | O55: NO APLICA
A56: LIMAMT 4.35 04/05/36 | B56: LIMAMT 4.35 04/05/36 | C56: LIMA METRO LINE | D56: LIMA METRO LINE 2 FIN LT | E56: USG54897AB28 | F56: LIMAMT | H56: Transportation | I56: Transport-Rail | J56: Industrial | K56: PE | L56: PE | M56: USD | N56: BBB- | O56: ILIQUIDO
A57: LIMAMT 5 ⅞ 07/05/34 | B57: LIMAMT 5 ⅞ 07/05/34 | C57: LIMA METRO LINE | D57: LIMA METRO LINE 2 FIN LT | E57: USG54897AA45 | F57: LIMAMT | H57: Transportation | I57: Transport-Rail | J57: Industrial | K57: PE | L57: PE | M57: USD | N57: BBB- | O57: ILIQUIDO
A58: LNZAV 7.95 01/26/32 | B58: LD Celulose International GmbH | C58: LD CELULOSE INTE | D58: LD CELULOSE INTERNATIONA | E58: USA4S42PAA32 | F58: LNZAV | G58: LNZAV | H58: Forest Products&Paper | I58: Basic Materials | J58: Paper&Related Products | K58: AT | L58: BR | M58: USD | N58: BB- | O58: NO APLICA
A59: MABEMX 5.6 10/23/28 | B59: Controladora Mabe SA de CV | C59: CONTROLADORA MAB | D59: CONTROLADORA MABE SA CV | E59: USP3100SAC81 | F59: MABEMX | G59: 1122Z MM | H59: Home Furnishings | I59: Consumer, Cyclical | J59: Appliances | K59: MX | L59: MX | M59: USD | N59: BBB | O59: VENCIMIENTO <= 2028
A60: MCBRAC 7 ¼ 06/30/31 | B60: MCBRAC 7 ¼ 06/30/31 | C60: MC BRAZIL | D60: MC BRAZIL DWNSTRM | E60: USL626A6AA24 | F60: MCBRAC | H60: Oil&Gas | I60: Energy | J60: Oil Refining&Marketing | K60: BR | L60: BR | M60: USD | N60: B+ | O60: NO APLICA
A61: MEX 5 ½ 08/17/30 | B61: Eagle Funding Luxco Sarl | C61: EAGLE LUXCO | D61: EAGLE FUNDING LUXCO SARL | E61: USL2660VAA37 | F61: MEX | H61: Sovereign | I61: SOV | J61: Sovereign | K61: LU | L61: MX | M61: USD | N61: BBB | O61: NO APLICA
A62: MEXCAT 3 ⅞ 04/30/28 | B62: Mexico City Airport Trust | C62: MEXICO CITY ARPT | D62: MEXICO CITY ARPT TRUST | E62: USP6629MAC66 | F62: MEXCAT | G62: 1441130D MM | H62: Engineering&Construction | I62: Industrial | J62: Airport Develop/Maint | K62: MX | L62: MX | M62: USD | N62: BBB- | O62: VENCIMIENTO <= 2028
A63: MRNOMX 11 09/12/30 | B63: Fideicomiso Irrevocable de Administracion y Fuente de Pago Numero CIB/4323 | C63: FIDEIC 4323 | D63: FIDEIC IRR ADMIN 4323 | E63: USP2R57MAA12 | F63: MRNOMX | G63: MRNOMX | H63: Real Estate | I63: Financial | J63: Real Estate Oper/Develop | K63: MX | L63: BB | M63: USD | N63: BB | O63: NO ELEGIBLE (CASO MEXCAT)
A64: MUNDOX 7.95 04/20/31 | B64: DB Terra Chile HoldCo SpA | C64: DB TERRA CHILE H | D64: DB TERRA CHILE HOLDCO SP | E64: USP3R80FAA52 | F64: MUNDOX | H64: Telecommunications | I64: IND | J64: Telecom Services | K64: CL | L64: CL | M64: USD | N64: BB- | O64: NO APLICA
A65: MVFPSO 6.748 06/01/34 | B65: MVFPSO 6.748 06/01/34 | C65: MV24 CAPITAL BV | D65: MV24 CAPITAL BV | E65: USN53766AA41 | F65: MVFPSO | H65: Transportation | I65: Transport-Marine | J65: Industrial | K65: BR | L65: BR | M65: USD | N65: BB | O65: NO APLICA
A66: NATURA 4 ⅛ 05/03/28 | B66: Natura &Co Luxembourg Holdings Sarl | C66: NATURA &CO LUX | D66: NATURA &CO LUX HLD SARL | E66: USP7088CAC03 | F66: NATURA | G66: NTCO3 BZ | H66: Cosmetics/Personal Care | I66: Consumer, Non-cyclical | J66: Cosmetics&Toiletries | K66: LU | L66: BR | M66: USD | N66: BB | O66: VENCIMIENTO <= 2028
A67: NEXTPR 4.869 01/15/30 | B67: Trust 2401 | C67: TRUST 2401 | D67: TRUST 2401 | E67: USP9402MAA73 | F67: NEXTPR | H67: REITS | I67: FIN | J67: REITS-Warehouse/Industr | K67: MX | L67: MX | M67: USD | N67: NR | O67: NO APLICA
A68: NEXTPR 6.39 01/15/50 | B68: Trust 2401 | C68: TRUST 2401 | D68: TRUST 2401 | E68: USP9402MAE95 | F68: NEXTPR | H68: REITS | I68: FIN | J68: REITS-Warehouse/Industr | K68: MX | L68: MX | M68: USD | N68: BBB- | O68: NO APLICA
A69: NEXTPR 6.95 01/30/44 | B69: Trust 2401 | C69: TRUST 2401 | D69: TRUST 2401 | E69: USP9402MAD13 | F69: NEXTPR | H69: REITS | I69: FIN | J69: REITS-Warehouse/Industr | K69: MX | L69: MX | M69: USD | N69: BBB- | O69: NO APLICA
A70: NEXTPR 7 ⅜ 02/13/34 | B70: Trust 2401 | C70: TRUST 2401 | D70: TRUST 2401 | E70: USP9402MAC30 | F70: NEXTPR | H70: REITS | I70: FIN | J70: REITS-Warehouse/Industr | K70: MX | L70: MX | M70: USD | N70: BBB- | O70: NO APLICA
A71: NEXTPR 7.7 01/23/32 | B71: Trust 2401 | C71: TRUST 2401 | D71: TRUST 2401 | E71: USP9402MAB56 | F71: NEXTPR | H71: REITS | I71: FIN | J71: REITS-Warehouse/Industr | K71: MX | L71: MX | M71: USD | N71: BBB- | O71: NO APLICA
A72: OENCBZ 11 ¼ 05/08/31 | B72: Oceanica Lux | C72: OCEANICA LUX | D72: OCEANICA LUX | E72: USL7151AAC01 | F72: OENCBZ | G72: 0199274D BZ | H72: Oil&Gas Services | I72: IND | J72: Oil-Field Services | K72: LU | L72: BR | M72: USD | N72: NR | O72: NO APLICA
A73: OENCBZ 13 10/02/29 | B73: Oceanica Lux | C73: OCEANICA LUX | D73: OCEANICA LUX | E73: USL7151AAA45 | F73: OENCBZ | G73: OENCBZ | H73: Oil&Gas Services | I73: Energy | J73: Oil-Field Services | K73: LU | L73: BR | M73: USD | N73: B | O73: NO APLICA
A74: OHIFLY 13 07/22/29 | B74: OHI Group SA | C74: OHI GROUP SA | D74: OHI GROUP SA | E74: USL7S61MAB59 | F74: OHIFLY | H74: Oil&Gas Services | I74: Energy | J74: Oil-Field Services | K74: LU | L74: BR | M74: USD | N74: B | O74: NO APLICA
A75: PEMEX 5.35 02/12/28 | B75: Petroleos Mexicanos | C75: PETROLEOS MEXICA | D75: PETROLEOS MEXICANOS | E75: USP78625DD22 | F75: PEMEX | G75: 1232Z MM | H75: Oil&Gas | I75: Energy | J75: Oil Comp-Integrated | K75: MX | L75: MX | M75: USD | N75: BB | O75: VENCIMIENTO <= 2028
A76: PEMEX 5.35 02/12/28 | B76: Petroleos Mexicanos | C76: PETROLEOS MEXICA | D76: PETROLEOS MEXICANOS | E76: US71654QCK67 | F76: PEMEX | G76: 1232Z MM | H76: Oil&Gas | I76: Energy | J76: Oil Comp-Integrated | K76: MX | L76: MX | M76: USD | N76: BB | O76: VENCIMIENTO <= 2028
A77: PEMEX 8 ¾ 06/02/29 | B77: Petroleos Mexicanos | C77: PETROLEOS MEXICA | D77: PETROLEOS MEXICANOS | E77: US71654QDK58 | F77: PEMEX | G77: 1232Z MM | H77: Oil&Gas | I77: FOA | J77: Oil Comp-Integrated | K77: MX | L77: MX | M77: USD | N77: BB | O77: REPETIDO
A78: PETBRA 5.999 01/27/28 | B78: Petrobras Global Finance BV | C78: PETROBRAS GLOB | D78: PETROBRAS GLOBAL FINANCE | E78: US71647NAY58 | F78: PETBRA | G78: 3617348Z BZ | H78: Oil&Gas | I78: Energy | J78: Oil Comp-Integrated | K78: NL | L78: BR | M78: USD | N78: BB | O78: VENCIMIENTO <= 2028
A79: PETBRA 5.999 01/27/28 | B79: Petrobras Global Finance BV | C79: PETROBRAS GLOB | D79: PETROBRAS GLOBAL FINANCE | E79: USN6945AAK36 | F79: PETBRA | G79: 3617348Z BZ | H79: Oil&Gas | I79: Energy | J79: Oil Comp-Integrated | K79: NL | L79: BR | M79: USD | N79: BB | O79: VENCIMIENTO <= 2028
A80: PETRPE 4 ¾ 06/19/32 | B80: Petroleos del Peru SA | C80: PETROLEOS DEL PE | D80: PETROLEOS DEL PERU SA | E80: USP7808BAA54 | F80: PETRPE | G80: PETROBC1 PE | H80: Oil&Gas | I80: FOA | J80: Oil Comp-Integrated | K80: PE | L80: PE | M80: USD | N80: CCC+ | O80: CCC+
A81: PETRPE 5 ⅝ 06/19/47 | B81: Petroleos del Peru SA | C81: PETROLEOS DEL PE | D81: PETROLEOS DEL PERU SA | E81: USP7808BAB38 | F81: PETRPE | G81: PETROBC1 PE | H81: Oil&Gas | I81: FOA | J81: Oil Comp-Integrated | K81: PE | L81: PE | M81: USD | N81: CCC+ | O81: CCC+
A82: PNSTTA 6 ⅝ 06/17/31 | B82: PNSTTA 6 ⅝ 06/17/31 | C82: POINSETTIA FINAN | D82: POINSETTIA FINANCE LTD | E82: USG7150PAA87 | F82: PNSTTA | G82: 1412220D US | H82: Oil&Gas Services | I82: Energy | J82: Oil-Field Services | K82: MX | L82: MX | M82: USD | N82: BB | O82: NO APLICA
A83: PRIOBZ 6 ¾ 10/15/30 | B83: PRIO Luxembourg Holding Sarl | C83: PRIO LUX HLD | D83: PRIO LUX HLD SARL | E83: USL7S62BAA03 | F83: PRIOBZ | G83: PRIO3 BZ | H83: Oil&Gas | I83: IND | J83: Oil Comp-Explor&Prodtn | K83: LU | L83: BR | M83: USD | N83: NR | O83: NO RATING
A84: RAILBZ 5 ¼ 01/10/28 | B84: Rumo Luxembourg Sarl | C84: RUMO LUX SARL | D84: RUMO LUXEMBOURG SARL | E84: USL79090AC78 | F84: RAILBZ | G84: RAIL3 BZ | H84: Transportation | I84: Industrial | J84: Transport-Rail | K84: LU | L84: BR | M84: USD | N84: BB | O84: VENCIMIENTO <= 2028
A85: RAIZBZ 5.7 01/17/35 | B85: Raizen Fuels Finance SA | C85: RAIZEN FUELS | D85: RAIZEN FUELS FINANCE | E85: USL7909CAE77 | F85: RAIZBZ | G85: 8180002Z BZ | H85: Oil&Gas | I85: IND | J85: Oil Refining&Marketing | K85: LU | L85: BR | M85: USD | N85: CCC | O85: CCC+
A86: RAIZBZ 6 ¼ 07/08/32 | B86: Raizen Fuels Finance SA | C86: RAIZEN FUELS | D86: RAIZEN FUELS FINANCE | E86: USL7909CAJ64 | F86: RAIZBZ | G86: 8180002Z BZ | H86: Oil&Gas | I86: IND | J86: Oil Refining&Marketing | K86: LU | L86: BR | M86: USD | N86: CCC | O86: CCC+
... A90: RDEDOR 4.95 01/17/28 | B90: Rede D'or Finance Sarl | C90: REDE D'OR FIN | D90: REDE D'OR FINANCE SARL | E90: USL7915RAA43 | F90: RDEDOR | G90: RDOR3 BZ | H90: Healthcare-Services | I90: Consumer, Non-cyclical | J90: Medical-Hospitals | K90: LU | L90: BR | M90: USD | N90: BB+ | O90: VENCIMIENTO <= 2028
A91: RIOOIL 8.2 04/06/28 | B91: RIOOIL 8.2 04/06/28 | C91: RIO OIL FINANCE | D91: RIO OIL FINANCE TRUST | E91: USU76673AC39 | F91: RIOOIL | H91: Oil&Gas | I91: Energy | J91: Oil-US Royalty Trusts | K91: BR | L91: BR | M91: USD | N91: BB- | O91: NO APLICA
A92: RIOOIL 9 ¾ 01/06/27 | B92: RIOOIL 9 ¾ 01/06/27 | C92: RIO OIL FINANCE | D92: RIO OIL FINANCE TRUST | E92: USU76673AB55 | F92: RIOOIL | H92: Oil&Gas | I92: Energy | J92: Oil-US Royalty Trusts | K92: BR | L92: BR | M92: USD | N92: BB- | O92: NO APLICA
A93: SAAVIE 8 ⅞ 02/10/35 | B93: Saavi Energia Sarl | C93: SAAVI ENERGIA | D93: SAAVI ENERGIA SARL | E93: USL02668AA66 | F93: SAAVIE | H93: Electric | I93: Independ Power Producer | J93: Independ Power Producer | K93: LU | L93: MX | M93: USD | N93: BB- | O93: NO APLICA
A94: SABESP 5 ⅝ 08/20/30 | B94: Sabesp Lux Sarl | C94: SABESP LUX SARL | D94: SABESP LUX SARL | E94: USL07120AB17 | F94: SABESP | H94: Water | I94: UTL | J94: Water | K94: LU | L94: BR | M94: USD | N94: BB | O94: NO APLICA
A95: SAMMIN 9 ½ 06/30/31 | B95: Samarco Mineracao SA | C95: SAMARCO MINERACA | D95: SAMARCO MINERACAO SA | E95: USP8405QAA78 | F95: SAMMIN | G95: 1019Z BZ | H95: Iron/Steel | I95: Basic Materials | J95: Metal-Iron | K95: BR | L95: BR | M95: USD | N95: B | O95: SINGLE B
A96: SAMMIN 9 ½ 06/30/31 | B96: Samarco Mineracao SA | C96: SAMARCO MINERACA | D96: SAMARCO MINERACAO SA | E96: USP8405QAB51 | F96: SAMMIN | G96: 1019Z BZ | H96: Iron/Steel | I96: IND | J96: Metal-Iron | K96: BR | L96: BR | M96: USD | N96: NR | O96: NR
A97: SBSPAB 5 ¾ 02/03/31 | B97: Nova Securitisation Sarl | C97: NOVA SECURITISAT | D97: NOVA SECURITISATION SARL | E97: USL70906AA73 | F97: SBSPAB | H97: Water | I97: UTL | J97: Water | K97: LU | L97: BR | M97: USD | N97: NR | O97: NR
A98: SBSPAB 6 ½ 02/03/36 | B98: Nova Securitisation Sarl | C98: NOVA SECURITISAT | D98: NOVA SECURITISATION SARL | E98: USL70906AB56 | F98: SBSPAB | H98: Water | I98: UTL | J98: Water | K98: LU | L98: BR | M98: USD | N98: NR | O98: NR
A99: SIERRA 6 06/15/28 | B99: SIERRA 6 06/15/28 | C99: SIERRACOL ENRGY | D99: SIERRACOL ENRGY ANDINA | E99: USU8215LAA27 | F99: SIERRA | G99: CG US | H99: Oil&Gas | I99: Energy | J99: Oil Comp-Explor&Prodtn | K99: CO | L99: CO | M99: USD | N99: B+ | O99: NO APLICA
A100: SIERRA 9 11/14/30 | B100: SierraCol Energy Andina LLC/SierraCol Energy Arauca/Colombia Energy Development | C100: SIERRACOL AN/A/D | D100: SIERRACOL EN AND/ARA/DEV | E100: USU8215PAA31 | F100: SIERRA | G100: 1859092D LN | H100: Oil&Gas | I100: Energy | J100: Oil Comp-Explor&Prodtn | K100: US | L100: CO | M100: USD | N100: B+ | O100: NO APLICA
A101: SIGMA 4 ⅞ 03/27/28 | B101: Sigma Finance Netherlands BV | C101: SIGMA FIN NL | D101: SIGMA FINANCE NL | E101: USN8133NAA56 | F101: SIGMA | G101: SIGMAA MM | H101: Food | I101: Consumer, Non-cyclical | J101: Food-Misc/Diversified | K101: NL | L101: MX | M101: USD | N101: BBB- | O101: VENCIMIENTO <= 2028
A102: SMIPET 3 ½ 08/02/28 | B102: SAN Miguel Industrias Pet SA / NG PET R&P Latin America SA | C102: SAN MIGUEL INDUS | D102: SAN MIGUEL INDUSTRIAS | E102: USP84527AA17 | F102: SMIPET | H102: Packaging&Containers | I102: Industrial | J102: Containers-Paper/Plastic | K102: PE | L102: PE | M102: USD | N102: BB | O102: VENCIMIENTO <= 2028
A103: SOTMCL 6.385 12/15/55 | B103: Sociedad Transmisora Metropolitana SpA | C103: SOCIEDAD TRANSMI | D103: SOCIEDAD TRANSMISORA MET | E103: USP8725GAB07 | F103: SOTMCL | G103: 2210915D CI | H103: Electric | I103: UTL | J103: Electric-Integrated | K103: CL | L103: CL | M103: USD | N103: NR | O103: NO APLICA
...
